Workbook

Sheet Задание 3
B1: Задание 3. Ориентировочное время - 15-20 минут | G1: Год | H1: 2020 | I1: =H1+1 -> 2021 | J1: =I1+1 -> 2022 | K1: =J1+1 -> 2023 | L1: =K1+1 -> 2024 | N1: 2020 | O1: 2020 | P1: 2020 | Q1: 2020 | R1: 2020 | S1: 2020 | T1: 2020 | U1: 2020 | V1: 2020 | W1: 2020 | X1: 2020 | Y1: 2020 | Z1: =N1+1 -> 2021 | AA1: =O1+1 -> 2021 | AB1: =P1+1 -> 2021 | AC1: =Q1+1 -> 2021 | AD1: =R1+1 -> 2021 | AE1: =S1+1 -> 2021 | AF1: =T1+1 -> 2021 | AG1: =U1+1 -> 2021 | ... BU1: =BI1+1 -> 2024
B2: Показатель | E2: ед. изм. | G2: Месяц | N2: 1 | O2: =N2+1 -> 2 | P2: =O2+1 -> 3 | Q2: =P2+1 -> 4 | R2: =Q2+1 -> 5 | S2: =R2+1 -> 6 | T2: =S2+1 -> 7 | U2: =T2+1 -> 8 | V2: =U2+1 -> 9 | ... Y2: =X2+1 -> 12 | Z2: =N2 -> 1 | AA2: =O2 -> 2 | AB2: =P2 -> 3 | AC2: =Q2 -> 4 | AD2: =R2 -> 5 | AE2: =S2 -> 6 | AF2: =T2 -> 7 | AG2: =U2 -> 8 | ... BU2: =BI2 -> 12
E3: 5. Закрепляем строки/столбцы
B4: Задачи:
B5: На основе листа "Декларации" - нужно посчитать и заполнить выделенные блоки ниже (то, что фиолетовым)
B6: Расчеты - делать по месяцам, далее суммирование в годы
B7: hint 1 - можно (даже нужно) делать дополнительные расчетные столбцы/ячейки
B8: hint 2 - для идентификации нужных товаров (гороховый изолят и гороховый концентрат) - использовать слова "горох", "изолят", "концентр"
B11: Важно!!!
B12: Все должно быть аккуратно оформлено
B14: Импорт
N15: 7. Аккуратно пишем формулу: без хардов, правильно закрепленные ячейки и тд
B16: В тоннах | F16: 6. Создаем доп столбец - "ИМ" и "ЭК" - чтобы не менять фомрулу | H16: 8. Через суммесли - сводим месячные данные по годам
B17: Гороховый изолят | E17: тонн | F17: ИМ | H17: =SUMIFS($N17:$BU17,$N$1:$BU$1,H$1) -> 91.51197 | I17: =SUMIFS($N17:$BU17,$N$1:$BU$1,I$1) -> 387.48 | J17: =SUMIFS($N17:$BU17,$N$1:$BU$1,J$1) -> 728.367 | K17: =SUMIFS($N17:$BU17,$N$1:$BU$1,K$1) -> 957.70136 | L17: =SUMIFS($N17:$BU17,$N$1:$BU$1,L$1) -> 771.04255 | N17: =SUMIFS(Декларации!$O:$O,Декларации!$C:$C,N$1,Декларации!$D:$D,N$2,Декларации!$E:$E,$F17,Декларации!$L:$L,$B17)/1000 -> 10.52 | O17: =SUMIFS(Декларации!$O:$O,Декларации!$C:$C,O$1,Декларации!$D:$D,O$2,Декларации!$E:$E,$F17,Декларации!$L:$L,$B17)/1000 -> 6.303 | P17: =SUMIFS(Декларации!$O:$O,Декларации!$C:$C,P$1,Декларации!$D:$D,P$2,Декларации!$E:$E,$F17,Декларации!$L:$L,$B17)/1000 -> 3.78 | Q17: =SUMIFS(Декларации!$O:$O,Декларации!$C:$C,Q$1,Декларации!$D:$D,Q$2,Декларации!$E:$E,$F17,Декларации!$L:$L,$B17)/1000 -> 6.73 | R17: =SUMIFS(Декларации!$O:$O,Декларации!$C:$C,R$1,Декларации!$D:$D,R$2,Декларации!$E:$E,$F17,Декларации!$L:$L,$B17)/1000 -> 5.00879 | S17: =SUMIFS(Декларации!$O:$O,Декларации!$C:$C,S$1,Декларации!$D:$D,S$2,Декларации!$E:$E,$F17,Декларации!$L:$L,$B17)/1000 -> 8.20018 | T17: =SUMIFS(Декларации!$O:$O,Декларации!$C:$C,T$1,Декларации!$D:$D,T$2,Декларации!$E:$E,$F17,Декларации!$L:$L,$B17)/1000 -> 5.04 | U17: =SUMIFS(Декларации!$O:$O,Декларации!$C:$C,U$1,Декларации!$D:$D,U$2,Декларации!$E:$E,$F17,Декларации!$L:$L,$B17)/1000 -> 28.82 | ... BU17: =SUMIFS(Декларации!$O:$O,Декларации!$C:$C,BU$1,Декларации!$D:$D,BU$2,Декларации!$E:$E,$F17,Декларации!$L:$L,$B17)/1000 -> 82.2
B18: Гороховый концентрат | E18: тонн | F18: ИМ | H18: =SUMIFS($N18:$BU18,$N$1:$BU$1,H$1) -> 548.9 | I18: =SUMIFS($N18:$BU18,$N$1:$BU$1,I$1) -> 303.201 | J18: =SUMIFS($N18:$BU18,$N$1:$BU$1,J$1) -> 975.85405 | K18: =SUMIFS($N18:$BU18,$N$1:$BU$1,K$1) -> 790.7118 | L18: =SUMIFS($N18:$BU18,$N$1:$BU$1,L$1) -> 1174.9395 | N18: =SUMIFS(Декларации!$O:$O,Декларации!$C:$C,N$1,Декларации!$D:$D,N$2,Декларации!$E:$E,$F18,Декларации!$L:$L,$B18)/1000 -> 90 | O18: =SUMIFS(Декларации!$O:$O,Декларации!$C:$C,O$1,Декларации!$D:$D,O$2,Декларации!$E:$E,$F18,Декларации!$L:$L,$B18)/1000 -> 0 | P18: =SUMIFS(Декларации!$O:$O,Декларации!$C:$C,P$1,Декларации!$D:$D,P$2,Декларации!$E:$E,$F18,Декларации!$L:$L,$B18)/1000 -> 112 | Q18: =SUMIFS(Декларации!$O:$O,Декларации!$C:$C,Q$1,Декларации!$D:$D,Q$2,Декларации!$E:$E,$F18,Декларации!$L:$L,$B18)/1000 -> 80 | R18: =SUMIFS(Декларации!$O:$O,Декларации!$C:$C,R$1,Декларации!$D:$D,R$2,Декларации!$E:$E,$F18,Декларации!$L:$L,$B18)/1000 -> 22.2 | S18: =SUMIFS(Декларации!$O:$O,Декларации!$C:$C,S$1,Декларации!$D:$D,S$2,Декларации!$E:$E,$F18,Декларации!$L:$L,$B18)/1000 -> 40.7 | T18: =SUMIFS(Декларации!$O:$O,Декларации!$C:$C,T$1,Декларации!$D:$D,T$2,Декларации!$E:$E,$F18,Декларации!$L:$L,$B18)/1000 -> 62 | U18: =SUMIFS(Декларации!$O:$O,Декларации!$C:$C,U$1,Декларации!$D:$D,U$2,Декларации!$E:$E,$F18,Декларации!$L:$L,$B18)/1000 -> 40 | ... BU18: =SUMIFS(Декларации!$O:$O,Декларации!$C:$C,BU$1,Декларации!$D:$D,BU$2,Декларации!$E:$E,$F18,Декларации!$L:$L,$B18)/1000 -> 244.7836
B19: Всего | E19: тонн | F19: ИМ | H19: =SUMIFS($N19:$BU19,$N$1:$BU$1,H$1) -> 640.41197 | I19: =SUMIFS($N19:$BU19,$N$1:$BU$1,I$1) -> 690.681 | J19: =SUMIFS($N19:$BU19,$N$1:$BU$1,J$1) -> 1704.2211 | K19: =SUMIFS($N19:$BU19,$N$1:$BU$1,K$1) -> 1748.4132 | L19: =SUMIFS($N19:$BU19,$N$1:$BU$1,L$1) -> 1945.9821 | N19: =SUM(N17:N18) -> 100.52 | O19: =SUM(O17:O18) -> 6.303 | P19: =SUM(P17:P18) -> 115.78 | Q19: =SUM(Q17:Q18) -> 86.73 | R19: =SUM(R17:R18) -> 27.20879 | S19: =SUM(S17:S18) -> 48.90018 | T19: =SUM(T17:T18) -> 67.04 | U19: =SUM(U17:U18) -> 68.82 | ... BU19: =SUM(BU17:BU18) -> 326.9836
B21: В деньгах | H21: 9. Прям целиком копируем все расчеты в таблице выше и вставляем сюда | N21: 10. меняем ссылку на столбец - с веса на стоимость
B22: Гороховый изолят | E22: тыс. долл. | F22: ИМ | H22: =SUMIFS($N22:$BU22,$N$1:$BU$1,H$1) -> 412.67531 | I22: =SUMIFS($N22:$BU22,$N$1:$BU$1,I$1) -> 1463.085 | J22: =SUMIFS($N22:$BU22,$N$1:$BU$1,J$1) -> 2760.3047 | K22: =SUMIFS($N22:$BU22,$N$1:$BU$1,K$1) -> 3045.8797 | L22: =SUMIFS($N22:$BU22,$N$1:$BU$1,L$1) -> 2350.0055 | N22: =SUMIFS(Декларации!$P:$P,Декларации!$C:$C,N$1,Декларации!$D:$D,N$2,Декларации!$E:$E,$F22,Декларации!$L:$L,$B22)/1000 -> 37.67208 | O22: =SUMIFS(Декларации!$P:$P,Декларации!$C:$C,O$1,Декларации!$D:$D,O$2,Декларации!$E:$E,$F22,Декларации!$L:$L,$B22)/1000 -> 30.42155 | P22: =SUMIFS(Декларации!$P:$P,Декларации!$C:$C,P$1,Декларации!$D:$D,P$2,Декларации!$E:$E,$F22,Декларации!$L:$L,$B22)/1000 -> 18.41793 | Q22: =SUMIFS(Декларации!$P:$P,Декларации!$C:$C,Q$1,Декларации!$D:$D,Q$2,Декларации!$E:$E,$F22,Декларации!$L:$L,$B22)/1000 -> 35.14405 | R22: =SUMIFS(Декларации!$P:$P,Декларации!$C:$C,R$1,Декларации!$D:$D,R$2,Декларации!$E:$E,$F22,Декларации!$L:$L,$B22)/1000 -> 22.93789 | S22: =SUMIFS(Декларации!$P:$P,Декларации!$C:$C,S$1,Декларации!$D:$D,S$2,Декларации!$E:$E,$F22,Декларации!$L:$L,$B22)/1000 -> 40.4534 | T22: =SUMIFS(Декларации!$P:$P,Декларации!$C:$C,T$1,Декларации!$D:$D,T$2,Декларации!$E:$E,$F22,Декларации!$L:$L,$B22)/1000 -> 25.16574 | U22: =SUMIFS(Декларации!$P:$P,Декларации!$C:$C,U$1,Декларации!$D:$D,U$2,Декларации!$E:$E,$F22,Декларации!$L:$L,$B22)/1000 -> 106.98763 | ... BU22: =SUMIFS(Декларации!$P:$P,Декларации!$C:$C,BU$1,Декларации!$D:$D,BU$2,Декларации!$E:$E,$F22,Декларации!$L:$L,$B22)/1000 -> 240.7527
B23: Гороховый концентрат | E23: тыс. долл. | F23: ИМ | H23: =SUMIFS($N23:$BU23,$N$1:$BU$1,H$1) -> 1833.7213 | I23: =SUMIFS($N23:$BU23,$N$1:$BU$1,I$1) -> 855.42981 | J23: =SUMIFS($N23:$BU23,$N$1:$BU$1,J$1) -> 3358.2656 | K23: =SUMIFS($N23:$BU23,$N$1:$BU$1,K$1) -> 2435.1957 | L23: =SUMIFS($N23:$BU23,$N$1:$BU$1,L$1) -> 3346.3376 | N23: =SUMIFS(Декларации!$P:$P,Декларации!$C:$C,N$1,Декларации!$D:$D,N$2,Декларации!$E:$E,$F23,Декларации!$L:$L,$B23)/1000 -> 331.47394 | O23: =SUMIFS(Декларации!$P:$P,Декларации!$C:$C,O$1,Декларации!$D:$D,O$2,Декларации!$E:$E,$F23,Декларации!$L:$L,$B23)/1000 -> 0 | P23: =SUMIFS(Декларации!$P:$P,Декларации!$C:$C,P$1,Декларации!$D:$D,P$2,Декларации!$E:$E,$F23,Декларации!$L:$L,$B23)/1000 -> 351.84154 | Q23: =SUMIFS(Декларации!$P:$P,Декларации!$C:$C,Q$1,Декларации!$D:$D,Q$2,Декларации!$E:$E,$F23,Декларации!$L:$L,$B23)/1000 -> 270.0488 | R23: =SUMIFS(Декларации!$P:$P,Декларации!$C:$C,R$1,Декларации!$D:$D,R$2,Декларации!$E:$E,$F23,Декларации!$L:$L,$B23)/1000 -> 68.2 | S23: =SUMIFS(Декларации!$P:$P,Декларации!$C:$C,S$1,Декларации!$D:$D,S$2,Декларации!$E:$E,$F23,Декларации!$L:$L,$B23)/1000 -> 136.70943 | T23: =SUMIFS(Декларации!$P:$P,Декларации!$C:$C,T$1,Декларации!$D:$D,T$2,Декларации!$E:$E,$F23,Декларации!$L:$L,$B23)/1000 -> 201.61174 | U23: =SUMIFS(Декларации!$P:$P,Декларации!$C:$C,U$1,Декларации!$D:$D,U$2,Декларации!$E:$E,$F23,Декларации!$L:$L,$B23)/1000 -> 134.41511 | ... BU23: =SUMIFS(Декларации!$P:$P,Декларации!$C:$C,BU$1,Декларации!$D:$D,BU$2,Декларации!$E:$E,$F23,Декларации!$L:$L,$B23)/1000 -> 715.61362
B24: Всего | E24: тыс. долл. | F24: ИМ | H24: =SUMIFS($N24:$BU24,$N$1:$BU$1,H$1) -> 2246.3966 | I24: =SUMIFS($N24:$BU24,$N$1:$BU$1,I$1) -> 2318.5149 | J24: =SUMIFS($N24:$BU24,$N$1:$BU$1,J$1) -> 6118.5703 | K24: =SUMIFS($N24:$BU24,$N$1:$BU$1,K$1) -> 5481.0754 | L24: =SUMIFS($N24:$BU24,$N$1:$BU$1,L$1) -> 5696.3431 | N24: =SUM(N22:N23) -> 369.14602 | O24: =SUM(O22:O23) -> 30.42155 | P24: =SUM(P22:P23) -> 370.25947 | Q24: =SUM(Q22:Q23) -> 305.19285 | R24: =SUM(R22:R23) -> 91.13789 | S24: =SUM(S22:S23) -> 177.16283 | T24: =SUM(T22:T23) -> 226.77748 | U24: =SUM(U22:U23) -> 241.40274 | ... BU24: =SUM(BU22:BU23) -> 956.36632
B26: Цена | N26: 11. Считаем среднюю цену. Обязательно - через "еслиошибка"
B27: Гороховый изолят | E27: долл./кг | F27: ИМ | H27: =IFERROR(H22/H17,0) -> 4.5095227 | I27: =IFERROR(I22/I17,0) -> 3.7758982 | J27: =IFERROR(J22/J17,0) -> 3.7897169 | K27: =IFERROR(K22/K17,0) -> 3.1804066 | L27: =IFERROR(L22/L17,0) -> 3.0478285 | N27: =IFERROR(N22/N17,0) -> 3.5809962 | O27: =IFERROR(O22/O17,0) -> 4.8265191 | P27: =IFERROR(P22/P17,0) -> 4.8724683 | Q27: =IFERROR(Q22/Q17,0) -> 5.2219985 | R27: =IFERROR(R22/R17,0) -> 4.5795272 | S27: =IFERROR(S22/S17,0) -> 4.9332332 | T27: =IFERROR(T22/T17,0) -> 4.9932024 | U27: =IFERROR(U22/U17,0) -> 3.7122703 | ... BU27: =IFERROR(BU22/BU17,0) -> 2.928865
B28: Гороховый концентрат | E28: долл./кг | F28: ИМ | H28: =IFERROR(H23/H18,0) -> 3.3407202 | I28: =IFERROR(I23/I18,0) -> 2.8213291 | J28: =IFERROR(J23/J18,0) -> 3.4413605 | K28: =IFERROR(K23/K18,0) -> 3.0797513 | L28: =IFERROR(L23/L18,0) -> 2.8480935 | N28: =IFERROR(N23/N18,0) -> 3.6830438 | O28: =IFERROR(O23/O18,0) -> 0 | P28: =IFERROR(P23/P18,0) -> 3.1414423 | Q28: =IFERROR(Q23/Q18,0) -> 3.37561 | R28: =IFERROR(R23/R18,0) -> 3.0720721 | S28: =IFERROR(S23/S18,0) -> 3.3589541 | T28: =IFERROR(T23/T18,0) -> 3.2518023 | U28: =IFERROR(U23/U18,0) -> 3.3603778 | ... BU28: =IFERROR(BU23/BU18,0) -> 2.9234541
B29: Всего | E29: долл./кг | F29: ИМ | H29: =IFERROR(H24/H19,0) -> 3.5077368 | I29: =IFERROR(I24/I19,0) -> 3.3568534 | J29: =IFERROR(J24/J19,0) -> 3.5902446 | K29: =IFERROR(K24/K19,0) -> 3.1348857 | L29: =IFERROR(L24/L19,0) -> 2.9272331 | N29: =IFERROR(N24/N19,0) -> 3.6723639 | O29: =IFERROR(O24/O19,0) -> 4.8265191 | P29: =IFERROR(P24/P19,0) -> 3.1979571 | Q29: =IFERROR(Q24/Q19,0) -> 3.5188845 | R29: =IFERROR(R24/R19,0) -> 3.3495753 | S29: =IFERROR(S24/S19,0) -> 3.6229484 | T29: =IFERROR(T24/T19,0) -> 3.382719 | U29: =IFERROR(U24/U19,0) -> 3.5077411 | ... BU29: =IFERROR(BU24/BU19,0) -> 2.9248143
B31: Экспорт
B33: В тоннах | H33: 12. Прям целиком копируем со столбца Н строки 17-29. И все должно нормально сразу посчитаться по экспорту
B34: Гороховый изолят | E34: тонн | F34: ЭК | H34: =SUMIFS($N34:$BU34,$N$1:$BU$1,H$1) -> 0.10231 | I34: =SUMIFS($N34:$BU34,$N$1:$BU$1,I$1) -> 0.00768 | J34: =SUMIFS($N34:$BU34,$N$1:$BU$1,J$1) -> 0 | K34: =SUMIFS($N34:$BU34,$N$1:$BU$1,K$1) -> 0.0511 | L34: =SUMIFS($N34:$BU34,$N$1:$BU$1,L$1) -> 0 | N34: =SUMIFS(Декларации!$O:$O,Декларации!$C:$C,N$1,Декларации!$D:$D,N$2,Декларации!$E:$E,$F34,Декларации!$L:$L,$B34)/1000 -> 0 | O34: =SUMIFS(Декларации!$O:$O,Декларации!$C:$C,O$1,Декларации!$D:$D,O$2,Декларации!$E:$E,$F34,Декларации!$L:$L,$B34)/1000 -> 0 | P34: =SUMIFS(Декларации!$O:$O,Декларации!$C:$C,P$1,Декларации!$D:$D,P$2,Декларации!$E:$E,$F34,Декларации!$L:$L,$B34)/1000 -> 0 | Q34: =SUMIFS(Декларации!$O:$O,Декларации!$C:$C,Q$1,Декларации!$D:$D,Q$2,Декларации!$E:$E,$F34,Декларации!$L:$L,$B34)/1000 -> 0 | R34: =SUMIFS(Декларации!$O:$O,Декларации!$C:$C,R$1,Декларации!$D:$D,R$2,Декларации!$E:$E,$F34,Декларации!$L:$L,$B34)/1000 -> 0 | S34: =SUMIFS(Декларации!$O:$O,Декларации!$C:$C,S$1,Декларации!$D:$D,S$2,Декларации!$E:$E,$F34,Декларации!$L:$L,$B34)/1000 -> 0 | T34: =SUMIFS(Декларации!$O:$O,Декларации!$C:$C,T$1,Декларации!$D:$D,T$2,Декларации!$E:$E,$F34,Декларации!$L:$L,$B34)/1000 -> 0.10231 | U34: =SUMIFS(Декларации!$O:$O,Декларации!$C:$C,U$1,Декларации!$D:$D,U$2,Декларации!$E:$E,$F34,Декларации!$L:$L,$B34)/1000 -> 0 | ... BU34: =SUMIFS(Декларации!$O:$O,Декларации!$C:$C,BU$1,Декларации!$D:$D,BU$2,Декларации!$E:$E,$F34,Декларации!$L:$L,$B34)/1000 -> 0
B35: Гороховый концентрат | E35: тонн | F35: ЭК | H35: =SUMIFS($N35:$BU35,$N$1:$BU$1,H$1) -> 1.87 | I35: =SUMIFS($N35:$BU35,$N$1:$BU$1,I$1) -> 0 | J35: =SUMIFS($N35:$BU35,$N$1:$BU$1,J$1) -> 0.464 | K35: =SUMIFS($N35:$BU35,$N$1:$BU$1,K$1) -> 0 | L35: =SUMIFS($N35:$BU35,$N$1:$BU$1,L$1) -> 0.039 | N35: =SUMIFS(Декларации!$O:$O,Декларации!$C:$C,N$1,Декларации!$D:$D,N$2,Декларации!$E:$E,$F35,Декларации!$L:$L,$B35)/1000 -> 0 | O35: =SUMIFS(Декларации!$O:$O,Декларации!$C:$C,O$1,Декларации!$D:$D,O$2,Декларации!$E:$E,$F35,Декларации!$L:$L,$B35)/1000 -> 0 | P35: =SUMIFS(Декларации!$O:$O,Декларации!$C:$C,P$1,Декларации!$D:$D,P$2,Декларации!$E:$E,$F35,Декларации!$L:$L,$B35)/1000 -> 0 | Q35: =SUMIFS(Декларации!$O:$O,Декларации!$C:$C,Q$1,Декларации!$D:$D,Q$2,Декларации!$E:$E,$F35,Декларации!$L:$L,$B35)/1000 -> 0 | R35: =SUMIFS(Декларации!$O:$O,Декларации!$C:$C,R$1,Декларации!$D:$D,R$2,Декларации!$E:$E,$F35,Декларации!$L:$L,$B35)/1000 -> 0.21 | S35: =SUMIFS(Декларации!$O:$O,Декларации!$C:$C,S$1,Декларации!$D:$D,S$2,Декларации!$E:$E,$F35,Декларации!$L:$L,$B35)/1000 -> 0.58 | T35: =SUMIFS(Декларации!$O:$O,Декларации!$C:$C,T$1,Декларации!$D:$D,T$2,Декларации!$E:$E,$F35,Декларации!$L:$L,$B35)/1000 -> 0 | U35: =SUMIFS(Декларации!$O:$O,Декларации!$C:$C,U$1,Декларации!$D:$D,U$2,Декларации!$E:$E,$F35,Декларации!$L:$L,$B35)/1000 -> 0 | ... BU35: =SUMIFS(Декларации!$O:$O,Декларации!$C:$C,BU$1,Декларации!$D:$D,BU$2,Декларации!$E:$E,$F35,Декларации!$L:$L,$B35)/1000 -> 0.039
B36: Всего | E36: тонн | F36: ЭК | H36: =SUMIFS($N36:$BU36,$N$1:$BU$1,H$1) -> 1.97231 | I36: =SUMIFS($N36:$BU36,$N$1:$BU$1,I$1) -> 0.00768 | J36: =SUMIFS($N36:$BU36,$N$1:$BU$1,J$1) -> 0.464 | K36: =SUMIFS($N36:$BU36,$N$1:$BU$1,K$1) -> 0.0511 | L36: =SUMIFS($N36:$BU36,$N$1:$BU$1,L$1) -> 0.039 | N36: =SUM(N34:N35) -> 0 | O36: =SUM(O34:O35) -> 0 | P36: =SUM(P34:P35) -> 0 | Q36: =SUM(Q34:Q35) -> 0 | R36: =SUM(R34:R35) -> 0.21 | S36: =SUM(S34:S35) -> 0.58 | T36: =SUM(T34:T35) -> 0.10231 | U36: =SUM(U34:U35) -> 0 | ... BU36: =SUM(BU34:BU35) -> 0.039
B38: В деньгах
B39: Гороховый изолят | E39: тыс. долл. | F39: ЭК | H39: =SUMIFS($N39:$BU39,$N$1:$BU$1,H$1) -> 1.89254 | I39: =SUMIFS($N39:$BU39,$N$1:$BU$1,I$1) -> 0.10791 | J39: =SUMIFS($N39:$BU39,$N$1:$BU$1,J$1) -> 0 | K39: =SUMIFS($N39:$BU39,$N$1:$BU$1,K$1) -> 1.34909 | L39: =SUMIFS($N39:$BU39,$N$1:$BU$1,L$1) -> 0 | N39: =SUMIFS(Декларации!$P:$P,Декларации!$C:$C,N$1,Декларации!$D:$D,N$2,Декларации!$E:$E,$F39,Декларации!$L:$L,$B39)/1000 -> 0 | O39: =SUMIFS(Декларации!$P:$P,Декларации!$C:$C,O$1,Декларации!$D:$D,O$2,Декларации!$E:$E,$F39,Декларации!$L:$L,$B39)/1000 -> 0 | P39: =SUMIFS(Декларации!$P:$P,Декларации!$C:$C,P$1,Декларации!$D:$D,P$2,Декларации!$E:$E,$F39,Декларации!$L:$L,$B39)/1000 -> 0 | Q39: =SUMIFS(Декларации!$P:$P,Декларации!$C:$C,Q$1,Декларации!$D:$D,Q$2,Декларации!$E:$E,$F39,Декларации!$L:$L,$B39)/1000 -> 0 | R39: =SUMIFS(Декларации!$P:$P,Декларации!$C:$C,R$1,Декларации!$D:$D,R$2,Декларации!$E:$E,$F39,Декларации!$L:$L,$B39)/1000 -> 0 | S39: =SUMIFS(Декларации!$P:$P,Декларации!$C:$C,S$1,Декларации!$D:$D,S$2,Декларации!$E:$E,$F39,Декларации!$L:$L,$B39)/1000 -> 0 | T39: =SUMIFS(Декларации!$P:$P,Декларации!$C:$C,T$1,Декларации!$D:$D,T$2,Декларации!$E:$E,$F39,Декларации!$L:$L,$B39)/1000 -> 1.89254 | U39: =SUMIFS(Декларации!$P:$P,Декларации!$C:$C,U$1,Декларации!$D:$D,U$2,Декларации!$E:$E,$F39,Декларации!$L:$L,$B39)/1000 -> 0 | ... BU39: =SUMIFS(Декларации!$P:$P,Декларации!$C:$C,BU$1,Декларации!$D:$D,BU$2,Декларации!$E:$E,$F39,Декларации!$L:$L,$B39)/1000 -> 0
B40: Гороховый концентрат | E40: тыс. долл. | F40: ЭК | H40: =SUMIFS($N40:$BU40,$N$1:$BU$1,H$1) -> 8.22991 | I40: =SUMIFS($N40:$BU40,$N$1:$BU$1,I$1) -> 0 | J40: =SUMIFS($N40:$BU40,$N$1:$BU$1,J$1) -> 2.67935 | K40: =SUMIFS($N40:$BU40,$N$1:$BU$1,K$1) -> 0 | L40: =SUMIFS($N40:$BU40,$N$1:$BU$1,L$1) -> 0.13735 | N40: =SUMIFS(Декларации!$P:$P,Декларации!$C:$C,N$1,Декларации!$D:$D,N$2,Декларации!$E:$E,$F40,Декларации!$L:$L,$B40)/1000 -> 0 | O40: =SUMIFS(Декларации!$P:$P,Декларации!$C:$C,O$1,Декларации!$D:$D,O$2,Декларации!$E:$E,$F40,Декларации!$L:$L,$B40)/1000 -> 0 | P40: =SUMIFS(Декларации!$P:$P,Декларации!$C:$C,P$1,Декларации!$D:$D,P$2,Декларации!$E:$E,$F40,Декларации!$L:$L,$B40)/1000 -> 0 | Q40: =SUMIFS(Декларации!$P:$P,Декларации!$C:$C,Q$1,Декларации!$D:$D,Q$2,Декларации!$E:$E,$F40,Декларации!$L:$L,$B40)/1000 -> 0 | R40: =SUMIFS(Декларации!$P:$P,Декларации!$C:$C,R$1,Декларации!$D:$D,R$2,Декларации!$E:$E,$F40,Декларации!$L:$L,$B40)/1000 -> 1.56009 | S40: =SUMIFS(Декларации!$P:$P,Декларации!$C:$C,S$1,Декларации!$D:$D,S$2,Декларации!$E:$E,$F40,Декларации!$L:$L,$B40)/1000 -> 2.21482 | T40: =SUMIFS(Декларации!$P:$P,Декларации!$C:$C,T$1,Декларации!$D:$D,T$2,Декларации!$E:$E,$F40,Декларации!$L:$L,$B40)/1000 -> 0 | U40: =SUMIFS(Декларации!$P:$P,Декларации!$C:$C,U$1,Декларации!$D:$D,U$2,Декларации!$E:$E,$F40,Декларации!$L:$L,$B40)/1000 -> 0 | ... BU40: =SUMIFS(Декларации!$P:$P,Декларации!$C:$C,BU$1,Декларации!$D:$D,BU$2,Декларации!$E:$E,$F40,Декларации!$L:$L,$B40)/1000 -> 0.13735
B41: Всего | E41: тыс. долл. | F41: ЭК | H41: =SUMIFS($N41:$BU41,$N$1:$BU$1,H$1) -> 10.12245 | I41: =SUMIFS($N41:$BU41,$N$1:$BU$1,I$1) -> 0.10791 | J41: =SUMIFS($N41:$BU41,$N$1:$BU$1,J$1) -> 2.67935 | K41: =SUMIFS($N41:$BU41,$N$1:$BU$1,K$1) -> 1.34909 | L41: =SUMIFS($N41:$BU41,$N$1:$BU$1,L$1) -> 0.13735 | N41: =SUM(N39:N40) -> 0 | O41: =SUM(O39:O40) -> 0 | P41: =SUM(P39:P40) -> 0 | Q41: =SUM(Q39:Q40) -> 0 | R41: =SUM(R39:R40) -> 1.56009 | S41: =SUM(S39:S40) -> 2.21482 | T41: =SUM(T39:T40) -> 1.89254 | U41: =SUM(U39:U40) -> 0 | ... BU41: =SUM(BU39:BU40) -> 0.13735
B43: Средневзвешенная цена
B44: Гороховый изолят | E44: долл./кг | F44: ЭК | H44: =IFERROR(H39/H34,0) -> 18.498094 | I44: =IFERROR(I39/I34,0) -> 14.050781 | J44: =IFERROR(J39/J34,0) -> 0 | K44: =IFERROR(K39/K34,0) -> 26.400978 | L44: =IFERROR(L39/L34,0) -> 0 | N44: =IFERROR(N39/N34,0) -> 0 | O44: =IFERROR(O39/O34,0) -> 0 | P44: =IFERROR(P39/P34,0) -> 0 | Q44: =IFERROR(Q39/Q34,0) -> 0 | R44: =IFERROR(R39/R34,0) -> 0 | S44: =IFERROR(S39/S34,0) -> 0 | T44: =IFERROR(T39/T34,0) -> 18.498094 | U44: =IFERROR(U39/U34,0) -> 0 | ... BU44: =IFERROR(BU39/BU34,0) -> 0
B45: Гороховый концентрат | E45: долл./кг | F45: ЭК | H45: =IFERROR(H40/H35,0) -> 4.4010214 | I45: =IFERROR(I40/I35,0) -> 0 | J45: =IFERROR(J40/J35,0) -> 5.7744612 | K45: =IFERROR(K40/K35,0) -> 0 | L45: =IFERROR(L40/L35,0) -> 3.5217949 | N45: =IFERROR(N40/N35,0) -> 0 | O45: =IFERROR(O40/O35,0) -> 0 | P45: =IFERROR(P40/P35,0) -> 0 | Q45: =IFERROR(Q40/Q35,0) -> 0 | R45: =IFERROR(R40/R35,0) -> 7.429 | S45: =IFERROR(S40/S35,0) -> 3.8186552 | T45: =IFERROR(T40/T35,0) -> 0 | U45: =IFERROR(U40/U35,0) -> 0 | ... BU45: =IFERROR(BU40/BU35,0) -> 3.5217949
B46: Всего | E46: долл./кг | F46: ЭК | H46: =IFERROR(H41/H36,0) -> 5.1322814 | I46: =IFERROR(I41/I36,0) -> 14.050781 | J46: =IFERROR(J41/J36,0) -> 5.7744612 | K46: =IFERROR(K41/K36,0) -> 26.400978 | L46: =IFERROR(L41/L36,0) -> 3.5217949 | N46: =IFERROR(N41/N36,0) -> 0 | O46: =IFERROR(O41/O36,0) -> 0 | P46: =IFERROR(P41/P36,0) -> 0 | Q46: =IFERROR(Q41/Q36,0) -> 0 | R46: =IFERROR(R41/R36,0) -> 7.429 | S46: =IFERROR(S41/S36,0) -> 3.8186552 | T46: =IFERROR(T41/T36,0) -> 18.498094 | U46: =IFERROR(U41/U36,0) -> 0 | ... BU46: =IFERROR(BU41/BU36,0) -> 3.5217949
B48: Импорт - в разрезе стран (суммарно - изолят и концентрат)
H49: Дальше, думаю, понятно, как это работает
B50: Доля крупнейшей страны от общего импорта | E50: %
B52: Страна 1 | E52: тонн
B53: Страна 2 | E53: тонн
B54: Страна 3 | E54: тонн
B55: Страна … | E55: тонн
B56: Страна … | E56: тонн
B57: Страна … | E57: тонн
B58: Страна … | E58: тонн
B59: Страна … | E59: тонн
B61: Страна 1 | E61: тыс. долл.
B62: Страна 2 | E62: тыс. долл.
B63: Страна 3 | E63: тыс. долл.
... B77: Страна … | E77: долл./кг
B79: Дополнительно - тут сделать сводную таблицу по импорту горохового изолята в разрезе стран - в тоннах

Sheet Декларации
C1: 1. Добавляем столбец год | D1: 2. Добавляем столбец месяц | I1: 3. Добавляем расчеты, которые находят нужные слова: 1 - есть, 0 - нет | L1: 4. Собираем столбец с названием продукта. Лучше это делать в одном столбце, чтобы формулу не менять) | M1: 4.1 Либо - можно так 2 столбца сделать, но тогда нужно будет менять формулы на сводном листе
B2: D1 Дата выпуска груза | C2: Год | D2: Месяц | E2: 011 ИМ.ЭК - направление перемещения | F2: 16 Страна происхождения | G2: 17 Страна назначения | H2: 31_1 Описание и характеристика товара | I2: горох | J2: изолят | K2: концентрат | L2: Продукт | M2: Гороховый изолят | N2: Гороховый концентрат | O2: 38 Вес нетто, кг | P2: 46 Статистическая стоимость, долл.
B3: 45588 | C3: =YEAR(B3) -> 2024 | D3: =MONTH(B3) -> 10 | E3: Им | F3: КИТАЙ | G3: РОССИЯ | H3: -НАРЕЗАННЯ СОЕВАЯ СУХАЯ СПАРЖА ФУЧЖУ, СОЕВЫЙ ПРОДУКТ ДЛЯ ПРИГОТОВЛЕНИЯ ГОТОВЫХ БЛЮД ЯПОНСКОЙ КУХНИ ДЛЯ УПОТРЕБЛЕНИЯ В ПИЩУ, НЕ CОДЕРЖИТ ГМО.. | I3: =MIN(1,IFERROR(SEARCH(I$2,$H3),0)) -> 0 | J3: =MIN(1,IFERROR(SEARCH(J$2,$H3),0)) -> 0 | K3: =MIN(1,IFERROR(SEARCH(K$2,$H3),0)) -> 0 | L3: =IF(I3*J3=1,"Гороховый изолят",IF(I3*K3=1,"Гороховый концентрат",0)) -> 0 | M3: =$I3*J3 -> 0 | N3: =$I3*K3 -> 0 | O3: 18000 | P3: 51399.62
B4: 200 | C4: =YEAR(B4) -> 1900 | D4: =MONTH(B4) -> 7 | E4: ЭК | F4: РОССИЯ | G4: ГРУЗИЯ | H4: ТЕКСТУРИРОВАННЫЕ БЕЛКОВЫЕ ПРОДУКТЫ, ПРЕДНАЗНАЧЕННЫЕ ДЛЯ ПРИГОТОВЛЕНИЯ ПИЩИ, А ТАК ЖЕ ДЛЯ ПЕРЕРАБОТКИ В ГОТОВЫЕ БЛЮДА, НЕ СОДЕРЖАТ ГМО: | I4: =MIN(1,IFERROR(SEARCH(I$2,$H4),0)) -> 0 | J4: =MIN(1,IFERROR(SEARCH(J$2,$H4),0)) -> 0 | K4: =MIN(1,IFERROR(SEARCH(K$2,$H4),0)) -> 0 | L4: =IF(I4*J4=1,"Гороховый изолят",IF(I4*K4=1,"Гороховый концентрат",0)) -> 0 | M4: =$I4*J4 -> 0 | N4: =$I4*K4 -> 0 | O4: 200 | P4: 919.93
B5: 10.11.2023 | C5: =YEAR(B5) -> 2023 | D5: =MONTH(B5) -> 11 | E5: ИМ | F5: СОЕДИНЕННЫЕ ШТАТЫ | G5: РОССИЯ | H5: "KERA TEIN Z 1000 SD". СОСТОИТ ИЗ СМЕСИ: ГИДРОЛИЗОВАННЫЙ КЕРАТИН (HYDROLYZED KERATIN) 89% И ВОДА 8% + БЕНЗОАТ НАТРИЯ (SODIUM BENZOATE) 1-3%. ЯВЛЯЕТСЯ АКТИВНЫМ ИНГРЕДИЕНТОМ В КОСМЕТИЧЕСКИХ СРЕДСТВАХ И СРЕДСТВАХ ЛИЧНОЙ ГИГИЕНЫ. ИСПОЛЬЗУЕТСЯ ПРИ ПРОИЗВО | I5: =MIN(1,IFERROR(SEARCH(I$2,$H5),0)) -> 0 | J5: =MIN(1,IFERROR(SEARCH(J$2,$H5),0)) -> 0 | K5: =MIN(1,IFERROR(SEARCH(K$2,$H5),0)) -> 0 | L5: =IF(I5*J5=1,"Гороховый изолят",IF(I5*K5=1,"Гороховый концентрат",0)) -> 0 | M5: =$I5*J5 -> 0 | N5: =$I5*K5 -> 0 | O5: 180 | P5: 17208.79
B6: 18.03.2020 | C6: =YEAR(B6) -> 2020 | D6: =MONTH(B6) -> 3 | E6: ИМ | F6: ФЕДЕРАТИВНАЯ РЕСПУБЛИКА ГЕРМАНИЯ | G6: РОССИЯ | H6: (КФ РОХШТОФФ 65). КОНЦЕНТРАТ СОЕВОГО БЕЛКА. СОСТАВ: КОНЦЕНТРАТ СОЕВОГО БЕЛКА. (КФ РОХШТОФФ 65). КОНЦЕНТРАТ СОЕВОГО БЕЛКА. СОСТАВ: КОНЦЕНТРАТ СОЕВОГО БЕЛКА. НЕ СОДЕРЖ.МОЛОЧНЫХ ЖИРОВ,САХАРОЗЫ,ИЗОГЛЮКОЗЫ,ГЛЮКОЗЫ ИЛИ КРАХМАЛА, ПОЛУЧЕННЫЙ ВОДНОЙ ЭКСТРАКЦИЕЙ, ДЛЯ ИСПОЛЬЗ. В ПИЩ. ПРОМЫШЛЕННОСТИ. KOENIGSHOF GMBH LEBENSMITTELADDITIVE ОТСУТСТВУЕТ KF ROHSTOFF 65 KF ROHSTOFF 65 20 | I6: =MIN(1,IFERROR(SEARCH(I$2,$H6),0)) -> 0 | J6: =MIN(1,IFERROR(SEARCH(J$2,$H6),0)) -> 0 | K6: =MIN(1,IFERROR(SEARCH(K$2,$H6),0)) -> 1 | L6: =IF(I6*J6=1,"Гороховый изолят",IF(I6*K6=1,"Гороховый концентрат",0)) -> 0 | M6: =$I6*J6 -> 0 | N6: =$I6*K6 -> 0 | O6: 20.24 | P6: 79.71
B7: 13.01.2022 | C7: =YEAR(B7) -> 2022 | D7: =MONTH(B7) -> 1 | E7: ИМ | F7: ГЕРМАНИЯ | G7: РОССИЯ | H7: (ТРИПТИЧЕСКИЙ ПЕПТОН ИЗ КАЗЕИНА) ТРИПТОН ДЛЯ БИОХИМИИ, РЕАГЕНТ ДЛЯ НАУЧНО-ИССЛЕДОВАТЕЛЬСКИХ РАБОТ, КАС № 91079-40-2, НЕ ДЛЯ МЕДИЦИНЫ, НЕ ДЛЯ ВЕТЕРИНАРИИ, НЕ ЯВЛЯЕТСЯ ОТХОДАМИ,НЕ ФАРМ. СУБСТАНЦИЯ, БЕЗ СОДЕРЖАНИЯ ЭТИЛОВОГО СПИРТА: | I7: =MIN(1,IFERROR(SEARCH(I$2,$H7),0)) -> 0 | J7: =MIN(1,IFERROR(SEARCH(J$2,$H7),0)) -> 0 | K7: =MIN(1,IFERROR(SEARCH(K$2,$H7),0)) -> 0 | L7: =IF(I7*J7=1,"Гороховый изолят",IF(I7*K7=1,"Гороховый концентрат",0)) -> 0 | M7: =$I7*J7 -> 0 | N7: =$I7*K7 -> 0 | O7: 28 | P7: 1689.43
B8: 45433 | C8: =YEAR(B8) -> 2024 | D8: =MONTH(B8) -> 5 | E8: Им | F8: КИТАЙ | G8: РОССИЯ | H8: <СЫРЬЁ (КОМПОНЕНТЫ) ДЛЯ ПРИМЕНЕНИЯ В ПИЩЕВОЙ ПРОМЫШЛЕННОСТИ>: ГИДРОЛИЗОВАННЫЙ КЕРАТИН. МЕЖДУНАРОДНОЕ (АНГЛИЙСКОЕ) НАЗВАНИЕ: HYDROLIZED KERATIN. СИНОНИM: ГИДРОЛИЗАТ КЕРАТИНА. CAS NO: 92113-31-0. ПАРТИЯ 2024032261. ДАТА ПРОИЗВОДСТВА 22.03.2024, СРОК | I8: =MIN(1,IFERROR(SEARCH(I$2,$H8),0)) -> 0 | J8: =MIN(1,IFERROR(SEARCH(J$2,$H8),0)) -> 0 | K8: =MIN(1,IFERROR(SEARCH(K$2,$H8),0)) -> 0 | L8: =IF(I8*J8=1,"Гороховый изолят",IF(I8*K8=1,"Гороховый концентрат",0)) -> 0 | M8: =$I8*J8 -> 0 | N8: =$I8*K8 -> 0 | O8: 100 | P8: 3353.34
B9: 20.08.2021 | C9: =YEAR(B9) -> 2021 | D9: =MONTH(B9) -> 8 | E9: ИМ | F9: ЯПОНИЯ | G9: РОССИЯ | H9: 1- СЕРТИФИЦИРОВАННЫЕ СТАНДАРТНЫЕ ОБРАЗЦЫ, РАСХОДНЫЙ МАТЕРИАЛ ДЛЯ ПРОВЕДЕНИЯ ЭКСПЕРТИЗЫ КАЧЕСТВА, НЕ ДЛЯ ПРОИЗВОДСТВА ИЛИ ИЗГОТОВЛЕНИЯ ЛЕКАРСТВЕННЫХ СРЕДСТВ, ПРЕПАРАТОВ, НЕ ДЛЯ МЕДИЦИНЫ, НЕ ДЛЯ КЛИНИЧЕСКИХ ИССЛЕДОВАНИЙ, | I9: =MIN(1,IFERROR(SEARCH(I$2,$H9),0)) -> 0 | J9: =MIN(1,IFERROR(SEARCH(J$2,$H9),0)) -> 0 | K9: =MIN(1,IFERROR(SEARCH(K$2,$H9),0)) -> 0 | L9: =IF(I9*J9=1,"Гороховый изолят",IF(I9*K9=1,"Гороховый концентрат",0)) -> 0 | M9: =$I9*J9 -> 0 | N9: =$I9*K9 -> 0 | O9: 1.7 | P9: 13761.87
B10: 7.536 | C10: =YEAR(B10) -> 1900 | D10: =MONTH(B10) -> 1 | E10: ЭК | F10: РОССИЯ | G10: ТАДЖИКИСТАН | H10: БЕЛКОВЫЕ КОНЦЕНТРАТЫ И ТЕКСТУРИРОВАННЫЕ БЕЛКОВЫЕ ВЕЩЕСТВА,НЕ СОДЕРЖ.МОЛОЧНЫХ ЖИРОВ,САХАРОЗЫ,ИЗОГЛЮКОЗЫ,ГЛЮКОЗЫ ИЛИ КРАХМАЛА ИЛИ СОДЕРЖАЩИЕ МЕНЕЕ 1,5 МАС.% МОЛОЧНОГО ЖИРА,5 МАС.% САХАРОЗЫ/ИЗОГЛЮКОЗЫ, 5 МАС.% ГЛЮКОЗЫ ИЛИ КРАХМАЛА: | I10: =MIN(1,IFERROR(SEARCH(I$2,$H10),0)) -> 0 | J10: =MIN(1,IFERROR(SEARCH(J$2,$H10),0)) -> 0 | K10: =MIN(1,IFERROR(SEARCH(K$2,$H10),0)) -> 1 | L10: =IF(I10*J10=1,"Гороховый изолят",IF(I10*K10=1,"Гороховый концентрат",0)) -> 0 | M10: =$I10*J10 -> 0 | N10: =$I10*K10 -> 0 | O10: 7.536 | P10: 104.43
B11: 7.52 | C11: =YEAR(B11) -> 1900 | D11: =MONTH(B11) -> 1 | E11: ЭК | F11: РОССИЯ | G11: ТАДЖИКИСТАН | H11: БЕЛКОВЫЕ КОНЦЕНТРАТЫ И ТЕКСТУРИРОВАННЫЕ БEЛКОВЫЕ ВЕЩЕСТВА: | I11: =MIN(1,IFERROR(SEARCH(I$2,$H11),0)) -> 0 | J11: =MIN(1,IFERROR(SEARCH(J$2,$H11),0)) -> 0 | K11: =MIN(1,IFERROR(SEARCH(K$2,$H11),0)) -> 1 | L11: =IF(I11*J11=1,"Гороховый изолят",IF(I11*K11=1,"Гороховый концентрат",0)) -> 0 | M11: =$I11*J11 -> 0 | N11: =$I11*K11 -> 0 | O11: 7.52 | P11: 123.25
B12: 25.08.2021 | C12: =YEAR(B12) -> 2021 | D12: =MONTH(B12) -> 8 | E12: ИМ | F12: ЯПОНИЯ | G12: РОССИЯ | H12: 1- СЕРТИФИЦИРОВАННЫЕ СТАНДАРТНЫЕ ОБРАЗЦЫ, РАСХОДНЫЙ МАТЕРИАЛ ДЛЯ ПРОВЕДЕНИЯ ЭКСПЕРТИЗЫ КАЧЕСТВА, НЕ ДЛЯ ПРОИЗВОДСТВА ИЛИ ИЗГОТОВЛЕНИЯ ЛЕКАРСТВЕННЫХ СРЕДСТВ, ПРЕПАРАТОВ, НЕ ДЛЯ МЕДИЦИНЫ, НЕ ДЛЯ КЛИНИЧЕСКИХ ИССЛЕДОВАНИЙ, | I12: =MIN(1,IFERROR(SEARCH(I$2,$H12),0)) -> 0 | J12: =MIN(1,IFERROR(SEARCH(J$2,$H12),0)) -> 0 | K12: =MIN(1,IFERROR(SEARCH(K$2,$H12),0)) -> 0 | L12: =IF(I12*J12=1,"Гороховый изолят",IF(I12*K12=1,"Гороховый концентрат",0)) -> 0 | M12: =$I12*J12 -> 0 | N12: =$I12*K12 -> 0 | O12: 1.7 | P12: 13712.57
B13: 23.06.2021 | C13: =YEAR(B13) -> 2021 | D13: =MONTH(B13) -> 6 | E13: ИМ | F13: ГЕРМАНИЯ | G13: РОССИЯ | H13: 1- СЕРТИФИЦИРОВАННЫЕ СТАНДАРТНЫЕ ОБРАЗЦЫ, РАСХОДНЫЙ МАТЕРИАЛ ДЛЯ ПРОВЕДЕНИЯ ЭКСПЕРТИЗЫ КАЧЕСТВА, НЕ ДЛЯ ПРОИЗВОДСТВА ИЛИ ИЗГОТОВЛЕНИЯ ЛЕКАРСТВЕННЫХ СРЕДСТВ, ПРЕПАРАТОВ, НЕ ДЛЯ МЕДИЦИНЫ, НЕ ДЛЯ КЛИНИЧЕСКИХ ИССЛЕДОВАНИЙ, | I13: =MIN(1,IFERROR(SEARCH(I$2,$H13),0)) -> 0 | J13: =MIN(1,IFERROR(SEARCH(J$2,$H13),0)) -> 0 | K13: =MIN(1,IFERROR(SEARCH(K$2,$H13),0)) -> 0 | L13: =IF(I13*J13=1,"Гороховый изолят",IF(I13*K13=1,"Гороховый концентрат",0)) -> 0 | M13: =$I13*J13 -> 0 | N13: =$I13*K13 -> 0 | O13: 1 | P13: 278.91
B14: 23.06.2021 | C14: =YEAR(B14) -> 2021 | D14: =MONTH(B14) -> 6 | E14: ИМ | F14: ЯПОНИЯ | G14: РОССИЯ | H14: 1- СЕРТИФИЦИРОВАННЫЕ СТАНДАРТНЫЕ ОБРАЗЦЫ, РАСХОДНЫЙ МАТЕРИАЛ ДЛЯ ПРОВЕДЕНИЯ ЭКСПЕРТИЗЫ КАЧЕСТВА, НЕ ДЛЯ ПРОИЗВОДСТВА ИЛИ ИЗГОТОВЛЕНИЯ ЛЕКАРСТВЕННЫХ СРЕДСТВ, ПРЕПАРАТОВ, НЕ ДЛЯ МЕДИЦИНЫ, НЕ ДЛЯ КЛИНИЧЕСКИХ ИССЛЕДОВАНИЙ, | I14: =MIN(1,IFERROR(SEARCH(I$2,$H14),0)) -> 0 | J14: =MIN(1,IFERROR(SEARCH(J$2,$H14),0)) -> 0 | K14: =MIN(1,IFERROR(SEARCH(K$2,$H14),0)) -> 0 | L14: =IF(I14*J14=1,"Гороховый изолят",IF(I14*K14=1,"Гороховый концентрат",0)) -> 0 | M14: =$I14*J14 -> 0 | N14: =$I14*K14 -> 0 | O14: 0.15 | P14: 1272.03
B15: 0.3 | C15: =YEAR(B15) -> 1900 | D15: =MONTH(B15) -> 1 | E15: ЭК | F15: РОССИЯ | H15: ПРОИЗВОДНЫЕ БЕЛКОВЫЕ ВЕЩЕСТВА (ПЕПТОНЫ), БЕЗ СОДЕРЖАНИЯ МОЛОЧНЫХ ЖИРОВ, ЭТИЛОВОГО СПИРТА, ПРЕКУРСОРОВ И КОНТРОЛИРУЕМЫХ ВЕЩЕСТВ, ДЛЯ ИСПОЛЬЗОВАНИЯ В МЕДИКО-ДИАГНОСТИЧЕСКИХ ЦЕЛЯХ: ПЕПТОН ФЕРМЕНТАТИВНЫЙ (НИЦФ) ООО НИЦФ ОТСУТСТВУЕТ .25 | I15: =MIN(1,IFERROR(SEARCH(I$2,$H15),0)) -> 0 | J15: =MIN(1,IFERROR(SEARCH(J$2,$H15),0)) -> 0 | K15: =MIN(1,IFERROR(SEARCH(K$2,$H15),0)) -> 0 | L15: =IF(I15*J15=1,"Гороховый изолят",IF(I15*K15=1,"Гороховый концентрат",0)) -> 0 | M15: =$I15*J15 -> 0 | N15: =$I15*K15 -> 0 | O15: 0.3 | P15: 21.97
B16: 23.06.2021 | C16: =YEAR(B16) -> 2021 | D16: =MONTH(B16) -> 6 | E16: ИМ | F16: ЯПОНИЯ | G16: РОССИЯ | H16: 1- СЕРТИФИЦИРОВАННЫЕ СТАНДАРТНЫЕ ОБРАЗЦЫ, РАСХОДНЫЙ МАТЕРИАЛ ДЛЯ ПРОВЕДЕНИЯ ЭКСПЕРТИЗЫ КАЧЕСТВА, НЕ ДЛЯ ПРОИЗВОДСТВА ИЛИ ИЗГОТОВЛЕНИЯ ЛЕКАРСТВЕННЫХ СРЕДСТВ, ПРЕПАРАТОВ, НЕ ДЛЯ МЕДИЦИНЫ, НЕ ДЛЯ КЛИНИЧЕСКИХ ИССЛЕДОВАНИЙ, | I16: =MIN(1,IFERROR(SEARCH(I$2,$H16),0)) -> 0 | J16: =MIN(1,IFERROR(SEARCH(J$2,$H16),0)) -> 0 | K16: =MIN(1,IFERROR(SEARCH(K$2,$H16),0)) -> 0 | L16: =IF(I16*J16=1,"Гороховый изолят",IF(I16*K16=1,"Гороховый концентрат",0)) -> 0 | M16: =$I16*J16 -> 0 | N16: =$I16*K16 -> 0 | O16: 0.01 | P16: 155.46
B17: 45490 | C17: =YEAR(B17) -> 2024 | D17: =MONTH(B17) -> 7 | E17: Им | F17: ШВЕЙЦАРИЯ | G17: РОССИЯ | H17: 100% ГИДРОЛИЗАТ КОЛЛАГЕНА, БЕЛКОВЫЙ ГИДРОЛИЗАТ ГОВЯЖЬЕГО ПРОИСХОЖДЕНИЯ, БИОЛОГИЧЕСКИ АКTИВНАЯ ДОБАВКА (БАД) К ПИЩЕ - ДОПОЛНИТЕЛЬНЫЙ ИСТОЧНИК АМИНОКИСЛОТ, ПОРОШОК В ПЛАСТИКОВЫХ БАНКАХ ПО 310 Г (ВСЕГО 2160 БАНОК), С МЕРНОЙ ЛОЖКОЙ; | I17: =MIN(1,IFERROR(SEARCH(I$2,$H17),0)) -> 0 | J17: =MIN(1,IFERROR(SEARCH(J$2,$H17),0)) -> 0 | K17: =MIN(1,IFERROR(SEARCH(K$2,$H17),0)) -> 0 | L17: =IF(I17*J17=1,"Гороховый изолят",IF(I17*K17=1,"Гороховый концентрат",0)) -> 0 | M17: =$I17*J17 -> 0 | N17: =$I17*K17 -> 0 | O17: 669.6 | P17: 24275.68
B18: 45492 | C18: =YEAR(B18) -> 2024 | D18: =MONTH(B18) -> 7 | E18: Им | F18: ШВЕЙЦАРИЯ | G18: РОССИЯ | H18: 100% ГИДРОЛИЗАТ КОЛЛАГЕНА, БЕЛКОВЫЙ ГИДРОЛИЗАТ ГОВЯЖЬЕГО ПРОИСХОЖДЕНИЯ, БИОЛОГИЧЕСКИ АКТИВНАЯ ДОБАВКА (БАД) К ПИЩЕ - ДОПОЛНИТЕЛЬНЫЙ ИСТОЧНИК АМИНОКИСЛОТ, ПОРОШОК В ПЛАСТИКОВЫХ БАНКАХ ПО 310 Г (ВСЕГО 2160 БАНОК), С МЕРНОЙ ЛОЖКОЙ; | I18: =MIN(1,IFERROR(SEARCH(I$2,$H18),0)) -> 0 | J18: =MIN(1,IFERROR(SEARCH(J$2,$H18),0)) -> 0 | K18: =MIN(1,IFERROR(SEARCH(K$2,$H18),0)) -> 0 | L18: =IF(I18*J18=1,"Гороховый изолят",IF(I18*K18=1,"Гороховый концентрат",0)) -> 0 | M18: =$I18*J18 -> 0 | N18: =$I18*K18 -> 0 | O18: 669.6 | P18: 24333.31
B19: 700 | C19: =YEAR(B19) -> 1901 | D19: =MONTH(B19) -> 11 | E19: ЭК | F19: РОССИЯ | H19: БЕЛОК ЖИВОТНЫЙ ИЗ СВИНОЙ ШКУРЫ, ПРЕДНАЗНАЧЕН ДЛЯ ИСПОЛЬЗОВАНИЯ В КАЧЕСТВЕ ДОБАВКИ В ПИЩЕВОЙ ПРОМЫШЛЕННОСТИ ДЛЯ ИСПОЛЬЗОВАНИЯ В ЭМУЛЬГИРОВАННЫХ МЯСНЫХ СИСТЕМАХ С ПРИМЕНЕНИЕМ КУТТЕРА: БЕЛОК ЖИВОТНЫЙ БЕЛКОТОН А 96 ООО ДБК ОТСУТСТВУЕТ 700 | I19: =MIN(1,IFERROR(SEARCH(I$2,$H19),0)) -> 0 | J19: =MIN(1,IFERROR(SEARCH(J$2,$H19),0)) -> 0 | K19: =MIN(1,IFERROR(SEARCH(K$2,$H19),0)) -> 0 | L19: =IF(I19*J19=1,"Гороховый изолят",IF(I19*K19=1,"Гороховый концентрат",0)) -> 0 | M19: =$I19*J19 -> 0 | N19: =$I19*K19 -> 0 | O19: 700 | P19: 3853.48
B20: 09.07.2022 | C20: =YEAR(B20) -> 2022 | D20: =MONTH(B20) -> 7 | E20: ИМ | F20: СОЕДИНЕННЫЕ ШТАТЫ | G20: РОССИЯ | H20: 1-БЕЛКОВЫЕ КОНЦЕНТРАТЫ И ТЕКСТУРИРОВАННЫЕ БЕЛКОВЫЕ ВЕЩЕСТВА,НЕ СОДЕРЖ.МОЛОЧНЫХ ЖИРОВ,САХАРОЗЫ,ИЗОГЛЮКОЗЫ,ГЛЮКОЗЫ ИЛИ КРАХМАЛА ИЛИ СОДЕРЖАЩИЕ МЕНЕЕ 1,5 МАС.% МОЛОЧНОГО ЖИРА,5 МАС.% САХАРОЗЫ/ИЗОГЛЮКОЗЫ, 5 МАС.% ГЛЮКОЗЫ ИЛИ КРАХМАЛА: | I20: =MIN(1,IFERROR(SEARCH(I$2,$H20),0)) -> 0 | J20: =MIN(1,IFERROR(SEARCH(J$2,$H20),0)) -> 0 | K20: =MIN(1,IFERROR(SEARCH(K$2,$H20),0)) -> 1 | L20: =IF(I20*J20=1,"Гороховый изолят",IF(I20*K20=1,"Гороховый концентрат",0)) -> 0 | M20: =$I20*J20 -> 0 | N20: =$I20*K20 -> 0 | O20: 4989.6 | P20: 30386.66
B21: 45482 | C21: =YEAR(B21) -> 2024 | D21: =MONTH(B21) -> 7 | E21: Им | F21: КИТАЙ | G21: РОССИЯ | H21: 1-КОРМОВАЯ ДОБАВKА: БЕЛОК РАСТИТЕЛЬНЫЙ "МСГ БАЙ-ПРОДУКТ", С МАРКИРОВКОЙ "MSG BY-PRODUCT". СОСТАВ "МСГ БАЙ-ПРОДУКТ" ПРЕДСТАВЛЯЕТ СОБОЙ ПОБОЧНЫЙ ПРОДУКТ КУЛЬТИВИРОВАНИЯ CORYNEBACTERIUM GLUTAMICUM ПРИ ПРОИЗВОДСТВЕ ГЛУТАМИНОВОЙ КИСЛОТЫ. | I21: =MIN(1,IFERROR(SEARCH(I$2,$H21),0)) -> 0 | J21: =MIN(1,IFERROR(SEARCH(J$2,$H21),0)) -> 0 | K21: =MIN(1,IFERROR(SEARCH(K$2,$H21),0)) -> 0 | L21: =IF(I21*J21=1,"Гороховый изолят",IF(I21*K21=1,"Гороховый концентрат",0)) -> 0 | M21: =$I21*J21 -> 0 | N21: =$I21*K21 -> 0 | O21: 65000 | P21: 35328.87
B22: 377.52 | C22: =YEAR(B22) -> 1901 | D22: =MONTH(B22) -> 1 | E22: ЭК | F22: РОССИЯ | H22: ГОТОВЫЕ ПИЩЕВЫЕ ПРОДУКТЫ: ЗАМЕНИТЕЛИ ИКРЫ ЛОСОСЕВЫХ, ПРЕДСТАВЛЯЮТ СОБОЙ БЕЛКОВЫЙ КОНЦЕНТРАТ,НЕ СОДЕРЖАЩИЙ МОЛОЧНЫХ ЖИРОВ, САХАРОЗЫ, ИЗОГЛЮКОЗЫ, ГЛЮКОЗЫ ИЛИ КРАХМАЛА ИЛИ СОДЕРЖАЩИЙ МЕНЕЕ 1,5 МАС% МОЛОЧНОГО ЖИРА, 5 МАС% САХАРОЗЫ ИЛИ ИЗОГЛЮКОЗЫ, 5 ИКРА АНАЛОГ. КРАСНАЯ КЕТА 220 Г С/Б ББ ИКРА АНАЛОГ. КРАСНАЯ ГОРБУША 220 Г С/Б ББ ИКРА АНАЛОГ. КРАСНАЯ ГОРБУША 220 Г С/Б ББ ИКРА АНАЛОГ. КРАСНАЯ КЕТА 220 Г С/Б ББ ИКРА АНАЛОГ. КРАСНАЯ ФОРЕЛЬ 220 Г С/Б ББ ИКРА АНАЛОГ. КРАСНАЯ КЕТА 220 Г С/Б ББ ИКРА АНАЛОГ. КРАСНАЯ НЕРКА 220 Г С/Б ББ ИКРА АНАЛОГ. КРАСНАЯ ФОРЕЛЬ 220 Г С/Б ББ МАС.% ГЛЮКОЗЫ ИЛИ КРАХМАЛА, СФОРМОВАННЫЙ В ШАРИКИ, ВИЗУАЛЬНО СХОДНЫЕ С ИКРОЙ ЛОСОСЕВЫХ РЫБ. ООО ТОРГОВЫЙ ДОМ БАЛТИЙСКИЙ БЕРЕГ БАЛТИЙСКИЙ БЕРЕГ БАЛТИЙСКИЙ БЕРЕГ ОТСУТСТВУЕТ ОТСУТСТВУЕТ 402 ООО ТОРГОВЫЙ ДОМ БАЛТИЙСКИЙ БЕРЕГ БАЛТИЙСКИЙ БЕРЕГ БАЛТИЙСКИЙ БЕРЕГ ОТСУТСТВУЕТ ОТСУТСТВУЕТ 300 ООО ТОРГОВЫЙ ДОМ БАЛТИЙСКИЙ БЕРЕГ БАЛТИЙСКИЙ БЕРЕГ БАЛТИЙСКИЙ БЕРЕГ ОТСУТСТВУЕТ ОТСУТСТВУЕТ 18 ООО ТОРГОВЫЙ ДОМ БАЛТИЙСКИЙ БЕРЕГ БАЛТИЙСКИЙ БЕРЕГ БАЛТИЙСКИЙ БЕРЕГ ОТСУТСТВУЕТ ОТСУТСТВУЕТ 168 ООО ТОРГОВЫЙ ДОМ БАЛТИЙСКИЙ БЕРЕГ БАЛТИЙСКИЙ БЕРЕГ БАЛТИЙСКИЙ БЕРЕГ ОТСУТСТВУЕТ ОТСУТСТВУЕТ 300 ООО ТОРГОВЫЙ ДОМ БАЛТИЙСКИЙ БЕРЕГ БАЛТИЙСКИЙ БЕРЕГ БАЛТИЙСКИЙ БЕРЕГ ОТСУТСТВУЕТ ОТСУТСТВУЕТ 84 ООО ТОРГОВЫЙ ДОМ БАЛТИЙСКИЙ БЕРЕГ БАЛТИЙСКИЙ БЕРЕГ БАЛТИЙСКИЙ БЕРЕГ ОТСУТСТВУЕТ ОТСУТСТВУЕТ 360 ООО ТОРГОВЫЙ ДОМ БАЛТИЙСКИЙ БЕРЕГ БАЛТИЙСКИЙ БЕРЕГ БАЛТИЙСКИЙ БЕРЕГ ОТСУТСТВУЕТ ОТСУТСТВУЕТ 84 | I22: =MIN(1,IFERROR(SEARCH(I$2,$H22),0)) -> 0 | J22: =MIN(1,IFERROR(SEARCH(J$2,$H22),0)) -> 0 | K22: =MIN(1,IFERROR(SEARCH(K$2,$H22),0)) -> 1 | L22: =IF(I22*J22=1,"Гороховый изолят",IF(I22*K22=1,"Гороховый концентрат",0)) -> 0 | M22: =$I22*J22 -> 0 | N22: =$I22*K22 -> 0 | O22: 377.52 | P22: 1154.27
B23: 02.03.2020 | C23: =YEAR(B23) -> 2020 | D23: =MONTH(B23) -> 3 | E23: ИМ | F23: ШВЕЦИЯ | G23: РОССИЯ | H23: 1-ПОРОШКООБРАЗНЫЙ СВИНОЙ БЕЛОК GELIPRO ИЗ СЫРОЙ КОЖИ ДЛЯ ПРОИЗВОДСТВА ЭКСТРУДИРОВАННЫХ СУХИХ КОРМОВ ПРОДУКТ ПОЛУЧАЮТ ПУТЕМ ЭКСТРАКЦИИ ЖИРА ИЗ ИЗМЕЛЬЧЕННОЙ СВИНОЙ НЕДУБЛЕНОЙ КОЖИ С УДАЛЕННОЙ ЩЕТИНОЙ, ОБРАБОТКИ, СУШКИ И РАЗМОЛА СУХОГО БЕЛКА. СОЕДИНЕНИЙ 6-ТИ ВАЛЕНТНОГО ХРОМА И БИОЦИДОВ НЕ СОДЕРЖИТ. ДАННЫЙ ПРОДУКТ ИСПОЛЬЗУЕТСЯ КАК ЗАМЕНИТЕЛЬ МЯСОСЫРЬЯ ПРИ ИЗГОТОВЛЕНИИ СУХИХ КОРМОВ ДЛЯ КОШЕК И СОБАК. ДОБАВЛЕНИЕ ПРОИСХОДИТ НА ЭТАПЕ РЕЦЕПТУРНОЙ КОМПОНОВКИ КОРМА. СОДЕРЖАНИЕ БЕЛКА 83.4%, СОДЕРЖАНИЕ ЖИРА 9.8%. СОДЕРЖАНИЕ СУХОГО ВЕЩЕСТВА 98.1%, СОДЕРЖАНИЕ ЗОЛЫ 5.1%. GELITA SWEDEN AB GELITA 7130010 20080 | I23: =MIN(1,IFERROR(SEARCH(I$2,$H23),0)) -> 0 | J23: =MIN(1,IFERROR(SEARCH(J$2,$H23),0)) -> 0 | K23: =MIN(1,IFERROR(SEARCH(K$2,$H23),0)) -> 0 | L23: =IF(I23*J23=1,"Гороховый изолят",IF(I23*K23=1,"Гороховый концентрат",0)) -> 0 | M23: =$I23*J23 -> 0 | N23: =$I23*K23 -> 0 | O23: 20080 | P23: 25568.93
B24: 12.03.2020 | C24: =YEAR(B24) -> 2020 | D24: =MONTH(B24) -> 3 | E24: ИМ | F24: ШВЕЦИЯ | G24: РОССИЯ | H24: 1-ПОРОШКООБРАЗНЫЙ СВИНОЙ БЕЛОК GELIPRO ИЗ СЫРОЙ КОЖИ ДЛЯ ПРОИЗВОДСТВА ЭКСТРУДИРОВАННЫХ СУХИХ КОРМОВ; ПРОДУКТ ПОЛУЧАЮТ ПУТЕМ ЭКСТРАКЦИИ ЖИРА ИЗ ИЗМЕЛЬЧЕННОЙ СВИНОЙ НЕДУБЛЕНОЙ КОЖИ С УДАЛЕННОЙ ЩЕТИНОЙ, ОБРАБОТКИ, СУШКИ И РАЗМОЛА СУХОГО БЕЛКА. СОЕДИНЕНИЙ 6-ТИ ВАЛЕНТНОГО ХРОМА И БИОЦИДОВ НЕ СОДЕРЖИТ. ДАННЫЙ ПРОДУКТ ИСПОЛЬЗУЕТСЯ КАК ЗАМЕНИТЕЛЬ МЯСОСЫРЬЯ ПРИ ИЗГОТОВЛЕНИИ СУХИХ КОРМОВ ДЛЯ КОШЕК И СОБАК. ДОБАВЛЕНИЕ ПРОИСХОДИТ НА ЭТАПЕ РЕЦЕПТУРНОЙ КОМПОНОВКИ КОРМА. СОДЕРЖАНИЕ БЕЛКА 83.4%, СОДЕРЖАНИЕ ЖИРА 9.8%. СОДЕРЖАНИЕ СУХОГО ВЕЩЕСТВА 98.1%, СОДЕРЖАНИЕ ЗОЛЫ 5.1%. GELITA SWEDEN AB GELITA 7130010 20060 | I24: =MIN(1,IFERROR(SEARCH(I$2,$H24),0)) -> 0 | J24: =MIN(1,IFERROR(SEARCH(J$2,$H24),0)) -> 0 | K24: =MIN(1,IFERROR(SEARCH(K$2,$H24),0)) -> 0 | L24: =IF(I24*J24=1,"Гороховый изолят",IF(I24*K24=1,"Гороховый концентрат",0)) -> 0 | M24: =$I24*J24 -> 0 | N24: =$I24*K24 -> 0 | O24: 20060 | P24: 26311.75
B25: 26.11.2020 | C25: =YEAR(B25) -> 2020 | D25: =MONTH(B25) -> 11 | E25: ИМ | F25: СОЕДИНЕННОЕ КОРОЛЕВСТВО | G25: РОССИЯ | H25: 693623 EXTRUDED SOYA 9403-ТЕКСТУРИРОВАННАЯ СОЕВАЯ МУКА ДЛЯ ИСПОЛЬЗОВАНИЯ В ПИЩЕВОЙ ПРОМЫШЛЕННОСТИ ПРИ ПРОИЗВОДСТВЕ ПИЩЕВЫХ ПРОДУКТОВ.УПАКОВАНА В МЕШОК ПО 10 КГ. НЕ СОДЕРЖИТ ГМО,МОЛОЧНЫХ,ЖИРОВ,САХАРОЗЫ, ИЗОГЛЮКОЗЫ, ГЛЮКОЗЫ,КРАХМАЛА. ПРЕДНАЗНАЧЕНА ДЛЯ | I25: =MIN(1,IFERROR(SEARCH(I$2,$H25),0)) -> 0 | J25: =MIN(1,IFERROR(SEARCH(J$2,$H25),0)) -> 0 | K25: =MIN(1,IFERROR(SEARCH(K$2,$H25),0)) -> 0 | L25: =IF(I25*J25=1,"Гороховый изолят",IF(I25*K25=1,"Гороховый концентрат",0)) -> 0 | M25: =$I25*J25 -> 0 | N25: =$I25*K25 -> 0 | O25: 10 | P25: 54.24
B26: 15.02.2021 | C26: =YEAR(B26) -> 2021 | D26: =MONTH(B26) -> 2 | E26: ИМ | F26: СОЕДИНЕННОЕ КОРОЛЕВСТВО | G26: РОССИЯ | H26: 693623 EXTRUDED SOYA 9403-ТЕКСТУРИРОВАННАЯ СОЕВАЯ МУКА ДЛЯ ИСПОЛЬЗОВАНИЯ В ПИЩЕВОЙ ПРОМЫШЛЕННОСТИ ПРИ ПРОИЗВОДСТВЕ ПИЩЕВЫХ ПРОДУКТОВ.УПАКОВАНА В МЕШОК ПО 10 КГ. НЕ СОДЕРЖИТ ГМО,МОЛОЧНЫХ,ЖИРОВ,САХАРОЗЫ, ИЗОГЛЮКОЗЫ, ГЛЮКОЗЫ,КРАХМАЛА. ПРЕДНАЗНАЧЕНА ДЛЯ | I26: =MIN(1,IFERROR(SEARCH(I$2,$H26),0)) -> 0 | J26: =MIN(1,IFERROR(SEARCH(J$2,$H26),0)) -> 0 | K26: =MIN(1,IFERROR(SEARCH(K$2,$H26),0)) -> 0 | L26: =IF(I26*J26=1,"Гороховый изолят",IF(I26*K26=1,"Гороховый концентрат",0)) -> 0 | M26: =$I26*J26 -> 0 | N26: =$I26*K26 -> 0 | O26: 70 | P26: 171.6
B27: 09.06.2023 | C27: =YEAR(B27) -> 2023 | D27: =MONTH(B27) -> 6 | E27: ИМ | F27: СОЕДИНЕННЫЕ ШТАТЫ | G27: РОССИЯ | H27: B- ЛАКТОГЛОБУЛИН , ИЗ КОРОВЬЕГО МОЛОКА, ЛАБОРАТОРНЫЙ РЕАГЕНТ ДЛЯ ПРОВЕДЕНИЯ ЛАБОРАТОРНЫХ И НАУЧНО-ИССЛЕДОВАТЕЛЬСКИХ РАБОТ. РАЗРЕШЕНИЕ ФС/УВН-03/ 596100 ОТ <23> МАРТА 2023 Г., СРОКИ ГОДНОСТИ ОТ 15.07.2021 ДО 07.2025, KАС № 9045-23-2, НЕ ДЛЯ МЕДИЦИНЫ, | I27: =MIN(1,IFERROR(SEARCH(I$2,$H27),0)) -> 0 | J27: =MIN(1,IFERROR(SEARCH(J$2,$H27),0)) -> 0 | K27: =MIN(1,IFERROR(SEARCH(K$2,$H27),0)) -> 0 | L27: =IF(I27*J27=1,"Гороховый изолят",IF(I27*K27=1,"Гороховый концентрат",0)) -> 0 | M27: =$I27*J27 -> 0 | N27: =$I27*K27 -> 0 | O27: 0.001 | P27: 398.68
B28: 23.04.2021 | C28: =YEAR(B28) -> 2021 | D28: =MONTH(B28) -> 4 | E28: ИМ | F28: СОЕДИНЕННЫЕ ШТАТЫ | G28: РОССИЯ | H28: BACTO МЯСНОЙ ЭКСТРАКТ, СУХОЙ, ЛАБОРАТОРНЫЙ РЕАКТИВ, НЕ ДЛЯ МЕДИЦИНЫ, НЕ ДЛЯ ВЕТЕРИНАРИИ, НЕ ЯВЛЯЕТСЯ ОТХОДАМИ,НЕ ФАРМ. СУБСТАНЦИЯ, БЕЗ СОДЕРЖАНИЯ ЭТИЛОВОГО СПИРТА: | I28: =MIN(1,IFERROR(SEARCH(I$2,$H28),0)) -> 0 | J28: =MIN(1,IFERROR(SEARCH(J$2,$H28),0)) -> 0 | K28: =MIN(1,IFERROR(SEARCH(K$2,$H28),0)) -> 0 | L28: =IF(I28*J28=1,"Гороховый изолят",IF(I28*K28=1,"Гороховый концентрат",0)) -> 0 | M28: =$I28*J28 -> 0 | N28: =$I28*K28 -> 0 | O28: 1.9 | P28: 310.69
B29: 12.01.2022 | C29: =YEAR(B29) -> 2022 | D29: =MONTH(B29) -> 1 | E29: ИМ | F29: СОЕДИНЕННЫЕ ШТАТЫ | G29: РОССИЯ | H29: BАСТО МЯСНОЙ ПЕПТОН, ДЛЯ МИКРОБИОЛОГИИ, 500 Г, ЛАБОРАТОРНЫЙРЕАГЕНТ ДЛЯ ПРОВЕДЕНИЯ ЛАБОРАТОРНЫХ И НАУЧНО-ИССЛЕДОВАТЕЛЬСКИХ РАБОТ, КАС № 73049-73-7, НЕ ДЛЯ МЕДИЦИНЫ, НЕ ДЛЯ ВЕТЕРИНАРИИ, НЕ ЯВЛЯЕТСЯ ОТХОДАМИ,НЕ ФАРМ. СУБСТАНЦИЯ, БЕЗ СОДЕРЖАНИЯ | I29: =MIN(1,IFERROR(SEARCH(I$2,$H29),0)) -> 0 | J29: =MIN(1,IFERROR(SEARCH(J$2,$H29),0)) -> 0 | K29: =MIN(1,IFERROR(SEARCH(K$2,$H29),0)) -> 0 | L29: =IF(I29*J29=1,"Гороховый изолят",IF(I29*K29=1,"Гороховый концентрат",0)) -> 0 | M29: =$I29*J29 -> 0 | N29: =$I29*K29 -> 0 | O29: 4.4 | P29: 1413.35
B30: 13.07.2021 | C30: =YEAR(B30) -> 2021 | D30: =MONTH(B30) -> 7 | E30: ИМ | F30: ФРАНЦИЯ | G30: РОССИЯ | H30: BАСТО ТРИПТИЧЕСКИЙ ПЕПТОН ИЗ КАЗЕИНА (ТРИПТОН), ДЛЯ МИКРОБИОЛОГИИ, 10 КГ, ЛАБОРАТОРНЫЙ РЕАКТИВ, КАС № 91079-40-2, НЕ ДЛЯ МЕДИЦИНЫ, НЕ ДЛЯ ВЕТЕРИНАРИИ, НЕ ЯВЛЯЕТСЯ ОТХОДАМИ,НЕ ФАРМ. СУБСТАНЦИЯ, БЕЗ СОДЕРЖАНИЯ ЭТИЛОВОГО СПИРТА: | I30: =MIN(1,IFERROR(SEARCH(I$2,$H30),0)) -> 0 | J30: =MIN(1,IFERROR(SEARCH(J$2,$H30),0)) -> 0 | K30: =MIN(1,IFERROR(SEARCH(K$2,$H30),0)) -> 0 | L30: =IF(I30*J30=1,"Гороховый изолят",IF(I30*K30=1,"Гороховый концентрат",0)) -> 0 | M30: =$I30*J30 -> 0 | N30: =$I30*K30 -> 0 | O30: 24 | P30: 4152.09
B31: 4813.68 | C31: =YEAR(B31) -> 1913 | D31: =MONTH(B31) -> 3 | E31: ЭК | F31: ИТАЛЬЯНСКАЯ РЕСПУБЛИКА | H31: СПЕЦИАЛИЗИРОВАННЫЙ ПИЩЕВОЙ ПРОДУКТ ДЛЯ ДИЕТИЧЕСКОГО И ПРОФИЛАКТИЧЕСКОГО ПИТАНИЯ ФОРМУЛА 3 ПРОДУКТ БЕЛКОВЫЙ СПЕЦИАЛИЗИРОВАННЫЙ СУХОЙ ПОРОШКООБРАЗНЫЙ БЕЛКОВЫЙ ПРОДУКТ В УПАКОВКЕ ДЛЯ РОЗНИЧНОЙ ПРОДАЖИ НА ОСНОВЕ СОЕВОГО БЕЛКА С ДОБАВЛЕНИЕМ НЕЗНАЧИТЕЛЬН :СОСТАВ: ИЗОЛЯТ СОЕВОГО БЕЛКА, МОЛОЧНЫЙ БЕЛОК, ВАНИЛИН, АНТИСЛЕЖИВАЮЩИЙ АГЕНТ (КРЕМНИЯ ДИОКСИД), АРОМАТИЗАТОР (АРОМАТИЗАТОРЫ, СТАБИЛИЗАТОР: ГУММИАРАБИК). РАСФАСОВАНО В ПЛАСТИКОВЫЕ БАНКИ ПО 240ГР. (НЕТТО). ОГО КОЛИЧЕСТВА МОЛОЧНОГО БЕЛКА (СУММАРНЫМ СОДЕРЖАНИЕМ 82.2 МАС.%), СОДЕРЖАЩИЙ В СВОЕМ СОСТАВЕ ЖИРОВОЙ КОМПОНЕНТ 4,9 МАС.% ЛАКТОЗУ ИЗ СОСТАВА МОЛОЧНОГО СЫРЬЯ (1,0 МАС.%) , АРОМАТООБРАЗЮЩИЙ КОМПОНЕНТ (ВАНИЛИН) И ПРОЧИЕ ФУНКЦИОНАЛЬНЫЕ ДОБАВКИ (СОГЛАСНО ДАННЫМ С ЭТИКЕТКИ ТОВАРА- КРЕМНИЯ ДИОКСИД (АНТИСЛЕЖИВАЮЩИЙ АГЕНТ), ГУММИАРАБИК (СТАБИЛИЗАТОР), СОДЕРЖАНИЕ МОЛОЧНОГО ЖИРАИЗ СОСТАВА МОЛОЧНОГО СЫРЬЯ СОСТАВЛЯЕТ МЕНЕЕ 1,5 МАС. % (ФАКТИЧЕСКИ 0,5 МАС.%), НЕ СОДЕРЖИТ В СОСТАВЕ КРАХМАЛ И ПРОДУКТЫЕГО ГИДРОЛИ ЗА, ГЛЮКОЗУ, ФРУКТОЗУ, САХАРОЗУ. РАСФАСОВАНО В ПЛАСТИКОВЫЕ БАНКИ ПО 240ГР. (НЕТТО) FINE FOODS NTM S.P.A HERBALIFE ФОРМУЛА 3 ПРОДУКТ БЕЛКОВЫЙ СПЕЦИАЛИЗИРОВАННЫЙ 0242RS ОТСУТСТВУЕТ 15528 | I31: =MIN(1,IFERROR(SEARCH(I$2,$H31),0)) -> 0 | J31: =MIN(1,IFERROR(SEARCH(J$2,$H31),0)) -> 1 | K31: =MIN(1,IFERROR(SEARCH(K$2,$H31),0)) -> 0 | L31: =IF(I31*J31=1,"Гороховый изолят",IF(I31*K31=1,"Гороховый концентрат",0)) -> 0 | M31: =$I31*J31 -> 0 | N31: =$I31*K31 -> 0 | O31: 4813.68 | P31: 29504.56
B32: 04.05.2022 | C32: =YEAR(B32) -> 2022 | D32: =MONTH(B32) -> 5 | E32: ИМ | F32: СОЕДИНЕННЫЕ ШТАТЫ | G32: РОССИЯ | H32: BАСТО ТРИПТИЧЕСКИЙ ПЕПТОН ИЗ КАЗЕИНА (ТРИПТОН),ЛАБОРАТОРНЫЙРЕАГЕНТ ДЛЯ ПРОВЕДЕНИЯ ЛАБОРАТОРНЫХ И НАУЧНО-ИССЛЕДОВАТЕЛЬСКИХ РАБОТ, КАС № 91079-40-2, НЕ ДЛЯ МЕДИЦИНЫ, НЕ ДЛЯ ВЕТЕРИНАРИИ, НЕ ЯВЛЯЕТСЯ ОТХОДАМИ,НЕ ФАРМ. СУБСТАНЦИЯ, БЕЗ СОДЕРЖАНИЯ ЭТИЛОВОГО | I32: =MIN(1,IFERROR(SEARCH(I$2,$H32),0)) -> 0 | J32: =MIN(1,IFERROR(SEARCH(J$2,$H32),0)) -> 0 | K32: =MIN(1,IFERROR(SEARCH(K$2,$H32),0)) -> 0 | L32: =IF(I32*J32=1,"Гороховый изолят",IF(I32*K32=1,"Гороховый концентрат",0)) -> 0 | M32: =$I32*J32 -> 0 | N32: =$I32*K32 -> 0 | O32: 0.8 | P32: 247.61
B33: 17008 | C33: =YEAR(B33) -> 1946 | D33: =MONTH(B33) -> 7 | E33: ЭК | F33: РОССИЯ | H33: МУКА СОЕВАЯ ТЕКСТУРИРОВАННАЯ РОССТЕКС Ф 3-5/Р2, С СОДЕРЖАНИЕМ БЕЛКА НЕ МЕНЕЕ 47%, СЫРОГО ЖИРА НЕ БОЛЕЕ 2.0 %, ПРЕДНАЗНАЧЕННАЯ ДЛЯ ПРИГОТОВЛЕНИЯ ПИЩИ, А ТАК ЖЕ ДЛЯ ПЕРЕРАБОТКИ В ГОТОВЫЕ БЛЮДА - 17008 КГ (1063 МЕШКА ПО 16 КГ). : ЗАО ПАРТНЕР-М ОТСУТСТВУЕТ 0 | I33: =MIN(1,IFERROR(SEARCH(I$2,$H33),0)) -> 0 | J33: =MIN(1,IFERROR(SEARCH(J$2,$H33),0)) -> 0 | K33: =MIN(1,IFERROR(SEARCH(K$2,$H33),0)) -> 0 | L33: =IF(I33*J33=1,"Гороховый изолят",IF(I33*K33=1,"Гороховый концентрат",0)) -> 0 | M33: =$I33*J33 -> 0 | N33: =$I33*K33 -> 0 | O33: 17008 | P33: 13807.05
B34: 17008 | C34: =YEAR(B34) -> 1946 | D34: =MONTH(B34) -> 7 | E34: ЭК | F34: РОССИЯ | H34: МУКА СОЕВАЯ ТЕКСТУРИРОВАННАЯ РОССТЕКС Ф 3-5/Р2, С СОДЕРЖАНИЕМ БЕЛКА НЕ МЕНЕЕ 47%, СЫРОГО ЖИРА НЕ БОЛЕЕ 2.0 %, ПРЕДНАЗНАЧЕННАЯ ДЛЯ ПРИГОТОВЛЕНИЯ ПИЩИ, А ТАК ЖЕ ДЛЯ ПЕРЕРАБОТКИ В ГОТОВЫЕ БЛЮДА - 17008 КГ (1063 МЕШКА ПО 16 КГ). : ЗАО ПАРТНЕР-М ОТСУТСТВУЕТ 0 | I34: =MIN(1,IFERROR(SEARCH(I$2,$H34),0)) -> 0 | J34: =MIN(1,IFERROR(SEARCH(J$2,$H34),0)) -> 0 | K34: =MIN(1,IFERROR(SEARCH(K$2,$H34),0)) -> 0 | L34: =IF(I34*J34=1,"Гороховый изолят",IF(I34*K34=1,"Гороховый концентрат",0)) -> 0 | M34: =$I34*J34 -> 0 | N34: =$I34*K34 -> 0 | O34: 17008 | P34: 12811.27
B35: 16848 | C35: =YEAR(B35) -> 1946 | D35: =MONTH(B35) -> 2 | E35: ЭК | F35: РОССИЯ | H35: МУКА СОЕВАЯ ТЕКСТУРИРОВАННАЯ РОССТЕКС Ф 3-5/Р2, С СОДЕРЖАНИЕМ БЕЛКА НЕ МЕНЕЕ 47%, СЫРОГО ЖИРА НЕ БОЛЕЕ 2.0 %, ПРЕДНАЗНАЧЕННАЯ ДЛЯ ПРИГОТОВЛЕНИЯ ПИЩИ, А ТАК ЖЕ ДЛЯ ПЕРЕРАБОТКИ В ГОТОВЫЕ БЛЮДА - 16848 КГ (1053 МЕШКА ПО 16 КГ). : ЗАО ПАРТНЕР-М ОТСУТСТВУЕТ 0 | I35: =MIN(1,IFERROR(SEARCH(I$2,$H35),0)) -> 0 | J35: =MIN(1,IFERROR(SEARCH(J$2,$H35),0)) -> 0 | K35: =MIN(1,IFERROR(SEARCH(K$2,$H35),0)) -> 0 | L35: =IF(I35*J35=1,"Гороховый изолят",IF(I35*K35=1,"Гороховый концентрат",0)) -> 0 | M35: =$I35*J35 -> 0 | N35: =$I35*K35 -> 0 | O35: 16848 | P35: 13286.94
B36: 24.11.2022 | C36: =YEAR(B36) -> 2022 | D36: =MONTH(B36) -> 11 | E36: ИМ | F36: ФРАНЦИЯ | G36: РОССИЯ | H36: COLLAGENNA H - ВОДНЫЙ РАСТВОР МОРСКОГО ГИДРОЛИЗОВАННОГО КОЛЛАГЕНА, ЭКСТРАГИРОВАННОГО ИЗ КОЖИ РЫБЫ,ПРИМЕНЯЕТСЯ В КОСМЕТИЧЕСКОЙ ПРОМЫШЛЕННОСТИ В КАЧЕСТВЕ СЫРЬЯ ПРИ ПРОИЗВОДСТВЕ СРЕДСТВ ПО УХОДУ ЗА КОЖЕЙ: | I36: =MIN(1,IFERROR(SEARCH(I$2,$H36),0)) -> 0 | J36: =MIN(1,IFERROR(SEARCH(J$2,$H36),0)) -> 0 | K36: =MIN(1,IFERROR(SEARCH(K$2,$H36),0)) -> 0 | L36: =IF(I36*J36=1,"Гороховый изолят",IF(I36*K36=1,"Гороховый концентрат",0)) -> 0 | M36: =$I36*J36 -> 0 | N36: =$I36*K36 -> 0 | O36: 25 | P36: 444.76
B37: 30.06.2020 | C37: =YEAR(B37) -> 2020 | D37: =MONTH(B37) -> 6 | E37: ИМ | F37: СОЕДИНЕННОЕ КОРОЛЕВСТВО | G37: РОССИЯ | H37: CROTEIN C-PW-(WD).ГИДРОЛИЗОВАННЫЙ КОЛЛАГЕН. АРТИКУЛ IDH68292.1 МЕШОК ПО 25 КГ. ПРИМЕНЯЕТСЯ В КОСМЕТИЧЕСКОЙ ПРОМЫШЛЕННОСТИ. НЕ ДЛЯ ПИЩ., НЕ ДЛЯ ЛЕК., НЕ ДЛЯ ВЕТ. : CRODA EUROPE LIMITED ОТСУТСТВУЕТ IDH68292 25 | I37: =MIN(1,IFERROR(SEARCH(I$2,$H37),0)) -> 0 | J37: =MIN(1,IFERROR(SEARCH(J$2,$H37),0)) -> 0 | K37: =MIN(1,IFERROR(SEARCH(K$2,$H37),0)) -> 0 | L37: =IF(I37*J37=1,"Гороховый изолят",IF(I37*K37=1,"Гороховый концентрат",0)) -> 0 | M37: =$I37*J37 -> 0 | N37: =$I37*K37 -> 0 | O37: 25 | P37: 465.49
B38: 03.04.2020 | C38: =YEAR(B38) -> 2020 | D38: =MONTH(B38) -> 4 | E38: ИМ | F38: КИТАЙ | G38: РОССИЯ | H38: CYTOCHROME C FROM BOVINE HEART/ ЦИТОХРОМ С ИЗ БЫЧЬЕГО СЕРДЦА, НОМЕР ПАРТИИ (СЕРИЯ) DCY200201(P), CAS N 9007-43-6, ВСЕГО 1 УПАКОВКА (ДВОЙНОЙ ПОЛИЭТИЛЕНОВЫЙ ПАКЕТ В АЛЮМИНИЕВОМ ПАКЕТЕ): ВЕС ВЕЩЕСТВА 50 ГРАММ -СУБСТАНЦИЯ-ПОРОШОК В КАЧЕСТВЕ ОБРАЗЦА ДЛЯ И : CYTOCHROME C FROM BOVINE HEART/ ЦИТОХРОМ С ИЗ БЫЧЬЕГО СЕРДЦА, НОМЕР ПАРТИИ (СЕРИЯ) DCY200201(P), CAS N 9007-43-6, ВСЕГО 1 УПАКОВКА (ДВОЙНОЙ ПОЛИЭТИЛЕНОВЫЙ ПАКЕТ В АЛЮМИНИЕВОМ ПАКЕТЕ): ВЕС ВЕЩЕСТВА 50 ГРАММ -СУБСТАНЦИЯ-ПОРОШОК В КАЧЕСТВЕОБРАЗЦА ДЛЯ ИСПЫТАНИЙ, ИЗУЧЕНИЙ 15 ГРАММ - ИЗУЧЕНИЕ МИКРОБИОЛОГИЧЕСКИХ СВОЙСТВ ВЕЩЕСТВА 10 ГРАММ - ИЗУЧЕНИЕ ИЗМЕНЧИВОСТИ ФИЗИКО-ХИМИЧЕСКИХ ПАРАМЕТРОВ ВЕЩЕСТВА 25 ГРАММ - ИЗУЧЕНИЕ УСТОЙЧИВОСТИ И СТАБИЛЬНОСТИ ВЕЩЕСТВА В РАЗЛИЧНЫХ УСЛОВИЯХ СПЫТАНИЙ, ИЗУЧЕНИЙ, ЦЕЛЬ ВВОЗА: ИСПОЛЬЗОВАНИЕ В НАУЧНЫХ ЦЕЛЯХ В КАЧЕСТВЕ ЛАБОРАТОРНОГО РЕАКТИВА, НЕ ЯВЛЯЮТСЯ ЛЕКАРСТВЕННЫМИ СРЕДСТВАМИ И ФАРМАЦЕВТИЧЕСКИМИ СУБСТАНЦИЯМИ. НЕ ДЛЯ ВЕТЕРИНАРИИ. НЕ СОДЕРЖАТ ЭТИЛОВОГО СПИРТА. ЦЕЛЬ ИССЛЕДОВАНИЙ: ИССЛЕДОВАНИЕ ЭФФЕКТИВНОСТИ, БЕЗОПАСНОСТИ, МИКРОБИОЛОГИЧЕСКИХ СВОЙСТВ, ИЗМЕНЧИВОСТИ ФИЗИКО-ХИМИЧЕСКИХ ПАРАМЕТРОВ ВЕЩЕСТВА, УСТОЙЧИВОСТИ И СТАБИЛЬНОСТИ ВЕЩЕСТВА В РАЗЛИЧНЫХ УСЛОВИЯХ. НЕ БУДЕТ ПРИМЕНЕНО ДЛЯ ПРОИЗВОДСТВА ПРОДУКЦИИ. ZHEJIANG JIANFENG INTERNATIONAL TRADE CO., LTD ОТСУТСТВУЕТ ОТСУТСТВУЕТ ОТСУТСТВУЕТ ОТСУТСТВУЕТ 50 | I38: =MIN(1,IFERROR(SEARCH(I$2,$H38),0)) -> 0 | J38: =MIN(1,IFERROR(SEARCH(J$2,$H38),0)) -> 0 | K38: =MIN(1,IFERROR(SEARCH(K$2,$H38),0)) -> 0 | L38: =IF(I38*J38=1,"Гороховый изолят",IF(I38*K38=1,"Гороховый концентрат",0)) -> 0 | M38: =$I38*J38 -> 0 | N38: =$I38*K38 -> 0 | O38: 0.8 | P38: 3650
B39: 45367 | C39: =YEAR(B39) -> 2024 | D39: =MONTH(B39) -> 3 | E39: Им | F39: КИТАЙ | G39: РОССИЯ | H39: CПАРЖА СУХАЯ СОЕВАЯ, В УПАКОВКАХ ИЗ ПОЛИМЕРНЫХ МАТЕРИАЛОВ, В КАРТОННЫХ КОРОБКАХ МАССОЙ НЕТТО 9 КГ С МАРКИРОВКОЙ SUIFENHE DAYUAN GREEN FOOD CO., LTD. | I39: =MIN(1,IFERROR(SEARCH(I$2,$H39),0)) -> 0 | J39: =MIN(1,IFERROR(SEARCH(J$2,$H39),0)) -> 0 | K39: =MIN(1,IFERROR(SEARCH(K$2,$H39),0)) -> 0 | L39: =IF(I39*J39=1,"Гороховый изолят",IF(I39*K39=1,"Гороховый концентрат",0)) -> 0 | M39: =$I39*J39 -> 0 | N39: =$I39*K39 -> 0 | O39: 23400 | P39: 49893.7
B40: 25.09.2020 | C40: =YEAR(B40) -> 2020 | D40: =MONTH(B40) -> 9 | E40: ИМ | F40: ФЕДЕРАТИВНАЯ РЕСПУБЛИКА ГЕРМАНИЯ | G40: РОССИЯ | H40: DRK БЕЛКОВЫЕ ВЕЩЕСТВА (НЕ ПИЩ.ПРОДУКЦИЯ),ВЕС БРУТТО С С ПАЛЛ.502.600 КГ: BPIN | I40: =MIN(1,IFERROR(SEARCH(I$2,$H40),0)) -> 0 | J40: =MIN(1,IFERROR(SEARCH(J$2,$H40),0)) -> 0 | K40: =MIN(1,IFERROR(SEARCH(K$2,$H40),0)) -> 0 | L40: =IF(I40*J40=1,"Гороховый изолят",IF(I40*K40=1,"Гороховый концентрат",0)) -> 0 | M40: =$I40*J40 -> 0 | N40: =$I40*K40 -> 0 | O40: 435 | P40: 3970.13
B41: 08.10.2020 | C41: =YEAR(B41) -> 2020 | D41: =MONTH(B41) -> 10 | E41: ИМ | F41: ФЕДЕРАТИВНАЯ РЕСПУБЛИКА БРАЗИЛИЯ | G41: РОССИЯ | H41: DRK ГИДРОЛИЗИРОВАННЫЙ ПРОТЕИН ШЕЛКА CHEMYPROTEIN SILK SPD, ИСПОЛЬЗУЕТСЯ ПРИ ПРИ ПРОИЗВОДСТВЕ СРЕДСТВ ПО УХОДУ ЗА ВОЛОСАМИ НА ТЕРРИТОРИИ РФ В КАЧЕСТВЕ КОМПОНЕНТА (СЫРЬЯ) CACF | I41: =MIN(1,IFERROR(SEARCH(I$2,$H41),0)) -> 0 | J41: =MIN(1,IFERROR(SEARCH(J$2,$H41),0)) -> 0 | K41: =MIN(1,IFERROR(SEARCH(K$2,$H41),0)) -> 0 | L41: =IF(I41*J41=1,"Гороховый изолят",IF(I41*K41=1,"Гороховый концентрат",0)) -> 0 | M41: =$I41*J41 -> 0 | N41: =$I41*K41 -> 0 | O41: 20 | P41: 479.9
B42: 05.09.2020 | C42: =YEAR(B42) -> 2020 | D42: =MONTH(B42) -> 9 | E42: ИМ | F42: ВЕНГРИЯ | G42: РОССИЯ | H42: DRK ГЛЮТЕН КУКУРУЗНЫЙ СУХОЙ. CORN GLUTEN: MEAL ИСП, В КАЧЕСТВЕ РАСТИТЕЛЬНОГО, БЕЛКА ПРИ: ПРИ ПРОИЗВОДСТВЕ КОРМОВ. ДЛЯ ЖИВОТНЫХ НА: ТЕРРИТОРИИ РФ | I42: =MIN(1,IFERROR(SEARCH(I$2,$H42),0)) -> 0 | J42: =MIN(1,IFERROR(SEARCH(J$2,$H42),0)) -> 0 | K42: =MIN(1,IFERROR(SEARCH(K$2,$H42),0)) -> 0 | L42: =IF(I42*J42=1,"Гороховый изолят",IF(I42*K42=1,"Гороховый концентрат",0)) -> 0 | M42: =$I42*J42 -> 0 | N42: =$I42*K42 -> 0 | O42: 21000 | P42: 20743.05
B43: 14.04.2021 | C43: =YEAR(B43) -> 2021 | D43: =MONTH(B43) -> 4 | E43: ИМ | F43: КИТАЙ | G43: РОССИЯ | H43: DRK МАССА СОЕВАЯ ПРОТЕИНОВАЯ - СПАРЖА, ДЛЯ УПОТРЕБЛЕНИЯ В В ПИЩУ, ВСЕГО- 143 ГР.МЕСТ, - 1287КГ BBJEDF | I43: =MIN(1,IFERROR(SEARCH(I$2,$H43),0)) -> 0 | J43: =MIN(1,IFERROR(SEARCH(J$2,$H43),0)) -> 0 | K43: =MIN(1,IFERROR(SEARCH(K$2,$H43),0)) -> 0 | L43: =IF(I43*J43=1,"Гороховый изолят",IF(I43*K43=1,"Гороховый концентрат",0)) -> 0 | M43: =$I43*J43 -> 0 | N43: =$I43*K43 -> 0 | O43: 1287 | P43: 646.35
B44: 13.04.2021 | C44: =YEAR(B44) -> 2021 | D44: =MONTH(B44) -> 4 | E44: ИМ | F44: КИТАЙ | G44: РОССИЯ | H44: DRK ПРОДУКТ БЕЛКОВЫЙ ИЗ: ТЕКСТУРИРОВАННОЙ СОЕВОЙ МУКИ, ПРЕДНАЗНАЧЕННЫЙ ДЛЯ УПОТРЕБЛЕНИЯ; В В, ПИЩУ НЕ СОДЕРЖАЩИЙ, МОЛОЧНЫХ ЖИРОВ С: СОДЕРЖАНИЕМ САХАРОЗЫ ИЗОГЛЮКОЗЫ, ГЛЮКОЗЫ И: КРАХМАЛА БОЛЕЕ 5%МАС, НЕ СОДЕРЖИТ, ГМО ПРОДУКТ ИЗ, СОЕВОЙ МАССЫ | I44: =MIN(1,IFERROR(SEARCH(I$2,$H44),0)) -> 0 | J44: =MIN(1,IFERROR(SEARCH(J$2,$H44),0)) -> 0 | K44: =MIN(1,IFERROR(SEARCH(K$2,$H44),0)) -> 0 | L44: =IF(I44*J44=1,"Гороховый изолят",IF(I44*K44=1,"Гороховый концентрат",0)) -> 0 | M44: =$I44*J44 -> 0 | N44: =$I44*K44 -> 0 | O44: 1093.68 | P44: 940.57
B45: 06.02.2021 | C45: =YEAR(B45) -> 2021 | D45: =MONTH(B45) -> 2 | E45: ИМ | F45: КИТАЙ | G45: РОССИЯ | H45: DRK ФУЧЖУ (SOYBEAN STICK) ВЫСУШЕННАЯ ПЛЕНКА, СНЯТАЯ С С№$ СОЕВОГО МОЛОКА: СПАРЖА СОЕВАЯ СУХАЯ$* - 1450 КОРОБОК. СОЕВЫЙ ПИЩЕВОЙ#№ БЕЛКОВЫЙ ПРОДУКТ НЕ СОДЕРЖИТ МОЛОЧНЫХ ЖИРОВ, САХАРОЗЫ, ГЛЮКОЗЫ, КРАХМАЛА, ЯВЛЯЕТСЯ ГОТОВЫМ ПИЩЕВЫМ | I45: =MIN(1,IFERROR(SEARCH(I$2,$H45),0)) -> 0 | J45: =MIN(1,IFERROR(SEARCH(J$2,$H45),0)) -> 0 | K45: =MIN(1,IFERROR(SEARCH(K$2,$H45),0)) -> 0 | L45: =IF(I45*J45=1,"Гороховый изолят",IF(I45*K45=1,"Гороховый концентрат",0)) -> 0 | M45: =$I45*J45 -> 0 | N45: =$I45*K45 -> 0 | O45: 13050 | P45: 39128.28
B46: 45535 | C46: =YEAR(B46) -> 2024 | D46: =MONTH(B46) -> 8 | E46: Им | F46: ХОРВАТИЯ | G46: РОССИЯ | H46: FAVA PROTEIN ISOLATE NUTRISMART P85A" ( БЕЛКОВЫЙ ИЗОЛЯТ БОБОВ ФАВА (ФАСОЛЬ) , СОДЕРЖАНИЕ БЕЛКА В ПЕРЕСЧЕТЕ НА СУХ.ВЕЩЕСТВО - 85%) ПОСТАВЛЯЕТСЯ В КАЧЕСТВЕ ОБРАЗЦОВ ДЛЯ ПРОBЕДЕНИЯ РЕКЛАМНО-МАРКЕТИНГОВЫХ МЕРОПРИЯТИЙ НА БЕЗВОЗМЕЗДНОЙ ОСНОВЕ. НЕДЛЯ РОЗНИЧ | I46: =MIN(1,IFERROR(SEARCH(I$2,$H46),0)) -> 0 | J46: =MIN(1,IFERROR(SEARCH(J$2,$H46),0)) -> 1 | K46: =MIN(1,IFERROR(SEARCH(K$2,$H46),0)) -> 0 | L46: =IF(I46*J46=1,"Гороховый изолят",IF(I46*K46=1,"Гороховый концентрат",0)) -> 0 | M46: =$I46*J46 -> 0 | N46: =$I46*K46 -> 0 | O46: 15 | P46: 121.72
B47: 30.10.2020 | C47: =YEAR(B47) -> 2020 | D47: =MONTH(B47) -> 10 | E47: ИМ | F47: ФЕДЕРАТИВНАЯ РЕСПУБЛИКА ГЕРМАНИЯ | G47: РОССИЯ | H47: FQX БЕЛКИ ХИМ ЛАБОР, РЕАКТИВ ДЛЯ, ИССЛЕДОВАНИЙ IN: VITRO НЕ: ЯВЛ ФАРМ СУБСТАНЦИЕЙ, НЕ ВНЕСЕН, В ГОС: РЕЕСТР РЕЕСТР, ЛЕКАРСТВЕННЫХ СРЕДСТВ: НЕ СОД, СПИРТ НЕ ДЛЯ. ВЕТЕРИНАРИИ УПАК; В ПЕНОПЛАСТ КОНТ: С СУХИМ ЛЬДОМ. | I47: =MIN(1,IFERROR(SEARCH(I$2,$H47),0)) -> 0 | J47: =MIN(1,IFERROR(SEARCH(J$2,$H47),0)) -> 0 | K47: =MIN(1,IFERROR(SEARCH(K$2,$H47),0)) -> 0 | L47: =IF(I47*J47=1,"Гороховый изолят",IF(I47*K47=1,"Гороховый концентрат",0)) -> 0 | M47: =$I47*J47 -> 0 | N47: =$I47*K47 -> 0 | O47: 0.25 | P47: 119.56
B48: 30.03.2021 | C48: =YEAR(B48) -> 2021 | D48: =MONTH(B48) -> 3 | E48: ИМ | F48: ФРАНЦИЯ | G48: РОССИЯ | H48: FQX БЕЛКОВОЕ В-ВО. ХИМ. РЕАКТИВ ДЛЯ/| ЛАБ. ИССЛЕД. IN VITRO.(№ ПРИЛАГАЕТСЯ ПРИЛАГАЕТСЯ$^ ПРОТОКОЛ ПОСТ .РЕАКЦ. НЕ ДЛЯ ВЕТЕРИНАРИИ. УПАК. В ПЕНОПЛАСТ. КОНТ. С СУХИМ ЛЬДОМ. | I48: =MIN(1,IFERROR(SEARCH(I$2,$H48),0)) -> 0 | J48: =MIN(1,IFERROR(SEARCH(J$2,$H48),0)) -> 0 | K48: =MIN(1,IFERROR(SEARCH(K$2,$H48),0)) -> 0 | L48: =IF(I48*J48=1,"Гороховый изолят",IF(I48*K48=1,"Гороховый концентрат",0)) -> 0 | M48: =$I48*J48 -> 0 | N48: =$I48*K48 -> 0 | O48: 0.01 | P48: 95.49
B49: 20.08.2020 | C49: =YEAR(B49) -> 2020 | D49: =MONTH(B49) -> 8 | E49: ИМ | F49: ФЕДЕРАТИВНАЯ РЕСПУБЛИКА ГЕРМАНИЯ | G49: РОССИЯ | H49: FQX БЕЛКОВЫЕ БЕЛКОВЫЕ ВЕЩЕСТВA (ВЕС БРУТТО С ПАЛЛ.258.400 КГ): | I49: =MIN(1,IFERROR(SEARCH(I$2,$H49),0)) -> 0 | J49: =MIN(1,IFERROR(SEARCH(J$2,$H49),0)) -> 0 | K49: =MIN(1,IFERROR(SEARCH(K$2,$H49),0)) -> 0 | L49: =IF(I49*J49=1,"Гороховый изолят",IF(I49*K49=1,"Гороховый концентрат",0)) -> 0 | M49: =$I49*J49 -> 0 | N49: =$I49*K49 -> 0 | O49: 200 | P49: 1872.28
B50: 14.10.2020 | C50: =YEAR(B50) -> 2020 | D50: =MONTH(B50) -> 10 | E50: ИМ | F50: ФЕДЕРАТИВНАЯ РЕСПУБЛИКА ГЕРМАНИЯ | G50: РОССИЯ | H50: FQX БЕЛКОВЫЕ БЕЛКОВЫЕ{ ВЕЩЕСТВА (ВЕС БРУТТО$% С ПАЛЛ.2416.500 КГ): | I50: =MIN(1,IFERROR(SEARCH(I$2,$H50),0)) -> 0 | J50: =MIN(1,IFERROR(SEARCH(J$2,$H50),0)) -> 0 | K50: =MIN(1,IFERROR(SEARCH(K$2,$H50),0)) -> 0 | L50: =IF(I50*J50=1,"Гороховый изолят",IF(I50*K50=1,"Гороховый концентрат",0)) -> 0 | M50: =$I50*J50 -> 0 | N50: =$I50*K50 -> 0 | O50: 2250 | P50: 18491.35
B51: 09.06.2021 | C51: =YEAR(B51) -> 2021 | D51: =MONTH(B51) -> 6 | E51: ИМ | F51: СОЕДИНЕННЫЕ ШТАТЫ | G51: РОССИЯ | H51: FQX БЕЛКОВЫЕ ВЕЩЕСТВА - СЫРЬЕ ДЛЯ ПРОМПЕРЕРАБОТКИ ПРОМПЕРЕРАБОТКИ В ПИЩЕВОЙ ПРОМЫШЛЕННОСТИ. BNBKNC | I51: =MIN(1,IFERROR(SEARCH(I$2,$H51),0)) -> 0 | J51: =MIN(1,IFERROR(SEARCH(J$2,$H51),0)) -> 0 | K51: =MIN(1,IFERROR(SEARCH(K$2,$H51),0)) -> 0 | L51: =IF(I51*J51=1,"Гороховый изолят",IF(I51*K51=1,"Гороховый концентрат",0)) -> 0 | M51: =$I51*J51 -> 0 | N51: =$I51*K51 -> 0 | O51: 5980 | P51: 49813.4
B52: 07.06.2021 | C52: =YEAR(B52) -> 2021 | D52: =MONTH(B52) -> 6 | E52: ИМ | F52: БЕЛЬГИЯ | G52: РОССИЯ | H52: FQX БЕЛКОВЫЕ КОНЦЕНТРАТЫ И ТЕКСТУРИРОВАННЫЕ БЕЛКОВЫЕ ВЕЩЕСТВА, ДЛЯ ПРОИЗВОДСТВА ПРОИЗВОДСТВА КОНДИТЕРСКИХ ИЗДЕЛИЙ БЕЗ ГМО (ВЕС БРУТТО С С ПОДДОНАМИ 1378.900 КГ) | I52: =MIN(1,IFERROR(SEARCH(I$2,$H52),0)) -> 0 | J52: =MIN(1,IFERROR(SEARCH(J$2,$H52),0)) -> 0 | K52: =MIN(1,IFERROR(SEARCH(K$2,$H52),0)) -> 1 | L52: =IF(I52*J52=1,"Гороховый изолят",IF(I52*K52=1,"Гороховый концентрат",0)) -> 0 | M52: =$I52*J52 -> 0 | N52: =$I52*K52 -> 0 | O52: 1260 | P52: 9015.66
B53: 20.07.2021 | C53: =YEAR(B53) -> 2021 | D53: =MONTH(B53) -> 7 | E53: ИМ | F53: НИДЕРЛАНДЫ | G53: РОССИЯ | H53: FQX БЕЛКОВЫЕ КОНЦЕНТРАТЫ И ТЕКСТУРИРОВАННЫЕ БЕЛКОВЫЕ ВЕЩЕСТВА, НЕ СОДЕРЖАЩИЕ МОЛОЧНЫХ ЖИРОВ, САХАРОЗЫ, САХАРОЗЫ, ИЗОГЛЮКОЗЫ, ГЛЮКОЗЫ ИЛИ КРАХМАЛА ИЛИ СОДЕРЖАЩИЕ МЕНЕЕ 1,5 МАС% МОЛОЧНОГО ЖИРА, 5 МАС% САХАРОЗЫ CGFJGC | I53: =MIN(1,IFERROR(SEARCH(I$2,$H53),0)) -> 0 | J53: =MIN(1,IFERROR(SEARCH(J$2,$H53),0)) -> 0 | K53: =MIN(1,IFERROR(SEARCH(K$2,$H53),0)) -> 1 | L53: =IF(I53*J53=1,"Гороховый изолят",IF(I53*K53=1,"Гороховый концентрат",0)) -> 0 | M53: =$I53*J53 -> 0 | N53: =$I53*K53 -> 0 | O53: 110.5 | P53: 892.62
B54: 30.12.2021 | C54: =YEAR(B54) -> 2021 | D54: =MONTH(B54) -> 12 | E54: ИМ | F54: КИТАЙ | G54: РОССИЯ | H54: FQX ВЕЩЕСТВА БЕЛКОВЫЕ: ИЗОЛЯТ СОЕВОГО БЕЛКА, В ВИДЕ ПОРОШКА БЕЛО-ЖЕЛТОГО БЕЛО-ЖЕЛТОГО ЦВЕТА, В КАЧЕСТВЕ СЫРЬЯ ДЛЯ ПРОМПЕРЕРАБОТКИ EHNDPD | I54: =MIN(1,IFERROR(SEARCH(I$2,$H54),0)) -> 0 | J54: =MIN(1,IFERROR(SEARCH(J$2,$H54),0)) -> 1 | K54: =MIN(1,IFERROR(SEARCH(K$2,$H54),0)) -> 0 | L54: =IF(I54*J54=1,"Гороховый изолят",IF(I54*K54=1,"Гороховый концентрат",0)) -> 0 | M54: =$I54*J54 -> 0 | N54: =$I54*K54 -> 0 | O54: 20000 | P54: 73800
B55: 14.10.2021 | C55: =YEAR(B55) -> 2021 | D55: =MONTH(B55) -> 10 | E55: ИМ | F55: ВЕНГРИЯ | G55: РОССИЯ | H55: FQX ГЛЮТЕН КУКУРУЗНЫЙ СУХОЙ "CORN GLUTEN@+ MEAL", ИСП. В КАЧЕСТВЕ|| РАСТИТЕЛЬНОГО БЕЛКА ПРИ ПРИ ПРОИЗВОДСТВЕ|$ КОРМОВ ДЛЯ ЖИВОТНЫХ НА ТЕРРИТОРИИ РФ; | I55: =MIN(1,IFERROR(SEARCH(I$2,$H55),0)) -> 0 | J55: =MIN(1,IFERROR(SEARCH(J$2,$H55),0)) -> 0 | K55: =MIN(1,IFERROR(SEARCH(K$2,$H55),0)) -> 0 | L55: =IF(I55*J55=1,"Гороховый изолят",IF(I55*K55=1,"Гороховый концентрат",0)) -> 0 | M55: =$I55*J55 -> 0 | N55: =$I55*K55 -> 0 | O55: 21000 | P55: 19599.32
B56: 02.11.2021 | C56: =YEAR(B56) -> 2021 | D56: =MONTH(B56) -> 11 | E56: ИМ | F56: ГЕРМАНИЯ | G56: РОССИЯ | H56: FQX ПЕПТОНЫ, БЕЛКОВЫЕ ВЕЩЕСТВА И ИХ ПРОИЗВОДНЫЕ, ПРИМЕНЯЮТСЯ В КОСМЕТИЧЕСКОЙ ПРОМЫШЛЕННОСТИ. НЕ ДЛЯ МЕД.ЦЕЛЕЙ. МЕД.ЦЕЛЕЙ. НЕ ДЛЯ ВЕТЕРИНАРИИ. НЕ СОДЕРЖАТ ЭТИЛОВОГО СПИРТА: DOLCGH | I56: =MIN(1,IFERROR(SEARCH(I$2,$H56),0)) -> 0 | J56: =MIN(1,IFERROR(SEARCH(J$2,$H56),0)) -> 0 | K56: =MIN(1,IFERROR(SEARCH(K$2,$H56),0)) -> 0 | L56: =IF(I56*J56=1,"Гороховый изолят",IF(I56*K56=1,"Гороховый концентрат",0)) -> 0 | M56: =$I56*J56 -> 0 | N56: =$I56*K56 -> 0 | O56: 650 | P56: 11193.23
B57: 23.02.2021 | C57: =YEAR(B57) -> 2021 | D57: =MONTH(B57) -> 2 | E57: ИМ | F57: КИТАЙ | G57: РОССИЯ | H57: FQX ПРОДУКТ БЕЛКОВЫЙ - ТОФУ, ИЗ ТЕКСТУРИРОВАННОЙ СОЕВОЙ МУКИ ПРЕДНАЗНАЧЕННЫЙ ДЛЯ УПОТРЕБЛЕНИЯ УПОТРЕБЛЕНИЯ В ПИЩУ, НЕ СОДЕРЖАЩИЙ МОЛОЧНЫХ ЖИРОВ,С СОДЕРЖАНИЕМ САХАРОЗЫ, ИЗОГЛЮКОЗЫ, ГЛЮКОЗЫ ИЛИ КРАХМАЛА БОЛЕЕ 5%МАС..НЕ СОДЕРЖИТ ГМО: | I57: =MIN(1,IFERROR(SEARCH(I$2,$H57),0)) -> 0 | J57: =MIN(1,IFERROR(SEARCH(J$2,$H57),0)) -> 0 | K57: =MIN(1,IFERROR(SEARCH(K$2,$H57),0)) -> 0 | L57: =IF(I57*J57=1,"Гороховый изолят",IF(I57*K57=1,"Гороховый концентрат",0)) -> 0 | M57: =$I57*J57 -> 0 | N57: =$I57*K57 -> 0 | O57: 1242 | P57: 1068.12
B58: 28.12.2021 | C58: =YEAR(B58) -> 2021 | D58: =MONTH(B58) -> 12 | E58: ИМ | F58: КИТАЙ | G58: РОССИЯ | H58: FQX ПРОДУКТ БЕЛКОВЫЙ ИЗ ИЗ ТЕКСТУРИРОВАННОЙ СОЕВОЙ СОЕВОЙ МУКИ ПРЕДНАЗНАЧЕННЫЙ ДЛЯ УПОТРЕБЛЕНИЯ В ПИЩУ, НЕ СОДЕРЖАЩИЙ МОЛОЧНЫХ ЖИРОВ, С СОДЕРЖАНИЕМ КРАХМАЛА БОЛЕЕ 5%МАС. НЕ СОДЕРЖИТ ГМО: | I58: =MIN(1,IFERROR(SEARCH(I$2,$H58),0)) -> 0 | J58: =MIN(1,IFERROR(SEARCH(J$2,$H58),0)) -> 0 | K58: =MIN(1,IFERROR(SEARCH(K$2,$H58),0)) -> 0 | L58: =IF(I58*J58=1,"Гороховый изолят",IF(I58*K58=1,"Гороховый концентрат",0)) -> 0 | M58: =$I58*J58 -> 0 | N58: =$I58*K58 -> 0 | O58: 1948.6 | P58: 3902.21
... B122: 22.12.2021 | C122: =YEAR(B122) -> 2021 | D122: =MONTH(B122) -> 12 | E122: ИМ | F122: НИДЕРЛАНДЫ | G122: РОССИЯ | H122: HYGEL PEA 8436- ВЗБИВНОЙ АГЕНТ НА ОСНОВЕ ГИДРОЛИЗОВАННОГО ГОРОХОВОГО БЕЛКА.ДЛЯ ИСПОЛЬЗОВАНИЯ В ПИЩЕВОЙ ПРОМЫШЛЕННОСТИ.НЕ СОДЕРЖИТ ГМО. УПАКОВАН В КОРОБКИ ПО 10 КГ. ВЕС БРУТТО С УЧЕТОМ ВЕСА ПОДДОНА 90.50 КГ. | I122: =MIN(1,IFERROR(SEARCH(I$2,$H122),0)) -> 1 | J122: =MIN(1,IFERROR(SEARCH(J$2,$H122),0)) -> 0 | K122: =MIN(1,IFERROR(SEARCH(K$2,$H122),0)) -> 0 | L122: =IF(I122*J122=1,"Гороховый изолят",IF(I122*K122=1,"Гороховый концентрат",0)) -> 0 | M122: =$I122*J122 -> 0 | N122: =$I122*K122 -> 0 | O122: 60 | P122: 1247.21
B123: 45328 | C123: =YEAR(B123) -> 2024 | D123: =MONTH(B123) -> 2 | E123: Им | F123: КИТАЙ | G123: РОССИЯ | H123: ISOPRO 900 HI - ИЗОЛЯТ СОЕВОГО БЕЛKА С ВЫСОКОЙ ВЛАГОСВЯЗЫВАЮЩЕЙ СПОСОБНОСТЬЮ ДЛЯ ПИЩЕВОЙ ПРОМЫШЛЕННОСТИ, 40 МЕШКОВ 1420 КГ. : | I123: =MIN(1,IFERROR(SEARCH(I$2,$H123),0)) -> 0 | J123: =MIN(1,IFERROR(SEARCH(J$2,$H123),0)) -> 1 | K123: =MIN(1,IFERROR(SEARCH(K$2,$H123),0)) -> 0 | L123: =IF(I123*J123=1,"Гороховый изолят",IF(I123*K123=1,"Гороховый концентрат",0)) -> 0 | M123: =$I123*J123 -> 0 | N123: =$I123*K123 -> 0 | O123: 1429.6 | P123: 8498.59
B124: 19.08.2022 | C124: =YEAR(B124) -> 2022 | D124: =MONTH(B124) -> 8 | E124: ИМ | F124: КИТАЙ | G124: РОССИЯ | H124: ISOPRO 900 HI - ИЗОЛЯТ СОЕВОГО БЕЛКА С ВЫСОКОЙ ВЛАГОСВЯЗЫВАЮЩЕЙ СПОСОБНОСТЬЮ ДЛЯ ПИЩЕВОЙ ПРОМЫШЛЕННОСТИ, 155 МЕШКОВ 3100 КГ. : | I124: =MIN(1,IFERROR(SEARCH(I$2,$H124),0)) -> 0 | J124: =MIN(1,IFERROR(SEARCH(J$2,$H124),0)) -> 1 | K124: =MIN(1,IFERROR(SEARCH(K$2,$H124),0)) -> 0 | L124: =IF(I124*J124=1,"Гороховый изолят",IF(I124*K124=1,"Гороховый концентрат",0)) -> 0 | M124: =$I124*J124 -> 0 | N124: =$I124*K124 -> 0 | O124: 3140.3 | P124: 17399.78
B125: 09.09.2022 | C125: =YEAR(B125) -> 2022 | D125: =MONTH(B125) -> 9 | E125: ИМ | F125: КИТАЙ | G125: РОССИЯ | H125: ISOPRO 900 HI - ИЗОЛЯТ СОЕВОГО БЕЛКА С ВЫСОКОЙ ВЛАГОСВЯЗЫВАЮЩЕЙ СПОСОБНОСТЬЮ ДЛЯ ПИЩЕВОЙ ПРОМЫШЛЕННОСТИ, 61 МЕШКОВ 1220 КГ. : | I125: =MIN(1,IFERROR(SEARCH(I$2,$H125),0)) -> 0 | J125: =MIN(1,IFERROR(SEARCH(J$2,$H125),0)) -> 1 | K125: =MIN(1,IFERROR(SEARCH(K$2,$H125),0)) -> 0 | L125: =IF(I125*J125=1,"Гороховый изолят",IF(I125*K125=1,"Гороховый концентрат",0)) -> 0 | M125: =$I125*J125 -> 0 | N125: =$I125*K125 -> 0 | O125: 1235.86 | P125: 7342.72
B126: 29.06.2022 | C126: =YEAR(B126) -> 2022 | D126: =MONTH(B126) -> 6 | E126: ИМ | F126: КИТАЙ | G126: РОССИЯ | H126: ISOPRO 900 HI - ИЗОЛЯТ СОЕВОГО БЕЛКА С ВЫСОКОЙ ВЛАГОСВЯЗЫВАЮЩЕЙ СПОСОБНОСТЬЮ ДЛЯ ПИЩЕВОЙ ПРОМЫШЛЕННОСТИ, 61 МЕШКОВ 1220 КГ. : | I126: =MIN(1,IFERROR(SEARCH(I$2,$H126),0)) -> 0 | J126: =MIN(1,IFERROR(SEARCH(J$2,$H126),0)) -> 1 | K126: =MIN(1,IFERROR(SEARCH(K$2,$H126),0)) -> 0 | L126: =IF(I126*J126=1,"Гороховый изолят",IF(I126*K126=1,"Гороховый концентрат",0)) -> 0 | M126: =$I126*J126 -> 0 | N126: =$I126*K126 -> 0 | O126: 1235.86 | P126: 7342.72
B127: 01.06.2021 | C127: =YEAR(B127) -> 2021 | D127: =MONTH(B127) -> 6 | E127: ИМ | F127: КИТАЙ | G127: РОССИЯ | H127: ISOPRO 900 HI - ИЗОЛЯТ СОЕВОГО БЕЛКА С ВЫСОКОЙ ВЛАГОСВЯЗЫВАЮЩЕЙ СПОСОБНОСТЬЮ ДЛЯ ПИЩЕВОЙ ПРОМЫШЛЕННОСТИ, 80 МЕШКОВ 1600 КГ. : | I127: =MIN(1,IFERROR(SEARCH(I$2,$H127),0)) -> 0 | J127: =MIN(1,IFERROR(SEARCH(J$2,$H127),0)) -> 1 | K127: =MIN(1,IFERROR(SEARCH(K$2,$H127),0)) -> 0 | L127: =IF(I127*J127=1,"Гороховый изолят",IF(I127*K127=1,"Гороховый концентрат",0)) -> 0 | M127: =$I127*J127 -> 0 | N127: =$I127*K127 -> 0 | O127: 1620.8 | P127: 6784.63
B128: 04.05.2021 | C128: =YEAR(B128) -> 2021 | D128: =MONTH(B128) -> 5 | E128: ИМ | F128: СОЕДИНЕННОЕ КОРОЛЕВСТВО | G128: РОССИЯ | H128: IXC HVP (POWDER) SOY/MAIZE -ГИДРОЛИЗОВАННЫЙ РАСТИТЕЛЬНЫЙ БЕЛОК ДЛЯ ИСПОЛЬЗОВАНИЯ В МЯСНОЙ ПРОМЫШЛЕННОСТИ ДЛЯ УЛУЧШЕНИЯ ВКУСА И АРОМАТА ПРОДУКТА. УПАКОВАН В МЕШКИ ПО 25 КГ. ВЕС БРУТТО С УЧЕТОМ ВЕСА ПОДДОНА 61.435 КГ. | I128: =MIN(1,IFERROR(SEARCH(I$2,$H128),0)) -> 0 | J128: =MIN(1,IFERROR(SEARCH(J$2,$H128),0)) -> 0 | K128: =MIN(1,IFERROR(SEARCH(K$2,$H128),0)) -> 0 | L128: =IF(I128*J128=1,"Гороховый изолят",IF(I128*K128=1,"Гороховый концентрат",0)) -> 0 | M128: =$I128*J128 -> 0 | N128: =$I128*K128 -> 0 | O128: 50 | P128: 231.76
B129: 29.07.2021 | C129: =YEAR(B129) -> 2021 | D129: =MONTH(B129) -> 7 | E129: ИМ | F129: СОЕДИНЕННЫЕ ШТАТЫ | G129: РОССИЯ | H129: IXC БЕЛКИ. (ХИМ.ЛАБОР.) РЕАКТИВ ДЛЯ ИССЛЕДОВАНИЙ IN VITRO. НЕ ЯВЛ. ФАРМ.СУБСТАНЦИЕЙ. НЕ ВНЕСЕН В ГОС. РЕЕСТР ЛЕКАРСТВЕННЫХ СРЕДСТВ. НЕ СОД. СПИРТ. НЕ ДЛЯ ВЕТЕРИНАРИИ. | I129: =MIN(1,IFERROR(SEARCH(I$2,$H129),0)) -> 0 | J129: =MIN(1,IFERROR(SEARCH(J$2,$H129),0)) -> 0 | K129: =MIN(1,IFERROR(SEARCH(K$2,$H129),0)) -> 0 | L129: =IF(I129*J129=1,"Гороховый изолят",IF(I129*K129=1,"Гороховый концентрат",0)) -> 0 | M129: =$I129*J129 -> 0 | N129: =$I129*K129 -> 0 | O129: 0.164 | P129: 2705
B130: 03.08.2021 | C130: =YEAR(B130) -> 2021 | D130: =MONTH(B130) -> 8 | E130: ИМ | F130: СОЕДИНЕННЫЕ ШТАТЫ | G130: РОССИЯ | H130: IXC БЕЛКОВЫЕ "ВЕЩЕСТВА" ДЛЯ ИСПОЛЬЗОВАНИЯ В КАЧЕСТВЕ ЛАБОРАТОРНЫХ РЕАКТИВОВ В НАУЧНЫХ ИССЛЕДОВАНИЯХ. НЕ СОДЕРЖАТ ЭТИЛОВОГО СПИРТА: | I130: =MIN(1,IFERROR(SEARCH(I$2,$H130),0)) -> 0 | J130: =MIN(1,IFERROR(SEARCH(J$2,$H130),0)) -> 0 | K130: =MIN(1,IFERROR(SEARCH(K$2,$H130),0)) -> 0 | L130: =IF(I130*J130=1,"Гороховый изолят",IF(I130*K130=1,"Гороховый концентрат",0)) -> 0 | M130: =$I130*J130 -> 0 | N130: =$I130*K130 -> 0 | O130: 0.03 | P130: 283.18
B131: 23.11.2021 | C131: =YEAR(B131) -> 2021 | D131: =MONTH(B131) -> 11 | E131: ИМ | F131: ДАНИЯ | G131: РОССИЯ | H131: IXC БЕЛКОВЫЕ "ВЕЩЕСТВА" ДЛЯ ПРОМЫШЛЕННОГО ПРОИЗВОДСТВА ПИЩЕВЫХ ПРОДУКТОВ, БЕЗ ГМО, НЕ СОДЕРЖАТ ЭТАНОЛА | I131: =MIN(1,IFERROR(SEARCH(I$2,$H131),0)) -> 0 | J131: =MIN(1,IFERROR(SEARCH(J$2,$H131),0)) -> 0 | K131: =MIN(1,IFERROR(SEARCH(K$2,$H131),0)) -> 0 | L131: =IF(I131*J131=1,"Гороховый изолят",IF(I131*K131=1,"Гороховый концентрат",0)) -> 0 | M131: =$I131*J131 -> 0 | N131: =$I131*K131 -> 0 | O131: 20000 | P131: 108295.11
B132: 20.01.2021 | C132: =YEAR(B132) -> 2021 | D132: =MONTH(B132) -> 1 | E132: ИМ | F132: КИТАЙ | G132: РОССИЯ | H132: IXC БЕЛКОВЫЕ "ВЕЩЕСТВА" ПРОЧИЕ И ИХ ПРОИЗВОДНЫЕ | I132: =MIN(1,IFERROR(SEARCH(I$2,$H132),0)) -> 0 | J132: =MIN(1,IFERROR(SEARCH(J$2,$H132),0)) -> 0 | K132: =MIN(1,IFERROR(SEARCH(K$2,$H132),0)) -> 0 | L132: =IF(I132*J132=1,"Гороховый изолят",IF(I132*K132=1,"Гороховый концентрат",0)) -> 0 | M132: =$I132*J132 -> 0 | N132: =$I132*K132 -> 0 | O132: 0.06 | P132: 4600.41
B133: 24.07.2020 | C133: =YEAR(B133) -> 2020 | D133: =MONTH(B133) -> 7 | E133: ЭК | F133: ИТАЛЬЯНСКАЯ РЕСПУБЛИКА | G133: АБХАЗИЯ | H133: КОМПЛЕКСНАЯ ПИЩЕВАЯ ДОБАВКА ДЛЯ ИСПОЛЬЗОВАНИЯ В ВИНОДЕЛЬЧЕСКОЙ ПРОМЫШЛЕННОСТИ - ПРОТЕИН ГОРОХА. ПРЕДСТАВЛЯЕТ СОБОЙ ИЗОЛЯТ ГОРОХОВОГО БЕЛКА ПОЛУЧЕННЫЙ ПУТЁМ ШЕЛУШЕНИЯ ЗЁРЕН ГОРОХА, ИХ ИЗМЕЛЬЧЕНИЕ, ЗАМАЧИВАНИЕ В ВОДЕ, ОТДЕЛЕНИЕ БЕЛКА И ВЫСУШИВАНИЕ РАСП | I133: =MIN(1,IFERROR(SEARCH(I$2,$H133),0)) -> 1 | J133: =MIN(1,IFERROR(SEARCH(J$2,$H133),0)) -> 1 | K133: =MIN(1,IFERROR(SEARCH(K$2,$H133),0)) -> 0 | L133: =IF(I133*J133=1,"Гороховый изолят",IF(I133*K133=1,"Гороховый концентрат",0)) -> Гороховый изолят | M133: =$I133*J133 -> 1 | N133: =$I133*K133 -> 0 | O133: 102.31 | P133: 1892.54
B134: 14.12.2021 | C134: =YEAR(B134) -> 2021 | D134: =MONTH(B134) -> 12 | E134: ИМ | F134: НИДЕРЛАНДЫ | G134: РОССИЯ | H134: IXC БЕЛКОВЫЕ "КОНЦЕНТРАТЫ" И ТЕКСТУРИРОВАННЫЕ БЕЛКОВЫЕ ВЕЩЕСТВА ДЛЯ ИСПОЛЬЗОВАНИЯ В ПИЩЕВОЙ ПРОМЫШЛЕННОСТИ, : | I134: =MIN(1,IFERROR(SEARCH(I$2,$H134),0)) -> 0 | J134: =MIN(1,IFERROR(SEARCH(J$2,$H134),0)) -> 0 | K134: =MIN(1,IFERROR(SEARCH(K$2,$H134),0)) -> 1 | L134: =IF(I134*J134=1,"Гороховый изолят",IF(I134*K134=1,"Гороховый концентрат",0)) -> 0 | M134: =$I134*J134 -> 0 | N134: =$I134*K134 -> 0 | O134: 420 | P134: 7160.22
B135: 27.08.2021 | C135: =YEAR(B135) -> 2021 | D135: =MONTH(B135) -> 8 | E135: ИМ | F135: СОЕДИНЕННЫЕ ШТАТЫ | G135: РОССИЯ | H135: IXC БЕЛКОВЫЕ (ВЕЩЕСТВА) ДЛЯ ИСПОЛЬЗОВАНИЯ В КАЧЕСТВЕ ЛАБОРАТОРНЫХ РЕАКТИВОВ В НАУЧНЫХ ИССЛЕДОВАНИЯХ. НЕ СОДЕРЖАТ ЭТИЛОВОГО СПИРТА: | I135: =MIN(1,IFERROR(SEARCH(I$2,$H135),0)) -> 0 | J135: =MIN(1,IFERROR(SEARCH(J$2,$H135),0)) -> 0 | K135: =MIN(1,IFERROR(SEARCH(K$2,$H135),0)) -> 0 | L135: =IF(I135*J135=1,"Гороховый изолят",IF(I135*K135=1,"Гороховый концентрат",0)) -> 0 | M135: =$I135*J135 -> 0 | N135: =$I135*K135 -> 0 | O135: 0.198 | P135: 425.18
... B153: 10.12.2020 | C153: =YEAR(B153) -> 2020 | D153: =MONTH(B153) -> 12 | E153: ИМ | F153: КИТАЙ | G153: РОССИЯ | H153: IXC ФУЧЖУ (SOYBEAN STICKS) ВЫСУШЕННАЯ ПЛЕНКА, СНЯТАЯ С СОЕВОГО МОЛОКА: СПАРЖА СОЕВАЯ СУХАЯ - 1450 КОРОБОК. СОЕВЫЙ ПИЩЕВОЙ БЕЛКОВЫЙ ПРОДУКТ НЕ СОДЕРЖИТ МОЛОЧНЫХ ЖИРОВ, САХАРОЗЫ, ГЛЮКОЗЫ, КРАХМАЛА, ЯВЛЯЕТСЯ ГОТОВЫМ ПИЩЕВЫМ | I153: =MIN(1,IFERROR(SEARCH(I$2,$H153),0)) -> 0 | J153: =MIN(1,IFERROR(SEARCH(J$2,$H153),0)) -> 0 | K153: =MIN(1,IFERROR(SEARCH(K$2,$H153),0)) -> 0 | L153: =IF(I153*J153=1,"Гороховый изолят",IF(I153*K153=1,"Гороховый концентрат",0)) -> 0 | M153: =$I153*J153 -> 0 | N153: =$I153*K153 -> 0 | O153: 13050 | P153: 37582.22
B154: 45633 | C154: =YEAR(B154) -> 2024 | D154: =MONTH(B154) -> 12 | E154: Им | F154: КИТАЙ | G154: РОССИЯ | H154: JAPOLY-HDK - ГИДРОЛИЗОВАННЫЙ БЕЛОК КЕРАТИНА, ПРЕДСТАВЛЯЕТ СОБОЙ ТВЕРДОЕ ВЕЩЕСТВО (ПОРОШКООБРАЗНОЕ ТВЕРДОЕ ВЕЩЕСТВО), ПОСТАВЛЯЕТСЯ ДЛЯ СОБСТВЕННЫХ НУЖД ООО "АЛВА" ИСКЛЮЧИТЕЛЬНО ДЛЯ ИСПОЛЬЗОВАНИЯ B ПАРФЮМЕРНО-КОСМЕТИЧЕСКОМ ПРОИЗВОДСТВЕ И БЫТОВОЙ ХИМИИ, | I154: =MIN(1,IFERROR(SEARCH(I$2,$H154),0)) -> 0 | J154: =MIN(1,IFERROR(SEARCH(J$2,$H154),0)) -> 0 | K154: =MIN(1,IFERROR(SEARCH(K$2,$H154),0)) -> 0 | L154: =IF(I154*J154=1,"Гороховый изолят",IF(I154*K154=1,"Гороховый концентрат",0)) -> 0 | M154: =$I154*J154 -> 0 | N154: =$I154*K154 -> 0 | O154: 900 | P154: 38418.39
B155: 19.10.2023 | C155: =YEAR(B155) -> 2023 | D155: =MONTH(B155) -> 10 | E155: ИМ | F155: ГЕРМАНИЯ | G155: РОССИЯ | H155: KF ROHSTOFF 65 ( КФ РОХШТОФФ 65 ). КОНЦЕНТРАТ СОЕВОГО БЕЛКА. СОСТАВ | I155: =MIN(1,IFERROR(SEARCH(I$2,$H155),0)) -> 0 | J155: =MIN(1,IFERROR(SEARCH(J$2,$H155),0)) -> 0 | K155: =MIN(1,IFERROR(SEARCH(K$2,$H155),0)) -> 1 | L155: =IF(I155*J155=1,"Гороховый изолят",IF(I155*K155=1,"Гороховый концентрат",0)) -> 0 | M155: =$I155*J155 -> 0 | N155: =$I155*K155 -> 0 | O155: 1319.5 | P155: 9516.88
B156: 05.09.2023 | C156: =YEAR(B156) -> 2023 | D156: =MONTH(B156) -> 9 | E156: ИМ | F156: ГЕРМАНИЯ | G156: РОССИЯ | H156: KF ROHSTOFF 65 ( КФ РОХШТОФФ 65 ). КОНЦЕНТРАТ СОЕВОГО БЕЛКА. СОСТАВ: КОНЦЕНТРАТ СОЕВОГО БЕЛКА. | I156: =MIN(1,IFERROR(SEARCH(I$2,$H156),0)) -> 0 | J156: =MIN(1,IFERROR(SEARCH(J$2,$H156),0)) -> 0 | K156: =MIN(1,IFERROR(SEARCH(K$2,$H156),0)) -> 1 | L156: =IF(I156*J156=1,"Гороховый изолят",IF(I156*K156=1,"Гороховый концентрат",0)) -> 0 | M156: =$I156*J156 -> 0 | N156: =$I156*K156 -> 0 | O156: 2233 | P156: 18969.12
B157: 14.08.2023 | C157: =YEAR(B157) -> 2023 | D157: =MONTH(B157) -> 8 | E157: ИМ | F157: ГЕРМАНИЯ | G157: РОССИЯ | H157: KF ROHSTOFF 65 ( КФ РОХШТОФФ 65 ). КОНЦЕНТРАТ СОЕВОГО БЕЛКА. СОСТАВ: КОНЦЕНТРАТ СОЕВОГО БЕЛКА. | I157: =MIN(1,IFERROR(SEARCH(I$2,$H157),0)) -> 0 | J157: =MIN(1,IFERROR(SEARCH(J$2,$H157),0)) -> 0 | K157: =MIN(1,IFERROR(SEARCH(K$2,$H157),0)) -> 1 | L157: =IF(I157*J157=1,"Гороховый изолят",IF(I157*K157=1,"Гороховый концентрат",0)) -> 0 | M157: =$I157*J157 -> 0 | N157: =$I157*K157 -> 0 | O157: 1116.5 | P157: 9651.78
B158: 07.10.2023 | C158: =YEAR(B158) -> 2023 | D158: =MONTH(B158) -> 10 | E158: ИМ | F158: ГЕРМАНИЯ | G158: РОССИЯ | H158: KF ROHSTOFF 65 ( КФ РОХШТОФФ 65 ). КОНЦЕНТРАТ СОЕВОГО БЕЛКА. СОСТАВ: КОНЦЕНТРАТ СОЕВОГО БЕЛКА. | I158: =MIN(1,IFERROR(SEARCH(I$2,$H158),0)) -> 0 | J158: =MIN(1,IFERROR(SEARCH(J$2,$H158),0)) -> 0 | K158: =MIN(1,IFERROR(SEARCH(K$2,$H158),0)) -> 1 | L158: =IF(I158*J158=1,"Гороховый изолят",IF(I158*K158=1,"Гороховый концентрат",0)) -> 0 | M158: =$I158*J158 -> 0 | N158: =$I158*K158 -> 0 | O158: 86.28 | P158: 1025.21
B159: 45341 | C159: =YEAR(B159) -> 2024 | D159: =MONTH(B159) -> 2 | E159: Им | F159: НИДЕРЛАНДЫ | G159: РОССИЯ | H159: KОНЦЕНТРАТ СМЕСИ ГИДРОЛИЗИРОВАННЫХ РАСТИТЕЛЬНЫХ БЕЛКОВ. НЕ СОДЕРЖИТ ГМО. ИСПОЛЬЗУЕТСЯ В ПИЩЕВОЙ ПРОМЫШЛЕННОСТИ.. | I159: =MIN(1,IFERROR(SEARCH(I$2,$H159),0)) -> 0 | J159: =MIN(1,IFERROR(SEARCH(J$2,$H159),0)) -> 0 | K159: =MIN(1,IFERROR(SEARCH(K$2,$H159),0)) -> 0 | L159: =IF(I159*J159=1,"Гороховый изолят",IF(I159*K159=1,"Гороховый концентрат",0)) -> 0 | M159: =$I159*J159 -> 0 | N159: =$I159*K159 -> 0 | O159: 700 | P159: 6336.86
B160: 02.05.2021 | C160: =YEAR(B160) -> 2021 | D160: =MONTH(B160) -> 5 | E160: ИМ | F160: ШВЕЦИЯ | G160: РОССИЯ | H160: LYU БЕЛКИ ХИМ ЛАБОР: РЕАКТИВ ДЛЯ, ИССЛЕДОВАНИЙ IN, VITRO НЕ. ЯВЛ ФАРМ СУБСТАНЦИЕЙ: НЕ ВНЕСЕН В, ГОС РЕЕСТР ЛЕКАРСТВЕННЫХ: СРЕДСТВ НЕ СОД. СПИРТ НЕ, ДЛЯ ВЕТЕРИНАРИИ, | I160: =MIN(1,IFERROR(SEARCH(I$2,$H160),0)) -> 0 | J160: =MIN(1,IFERROR(SEARCH(J$2,$H160),0)) -> 0 | K160: =MIN(1,IFERROR(SEARCH(K$2,$H160),0)) -> 0 | L160: =IF(I160*J160=1,"Гороховый изолят",IF(I160*K160=1,"Гороховый концентрат",0)) -> 0 | M160: =$I160*J160 -> 0 | N160: =$I160*K160 -> 0 | O160: 0.1 | P160: 258.15
B161: 13.08.2021 | C161: =YEAR(B161) -> 2021 | D161: =MONTH(B161) -> 8 | E161: ИМ | F161: ГЕРМАНИЯ | G161: РОССИЯ | H161: LYU БЕЛКОВЫЕ ВЕЩЕСТВA: | I161: =MIN(1,IFERROR(SEARCH(I$2,$H161),0)) -> 0 | J161: =MIN(1,IFERROR(SEARCH(J$2,$H161),0)) -> 0 | K161: =MIN(1,IFERROR(SEARCH(K$2,$H161),0)) -> 0 | L161: =IF(I161*J161=1,"Гороховый изолят",IF(I161*K161=1,"Гороховый концентрат",0)) -> 0 | M161: =$I161*J161 -> 0 | N161: =$I161*K161 -> 0 | O161: 500 | P161: 4112.2
B162: 01.10.2020 | C162: =YEAR(B162) -> 2020 | D162: =MONTH(B162) -> 10 | E162: ИМ | F162: СОЕДИНЕННЫЕ ШТАТЫ АМЕРИКИ | G162: РОССИЯ | H162: LYU БЕЛКОВЫЕ ВЕЩЕСТВА ДЛЯ ИСПОЛЬЗОВАНИЯ В КАЧЕСТВЕ ЛАБОРАТОРНЫХ РЕАКТИВОВ В НАУЧНЫХ ИССЛЕДОВАНИЯХ. НЕ СОДЕРЖАТ ЭТИЛОВОГО СПИРТА: CACF | I162: =MIN(1,IFERROR(SEARCH(I$2,$H162),0)) -> 0 | J162: =MIN(1,IFERROR(SEARCH(J$2,$H162),0)) -> 0 | K162: =MIN(1,IFERROR(SEARCH(K$2,$H162),0)) -> 0 | L162: =IF(I162*J162=1,"Гороховый изолят",IF(I162*K162=1,"Гороховый концентрат",0)) -> 0 | M162: =$I162*J162 -> 0 | N162: =$I162*K162 -> 0 | O162: 3.581 | P162: 1682.85
B163: 03.05.2021 | C163: =YEAR(B163) -> 2021 | D163: =MONTH(B163) -> 5 | E163: ИМ | F163: ДАНИЯ | G163: РОССИЯ | H163: LYU БЕЛКОВЫЕ ВЕЩЕСТВА ДЛЯ ПРОМЫШЛЕННОГО ПРОИЗВОДСТВА ПИЩЕВЫХ ПРОДУКТОВ, БЕЗ ГМО, НЕ СОДЕРЖАТ ЭТАНОЛА BFKFGL | I163: =MIN(1,IFERROR(SEARCH(I$2,$H163),0)) -> 0 | J163: =MIN(1,IFERROR(SEARCH(J$2,$H163),0)) -> 0 | K163: =MIN(1,IFERROR(SEARCH(K$2,$H163),0)) -> 0 | L163: =IF(I163*J163=1,"Гороховый изолят",IF(I163*K163=1,"Гороховый концентрат",0)) -> 0 | M163: =$I163*J163 -> 0 | N163: =$I163*K163 -> 0 | O163: 21000 | P163: 134960.52
B164: 21.01.2021 | C164: =YEAR(B164) -> 2021 | D164: =MONTH(B164) -> 1 | E164: ИМ | F164: ДАНИЯ | G164: РОССИЯ | H164: LYU БЕЛКОВЫЕ ВЕЩЕСТВА ДЛЯ ДЛЯ ПРОМЫШЛЕННОГО ПРОИЗВОДСТВА ПИЩЕВЫХ ПРОДУКТОВ,, БЕЗ ГМО, НЕ СОДЕРЖАТ ЭТАНОЛА | I164: =MIN(1,IFERROR(SEARCH(I$2,$H164),0)) -> 0 | J164: =MIN(1,IFERROR(SEARCH(J$2,$H164),0)) -> 0 | K164: =MIN(1,IFERROR(SEARCH(K$2,$H164),0)) -> 0 | L164: =IF(I164*J164=1,"Гороховый изолят",IF(I164*K164=1,"Гороховый концентрат",0)) -> 0 | M164: =$I164*J164 -> 0 | N164: =$I164*K164 -> 0 | O164: 21000 | P164: 135518.06
B165: 21.01.2021 | C165: =YEAR(B165) -> 2021 | D165: =MONTH(B165) -> 1 | E165: ИМ | F165: МЕКСИКА | G165: РОССИЯ | H165: LYU БЕЛКОВЫЕ ВЕЩЕСТВА ДЛЯ ИСПОЛЬЗОВАНИЯ В КАЧЕСТВЕ ЛАБОРАТОРНЫХ РЕАКТИВОВ В НАУЧНЫХ НАУЧНЫХ ИССЛЕДОВАНИЯХ. НЕ СОДЕРЖАТ ЭТИЛОВОГО СПИРТА:: | I165: =MIN(1,IFERROR(SEARCH(I$2,$H165),0)) -> 0 | J165: =MIN(1,IFERROR(SEARCH(J$2,$H165),0)) -> 0 | K165: =MIN(1,IFERROR(SEARCH(K$2,$H165),0)) -> 0 | L165: =IF(I165*J165=1,"Гороховый изолят",IF(I165*K165=1,"Гороховый концентрат",0)) -> 0 | M165: =$I165*J165 -> 0 | N165: =$I165*K165 -> 0 | O165: 1.686 | P165: 360.05
B166: 11.12.2020 | C166: =YEAR(B166) -> 2020 | D166: =MONTH(B166) -> 12 | E166: ИМ | F166: СОЕДИНЕННЫЕ ШТАТЫ АМЕРИКИ | G166: РОССИЯ | H166: LYU БЕЛКОВЫЕ ВЕЩЕСТВА ДЛЯ; ИСПОЛЬЗОВАНИЯ В; КАЧЕСТВЕ ЛАБОРАТОРНЫХ. РЕАКТИВОВ В НАУЧНЫХ. ИССЛЕДОВАНИЯХ НЕ СОДЕРЖАТ, ЭТИЛОВОГО СПИРТА | I166: =MIN(1,IFERROR(SEARCH(I$2,$H166),0)) -> 0 | J166: =MIN(1,IFERROR(SEARCH(J$2,$H166),0)) -> 0 | K166: =MIN(1,IFERROR(SEARCH(K$2,$H166),0)) -> 0 | L166: =IF(I166*J166=1,"Гороховый изолят",IF(I166*K166=1,"Гороховый концентрат",0)) -> 0 | M166: =$I166*J166 -> 0 | N166: =$I166*K166 -> 0 | O166: 1.2 | P166: 217.93
B167: 17.12.2020 | C167: =YEAR(B167) -> 2020 | D167: =MONTH(B167) -> 12 | E167: ИМ | F167: КОРЕЯ, РЕСПУБЛИКА | G167: РОССИЯ | H167: LYU БЕЛКОВЫЕ ВЕЩЕСТВА И ИХ ПРОИЗВОДНЫЕ, В ДРУГОМ МЕСТЕ НЕ ПОИМЕНОВАННЫЕ ИЛИ НЕ ВКЛЮЧЕННЫЕ: НАТУРАЛЬНЫЙ КОЛЛАГЕНОВЫЙ ТРИПЕПТИД, ИЗВЛЕЧЕННЫЙ ИЗ РЫБЬЕЙ ЧЕШУИ.. | I167: =MIN(1,IFERROR(SEARCH(I$2,$H167),0)) -> 0 | J167: =MIN(1,IFERROR(SEARCH(J$2,$H167),0)) -> 0 | K167: =MIN(1,IFERROR(SEARCH(K$2,$H167),0)) -> 0 | L167: =IF(I167*J167=1,"Гороховый изолят",IF(I167*K167=1,"Гороховый концентрат",0)) -> 0 | M167: =$I167*J167 -> 0 | N167: =$I167*K167 -> 0 | O167: 5 | P167: 307.17
B168: 19.11.2021 | C168: =YEAR(B168) -> 2021 | D168: =MONTH(B168) -> 11 | E168: ИМ | F168: БЕЛЬГИЯ | G168: РОССИЯ | H168: LYU БЕЛКОВЫЕ КОНЦЕНТРАТЫ И ТЕКСТУРИРОВАННЫЕ БЕЛКОВЫЕ ВЕЩЕСТВА, ДЛЯ ПРОИЗВОДСТВА КОНДИТЕРСКИХ ИЗДЕЛИЙ БЕЗ ГМО (ВЕС БРУТТО С ПОДДОНАМИ 3447..250 КГ) EAHDPG | I168: =MIN(1,IFERROR(SEARCH(I$2,$H168),0)) -> 0 | J168: =MIN(1,IFERROR(SEARCH(J$2,$H168),0)) -> 0 | K168: =MIN(1,IFERROR(SEARCH(K$2,$H168),0)) -> 1 | L168: =IF(I168*J168=1,"Гороховый изолят",IF(I168*K168=1,"Гороховый концентрат",0)) -> 0 | M168: =$I168*J168 -> 0 | N168: =$I168*K168 -> 0 | O168: 3150 | P168: 22794.88
B169: 20.07.2021 | C169: =YEAR(B169) -> 2021 | D169: =MONTH(B169) -> 7 | E169: ИМ | F169: БРАЗИЛИЯ | G169: РОССИЯ | H169: LYU БЕЛОК КОЛЛАГЕНОВЫЙ ЖИВОТНЫЙ ГОВЯЖИЙ МАРКИ "NOVAPRO",, В В ВИДЕ ПУДРЫ, СОДЕРЖАНИЕ ПРОТЕИНА 98,00%, ИСПОЛЬЗУЕТСЯ В ПИЩЕВОЙ ПРОМЫШЛЕННОСТИ В КАЧЕСТВЕ ДОБАВКИ, В КАРТОННЫХ КОРОБКАХ С П/Э ВКЛАДЫШЕМ ПО 20 КГ | I169: =MIN(1,IFERROR(SEARCH(I$2,$H169),0)) -> 0 | J169: =MIN(1,IFERROR(SEARCH(J$2,$H169),0)) -> 0 | K169: =MIN(1,IFERROR(SEARCH(K$2,$H169),0)) -> 0 | L169: =IF(I169*J169=1,"Гороховый изолят",IF(I169*K169=1,"Гороховый концентрат",0)) -> 0 | M169: =$I169*J169 -> 0 | N169: =$I169*K169 -> 0 | O169: 11400 | P169: 51300
B170: 23.02.2021 | C170: =YEAR(B170) -> 2021 | D170: =MONTH(B170) -> 2 | E170: ИМ | F170: ГЕРМАНИЯ | G170: РОССИЯ | H170: LYU ГИДРОЛИЗОВАННЫЙ РАСТИТЕЛЬНЫЙ БЕЛОК <КФ РОХШТОФФ 90> ((<KF ROHSTOFF 90>) FHDFH | I170: =MIN(1,IFERROR(SEARCH(I$2,$H170),0)) -> 0 | J170: =MIN(1,IFERROR(SEARCH(J$2,$H170),0)) -> 0 | K170: =MIN(1,IFERROR(SEARCH(K$2,$H170),0)) -> 0 | L170: =IF(I170*J170=1,"Гороховый изолят",IF(I170*K170=1,"Гороховый концентрат",0)) -> 0 | M170: =$I170*J170 -> 0 | N170: =$I170*K170 -> 0 | O170: 101.2 | P170: 670.34
B171: 14.10.2021 | C171: =YEAR(B171) -> 2021 | D171: =MONTH(B171) -> 10 | E171: ИМ | F171: ВЕНГРИЯ | G171: РОССИЯ | H171: LYU ГЛЮТЕН КУКУРУЗНЫЙ СУХОЙ "CORN GLUTEN MEAL", ИСП. В КАЧЕСТВЕ РАСТИТЕЛЬНОГО БЕЛКА ПРИ ПРИ ПРОИЗВОДСТВЕ КОРМОВ ДЛЯ ЖИВОТНЫХ НА ТЕРРИТОРИИ РФ;; | I171: =MIN(1,IFERROR(SEARCH(I$2,$H171),0)) -> 0 | J171: =MIN(1,IFERROR(SEARCH(J$2,$H171),0)) -> 0 | K171: =MIN(1,IFERROR(SEARCH(K$2,$H171),0)) -> 0 | L171: =IF(I171*J171=1,"Гороховый изолят",IF(I171*K171=1,"Гороховый концентрат",0)) -> 0 | M171: =$I171*J171 -> 0 | N171: =$I171*K171 -> 0 | O171: 21000 | P171: 19431.1
... B201: 02.06.2021 | C201: =YEAR(B201) -> 2021 | D201: =MONTH(B201) -> 6 | E201: ИМ | F201: БЕЛЬГИЯ | G201: РОССИЯ | H201: MRW ЭКСТРУДИРОВАННЫЙ ПИЩЕВОЙ ИНГРЕДИЕНТ; НА ОСНОВЕ ПШЕНИЧНОГО: ПРОТЕИНА (ГЛЮТЕН): И ПШЕНИЧНОЙ МУКИ: ПРИМЕНЯЕТСЯ В: ПИЩЕВОЙ ПРОМЫШЛЕННОСТИ BNBKNC | I201: =MIN(1,IFERROR(SEARCH(I$2,$H201),0)) -> 0 | J201: =MIN(1,IFERROR(SEARCH(J$2,$H201),0)) -> 0 | K201: =MIN(1,IFERROR(SEARCH(K$2,$H201),0)) -> 0 | L201: =IF(I201*J201=1,"Гороховый изолят",IF(I201*K201=1,"Гороховый концентрат",0)) -> 0 | M201: =$I201*J201 -> 0 | N201: =$I201*K201 -> 0 | O201: 600 | P201: 2065.62
B202: 45531 | C202: =YEAR(B202) -> 2024 | D202: =MONTH(B202) -> 8 | E202: Им | F202: КИТАЙ | G202: РОССИЯ | H202: MАССА СОЕВАЯ ПРОТЕИНОВАЯ - СПАРЖА, ДЛЯ УПОТРЕБЛЕНИЯ В ПИЩУ, МАРКИРОВКА - XUCHANG WANGJIA FOOD CO., LTD ВВОЗИМАЯ ПРОДУКЦИЯ ПРЕДНАЗНАЧЕНА ДЛЯ ОБРАЩЕНИЯ ИСКЛЮЧИТЕЛЬНО НА ТЕРРИТОРИИ РФ. | I202: =MIN(1,IFERROR(SEARCH(I$2,$H202),0)) -> 0 | J202: =MIN(1,IFERROR(SEARCH(J$2,$H202),0)) -> 0 | K202: =MIN(1,IFERROR(SEARCH(K$2,$H202),0)) -> 0 | L202: =IF(I202*J202=1,"Гороховый изолят",IF(I202*K202=1,"Гороховый концентрат",0)) -> 0 | M202: =$I202*J202 -> 0 | N202: =$I202*K202 -> 0 | O202: 1350 | P202: 2713.5
B203: 29.05.2020 | C203: =YEAR(B203) -> 2020 | D203: =MONTH(B203) -> 5 | E203: ИМ | F203: ФРАНЦИЯ | G203: РОССИЯ | H203: NUTELINE PS- ЯВЛЯЕТСЯ НИЗКОМОЛЕКУЛЯРНЫМ ПЕПТИДНЫМ ЭКСТРАКТОМ ИЗ ЛЕСНОГО ОРЕХА, ПРОДУКТ ПОЛУЧАЮТ БИОТЕХНОЛОГИЧЕСКИМ ПУТЕМ С ИСПОЛЬЗОВАНИЕМ РЕГУЛИРУЕМОГО ФЕРМЕНТАТИВНОГО ГИДРОЛИЗА. (НЕ СОДЕРЖИТ ЭТИЛ.СПИРТ, НЕ ДЛЯ РОЗНИЧНОЙ ПРОДАЖИ, НЕ ДЛЯ ВЕТЕРИНАРИИ NUTELINE PS (CAS № 100209-45-8) -98,2% ГИДРОЛИЗОВАННОГО БЕЛКА ФУНДУКА, ПОЛУПРОЗРАЧНАЯ ЖИДКОСТЬ ОТ ТЕМНО-ОРАНЖЕВОГО ДО ТЕМНО-КОРИЧНЕВОГО ЦВЕТА С ХАРАКТЕРНЫМ ЗАПАХОМ, УПАК. 4 БОЧКИ ПО 5КГ ):ПРИМЕНЯЕТСЯ В КАЧЕСТВЕ СЫРЬЕВОГО КОМПОНЕНТА ДЛЯ ПРОИЗВОДСТВА КОСМЕТИЧЕСКИХ СРЕДСТВ SOLABIA ОТСУТСТВУЕТ NUTELINE PS 20 | I203: =MIN(1,IFERROR(SEARCH(I$2,$H203),0)) -> 0 | J203: =MIN(1,IFERROR(SEARCH(J$2,$H203),0)) -> 0 | K203: =MIN(1,IFERROR(SEARCH(K$2,$H203),0)) -> 0 | L203: =IF(I203*J203=1,"Гороховый изолят",IF(I203*K203=1,"Гороховый концентрат",0)) -> 0 | M203: =$I203*J203 -> 0 | N203: =$I203*K203 -> 0 | O203: 20 | P203: 1344.85
B204: 07.08.2023 | C204: =YEAR(B204) -> 2023 | D204: =MONTH(B204) -> 8 | E204: ИМ | F204: ТУРЦИЯ | G204: РОССИЯ | H204: NUTRILAN KERATIN LM-КОСМЕТИЧЕСКИЙ ИНГРЕДИЕНТ, ГИДРОЛИЗОВАННЫЙ КЕРАТИНОВЫЙ БЕЛОК, ПОДХОДЯЩИЙ ДЛЯ СРЕДСТВ ПО УХОДУ ЗА КОЖЕЙ И ВОЛОСАМИ, ОСОБЕННО ДЛЯ СРЕДСТВ ПО УХОДУ ЗА ВОЛОСАМИ С ВОССТАНАВЛИВАЮЩИМИ И РЕСТРУКТУРИРУЮЩИМИ СВОЙСТВАМИ. . НЕ ДЛЯ ПИЩ. | I204: =MIN(1,IFERROR(SEARCH(I$2,$H204),0)) -> 0 | J204: =MIN(1,IFERROR(SEARCH(J$2,$H204),0)) -> 0 | K204: =MIN(1,IFERROR(SEARCH(K$2,$H204),0)) -> 0 | L204: =IF(I204*J204=1,"Гороховый изолят",IF(I204*K204=1,"Гороховый концентрат",0)) -> 0 | M204: =$I204*J204 -> 0 | N204: =$I204*K204 -> 0 | O204: 25 | P204: 1519.34
B205: 13.07.2021 | C205: =YEAR(B205) -> 2021 | D205: =MONTH(B205) -> 7 | E205: ИМ | F205: СОЕДИНЕННОЕ КОРОЛЕВСТВО | G205: РОССИЯ | H205: OXOID ПЕПТОН БАКТЕРИОЛОГИЧЕСКИЙ НЕЙТРАЛИЗОВАННЫЙ, БЫЧИЙ, ЛАБОРАТОРНЫЙ РЕАКТИВ, КАС № 73049-73-7, НЕ ДЛЯ МЕДИЦИНЫ, НЕ ДЛЯ ВЕТЕРИНАРИИ, НЕ ЯВЛЯЕТСЯ ОТХОДАМИ,НЕ ФАРМ. СУБСТАНЦИЯ, БЕЗ СОДЕРЖАНИЯ ЭТИЛОВОГО СПИРТА: | I205: =MIN(1,IFERROR(SEARCH(I$2,$H205),0)) -> 0 | J205: =MIN(1,IFERROR(SEARCH(J$2,$H205),0)) -> 0 | K205: =MIN(1,IFERROR(SEARCH(K$2,$H205),0)) -> 0 | L205: =IF(I205*J205=1,"Гороховый изолят",IF(I205*K205=1,"Гороховый концентрат",0)) -> 0 | M205: =$I205*J205 -> 0 | N205: =$I205*K205 -> 0 | O205: 2.25 | P205: 157.79
B206: 13.07.2021 | C206: =YEAR(B206) -> 2021 | D206: =MONTH(B206) -> 7 | E206: ИМ | F206: СОЕДИНЕННОЕ КОРОЛЕВСТВО | G206: РОССИЯ | H206: OXOID ПЕПТОН БАКТЕРИОЛОГИЧЕСКИЙ НЕЙТРАЛИЗОВАННЫЙ, ЛАБОРАТОРНЫЙ РЕАКТИВ, КАС № 73049-73-7, НЕ ДЛЯ МЕДИЦИНЫ, НЕ ДЛЯ ВЕТЕРИНАРИИ, НЕ ЯВЛЯЕТСЯ ОТХОДАМИ,НЕ ФАРМ. СУБСТАНЦИЯ, БЕЗ СОДЕРЖАНИЯ ЭТИЛОВОГО СПИРТА: | I206: =MIN(1,IFERROR(SEARCH(I$2,$H206),0)) -> 0 | J206: =MIN(1,IFERROR(SEARCH(J$2,$H206),0)) -> 0 | K206: =MIN(1,IFERROR(SEARCH(K$2,$H206),0)) -> 0 | L206: =IF(I206*J206=1,"Гороховый изолят",IF(I206*K206=1,"Гороховый концентрат",0)) -> 0 | M206: =$I206*J206 -> 0 | N206: =$I206*K206 -> 0 | O206: 0.75 | P206: 56.21
B207: 23.03.2022 | C207: =YEAR(B207) -> 2022 | D207: =MONTH(B207) -> 3 | E207: ИМ | F207: КИТАЙ | G207: РОССИЯ | H207: PEA PROTEIN POWDER B80-ГОРОХОВЫЙ БЕЛОК ДЛЯ ПРОМЫШЛЕННОГО ПРИМЕНЕНИЯ В ПИЩЕВОЙ ПРОМЫШЛЕННОСТИ . НЕ СОДЕРЖИТ ГМО. УПАКОВАН В МЕШКИ ПО 25 КГ. ВЕС БРУТТО С УЧЕТОМ ВЕСА ПОДДОНОВ 1058.00 КГ. ИЗОЛЯТ | I207: =MIN(1,IFERROR(SEARCH(I$2,$H207),0)) -> 1 | J207: =MIN(1,IFERROR(SEARCH(J$2,$H207),0)) -> 1 | K207: =MIN(1,IFERROR(SEARCH(K$2,$H207),0)) -> 0 | L207: =IF(I207*J207=1,"Гороховый изолят",IF(I207*K207=1,"Гороховый концентрат",0)) -> Гороховый изолят | M207: =$I207*J207 -> 1 | N207: =$I207*K207 -> 0 | O207: 1000 | P207: 5256
B208: 18.03.2022 | C208: =YEAR(B208) -> 2022 | D208: =MONTH(B208) -> 3 | E208: ИМ | F208: НИДЕРЛАНДЫ | G208: РОССИЯ | H208: PRODIEM REFRESH PEA 7304- ГИДРОЛИЗАТ ГОРОХОВОГО БЕЛКА ДЛЯ ИСПОЛЬЗОВАНИЯ В ПИЩЕВОЙ ПРОМЫШЛЕННОСТИ В КАЧЕСТВЕ ИСТОЧНИКА РАСТВОРИМЫХ ПЕПТИДОВ В ДИЕТИЧЕСКИХ ПРОДУКТАХ, НАПИТКАХ,ОБОГАЩЕННЫХ БЕЛКОМ, И СПОРТИВНЫХ НАПИТКАХ.НЕ СОДЕРЖИТ ГМО. УПАКОВАН В КОРОБКИ | I208: =MIN(1,IFERROR(SEARCH(I$2,$H208),0)) -> 1 | J208: =MIN(1,IFERROR(SEARCH(J$2,$H208),0)) -> 0 | K208: =MIN(1,IFERROR(SEARCH(K$2,$H208),0)) -> 0 | L208: =IF(I208*J208=1,"Гороховый изолят",IF(I208*K208=1,"Гороховый концентрат",0)) -> 0 | M208: =$I208*J208 -> 0 | N208: =$I208*K208 -> 0 | O208: 15 | P208: 321.96
B209: 04.05.2022 | C209: =YEAR(B209) -> 2022 | D209: =MONTH(B209) -> 5 | E209: ИМ | F209: НИДЕРЛАНДЫ | G209: РОССИЯ | H209: PRODIEM REFRESH SOY 1307-ГИДРОЛИЗАТ ИЗОЛЯТА СОЕВОГО БЕЛКА. ДЛЯ ИСПОЛЬЗОВАНИЯ В ПИЩЕВОЙ ПРОМЫШЛЕННОСТИ В КАЧЕСТВЕ ИСТОЧНИКА РАСТВОРИМЫХ ПЕПТИДОВ В ДИЕТИЧЕСКИХ ПРОДУКТАХ И НАПИТКАХ, ОБОГАЩЕННЫХ БЕЛКОМ. НЕ СОДЕРЖИТ ГМО. УПАКОВАН В КОРОБКИ ПО 15 КГ. | I209: =MIN(1,IFERROR(SEARCH(I$2,$H209),0)) -> 0 | J209: =MIN(1,IFERROR(SEARCH(J$2,$H209),0)) -> 1 | K209: =MIN(1,IFERROR(SEARCH(K$2,$H209),0)) -> 0 | L209: =IF(I209*J209=1,"Гороховый изолят",IF(I209*K209=1,"Гороховый концентрат",0)) -> 0 | M209: =$I209*J209 -> 0 | N209: =$I209*K209 -> 0 | O209: 15 | P209: 318.76
...
