Workbook

Sheet Задание
B2: Домашнее задание №2
B4: Описание
C5: Исходные данные
C6: Таможенные декларации по импорту и экспорту кормов для домашних животных
C7: Объемы производства кормов для домашних животных (7 листов)
C8: Цены на корма для домашних животных
C9: Продажи Компании
B11: Задание
B12: 1 | C12: Провести анализ внешней торговли
B13: 1.1 | C13: Посчитать за 2023 г. импорт и экспорт кормов для домашних животных в тоннах и в рублях - по месяцам и суммарно по году
C14: Для расчета в рублях использовать столбец "46 Статистическая стоимость" с дальнейшим переводом в рубли по курсу доллара 90
B15: 1.2 | C15: Определить топ стран-поставщиков кормов в Россию по итогам годам 2023 г. (столбец - 16 Страна происхождения)
B17: 2 | C17: Посчитать объем рынка* кормов за 2023 г. в стоимостном и натуральном выражении - по месяцам и суммарно по году
C18: * Объем рынка = производство + импорт - экспорт
C19: * Проиводство в стоим. выражении = Проиводство выражении в тоннах * цены
B21: 3 | C21: Посчитать долю рынка Компании по месяцам и суммарно по году в стоимостном и натуральном выражении
C23: Обязательно:
C24: Аккуратно все структурировать и сгруппировать
C25: Использовать корректные форматы чисел
C26: Единообразный формат (ссылки, итоги и пр.)
B28: Hints
C30: Не нужно искать/использовать дополнительные данные
C31: В декларациях могут быть не только корма и не только 2023 г. Делайте поиск по слову "корм"
C32: Можно что-то изменять на листах исходных данных (например, разъединять ячейки, добавлять столбцы, делать расчеты и тд)
C34: Нужные столбцы на листе Декларации:
C35: D1 Дата выпуска груза
C36: 011 ИМ.ЭК - направление перемещения
C37: 16 Страна происхождения
C38: 31_1 Описание и характеристика товара
C39: 38 Вес нетто, кг
C40: 46 Статистическая стоимость

Sheet Sheet1
D1: янв | E1: фев | F1: мар | G1: апр | H1: май | I1: июн | J1: июл | K1: авг | L1: сен | M1: окт | N1: ноя | O1: дек | Q1: 2023 | S1: Вспом. столб.
A2: Номер месяца | D2: 1 | E2: 2 | F2: 3 | G2: 4 | H2: 5 | I2: 6 | J2: 7 | K2: 8 | L2: 9 | M2: 10 | N2: 11 | O2: 12
A4: Импорт | B4: т | D4: =SUMIFS(Декларации!$CI:$CI,Декларации!$C:$C,D$2,Декларации!$G:$G,$S4,Декларации!$BR:$BR,1)/1000 -> 939.79081 | E4: =SUMIFS(Декларации!$CI:$CI,Декларации!$C:$C,E$2,Декларации!$G:$G,$S4,Декларации!$BR:$BR,1)/1000 -> 665.98533 | F4: =SUMIFS(Декларации!$CI:$CI,Декларации!$C:$C,F$2,Декларации!$G:$G,$S4,Декларации!$BR:$BR,1)/1000 -> 1049.6604 | G4: =SUMIFS(Декларации!$CI:$CI,Декларации!$C:$C,G$2,Декларации!$G:$G,$S4,Декларации!$BR:$BR,1)/1000 -> 760.35202 | H4: =SUMIFS(Декларации!$CI:$CI,Декларации!$C:$C,H$2,Декларации!$G:$G,$S4,Декларации!$BR:$BR,1)/1000 -> 657.949 | I4: =SUMIFS(Декларации!$CI:$CI,Декларации!$C:$C,I$2,Декларации!$G:$G,$S4,Декларации!$BR:$BR,1)/1000 -> 853.88824 | J4: =SUMIFS(Декларации!$CI:$CI,Декларации!$C:$C,J$2,Декларации!$G:$G,$S4,Декларации!$BR:$BR,1)/1000 -> 1110.9289 | K4: =SUMIFS(Декларации!$CI:$CI,Декларации!$C:$C,K$2,Декларации!$G:$G,$S4,Декларации!$BR:$BR,1)/1000 -> 869.0245 | ... O4: =SUMIFS(Декларации!$CI:$CI,Декларации!$C:$C,O$2,Декларации!$G:$G,$S4,Декларации!$BR:$BR,1)/1000 -> 992.1899 | Q4: =SUM(D4:O4) -> 10832.678 | S4: ИМ
A5: Импорт | B5: тыс. руб. | D5: =SUMIFS(Декларации!$CR:$CR,Декларации!$C:$C,D$2,Декларации!$G:$G,$S5,Декларации!$BR:$BR,1)/1000*90 -> 264542.99 | E5: =SUMIFS(Декларации!$CR:$CR,Декларации!$C:$C,E$2,Декларации!$G:$G,$S5,Декларации!$BR:$BR,1)/1000*90 -> 181764.48 | F5: =SUMIFS(Декларации!$CR:$CR,Декларации!$C:$C,F$2,Декларации!$G:$G,$S5,Декларации!$BR:$BR,1)/1000*90 -> 290733.7 | G5: =SUMIFS(Декларации!$CR:$CR,Декларации!$C:$C,G$2,Декларации!$G:$G,$S5,Декларации!$BR:$BR,1)/1000*90 -> 209525.84 | H5: =SUMIFS(Декларации!$CR:$CR,Декларации!$C:$C,H$2,Декларации!$G:$G,$S5,Декларации!$BR:$BR,1)/1000*90 -> 181208.44 | I5: =SUMIFS(Декларации!$CR:$CR,Декларации!$C:$C,I$2,Декларации!$G:$G,$S5,Декларации!$BR:$BR,1)/1000*90 -> 240790.71 | J5: =SUMIFS(Декларации!$CR:$CR,Декларации!$C:$C,J$2,Декларации!$G:$G,$S5,Декларации!$BR:$BR,1)/1000*90 -> 309665.29 | K5: =SUMIFS(Декларации!$CR:$CR,Декларации!$C:$C,K$2,Декларации!$G:$G,$S5,Декларации!$BR:$BR,1)/1000*90 -> 241078.11 | ... O5: =SUMIFS(Декларации!$CR:$CR,Декларации!$C:$C,O$2,Декларации!$G:$G,$S5,Декларации!$BR:$BR,1)/1000*90 -> 274120.11 | Q5: =SUM(D5:O5) -> 3002127.1 | S5: ИМ
A7: Экспорт | B7: т | D7: =SUMIFS(Декларации!$CI:$CI,Декларации!$C:$C,D$2,Декларации!$G:$G,$S7,Декларации!$BR:$BR,1)/1000 -> 148.21436 | E7: =SUMIFS(Декларации!$CI:$CI,Декларации!$C:$C,E$2,Декларации!$G:$G,$S7,Декларации!$BR:$BR,1)/1000 -> 126.01284 | F7: =SUMIFS(Декларации!$CI:$CI,Декларации!$C:$C,F$2,Декларации!$G:$G,$S7,Декларации!$BR:$BR,1)/1000 -> 180.60737 | G7: =SUMIFS(Декларации!$CI:$CI,Декларации!$C:$C,G$2,Декларации!$G:$G,$S7,Декларации!$BR:$BR,1)/1000 -> 81.72427 | H7: =SUMIFS(Декларации!$CI:$CI,Декларации!$C:$C,H$2,Декларации!$G:$G,$S7,Декларации!$BR:$BR,1)/1000 -> 166.78133 | I7: =SUMIFS(Декларации!$CI:$CI,Декларации!$C:$C,I$2,Декларации!$G:$G,$S7,Декларации!$BR:$BR,1)/1000 -> 207.91249 | J7: =SUMIFS(Декларации!$CI:$CI,Декларации!$C:$C,J$2,Декларации!$G:$G,$S7,Декларации!$BR:$BR,1)/1000 -> 83.24303 | K7: =SUMIFS(Декларации!$CI:$CI,Декларации!$C:$C,K$2,Декларации!$G:$G,$S7,Декларации!$BR:$BR,1)/1000 -> 150.52447 | ... O7: =SUMIFS(Декларации!$CI:$CI,Декларации!$C:$C,O$2,Декларации!$G:$G,$S7,Декларации!$BR:$BR,1)/1000 -> 81.91393 | Q7: =SUM(D7:O7) -> 1495.1891 | S7: ЭК
A8: Экспорт | B8: тыс. руб. | D8: =SUMIFS(Декларации!$CR:$CR,Декларации!$C:$C,D$2,Декларации!$G:$G,$S8,Декларации!$BR:$BR,1)/1000*90 -> 42517.071 | E8: =SUMIFS(Декларации!$CR:$CR,Декларации!$C:$C,E$2,Декларации!$G:$G,$S8,Декларации!$BR:$BR,1)/1000*90 -> 35326.055 | F8: =SUMIFS(Декларации!$CR:$CR,Декларации!$C:$C,F$2,Декларации!$G:$G,$S8,Декларации!$BR:$BR,1)/1000*90 -> 49728.294 | G8: =SUMIFS(Декларации!$CR:$CR,Декларации!$C:$C,G$2,Декларации!$G:$G,$S8,Декларации!$BR:$BR,1)/1000*90 -> 23009.752 | H8: =SUMIFS(Декларации!$CR:$CR,Декларации!$C:$C,H$2,Декларации!$G:$G,$S8,Декларации!$BR:$BR,1)/1000*90 -> 46028.2 | I8: =SUMIFS(Декларации!$CR:$CR,Декларации!$C:$C,I$2,Декларации!$G:$G,$S8,Декларации!$BR:$BR,1)/1000*90 -> 55344.224 | J8: =SUMIFS(Декларации!$CR:$CR,Декларации!$C:$C,J$2,Декларации!$G:$G,$S8,Декларации!$BR:$BR,1)/1000*90 -> 21577.476 | K8: =SUMIFS(Декларации!$CR:$CR,Декларации!$C:$C,K$2,Декларации!$G:$G,$S8,Декларации!$BR:$BR,1)/1000*90 -> 40505.251 | ... O8: =SUMIFS(Декларации!$CR:$CR,Декларации!$C:$C,O$2,Декларации!$G:$G,$S8,Декларации!$BR:$BR,1)/1000*90 -> 22563.588 | Q8: =SUM(D8:O8) -> 408639.28 | S8: ЭК
A10: Производство | B10: т | D10: ='Росстат_Пр-во ЦФО'!D5+'Росстат_Пр-во СЗФО'!D5+'Росстат_Пр-во ЮФО'!D5+'Росстат_Пр-во ЮФО'!D5+'Росстат_Пр-во ЮФО'!D5+'Росстат_Пр-во ПФО'!D5+'Росстат_Пр-во УФО'!D5+'Росстат_Пр-во СФО'!D5+'Росстат_Пр-во ДФО'!D5 -> 5900.11 | E10: ='Росстат_Пр-во ЦФО'!E5+'Росстат_Пр-во СЗФО'!E5+'Росстат_Пр-во ЮФО'!E5+'Росстат_Пр-во ЮФО'!E5+'Росстат_Пр-во ЮФО'!E5+'Росстат_Пр-во ПФО'!E5+'Росстат_Пр-во УФО'!E5+'Росстат_Пр-во СФО'!E5+'Росстат_Пр-во ДФО'!E5 -> 6852.75 | F10: ='Росстат_Пр-во ЦФО'!F5+'Росстат_Пр-во СЗФО'!F5+'Росстат_Пр-во ЮФО'!F5+'Росстат_Пр-во ЮФО'!F5+'Росстат_Пр-во ЮФО'!F5+'Росстат_Пр-во ПФО'!F5+'Росстат_Пр-во УФО'!F5+'Росстат_Пр-во СФО'!F5+'Росстат_Пр-во ДФО'!F5 -> 7787.96 | G10: ='Росстат_Пр-во ЦФО'!G5+'Росстат_Пр-во СЗФО'!G5+'Росстат_Пр-во ЮФО'!G5+'Росстат_Пр-во ЮФО'!G5+'Росстат_Пр-во ЮФО'!G5+'Росстат_Пр-во ПФО'!G5+'Росстат_Пр-во УФО'!G5+'Росстат_Пр-во СФО'!G5+'Росстат_Пр-во ДФО'!G5 -> 7668.92 | H10: ='Росстат_Пр-во ЦФО'!H5+'Росстат_Пр-во СЗФО'!H5+'Росстат_Пр-во ЮФО'!H5+'Росстат_Пр-во ЮФО'!H5+'Росстат_Пр-во ЮФО'!H5+'Росстат_Пр-во ПФО'!H5+'Росстат_Пр-во УФО'!H5+'Росстат_Пр-во СФО'!H5+'Росстат_Пр-во ДФО'!H5 -> 8522.6 | I10: ='Росстат_Пр-во ЦФО'!I5+'Росстат_Пр-во СЗФО'!I5+'Росстат_Пр-во ЮФО'!I5+'Росстат_Пр-во ЮФО'!I5+'Росстат_Пр-во ЮФО'!I5+'Росстат_Пр-во ПФО'!I5+'Росстат_Пр-во УФО'!I5+'Росстат_Пр-во СФО'!I5+'Росстат_Пр-во ДФО'!I5 -> 8773.36 | J10: ='Росстат_Пр-во ЦФО'!J5+'Росстат_Пр-во СЗФО'!J5+'Росстат_Пр-во ЮФО'!J5+'Росстат_Пр-во ЮФО'!J5+'Росстат_Пр-во ЮФО'!J5+'Росстат_Пр-во ПФО'!J5+'Росстат_Пр-во УФО'!J5+'Росстат_Пр-во СФО'!J5+'Росстат_Пр-во ДФО'!J5 -> 8648.69 | K10: ='Росстат_Пр-во ЦФО'!K5+'Росстат_Пр-во СЗФО'!K5+'Росстат_Пр-во ЮФО'!K5+'Росстат_Пр-во ЮФО'!K5+'Росстат_Пр-во ЮФО'!K5+'Росстат_Пр-во ПФО'!K5+'Росстат_Пр-во УФО'!K5+'Росстат_Пр-во СФО'!K5+'Росстат_Пр-во ДФО'!K5 -> 8792.88 | ... O10: ='Росстат_Пр-во ЦФО'!O5+'Росстат_Пр-во СЗФО'!O5+'Росстат_Пр-во ЮФО'!O5+'Росстат_Пр-во ЮФО'!O5+'Росстат_Пр-во ЮФО'!O5+'Росстат_Пр-во ПФО'!O5+'Росстат_Пр-во УФО'!O5+'Росстат_Пр-во СФО'!O5+'Росстат_Пр-во ДФО'!O5 -> 9783.28 | Q10: =SUM(D10:O10) -> 100065.54
A11: Производство | B11: тыс. руб. | D11: =D10*Росстат_Цены!C5 -> 1807970.7 | E11: =E10*Росстат_Цены!D5 -> 2077205.6 | F11: =F10*Росстат_Цены!E5 -> 2359440.4 | G11: =G10*Росстат_Цены!F5 -> 2357426 | H11: =H10*Росстат_Цены!G5 -> 2617290.5 | I11: =I10*Росстат_Цены!H5 -> 2705528.8 | J11: =J10*Росстат_Цены!I5 -> 2720359 | K11: =K10*Росстат_Цены!J5 -> 2914312.1 | ... O11: =O10*Росстат_Цены!N5 -> 3373470.6 | Q11: =SUM(D11:O11) -> 32255963
A13: Объем рынка | B13: т | D13: =D10+D4-D7 -> 6691.6864 | E13: =E10+E4-E7 -> 7392.7225 | F13: =F10+F4-F7 -> 8657.0131 | G13: =G10+G4-G7 -> 8347.5478 | H13: =H10+H4-H7 -> 9013.7677 | I13: =I10+I4-I7 -> 9419.3358 | J13: =J10+J4-J7 -> 9676.3758 | K13: =K10+K4-K7 -> 9511.38 | ... O13: =O10+O4-O7 -> 10693.556 | Q13: =SUM(D13:O13) -> 109403.03
A14: Объем рынка | B14: тыс. руб. | D14: =D11+D5-D8 -> 2029996.6 | E14: =E11+E5-E8 -> 2223644 | F14: =F11+F5-F8 -> 2600445.8 | G14: =G11+G5-G8 -> 2543942.1 | H14: =H11+H5-H8 -> 2752470.7 | I14: =I11+I5-I8 -> 2890975.2 | J14: =J11+J5-J8 -> 3008446.8 | K14: =K11+K5-K8 -> 3114885 | ... O14: =O11+O5-O8 -> 3625027.1 | Q14: =SUM(D14:O14) -> 34849451
A16: Доля компании, нат. выраж. | B16: % | D16: ='Продажи Компании'!K22/D13 -> 0.29816536 | E16: ='Продажи Компании'!L22/E13 -> 0.2804771 | F16: ='Продажи Компании'!M22/F13 -> 0.30984334 | G16: ='Продажи Компании'!N22/G13 -> 0.29249056 | H16: ='Продажи Компании'!O22/H13 -> 0.26935293 | I16: ='Продажи Компании'!P22/I13 -> 0.21891335 | J16: ='Продажи Компании'!Q22/J13 -> 0.23176583 | K16: ='Продажи Компании'!R22/K13 -> 0.26537718 | ... O16: ='Продажи Компании'!V22/O13 -> 0.18971229 | Q16: ='Продажи Компании'!X22/Q13 -> 0.25493142
A17: Доля компании, стоим. выраж. | B17: % | D17: ='Продажи Компании'!K64*1000/D14 -> 0.25886615 | E17: ='Продажи Компании'!L64*1000/E14 -> 0.2411137 | F17: ='Продажи Компании'!M64*1000/F14 -> 0.25364764 | G17: ='Продажи Компании'!N64*1000/G14 -> 0.26663299 | H17: ='Продажи Компании'!O64*1000/H14 -> 0.25230022 | I17: ='Продажи Компании'!P64*1000/I14 -> 0.19598268 | J17: ='Продажи Компании'!Q64*1000/J14 -> 0.20227735 | K17: ='Продажи Компании'!R64*1000/K14 -> 0.21232977 | ... O17: ='Продажи Компании'!V64*1000/O14 -> 0.15244312 | Q17: ='Продажи Компании'!X64*1000/Q14 -> 0.21371817
A19: Топ импортеров в РФ
A20: =Sheet2!A17 -> БЕЛЬГИЯ
A21: =Sheet2!A18 -> ФРАНЦИЯ

Sheet Исходные данные→

Sheet Продажи Компании
B1: Показатель | G1: ед. изм. | H1: Предпосылка | K1: 44927 | L1: =EDATE(K1,1) -> 44958 | M1: =EDATE(L1,1) -> 44986 | N1: =EDATE(M1,1) -> 45017 | O1: =EDATE(N1,1) -> 45047 | P1: =EDATE(O1,1) -> 45078 | Q1: =EDATE(P1,1) -> 45108 | R1: =EDATE(Q1,1) -> 45139 | S1: =EDATE(R1,1) -> 45170 | ... V1: =EDATE(U1,1) -> 45261 | X1: 2023
B2: Продажи в натуральном выражении
B4: Корма для собак | G4: т | K4: =K5+K9 -> 919.94381 | L4: =L5+L9 -> 919.94381 | M4: =M5+M9 -> 919.94381 | N4: =N5+N9 -> 919.94381 | O4: =O5+O9 -> 919.94381 | P4: =P5+P9 -> 919.94381 | Q4: =Q5+Q9 -> 919.94381 | R4: =R5+R9 -> 919.94381 | ... V4: =V5+V9 -> 919.94381 | X4: =SUM(K4:V4) -> 11039.326
C5: Онлайн продажи | G5: т | K5: =K6+K7 -> 533.23056 | L5: =L6+L7 -> 533.23056 | M5: =M6+M7 -> 533.23056 | N5: =N6+N7 -> 533.23056 | O5: =O6+O7 -> 533.23056 | P5: =P6+P7 -> 533.23056 | Q5: =Q6+Q7 -> 533.23056 | R5: =R6+R7 -> 533.23056 | ... V5: =V6+V7 -> 533.23056 | X5: =SUM(K5:V5) -> 6398.7667
D6: Эконом сегмент | G6: т | K6: 221.90827 | L6: 221.90827 | M6: 221.90827 | N6: 221.90827 | O6: 221.90827 | P6: 221.90827 | Q6: 221.90827 | R6: 221.90827 | S6: 221.90827 | T6: 221.90827 | U6: 221.90827 | V6: 221.90827 | X6: =SUM(K6:V6) -> 2662.8993
D7: Премиум сегмент | G7: т | K7: 311.32228 | L7: 311.32228 | M7: 311.32228 | N7: 311.32228 | O7: 311.32228 | P7: 311.32228 | Q7: 311.32228 | R7: 311.32228 | S7: 311.32228 | T7: 311.32228 | U7: 311.32228 | V7: 311.32228 | X7: =SUM(K7:V7) -> 3735.8674
C9: Офлайн продажи | G9: т | K9: =K10+K11 -> 386.71326 | L9: =L10+L11 -> 386.71326 | M9: =M10+M11 -> 386.71326 | N9: =N10+N11 -> 386.71326 | O9: =O10+O11 -> 386.71326 | P9: =P10+P11 -> 386.71326 | Q9: =Q10+Q11 -> 386.71326 | R9: =R10+R11 -> 386.71326 | ... V9: =V10+V11 -> 386.71326 | X9: =SUM(K9:V9) -> 4640.5591
D10: Эконом сегмент | G10: т | K10: 193.7266 | L10: 193.7266 | M10: 193.7266 | N10: 193.7266 | O10: 193.7266 | P10: 193.7266 | Q10: 193.7266 | R10: 193.7266 | S10: 193.7266 | T10: 193.7266 | U10: 193.7266 | V10: 193.7266 | X10: =SUM(K10:V10) -> 2324.7192
D11: Премиум сегмент | G11: т | K11: 192.98665 | L11: 192.98665 | M11: 192.98665 | N11: 192.98665 | O11: 192.98665 | P11: 192.98665 | Q11: 192.98665 | R11: 192.98665 | S11: 192.98665 | T11: 192.98665 | U11: 192.98665 | V11: 192.98665 | X11: =SUM(K11:V11) -> 2315.8398
B13: Корма для кошек | G13: т | K13: =K14+K18 -> 1075.2853 | L13: =L14+L18 -> 1153.5455 | M13: =M14+M18 -> 1762.374 | N13: =N14+N18 -> 1521.6351 | O13: =O14+O18 -> 1507.9409 | P13: =P14+P18 -> 1142.0745 | Q13: =Q14+Q18 -> 1322.7094 | R13: =R14+R18 -> 1604.1594 | ... V13: =V14+V18 -> 1108.7552 | X13: =SUM(K13:V13) -> 16850.944
C14: Онлайн продажи | G14: т | K14: =K15+K16 -> 429.01237 | L14: =L15+L16 -> 521.78334 | M14: =M15+M16 -> 641.30919 | N14: =N15+N16 -> 531.86453 | O14: =O15+O16 -> 603.5511 | P14: =P15+P16 -> 441.30446 | Q14: =Q15+Q16 -> 535.61208 | R14: =R15+R16 -> 595.24076 | ... V14: =V15+V16 -> 452.46089 | X14: =SUM(K14:V14) -> 6589.1002
D15: Эконом сегмент | G15: т | K15: 164.50864 | L15: 238.58801 | M15: 323.25906 | N15: 196.03272 | O15: 344.96264 | P15: 204.67803 | Q15: 272.71168 | R15: 270.14438 | S15: 258.44967 | T15: 352.79026 | U15: 282.88535 | V15: 295.01213 | X15: =SUM(K15:V15) -> 3204.0226
D16: Премиум сегмент | G16: т | K16: 264.50373 | L16: 283.19533 | M16: 318.05013 | N16: 335.83181 | O16: 258.58846 | P16: 236.62643 | Q16: 262.9004 | R16: 325.09637 | S16: 283.05502 | T16: 355.81517 | U16: 303.96598 | V16: 157.44877 | X16: =SUM(K16:V16) -> 3385.0776
C18: Офлайн продажи | G18: т | K18: =K19+K20 -> 646.27288 | L18: =L19+L20 -> 631.76218 | M18: =M19+M20 -> 1121.0648 | N18: =N19+N20 -> 989.77061 | O18: =O19+O20 -> 904.38981 | P18: =P19+P20 -> 700.77005 | Q18: =Q19+Q20 -> 787.09735 | R18: =R19+R20 -> 1008.9186 | ... V18: =V19+V20 -> 656.29428 | X18: =SUM(K18:V18) -> 10261.844
D19: Эконом сегмент | G19: т | K19: 281.84381 | L19: 278.8877 | M19: 527.46729 | N19: 358.57814 | O19: 485.32985 | P19: 325.69236 | Q19: 447.45604 | R19: 496.91693 | S19: 310.41882 | T19: 621.47671 | U19: 462.13505 | V19: 418.87952 | X19: =SUM(K19:V19) -> 5015.0822
D20: Премиум сегмент | G20: т | K20: 364.42907 | L20: 352.87448 | M20: 593.59751 | N20: 631.19247 | O20: 419.05996 | P20: 375.07769 | Q20: 339.64131 | R20: 512.00168 | S20: 498.08946 | T20: 483.4758 | U20: 439.90733 | V20: 237.41476 | X20: =SUM(K20:V20) -> 5246.7615
B22: Всего | G22: т | K22: =K4+K13 -> 1995.2291 | L22: =L4+L13 -> 2073.4893 | M22: =M4+M13 -> 2682.3178 | N22: =N4+N13 -> 2441.5789 | O22: =O4+O13 -> 2427.8847 | P22: =P4+P13 -> 2062.0183 | Q22: =Q4+Q13 -> 2242.6532 | R22: =R4+R13 -> 2524.1032 | ... V22: =V4+V13 -> 2028.699 | X22: =X4+X13 -> 27890.27
B24: Цены реализации
B26: Корма для собак
C27: Онлайн продажи
D28: Эконом сегмент | G28: руб./кг | K28: 156.82142 | L28: 151.9801 | M28: 123.71241 | N28: 214.14255 | O28: 143.92073 | P28: 220.32397 | Q28: 310.21998 | R28: 184.65679 | S28: 210.24478 | T28: 256.07004 | U28: 157.76812 | V28: 203.15255
D29: Премиум сегмент | G29: руб./кг | K29: 357.15683 | L29: 253.52639 | M29: 275.29483 | N29: 252.21148 | O29: 353.6967 | P29: 255.5361 | Q29: 309.02673 | R29: 279.87634 | S29: 208.11919 | T29: 326.25212 | U29: 334.17688 | V29: 318.56159
C31: Офлайн продажи
D32: Эконом сегмент | G32: руб./кг | K32: 152.22934 | L32: 192.95474 | M32: 153.77688 | N32: 196.44314 | O32: 296.33762 | P32: 266.12095 | Q32: 241.60356 | R32: 187.19867 | S32: 108.0896 | T32: 149.23104 | U32: 308.67102 | V32: 217.70173
D33: Премиум сегмент | G33: руб./кг | K33: 334.64215 | L33: 453.72332 | M33: 276.7244 | N33: 424.20757 | O33: 678.93128 | P33: 479.74478 | Q33: 386.32654 | R33: 493.24091 | S33: 449.48909 | T33: 422.02649 | U33: 572.98116 | V33: 563.24297
B35: Корма для кошек
C36: Онлайн продажи
D37: Эконом сегмент | G37: руб./кг | K37: 167.1141 | L37: 171.17396 | M37: 174.57979 | N37: 142.18712 | O37: 137.72079 | P37: 149.05061 | Q37: 162.8598 | R37: 173.86068 | S37: 158.9307 | T37: 149.54754 | U37: 136.75411 | V37: 166.76807
D38: Премиум сегмент | G38: руб./кг | K38: 353.00794 | L38: 336.68402 | M38: 346.33538 | N38: 346.38452 | O38: 340.74052 | P38: 349.50971 | Q38: 357.1767 | R38: 329.41838 | S38: 360.99303 | T38: 336.02545 | U38: 341.4822 | V38: 356.45511
C40: Офлайн продажи
D41: Эконом сегмент | G41: руб./кг | K41: 135.2753 | L41: 144.85025 | M41: 161.85607 | N41: 162.49087 | O41: 150.18898 | P41: 152.79492 | Q41: 151.22624 | R41: 143.67777 | S41: 155.28266 | T41: 142.32903 | U41: 156.4147 | V41: 152.53764
D42: Премиум сегмент | G42: руб./кг | K42: 346.96488 | L42: 345.64591 | M42: 355.93752 | N42: 364.18564 | O42: 370.95805 | P42: 349.31821 | Q42: 341.97747 | R42: 344.45946 | S42: 342.26039 | T42: 351.71009 | U42: 363.7693 | V42: 371.77124
B44: Выручка
B46: Корма для собак | G46: млн руб. | K46: =K47+K51 -> 240.06319 | L46: =L47+L51 -> 237.59707 | M46: =M47+M51 -> 196.35301 | N46: =N47+N51 -> 245.96172 | O46: =O47+O51 -> 330.48402 | P46: =P47+P51 -> 272.58484 | Q46: =Q47+Q51 -> 286.40819 | R46: =R47+R51 -> 259.56289 | ... V46: =V47+V51 -> 295.12955 | X46: =SUM(K46:V46) -> 3161.4483
C47: Онлайн продажи | G47: млн руб. | K47: =K48+K49 -> 145.99085 | L47: =L48+L49 -> 112.65406 | M47: =M48+M49 -> 113.15822 | N47: =N48+N49 -> 126.03906 | O47: =O48+O49 -> 142.05086 | P47: =P48+P49 -> 128.4458 | Q47: =Q48+Q49 -> 165.04729 | R47: =R48+R49 -> 128.10861 | ... V47: =V48+V49 -> 144.25655 | X47: =SUM(K47:V47) -> 1614.6389
D48: Эконом сегмент | G48: млн руб. | K48: =K6*K28/1000 -> 34.79997 | L48: =L6*L28/1000 -> 33.725642 | M48: =M6*M28/1000 -> 27.452807 | N48: =N6*N28/1000 -> 47.520004 | O48: =O6*O28/1000 -> 31.9372 | P48: =P6*P28/1000 -> 48.891712 | Q48: =Q6*Q28/1000 -> 68.84038 | R48: =R6*R28/1000 -> 40.97687 | ... V48: =V6*V28/1000 -> 45.081233 | X48: =SUM(K48:V48) -> 517.71498
D49: Премиум сегмент | G49: млн руб. | K49: =K7*K29/1000 -> 111.19088 | L49: =L7*L29/1000 -> 78.928413 | M49: =M7*M29/1000 -> 85.705416 | N49: =N7*N29/1000 -> 78.519054 | O49: =O7*O29/1000 -> 110.11366 | P49: =P7*P29/1000 -> 79.554083 | Q49: =Q7*Q29/1000 -> 96.206907 | R49: =R7*R29/1000 -> 87.131741 | ... V49: =V7*V29/1000 -> 99.17532 | X49: =SUM(K49:V49) -> 1096.9239
C51: Офлайн продажи | G51: млн руб. | K51: =K52+K53 -> 94.072342 | L51: =L52+L53 -> 124.94301 | M51: =M52+M53 -> 83.194789 | N51: =N52+N53 -> 119.92266 | O51: =O52+O53 -> 188.43316 | P51: =P52+P53 -> 144.13905 | Q51: =Q52+Q53 -> 121.3609 | R51: =R52+R53 -> 131.45428 | ... V51: =V52+V53 -> 150.87299 | X51: =SUM(K51:V51) -> 1546.8094
D52: Эконом сегмент | G52: млн руб. | K52: =K10*K32/1000 -> 29.490874 | L52: =L10*L32/1000 -> 37.380467 | M52: =M10*M32/1000 -> 29.790673 | N52: =N10*N32/1000 -> 38.056262 | O52: =O10*O32/1000 -> 57.40848 | P52: =P10*P32/1000 -> 51.554707 | Q52: =Q10*Q32/1000 -> 46.805037 | R52: =R10*R32/1000 -> 36.265362 | ... V52: =V10*V32/1000 -> 42.174617 | X52: =SUM(K52:V52) -> 478.57412
D53: Премиум сегмент | G53: млн руб. | K53: =K11*K33/1000 -> 64.581468 | L53: =L11*L33/1000 -> 87.562544 | M53: =M11*M33/1000 -> 53.404116 | N53: =N11*N33/1000 -> 81.866398 | O53: =O11*O33/1000 -> 131.02468 | P53: =P11*P33/1000 -> 92.584339 | Q53: =Q11*Q33/1000 -> 74.555865 | R53: =R11*R33/1000 -> 95.188913 | ... V53: =V11*V33/1000 -> 108.69838 | X53: =SUM(K53:V53) -> 1068.2353
B55: Корма для кошек | G55: млн руб. | K55: =K56+K60 -> 285.43423 | L55: =L56+L60 -> 298.55397 | M55: =M56+M60 -> 463.24392 | N55: =N56+N60 -> 432.33718 | O55: =O56+O60 -> 363.96496 | P55: =P56+P60 -> 293.99623 | Q55: =Q56+Q60 -> 322.13244 | R55: =R56+R60 -> 401.81994 | ... V55: =V56+V60 -> 257.4809 | X55: =SUM(K55:V55) -> 4286.5128
C56: Онлайн продажи | G56: млн руб. | K56: =K57+K58 -> 120.86363 | L56: =L57+L58 -> 136.1874 | M56: =M57+M58 -> 166.58651 | N56: =N57+N58 -> 144.20027 | O56: =O57+O58 -> 135.62009 | P56: =P57+P58 -> 113.21062 | Q56: =Q57+Q58 -> 138.31567 | R56: =R57+R58 -> 154.06021 | ... V56: =V57+V58 -> 105.32202 | X56: =SUM(K56:V56) -> 1672.4295
D57: Эконом сегмент | G57: млн руб. | K57: =K15*K37/1000 -> 27.491715 | L57: =L15*L37/1000 -> 40.840055 | M57: =M15*M37/1000 -> 56.4345 | N57: =N15*N37/1000 -> 27.873328 | O57: =O15*O37/1000 -> 47.508528 | P57: =P15*P37/1000 -> 30.507385 | Q57: =Q15*Q37/1000 -> 44.413771 | R57: =R15*R37/1000 -> 46.967485 | ... V57: =V15*V37/1000 -> 49.198604 | X57: =SUM(K57:V57) -> 503.75561
D58: Премиум сегмент | G58: млн руб. | K58: =K16*K38/1000 -> 93.371916 | L58: =L16*L38/1000 -> 95.347345 | M58: =M16*M38/1000 -> 110.15201 | N58: =N16*N38/1000 -> 116.32694 | O58: =O16*O38/1000 -> 88.111566 | P58: =P16*P38/1000 -> 82.703235 | Q58: =Q16*Q38/1000 -> 93.901897 | R58: =R16*R38/1000 -> 107.09272 | ... V58: =V16*V38/1000 -> 56.123418 | X58: =SUM(K58:V58) -> 1168.6739
C60: Офлайн продажи | G60: млн руб. | K60: =K61+K62 -> 164.5706 | L60: =L61+L62 -> 162.36657 | M60: =M61+M62 -> 296.65741 | N60: =N61+N62 -> 288.13691 | O60: =O61+O62 -> 228.34486 | P60: =P61+P62 -> 180.78561 | Q60: =Q61+Q62 -> 183.81677 | R60: =R61+R62 -> 247.75974 | ... V60: =V61+V62 -> 152.15887 | X60: =SUM(K60:V60) -> 2614.0833
D61: Эконом сегмент | G61: млн руб. | K61: =K19*K41/1000 -> 38.126506 | L61: =L19*L41/1000 -> 40.396953 | M61: =M19*M41/1000 -> 85.373781 | N61: =N19*N41/1000 -> 58.265673 | O61: =O19*O41/1000 -> 72.891197 | P61: =P19*P41/1000 -> 49.76414 | Q61: =Q19*Q41/1000 -> 67.667094 | R61: =R19*R41/1000 -> 71.395915 | ... V61: =V19*V41/1000 -> 63.894894 | X61: =SUM(K61:V61) -> 756.71771
D62: Премиум сегмент | G62: млн руб. | K62: =K20*K42/1000 -> 126.44409 | L62: =L20*L42/1000 -> 121.96962 | M62: =M20*M42/1000 -> 211.28363 | N62: =N20*N42/1000 -> 229.87123 | O62: =O20*O42/1000 -> 155.45367 | P62: =P20*P42/1000 -> 131.02147 | Q62: =Q20*Q42/1000 -> 116.14968 | R62: =R20*R42/1000 -> 176.36382 | ... V62: =V20*V42/1000 -> 88.26398 | X62: =SUM(K62:V62) -> 1857.3656
B64: Всего | G64: млн руб. | K64: =K46+K55 -> 525.49742 | L64: =L46+L55 -> 536.15104 | M64: =M46+M55 -> 659.59693 | N64: =N46+N55 -> 678.29889 | O64: =O46+O55 -> 694.44898 | P64: =P46+P55 -> 566.58107 | Q64: =Q46+Q55 -> 608.54063 | R64: =R46+R55 -> 661.38283 | ... V64: =V46+V55 -> 552.61044 | X64: =SUM(K64:V64) -> 7447.961

Sheet Sheet2
A1: 011 ИМ.ЭК - направление перемещения | B1: ИМ
A2: ДАТА2 | B2: (Multiple Items)
A3: Column1 | B3: 1
A5: Row Labels | B5: Sum of 46 Статистическая стоимость | C5: Sum of 38 Вес нетто, кг
A6: БЕЛЬГИЯ | B6: 31975558 | C6: 10445471
A7: ФРАНЦИЯ | B7: 972244.41 | C7: 256500.39
B8: 409165.53 | C8: 130705.82
A9: Grand Total | B9: 33356968 | C9: 10832678
A12: 011 ИМ.ЭК - направление перемещения | B12: ИМ
A13: ДАТА2 | B13: (Multiple Items)
A14: Column1 | B14: 1
A16: Row Labels | B16: Sum of 46 Статистическая стоимость | C16: Sum of 38 Вес нетто, кг
A17: БЕЛЬГИЯ | B17: 31975558 | C17: 10445471
A18: ФРАНЦИЯ | B18: 972244.41 | C18: 256500.39
B19: 409165.53 | C19: 130705.82
A20: Grand Total | B20: 33356968 | C20: 10832678

Sheet Декларации
BR1: корм
A2: STAT Учет в статистике 0/1 | B2: Дата | C2: ДАТА2 | D2: ND Номер декларации на товары | E2: 071 Таможня оформления ДТ | F2: 073 Порядковый № ДТ | G2: 011 ИМ.ЭК - направление перемещения | H2: 012 Основной таможенный режим | I2: 013 Дополнительный признак | J2: 020 ОГРН.ОГРНИП отправителя | K2: 021 ИНН отправителя | L2: 022 Наименование.ФИО отправителя | M2: 023 Адрес отправителя | N2: 024 ОКАТО отправителя | O2: 027 КПП отправителя | P2: 03 Листов ДТ | Q2: 04 Спецификаций ДТ | R2: 05 Товаров всего | S2: 06 Мест товара всего | T2: 080 ОГРН.ОГРНИП получателя | U2: 081 ИНН получателя | V2: 082 Наименование.ФИО получателя | W2: 083 Адрес получателя | X2: 084 ОКАТО получателя | Y2: 087 КПП получателя | Z2: 090 ОГРН.ОГРНИП контрактодержателя | AA2: 091 ИНН контрактодержателя | AB2: 092 Наименование.ФИО контрактодержателя | AC2: 093 Адрес контрактодержателя | AD2: 094 ОКАТО контрактодержателя | AE2: 097 КПП контрактодержателя | AF2: 11 Код торгующей страны | AG2: 11 Торгующая страна | AH2: 12 Общая таможенная стоимость | AI2: 140 ОГРН.ОГРНИП декларанта | AJ2: 141 ИНН контрактодержателя | AK2: 142 Наименование.ФИО декларанта | AL2: 143 Адрес контрактодержателя | AM2: 144 ОКАТО контрактодержателя | AN2: 147 КПП контрактодержателя | AO2: 15А Код страны отправления | AP2: 15 Страна отправления | AQ2: 16 Страна происхождения | AR2: 17А Код страны назначения | AS2: 17 Страна назначения | AT2: 18 Кол-во транспорта при отправлении | AU2: 19 Признак контейнерных перевозок 0ю1 | AV2: 202 Условие поставки | AW2: 2021 Пункт поставки товара | AX2: 21 Кол-во трансп на границе | AY2: 221 Валюта контракта | AZ2: 222 Общая фактурная стоимость | BA2: 2220 Общая фактурная стоимость, руб | BB2: 226 Статистическая стоимость суммарная | BC2: 23 Курс валюты | BD2: 24 Характер сделки | BE2: 25 Вид транспортного средства | BF2: 28 ОКПО банка.паспорт сделки | BG2: 29 Таможня на границе | BH2: 300 Тип информации | BI2: 301 № свидетельства СВХ.ТС | BJ2: 302 Вид документа.Вид ТС | BK2: 30POST Индекс места нахождения товара | BL2: 30SUBD Регион | BM2: 30CITY Населенный пункт | BN2: 30STREET Адрес местонахождения товара | BO2: 3012 Таможня в зоне которой склад | BP2: 3 Порядковый № листа ДТ | BQ2: 31_1 Описание и характеристика товара | BR2: Column1 | BS2: 31_11 Товарный знак | BT2: 31_12 Наименование фирмы изготовителя | BU2: 31_2 Кол-во мест товара | BV2: 31_3 Кол-во контейнеров | BW2: 31_7 Кол-во товара в доп ед. измерения | BX2: 31_71 Дополнительная единица | BY2: 31_8 Кол-во товара в доп единице | BZ2: 31_81 Дополнительная единица | CA2: 32 Номер товара по ДТ | CB2: 33 Код товара по ТН ВЭД РФ | CC2: 331 Признак нетарифного регулирования | CD2: 332 Признак объекта интеллект собственности | CE2: 34 Код страны происхождения | CF2: 35 Вес брутто, кг | CG2: 36 Преференции | CH2: 37 Процедура | CI2: 38 Вес нетто, кг | CJ2: 39 Квота | CK2: 391 Код валюты квоты | CL2: 392 Единица измерения квоты | CM2: 42 Фактурная стоимость | CN2: 420 Фактурная стоимость, руб | CO2: 43 Признак корректировки таможенной стоимости (КТС) | CP2: 431 Метод определения таможенной стоимости | CQ2: 45 Таможенная стоимость | CR2: 46 Статистическая стоимость | CS2: D0 Код завршения таможенного оформления | CT2: Стат сумма, долл | CU2: USD/KG Статистическая стоимость, USD/Dtc НЕТТО, кг | CV2: 541 Свидетельство таможенного брокера | CW2: 5411 Договор брокера с декларантом | CX2: 5441 ФИО заполнившего ДТ | CY2: ЛНП выпускающего инспектора | CZ2: ND_DEL Признак удаления декларации
A3: 1 | B3: 45117 | C3: =IF(YEAR(Таблица1[[#This Row],[Дата]])=2023,MONTH(Таблица1[[#This Row],[Дата]]),0) -> 7 | D3: 10805010/261222/3028298 | E3: 10805010 | F3: 3028298 | G3: ИМ | H3: 40 | L3: ITALTHERM S.P.A. | M3: 29010, , PONTENURE (PC), VIA SALVO D'ACQUISTO SNC, | P3: 1 | Q3: 0 | R3: 1 | S3: 62 | T3: 1212600005826 | U3: 2632117991 | V3: ООО ТЁПЛЫЙ РИМ | W3: 357502, СТАВРОПОЛЬСКИЙ КРАЙ, Г. ПЯТИГОРСК, Ш. ЧЕРКЕССКОЕ, Д. 56,ПОМЕЩ. 8 | X3: 07000 | Y3: 263201001 | Z3: 1212600005826 | AA3: 2632117991 | AB3: ООО ТЁПЛЫЙ РИМ | AC3: 357502, СТАВРОПОЛЬСКИЙ КРАЙ, Г. ПЯТИГОРСК, Ш. ЧЕРКЕССКОЕ, Д. 56,ПОМЕЩ. 8 | AD3: 07000 | AE3: 263201001 | AF3: IT | AG3: ИТАЛИЯ | AH3: 15361774 | AI3: 1212600005826 | AJ3: 2632117991 | AK3: ООО ТЁПЛЫЙ РИМ | AL3: 357502, СТАВРОПОЛЬСКИЙ КРАЙ, Г. ПЯТИГОРСК, Ш. ЧЕРКЕССКОЕ, Д. 56,ПОМЕЩ. 8 | AM3: 07000 | AN3: 263201001 | AO3: IT | AP3: ИТАЛИЯ | AQ3: ИТАЛИЯ | AR3: RU | AS3: РОССИЯ | AT3: 2 | AU3: 0 | AV3: FCA | AW3: PONTENURE (PIACENZA) | AX3: 1 | AY3: EUR | AZ3: 205407 | BA3: 15003071 | BB3: 223684.75 | BC3: 73.0407 | BD3: 010 | BE3: 30 | BF3: 21090222/1000/0081/2/1 | BG3: - | BH3: 99 | BL3: БРЯНСКАЯ ОБЛАСТЬ, Р-Н БРЯНСКИЙ | BM3: П. СВЕНЬ | BN3: УЛ. СОБОРНАЯ | BO3: 10102032 ОТО и ТК №2 т/п Брянский | BP3: 1 | BQ3: КОТЛЫ ОТОПИТЕЛЬНЫЕ ГАЗОВЫЕ (ВОДОГРЕЙНЫЕ) СТАЛЬНЫЕ. ПРЕДНАЗНАЧЕНЫ ДЛЯ ОТОПЛЕНИЯ ЖИЛЫХ ДОМОВ И ЗДАНИЙ КОММУНАЛЬНО-БЫТОВОГО НАЗНАЧЕНИЯ, ОБОРУДОВАННЫХ СИСТЕМАМИ ОТОПЛЕНИЯ НЕПРЕРЫВНОГО ДЕЙСТВИЯ С ЕСТЕСТВЕННОЙ ИЛИ ПРИНУДИТЕЛЬНОЙ ЦИРКУЛЯЦИЕЙ ТЕПЛОНОСИТЕЛЯ, | BR3: =ISNUMBER(SEARCH($BR$1,Таблица1[[#This Row],[31_1 Описание и характеристика товара]]))*1 -> 0 | BT3: ITALTHERM S.P.A. | BU3: 62 | BV3: 0 | BW3: 383 | BX3: ШТ | BY3: 0 | CA3: 1 | CB3: 8403109000 | CE3: IT | CF3: 15554.5 | CG3: ОООО-ОО | CH3: 4000000 | CI3: 13783.972 | CJ3: 0 | CM3: 205407 | CN3: 15003071 | CO3: 0 | CP3: 1 | CQ3: 15361774 | CR3: 223684.75 | CS3: 10 | CT3: 16.2279 | CU3: 1069 | CV3: 1069-21-54-1264 | CX3: ЖУРАВКОВ СЕРГЕЙ ИВАНОВИЧ | CY3: 1
A4: 1 | B4: 45200 | C4: =IF(YEAR(Таблица1[[#This Row],[Дата]])=2023,MONTH(Таблица1[[#This Row],[Дата]]),0) -> 10 | D4: 10720010/251222/3095701 | E4: 10720010 | F4: 3095701 | G4: ИМ | H4: 40 | L4: INNER MONGOLIA THE ERA OF BINHANG SUPPLY CHAIN MANAGEMENT CO, LTD | M4: , INNER MONGOLIA, MANZHOULI CITY, BICAO YUNTIAN 20,STREET, HUMAO DISTRICT, NO. 7 | P4: 1 | Q4: 0 | R4: 1 | S4: 2 | T4: 1227500001860 | U4: 7500002418 | V4: ООО ФРЕГАТ | W4: 672000, ЗАБАЙКАЛЬСКИЙ КРАЙ, Г.ЧИТА, УЛ. БАБУШКИНА, Д.42, КОРП. А, ОФИС 209 | X4: 76000 | Y4: 750001001 | Z4: 1227500001860 | AA4: 7500002418 | AB4: ООО ФРЕГАТ | AC4: 672000, ЗАБАЙКАЛЬСКИЙ КРАЙ, Г.ЧИТА, УЛ. БАБУШКИНА, Д.42, КОРП. А, ОФИС 209 | AD4: 76000 | AE4: 750001001 | AF4: CN | AG4: КИТАЙ | AH4: 27470.4 | AI4: 1227500001860 | AJ4: 7500002418 | AK4: ООО ФРЕГАТ | AL4: 672000, ЗАБАЙКАЛЬСКИЙ КРАЙ, Г.ЧИТА, УЛ. БАБУШКИНА, Д.42, КОРП. А, ОФИС 209 | AM4: 76000 | AN4: 750001001 | AO4: CN | AP4: КИТАЙ | AQ4: КИТАЙ | AR4: RU | AS4: РОССИЯ | AT4: 2 | AU4: 0 | AV4: DAP | AW4: ЗАБАЙКАЛЬСК | AX4: 1 | AY4: USD | AZ4: 400 | BA4: 27470 | BB4: 400 | BC4: 68.676 | BD4: 010 | BF4: 22050009/1481/1727/2/1 | BG4: - | BH4: 11 | BI4: 10719/291015/10027/8 | BL4: ЗАБАЙКАЛЬСКИЙ КРАЙ | BM4: ПГТ. ЗАБАЙКАЛЬСК | BN4: МКР.МАПП ЗАБАЙКАЛЬСК УЧАСТОК № 6 | BO4: 10719030 т/п Забайкальский | BP4: 1 | BQ4: ТВЕРДОТОПЛИВНЫЙ ВОДОГРЕЙНЫЙ ОТОПИТЕЛЬНЫЙ КОТЕЛ ТОРГОВОЙ МАРКИ CHENG CHENG, МОДЕЛЬ СС-2000W-01, ИЗГОТОВИТЕЛЬ ANHUI CHENGCHENG MACHINERY CO., LTD.В ЧАСТИЧНО РАЗОБРАННОМ ВИДЕ ДЛЯ УДОБСТВА ТРАНСПОРТИРОВКИ СОГЛАСНО УПАКОВОЧНОГО ЛИСТА:КАБЕЛЬ ПИТАНИЯ1 ШТ 1 | BR4: =ISNUMBER(SEARCH($BR$1,Таблица1[[#This Row],[31_1 Описание и характеристика товара]]))*1 -> 0 | BT4: ANHUI CHENGCHENG MACHINERY CO., LTD | BU4: 2 | BV4: 0 | BW4: 1 | BX4: ШТ | BY4: 0 | CA4: 1 | CB4: 8403109000 | CE4: CN | CF4: 232 | CG4: ОООО-ОО | CH4: 4000000 | CI4: 175 | CJ4: 0 | CM4: 400 | CN4: 27470 | CO4: 2 | CP4: 1 | CQ4: 27470.4 | CR4: 400 | CS4: 12 | CT4: 2.2857 | CX4: ЕКИМОВ ОЛЕГ ВАЛЕРЬЕВИЧ | CY4: 79
A5: 1 | B5: 44990 | C5: =IF(YEAR(Таблица1[[#This Row],[Дата]])=2023,MONTH(Таблица1[[#This Row],[Дата]]),0) -> 3 | D5: 10702070/211222/3458521 | E5: 10702070 | F5: 3458521 | G5: ИМ | H5: 40 | L5: HYDROSTA CO.,LTD | M5: , BUSAN, HAEUNDAE-GU,U-DONG, ACE HIGHTECH 1470,21, NO.1813, | P5: 6 | Q5: 0 | R5: 14 | S5: 215 | T5: 1042502960500 | U5: 2536144625 | V5: ООО ИМПОРТ-СЕРВИС | W5: 690001, ПРИМОРСКИЙ КРАЙ, ВЛАДИВОСТОК, УЛ.АБРЕКСКАЯ, ДОМ 8 В ОФ.6, | X5: 05000 | Y5: 253601001 | Z5: 1042502960500 | AA5: 2536144625 | AB5: ООО ИМПОРТ-СЕРВИС | AC5: 690001, ПРИМОРСКИЙ КРАЙ, ВЛАДИВОСТОК, УЛ.АБРЕКСКАЯ, ДОМ 8 В ОФ.6, | AD5: 05000 | AE5: 253601001 | AF5: KR | AG5: КОРЕЯ, РЕСПУБЛИКА | AH5: 4307880.3 | AI5: 1042502960500 | AJ5: 2536144625 | AK5: ООО ИМПОРТ-СЕРВИС | AL5: 690001, ПРИМОРСКИЙ КРАЙ, ВЛАДИВОСТОК, УЛ.АБРЕКСКАЯ, ДОМ 8 В ОФ.6, | AM5: 05000 | AN5: 253601001 | AO5: KR | AP5: КОРЕЯ, РЕСПУБЛИКА | AQ5: КОРЕЯ, РЕСПУБЛИКА | AR5: RU | AS5: РОССИЯ | AT5: 0 | AU5: 1 | AV5: CFR | AW5: ВЛАДИВОСТОК | AX5: 1 | AY5: USD | AZ5: 62429.7 | BA5: 4307880 | BB5: 62429.7 | BC5: 69.0037 | BD5: 010 | BE5: 10 | BF5: 15120005/2733/0000/2/1 | BG5: - | BH5: 99 | BJ5: 10702000/180322/00045/2 | BL5: ПРИМОРСКИЙ КРАЙ | BM5: Г. ВЛАДИВОСТОК | BN5: УЛ.СТРЕЛЬНИКОВА,9 ВМТП | BO5: 10702030 т/п Морской порт Владивосток | BP5: 2 | BQ5: КОТЛЫ МАРКИ OLYMPIA ВОДОГРЕЙНЫЕ:ДИЗЕЛЬНЫЕ,ГАЗОВЫЕ ДЛЯ ЦЕНТРАЛЬНОГО ОТОПЛЕНИЯ, С ГОРЕЛКАМИ БЛОЧНЫМИ НА ЖИДКОМ ТОПЛИВЕ И ГАЗОВЫМИ ГОРЕЛКАМИ. КОД ОКП 493112 OLYMPIA OIL BOILER/ДИЗЕЛЬНЫЕ КОТЛЫ ВОДОГЕЙНЫЕ OLB-250F-R(Q=25000KCAL/H)WITH OIL BURNER (T | BR5: =ISNUMBER(SEARCH($BR$1,Таблица1[[#This Row],[31_1 Описание и характеристика товара]]))*1 -> 0 | BT5: OLYMPIA INDUSTRIAL CO.,LTD | BU5: 23 | BV5: 1 | BW5: 16 | BX5: ШТ | BY5: 0 | CA5: 2 | CB5: 8403109000 | CE5: KR | CF5: 5290.7 | CG5: ОООО-ОО | CH5: 4000000 | CI5: 4697.3 | CJ5: 0 | CM5: 32981 | CN5: 2275811 | CO5: 0 | CP5: 1 | CQ5: 2275811 | CR5: 32981 | CS5: 10 | CT5: 7.0213 | CX5: СУЩИНСКАЯ ТАТЬЯНА ЭДУАРДОВНА | CY5: 621
A6: 1 | B6: 45041 | C6: =IF(YEAR(Таблица1[[#This Row],[Дата]])=2023,MONTH(Таблица1[[#This Row],[Дата]]),0) -> 4 | D6: 10702070/191222/3455568 | E6: 10702070 | F6: 3455568 | G6: ИМ | H6: 40 | L6: NINGBO FOURTH PARTY LOGISTICS CO.,LTD | M6: 315000, ., NINGBO, RM 1815 FIFTH AVENUE HUAHONG NO.719 ZHONGXING RD N, | P6: 1 | Q6: 0 | R6: 1 | S6: 200 | T6: 1213000003908 | U6: 3019030445 | V6: ООО САРМАТ + | W6: 414041, АСТРАХАНСКАЯ ОБЛ.,Г.О. ГОРОД АСТРАХАНЬ, Г АСТРАХАНЬ, УЛ ЕРЕВАНСКАЯ,Д. 3, | X6: 12000 | Y6: 301901001 | Z6: 1213000003908 | AA6: 3019030445 | AB6: ООО САРМАТ + | AC6: 414041, АСТРАХАНСКАЯ ОБЛ.,Г.О. ГОРОД АСТРАХАНЬ, Г АСТРАХАНЬ, УЛ ЕРЕВАНСКАЯ,Д. 3, | AD6: 12000 | AE6: 301901001 | AF6: CN | AG6: КИТАЙ | AH6: 3570761.5 | AI6: 1213000003908 | AJ6: 3019030445 | AK6: ООО САРМАТ + | AL6: 414041, АСТРАХАНСКАЯ ОБЛ.,Г.О. ГОРОД АСТРАХАНЬ, Г АСТРАХАНЬ, УЛ ЕРЕВАНСКАЯ,Д. 3, | AM6: 12000 | AN6: 301901001 | AO6: CN | AP6: КИТАЙ | AQ6: КИТАЙ | AR6: RU | AS6: РОССИЯ | AT6: 0 | AU6: 1 | AV6: FOB | AW6: NINGBO | AX6: 1 | AY6: CNY | AZ6: 364800 | BA6: 3465469 | BB6: 55268.27 | BC6: 92.4382 | BD6: 010 | BE6: 10 | BF6: 22050007/2272/0026/2/1 | BG6: - | BH6: 99 | BJ6: 10702000/180322/00045/2 | BL6: ПРИМОРСКИЙ КРАЙ | BM6: ВЛАДИВОСТОК Г | BN6: СТРЕЛЬНИКОВА УЛ, ДОМ № 9 | BO6: 10702030 т/п Морской порт Владивосток | BP6: 1 | BQ6: КОТЛЫ БЫТОВЫЕ ЦЕНТРАЛЬНОГО ОТОПЛЕНИЯ, ВОДОГРЕЙНЫЕ, ГАЗОВЫЕ В СТАЛЬНОМ КОРПУСЕ; ДВУХКОНТУРНЫЕ НАСТЕННЫЕ ГАЗОВЫЕ КОТЛЫ. | BR6: =ISNUMBER(SEARCH($BR$1,Таблица1[[#This Row],[31_1 Описание и характеристика товара]]))*1 -> 0 | BT6: JIANGSU SPRING THERMAL TECHNOLOGY CO., LTD | BU6: 200 | BV6: 1 | BW6: 200 | BX6: ШТ | BY6: 0 | CA6: 1 | CB6: 8403109000 | CE6: CN | CF6: 7785 | CG6: ОООО-ОО | CH6: 4000000 | CI6: 7325 | CJ6: 0 | CM6: 364800 | CN6: 3372146 | CO6: 0 | CP6: 1 | CQ6: 3570761.5 | CR6: 55268.27 | CS6: 10 | CT6: 7.5452 | CU6: 1027 | CV6: 1027/22/1002-01 | CX6: ДОРОФЕЕВА ЕЛЕНА АЛЕКСАНДРОВНА | CY6: 215
A7: 0 | B7: 45180 | C7: =IF(YEAR(Таблица1[[#This Row],[Дата]])=2023,MONTH(Таблица1[[#This Row],[Дата]]),0) -> 9 | D7: 10702070/191222/3454036 | E7: 10702070 | F7: 3454036 | G7: ИМ | H7: 78 | L7: HAINAN LITA IMPORT & EXPORT TRADE CO., LTD | M7: , , DISTRICT HAIKOU CITY, SAN XIAN HUI FU, NO.9 CHANG BIN 4TH ROAD, XIU YING, | P7: 3 | Q7: 0 | R7: 7 | S7: 9 | T7: 1024900953043 | U7: 4909021566 | V7: СП ЗАО ОМСУКЧАНСКАЯ ГОРНО-ГЕОЛОГИЧЕСКАЯ КОМПАНИЯ | W7: 685030```, `````МАГАДАНСКАЯ ОБЛАСТЬ, Г. МАГАДАН, УЛ. ПРОЛЕТАРСКАЯ, Д. 84, КОРП. | X7: 44000 | Y7: 490901001 | Z7: 1024900953043 | AA7: 4909021566 | AB7: СП ЗАО ОМСУКЧАНСКАЯ ГОРНО-ГЕОЛОГИЧЕСКАЯ КОМПАНИЯ | AC7: 685030```, `````МАГАДАНСКАЯ ОБЛАСТЬ, Г. МАГАДАН, УЛ. ПРОЛЕТАРСКАЯ, Д. 84, КОРП. | AD7: 44000 | AE7: 490901001 | AF7: CN | AG7: КИТАЙ | AH7: 2159726.1 | AI7: 1024900953043 | AJ7: 4909021566 | AK7: СП ЗАО ОМСУКЧАНСКАЯ ГОРНО-ГЕОЛОГИЧЕСКАЯ КОМПАНИЯ | AL7: 685030```, `````МАГАДАНСКАЯ ОБЛАСТЬ, Г. МАГАДАН, УЛ. ПРОЛЕТАРСКАЯ, Д. 84, КОРП. | AM7: 44000 | AN7: 490901001 | AO7: CN | AP7: КИТАЙ | AQ7: КИТАЙ | AR7: RU | AS7: РОССИЯ | AT7: 1 | AU7: 1 | AV7: CIF | AW7: MAGADAN | AX7: 1 | AY7: CNY | AZ7: 233640 | BA7: 2219496 | BB7: 33428.26 | BC7: 92.4382 | BD7: 010 | BE7: 10 | BG7: - | BH7: 99 | BJ7: 10707000/251122/00089/2 | BL7: МАГАДАНСКАЯ ОБЛ. | BM7: Г. МАГАДАН | BN7: ММТП | BO7: 10707160 т/п Морской порт Магадан | BP7: 3 | BQ7: БОЙЛЕР ЕМКОСТНОЙ НЕЭЛЕКТРИЧЕСКИЙ ВЕРТИКАЛЬНОГО ИСПОЛНЕНИЯ, ПРЕДНАЗНАЧЕН ДЛЯ ОТОПЛЕНИЯ КОМНАТ ФАБРИКИ, ОБЪЕМОМ 0.75 М3, РАСХОД ТОПЛИВА 10 КГ/Ч, ВЫХОДНАЯ МОЩНОСТЬ 120 КВТ, ПЛОЩАДЬ ОБОГРЕВА 1000 КВ.М., НАПРЯЖЕНИЕ 120 ВОЛЬТ, ОСНАЩЕН КОМПЛЕКТОМ | BR7: =ISNUMBER(SEARCH($BR$1,Таблица1[[#This Row],[31_1 Описание и характеристика товара]]))*1 -> 0 | BT7: DONGGUAN HENGSEN THERMAL ENERGY TECHNOLOGY CO.,LTD | BU7: 2 | BV7: 1 | BW7: 1 | BX7: ШТ | BY7: 0 | CA7: 7 | CB7: 8403109000 | CE7: CN | CF7: 338 | CG7: ООПП-ПП | CH7: 7800171 | CI7: 303 | CJ7: 0 | CM7: 40085 | CN7: 370539 | CO7: 0 | CP7: 1 | CQ7: 370538.52 | CR7: 5735.2 | CS7: 10 | CT7: 18.9281 | CU7: 860 | CV7: 0714/00-15-01 | CX7: БЕЛЬМАС ЭДУАРД ВЛАДИМИРОВИЧ | CY7: 483
A8: 1 | B8: 44943 | C8: =IF(YEAR(Таблица1[[#This Row],[Дата]])=2023,MONTH(Таблица1[[#This Row],[Дата]]),0) -> 1 | D8: 10702070/151222/3450013 | E8: 10702070 | F8: 3450013 | G8: ИМ | H8: 40 | L8: HEATMASTER (NANTONG) BOILER CO., LTD | M8: , JIANGSU PROVINCE, NANTONG CITY, XINGHE ROAD, GANGZHA ECONOMIC DEVELOPMENT ZONE | P8: 1 | Q8: 0 | R8: 1 | S8: 13 | T8: 1095190011333 | U8: 5190909506 | V8: АО НОРД ВЕСТ ФЛОТ КОМПАНИ | W8: 183039, МУРМАНСКАЯ ОБЛАСТЬ, МУРМАНСК, РОГОЗЕРСКАЯ, 15 | X8: 47000 | Y8: 519001001 | Z8: 1095190011333 | AA8: 5190909506 | AB8: АО НОРД ВЕСТ ФЛОТ КОМПАНИ | AC8: 183039, МУРМАНСКАЯ ОБЛАСТЬ, МУРМАНСК, РОГОЗЕРСКАЯ, 15 | AD8: 47000 | AE8: 519001001 | AF8: CN | AG8: КИТАЙ | AH8: 8357933.8 | AI8: 1095190011333 | AJ8: 5190909506 | AK8: АО НОРД ВЕСТ ФЛОТ КОМПАНИ | AL8: 183039, МУРМАНСКАЯ ОБЛАСТЬ, МУРМАНСК, РОГОЗЕРСКАЯ, 15 | AM8: 47000 | AN8: 519001001 | AO8: CN | AP8: КИТАЙ | AQ8: КИТАЙ | AR8: RU | AS8: РОССИЯ | AT8: 0 | AU8: 1 | AV8: FCA | AW8: NANTONG CITY | AX8: 1 | AY8: EUR | AZ8: 120850 | BA8: 8151067 | BB8: 131913.92 | BC8: 67.4478 | BD8: 010 | BE8: 10 | BF8: 21110073/1326/0002/2/1 | BG8: - | BH8: 99 | BJ8: 10702000/180322/00045/2 | BL8: ПРИМОРСКИЙ КРАЙ | BM8: Г.ВЛАДИВОСТОК | BN8: УЛ.СТРЕЛЬНИКОВА | BO8: 10702030 т/п Морской порт Владивосток | BP8: 1 | BQ8: СИСТЕМА ПОДОГРЕВА ВОДЫ НА СУДНЕ, ПОСТАВЛЯЕТСЯ В РАЗОБРАННОМ ВИДЕ ДЛЯ УДОБСТВА ТРАНСПОРТИРОВКИ. ВВОЗИТСЯ ДЛЯ СОБСТВЕННОГО ИСПОЛЬЗОВАНИЯ; ПРОДАЖЕ НЕ ПОДЛЕЖИТ | BR8: =ISNUMBER(SEARCH($BR$1,Таблица1[[#This Row],[31_1 Описание и характеристика товара]]))*1 -> 0 | BT8: HEATMASTER (NANTONG) BOILER CO., LTD | BU8: 13 | BV8: 1 | BW8: 1 | BX8: ШТ | BY8: 0 | CA8: 1 | CB8: 8403109000 | CC8: С | CE8: CN | CF8: 3760 | CG8: ОООО-ОО | CH8: 4000000 | CI8: 3500 | CJ8: 0 | CM8: 120850 | CN8: 8151067 | CO8: 0 | CP8: 1 | CQ8: 8357933.8 | CR8: 131913.92 | CS8: 10 | CT8: 37.6897 | CU8: 1067 | CV8: 202012/32 | CX8: РОССОЛОВ АРТЕМ НИКОЛАЕВИЧ | CY8: 0
A9: 1 | B9: 44772 | C9: =IF(YEAR(Таблица1[[#This Row],[Дата]])=2023,MONTH(Таблица1[[#This Row],[Дата]]),0) -> 0 | D9: 10511010/281222/3174551 | E9: 10511010 | F9: 3174551 | G9: ИМ | H9: 40 | L9: UNICAL A.G. S.P.A. | M9: 460033, , CASTEL D'ARIO (MN), VIA ROMA 123, | P9: 1 | Q9: 0 | R9: 1 | S9: 9 | T9: 1069674029050 | U9: 6674177799 | V9: ООО КОТЕЛЬНЫЕ СИСТЕМЫ УРАЛА | W9: 620076, СВЕРДЛОВСКАЯ ОБЛ, Г ЕКАТЕРИНБУРГ, ГОНЧАРНЫЙ ПЕР, ДОМ 4 | X9: 65000 | Y9: 667901001 | Z9: 1069674029050 | AA9: 6674177799 | AB9: ООО КОТЕЛЬНЫЕ СИСТЕМЫ УРАЛА | AC9: 620076, СВЕРДЛОВСКАЯ ОБЛ, Г ЕКАТЕРИНБУРГ, ГОНЧАРНЫЙ ПЕР, ДОМ 4 | AD9: 65000 | AE9: 667901001 | AF9: IT | AG9: ИТАЛИЯ | AH9: 2536832.6 | AI9: 1069674029050 | AJ9: 6674177799 | AK9: ООО КОТЕЛЬНЫЕ СИСТЕМЫ УРАЛА | AL9: 620076, СВЕРДЛОВСКАЯ ОБЛ, Г ЕКАТЕРИНБУРГ, ГОНЧАРНЫЙ ПЕР, ДОМ 4 | AM9: 65000 | AN9: 667901001 | AO9: IT | AP9: ИТАЛИЯ | AQ9: ИТАЛИЯ | AR9: RU | AS9: РОССИЯ | AT9: 2 | AU9: 0 | AV9: FCA | AW9: BORGOCАRBONARA (MN) | AX9: 1 | AY9: EUR | AZ9: 29757 | BA9: 2207461 | BB9: 36274.36 | BC9: 74.1829 | BD9: 010 | BF9: 21110008/1481/0373/2/1 | BG9: - | BH9: 11 | BI9: 10113/160611/10039/6 | BL9: СМОЛЕНСКАЯ ОБЛАСТЬ | BM9: КРАСНИНСКИЙ РАЙОН | BN9: В 250 М ЗАПАДНЕЕ Д.БУДА И СЕВЕРНЕЕ (В 650 М) ЖЕЛЕ | BO9: 10113090 т/п Краснинский | BP9: 1 | BQ9: КОТЛЫ СТАЛЬНЫЕ,ВОДОГРЕЙНЫЕ,ДЫМОГАРНЫЕ,ДВУХХОДОВЫЕ ПРОМЫШЛЕННЫЕ: АРТ.102258RU/UNICAL ELLPREX 970-7ШТ. ПРЕДНАЗНАЧЕНЫ ДЛЯ РАБОТЫ НА ГАЗООБРАЗНОМ И ЖИДКОМ ТОПЛИВЕ И ПРИМЕНЕНИЯ В СИСТЕМАХ ЦЕНТРАЛЬНОГО ОТОПЛЕНИЯ С ТЕМПЕРАТУРОЙ ДО 100С | BR9: =ISNUMBER(SEARCH($BR$1,Таблица1[[#This Row],[31_1 Описание и характеристика товара]]))*1 -> 0 | BT9: UNICAL AG S.P.A. | BU9: 9 | BV9: 0 | BW9: 7 | BX9: ШТ | BY9: 0 | CA9: 1 | CB9: 8403109000 | CE9: IT | CF9: 11797 | CG9: ОООО-ОО | CH9: 4000000 | CI9: 11767 | CJ9: 0 | CM9: 29757 | CN9: 2207461 | CO9: 0 | CP9: 1 | CQ9: 2536832.6 | CR9: 36274.36 | CS9: 10 | CT9: 3.0827 | CX9: ФАЙЗУЛИНА ДАРЬЯ ВИТАЛЬЕВНА | CY9: 0
A10: 1 | B10: 45243 | C10: =IF(YEAR(Таблица1[[#This Row],[Дата]])=2023,MONTH(Таблица1[[#This Row],[Дата]]),0) -> 11 | D10: 10418010/221222/3235079 | E10: 10418010 | F10: 3235079 | G10: ИМ | H10: 40 | L10: VARMECOM INDUSTRY INC. | M10: , ESKISEHIR, ODUNPAZAR, 75TH YEAR OSB DISTRICT, STREET 104, 12 | P10: 1 | Q10: 0 | R10: 1 | S10: 595 | T10: 1060278101982 | U10: 0278122273 | V10: ООО ГАЗСТРОЙИНВЕСТ | W10: 450006, РЕСПУБЛИКА БАШКОРТОСТАН, УФА, УЛ. 50-ЛЕТИЯ ОКТЯБРЯ, 15 | X10: 80000 | Y10: 027801001 | Z10: 1060278101982 | AA10: 0278122273 | AB10: ООО ГАЗСТРОЙИНВЕСТ | AC10: 450006, РЕСПУБЛИКА БАШКОРТОСТАН, УФА, УЛ. 50-ЛЕТИЯ ОКТЯБРЯ, 15 | AD10: 80000 | AE10: 027801001 | AF10: TR | AG10: ТУРЦИЯ | AH10: 12796878 | AI10: 1060278101982 | AJ10: 0278122273 | AK10: ООО ГАЗСТРОЙИНВЕСТ | AL10: 450006, РЕСПУБЛИКА БАШКОРТОСТАН, УФА, УЛ. 50-ЛЕТИЯ ОКТЯБРЯ, 15 | AM10: 80000 | AN10: 027801001 | AO10: TR | AP10: ТУРЦИЯ | AQ10: ТУРЦИЯ | AR10: RU | AS10: РОССИЯ | AT10: 2 | AU10: 0 | AV10: EXW | AW10: ESKISEHIR | AX10: 1 | AY10: EUR | AZ10: 165890.25 | BA10: 12456931 | BB10: 181450.12 | BC10: 75.0914 | BD10: 010 | BF10: 22110036/3292/0006/2/1 | BG10: - | BH10: 11 | BI10: 10413/070318/10059/1 | BL10: САРАТОВСКАЯ ОБЛ. | BM10: Г. САРАТОВ | BN10: УЛ. ТАМОЖЕННЫЙ ПР-Д, Д. 6 | BO10: 10413070 т/п Саратовский | BP10: 1 | BQ10: ГАЗОВЫЙ НАСТЕННЫЙ КОТЕЛ КОНВЕКЦИОННОГО ТИПА FEDERICA BUGATTI VARME ПРЕДНАЗНАЧЕН ДЛЯ ОТОПЛЕНИЯ И ПРИГОТОВЛЕНИЯ ГОРЯЧЕЙ ВОДЫ В КОТТЕДЖАХ, В КВАРТИРАХ МНОГОЭТАЖНЫХ ДОМОВ С КОЛЛЕКТИВНЫМИ ДЫМОХОДАМИ И ДРУГИХ ЗДАНИЯХ ПЛОЩАДЬЮ ДО 360 М2. | BR10: =ISNUMBER(SEARCH($BR$1,Таблица1[[#This Row],[31_1 Описание и характеристика товара]]))*1 -> 0 | BT10: VARMECOM INDUSTRY | BU10: 595 | BV10: 0 | BW10: 595 | BX10: ШТ | BY10: 0 | CA10: 1 | CB10: 8403109000 | CE10: TR | CF10: 19367 | CG10: ОООО-ОО | CH10: 4000000 | CI10: 17498 | CJ10: 0 | CM10: 165890.25 | CN10: 12456931 | CO10: 0 | CP10: 1 | CQ10: 12796878 | CR10: 181450.12 | CS10: 10 | CT10: 10.3698 | CU10: 696 | CV10: ТБ696/18/06/15/3 | CX10: ДАВИТАШВИЛИ ДЖАМАЛ РОЛАНДОВИЧ | CY10: 113
A11: 1 | B11: 45136 | C11: =IF(YEAR(Таблица1[[#This Row],[Дата]])=2023,MONTH(Таблица1[[#This Row],[Дата]]),0) -> 7 | D11: 10323010/161222/3178880 | E11: 10323010 | F11: 3178880 | G11: ИМ | H11: 40 | L11: S PLUSZ K TECHNIK KFT | M11: 4400, HUNGARY, NYIREGYHAZA, VAY ADAM KRT.4-6. 2/208, | P11: 5 | Q11: 0 | R11: 11 | S11: 383 | T11: 1026102578017 | U11: 6154001478 | V11: ООО ЛЕМАКС | W11: 347913, ОБЛАСТЬ РОСТОВСКАЯ, ТАГАНРОГ, УЛИЦА НИКОЛАЕВСКОЕ ШОССЕ, Д0М.10, КОРПУС В | X11: 60000 | Y11: 615401001 | Z11: 1026102578017 | AA11: 6154001478 | AB11: ООО ЛЕМАКС | AC11: 347913, ОБЛАСТЬ РОСТОВСКАЯ, ТАГАНРОГ, УЛИЦА НИКОЛАЕВСКОЕ ШОССЕ, Д0М.10, КОРПУС В | AD11: 60000 | AE11: 615401001 | AF11: HU | AG11: ВЕНГРИЯ | AH11: 22359773 | AI11: 1026102578017 | AJ11: 6154001478 | AK11: ООО ЛЕМАКС | AL11: 347913, ОБЛАСТЬ РОСТОВСКАЯ, ТАГАНРОГ, УЛИЦА НИКОЛАЕВСКОЕ ШОССЕ, Д0М.10, КОРПУС В | AM11: 60000 | AN11: 615401001 | AO11: HU | AP11: ВЕНГРИЯ | AQ11: ВЕНГРИЯ | AR11: RU | AS11: РОССИЯ | AT11: 2 | AU11: 0 | AV11: EXW | AW11: ZSURK | AX11: 1 | AY11: EUR | AZ11: 321360.06 | BA11: 21996132 | BB11: 347733.27 | BC11: 68.447 | BD11: 010 | BE11: 31 | BF11: 19060035/1481/1898/2/1 | BG11: - | BH11: 99 | BJ11: 1237 | BK11: 197761 | BL11: САНКТ-ПЕТЕРБУРГ | BM11: КРОНШТАДТ | BN11: КРОНШТАДТСКОЕ Ш., Д.33, ЛИТЕР А | BO11: 10210040 т/п Котлинский | BP11: 1 | BQ11: КОТЛЫ ОТОПИТЕЛЬНЫЕ ЭЛЕКТРИЧЕСКИЕ , ПРЕДНАЗНАЧЕНЫ ДЛЯ ОТОПЛЕНИЯ ПОМЕЩЕНИЙ ТОРГОВОЙ МАРКИ LEMАХ | BR11: =ISNUMBER(SEARCH($BR$1,Таблица1[[#This Row],[31_1 Описание и характеристика товара]]))*1 -> 0 | BT11: S PLUSZ K TECHNIK KFT. | BU11: 368 | BV11: 0 | BW11: 420 | BX11: ШТ | BY11: 0 | CA11: 1 | CB11: 8403109000 | CC11: С | CE11: HU | CF11: 9487.075 | CG11: ОООО-ОО | CH11: 4000000 | CI11: 8750.825 | CJ11: 0 | CM11: 133189.06 | CN11: 9116392 | CO11: 0 | CP11: 1 | CQ11: 9389407.4 | CR11: 146021.59 | CS11: 10 | CT11: 16.6866 | CU11: 1117 | CV11: 0149/01-173 | CX11: АНТРОПОВА ОЛЬГА ВЕНИАМИНОВНА | CY11: 92
A12: 1 | B12: 44995 | C12: =IF(YEAR(Таблица1[[#This Row],[Дата]])=2023,MONTH(Таблица1[[#This Row],[Дата]]),0) -> 3 | D12: 10317120/301222/3176625 | E12: 10317120 | F12: 3176625 | G12: ИМ | H12: 40 | L12: VARMECOM INDUSTRY(VARMECOM ENDUSTRIYEL SANAYI VE TICARET ANONIM SIRKETI) | M12: 49308, ODUNPAZARI, ESKISEHIR, KOBI ORGANIZE SANAYI BOLGESI 75 YIL OSB MAH. 104 C | P12: 2 | Q12: 0 | R12: 4 | S12: 496 | T12: 1131650002494 | U12: 1650258175 | V12: ООО ТД ГИГАЗ | W12: 450000, РЕСПУБЛИКА БАШКОРТОСТАН, Г. УФА, УЛ. 50-ЛЕТИЯ ОКТЯБРЯ, 15 | X12: 80000 | Y12: 027801001 | Z12: 1131650002494 | AA12: 1650258175 | AB12: ООО ТД ГИГАЗ | AC12: 450000, РЕСПУБЛИКА БАШКОРТОСТАН, Г. УФА, УЛ. 50-ЛЕТИЯ ОКТЯБРЯ, 15 | AD12: 80000 | AE12: 027801001 | AF12: TR | AG12: ТУРЦИЯ | AH12: 11038148 | AI12: 1131650002494 | AJ12: 1650258175 | AK12: ООО ТД ГИГАЗ | AL12: 450000, РЕСПУБЛИКА БАШКОРТОСТАН, Г. УФА, УЛ. 50-ЛЕТИЯ ОКТЯБРЯ, 15 | AM12: 80000 | AN12: 027801001 | AO12: TR | AP12: ТУРЦИЯ | AQ12: ТУРЦИЯ | AR12: RU | AS12: РОССИЯ | AT12: 0 | AU12: 1 | AV12: EXW | AW12: ESKISEHIR | AX12: 1 | AY12: EUR | AZ12: 139586.16 | BA12: 10619227 | BB12: 153354.9 | BC12: 76.0765 | BD12: 010 | BF12: 22080001/0067/0000/2/1 | BG12: - | BH12: 99 | BJ12: 10317000/031221/00006/2 | BL12: КРАСНОДАРСКИЙ КРАЙ | BM12: НОВОРОССИЙСК | BN12: УЛ. СУХУМСКОЕ ШОССЕ, ПЗТК ООО НУТЭП | BO12: 10317110 т/п Новороссийский юго-восточный | BP12: 1 | BQ12: КОТЕЛЬНАЯ АВТОМАТИЗИРОВАННАЯ ИЗ МЕТАЛЛА(НЕ ИЗ ЧУГУНА), НОМИНАЛЬНОЙ ТЕПЛОПРОИЗВОДИТЕЛЬНОСТЬЮ ДО 33 КВТ. ПРЕДНАЗНАЧЕНА ДЛЯ ИСПОЛЬЗОВАНИЯ В КАЧЕСТВЕ ИСТОЧНИКА ТЕПЛОНОСИТЕЛЯ И ГОРЯЧЕЙ ВОДЫ ДЛЯ ЗДАНИЙ И СООРУЖЕНИЙ РАЗЛИЧНОГО НАЗНАЧЕНИЯ. КОТЕЛЬНАЯ | BR12: =ISNUMBER(SEARCH($BR$1,Таблица1[[#This Row],[31_1 Описание и характеристика товара]]))*1 -> 0 | BT12: VARMECOM INDUSTRY | BU12: 486 | BV12: 1 | BW12: 486 | BX12: ШТ | BY12: 0 | CA12: 1 | CB12: 8403109000 | CE12: TR | CF12: 15217.3 | CG12: ОООО-ОО | CH12: 4000000 | CI12: 14354.1 | CJ12: 0 | CM12: 133319 | CN12: 10142443 | CO12: 0 | CP12: 1 | CQ12: 10555046 | CR12: 146643.08 | CS12: 10 | CT12: 10.2161 | CU12: 727 | CV12: 0491/01-15/009 | CX12: ЗАРИПОВ ЭДУАРД КАМИЛЬЕВИЧ | CY12: 0
A13: 1 | B13: 44940 | C13: =IF(YEAR(Таблица1[[#This Row],[Дата]])=2023,MONTH(Таблица1[[#This Row],[Дата]]),0) -> 1 | D13: 10317120/301222/3176508 | E13: 10317120 | F13: 3176508 | G13: ИМ | H13: 40 | L13: VARMECOM INDUSTRY(VARMECOM ENDUSTRIYEL SANAYI VE TICARET ANONIM SIRKETI) | M13: 49308, ODUNPAZARI, ESKISEHIR, KOBI ORGANIZE SANAYI BOLGESI 75 YIL OSB MAH. 104 C | P13: 1 | Q13: 0 | R13: 1 | S13: 490 | T13: 1131650002494 | U13: 1650258175 | V13: ООО ТД ГИГАЗ | W13: 450000, РЕСПУБЛИКА БАШКОРТОСТАН, Г. УФА, УЛ. 50-ЛЕТИЯ ОКТЯБРЯ, 15 | X13: 80000 | Y13: 027801001 | Z13: 1131650002494 | AA13: 1650258175 | AB13: ООО ТД ГИГАЗ | AC13: 450000, РЕСПУБЛИКА БАШКОРТОСТАН, Г. УФА, УЛ. 50-ЛЕТИЯ ОКТЯБРЯ, 15 | AD13: 80000 | AE13: 027801001 | AF13: TR | AG13: ТУРЦИЯ | AH13: 10222790 | AI13: 1131650002494 | AJ13: 1650258175 | AK13: ООО ТД ГИГАЗ | AL13: 450000, РЕСПУБЛИКА БАШКОРТОСТАН, Г. УФА, УЛ. 50-ЛЕТИЯ ОКТЯБРЯ, 15 | AM13: 80000 | AN13: 027801001 | AO13: TR | AP13: ТУРЦИЯ | AQ13: ТУРЦИЯ | AR13: RU | AS13: РОССИЯ | AT13: 0 | AU13: 1 | AV13: EXW | AW13: ESKISEHIR | AX13: 1 | AY13: EUR | AZ13: 129000 | BA13: 9813869 | BB13: 142026.98 | BC13: 76.0765 | BD13: 010 | BF13: 22080001/0067/0000/2/1 | BG13: - | BH13: 99 | BJ13: 10317000/031221/00006/2 | BL13: КРАСНОДАРСКИЙ КРАЙ | BM13: НОВОРОССИЙСК | BN13: УЛ. СУХУМСКОЕ ШОССЕ, ПЗТК ООО НУТЭП | BO13: 10317110 т/п Новороссийский юго-восточный | BP13: 1 | BQ13: КОТЕЛЬНАЯ АВТОМАТИЗИРОВАННАЯ ИЗ МЕТАЛЛА(НЕ ИЗ ЧУГУНА), НОМИНАЛЬНОЙ ТЕПЛОПРОИЗВОДИТЕЛЬНОСТЬЮ ДО 33 КВТ. ПРЕДНАЗНАЧЕНА ДЛЯ ИСПОЛЬЗОВАНИЯ В КАЧЕСТВЕ ИСТОЧНИКА ТЕПЛОНОСИТЕЛЯ И ГОРЯЧЕЙ ВОДЫ ДЛЯ ЗДАНИЙ И СООРУЖЕНИЙ РАЗЛИЧНОГО НАЗНАЧЕНИЯ. КОТЕЛЬНАЯ | BR13: =ISNUMBER(SEARCH($BR$1,Таблица1[[#This Row],[31_1 Описание и характеристика товара]]))*1 -> 0 | BT13: VARMECOM INDUSTRY | BU13: 490 | BV13: 1 | BW13: 490 | BX13: ШТ | BY13: 0 | CA13: 1 | CB13: 8403109000 | CE13: TR | CF13: 15034 | CG13: ОООО-ОО | CH13: 4000000 | CI13: 14207 | CJ13: 0 | CM13: 129000 | CN13: 9813869 | CO13: 0 | CP13: 1 | CQ13: 10222790 | CR13: 142026.98 | CS13: 10 | CT13: 9.997 | CU13: 727 | CV13: 0491/01-15/009 | CX13: ЗАРИПОВ ЭДУАРД КАМИЛЬЕВИЧ | CY13: 0
A14: 1 | B14: 44610 | C14: =IF(YEAR(Таблица1[[#This Row],[Дата]])=2023,MONTH(Таблица1[[#This Row],[Дата]]),0) -> 0 | D14: 10317120/261222/3173190 | E14: 10317120 | F14: 3173190 | G14: ИМ | H14: 40 | L14: ELEKS DIS TICARET A.S. | M14: 34394, SISLI, ISTANBUL, ESENTERE MAH.KASAR SK. ELGINKAN HOLDING BLOK NO:15, | P14: 2 | Q14: 0 | R14: 4 | S14: 471 | T14: 1197746381986 | U14: 7720470130 | V14: ООО ВЕССЕН | W14: 109518, ЮВАО РАЙОН ТЕКСТИЛЬЩИКИ, Г. МОСКВА, 1-Й ГРАЙВОРОНОВСКИЙ ПРОЕЗД, Д. 20, С | X14: 45000 | Y14: 772201001 | Z14: 1197746381986 | AA14: 7720470130 | AB14: ООО ВЕССЕН | AC14: 109518, ЮВАО РАЙОН ТЕКСТИЛЬЩИКИ, Г. МОСКВА, 1-Й ГРАЙВОРОНОВСКИЙ ПРОЕЗД, Д. 20, С | AD14: 45000 | AE14: 772201001 | AF14: TR | AG14: ТУРЦИЯ | AH14: 9189223.9 | AI14: 1197746381986 | AJ14: 7720470130 | AK14: ООО ВЕССЕН | AL14: 109518, ЮВАО РАЙОН ТЕКСТИЛЬЩИКИ, Г. МОСКВА, 1-Й ГРАЙВОРОНОВСКИЙ ПРОЕЗД, Д. 20, С | AM14: 45000 | AN14: 772201001 | AO14: TR | AP14: ТУРЦИЯ | AQ14: ТУРЦИЯ | AR14: RU | AS14: РОССИЯ | AT14: 0 | AU14: 1 | AV14: FCA | AW14: MANISA (ТУРЦИЯ) | AX14: 1 | AY14: USD | AZ14: 131226.62 | BA14: 9012119 | BB14: 133805.46 | BC14: 68.676 | BD14: 010 | BF14: 20050760/1326/0000/2/1 | BG14: - | BH14: 95 | BJ14: 10317000/021222/00006/2 | BL14: КРАСНОДАРСКИЙ КРАЙ | BM14: Г. НОВОРОССИЙСК | BN14: СУХУМСКОЕ ШОССЕ, Д.17А | BO14: 10317110 т/п Новороссийский юго-восточный | BP14: 1 | BQ14: КОТЛЫ БЫТОВЫЕ, ЦЕНТРАЛЬНОГО ОТОПЛЕНИЯ, ГАЗОВЫЕ, ОДНОКОНТУРНЫЕ, НАСТЕННЫЕ. ТОРГОВАЯ МАРКА Е.С.А., ИЗГОТОВЛЕНЫ ИЗ КОМПОЗИТНЫХ МАТЕРИАЛОВ, ЛАТУННЫХ И МЕТАЛЛИЧЕСКИХ ЧАСТЕЙ, В КОМПЛЕКТЕ С ИНСТРУКЦИЕЙ ПО УСТАНОВКЕ И ЭКСПЛУАТАЦИИ И КРЕПЕЖНОЙ ФУРНИТУРОЙ. | BR14: =ISNUMBER(SEARCH($BR$1,Таблица1[[#This Row],[31_1 Описание и характеристика товара]]))*1 -> 0 | BT14: EMAS MAKINA SANAYI A.S. | BU14: 305 | BV14: 1 | BW14: 305 | BX14: ШТ | BY14: 0 | CA14: 1 | CB14: 8403109000 | CE14: TR | CF14: 10190 | CG14: ОООО-ОО | CH14: 4000000 | CI14: 9677 | CJ14: 0 | CM14: 111308.47 | CN14: 7644220 | CO14: 0 | CP14: 1 | CQ14: 7811476.8 | CR14: 113743.91 | CS14: 10 | CT14: 11.754 | CU14: 1405 | CV14: 140 | CX14: КОЛЕСНИКОВА ЕКАТЕРИНА ИВАНОВНА | CY14: 308
A15: 1 | B15: 44860 | C15: =IF(YEAR(Таблица1[[#This Row],[Дата]])=2023,MONTH(Таблица1[[#This Row],[Дата]]),0) -> 0 | D15: 10317120/261222/3173172 | E15: 10317120 | F15: 3173172 | G15: ИМ | H15: 40 | L15: KATRE ISI SANAYI TICARET A. S. | M15: 34394, ZEYTINBURNU/, ISTANBUL, SEYITNIZAM MAH. DEMIRCILER SITESI 1 YOL NO:73/75, | P15: 2 | Q15: 0 | R15: 2 | S15: 11 | T15: 1197746381986 | U15: 7720470130 | V15: ООО ВЕССЕН | W15: 109518, ВН.ТЕР.Г. МУНИЦИПАЛЬНЫЙ ОКРУГ ТЕКСТИЛЬЩИКИ, МОСКВА, 1-Й ГРАЙВОРОНОВСКИЙ | X15: 45000 | Y15: 772201001 | Z15: 1197746381986 | AA15: 7720470130 | AB15: ООО ВЕССЕН | AC15: 109518, ВН.ТЕР.Г. МУНИЦИПАЛЬНЫЙ ОКРУГ ТЕКСТИЛЬЩИКИ, МОСКВА, 1-Й ГРАЙВОРОНОВСКИЙ | AD15: 45000 | AE15: 772201001 | AF15: TR | AG15: ТУРЦИЯ | AH15: 2934124.7 | AI15: 1197746381986 | AJ15: 7720470130 | AK15: ООО ВЕССЕН | AL15: 109518, ВН.ТЕР.Г. МУНИЦИПАЛЬНЫЙ ОКРУГ ТЕКСТИЛЬЩИКИ, МОСКВА, 1-Й ГРАЙВОРОНОВСКИЙ | AM15: 45000 | AN15: 772201001 | AO15: TR | AP15: ТУРЦИЯ | AQ15: ТУРЦИЯ | AR15: RU | AS15: РОССИЯ | AT15: 0 | AU15: 1 | AV15: FCA | AW15: ISTANBUL | AX15: 1 | AY15: USD | AZ15: 41551.64 | BA15: 2853600 | BB15: 42724.17 | BC15: 68.676 | BD15: 010 | BF15: 20081050/1326/0000/2/1 | BG15: - | BH15: 95 | BJ15: 10317000/021222/00006/2 | BL15: КРАСНОДАРСКИЙ КРАЙ | BM15: Г. НОВОРОССИЙСК | BN15: СУХУМСКОЕ ШОССЕ, Д.17А | BO15: 10317110 т/п Новороссийский юго-восточный | BP15: 1 | BQ15: КОТЛЫ БЫТОВЫЕ, ЦЕНТРАЛЬНОГО ОТОПЛЕНИЯ, ГАЗОВЫЕ, ОДНОКОНТУРНЫЕ, НАСТЕННЫЕ. ТОРГОВАЯ МАРКА Е.С.А., ИЗГОТОВЛЕНЫ ИЗ КОМПОЗИТНЫХ МАТЕРИАЛОВ, ЛАТУННЫХ И МЕТАЛЛИЧЕСКИХ ЧАСТЕЙ, В КОМПЛЕКТЕ С ИНСТРУКЦИЕЙ ПО УСТАНОВКЕ И ЭКСПЛУАТАЦИИ И КРЕПЕЖНОЙ ФУРНИТУРОЙ. С | BR15: =ISNUMBER(SEARCH($BR$1,Таблица1[[#This Row],[31_1 Описание и характеристика товара]]))*1 -> 0 | BT15: ЕМАS MAKINA SANAYI A.S. | BU15: 10 | BV15: 1 | BW15: 10 | BX15: ШТ | BY15: 0 | CA15: 1 | CB15: 8403109000 | CE15: TR | CF15: 1815 | CG15: ОООО-ОО | CH15: 4000000 | CI15: 1794 | CJ15: 0 | CM15: 13718.04 | CN15: 942100 | CO15: 0 | CP15: 1 | CQ15: 971889.59 | CR15: 14151.81 | CS15: 10 | CT15: 7.8884 | CU15: 1405 | CV15: 140 | CX15: КОЛЕСНИКОВА ЕКАТЕРИНА ИВАНОВНА | CY15: 145
A16: 1 | B16: 45112 | C16: =IF(YEAR(Таблица1[[#This Row],[Дата]])=2023,MONTH(Таблица1[[#This Row],[Дата]]),0) -> 7 | D16: 10317120/261222/3173152 | E16: 10317120 | F16: 3173152 | G16: ИМ | H16: 40 | L16: VESSEN DIS TICARET A. S. | M16: , ZEYTINBURNU, ISTANBUL, SEYITNIZAM MAH. DEMIRCILER SITESI 1 YOL NO:75, | P16: 1 | Q16: 0 | R16: 1 | S16: 1 | T16: 1197746381986 | U16: 7720470130 | V16: ООО ВЕССЕН | W16: 109518, ЮВАО РАЙОН ТЕКСТИЛЬЩИКИ, Г. МОСКВА, 1-Й ГРАЙВОРОНОВСКИЙ ПРОЕЗД, Д. 20, С | X16: 45000 | Y16: 772201001 | Z16: 1197746381986 | AA16: 7720470130 | AB16: ООО ВЕССЕН | AC16: 109518, ЮВАО РАЙОН ТЕКСТИЛЬЩИКИ, Г. МОСКВА, 1-Й ГРАЙВОРОНОВСКИЙ ПРОЕЗД, Д. 20, С | AD16: 45000 | AE16: 772201001 | AF16: TR | AG16: ТУРЦИЯ | AH16: 323452.87 | AI16: 1197746381986 | AJ16: 7720470130 | AK16: ООО ВЕССЕН | AL16: 109518, ЮВАО РАЙОН ТЕКСТИЛЬЩИКИ, Г. МОСКВА, 1-Й ГРАЙВОРОНОВСКИЙ ПРОЕЗД, Д. 20, С | AM16: 45000 | AN16: 772201001 | AO16: TR | AP16: ТУРЦИЯ | AQ16: ТУРЦИЯ | AR16: RU | AS16: РОССИЯ | AT16: 0 | AU16: 1 | AV16: FCA | AW16: ISTANBUL | AX16: 1 | AY16: TRY | AZ16: 85900 | BA16: 314829 | BB16: 4709.84 | BC16: 36.7861 | BD16: 010 | BF16: 22110090/3311/0000/2/1 | BG16: - | BH16: 95 | BJ16: 10317000/021222/00006/2 | BL16: КРАСНОДАРСКИЙ КРАЙ | BM16: Г. НОВОРОССИЙСК | BN16: СУХУМСКОЕ ШОССЕ, Д.17А | BO16: 10317110 т/п Новороссийский юго-восточный | BP16: 1 | BQ16: КОТЛЫ БЫТОВЫЕ, ЦЕНТРАЛЬНОГО ОТОПЛЕНИЯ, ГАЗОВЫЕ, ИЗГОТОВЛЕНЫ ИЗ КОМПОЗИТНЫХ МАТЕРИАЛОВ, ЛАТУННЫХ И МЕТАЛЛИЧЕСКИХ ЧАСТЕЙ. ОДНОКОНТУРНЫЕ, НАСТЕННЫЕ КОНДЕНСАЦИОННЫЕ, НА НАПРЯЖЕНИЕ 220-240 В. В КОМПЛЕКТЕ С ДЫМОХОДОМ. ПРЕДНАЗНАЧЕНЫ ДЛЯ ОТОПЛЕНИЯ ЧАСТНЫХ | BR16: =ISNUMBER(SEARCH($BR$1,Таблица1[[#This Row],[31_1 Описание и характеристика товара]]))*1 -> 0 | BT16: TERMO ISI SISTEMLERI TIC. VE SAN. A.S. | BU16: 1 | BV16: 1 | BW16: 5 | BX16: ШТ | BY16: 0 | CA16: 1 | CB16: 8403109000 | CE16: TR | CF16: 444 | CG16: ОООО-ОО | CH16: 4000000 | CI16: 415 | CJ16: 0 | CM16: 85900 | CN16: 314829 | CO16: 0 | CP16: 1 | CQ16: 323452.87 | CR16: 4709.84 | CS16: 10 | CT16: 11.349 | CU16: 1405 | CV16: 140 | CX16: КОЛЕСНИКОВА ЕКАТЕРИНА ИВАНОВНА | CY16: 151
A17: 1 | B17: 44931 | C17: =IF(YEAR(Таблица1[[#This Row],[Дата]])=2023,MONTH(Таблица1[[#This Row],[Дата]]),0) -> 1 | D17: 10317120/221222/5000957 | E17: 10317120 | F17: 5000957 | G17: ИМ | H17: 40 | L17: BAYMAK MAKINA SANAYI VE TICARET A.S. | M17: 34959, , ORHANLI-TUZLA/ISTANBUL, ORHANLI BELDESI ORTA MAH. AKDENIZ SOK.NO:8, | P17: 1 | R17: 1 | S17: 28 | T17: 1087746423005 | U17: 7717615508 | V17: ООО БДР ТЕРМИЯ РУС | W17: 129164, , Г.МОСКВА, ЗУБАРЕВ ПЕР., Д.15, К.1, ЭТ.3, ПОМ.1, КОМ.67Г, | X17: 45000 | Y17: 771701001 | Z17: 1087746423005 | AA17: 7717615508 | AB17: ООО БДР ТЕРМИЯ РУС | AC17: 129164, , Г.МОСКВА, ЗУБАРЕВ ПЕР., Д.15, К.1, ЭТ.3, ПОМ.1, КОМ.67Г, | AD17: 45000 | AE17: 771701001 | AF17: TR | AG17: ТУРЦИЯ | AH17: 7119229.7 | AI17: 1087746423005 | AJ17: 7717615508 | AK17: ООО БДР ТЕРМИЯ РУС | AL17: 129164, , Г.МОСКВА, ЗУБАРЕВ ПЕР., Д.15, К.1, ЭТ.3, ПОМ.1, КОМ.67Г, | AM17: 45000 | AN17: 771701001 | AO17: TR | AP17: ТУРЦИЯ | AQ17: ТУРЦИЯ | AR17: RU | AS17: РОССИЯ | AU17: 1 | AV17: EXW | AW17: TUZLA | AX17: 1 | AY17: EUR | AZ17: 91116.48 | BA17: 6842064 | BB17: 100945.33 | BC17: 75.0914 | BD17: 010 | BE17: 30 | BF17: 16080084/0001/0000/2/1 | BG17: - | BH17: 99 | BJ17: 10317000/021222/00006/2 | BL17: КРАСНОДАРСКИЙ КРАЙ | BM17: Г. НОВОРОССИЙСК | BN17: СУХУМСКОЕ ШОССЕ, Д. 17А ПЗТК ООО НУТЭП | BO17: 10317110 т/п Новороссийский юго-восточный | BP17: 1 | BQ17: КОТЛЫ ГАЗОВЫЕ ЦЕНТРАЛЬНОГО ОТОПЛЕНИЯ, СТАЛЬНЫЕ: | BR17: =ISNUMBER(SEARCH($BR$1,Таблица1[[#This Row],[31_1 Описание и характеристика товара]]))*1 -> 0 | BT17: BAYMAK MAKINA SANAYI VE TICARET A.S. | BU17: 28 | BV17: 1 | BW17: 336 | BX17: ШТ | CA17: 1 | CB17: 8403109000 | CE17: TR | CF17: 10836 | CG17: ОООО-ОО | CH17: 4000000 | CI17: 10416 | CM17: 91116.48 | CN17: 6842064 | CO17: 0 | CP17: 1 | CQ17: 7119229.7 | CR17: 100945.33 | CS17: 10 | CT17: 9.6914 | CU17: 1168 | CV17: ЛС-БДРТР/220/07/2022 | CX17: ДАВЫДОВА СВЕТЛАНА АЛЕКСАНДРОВНА | CY17: 0
A18: 1 | B18: 45164 | C18: =IF(YEAR(Таблица1[[#This Row],[Дата]])=2023,MONTH(Таблица1[[#This Row],[Дата]]),0) -> 8 | D18: 10317120/221222/3169345 | E18: 10317120 | F18: 3169345 | G18: ИМ | H18: 40 | L18: BAYMAK MAKINA SANAYI VE TICARET A.S. | M18: 34959, ORHANLI/TUZLA, ISTANBUL, ORHANLI BELDESI, ORTA MAHALLE, AKDENIZ SOK.NO:8, | P18: 1 | Q18: 0 | R18: 1 | S18: 28 | T18: 1087746423005 | U18: 7717615508 | V18: ООО БДР ТЕРМИЯ РУС | W18: 129164, , Г.МОСКВА, ЗУБАРЕВ ПЕР., Д.15, К.1, ЭТ.3, ПОМ.1, КОМ.67Г, | X18: 45000 | Y18: 771701001 | Z18: 1087746423005 | AA18: 7717615508 | AB18: ООО БДР ТЕРМИЯ РУС | AC18: 129164, , Г.МОСКВА, ЗУБАРЕВ ПЕР., Д.15, К.1, ЭТ.3, ПОМ.1, КОМ.67Г, | AD18: 45000 | AE18: 771701001 | AF18: TR | AG18: ТУРЦИЯ | AH18: 7084237.1 | AI18: 1087746423005 | AJ18: 7717615508 | AK18: ООО БДР ТЕРМИЯ РУС | AL18: 129164, , Г.МОСКВА, ЗУБАРЕВ ПЕР., Д.15, К.1, ЭТ.3, ПОМ.1, КОМ.67Г, | AM18: 45000 | AN18: 771701001 | AO18: TR | AP18: ТУРЦИЯ | AQ18: ТУРЦИЯ | AR18: RU | AS18: РОССИЯ | AT18: 0 | AU18: 1 | AV18: EXW | AW18: TUZLA | AX18: 1 | AY18: EUR | AZ18: 90650.48 | BA18: 6807071 | BB18: 100449.16 | BC18: 75.0914 | BD18: 010 | BE18: 30 | BF18: 16080084/0001/0000/2/1 | BG18: - | BH18: 99 | BJ18: 10317000/021222/00006/2 | BL18: КРАСНОДАРСКИЙ КРАЙ | BM18: Г. НОВОРОССИЙСК | BN18: СУХУМСКОЕ ШОССЕ, Д. 17 А. ПЗТК ООО НУТЭП | BO18: 10317110 т/п Новороссийский юго-восточный | BP18: 1 | BQ18: КОТЛЫ ЦЕНТРАЛЬНОГО ОТОПЛЕНИЯ ГАЗОВЫЕ СТАЛЬНЫЕ | BR18: =ISNUMBER(SEARCH($BR$1,Таблица1[[#This Row],[31_1 Описание и характеристика товара]]))*1 -> 0 | BT18: BAYMAK MAKINA SANAYI VE TICARET A.S. | BU18: 28 | BV18: 1 | BW18: 336 | BX18: ШТ | BY18: 0 | CA18: 1 | CB18: 8403109000 | CE18: TR | CF18: 10836 | CG18: ОООО-ОО | CH18: 4000000 | CI18: 10416 | CJ18: 0 | CM18: 90650.48 | CN18: 6807071 | CO18: 0 | CP18: 1 | CQ18: 7084237.1 | CR18: 100449.16 | CS18: 10 | CT18: 9.6437 | CU18: 1168 | CV18: ЛС-БДРТР/220/07/2022 | CX18: СЛЮСАРЬ ЕГОР ВИТАЛЬЕВИЧ | CY18: 0
A19: 1 | B19: 45048 | C19: =IF(YEAR(Таблица1[[#This Row],[Дата]])=2023,MONTH(Таблица1[[#This Row],[Дата]]),0) -> 5 | D19: 10317120/211222/3168635 | E19: 10317120 | F19: 3168635 | G19: ИМ | H19: 40 | L19: BAYMAK MAK SAN VE TIC. AS. | M19: 34959, ISTANBUL, ORHANLI-TUZLA, ORHANLI BELDESI ORTA MAH. AKDENIZ, SOK.NO:8 | P19: 1 | Q19: 0 | R19: 1 | S19: 28 | T19: 1087746423005 | U19: 7717615508 | V19: ООО БДР ТЕРМИЯ РУС | W19: 129164, , Г. МОСКВА, ЗУБАРЕВ ПЕРЕУЛОК, Д. 15, КОРП.1, ЭТАЖ 3, ПОМ.1, КО, | X19: 45000 | Y19: 771701001 | Z19: 1087746423005 | AA19: 7717615508 | AB19: ООО БДР ТЕРМИЯ РУС | AC19: 129164, , Г. МОСКВА, ЗУБАРЕВ ПЕРЕУЛОК, Д. 15, КОРП.1, ЭТАЖ 3, ПОМ.1, КО, | AD19: 45000 | AE19: 771701001 | AF19: TR | AG19: ТУРЦИЯ | AH19: 6935230.4 | AI19: 1087746423005 | AJ19: 7717615508 | AK19: ООО БДР ТЕРМИЯ РУС | AL19: 129164, , Г. МОСКВА, ЗУБАРЕВ ПЕРЕУЛОК, Д. 15, КОРП.1, ЭТАЖ 3, ПОМ.1, КО, | AM19: 45000 | AN19: 771701001 | AO19: TR | AP19: ТУРЦИЯ | AQ19: ТУРЦИЯ | AR19: RU | AS19: РОССИЯ | AT19: 0 | AU19: 1 | AV19: EXW | AW19: TUZLA | AX19: 1 | AY19: EUR | AZ19: 91116.48 | BA19: 6682382 | BB19: 100505.2 | BC19: 73.3389 | BD19: 010 | BE19: 30 | BF19: 16080084/0001/0000/2/1 | BG19: - | BH19: 99 | BJ19: 10317000/021222/00006/2 | BL19: КРАСНОДАРСКИЙ КРАЙ | BM19: Г. НОВОРОССИЙСК | BN19: УЛ.СУХУМСКОЕ ШОССЕ | BO19: 10317110 т/п Новороссийский юго-восточный | BP19: 1 | BQ19: КОТЛЫ ЦЕНТРАЛЬНОГО ОТОПЛЕНИЯ | BR19: =ISNUMBER(SEARCH($BR$1,Таблица1[[#This Row],[31_1 Описание и характеристика товара]]))*1 -> 0 | BT19: BAYMAK MAKINA SANAYI VE TICARET A.S. | BU19: 28 | BV19: 1 | BW19: 336 | BX19: ШТ | BY19: 0 | CA19: 1 | CB19: 8403109000 | CE19: TR | CF19: 10836 | CG19: ОООО-ОО | CH19: 4000000 | CI19: 10836 | CJ19: 0 | CM19: 91116.48 | CN19: 6682382 | CO19: 0 | CP19: 1 | CQ19: 6935230.4 | CR19: 100505.2 | CS19: 10 | CT19: 9.2751 | CU19: 897 | CV19: 0897/00-2022-078 | CX19: ПАСЛЕН АННА ПЕТРОВНА | CY19: 0
A20: 1 | B20: 44928 | C20: =IF(YEAR(Таблица1[[#This Row],[Дата]])=2023,MONTH(Таблица1[[#This Row],[Дата]]),0) -> 1 | D20: 10317120/201222/3167790 | E20: 10317120 | F20: 3167790 | G20: ИМ | H20: 40 | L20: CAGDAS KARAGOL-CAGDAS NAKLIYAT | M20: , , ISTANBUL, INONU MH. ORKIDEM SK. NO:NO:4/4 ATASEHIR, | P20: 1 | Q20: 0 | R20: 1 | S20: 404 | T20: 1213000003908 | U20: 3019030445 | V20: ООО САРМАТ + | W20: 414041, АСТРАХАНСКАЯ ОБЛ.,Г.О. ГОРОД АСТРАХАНЬ, Г АСТРАХАНЬ, УЛ ЕРЕВАНСКАЯ,Д. 3, | X20: 12000 | Y20: 301901001 | Z20: 1213000003908 | AA20: 3019030445 | AB20: ООО САРМАТ + | AC20: 414041, АСТРАХАНСКАЯ ОБЛ.,Г.О. ГОРОД АСТРАХАНЬ, Г АСТРАХАНЬ, УЛ ЕРЕВАНСКАЯ,Д. 3, | AD20: 12000 | AE20: 301901001 | AF20: TR | AG20: ТУРЦИЯ | AH20: 8329581.8 | AI20: 1213000003908 | AJ20: 3019030445 | AK20: ООО САРМАТ + | AL20: 414041, АСТРАХАНСКАЯ ОБЛ.,Г.О. ГОРОД АСТРАХАНЬ, Г АСТРАХАНЬ, УЛ ЕРЕВАНСКАЯ,Д. 3, | AM20: 12000 | AN20: 301901001 | AO20: TR | AP20: ТУРЦИЯ | AQ20: ТУРЦИЯ | AR20: RU | AS20: РОССИЯ | AT20: 1 | AU20: 1 | AV20: CFR | AW20: НОВОРОССИЙСК | AX20: 1 | AY20: EUR | AZ20: 117950 | BA20: 8329582 | BB20: 125544.96 | BC20: 70.6196 | BD20: 010 | BE20: 10 | BF20: 22090030/2272/0026/2/1 | BG20: - | BH20: 95 | BJ20: 10317000/021222/00006/2 | BL20: КРАСНОДАРСКИЙ КРАЙ | BM20: Г. НОВОРОССИЙСК | BN20: СУХУМСКОЕ ШОССЕ, 17А | BO20: 10317110 т/п Новороссийский юго-восточный | BP20: 1 | BQ20: КОТЛЫ БЫТОВЫЕ ЦЕНТРАЛЬНОГО ОТОПЛЕНИЯ, ВОДОГРЕЙНЫЕ, ГАЗОВЫЕ В СТАЛЬНОМ КОРПУСЕ; ДВУХКОНТУРНЫЕ НАСТЕННЫЕ ГАЗОВЫЕ КОТЛЫ | BR20: =ISNUMBER(SEARCH($BR$1,Таблица1[[#This Row],[31_1 Описание и характеристика товара]]))*1 -> 0 | BT20: TURK DEMIR DOKUM FABRIKALARI A.S. | BU20: 404 | BV20: 1 | BW20: 404 | BX20: ШТ | BY20: 0 | CA20: 1 | CB20: 8403109000 | CE20: TR | CF20: 14050 | CG20: ОООО-ОО | CH20: 4000000 | CI20: 14050 | CJ20: 0 | CM20: 117950 | CN20: 8329582 | CO20: 0 | CP20: 1 | CQ20: 8329581.8 | CR20: 125544.96 | CS20: 10 | CT20: 8.9356 | CU20: 1027 | CV20: 1027/22/1002-01 | CX20: ДОРОФЕЕВА ЕЛЕНА АЛЕКСАНДРОВНА | CY20: 201
A21: 1 | B21: 45162 | C21: =IF(YEAR(Таблица1[[#This Row],[Дата]])=2023,MONTH(Таблица1[[#This Row],[Дата]]),0) -> 8 | D21: 10317120/191222/3166454 | E21: 10317120 | F21: 3166454 | G21: ИМ | H21: 40 | L21: VARMECOM ENDUSTRIYEL SANAYI VE TICARET ANONIM SIRKETI | M21: 26250, ODUNPAZARI, ESKISEHIR, 75 YIL OSB MAH. 104 CD. ADAR APT. NO 6, | P21: 2 | Q21: 0 | R21: 2 | S21: 650 | T21: 1161690104234 | U21: 1650331192 | V21: ООО ФЕДЕРИКА БУГАТТИ | W21: 423800, ТАТАРСТАН, НАБЕРЕЖНЫЕ ЧЕЛНЫ, КАЗАНСКИЙ ПРОСПЕКТ, 226 | X21: 92000 | Y21: 165001001 | Z21: 1161690104234 | AA21: 1650331192 | AB21: ООО ФЕДЕРИКА БУГАТТИ | AC21: 423800, ТАТАРСТАН, НАБЕРЕЖНЫЕ ЧЕЛНЫ, КАЗАНСКИЙ ПРОСПЕКТ, 226 | AD21: 92000 | AE21: 165001001 | AF21: TR | AG21: ТУРЦИЯ | AH21: 9550856 | AI21: 1161690104234 | AJ21: 1650331192 | AK21: ООО ФЕДЕРИКА БУГАТТИ | AL21: 423800, ТАТАРСТАН, НАБЕРЕЖНЫЕ ЧЕЛНЫ, КАЗАНСКИЙ ПРОСПЕКТ, 226 | AM21: 92000 | AN21: 165001001 | AO21: TR | AP21: ТУРЦИЯ | AQ21: ТУРЦИЯ | AR21: RU | AS21: РОССИЯ | AT21: 0 | AU21: 1 | AV21: EXW | AW21: ESKISEHIR | AX21: 1 | AY21: EUR | AZ21: 133881 | BA21: 9208308 | BB21: 147828.22 | BC21: 68.7798 | BD21: 010 | BF21: 21040004/0067/0000/2/1 | BG21: - | BH21: 99 | BJ21: 10317000/031221/00006/2 | BL21: КРАСНОДАРСКИЙ КРАЙ | BM21: НОВОРОССИЙСК | BN21: УЛ. СУХУМСКОЕ ШОССЕ, ПЗТК ООО НУТЭП | BO21: 10317110 т/п Новороссийский юго-восточный | BP21: 1 | BQ21: КОТЕЛЬНАЯ АВТОМАТИЗИРОВАННАЯ ИЗ МЕТАЛЛА(НЕ ИЗ ЧУГУНА), НОМИНАЛЬНОЙ ТЕПЛОПРОИЗВОДИТЕЛЬНОСТЬЮ ДО 32 КВТ. ПРЕДНАЗНАЧЕНА ДЛЯ ИСПОЛЬЗОВАНИЯ В КАЧЕСТВЕ ИСТОЧНИКА ТЕПЛОНОСИТЕЛЯ И ГОРЯЧЕЙ ВОДЫ ДЛЯ ЗДАНИЙ И СООРУЖЕНИЙ РАЗЛИЧНОГО НАЗНАЧЕНИЯ. КОТЕЛЬНАЯ | BR21: =ISNUMBER(SEARCH($BR$1,Таблица1[[#This Row],[31_1 Описание и характеристика товара]]))*1 -> 0 | BT21: VARMECOM INDUSTRY | BU21: 490 | BV21: 1 | BW21: 490 | BX21: ШТ | BY21: 0 | CA21: 1 | CB21: 8403109000 | CE21: TR | CF21: 15242 | CG21: ОООО-ОО | CH21: 4000000 | CI21: 14378.1 | CJ21: 0 | CM21: 132281 | CN21: 9098261 | CO21: 0 | CP21: 1 | CQ21: 9437070.3 | CR21: 146067.04 | CS21: 10 | CT21: 10.159 | CU21: 727 | CV21: 0491/01-21/25 | CX21: ЗАРИПОВ ЭДУАРД КАМИЛЬЕВИЧ | CY21: 18
A22: 1 | B22: 45241 | C22: =IF(YEAR(Таблица1[[#This Row],[Дата]])=2023,MONTH(Таблица1[[#This Row],[Дата]]),0) -> 11 | D22: 10317120/191222/3166354 | E22: 10317120 | F22: 3166354 | G22: ИМ | H22: 40 | L22: VARMECOM ENDUSTRIYEL SANAYI VE TICARET ANONIM SIRKETI | M22: 262502, ODUNPAZARI, ESKISEHIR, 75 YIL OSB MAH. 104 CD. ADAR APT. NO 6, | P22: 1 | Q22: 0 | R22: 1 | S22: 490 | T22: 1131650002494 | U22: 1650258175 | V22: ООО ТД ГИГАЗ | W22: 450000, РЕСПУБЛИКА БАШКОРТОСТАН, Г. УФА, УЛ. 50-ЛЕТИЯ ОКТЯБРЯ, 15 | X22: 80000 | Y22: 027801001 | Z22: 1131650002494 | AA22: 1650258175 | AB22: ООО ТД ГИГАЗ | AC22: 450000, РЕСПУБЛИКА БАШКОРТОСТАН, Г. УФА, УЛ. 50-ЛЕТИЯ ОКТЯБРЯ, 15 | AD22: 80000 | AE22: 027801001 | AF22: TR | AG22: ТУРЦИЯ | AH22: 9458278.4 | AI22: 1131650002494 | AJ22: 1650258175 | AK22: ООО ТД ГИГАЗ | AL22: 450000, РЕСПУБЛИКА БАШКОРТОСТАН, Г. УФА, УЛ. 50-ЛЕТИЯ ОКТЯБРЯ, 15 | AM22: 80000 | AN22: 027801001 | AO22: TR | AP22: ТУРЦИЯ | AQ22: ТУРЦИЯ | AR22: RU | AS22: РОССИЯ | AT22: 0 | AU22: 1 | AV22: EXW | AW22: ESKISEHIR | AX22: 1 | AY22: EUR | AZ22: 132535 | BA22: 9115731 | BB22: 146395.3 | BC22: 68.7798 | BD22: 010 | BF22: 22080001/0067/0000/2/1 | BG22: - | BH22: 99 | BJ22: 10317000/031221/00006/2 | BL22: КРАСНОДАРСКИЙ КРАЙ | BM22: НОВОРОССИЙСК | BN22: УЛ. СУХУМСКОЕ ШОССЕ, ПЗТК ООО НУТЭП | BO22: 10317110 т/п Новороссийский юго-восточный | BP22: 1 | BQ22: КОТЕЛЬНАЯ АВТОМАТИЗИРОВАННАЯ ИЗ МЕТАЛЛА(НЕ ИЗ ЧУГУНА), НОМИНАЛЬНОЙ ТЕПЛОПРОИЗВОДИТЕЛЬНОСТЬЮ ДО 32 КВТ. ПРЕДНАЗНАЧЕНА ДЛЯ ИСПОЛЬЗОВАНИЯ В КАЧЕСТВЕ ИСТОЧНИКА ТЕПЛОНОСИТЕЛЯ И ГОРЯЧЕЙ ВОДЫ ДЛЯ ЗДАНИЙ И СООРУЖЕНИЙ РАЗЛИЧНОГО НАЗНАЧЕНИЯ. КОТЕЛЬНАЯ | BR22: =ISNUMBER(SEARCH($BR$1,Таблица1[[#This Row],[31_1 Описание и характеристика товара]]))*1 -> 0 | BT22: VARMECOM INDUSTRY | BU22: 490 | BV22: 1 | BW22: 490 | BX22: ШТ | BY22: 0 | CA22: 1 | CB22: 8403109000 | CE22: TR | CF22: 15616.2 | CG22: ОООО-ОО | CH22: 4000000 | CI22: 14756.8 | CJ22: 0 | CM22: 132535 | CN22: 9115731 | CO22: 0 | CP22: 1 | CQ22: 9458278.4 | CR22: 146395.3 | CS22: 10 | CT22: 9.9205 | CU22: 727 | CV22: 0491/01-15/009 | CX22: ЗАРИПОВ ЭДУАРД КАМИЛЬЕВИЧ | CY22: 0
A23: 1 | B23: 45205 | C23: =IF(YEAR(Таблица1[[#This Row],[Дата]])=2023,MONTH(Таблица1[[#This Row],[Дата]]),0) -> 10 | D23: 10317120/191222/3166230 | E23: 10317120 | F23: 3166230 | G23: ИМ | H23: 40 | L23: TERMO ISI SISTEMLERI TIC. VE SAN. A.S. | M23: , KARTAL, ISTANBUL, MONUMENTO PLAZA, ESENTEPE MAH. MILANGAZ, NO:75 KAT:3 | P23: 3 | Q23: 0 | R23: 5 | S23: 6 | T23: 1147847439046 | U23: 7810372426 | V23: ООО ХОРТЭК-ПРОЕКТ | W23: 196191, , САНКТ-ПЕТЕРБУРГ, НОВОИЗМАЙЛОВСКИЙ ПР, Д.46, КОРП.2, ЛИТ. А, ПОМ. 10, | X23: 40000 | Y23: 781001001 | Z23: 1147847439046 | AA23: 7810372426 | AB23: ООО ХОРТЭК-ПРОЕКТ | AC23: 196191, , САНКТ-ПЕТЕРБУРГ, НОВОИЗМАЙЛОВСКИЙ ПР, Д.46, КОРП.2, ЛИТ. А, ПОМ. 10, | AD23: 40000 | AE23: 781001001 | AF23: TR | AG23: ТУРЦИЯ | AH23: 2970658 | AI23: 1147847439046 | AJ23: 7810372426 | AK23: ООО ХОРТЭК-ПРОЕКТ | AL23: 196191, , САНКТ-ПЕТЕРБУРГ, НОВОИЗМАЙЛОВСКИЙ ПР, Д.46, КОРП.2, ЛИТ. А, ПОМ. 10, | AM23: 40000 | AN23: 781001001 | AO23: TR | AP23: ТУРЦИЯ | AQ23: ТУРЦИЯ | AR23: RU | AS23: РОССИЯ | AT23: 2 | AU23: 1 | AV23: EXW | AW23: CORLU | AX23: 1 | AY23: EUR | AZ23: 39317 | BA23: 2704215 | BB23: 45979.86 | BC23: 68.7798 | BD23: 010 | BE23: 40 | BF23: 22060031/2867/0000/2/1 | BG23: - | BH23: 11 | BI23: 10317/080914/10025/4 | BL23: КРАСНОДАРСКИЙ КРАЙ | BM23: Г. НОВОРОССИЙСК | BN23: С. ЦЕМДОЛИНА | BO23: 10317080 т/п Приморский | BP23: 1 | BQ23: КОТЛЫ ОТОПИТЕЛЬНЫЕ ГАЗОВЫЕ КОНДЕНСАЦИОННЫЕ, ТОРГОВОЙ МАРКИ ECODENSE И HORTEK. МАТЕРИАЛ ИЗГОТОВЛЕНИЯ СТАЛЬ. В ЧАСТИЧНО РАЗОБРАННОМ ВИДЕ ДЛЯ УДОБСТВА ТРАНСПОРТИРОВКИ. ТОВАР РАСТАРЕН ИЗ КОНТЕЙНЕРА № TCKU3797157. | BR23: =ISNUMBER(SEARCH($BR$1,Таблица1[[#This Row],[31_1 Описание и характеристика товара]]))*1 -> 0 | BT23: TERMO ISI SISTEMLERI TIC. VE SAN.A.S | BU23: 6 | BV23: 1 | BW23: 21 | BX23: ШТ | BY23: 0 | CA23: 1 | CB23: 8403109000 | CE23: TR | CF23: 1898 | CG23: ОООО-ОО | CH23: 4000000 | CI23: 1898 | CJ23: 0 | CM23: 34888.73 | CN23: 2399640 | CO23: 0 | CP23: 1 | CQ23: 2647292.5 | CR23: 40974.81 | CS23: 10 | CT23: 21.5884 | CU23: 905 | CV23: 0905/18/12-3002 | CX23: МИХАЙЛОВ АНДРЕЙ НИКОЛАЕВИЧ | CY23: 145
A24: 1 | B24: 45073 | C24: =IF(YEAR(Таблица1[[#This Row],[Дата]])=2023,MONTH(Таблица1[[#This Row],[Дата]]),0) -> 5 | D24: 10317120/171222/3165437 | E24: 10317120 | F24: 3165437 | G24: ИМ | H24: 40 | L24: RIMA ISI SISTEMLERI SAN. A.S. | M24: , IKITELLI ORGANIZE SANAYI BOLGESI MAHALLESI, 25. CADDE, NO:10/A-BASAKSEHIR, IST | P24: 1 | Q24: 0 | R24: 1 | S24: 81 | T24: 5087746162983 | U24: 7703675923 | V24: ООО ДАИЧИ | W24: 125130, ГОРОД ФЕДЕРАЛЬНОГО ЗНАЧЕНИЯ, Г.МОСКВА, СТАРОПЕТРОВСКИЙ ПРОЕЗД Д.11,КОРП. | X24: 45000 | Y24: 774301001 | Z24: 5087746162983 | AA24: 7703675923 | AB24: ООО ДАИЧИ | AC24: 125130, ГОРОД ФЕДЕРАЛЬНОГО ЗНАЧЕНИЯ, Г.МОСКВА, СТАРОПЕТРОВСКИЙ ПРОЕЗД Д.11,КОРП. | AD24: 45000 | AE24: 774301001 | AF24: TR | AG24: ТУРЦИЯ | AH24: 4140372.9 | AI24: 5087746162983 | AJ24: 7703675923 | AK24: ООО ДАИЧИ | AL24: 125130, ГОРОД ФЕДЕРАЛЬНОГО ЗНАЧЕНИЯ, Г.МОСКВА, СТАРОПЕТРОВСКИЙ ПРОЕЗД Д.11,КОРП. | AM24: 45000 | AN24: 774301001 | AO24: TR | AP24: ТУРЦИЯ | AQ24: ТУРЦИЯ | AR24: RU | AS24: РОССИЯ | AT24: 0 | AU24: 1 | AV24: EXW | AW24: ISTANBUL | AX24: 1 | AY24: EUR | AZ24: 56815.8 | BA24: 3907779 | BB24: 64084.72 | BC24: 68.7798 | BD24: 010 | BF24: 16030057/1637/0000/2/1 | BG24: - | BH24: 99 | BJ24: 10317000/021222/00006/2 | BL24: КРАСНОДАРСКИЙ КРАЙ | BM24: НОВОРОССИЙСК | BN24: СУХУМСКОЕ Ш. 17А | BO24: 10317110 т/п Новороссийский юго-восточный | BP24: 1 | BQ24: КОТЛЫ ЦЕНРАЛЬНОГО ОТОПЛЕНИЯ, НАПОЛЬНЫЙ, ВОДОГРЕЙНЫЕ, БЫТОВЫЕ, В КОМПЛЕКТЕ С КОМПЛЕКУЮЩИМЕ, КРЕПЕЖЕМ, ИНСТРУКЦИЕЙ. | BR24: =ISNUMBER(SEARCH($BR$1,Таблица1[[#This Row],[31_1 Описание и характеристика товара]]))*1 -> 0 | BT24: RIMA ISI SISTEMLERI SAN. A.S. | BU24: 81 | BV24: 1 | BW24: 81 | BX24: ШТ | BY24: 0 | CA24: 1 | CB24: 8403101000 | CE24: TR | CF24: 18138 | CG24: ОООО-ОО | CH24: 4000000 | CI24: 16385 | CJ24: 0 | CM24: 56815.8 | CN24: 3907779 | CO24: 0 | CP24: 1 | CQ24: 4140372.9 | CR24: 64084.72 | CS24: 10 | CT24: 3.9112 | CU24: 1371 | CV24: НР/07-07.17 | CX24: ЛЕБЕДЕВ НИКОЛАЙ НИКОЛАЕВИЧ | CY24: 0
A25: 1 | B25: 45131 | C25: =IF(YEAR(Таблица1[[#This Row],[Дата]])=2023,MONTH(Таблица1[[#This Row],[Дата]]),0) -> 7 | D25: 10228010/301222/3426412 | E25: 10228010 | F25: 3426412 | G25: ИМ | H25: 40 | L25: ARISTON SPA | M25: 60044, ., FABRIANO (AN), VIALE A. MERLONI, 45, | P25: 4 | Q25: 0 | R25: 8 | S25: 356 | T25: 1024700561742 | U25: 4703066115 | V25: ООО АРИСТОН ТЕРМО РУСЬ | W25: 188676, ЛЕНИНГРАДСКАЯ ОБЛ., ВСЕВОЛОЖСКИЙ Р-ОН,Г.ВСЕВОЛОЖСК, П.З.Г.ВСЕВОЛОЖСКА,УЛ | X25: 41000 | Y25: 470301001 | Z25: 1024700561742 | AA25: 4703066115 | AB25: ООО АРИСТОН ТЕРМО РУСЬ | AC25: 188676, ЛЕНИНГРАДСКАЯ ОБЛ., ВСЕВОЛОЖСКИЙ Р-ОН,Г.ВСЕВОЛОЖСК, П.З.Г.ВСЕВОЛОЖСКА,УЛ | AD25: 41000 | AE25: 470301001 | AF25: IT | AG25: ИТАЛИЯ | AH25: 9937252.4 | AI25: 1024700561742 | AJ25: 4703066115 | AK25: ООО АРИСТОН ТЕРМО РУСЬ | AL25: 188676, ЛЕНИНГРАДСКАЯ ОБЛ., ВСЕВОЛОЖСКИЙ Р-ОН,Г.ВСЕВОЛОЖСК, П.З.Г.ВСЕВОЛОЖСКА,УЛ | AM25: 41000 | AN25: 470301001 | AO25: IT | AP25: ИТАЛИЯ | AQ25: ИТАЛИЯ | AR25: RU | AS25: РОССИЯ | AT25: 2 | AU25: 0 | AV25: DAP | AW25: САНКТ-ПЕТЕРБУРГ | AX25: 1 | AY25: EUR | AZ25: 130621.84 | BA25: 9937252 | BB25: 138059.97 | BC25: 76.0765 | BD25: 010 | BF25: 16020015/3290/0001/2/1 | BG25: - | BH25: 99 | BJ25: 1174 | BL25: Г. САНКТ-ПЕТЕРБУРГ | BM25: ПОС. ПАРГОЛОВО | BN25: ГОРСКОЕ ШОССЕ, Д.4, ЛИТ.А | BO25: 10210350 т/п Парголовский | BP25: 1 | BQ25: КОТЛЫ ГАЗОВЫЕ ОТОПИТЕЛЬНЫЕ ВОДОГРЕЙНЫЕ СО ВСТРОЕННОЙ ГОРЕЛКОЙ, В КОРПУСЕ ИЗ СТАЛИ, НЕЛИТЫЕ, МОЩНОСТЬЮ МЕНЕЕ 100 КВТ, МАРКИ ARISTON (В ПЕРВИЧНОЙ УПАКОВКЕ) | BR25: =ISNUMBER(SEARCH($BR$1,Таблица1[[#This Row],[31_1 Описание и характеристика товара]]))*1 -> 0 | BT25: ARISTON S.P.A. | BU25: 300 | BV25: 0 | BW25: 301 | BX25: ШТ | BY25: 0 | CA25: 1 | CB25: 8403109000 | CE25: IT | CF25: 9065.4 | CG25: ОООО-ОО | CH25: 4000000 | CI25: 9065.4 | CJ25: 0 | CM25: 100251.28 | CN25: 7626767 | CO25: 0 | CP25: 1 | CQ25: 7626766.5 | CR25: 105959.98 | CS25: 10 | CT25: 11.6884 | CU25: 53 | CV25: 0053/03-15-005 | CX25: ВЕРШКОВА МАРИНА ЕВГЕНЬЕВНА | CY25: 0
A26: 1 | B26: 45017 | C26: =IF(YEAR(Таблица1[[#This Row],[Дата]])=2023,MONTH(Таблица1[[#This Row],[Дата]]),0) -> 4 | D26: 10228010/291222/3425456 | E26: 10228010 | F26: 3425456 | G26: ИМ | H26: 40 | L26: THERMEX HEATING TECHNOLOGY (JIANGMEN) CO.,LTD | M26: , GUANGDONG PROVINCE, HESHAN CITY, TAOYUAN TOWN, JIANSHEDONGLU, NO. 51, | P26: 10 | Q26: 0 | R26: 26 | S26: 751 | T26: 1094025002246 | U26: 4025422770 | V26: АО ТАСКОМ ПО ПОРУЧЕНИЮ ООО ТОРГОВЫЙ ДОМ ТЕРМЕКС | W26: 249020, КАЛУЖСКАЯ ОБЛАСТЬ, БОРОВСКИЙ РАЙОН,, СЕЛО ВОРСИНО, СЕВЕРНАЯ ПРОМЫШЛЕННАЯ | X26: 29000 | Y26: 402501001 | Z26: 1094716001907 | AA26: 4716033195 | AB26: ООО ТОРГОВЫЙ ДОМ ТЕРМЕКС | AC26: 187002, ЛЕНИНГРАДСКАЯ ОБЛ., М.Р-Н ТОСНЕНСКИЙ, Г.П. ТОСНЕНС, Г.ТОСНО, МОСКОВСКОЕ | AD26: 41000 | AE26: 471601001 | AF26: CN | AG26: КИТАЙ | AH26: 9277052 | AI26: 1094716001907 | AJ26: 4716033195 | AK26: ООО ТОРГОВЫЙ ДОМ ТЕРМЕКС | AL26: 187002, ЛЕНИНГРАДСКАЯ ОБЛ., М.Р-Н ТОСНЕНСКИЙ, Г.П. ТОСНЕНС, Г.ТОСНО, МОСКОВСКОЕ | AM26: 41000 | AN26: 471601001 | AO26: CN | AP26: КИТАЙ | AQ26: КИТАЙ | AR26: RU | AS26: РОССИЯ | AT26: 1 | AU26: 1 | AV26: FCA | AW26: HESHAN | AX26: 0 | AY26: CNY | AZ26: 893291.9 | BA26: 9064144 | BB26: 130065.3 | BC26: 10.1469 | BD26: 010 | BE26: 10 | BF26: 20060023/2557/0001/2/1 | BG26: - | BH26: 11 | BI26: 10106/100913/10053/8 | BL26: КАЛУЖСКАЯ ОБЛАСТЬ | BM26: БОРОВСКИЙ Р-Н, СЕЛО ВОРСИНО | BN26: СЕВЕРНАЯ ПРОМЗОНА, ВЛАДЕНИЕ 6 | BO26: 10106050 т/п Обнинский | BP26: 1 | BQ26: КОТЛЫ ЭЛЕКТРИЧЕСКИЕ ОТОПИТЕЛЬНЫЕ ВОДОГРЕЙНЫЕ, НАСТЕННЫЕ, ДЛЯ СИСТЕМ ВОДЯНОГО ОТОПЛЕНИЯ И ГОРЯЧЕГО ВОДОСНАБЖЕНИЯ, ДЛЯ ИСПОЛЬЗОВАНИЯ В БЫТУ (НЕ ИЗ ЧУГУННОГО ЛИТЬЯ, НЕ ПРЕДНАЗНАЧЕНЫ ДЛЯ ПРОИЗВОДСТВА ПАРА, НЕ ВОЕННОГО НАЗНАЧЕНИЯ) | BR26: =ISNUMBER(SEARCH($BR$1,Таблица1[[#This Row],[31_1 Описание и характеристика товара]]))*1 -> 0 | BT26: THERMEX HEATING TECHNOLOGY(JIANGMEN)CO.,LTD | BU26: 579 | BV26: 1 | BW26: 579 | BX26: ШТ | BY26: 0 | CA26: 1 | CB26: 8403109000 | CE26: CN | CF26: 13179.9 | CG26: ОООО-ОО | CH26: 4000000 | CI26: 13179.9 | CJ26: 0 | CM26: 698493 | CN26: 7087539 | CO26: 0 | CP26: 1 | CQ26: 7266624.9 | CR26: 101878.9 | CS26: 10 | CT26: 7.7299 | CU26: 1075 | CV26: СПБ-А-072 | CX26: САВЧЕНКО ЮЛИЯ СТАНИСЛАВОВНА | CY26: 200
A27: 0 | B27: 44777 | C27: =IF(YEAR(Таблица1[[#This Row],[Дата]])=2023,MONTH(Таблица1[[#This Row],[Дата]]),0) -> 0 | D27: 10228010/281222/3423741 | E27: 10228010 | F27: 3423741 | G27: ИМ | H27: 40 | L27: RIMA ISI SISTEMLERI SAN.A.S. AS JUPITER PLUS CUSTOMS WAREHOUSE,LAO 13B,MAARDU 74114,ESTONIA | M27: ISTAMBUL, BASAKSEHIR,PK 34306, CADDE NO.10, IKITELLI OSB MAHALLESI, 25 | P27: 1 | Q27: 0 | R27: 1 | S27: 3 | T27: 1227800055845 | U27: 7804692788 | V27: ООО ЕТК | W27: 195221, Г.САНКТ-ПЕТЕРБУРГ,, ВН.ТЕР.Г. МУНИЦИПАЛЬНЫЙ ОКРУГ, ФИНЛЯНДСКИЙ ОКРУГ УЛ | X27: 40000 | Y27: 780401001 | Z27: 1227800055845 | AA27: 7804692788 | AB27: ООО ЕТК | AC27: 195221, Г.САНКТ-ПЕТЕРБУРГ,, ВН.ТЕР.Г. МУНИЦИПАЛЬНЫЙ ОКРУГ, ФИНЛЯНДСКИЙ ОКРУГ УЛ | AD27: 40000 | AE27: 780401001 | AF27: TR | AG27: ТУРЦИЯ | AH27: 2335756.8 | AI27: 1227800055845 | AJ27: 7804692788 | AK27: ООО ЕТК | AL27: 195221, Г.САНКТ-ПЕТЕРБУРГ,, ВН.ТЕР.Г. МУНИЦИПАЛЬНЫЙ ОКРУГ, ФИНЛЯНДСКИЙ ОКРУГ УЛ | AM27: 40000 | AN27: 780401001 | AO27: TR | AP27: ТУРЦИЯ | AQ27: ТУРЦИЯ | AR27: RU | AS27: РОССИЯ | AT27: 2 | AU27: 0 | AV27: EXW | AW27: ISTAMBUL | AX27: 1 | AY27: TRY | AZ27: 532800 | BA27: 1994515 | BB27: 33399.16 | BC27: 37.4346 | BD27: 010 | BE27: 10 | BG27: - | BH27: 11 | BI27: 10210/300413/10110/2 | BL27: ГОРОД САНКТ-ПЕТЕРБУРГ | BM27: ПОСЕЛОК ШУШУРЫ | BN27: УЛ.ПОСЕЛКОВАЯ, | BO27: 10210100 т/п Южный | BP27: 1 | BQ27: КОТЛЫ ГАЗОВЫЕ ОТОПИТЕЛЬНЫЕ, НЕ ВОЕННОГО НАЗНАЧЕНИЯ, ОБРАЗЦЫ ДЛЯ ЦЕЛЕЙ ПРОВЕДЕНИЯ ИСПЫТАНИЯ ПРОЦЕДУРЫ ДЕКЛАРИРОВАНИЯ СООТВЕТСТВИЯ, | BR27: =ISNUMBER(SEARCH($BR$1,Таблица1[[#This Row],[31_1 Описание и характеристика товара]]))*1 -> 0 | BT27: RIMA ISI SISTEMLERI SAN. A.S | BU27: 3 | BV27: 0 | BW27: 3 | BX27: ШТ | BY27: 0 | CA27: 1 | CB27: 8403109000 | CE27: TR | CF27: 1875 | CG27: ОООО-ОО | CH27: 4000064 | CI27: 1410 | CJ27: 0 | CM27: 532800 | CN27: 1994515 | CO27: 0 | CP27: 1 | CQ27: 2335756.8 | CR27: 33399.16 | CS27: 10 | CT27: 23.6873 | CU27: 1446 | CV27: Б/Н | CX27: КОЛПАКОВА АЛЕКСАНДРА СЕРГЕЕВНА | CY27: 44
A28: 1 | B28: 44574 | C28: =IF(YEAR(Таблица1[[#This Row],[Дата]])=2023,MONTH(Таблица1[[#This Row],[Дата]]),0) -> 0 | D28: 10228010/261222/5001301 | E28: 10228010 | F28: 5001301 | G28: ИМ | H28: 40 | L28: SUMEC MACHINERY AND ELECTRIC CO LTD | M28: , ., NANJING, CHANGJIANG ROAD 198, | P28: 2 | R28: 2 | S28: 535 | T28: 1027809170069 | U28: 7815012515 | V28: ООО ВОСХОД ПО ПОРУЧЕНИЮ ИМПОРТЕРА ООО ТОРГОВЫЙ ДОМ ТЕРМЕКС | W28: 191144, , Г. САНКТ-ПЕТЕРБУРГ, УЛ. НОВГОРОДСКАЯ, Д. 14, ЛИТЕР А, | X28: 40000 | Y28: 784201001 | Z28: 1094716001907 | AA28: 4716033195 | AB28: ООО ТОРГОВЫЙ ДОМ ТЕРМЕКС | AC28: 187002, ЛЕНИНГРАДСКАЯ ОБЛ., М.Р-Н ТОСНЕНСКИЙ, Г.П. ТОСНЕНС, Г.ТОСНО, МОСКОВСКОЕ | AD28: 41000 | AE28: 471601001 | AF28: CN | AG28: КИТАЙ | AH28: 7766209.4 | AI28: 1094716001907 | AJ28: 4716033195 | AK28: ООО ТОРГОВЫЙ ДОМ ТЕРМЕКС | AL28: 187002, ЛЕНИНГРАДСКАЯ ОБЛ., М.Р-Н ТОСНЕНСКИЙ, Г.П. ТОСНЕНС, Г.ТОСНО, МОСКОВСКОЕ | AM28: 41000 | AN28: 471601001 | AO28: CN | AP28: КИТАЙ | AQ28: КИТАЙ | AR28: RU | AS28: РОССИЯ | AT28: 1 | AU28: 1 | AV28: FCA | AW28: NANJING | AY28: CNY | AZ28: 770914.75 | BA28: 7503575 | BB28: 113084.77 | BC28: 97.5884 | BD28: 010 | BE28: 10 | BF28: 18120007/0436/0000/2/1 | BG28: - | BH28: 97 | BJ28: 10210000/130422/00004/4 | BL28: С-ПБ | BM28: ПОС.ШУШАРЫ | BN28: УЧ.Ж.Д МОСКОВСКОЕ ШОССЕ-РЕКА КУЗЬМИНКА | BO28: 10210130 т/п Шушарский | BP28: 1 | BQ28: КОТЛЫ ЭЛЕКТРИЧЕСКИЕ ОТОПИТЕЛЬНЫЕ ВОДОГРЕЙНЫЕ, НАСТЕННЫЕ, С ТЭНАМИ ВМОНТИРОВАННЫМИ В ТЕПЛООБМЕННИК ИЗ АЛЮМИНИЙ-МАГНИЕВОГО СПЛАВА, ДЛЯ СИСТЕМ ВОДЯНОГО ОТОПЛЕНИЯ И ГОРЯЧЕГО ВОДОСНАБЖЕНИЯ, ДЛЯ ИСПОЛЬЗОВАНИЯ В БЫТУ (НЕ ПРЕДНАЗНАЧЕНЫ ДЛЯ ПРОИЗВОДСТВА ПАРА, | BR28: =ISNUMBER(SEARCH($BR$1,Таблица1[[#This Row],[31_1 Описание и характеристика товара]]))*1 -> 0 | BT28: THERMEX HEATING TECHNOLOGY (JIANGMEN) CO., LTD | BU28: 485 | BV28: 1 | BW28: 485 | BX28: ШТ | CA28: 1 | CB28: 8403109000 | CE28: CN | CF28: 10427.5 | CG28: ОООО-ОО | CH28: 4000000 | CI28: 10427.5 | CM28: 697114.75 | CN28: 6785255 | CO28: 0 | CP28: 1 | CQ28: 7030117.4 | CR28: 102366.44 | CS28: 10 | CT28: 9.817 | CU28: 1075 | CV28: СПБ-А-072 | CX28: ТИХОНОВ АНДРЕЙ ВЛАДИМИРОВИЧ | CY28: 82
A29: 1 | B29: 45229 | C29: =IF(YEAR(Таблица1[[#This Row],[Дата]])=2023,MONTH(Таблица1[[#This Row],[Дата]]),0) -> 10 | D29: 10228010/261222/3421030 | E29: 10228010 | F29: 3421030 | G29: ИМ | H29: 40 | L29: ARISTON SPA C/W LT LOGIC | M29: 60044, ., FABRIANO (AN), VIALE ARISTIDE MERLONI, 45, | P29: 1 | Q29: 0 | R29: 1 | S29: 667 | T29: 1024700561742 | U29: 4703066115 | V29: ООО АРИСТОН ТЕРМО РУСЬ | W29: 188676, ЛЕНИНГРАДСКАЯ ОБЛ., ВСЕВОЛОЖСКИЙ Р-ОН,Г.ВСЕВОЛОЖСК, П.З.Г.ВСЕВОЛОЖСКА,УЛ | X29: 41000 | Y29: 470301001 | Z29: 1024700561742 | AA29: 4703066115 | AB29: ООО АРИСТОН ТЕРМО РУСЬ | AC29: 188676, ЛЕНИНГРАДСКАЯ ОБЛ., ВСЕВОЛОЖСКИЙ Р-ОН,Г.ВСЕВОЛОЖСК, П.З.Г.ВСЕВОЛОЖСКА,УЛ | AD29: 41000 | AE29: 470301001 | AF29: IT | AG29: ИТАЛИЯ | AH29: 15296818 | AI29: 1024700561742 | AJ29: 4703066115 | AK29: ООО АРИСТОН ТЕРМО РУСЬ | AL29: 188676, ЛЕНИНГРАДСКАЯ ОБЛ., ВСЕВОЛОЖСКИЙ Р-ОН,Г.ВСЕВОЛОЖСК, П.З.Г.ВСЕВОЛОЖСКА,УЛ | AM29: 41000 | AN29: 470301001 | AO29: IT | AP29: ИТАЛИЯ | AQ29: ИТАЛИЯ | AR29: RU | AS29: РОССИЯ | AT29: 2 | AU29: 0 | AV29: DAP | AW29: САНКТ-ПЕТЕРБУРГ | AX29: 1 | AY29: EUR | AZ29: 209428.69 | BA29: 15296818 | BB29: 222738.92 | BC29: 73.0407 | BD29: 010 | BF29: 16020015/3290/0001/2/1 | BG29: - | BH29: 99 | BJ29: 1174 | BL29: Г. САНКТ-ПЕТЕРБУРГ | BM29: ПОС. ПАРГОЛОВО | BN29: ГОРСКОЕ ШОССЕ, Д.4, ЛИТ.А | BO29: 10210350 т/п Парголовский | BP29: 1 | BQ29: КОТЛЫ ГАЗОВЫЕ ОТОПИТЕЛЬНЫЕ ВОДОГРЕЙНЫЕ СО ВСТРОЕННОЙ ГОРЕЛКОЙ, В КОРПУСЕ ИЗ СТАЛИ, НЕЛИТЫЕ, МОЩНОСТЬЮ МЕНЕЕ 100 КВТ, МАРКИ ARISTON (В ПЕРВИЧНОЙ УПАКОВКЕ) | BR29: =ISNUMBER(SEARCH($BR$1,Таблица1[[#This Row],[31_1 Описание и характеристика товара]]))*1 -> 0 | BT29: ARISTON S.P.A. | BU29: 667 | BV29: 0 | BW29: 667 | BX29: ШТ | BY29: 0 | CA29: 1 | CB29: 8403109000 | CE29: IT | CF29: 19944.8 | CG29: ОООО-ОО | CH29: 4000000 | CI29: 19944.8 | CJ29: 0 | CM29: 209428.69 | CN29: 15296818 | CO29: 0 | CP29: 1 | CQ29: 15296818 | CR29: 222738.92 | CS29: 10 | CT29: 11.1678 | CU29: 53 | CV29: 0053/03-15-005 | CX29: ВЕРШКОВА МАРИНА ЕВГЕНЬЕВНА | CY29: 0
A30: 0 | B30: 45135 | C30: =IF(YEAR(Таблица1[[#This Row],[Дата]])=2023,MONTH(Таблица1[[#This Row],[Дата]]),0) -> 7 | D30: 10228010/251222/3420314 | E30: 10228010 | F30: 3420314 | G30: ИМ | H30: 40 | L30: SUMEC MACHINERY AND ELECTRIC CO LTD | M30: , ., NANJING, CHANGJIANG ROAD 198, | P30: 2 | Q30: 0 | R30: 2 | S30: 535 | T30: 1027809170069 | U30: 7815012515 | V30: ООО ВОСХОД ПО ПОРУЧЕНИЮ ИМПОРТЕРА ООО ТОРГОВЫЙ ДОМ ТЕРМЕКС | W30: 191144, , Г. САНКТ-ПЕТЕРБУРГ, УЛ. НОВГОРОДСКАЯ, Д. 14, ЛИТЕР А, | X30: 40000 | Y30: 784201001 | Z30: 1094716001907 | AA30: 4716033195 | AB30: ООО ТОРГОВЫЙ ДОМ ТЕРМЕКС | AC30: 187002, ЛЕНИНГРАДСКАЯ ОБЛ., М.Р-Н ТОСНЕНСКИЙ, Г.П. ТОСНЕНС, Г.ТОСНО, МОСКОВСКОЕ | AD30: 41000 | AE30: 471601001 | AF30: CN | AG30: КИТАЙ | AH30: 7766209.4 | AI30: 1094716001907 | AJ30: 4716033195 | AK30: ООО ТОРГОВЫЙ ДОМ ТЕРМЕКС | AL30: 187002, ЛЕНИНГРАДСКАЯ ОБЛ., М.Р-Н ТОСНЕНСКИЙ, Г.П. ТОСНЕНС, Г.ТОСНО, МОСКОВСКОЕ | AM30: 41000 | AN30: 471601001 | AO30: CN | AP30: КИТАЙ | AQ30: КИТАЙ | AR30: RU | AS30: РОССИЯ | AT30: 1 | AU30: 1 | AV30: FCA | AW30: NANJING | AX30: 0 | AY30: CNY | AZ30: 770914.75 | BA30: 7523234 | BB30: 113084.77 | BC30: 97.5884 | BD30: 010 | BE30: 10 | BF30: 18120007/0436/0000/2/1 | BG30: - | BH30: 97 | BJ30: 10210000/130422/00004/4 | BL30: С-ПБ | BM30: ПОС.ШУШАРЫ | BN30: УЧ.Ж.Д МОСКОВСКОЕ ШОССЕ-РЕКА КУЗЬМИНКА | BO30: 10210130 т/п Шушарский | BP30: 1 | BQ30: КОТЛЫ ЭЛЕКТРИЧЕСКИЕ ОТОПИТЕЛЬНЫЕ ВОДОГРЕЙНЫЕ, НАСТЕННЫЕ, С ТЭНАМИ ВМОНТИРОВАННЫМИ В ТЕПЛООБМЕННИК ИЗ АЛЮМИНИЙ-МАГНИЕВОГО СПЛАВА, ДЛЯ СИСТЕМ ВОДЯНОГО ОТОПЛЕНИЯ И ГОРЯЧЕГО ВОДОСНАБЖЕНИЯ, ДЛЯ ИСПОЛЬЗОВАНИЯ В БЫТУ (НЕ ПРЕДНАЗНАЧЕНЫ ДЛЯ ПРОИЗВОДСТВА ПАРА, | BR30: =ISNUMBER(SEARCH($BR$1,Таблица1[[#This Row],[31_1 Описание и характеристика товара]]))*1 -> 0 | BT30: THERMEX HEATING TECHNOLOGY (JIANGMEN) CO., LTD | BU30: 485 | BV30: 1 | BW30: 485 | BX30: ШТ | BY30: 0 | CA30: 1 | CB30: 8403109000 | CE30: CN | CF30: 10427.5 | CG30: ОООО-ОО | CH30: 4000000 | CI30: 10427.5 | CJ30: 0 | CM30: 697114.75 | CN30: 7152397 | CP30: 1 | CQ30: 7030117.4 | CR30: 102366.44 | CS30: 90 | CT30: 9.817 | CU30: 1075 | CV30: СПБ-А-072 | CX30: ТИХОНОВ АНДРЕЙ ВЛАДИМИРОВИЧ | CY30: 175
A31: 1 | B31: 45003 | C31: =IF(YEAR(Таблица1[[#This Row],[Дата]])=2023,MONTH(Таблица1[[#This Row],[Дата]]),0) -> 3 | D31: 10228010/231222/3419018 | E31: 10228010 | F31: 3419018 | G31: ИМ | H31: 40 | L31: ARISTON SPA | M31: 60044, ., FABRIANO (AN), VIALE A. MERLONI, 45, | P31: 2 | Q31: 0 | R31: 2 | S31: 602 | T31: 1024700561742 | U31: 4703066115 | V31: ООО АРИСТОН ТЕРМО РУСЬ | W31: 188676, ЛЕНИНГРАДСКАЯ ОБЛ., ВСЕВОЛОЖСКИЙ Р-ОН,Г.ВСЕВОЛОЖСК, П.З.Г.ВСЕВОЛОЖСКА,УЛ | X31: 41000 | Y31: 470301001 | Z31: 1024700561742 | AA31: 4703066115 | AB31: ООО АРИСТОН ТЕРМО РУСЬ | AC31: 188676, ЛЕНИНГРАДСКАЯ ОБЛ., ВСЕВОЛОЖСКИЙ Р-ОН,Г.ВСЕВОЛОЖСК, П.З.Г.ВСЕВОЛОЖСКА,УЛ | AD31: 41000 | AE31: 470301001 | AF31: IT | AG31: ИТАЛИЯ | AH31: 15865610 | AI31: 1024700561742 | AJ31: 4703066115 | AK31: ООО АРИСТОН ТЕРМО РУСЬ | AL31: 188676, ЛЕНИНГРАДСКАЯ ОБЛ., ВСЕВОЛОЖСКИЙ Р-ОН,Г.ВСЕВОЛОЖСК, П.З.Г.ВСЕВОЛОЖСКА,УЛ | AM31: 41000 | AN31: 470301001 | AO31: IT | AP31: ИТАЛИЯ | AQ31: ИТАЛИЯ | AR31: RU | AS31: РОССИЯ | AT31: 2 | AU31: 0 | AV31: DAP | AW31: САНКТ-ПЕТЕРБУРГ | AX31: 1 | AY31: EUR | AZ31: 207002.32 | BA31: 15865610 | BB31: 219956.72 | BC31: 76.6446 | BD31: 010 | BF31: 16020015/3290/0001/2/1 | BG31: - | BH31: 99 | BJ31: 1174 | BL31: Г. САНКТ-ПЕТЕРБУРГ | BM31: ПОС. ПАРГОЛОВО | BN31: ГОРСКОЕ ШОССЕ, Д.4, ЛИТ.А | BO31: 10210350 т/п Парголовский | BP31: 1 | BQ31: КОТЛЫ ГАЗОВЫЕ ОТОПИТЕЛЬНЫЕ ВОДОГРЕЙНЫЕ СО ВСТРОЕННОЙ ГОРЕЛКОЙ, В КОРПУСЕ ИЗ СТАЛИ, НЕЛИТЫЕ, МОЩНОСТЬЮ МЕНЕЕ 100 КВТ, МАРКИ ARISTON (В ПЕРВИЧНОЙ УПАКОВКЕ) | BR31: =ISNUMBER(SEARCH($BR$1,Таблица1[[#This Row],[31_1 Описание и характеристика товара]]))*1 -> 0 | BT31: ARISTON S.P.A. | BU31: 600 | BV31: 0 | BW31: 600 | BX31: ШТ | BY31: 0 | CA31: 1 | CB31: 8403109000 | CE31: IT | CF31: 18609.2 | CG31: ОООО-ОО | CH31: 4000000 | CI31: 18609.2 | CJ31: 0 | CM31: 203660.87 | CN31: 15609506 | CO31: 0 | CP31: 1 | CQ31: 15609506 | CR31: 216406.16 | CS31: 10 | CT31: 11.629 | CU31: 53 | CV31: 0053/03-15-005 | CX31: ВЕРШКОВА МАРИНА ЕВГЕНЬЕВНА | CY31: 0
A32: 1 | B32: 45282 | C32: =IF(YEAR(Таблица1[[#This Row],[Дата]])=2023,MONTH(Таблица1[[#This Row],[Дата]]),0) -> 12 | D32: 10228010/221222/3417999 | E32: 10228010 | F32: 3417999 | G32: ИМ | H32: 40 | L32: THERMEX HEATING TECHNOLOGY (JIANGMEN) CO.,LTD | M32: , GUANGDONG PROVINCE, HESHAN CITY, TAOYUAN TOWN, JIANSHEDONGLU, NO. 51, | P32: 1 | Q32: 0 | R32: 1 | S32: 672 | T32: 1027809170069 | U32: 7815012515 | V32: ООО ВОСХОД ПО ПОРУЧЕНИЮ ООО ТОРГОВЫЙ ДОМ ТЕРМЕКС | W32: 191144, , Г. САНКТ-ПЕТЕРБУРГ, УЛ. НОВГОРОДСКАЯ, Д. 14, ЛИТЕР А, | X32: 40000 | Y32: 784201001 | Z32: 1094716001907 | AA32: 4716033195 | AB32: ООО ТОРГОВЫЙ ДОМ ТЕРМЕКС | AC32: 187002, ЛЕНИНГРАДСКАЯ ОБЛ., М.Р-Н ТОСНЕНСКИЙ, Г.П. ТОСНЕНС, Г.ТОСНО, МОСКОВСКОЕ | AD32: 41000 | AE32: 471601001 | AF32: CN | AG32: КИТАЙ | AH32: 8392053.3 | AI32: 1094716001907 | AJ32: 4716033195 | AK32: ООО ТОРГОВЫЙ ДОМ ТЕРМЕКС | AL32: 187002, ЛЕНИНГРАДСКАЯ ОБЛ., М.Р-Н ТОСНЕНСКИЙ, Г.П. ТОСНЕНС, Г.ТОСНО, МОСКОВСКОЕ | AM32: 41000 | AN32: 471601001 | AO32: CN | AP32: КИТАЙ | AQ32: КИТАЙ | AR32: RU | AS32: РОССИЯ | AT32: 1 | AU32: 1 | AV32: FCA | AW32: HESHAN | AX32: 0 | AY32: CNY | AZ32: 810636 | BA32: 8174129 | BB32: 118993.01 | BC32: 10.0836 | BD32: 010 | BE32: 10 | BF32: 20060023/2557/0001/2/1 | BG32: - | BH32: 97 | BJ32: 10210000/130422/00004/4 | BL32: С-ПБ | BM32: ПОС.ШУШАРЫ | BN32: УЧ.Ж.Д МОСКОВСКОЕ ШОССЕ-РЕКА КУЗЬМИНКА | BO32: 10210130 т/п Шушарский | BP32: 1 | BQ32: КОТЛЫ ЭЛЕКТРИЧЕСКИЕ ОТОПИТЕЛЬНЫЕ ВОДОГРЕЙНЫЕ, НАСТЕННЫЕ, ДЛЯ СИСТЕМ ВОДЯНОГО ОТОПЛЕНИЯ И ГОРЯЧЕГО ВОДОСНАБЖЕНИЯ, ДЛЯ ИСПОЛЬЗОВАНИЯ В БЫТУ (НЕ ИЗ ЧУГУННОГО ЛИТЬЯ, НЕ ПРЕДНАЗНАЧЕНЫ ДЛЯ ПРОИЗВОДСТВА ПАРА, НЕ ВОЕННОГО НАЗНАЧЕНИЯ) | BR32: =ISNUMBER(SEARCH($BR$1,Таблица1[[#This Row],[31_1 Описание и характеристика товара]]))*1 -> 0 | BT32: THERMEX HEATING TECHNOLOGY(JIANGMEN)CO.,LTD | BU32: 672 | BV32: 1 | BW32: 672 | BX32: ШТ | BY32: 0 | CA32: 1 | CB32: 8403109000 | CE32: CN | CF32: 15296.6 | CG32: ОООО-ОО | CH32: 4000000 | CI32: 15296.6 | CJ32: 0 | CM32: 810636 | CN32: 8174129 | CO32: 0 | CP32: 1 | CQ32: 8392053.3 | CR32: 118993.01 | CS32: 10 | CT32: 7.779 | CU32: 1075 | CV32: СПБ-А-072 | CX32: САВЧЕНКО ЮЛИЯ СТАНИСЛАВОВНА | CY32: 0
A33: 1 | B33: 45078 | C33: =IF(YEAR(Таблица1[[#This Row],[Дата]])=2023,MONTH(Таблица1[[#This Row],[Дата]]),0) -> 6 | D33: 10228010/221222/3417894 | E33: 10228010 | F33: 3417894 | G33: ИМ | H33: 40 | L33: THERMEX IKLIMLENDIRME VE ISITMA SISTEMLERI SANAYI TIC LTD. STI | M33: 35865, TORBALI, IZMIR, ORGANIZE SANAYI BOLGESI MAH. 7.CAD. NO.17/2, | P33: 2 | Q33: 0 | R33: 2 | S33: 116 | T33: 1107847406237 | U33: 7820323555 | V33: ООО ТЕРМЕКС ГАЗПРО | W33: 196105, Г., САНКТ-ПЕТЕРБУРГ, УЛ. КУЗНЕЦОВСКАЯ, Д.52, КОРПУС 22, ЛИТЕР Г, | X33: 40000 | Y33: 781001001 | Z33: 1107847406237 | AA33: 7820323555 | AB33: ООО ТЕРМЕКС ГАЗПРО | AC33: 196105, Г., САНКТ-ПЕТЕРБУРГ, УЛ. КУЗНЕЦОВСКАЯ, Д.52, КОРПУС 22, ЛИТЕР Г, | AD33: 40000 | AE33: 781001001 | AF33: TR | AG33: ТУРЦИЯ | AH33: 11282558 | AI33: 1107847406237 | AJ33: 7820323555 | AK33: ООО ТЕРМЕКС ГАЗПРО | AL33: 196105, Г., САНКТ-ПЕТЕРБУРГ, УЛ. КУЗНЕЦОВСКАЯ, Д.52, КОРПУС 22, ЛИТЕР Г, | AM33: 40000 | AN33: 781001001 | AO33: TR | AP33: ТУРЦИЯ | AQ33: ТУРЦИЯ | AR33: RU | AS33: РОССИЯ | AT33: 2 | AU33: 0 | AV33: FCA | AW33: IZMIR | AX33: 1 | AY33: EUR | AZ33: 145651 | BA33: 10937138 | BB33: 159978.2 | BC33: 75.0914 | BD33: 010 | BF33: 21070038/0436/0000/2/1 | BG33: - | BH33: 11 | BI33: 10102/091210/10039/3 | BL33: БРЯНСКАЯ ОБЛАСТЬ, Р-Н БРЯНСКИЙ | BM33: П. СВЕНЬ | BN33: УЛ. СОБОРНАЯ | BO33: 10102032 ОТО и ТК №2 т/п Брянский | BP33: 1 | BQ33: КОТЛЫ ГАЗОВЫЕ ОТОПИТЕЛЬНЫЕ ВОДОГРЕЙНЫЕ, НАСТЕННЫЕ, СТАЛЬНЫЕ, ДЛЯ СИСТЕМ ВОДЯНОГО ОТОПЛЕНИЯ И ГОРЯЧЕГО ВОДОСНАБЖЕНИЯ, ДЛЯ ИСПОЛЬЗОВАНИЯ В БЫТУ, МАТЕРИАЛ ТЕПЛООБМЕННИКА СТАЛЬ И АЛЮМИНИЙ (НЕ ПРЕДНАЗНАЧЕНЫ ДЛЯ ПРОИЗВОДСТВА ПАРА, НЕ ВОЕННОГО НАЗНАЧЕНИЯ) | BR33: =ISNUMBER(SEARCH($BR$1,Таблица1[[#This Row],[31_1 Описание и характеристика товара]]))*1 -> 0 | BT33: THERMEX IKLIMLENDIRME VE ISITMA SISTEMLERI SAN. VE TIC. LTD.STI. | BU33: 116 | BV33: 0 | BW33: 400 | BX33: ШТ | BY33: 0 | CA33: 1 | CB33: 8403109000 | CE33: TR | CF33: 13886.58 | CG33: ОООО-ОО | CH33: 4000000 | CI33: 13707 | CJ33: 0 | CM33: 141360 | CN33: 10614920 | CO33: 0 | CP33: 1 | CQ33: 10935626 | CR33: 155058.96 | CS33: 10 | CT33: 11.3124 | CU33: 1075 | CV33: СПБ-А-015 | CX33: САВЧЕНКО ЮЛИЯ СТАНИСЛАВОВНА | CY33: 200
A34: 1 | B34: 44989 | C34: =IF(YEAR(Таблица1[[#This Row],[Дата]])=2023,MONTH(Таблица1[[#This Row],[Дата]]),0) -> 3 | D34: 10228010/211222/3415975 | E34: 10228010 | F34: 3415975 | G34: ИМ | H34: 40 | L34: ARISTON THERMO S.P.A. | M34: 60044, ., FABRIANO (AN), VIALE A. MERLONI, 45, | P34: 4 | Q34: 0 | R34: 9 | S34: 53 | T34: 1024700561742 | U34: 4703066115 | V34: ООО АРИСТОН ТЕРМО РУСЬ | W34: 188676, ЛЕНИНГРАДСКАЯ ОБЛ., ВСЕВОЛОЖСКИЙ Р-ОН,Г.ВСЕВОЛОЖСК, П.З.Г.ВСЕВОЛОЖСКА,УЛ | X34: 41000 | Y34: 470301001 | Z34: 1024700561742 | AA34: 4703066115 | AB34: ООО АРИСТОН ТЕРМО РУСЬ | AC34: 188676, ЛЕНИНГРАДСКАЯ ОБЛ., ВСЕВОЛОЖСКИЙ Р-ОН,Г.ВСЕВОЛОЖСК, П.З.Г.ВСЕВОЛОЖСКА,УЛ | AD34: 41000 | AE34: 470301001 | AF34: IT | AG34: ИТАЛИЯ | AH34: 7416706.5 | AI34: 1024700561742 | AJ34: 4703066115 | AK34: ООО АРИСТОН ТЕРМО РУСЬ | AL34: 188676, ЛЕНИНГРАДСКАЯ ОБЛ., ВСЕВОЛОЖСКИЙ Р-ОН,Г.ВСЕВОЛОЖСК, П.З.Г.ВСЕВОЛОЖСКА,УЛ | AM34: 41000 | AN34: 470301001 | AO34: IT | AP34: ИТАЛИЯ | AQ34: НИДЕРЛАНДЫ | AR34: RU | AS34: РОССИЯ | AT34: 2 | AU34: 0 | AV34: DAP | AW34: САНКТ-ПЕТЕРБУРГ | AX34: 1 | AY34: EUR | AZ34: 101129.23 | BA34: 7416706 | BB34: 107482.72 | BC34: 73.3389 | BD34: 010 | BF34: 16020015/3290/0001/2/1 | BG34: - | BH34: 99 | BJ34: 1174 | BL34: Г. САНКТ-ПЕТЕРБУРГ | BM34: ПОС. ПАРГОЛОВО | BN34: ГОРСКОЕ ШОССЕ, Д.4, ЛИТ.А | BO34: 10210350 т/п Парголовский | BP34: 4 | BQ34: КОТЛЫ ГАЗОВЫЕ ОТОПИТЕЛЬНЫЕ ВОДОГРЕЙНЫЕ, В КОРПУСЕ ИЗ СТАЛИ, НЕЛИТЫЕ, МОЩНОСТЬЮ БОЛЕЕ 100 КВТ, МАРКИ ЕLСО (В ПЕРВИЧНОЙ УПАКОВКЕ) | BR34: =ISNUMBER(SEARCH($BR$1,Таблица1[[#This Row],[31_1 Описание и характеристика товара]]))*1 -> 0 | BT34: ATAG HEATING BV | BU34: 1 | BV34: 0 | BW34: 2 | BX34: ШТ | BY34: 0 | CA34: 8 | CB34: 8403109000 | CE34: NL | CF34: 260 | CG34: ОООО-ОО | CH34: 4000000 | CI34: 260 | CJ34: 0 | CM34: 4777.04 | CN34: 350343 | CO34: 0 | CP34: 1 | CQ34: 350342.86 | CR34: 5077.16 | CS34: 10 | CT34: 19.5275 | CU34: 53 | CV34: 0053/03-15-005 | CX34: СИНИЦИНА ОЛЬГА ЮРЬЕВНА | CY34: 0
A35: 1 | B35: 45024 | C35: =IF(YEAR(Таблица1[[#This Row],[Дата]])=2023,MONTH(Таблица1[[#This Row],[Дата]]),0) -> 4 | D35: 10228010/211222/3415975 | E35: 10228010 | F35: 3415975 | G35: ИМ | H35: 40 | L35: ARISTON THERMO S.P.A. | M35: 60044, ., FABRIANO (AN), VIALE A. MERLONI, 45, | P35: 4 | Q35: 0 | R35: 9 | S35: 53 | T35: 1024700561742 | U35: 4703066115 | V35: ООО АРИСТОН ТЕРМО РУСЬ | W35: 188676, ЛЕНИНГРАДСКАЯ ОБЛ., ВСЕВОЛОЖСКИЙ Р-ОН,Г.ВСЕВОЛОЖСК, П.З.Г.ВСЕВОЛОЖСКА,УЛ | X35: 41000 | Y35: 470301001 | Z35: 1024700561742 | AA35: 4703066115 | AB35: ООО АРИСТОН ТЕРМО РУСЬ | AC35: 188676, ЛЕНИНГРАДСКАЯ ОБЛ., ВСЕВОЛОЖСКИЙ Р-ОН,Г.ВСЕВОЛОЖСК, П.З.Г.ВСЕВОЛОЖСКА,УЛ | AD35: 41000 | AE35: 470301001 | AF35: IT | AG35: ИТАЛИЯ | AH35: 7416706.5 | AI35: 1024700561742 | AJ35: 4703066115 | AK35: ООО АРИСТОН ТЕРМО РУСЬ | AL35: 188676, ЛЕНИНГРАДСКАЯ ОБЛ., ВСЕВОЛОЖСКИЙ Р-ОН,Г.ВСЕВОЛОЖСК, П.З.Г.ВСЕВОЛОЖСКА,УЛ | AM35: 41000 | AN35: 470301001 | AO35: IT | AP35: ИТАЛИЯ | AQ35: ИТАЛИЯ | AR35: RU | AS35: РОССИЯ | AT35: 2 | AU35: 0 | AV35: DAP | AW35: САНКТ-ПЕТЕРБУРГ | AX35: 1 | AY35: EUR | AZ35: 101129.23 | BA35: 7416706 | BB35: 107482.72 | BC35: 73.3389 | BD35: 010 | BF35: 16020015/3290/0001/2/1 | BG35: - | BH35: 99 | BJ35: 1174 | BL35: Г. САНКТ-ПЕТЕРБУРГ | BM35: ПОС. ПАРГОЛОВО | BN35: ГОРСКОЕ ШОССЕ, Д.4, ЛИТ.А | BO35: 10210350 т/п Парголовский | BP35: 1 | BQ35: КОТЛЫ КОНДЕНСАЦИОННЫЕ ОТОПИТЕЛЬНЫЕ ВОДОГРЕЙНЫЕ ГАЗОВЫЕ СО ВСТРОЕННОЙ ГОРЕЛКОЙ, В КОРПУСЕ ИЗ СТАЛИ, НЕЛИТЫЕ, МОЩНОСТЬЮ СВЫШЕ 100 КВТ, МАРКИ ELCO | BR35: =ISNUMBER(SEARCH($BR$1,Таблица1[[#This Row],[31_1 Описание и характеристика товара]]))*1 -> 0 | BT35: ARISTON S.P.A. | BU35: 5 | BV35: 0 | BW35: 5 | BX35: ШТ | BY35: 0 | CA35: 1 | CB35: 8403109000 | CE35: IT | CF35: 3529 | CG35: ОООО-ОО | CH35: 4000000 | CI35: 3375 | CJ35: 0 | CM35: 52413.64 | CN35: 3843959 | CO35: 0 | CP35: 1 | CQ35: 3843958.7 | CR35: 55706.56 | CS35: 10 | CT35: 16.5056 | CU35: 53 | CV35: 0053/03-15-005 | CX35: СИНИЦИНА ОЛЬГА ЮРЬЕВНА | CY35: 0
A36: 1 | B36: 45132 | C36: =IF(YEAR(Таблица1[[#This Row],[Дата]])=2023,MONTH(Таблица1[[#This Row],[Дата]]),0) -> 7 | D36: 10228010/211222/3415975 | E36: 10228010 | F36: 3415975 | G36: ИМ | H36: 40 | L36: ARISTON THERMO S.P.A. | M36: 60044, ., FABRIANO (AN), VIALE A. MERLONI, 45, | P36: 4 | Q36: 0 | R36: 9 | S36: 53 | T36: 1024700561742 | U36: 4703066115 | V36: ООО АРИСТОН ТЕРМО РУСЬ | W36: 188676, ЛЕНИНГРАДСКАЯ ОБЛ., ВСЕВОЛОЖСКИЙ Р-ОН,Г.ВСЕВОЛОЖСК, П.З.Г.ВСЕВОЛОЖСКА,УЛ | X36: 41000 | Y36: 470301001 | Z36: 1024700561742 | AA36: 4703066115 | AB36: ООО АРИСТОН ТЕРМО РУСЬ | AC36: 188676, ЛЕНИНГРАДСКАЯ ОБЛ., ВСЕВОЛОЖСКИЙ Р-ОН,Г.ВСЕВОЛОЖСК, П.З.Г.ВСЕВОЛОЖСКА,УЛ | AD36: 41000 | AE36: 470301001 | AF36: IT | AG36: ИТАЛИЯ | AH36: 7416706.5 | AI36: 1024700561742 | AJ36: 4703066115 | AK36: ООО АРИСТОН ТЕРМО РУСЬ | AL36: 188676, ЛЕНИНГРАДСКАЯ ОБЛ., ВСЕВОЛОЖСКИЙ Р-ОН,Г.ВСЕВОЛОЖСК, П.З.Г.ВСЕВОЛОЖСКА,УЛ | AM36: 41000 | AN36: 470301001 | AO36: IT | AP36: ИТАЛИЯ | AQ36: ИТАЛИЯ | AR36: RU | AS36: РОССИЯ | AT36: 2 | AU36: 0 | AV36: DAP | AW36: САНКТ-ПЕТЕРБУРГ | AX36: 1 | AY36: EUR | AZ36: 101129.23 | BA36: 7416706 | BB36: 107482.72 | BC36: 73.3389 | BD36: 010 | BF36: 16020015/3290/0001/2/1 | BG36: - | BH36: 99 | BJ36: 1174 | BL36: Г. САНКТ-ПЕТЕРБУРГ | BM36: ПОС. ПАРГОЛОВО | BN36: ГОРСКОЕ ШОССЕ, Д.4, ЛИТ.А | BO36: 10210350 т/п Парголовский | BP36: 2 | BQ36: КОТЛЫ ОТОПИТЕЛЬНЫЕ ВОДОГРЕЙНЫЕ ГАЗОВЫЕ, В КОРПУСЕ ИЗ СТАЛИ, НЕЛИТОЙ, МОЩНОСТЬЮ МЕНЕЕ/БОЛЕЕ 100 КВТ, МАРКИ ARISTON (В ПЕРВИЧНОЙ УПАКОВКЕ) | BR36: =ISNUMBER(SEARCH($BR$1,Таблица1[[#This Row],[31_1 Описание и характеристика товара]]))*1 -> 0 | BT36: ARISTON S.P.A. | BU36: 8 | BV36: 0 | BW36: 14 | BX36: ШТ | BY36: 0 | CA36: 2 | CB36: 8403109000 | CE36: IT | CF36: 1540 | CG36: ОООО-ОО | CH36: 4000000 | CI36: 1540 | CJ36: 0 | CM36: 35032.91 | CN36: 2569275 | CO36: 0 | CP36: 1 | CQ36: 2569275.1 | CR36: 37233.87 | CS36: 10 | CT36: 24.1778 | CU36: 53 | CV36: 0053/03-15-005 | CX36: СИНИЦИНА ОЛЬГА ЮРЬЕВНА | CY36: 0
A37: 1 | B37: 45181 | C37: =IF(YEAR(Таблица1[[#This Row],[Дата]])=2023,MONTH(Таблица1[[#This Row],[Дата]]),0) -> 9 | D37: 10228010/211222/3415856 | E37: 10228010 | F37: 3415856 | G37: ИМ | H37: 40 | L37: ARISTON SPA C/W LT LOGIS VILNIUS,LITHUANIA, NEMEZIO SEN | M37: 60044, ., FABRIANO (AN), VIALE A. MERLONI, 45, | P37: 4 | Q37: 0 | R37: 10 | S37: 360 | T37: 1024700561742 | U37: 4703066115 | V37: ООО АРИСТОН ТЕРМО РУСЬ | W37: 188676, ЛЕНИНГРАДСКАЯ ОБЛ., ВСЕВОЛОЖСКИЙ Р-ОН,Г.ВСЕВОЛОЖСК, П.З.Г.ВСЕВОЛОЖСКА,УЛ | X37: 41000 | Y37: 470301001 | Z37: 1024700561742 | AA37: 4703066115 | AB37: ООО АРИСТОН ТЕРМО РУСЬ | AC37: 188676, ЛЕНИНГРАДСКАЯ ОБЛ., ВСЕВОЛОЖСКИЙ Р-ОН,Г.ВСЕВОЛОЖСК, П.З.Г.ВСЕВОЛОЖСКА,УЛ | AD37: 41000 | AE37: 470301001 | AF37: IT | AG37: ИТАЛИЯ | AH37: 10762488 | AI37: 1024700561742 | AJ37: 4703066115 | AK37: ООО АРИСТОН ТЕРМО РУСЬ | AL37: 188676, ЛЕНИНГРАДСКАЯ ОБЛ., ВСЕВОЛОЖСКИЙ Р-ОН,Г.ВСЕВОЛОЖСК, П.З.Г.ВСЕВОЛОЖСКА,УЛ | AM37: 41000 | AN37: 470301001 | AO37: LT | AP37: ЛИТВА | AQ37: ИТАЛИЯ | AR37: RU | AS37: РОССИЯ | AT37: 2 | AU37: 0 | AV37: DAP | AW37: САНКТ-ПЕТЕРБУРГ | AX37: 1 | AY37: EUR | AZ37: 146750.06 | BA37: 10762488 | BB37: 155969.71 | BC37: 73.3389 | BD37: 010 | BF37: 16020015/3290/0001/2/1 | BG37: - | BH37: 99 | BJ37: 1174 | BL37: Г. САНКТ-ПЕТЕРБУРГ | BM37: ПОС. ПАРГОЛОВО | BN37: ГОРСКОЕ ШОССЕ, Д.4, ЛИТ.А | BO37: 10210350 т/п Парголовский | BP37: 1 | BQ37: КОТЛЫ ГАЗОВЫЕ ОТОПИТЕЛЬНЫЕ ВОДОГРЕЙНЫЕ СО ВСТРОЕННОЙ ГОРЕЛКОЙ, В КОРПУСЕ ИЗ СТАЛИ, НЕЛИТЫЕ, МОЩНОСТЬЮ МЕНЕЕ 100 КВТ, МАРКИ ARISTON (В ПЕРВИЧНОЙ УПАКОВКЕ) | BR37: =ISNUMBER(SEARCH($BR$1,Таблица1[[#This Row],[31_1 Описание и характеристика товара]]))*1 -> 0 | BT37: ARISTON S.P.A. | BU37: 328 | BV37: 0 | BW37: 328 | BX37: ШТ | BY37: 0 | CA37: 1 | CB37: 8403109000 | CE37: IT | CF37: 9807.3 | CG37: ОООО-ОО | CH37: 4000000 | CI37: 9807.3 | CJ37: 0 | CM37: 114186.64 | CN37: 8374323 | CO37: 0 | CP37: 1 | CQ37: 8374322.6 | CR37: 121360.49 | CS37: 10 | CT37: 12.3745 | CU37: 53 | CV37: 0053/03-15-005 | CX37: ВЕРШКОВА МАРИНА ЕВГЕНЬЕВНА | CY37: 0
A38: 1 | B38: 44961 | C38: =IF(YEAR(Таблица1[[#This Row],[Дата]])=2023,MONTH(Таблица1[[#This Row],[Дата]]),0) -> 2 | D38: 10228010/181222/3412529 | E38: 10228010 | F38: 3412529 | G38: ИМ | H38: 40 | L38: ARISTON SPA | M38: 60044, ., FABRIANO (AN), VIALE A. MERLONI, 45, | P38: 2 | Q38: 0 | R38: 2 | S38: 501 | T38: 1024700561742 | U38: 4703066115 | V38: ООО АРИСТОН ТЕРМО РУСЬ | W38: 188676, ЛЕНИНГРАДСКАЯ ОБЛ., ВСЕВОЛОЖСКИЙ Р-ОН,Г.ВСЕВОЛОЖСК, П.З.Г.ВСЕВОЛОЖСКА,УЛ | X38: 41000 | Y38: 470301001 | Z38: 1024700561742 | AA38: 4703066115 | AB38: ООО АРИСТОН ТЕРМО РУСЬ | AC38: 188676, ЛЕНИНГРАДСКАЯ ОБЛ., ВСЕВОЛОЖСКИЙ Р-ОН,Г.ВСЕВОЛОЖСК, П.З.Г.ВСЕВОЛОЖСКА,УЛ | AD38: 41000 | AE38: 470301001 | AF38: IT | AG38: ИТАЛИЯ | AH38: 11840330 | AI38: 1024700561742 | AJ38: 4703066115 | AK38: ООО АРИСТОН ТЕРМО РУСЬ | AL38: 188676, ЛЕНИНГРАДСКАЯ ОБЛ., ВСЕВОЛОЖСКИЙ Р-ОН,Г.ВСЕВОЛОЖСК, П.З.Г.ВСЕВОЛОЖСКА,УЛ | AM38: 41000 | AN38: 470301001 | AO38: IT | AP38: ИТАЛИЯ | AQ38: ИТАЛИЯ | AR38: RU | AS38: РОССИЯ | AT38: 2 | AU38: 0 | AV38: DAP | AW38: САНКТ-ПЕТЕРБУРГ | AX38: 1 | AY38: EUR | AZ38: 172148.36 | BA38: 11840330 | BB38: 183264.71 | BC38: 68.7798 | BD38: 010 | BF38: 16020015/3290/0001/2/1 | BG38: - | BH38: 11 | BI38: 10210/110312/10115/5 | BK38: 194362 | BL38: Г. САНКТ-ПЕТЕРБУРГ | BM38: ПОС. ПАРГОЛОВО | BN38: ГОРСКОЕ ШОССЕ, Д.4, ЛИТ.А | BO38: 10210350 т/п Парголовский | BP38: 2 | BQ38: КОТЛЫ ГАЗОВЫЕ ОТОПИТЕЛЬНЫЕ ВОДОГРЕЙНЫЕ СО ВСТРОЕННОЙ ГОРЕЛКОЙ, В КОРПУСЕ ИЗ СТАЛИ, НЕЛИТЫЕ, МОЩНОСТЬЮ МЕНЕЕ 100 КВТ, МАРКИ ARISTON (В ПЕРВИЧНОЙ УПАКОВКЕ) | BR38: =ISNUMBER(SEARCH($BR$1,Таблица1[[#This Row],[31_1 Описание и характеристика товара]]))*1 -> 0 | BT38: ARISTON S.P.A. | BU38: 489 | BV38: 0 | BW38: 489 | BX38: ШТ | BY38: 0 | CA38: 2 | CB38: 8403109000 | CE38: IT | CF38: 14860 | CG38: ОООО-ОО | CH38: 4000000 | CI38: 14860 | CJ38: 0 | CM38: 160002.84 | CN38: 11004963 | CO38: 0 | CP38: 1 | CQ38: 11004963 | CR38: 170334.9 | CS38: 10 | CT38: 11.4626 | CU38: 53 | CV38: 0053/03-15-005 | CX38: ВЕРШКОВА МАРИНА ЕВГЕНЬЕВНА | CY38: 27
A39: 1 | B39: 45215 | C39: =IF(YEAR(Таблица1[[#This Row],[Дата]])=2023,MONTH(Таблица1[[#This Row],[Дата]]),0) -> 10 | D39: 10228010/161222/3411226 | E39: 10228010 | F39: 3411226 | G39: ИМ | H39: 40 | L39: RIMA ISI SISTEMLERI SAN. A.S. | M39: 34806, ISTANBUL, BASAKSEHIR, IKITELLI OSB MAHALESI 25.CADDE NO:10/A, | P39: 1 | Q39: 0 | R39: 1 | S39: 4 | T39: 1107847406237 | U39: 7820323555 | V39: ООО ТЕРМЕКС ГАЗПРО | W39: 196105, Г., САНКТ-ПЕТЕРБУРГ, УЛ. КУЗНЕЦОВСКАЯ, Д.52, КОРПУС 22, ЛИТЕР Г, | X39: 40000 | Y39: 781001001 | Z39: 1107847406237 | AA39: 7820323555 | AB39: ООО ТЕРМЕКС ГАЗПРО | AC39: 196105, Г., САНКТ-ПЕТЕРБУРГ, УЛ. КУЗНЕЦОВСКАЯ, Д.52, КОРПУС 22, ЛИТЕР Г, | AD39: 40000 | AE39: 781001001 | AF39: TR | AG39: ТУРЦИЯ | AH39: 1170030.1 | AI39: 1107847406237 | AJ39: 7820323555 | AK39: ООО ТЕРМЕКС ГАЗПРО | AL39: 196105, Г., САНКТ-ПЕТЕРБУРГ, УЛ. КУЗНЕЦОВСКАЯ, Д.52, КОРПУС 22, ЛИТЕР Г, | AM39: 40000 | AN39: 781001001 | AO39: TR | AP39: ТУРЦИЯ | AQ39: ТУРЦИЯ | AR39: RU | AS39: РОССИЯ | AT39: 1 | AU39: 0 | AV39: EXW | AW39: ISTANBUL | AX39: 1 | AY39: USD | AZ39: 15096 | BA39: 970695 | BB39: 18196 | BC39: 64.3015 | BD39: 010 | BF39: 22040530/0436/0000/2/1 | BG39: - | BH39: 11 | BI39: 10102/091210/10039/3 | BL39: БРЯНСКАЯ ОБЛАСТЬ, Р-Н БРЯНСКИЙ | BM39: П. СВЕНЬ | BN39: УЛ. СОБОРНАЯ | BO39: 10102032 ОТО и ТК №2 т/п Брянский | BP39: 1 | BQ39: КОТЛЫ ГАЗОВЫЕ ОТОПИТЕЛЬНЫЕ ВОДОГРЕЙНЫЕ, ДЛЯ СИСТЕМ ВОДЯНОГО ОТОПЛЕНИЯ И ГОРЯЧЕГО ВОДОСНАБЖЕНИЯ (НЕ ИЗ ЧУГУННОГО ЛИТЬЯ, НЕ ПРЕДНАЗНАЧЕНЫ ДЛЯ ПРОИЗВОДСТВА ПАРА, НЕ ВОЕННОГО НАЗНАЧЕНИЯ) | BR39: =ISNUMBER(SEARCH($BR$1,Таблица1[[#This Row],[31_1 Описание и характеристика товара]]))*1 -> 0 | BT39: RIMA ISI SISTEMLERI SAN.TIC.A.S. | BU39: 4 | BV39: 0 | BW39: 4 | BX39: ШТ | BY39: 0 | CA39: 1 | CB39: 8403109000 | CE39: TR | CF39: 1300 | CG39: ОООО-ОО | CH39: 4000000 | CI39: 1200 | CJ39: 0 | CM39: 15096 | CN39: 970695 | CO39: 0 | CP39: 1 | CQ39: 1170030.1 | CR39: 18196 | CS39: 10 | CT39: 15.1633 | CU39: 1075 | CV39: СПБ-А-015 | CX39: КОРНОУХОВА ТАТЬЯНА СЕРГЕЕВНА | CY39: 0
A40: 1 | B40: 45060 | C40: =IF(YEAR(Таблица1[[#This Row],[Дата]])=2023,MONTH(Таблица1[[#This Row],[Дата]]),0) -> 5 | D40: 10228010/050223/3028595 | E40: 10228010 | F40: 3028595 | G40: ИМ | H40: 40 | L40: KATOEN NATIE CUSTOMS SERVICES | M40: 2060, , ANTWERPEN, VAN AERDTSTRAAT, 33 | P40: 1 | Q40: 0 | R40: 1 | S40: 27 | T40: 1137847143664 | U40: 7805619300 | V40: ООО "РАДИУС" | W40: 198095, РОССИЯ, САНКТ-ПЕТЕРБУРГ, МАРШАЛА ГОВОРОВА, Д.35, КОРП.4,ЛИТ.И, ОФ.607, | X40: 40000 | Y40: 780501001 | Z40: 1137847143664 | AA40: 7805619300 | AB40: ООО "РАДИУС" | AC40: 198095, РОССИЯ, САНКТ-ПЕТЕРБУРГ, МАРШАЛА ГОВОРОВА, Д.35, КОРП.4,ЛИТ.И, ОФ.607, | AD40: 40000 | AE40: 780501001 | AF40: GB | AG40: СОЕДИНЕННОЕ КОРОЛЕВСТВО | AH40: 2443275 | AI40: 1137847143664 | AJ40: 7805619300 | AK40: ООО "РАДИУС" | AL40: 198095, РОССИЯ, САНКТ-ПЕТЕРБУРГ, МАРШАЛА ГОВОРОВА, Д.35, КОРП.4,ЛИТ.И, ОФ.607, | AM40: 40000 | AN40: 780501001 | AO40: BE | AP40: БЕЛЬГИЯ | AQ40: ФРАНЦИЯ | AR40: RU | AS40: РОССИЯ | AT40: 2 | AU40: 1 | AV40: EXW | AW40: GHENT | AX40: 1 | AY40: EUR | AZ40: 29190.6 | BA40: 2239923 | BB40: 34713.16 | BC40: 76.7344 | BD40: 010 | BE40: 31 | BF40: 15120013/0052/0000/2/1 | BG40: - | BH40: 99 | BJ40: 1237 | BL40: РОССИЯ | BM40: Г. КРОНШТАДТ | BN40: КРОНШТАДТСКОЕ ШОССЕ, Д.33, ЛИТ. А | BO40: 10210040 т/п Котлинский | BP40: 1 | BQ40: СУХОЙ КОРМ ДЛЯ КОШЕК Т.М. "APPLAWS", РAСФАСОВАННЫЙ ДЛЯ РОЗНИЧНОЙ ПРОДАЖИ В ИНДИВИДУАЛЬНУЮ УПАКОВКУ, СОДЕРЖИТ МЕНЕЕ 10% КРАХМАЛА, НЕ СОДЕРЖИТ МОЛОЧНЫЕ ПРОДУКТЫ | BR40: =ISNUMBER(SEARCH($BR$1,Таблица1[[#This Row],[31_1 Описание и характеристика товара]]))*1 -> 1 | BT40: UNITED PETFOOD FRANCE-UPF | BU40: 27 | BV40: 1 | BW40: 0 | BY40: 0 | CA40: 1 | CB40: 2309101100 | CE40: FR | CF40: 10395 | CG40: ОООО-ОО | CH40: 4000000 | CI40: 10053 | CJ40: 0 | CM40: 29190.6 | CN40: 2239923 | CO40: 0 | CP40: 1 | CQ40: 2443275 | CR40: 34713.16 | CS40: 10 | CT40: 34713.009 | CU40: 3.453 | CX40: НИКИФОРОВА ТАТЬЯНА ВАЛЕРЬЕВНА | CY40: 35
A41: 1 | B41: 45046 | C41: =IF(YEAR(Таблица1[[#This Row],[Дата]])=2023,MONTH(Таблица1[[#This Row],[Дата]]),0) -> 4 | D41: 10228010/050223/3028527 | E41: 10228010 | F41: 3028527 | G41: ИМ | H41: 40 | L41: KATOEN NATIE CUSTOMS SERVICES | M41: 2060, , ANTWERPEN, VAN AERDTSTRAAT, 33 | P41: 1 | Q41: 0 | R41: 1 | S41: 28 | T41: 1137847143664 | U41: 7805619300 | V41: ООО "РАДИУС" | W41: 198095, РОССИЯ, САНКТ-ПЕТЕРБУРГ, МАРШАЛА ГОВОРОВА, Д.35, КОРП.4,ЛИТ.И, ОФ.607, | X41: 40000 | Y41: 780501001 | Z41: 1137847143664 | AA41: 7805619300 | AB41: ООО "РАДИУС" | AC41: 198095, РОССИЯ, САНКТ-ПЕТЕРБУРГ, МАРШАЛА ГОВОРОВА, Д.35, КОРП.4,ЛИТ.И, ОФ.607, | AD41: 40000 | AE41: 780501001 | AF41: GB | AG41: СОЕДИНЕННОЕ КОРОЛЕВСТВО | AH41: 2400858.5 | AI41: 1137847143664 | AJ41: 7805619300 | AK41: ООО "РАДИУС" | AL41: 198095, РОССИЯ, САНКТ-ПЕТЕРБУРГ, МАРШАЛА ГОВОРОВА, Д.35, КОРП.4,ЛИТ.И, ОФ.607, | AM41: 40000 | AN41: 780501001 | AO41: BE | AP41: БЕЛЬГИЯ | AQ41: ФРАНЦИЯ | AR41: RU | AS41: РОССИЯ | AT41: 2 | AU41: 1 | AV41: EXW | AW41: GENT | AX41: 1 | AY41: EUR | AZ41: 28637.83 | BA41: 2197507 | BB41: 34110.52 | BC41: 76.7344 | BD41: 010 | BE41: 40 | BF41: 15120013/0052/0000/2/1 | BG41: - | BH41: 99 | BJ41: 1237 | BL41: РОССИЯ | BM41: Г. КРОНШТАДТ | BN41: КРОНШТАДТСКОЕ ШОССЕ, Д.33, ЛИТ. А | BO41: 10210040 т/п Котлинский | BP41: 1 | BQ41: СУХОЙ КОРМ ДЛЯ КОШЕК И СОБАК Т.М. "APPLAWS", РАСФАСОВАННЫЙ ДЛЯ РОЗНИЧНОЙ ПРОДАЖИ В ИНДИВИДУАЛЬНУЮ УПАКОВКУ,СОДЕРЖИТ МЕНЕЕ 10% КРАХМАЛА, НЕ СОДЕРЖИТ MОЛОЧНЫЕ ПРОДУКТЫ | BR41: =ISNUMBER(SEARCH($BR$1,Таблица1[[#This Row],[31_1 Описание и характеристика товара]]))*1 -> 1 | BT41: UNITED PETFOOD FRANCE-UPF | BU41: 28 | BV41: 1 | BW41: 0 | BY41: 0 | CA41: 1 | CB41: 2309101100 | CE41: FR | CF41: 11234.15 | CG41: ОООО-ОО | CH41: 4000000 | CI41: 10978.95 | CJ41: 0 | CM41: 28637.83 | CN41: 2197507 | CO41: 0 | CP41: 1 | CQ41: 2400858.5 | CR41: 34110.52 | CS41: 10 | CT41: 34110.5 | CU41: 3.1069 | CX41: НИКИФОРОВА ТАТЬЯНА ВАЛЕРЬЕВНА | CY41: 204
A42: 1 | B42: 45179 | C42: =IF(YEAR(Таблица1[[#This Row],[Дата]])=2023,MONTH(Таблица1[[#This Row],[Дата]]),0) -> 9 | D42: 10228010/050223/3028355 | E42: 10228010 | F42: 3028355 | G42: ИМ | H42: 40 | L42: KATOEN NATIE CUSTOMS SERVICES | M42: 2060, , ANTWERPEN, VAN AERDTSTRAAT, 33 | P42: 1 | Q42: 0 | R42: 1 | S42: 33 | T42: 1137847143664 | U42: 7805619300 | V42: ООО "РАДИУС" | W42: 198095, РОССИЯ, САНКТ-ПЕТЕРБУРГ, МАРШАЛА ГОВОРОВА, Д.35, КОРП.4,ЛИТ.И, ОФ.607, | X42: 40000 | Y42: 780501001 | Z42: 1137847143664 | AA42: 7805619300 | AB42: ООО "РАДИУС" | AC42: 198095, РОССИЯ, САНКТ-ПЕТЕРБУРГ, МАРШАЛА ГОВОРОВА, Д.35, КОРП.4,ЛИТ.И, ОФ.607, | AD42: 40000 | AE42: 780501001 | AF42: GB | AG42: СОЕДИНЕННОЕ КОРОЛЕВСТВО | AH42: 2707379.3 | AI42: 1137847143664 | AJ42: 7805619300 | AK42: ООО "РАДИУС" | AL42: 198095, РОССИЯ, САНКТ-ПЕТЕРБУРГ, МАРШАЛА ГОВОРОВА, Д.35, КОРП.4,ЛИТ.И, ОФ.607, | AM42: 40000 | AN42: 780501001 | AO42: BE | AP42: БЕЛЬГИЯ | AQ42: ФРАНЦИЯ | AR42: RU | AS42: РОССИЯ | AT42: 2 | AU42: 1 | AV42: EXW | AW42: GENT | AX42: 1 | AY42: EUR | AZ42: 32270.04 | BA42: 2476222 | BB42: 38465.45 | BC42: 76.7344 | BD42: 010 | BE42: 40 | BF42: 15120013/0052/0000/2/1 | BG42: - | BH42: 11 | BI42: 10210/101120/10128/2 | BL42: РОССИЯ | BM42: СПБ, Г.КРОНДШТАДТ | BN42: КРОНШТАДСКОЕ ШОССЕ,Д.33,ЛИТ.А | BO42: 10210040 т/п Котлинский | BP42: 1 | BQ42: СУХОЙ КОРМ ДЛЯ КОШЕК T.М. "APPLAWS", РАСФАСОВАНЫЙ ДЛЯ РОЗНИЧНОЙ ПРОДАЖИ В ИНДИВИДУАЛЬНУЮ УПАКОВКУ, СОДЕРЖИТ 10 МАС.% ИЛИ МЕНЕЕ КРАХМАЛА, НЕ СОДЕРЖИТ МОЛОЧНЫЕ ПРОДУКТЫ | BR42: =ISNUMBER(SEARCH($BR$1,Таблица1[[#This Row],[31_1 Описание и характеристика товара]]))*1 -> 1 | BT42: UNITED PETFOOD FRANCE-UPF | BU42: 33 | BV42: 1 | BW42: 0 | BY42: 0 | CA42: 1 | CB42: 2309101100 | CE42: FR | CF42: 12173.04 | CG42: ОООО-ОО | CH42: 4000000 | CI42: 11790.24 | CJ42: 0 | CM42: 32270.04 | CN42: 2476222 | CO42: 0 | CP42: 1 | CQ42: 2707379.3 | CR42: 38465.45 | CS42: 10 | CT42: 38465.658 | CU42: 3.2625 | CX42: НИКИФОРОВА ТАТЬЯНА ВАЛЕРЬЕВНА | CY42: 108
A43: 1 | B43: 44964 | C43: =IF(YEAR(Таблица1[[#This Row],[Дата]])=2023,MONTH(Таблица1[[#This Row],[Дата]]),0) -> 2 | D43: 10228010/040223/3028159 | E43: 10228010 | F43: 3028159 | G43: ИМ | H43: 40 | L43: KATOEN NATIE CUSTOMS SERVICES | M43: 2060, , ANTWERPEN, VAN AERDTSTRAAT, 33 | P43: 1 | Q43: 0 | R43: 1 | S43: 33 | T43: 1137847143664 | U43: 7805619300 | V43: ООО "РАДИУС" | W43: 198095, РОССИЯ, САНКТ-ПЕТЕРБУРГ, МАРШАЛА ГОВОРОВА, Д.35, КОРП.4,ЛИТ.И, ОФ.607, | X43: 40000 | Y43: 780501001 | Z43: 1137847143664 | AA43: 7805619300 | AB43: ООО "РАДИУС" | AC43: 198095, РОССИЯ, САНКТ-ПЕТЕРБУРГ, МАРШАЛА ГОВОРОВА, Д.35, КОРП.4,ЛИТ.И, ОФ.607, | AD43: 40000 | AE43: 780501001 | AF43: GB | AG43: СОЕДИНЕННОЕ КОРОЛЕВСТВО | AH43: 2455798.1 | AI43: 1137847143664 | AJ43: 7805619300 | AK43: ООО "РАДИУС" | AL43: 198095, РОССИЯ, САНКТ-ПЕТЕРБУРГ, МАРШАЛА ГОВОРОВА, Д.35, КОРП.4,ЛИТ.И, ОФ.607, | AM43: 40000 | AN43: 780501001 | AO43: BE | AP43: БЕЛЬГИЯ | AQ43: ФРАНЦИЯ | AR43: RU | AS43: РОССИЯ | AT43: 2 | AU43: 1 | AV43: EXW | AW43: GENT | AX43: 1 | AY43: EUR | AZ43: 29353.8 | BA43: 2252446 | BB43: 34891.08 | BC43: 76.7344 | BD43: 010 | BE43: 40 | BF43: 15120013/0052/0000/2/1 | BG43: - | BH43: 99 | BJ43: 1237 | BL43: РОССИЯ | BM43: Г. КРОНШТАДТ | BN43: КРОНШТАДТСКОЕ ШОССЕ, Д.33, ЛИТ. А | BO43: 10210040 т/п Котлинский | BP43: 1 | BQ43: СУХОЙ КОРМ ДЛЯ КОШЕК Т.М:"APPLAWS", РАСФАСОВАНЫЙ ДЛЯ РОЗНИЧНОЙ ПРОДАЖИ В ИНДИВИДУАЛЬНУЮ УПАКОВКУ, СОДЕРЖИТ 10 МАС.% ИЛИ МЕНЕЕ КРАХМАЛА, НЕ СОДЕРЖИТ МОЛОЧНЫЕ ПРОДУКТЫ | BR43: =ISNUMBER(SEARCH($BR$1,Таблица1[[#This Row],[31_1 Описание и характеристика товара]]))*1 -> 1 | BT43: UNITED PETFOOD FRANCE-UPF | BU43: 33 | BV43: 1 | BW43: 0 | BY43: 0 | CA43: 1 | CB43: 2309101100 | CE43: FR | CF43: 13311 | CG43: ОООО-ОО | CH43: 4000000 | CI43: 13311 | CJ43: 0 | CM43: 29353.8 | CN43: 2252446 | CO43: 0 | CP43: 1 | CQ43: 2455798.1 | CR43: 34891.08 | CS43: 10 | CT43: 34890.793 | CU43: 2.6212 | CX43: НИКИФОРОВА ТАТЬЯНА ВАЛЕРЬЕВНА | CY43: 44
A44: 1 | B44: 45174 | C44: =IF(YEAR(Таблица1[[#This Row],[Дата]])=2023,MONTH(Таблица1[[#This Row],[Дата]]),0) -> 9 | D44: 10228010/040223/3028125 | E44: 10228010 | F44: 3028125 | G44: ИМ | H44: 40 | L44: KATOEN NATIE CUSTOMS SERVICES | M44: 2060, , ANTWERPEN, VAN AERDTSTRAAT, 33 | P44: 1 | Q44: 0 | R44: 1 | S44: 33 | T44: 1137847143664 | U44: 7805619300 | V44: ООО "РАДИУС" | W44: 198095, РОССИЯ, САНКТ-ПЕТЕРБУРГ, МАРШАЛА ГОВОРОВА, Д.35, КОРП.4,ЛИТ.И, ОФ.607, | X44: 40000 | Y44: 780501001 | Z44: 1137847143664 | AA44: 7805619300 | AB44: ООО "РАДИУС" | AC44: 198095, РОССИЯ, САНКТ-ПЕТЕРБУРГ, МАРШАЛА ГОВОРОВА, Д.35, КОРП.4,ЛИТ.И, ОФ.607, | AD44: 40000 | AE44: 780501001 | AF44: GB | AG44: СОЕДИНЕННОЕ КОРОЛЕВСТВО | AH44: 2609711.9 | AI44: 1137847143664 | AJ44: 7805619300 | AK44: ООО "РАДИУС" | AL44: 198095, РОССИЯ, САНКТ-ПЕТЕРБУРГ, МАРШАЛА ГОВОРОВА, Д.35, КОРП.4,ЛИТ.И, ОФ.607, | AM44: 40000 | AN44: 780501001 | AO44: BE | AP44: БЕЛЬГИЯ | AQ44: ФРАНЦИЯ | AR44: RU | AS44: РОССИЯ | AT44: 2 | AU44: 1 | AV44: EXW | AW44: GENT | AX44: 1 | AY44: EUR | AZ44: 31359.6 | BA44: 2406360 | BB44: 37077.83 | BC44: 76.7344 | BD44: 010 | BE44: 40 | BF44: 15120013/0052/0000/2/1 | BG44: - | BH44: 99 | BJ44: 1237 | BL44: РОССИЯ | BM44: Г. КРОНШТАДТ | BN44: КРОНШТАДТСКОЕ ШОССЕ, Д.33, ЛИТ. А | BO44: 10210040 т/п Котлинский | BP44: 1 | BQ44: СУХОЙ КОРМ ДЛЯ КОШЕК Т.М. "APPLAWS", РАСФАСОВАНЫЙ ДЛЯ РОЗНИЧНОЙ ПРОДАЖИ В ИНДИВИДУАЛЬНУЮ УПАКОВКУ, СОДЕРЖИT 10 МАС.% ИЛИ МЕНЕЕ КРАХМАЛА, НЕ СОДЕРЖИТ МОЛОЧНЫЕ ПРОДУКТЫ | BR44: =ISNUMBER(SEARCH($BR$1,Таблица1[[#This Row],[31_1 Описание и характеристика товара]]))*1 -> 1 | BT44: UNITED PETFOOD FRANCE-UPF | BU44: 33 | BV44: 1 | BW44: 0 | BY44: 0 | CA44: 1 | CB44: 2309101100 | CE44: FR | CF44: 11829.6 | CG44: ОООО-ОО | CH44: 4000000 | CI44: 11457.6 | CJ44: 0 | CM44: 31359.6 | CN44: 2406360 | CO44: 0 | CP44: 1 | CQ44: 2609711.9 | CR44: 37077.83 | CS44: 10 | CT44: 37077.939 | CU44: 3.2361 | CX44: НИКИФОРОВА ТАТЬЯНА ВАЛЕРЬЕВНА | CY44: 200
A45: 1 | B45: 45208 | C45: =IF(YEAR(Таблица1[[#This Row],[Дата]])=2023,MONTH(Таблица1[[#This Row],[Дата]]),0) -> 10 | D45: 10131010/311222/3564316 | E45: 10131010 | F45: 3564316 | G45: ИМ | H45: 40 | L45: BDR THERMEA HVAC CO., LTD | M45: 314000, , JIAXING, NO. 2000 GUANGQIONG ROAD, | P45: 1 | Q45: 0 | R45: 1 | S45: 56 | T45: 1087746423005 | U45: 7717615508 | V45: ООО БДР ТЕРМИЯ РУС ЧЕРЕЗ АО ТАСКОМ | W45: 129164, , Г. МОСКВА, ПЕР. ЗУБАРЕВ, Д.15, КОРП.1, ЭТ. 3, ПОМ.1, КОМ. 67Г | X45: 45000 | Y45: 771701001 | Z45: 1087746423005 | AA45: 7717615508 | AB45: ООО БДР ТЕРМИЯ РУС | AC45: 129164, , Г. МОСКВА, ПЕР. ЗУБАРЕВ, Д.15, КОРП.1, ЭТ. 3, ПОМ.1, КОМ. 67Г | AD45: 45000 | AE45: 771701001 | AF45: CN | AG45: КИТАЙ | AH45: 7849865.4 | AI45: 1087746423005 | AJ45: 7717615508 | AK45: ООО БДР ТЕРМИЯ РУС | AL45: 129164, , Г. МОСКВА, ПЕР. ЗУБАРЕВ, Д.15, КОРП.1, ЭТ. 3, ПОМ.1, КОМ. 67Г | AM45: 45000 | AN45: 771701001 | AO45: CN | AP45: КИТАЙ | AQ45: КИТАЙ | AR45: RU | AS45: РОССИЯ | AT45: 1 | AU45: 1 | AV45: EXW | AW45: JIAXING | AX45: 0 | AY45: EUR | AZ45: 99667.32 | BA45: 7540361 | BB45: 111602.85 | BC45: 75.6553 | BD45: 010 | BE45: 40 | BF45: 22060044/0001/0000/2/1 | BG45: - | BH45: 11 | BI45: 10106/100913/10053/9 | BL45: КАЛУЖСКАЯ ОБЛ., БОРОВСКИЙ Р-Н | BM45: С. ВОРСИНО | BN45: СЕВЕРНАЯ ПРОМЗОНА, ВЛД. 6 | BO45: 10106050 т/п Обнинский | BP45: 1 | BQ45: КОТЛЫ ЦЕНТРАЛЬНОГО ОТОПЛЕНИЯ, СТАЛЬНЫЕ, АССОРТИМЕНТ | BR45: =ISNUMBER(SEARCH($BR$1,Таблица1[[#This Row],[31_1 Описание и характеристика товара]]))*1 -> 0 | BT45: BDR THERMEA HVAC CO., LTD | BU45: 56 | BV45: 1 | BW45: 388 | BX45: ШТ | BY45: 0 | CA45: 1 | CB45: 8403109000 | CE45: CN | CF45: 11524 | CG45: ОООО-ОО | CH45: 4000000 | CI45: 11252 | CJ45: 0 | CM45: 99667.32 | CN45: 7540361 | CO45: 0 | CP45: 1 | CQ45: 7849865.4 | CR45: 111602.85 | CS45: 10 | CT45: 9.9185 | CU45: 1053 | CV45: 0719/00-16-055 | CX45: БЫКОВА ЛЮБОВЬ АЛЕКСАНДРОВНА | CY45: 0
A46: 1 | B46: 45043 | C46: =IF(YEAR(Таблица1[[#This Row],[Дата]])=2023,MONTH(Таблица1[[#This Row],[Дата]]),0) -> 4 | D46: 10131010/311222/3564309 | E46: 10131010 | F46: 3564309 | G46: ИМ | H46: 40 | L46: BDR THERMEA HVAC CO., LTD | M46: 314000, , JIAXING, NO. 2000 GUANGQIONG ROAD, | P46: 1 | Q46: 0 | R46: 1 | S46: 52 | T46: 1087746423005 | U46: 7717615508 | V46: ООО БДР ТЕРМИЯ РУС ЧЕРЕЗ АО ТАСКОМ | W46: 129164, , Г. МОСКВА, ПЕР. ЗУБАРЕВ, Д.15, КОРП.1, ЭТ. 3, ПОМ.1, КОМ. 67Г | X46: 45000 | Y46: 771701001 | Z46: 1087746423005 | AA46: 7717615508 | AB46: ООО БДР ТЕРМИЯ РУС | AC46: 129164, , Г. МОСКВА, ПЕР. ЗУБАРЕВ, Д.15, КОРП.1, ЭТ. 3, ПОМ.1, КОМ. 67Г | AD46: 45000 | AE46: 771701001 | AF46: CN | AG46: КИТАЙ | AH46: 7107262.3 | AI46: 1087746423005 | AJ46: 7717615508 | AK46: ООО БДР ТЕРМИЯ РУС | AL46: 129164, , Г. МОСКВА, ПЕР. ЗУБАРЕВ, Д.15, КОРП.1, ЭТ. 3, ПОМ.1, КОМ. 67Г | AM46: 45000 | AN46: 771701001 | AO46: CN | AP46: КИТАЙ | AQ46: КИТАЙ | AR46: RU | AS46: РОССИЯ | AT46: 1 | AU46: 1 | AV46: EXW | AW46: JIAXING | AX46: 0 | AY46: EUR | AZ46: 89851.71 | BA46: 6797758 | BB46: 101045.14 | BC46: 75.6553 | BD46: 010 | BE46: 40 | BF46: 22060044/0001/0000/2/1 | BG46: - | BH46: 11 | BI46: 10106/100913/10053/9 | BL46: КАЛУЖСКАЯ ОБЛ., БОРОВСКИЙ Р-Н | BM46: С. ВОРСИНО | BN46: СЕВЕРНАЯ ПРОМЗОНА, ВЛД. 6 | BO46: 10106050 т/п Обнинский | BP46: 1 | BQ46: КОТЛЫ ЦЕНТРАЛЬНОГО ОТОПЛЕНИЯ, СТАЛЬНЫЕ, АССОРТИМЕНТ | BR46: =ISNUMBER(SEARCH($BR$1,Таблица1[[#This Row],[31_1 Описание и характеристика товара]]))*1 -> 0 | BT46: BDR THERMEA HVAC CO., LTD | BU46: 52 | BV46: 1 | BW46: 324 | BX46: ШТ | BY46: 0 | CA46: 1 | CB46: 8403109000 | CE46: CN | CF46: 10656 | CG46: ОООО-ОО | CH46: 4000000 | CI46: 10196 | CJ46: 0 | CM46: 89851.71 | CN46: 6797758 | CO46: 0 | CP46: 1 | CQ46: 7107262.3 | CR46: 101045.14 | CS46: 10 | CT46: 9.9103 | CU46: 1053 | CV46: 0719/00-16-055 | CX46: БЫКОВА ЛЮБОВЬ АЛЕКСАНДРОВНА | CY46: 0
A47: 1 | B47: 44985 | C47: =IF(YEAR(Таблица1[[#This Row],[Дата]])=2023,MONTH(Таблица1[[#This Row],[Дата]]),0) -> 2 | D47: 10131010/311222/3564308 | E47: 10131010 | F47: 3564308 | G47: ИМ | H47: 40 | L47: BDR THERMEA HVAC CO., LTD | M47: 314000, , JIAXING, NO. 2000 GUANGQIONG ROAD, | P47: 1 | Q47: 0 | R47: 1 | S47: 52 | T47: 1087746423005 | U47: 7717615508 | V47: ООО БДР ТЕРМИЯ РУС ЧЕРЕЗ АО ТАСКОМ | W47: 129164, , Г. МОСКВА, ПЕР. ЗУБАРЕВ, Д.15, КОРП.1, ЭТ. 3, ПОМ.1, КОМ. 67Г | X47: 45000 | Y47: 771701001 | Z47: 1087746423005 | AA47: 7717615508 | AB47: ООО БДР ТЕРМИЯ РУС | AC47: 129164, , Г. МОСКВА, ПЕР. ЗУБАРЕВ, Д.15, КОРП.1, ЭТ. 3, ПОМ.1, КОМ. 67Г | AD47: 45000 | AE47: 771701001 | AF47: CN | AG47: КИТАЙ | AH47: 6989252.8 | AI47: 1087746423005 | AJ47: 7717615508 | AK47: ООО БДР ТЕРМИЯ РУС | AL47: 129164, , Г. МОСКВА, ПЕР. ЗУБАРЕВ, Д.15, КОРП.1, ЭТ. 3, ПОМ.1, КОМ. 67Г | AM47: 45000 | AN47: 771701001 | AO47: CN | AP47: КИТАЙ | AQ47: КИТАЙ | AR47: RU | AS47: РОССИЯ | AT47: 1 | AU47: 1 | AV47: EXW | AW47: JIAXING | AX47: 0 | AY47: EUR | AZ47: 88291.87 | BA47: 6679748 | BB47: 99367.38 | BC47: 75.6553 | BD47: 010 | BE47: 40 | BF47: 22060044/0001/0000/2/1 | BG47: - | BH47: 11 | BI47: 10106/100913/10053/9 | BL47: КАЛУЖСКАЯ ОБЛ., БОРОВСКИЙ Р-Н | BM47: С. ВОРСИНО | BN47: СЕВЕРНАЯ ПРОМЗОНА, ВЛД. 6 | BO47: 10106050 т/п Обнинский | BP47: 1 | BQ47: КОТЛЫ ЦЕНТРАЛЬНОГО ОТОПЛЕНИЯ, СТАЛЬНЫЕ, АССОРТИМЕНТ | BR47: =ISNUMBER(SEARCH($BR$1,Таблица1[[#This Row],[31_1 Описание и характеристика товара]]))*1 -> 0 | BT47: BDR THERMEA HVAC CO., LTD | BU47: 52 | BV47: 1 | BW47: 308 | BX47: ШТ | BY47: 0 | CA47: 1 | CB47: 8403109000 | CE47: CN | CF47: 10592 | CG47: ОООО-ОО | CH47: 4000000 | CI47: 10032 | CJ47: 0 | CM47: 88291.87 | CN47: 6679748 | CO47: 0 | CP47: 1 | CQ47: 6989252.8 | CR47: 99367.38 | CS47: 10 | CT47: 9.905 | CU47: 1053 | CV47: 0719/00-16-055 | CX47: БЫКОВА ЛЮБОВЬ АЛЕКСАНДРОВНА | CY47: 0
A48: 1 | B48: 45115 | C48: =IF(YEAR(Таблица1[[#This Row],[Дата]])=2023,MONTH(Таблица1[[#This Row],[Дата]]),0) -> 7 | D48: 10131010/311222/3564307 | E48: 10131010 | F48: 3564307 | G48: ИМ | H48: 40 | L48: BDR THERMEA HVAC CO., LTD | M48: 314000, , JIAXING, NO. 2000 GUANGQIONG ROAD, | P48: 1 | Q48: 0 | R48: 1 | S48: 56 | T48: 1087746423005 | U48: 7717615508 | V48: ООО БДР ТЕРМИЯ РУС ЧЕРЕЗ АО ТАСКОМ | W48: 129164, , Г. МОСКВА, ПЕР. ЗУБАРЕВ, Д.15, КОРП.1, ЭТ. 3, ПОМ.1, КОМ. 67Г | X48: 45000 | Y48: 771701001 | Z48: 1087746423005 | AA48: 7717615508 | AB48: ООО БДР ТЕРМИЯ РУС | AC48: 129164, , Г. МОСКВА, ПЕР. ЗУБАРЕВ, Д.15, КОРП.1, ЭТ. 3, ПОМ.1, КОМ. 67Г | AD48: 45000 | AE48: 771701001 | AF48: CN | AG48: КИТАЙ | AH48: 7849865.4 | AI48: 1087746423005 | AJ48: 7717615508 | AK48: ООО БДР ТЕРМИЯ РУС | AL48: 129164, , Г. МОСКВА, ПЕР. ЗУБАРЕВ, Д.15, КОРП.1, ЭТ. 3, ПОМ.1, КОМ. 67Г | AM48: 45000 | AN48: 771701001 | AO48: CN | AP48: КИТАЙ | AQ48: КИТАЙ | AR48: RU | AS48: РОССИЯ | AT48: 1 | AU48: 1 | AV48: EXW | AW48: JIAXING | AX48: 0 | AY48: EUR | AZ48: 99667.32 | BA48: 7540361 | BB48: 111602.85 | BC48: 75.6553 | BD48: 010 | BE48: 40 | BF48: 22060044/0001/0000/2/1 | BG48: - | BH48: 11 | BI48: 10106/100913/10053/9 | BL48: КАЛУЖСКАЯ ОБЛ., БОРОВСКИЙ Р-Н | BM48: С. ВОРСИНО | BN48: СЕВЕРНАЯ ПРОМЗОНА, ВЛД. 6 | BO48: 10106050 т/п Обнинский | BP48: 1 | BQ48: КОТЛЫ ЦЕНТРАЛЬНОГО ОТОПЛЕНИЯ, СТАЛЬНЫЕ, АССОРТИМЕНТ | BR48: =ISNUMBER(SEARCH($BR$1,Таблица1[[#This Row],[31_1 Описание и характеристика товара]]))*1 -> 0 | BT48: BDR THERMEA HVAC CO., LTD | BU48: 56 | BV48: 1 | BW48: 388 | BX48: ШТ | BY48: 0 | CA48: 1 | CB48: 8403109000 | CE48: CN | CF48: 11524 | CG48: ОООО-ОО | CH48: 4000000 | CI48: 11252 | CJ48: 0 | CM48: 99667.32 | CN48: 7540361 | CO48: 0 | CP48: 1 | CQ48: 7849865.4 | CR48: 111602.85 | CS48: 10 | CT48: 9.9185 | CU48: 1053 | CV48: 0719/00-16-055 | CX48: БЫКОВА ЛЮБОВЬ АЛЕКСАНДРОВНА | CY48: 0
A49: 1 | B49: 45245 | C49: =IF(YEAR(Таблица1[[#This Row],[Дата]])=2023,MONTH(Таблица1[[#This Row],[Дата]]),0) -> 11 | D49: 10131010/311222/3564303 | E49: 10131010 | F49: 3564303 | G49: ИМ | H49: 40 | L49: BDR THERMEA HVAC CO., LTD | M49: 314000, , JIAXING, NO. 2000 GUANGQIONG ROAD, | P49: 1 | Q49: 0 | R49: 1 | S49: 52 | T49: 1087746423005 | U49: 7717615508 | V49: ООО БДР ТЕРМИЯ РУС ЧЕРЕЗ АО ТАСКОМ | W49: 129164, , Г. МОСКВА, ПЕР. ЗУБАРЕВ, Д.15, КОРП.1, ЭТ. 3, ПОМ.1, КОМ. 67Г | X49: 45000 | Y49: 771701001 | Z49: 1087746423005 | AA49: 7717615508 | AB49: ООО БДР ТЕРМИЯ РУС | AC49: 129164, , Г. МОСКВА, ПЕР. ЗУБАРЕВ, Д.15, КОРП.1, ЭТ. 3, ПОМ.1, КОМ. 67Г | AD49: 45000 | AE49: 771701001 | AF49: CN | AG49: КИТАЙ | AH49: 6881277 | AI49: 1087746423005 | AJ49: 7717615508 | AK49: ООО БДР ТЕРМИЯ РУС | AL49: 129164, , Г. МОСКВА, ПЕР. ЗУБАРЕВ, Д.15, КОРП.1, ЭТ. 3, ПОМ.1, КОМ. 67Г | AM49: 45000 | AN49: 771701001 | AO49: CN | AP49: КИТАЙ | AQ49: КИТАЙ | AR49: RU | AS49: РОССИЯ | AT49: 1 | AU49: 1 | AV49: EXW | AW49: JIAXING | AX49: 0 | AY49: EUR | AZ49: 86864.67 | BA49: 6571773 | BB49: 97832.27 | BC49: 75.6553 | BD49: 010 | BE49: 40 | BF49: 22060044/0001/0000/2/1 | BG49: - | BH49: 11 | BI49: 10106/100913/10053/9 | BL49: КАЛУЖСКАЯ ОБЛ., БОРОВСКИЙ Р-Н | BM49: С. ВОРСИНО | BN49: СЕВЕРНАЯ ПРОМЗОНА, ВЛД. 6 | BO49: 10106050 т/п Обнинский | BP49: 1 | BQ49: КОТЛЫ ЦЕНТРАЛЬНОГО ОТОПЛЕНИЯ, СТАЛЬНЫЕ, АССОРТИМЕНТ | BR49: =ISNUMBER(SEARCH($BR$1,Таблица1[[#This Row],[31_1 Описание и характеристика товара]]))*1 -> 0 | BT49: BDR THERMEA HVAC CO., LTD | BU49: 52 | BV49: 1 | BW49: 300 | BX49: ШТ | BY49: 0 | CA49: 1 | CB49: 8403109000 | CE49: CN | CF49: 10560 | CG49: ОООО-ОО | CH49: 4000000 | CI49: 9820 | CJ49: 0 | CM49: 86864.67 | CN49: 6571773 | CO49: 0 | CP49: 1 | CQ49: 6881277 | CR49: 97832.27 | CS49: 10 | CT49: 9.9626 | CU49: 1053 | CV49: 0719/00-16-055 | CX49: БЫКОВА ЛЮБОВЬ АЛЕКСАНДРОВНА | CY49: 0
A50: 1 | B50: 44625 | C50: =IF(YEAR(Таблица1[[#This Row],[Дата]])=2023,MONTH(Таблица1[[#This Row],[Дата]]),0) -> 0 | D50: 10131010/311023/3362213 | E50: 10131010 | F50: 3362213 | G50: ИМ | H50: 40 | L50: UNITED PETFOOD PRODUCERS NV | M50: 9400, , ERPE-MERE, EVENBROEKVELD 1, | P50: 1 | R50: 1 | S50: 33 | U50: 770100448470 | V50: ИП ЭСТРИН КИРИЛЛ ВАДИМОВИЧ | W50: 129085, РОССИЯ, МОСКВА, ПРОСПЕКТ МИРА, Д.81, КВ.101 | X50: 45000 | AA50: 770100448470 | AB50: ИП ЭСТРИН КИРИЛЛ ВАДИМОВИЧ | AC50: 129085, РОССИЯ, МОСКВА, ПРОСПЕКТ МИРА, Д.81, КВ.101 | AD50: 45000 | AF50: BE | AG50: БЕЛЬГИЯ | AH50: 4106236 | AJ50: 770100448470 | AK50: ИП ЭСТРИН КИРИЛЛ ВАДИМОВИЧ | AL50: 129085, РОССИЯ, МОСКВА, ПРОСПЕКТ МИРА, Д.81, КВ.101 | AM50: 45000 | AO50: BE | AP50: БЕЛЬГИЯ | AQ50: БЕЛЬГИЯ | AR50: RU | AS50: РОССИЯ | AT50: 2 | AU50: 0 | AV50: FCA | AW50: ERPE-MERE | AY50: EUR | AZ50: 37118.47 | BC50: 98.6164 | BF50: 22040387/3292/0000/2/2 | BG50: - | BH50: 99 | BL50: "КАЛУЖСКАЯ ОБЛ., БОРОВСКИЙ Р-Н" | BM50: С. ВОРСИНО | BN50: СЕВЕРНАЯ ПРОМЗОНА, ВЛАД. 6 | BO50: 10106050 т/п Обнинский | BQ50: КОРМ ДЛЯ СОБАК И КОШЕК, РАСФАСОВАННЫЙ ДЛЯ РОЗНИЧНОЙ ПРОДАЖИ, БЕЗ СОДЕРЖАНИЯ КРАХМАЛА, БЕЗ СОДЕРЖАНИЯ МОЛОЧНЫХ ПРОДУКТОВ,БЕЗ СОДЕРЖАНИЯ ГМО, В АССОРТИМЕНТЕ: | BR50: =ISNUMBER(SEARCH($BR$1,Таблица1[[#This Row],[31_1 Описание и характеристика товара]]))*1 -> 1 | BT50: UNITED PETFOOD PRODUCERS NV | BU50: 33 | BV50: 0 | BW50: 0 | BY50: 0 | CA50: 1 | CB50: 2309101100 | CE50: BE | CF50: 16636.83 | CG50: ОООО-ОО | CH50: 4000000 | CI50: 16528.83 | CJ50: 0 | CM50: 37118.47 | CO50: 0 | CP50: 1 | CQ50: 4106236 | CR50: 44037.77 | CS50: 10 | CT50: 43966.688 | CU50: 2.66 | CV50: 45 | CX50: ЯШИНА | CY50: 1
A51: 1 | B51: 44982 | C51: =IF(YEAR(Таблица1[[#This Row],[Дата]])=2023,MONTH(Таблица1[[#This Row],[Дата]]),0) -> 2 | D51: 10131010/311023/3362194 | E51: 10131010 | F51: 3362194 | G51: ИМ | H51: 40 | L51: UNITED PETFOOD PRODUCERS NV | M51: 9400, , ERPE-MERE, EVENBROEKVELD 1, | P51: 1 | R51: 1 | S51: 33 | U51: 770100448470 | V51: ИП ЭСТРИН КИРИЛЛ ВАДИМОВИЧ | W51: 129085, РОССИЯ, МОСКВА, ПРОСПЕКТ МИРА, Д.81, КВ.101 | X51: 45000 | AA51: 770100448470 | AB51: ИП ЭСТРИН КИРИЛЛ ВАДИМОВИЧ | AC51: 129085, РОССИЯ, МОСКВА, ПРОСПЕКТ МИРА, Д.81, КВ.101 | AD51: 45000 | AF51: BE | AG51: БЕЛЬГИЯ | AH51: 5108309.8 | AJ51: 770100448470 | AK51: ИП ЭСТРИН КИРИЛЛ ВАДИМОВИЧ | AL51: 129085, РОССИЯ, МОСКВА, ПРОСПЕКТ МИРА, Д.81, КВ.101 | AM51: 45000 | AO51: BE | AP51: БЕЛЬГИЯ | AQ51: БЕЛЬГИЯ | AR51: RU | AS51: РОССИЯ | AT51: 2 | AU51: 0 | AV51: FCA | AW51: ERPE-MERE | AY51: EUR | AZ51: 47809.8 | BC51: 98.6164 | BF51: 22040387/3292/0000/2/2 | BG51: - | BH51: 99 | BL51: "КАЛУЖСКАЯ ОБЛ., БОРОВСКИЙ Р-Н" | BM51: С. ВОРСИНО | BN51: СЕВЕРНАЯ ПРОМЗОНА, ВЛАД. 6 | BO51: 10106050 т/п Обнинский | BQ51: КОРМ ДЛЯ СОБАК И КОШЕК, РАСФАСОВАННЫЙ ДЛЯ РОЗНИЧНОЙ ПРОДАЖИ, БЕЗ СОДЕРЖАНИЯ КРАХМАЛА, БЕЗ СОДЕРЖАНИЯ МОЛОЧНЫХ ПРОДУКТОВ,БЕЗ СОДЕРЖАНИЯ ГМО, В АССОРТИМЕНТЕ | BR51: =ISNUMBER(SEARCH($BR$1,Таблица1[[#This Row],[31_1 Описание и характеристика товара]]))*1 -> 1 | BT51: UNITED PETFOOD PRODUCERS NV | BU51: 33 | BV51: 0 | BW51: 0 | BY51: 0 | CA51: 1 | CB51: 2309101100 | CE51: BE | CF51: 16525.08 | CG51: ОООО-ОО | CH51: 4000000 | CI51: 16525.08 | CJ51: 0 | CM51: 47809.8 | CO51: 0 | CP51: 1 | CQ51: 5108309.8 | CR51: 54784.62 | CS51: 10 | CT51: 54863.266 | CU51: 3.32 | CV51: 45 | CX51: БЛАГОНРАВОВА | CY51: 71
A52: 1 | B52: 45217 | C52: =IF(YEAR(Таблица1[[#This Row],[Дата]])=2023,MONTH(Таблица1[[#This Row],[Дата]]),0) -> 10 | D52: 10131010/311023/3362192 | E52: 10131010 | F52: 3362192 | G52: ИМ | H52: 40 | L52: UNITED PETFOOD PRODUCERS NV | M52: 9400, , ERPE-MERE, EVENBROEKVELD 1, | P52: 1 | R52: 1 | S52: 33 | U52: 770100448470 | V52: ИП ЭСТРИН КИРИЛЛ ВАДИМОВИЧ | W52: 129085, РОССИЯ, МОСКВА, ПРОСПЕКТ МИРА, Д.81, КВ.101 | X52: 45000 | AA52: 770100448470 | AB52: ИП ЭСТРИН КИРИЛЛ ВАДИМОВИЧ | AC52: 129085, РОССИЯ, МОСКВА, ПРОСПЕКТ МИРА, Д.81, КВ.101 | AD52: 45000 | AF52: BE | AG52: БЕЛЬГИЯ | AH52: 4229107.1 | AJ52: 770100448470 | AK52: ИП ЭСТРИН КИРИЛЛ ВАДИМОВИЧ | AL52: 129085, РОССИЯ, МОСКВА, ПРОСПЕКТ МИРА, Д.81, КВ.101 | AM52: 45000 | AO52: BE | AP52: БЕЛЬГИЯ | AQ52: БЕЛЬГИЯ | AR52: RU | AS52: РОССИЯ | AT52: 2 | AU52: 0 | AV52: FCA | AW52: ERPE-MERE | AY52: EUR | AZ52: 38894.42 | BC52: 98.6164 | BF52: 22040387/3292/0000/2/2 | BG52: - | BH52: 99 | BL52: "КАЛУЖСКАЯ ОБЛ., БОРОВСКИЙ Р-Н" | BM52: С. ВОРСИНО | BN52: СЕВЕРНАЯ ПРОМЗОНА, ВЛАД. 6 | BO52: 10106050 т/п Обнинский | BQ52: КОРМ ДЛЯ СОБАК И КОШЕК, РАСФАСОВАННЫЙ ДЛЯ РОЗНИЧНОЙ ПРОДАЖИ, БЕЗ СОДЕРЖАНИЯ КРАХМАЛА, БЕЗ СОДЕРЖАНИЯ МОЛОЧНЫХ ПРОДУКТОВ,БЕЗ СОДЕРЖАНИЯ ГМО, В АССОРТИМЕНТЕ | BR52: =ISNUMBER(SEARCH($BR$1,Таблица1[[#This Row],[31_1 Описание и характеристика товара]]))*1 -> 1 | BT52: UNITED PETFOOD PRODUCERS NV | BU52: 33 | BV52: 0 | BW52: 0 | BY52: 0 | CA52: 1 | CB52: 2309101100 | CE52: BE | CF52: 16080.56 | CG52: ОООО-ОО | CH52: 4000000 | CI52: 15901.16 | CJ52: 0 | CM52: 38894.42 | CO52: 0 | CP52: 1 | CQ52: 4229107.1 | CR52: 45355.52 | CS52: 10 | CT52: 45318.306 | CU52: 2.85 | CV52: 45 | CX52: ЧУДИНА | CY52: 580
A53: 1 | B53: 44976 | C53: =IF(YEAR(Таблица1[[#This Row],[Дата]])=2023,MONTH(Таблица1[[#This Row],[Дата]]),0) -> 2 | D53: 10131010/311023/3362191 | E53: 10131010 | F53: 3362191 | G53: ИМ | H53: 40 | L53: UNITED PETFOOD PRODUCERS NV | M53: 9400, , ERPE-MERE, EVENBROEKVELD 1, | P53: 1 | R53: 1 | S53: 33 | U53: 770100448470 | V53: ИП ЭСТРИН КИРИЛЛ ВАДИМОВИЧ | W53: 129085, РОССИЯ, МОСКВА, ПРОСПЕКТ МИРА, Д.81, КВ.101 | X53: 45000 | AA53: 770100448470 | AB53: ИП ЭСТРИН КИРИЛЛ ВАДИМОВИЧ | AC53: 129085, РОССИЯ, МОСКВА, ПРОСПЕКТ МИРА, Д.81, КВ.101 | AD53: 45000 | AF53: BE | AG53: БЕЛЬГИЯ | AH53: 5111999 | AJ53: 770100448470 | AK53: ИП ЭСТРИН КИРИЛЛ ВАДИМОВИЧ | AL53: 129085, РОССИЯ, МОСКВА, ПРОСПЕКТ МИРА, Д.81, КВ.101 | AM53: 45000 | AO53: BE | AP53: БЕЛЬГИЯ | AQ53: БЕЛЬГИЯ | AR53: RU | AS53: РОССИЯ | AT53: 2 | AU53: 0 | AV53: FCA | AW53: ERPE-MERE | AY53: EUR | AZ53: 47317.21 | BC53: 98.6164 | BF53: 22040387/3292/0000/2/2 | BG53: - | BH53: 99 | BL53: "КАЛУЖСКАЯ ОБЛ., БОРОВСКИЙ Р-Н" | BM53: С. ВОРСИНО | BN53: СЕВЕРНАЯ ПРОМЗОНА, ВЛАД. 6 | BO53: 10106050 т/п Обнинский | BQ53: КОРМ ДЛЯ СОБАК И КОШЕК, РАСФАСОВАННЫЙ ДЛЯ РОЗНИЧНОЙ ПРОДАЖИ, БЕЗ СОДЕРЖАНИЯ КРАХМАЛА, БЕЗ СОДЕРЖАНИЯ МОЛОЧНЫХ ПРОДУКТОВ,БЕЗ СОДЕРЖАНИЯ ГМО, В АССОРТИМЕНТЕ: | BR53: =ISNUMBER(SEARCH($BR$1,Таблица1[[#This Row],[31_1 Описание и характеристика товара]]))*1 -> 1 | BT53: UNITED PETFOOD PRODUCERS NV | BU53: 33 | BV53: 0 | BW53: 0 | BY53: 0 | CA53: 1 | CB53: 2309101100 | CE53: BE | CF53: 15664.95 | CG53: ОООО-ОО | CH53: 4000000 | CI53: 15574.95 | CJ53: 0 | CM53: 47317.21 | CO53: 0 | CP53: 1 | CQ53: 5111999 | CR53: 54824.19 | CS53: 10 | CT53: 54823.824 | CU53: 3.52 | CV53: 45 | CX53: ДРУЗЯГИНА | CY53: 310
A54: 1 | B54: 45147 | C54: =IF(YEAR(Таблица1[[#This Row],[Дата]])=2023,MONTH(Таблица1[[#This Row],[Дата]]),0) -> 8 | D54: 10131010/310823/5021240 | E54: 10131010 | F54: 5021240 | G54: ИМ | H54: 40 | L54: UNITED PETFOOD PRODUCERS NV | M54: 9400, , ERPE-MERE, EVENBROEKVELD 1, | P54: 1 | R54: 1 | S54: 38 | U54: 7,7010044847 | V54: ИП ЭСТРИН КИРИЛЛ ВАДИМОВИЧ | W54: 129085, РОССИЯ, МОСКВА, ПРОСПЕКТ МИРА, Д.81, КВ.101 | X54: 45000 | AA54: 770100448470 | AB54: ИП ЭСТРИН КИРИЛЛ ВАДИМОВИЧ | AC54: 129085, РОССИЯ, МОСКВА, ПРОСПЕКТ МИРА, Д.81, КВ.101 | AD54: 45000 | AF54: BE | AG54: БЕЛЬГИЯ | AH54: 5232447.6 | AJ54: 770100448470 | AK54: ИП ЭСТРИН КИРИЛЛ ВАДИМОВИЧ | AL54: 129085, РОССИЯ, МОСКВА, ПРОСПЕКТ МИРА, Д.81, КВ.101 | AM54: 45000 | AO54: BE | AP54: БЕЛЬГИЯ | AQ54: БЕЛЬГИЯ | AR54: RU | AS54: РОССИЯ | AT54: 2 | AU54: 0 | AV54: FCA | AW54: ERPE-MERE | AY54: EUR | AZ54: 45965.43 | BC54: 104.4496 | BE54: 31 | BF54: 22040387/3292/0000/2/2 | BG54: 11209159-11209159 | BH54: 11 | BL54: КАЛУЖСКАЯ ОБЛ., БОРОВСКИЙ Р-Н | BM54: С. ВОРСИНО | BN54: СЕВЕРНАЯ ПРОМЗОНА, ВЛД. 6 | BO54: 10106050 т/п Обнинский | BQ54: КОРМ ДЛЯ СОБАК И КОШЕК, РАСФАСОВАННЫЙ ДЛЯ РОЗНИЧНОЙ ПРОДАЖИ, БЕЗ СОДЕРЖАНИЯ КРАХМАЛА, БЕЗ СОДЕРЖАНИЯ МОЛОЧНЫХ ПРОДУКТОВ, В АССОРТИМЕНТЕ | BR54: =ISNUMBER(SEARCH($BR$1,Таблица1[[#This Row],[31_1 Описание и характеристика товара]]))*1 -> 1 | BT54: UNITED PETFOOD PRODUCERS NV | BU54: 38 | CA54: 1 | CB54: 2309101100 | CE54: BE | CF54: 19480.81 | CG54: ОООО-ОО | CH54: 4000000 | CI54: 19378.81 | CM54: 45965.43 | CO54: 0 | CP54: 1 | CQ54: 5232447.6 | CR54: 54545.4 | CS54: 10 | CT54: 54454.456 | CU54: 2.81 | CV54: 45 | CX54: БЛАГОНРАВОВА | CY54: 296
A55: 1 | B55: 44985 | C55: =IF(YEAR(Таблица1[[#This Row],[Дата]])=2023,MONTH(Таблица1[[#This Row],[Дата]]),0) -> 2 | D55: 10131010/310823/3299344 | E55: 10131010 | F55: 3299344 | G55: ИМ | H55: 40 | L55: UNITED PETFOOD PRODUCERS NV | M55: 9400, , ERPE-MERE, EVENBROEKVELD 1, | P55: 1 | R55: 1 | S55: 33 | U55: 7,7010044847 | V55: ИП ЭСТРИН КИРИЛЛ ВАДИМОВИЧ | W55: 129085, РОССИЯ, МОСКВА, ПРОСПЕКТ МИРА, Д.81, КВ.101 | X55: 45000 | AA55: 770100448470 | AB55: ИП ЭСТРИН КИРИЛЛ ВАДИМОВИЧ | AC55: 129085, РОССИЯ, МОСКВА, ПРОСПЕКТ МИРА, Д.81, КВ.101 | AD55: 45000 | AF55: BE | AG55: БЕЛЬГИЯ | AH55: 4733204.7 | AJ55: 770100448470 | AK55: ИП ЭСТРИН КИРИЛЛ ВАДИМОВИЧ | AL55: 129085, РОССИЯ, МОСКВА, ПРОСПЕКТ МИРА, Д.81, КВ.101 | AM55: 45000 | AO55: BE | AP55: БЕЛЬГИЯ | AQ55: БЕЛЬГИЯ | AR55: RU | AS55: РОССИЯ | AT55: 2 | AU55: 0 | AV55: FCA | AW55: ERPE-MERE | AY55: EUR | AZ55: 41185.68 | BC55: 104.4496 | BE55: 31 | BF55: 22040387/3292/0000/2/2 | BG55: 11216463-11216463 | BH55: 99 | BL55: КАЛУЖСКАЯ ОБЛ., БОРОВСКИЙ Р-Н | BM55: С. ВОРСИНО | BN55: СЕВЕРНАЯ ПРОМЗОНА, ВЛАД. 6 | BO55: 10106050 т/п Обнинский | BQ55: КОРМ ДЛЯ СОБАК И КОШЕК, РАСФАСОВАННЫЙ ДЛЯ РОЗНИЧНОЙ ПРОДАЖИ, БЕЗ СОДЕРЖАНИЯ КРАХМАЛА, БЕЗ СОДЕРЖАНИЯ МОЛОЧНЫХ ПРОДУКТОВ,БЕЗ СОДЕРЖАНИЯ ГМО, В АССОРТИМЕНТЕ | BR55: =ISNUMBER(SEARCH($BR$1,Таблица1[[#This Row],[31_1 Описание и характеристика товара]]))*1 -> 1 | BT55: UNITED PETFOOD PRODUCERS NV | BU55: 33 | BV55: 0 | BW55: 0 | BY55: 0 | CA55: 1 | CB55: 2309101100 | CE55: BE | CF55: 16912.34 | CG55: ОООО-ОО | CH55: 4000000 | CI55: 16869.14 | CJ55: 0 | CM55: 41185.68 | CO55: 0 | CP55: 1 | CQ55: 4733204.7 | CR55: 49341.07 | CS55: 10 | CT55: 49257.889 | CU55: 2.92 | CV55: 45 | CX55: ЧУДИНА | CY55: 166
A56: 1 | B56: 45235 | C56: =IF(YEAR(Таблица1[[#This Row],[Дата]])=2023,MONTH(Таблица1[[#This Row],[Дата]]),0) -> 11 | D56: 10131010/310723/3267480 | E56: 10131010 | F56: 3267480 | G56: ИМ | H56: 40 | L56: UNITED PETFOOD PRODUCERS NV | M56: 9400, , ERPE-MERE, EVENBROEKVELD 1, | P56: 1 | Q56: 0 | R56: 1 | S56: 33 | T56: 316774600208441 | U56: 770100448470 | V56: ИП ЭСТРИН КИРИЛЛ ВАДИМОВИЧ | W56: 129085, РОССИЯ, МОСКВА, ПРОСПЕКТ МИРА, Д.81, КВ.101 | X56: 45000 | Z56: 316774600208441 | AA56: 770100448470 | AB56: ИП ЭСТРИН КИРИЛЛ ВАДИМОВИЧ | AC56: 129085, РОССИЯ, МОСКВА, ПРОСПЕКТ МИРА, Д.81, КВ.101 | AD56: 45000 | AF56: BE | AG56: БЕЛЬГИЯ | AH56: 4577002.3 | AI56: 316774600208441 | AJ56: 770100448470 | AK56: ИП ЭСТРИН КИРИЛЛ ВАДИМОВИЧ | AL56: 129085, РОССИЯ, МОСКВА, ПРОСПЕКТ МИРА, Д.81, КВ.101 | AM56: 45000 | AO56: BE | AP56: БЕЛЬГИЯ | AQ56: БЕЛЬГИЯ | AR56: RU | AS56: РОССИЯ | AT56: 2 | AU56: 0 | AV56: FCA | AW56: ERPE-MERE | AX56: 1 | AY56: EUR | AZ56: 40958.98 | BC56: 99.9586 | BD56: 10 | BE56: 31 | BF56: 22040387/3292/0000/2/2 | BG56: 10106050-т/п Обнинский | BH56: 99 | BL56: КАЛУЖСКАЯ ОБЛ., БОРОВСКИЙ Р-Н | BM56: С. ВОРСИНО | BN56: СЕВЕРНАЯ ПРОМЗОНА, ВЛАД. 6 | BO56: 10106050 т/п Обнинский | BQ56: КОРМ ДЛЯ СОБАК И КОШЕК, РАСФАСОВАННЫЙ ДЛЯ РОЗНИЧНОЙ ПРОДАЖИ, БЕЗ СОДЕРЖАНИЯ КРАХМАЛА, БЕЗ СОДЕРЖАНИЯ МОЛОЧНЫХ ПРОДУКТОВ,БЕЗ СОДЕРЖАНИЯ ГМО, В АССОРТИМЕНТЕ | BR56: =ISNUMBER(SEARCH($BR$1,Таблица1[[#This Row],[31_1 Описание и характеристика товара]]))*1 -> 1 | BT56: UNITED PETFOOD PRODUCERS NV | BU56: 33 | BV56: 0 | BW56: 0 | BY56: 0 | CA56: 1 | CB56: 2309101100 | CE56: BE | CF56: 16850.56 | CG56: ОООО-ОО | CH56: 4000000 | CI56: 16789.36 | CJ56: 0 | CM56: 40958.98 | CN56: 4094202.3 | CO56: 0 | CP56: 1 | CQ56: 4577002.3 | CR56: 50308.73 | CS56: 10 | CT56: 50368.08 | CU56: 3 | CV56: 45 | CW56: 2022/09 БР | CX56: БЛАГОНРАВОВА ДАРЬЯ ДМИТРИЕВНА | CY56: 553
A57: 1 | B57: 44966 | C57: =IF(YEAR(Таблица1[[#This Row],[Дата]])=2023,MONTH(Таблица1[[#This Row],[Дата]]),0) -> 2 | D57: 10131010/310723/3267477 | E57: 10131010 | F57: 3267477 | G57: ИМ | H57: 40 | L57: UNITED PETFOOD PRODUCERS NV | M57: 9400, , ERPE-MERE, EVENBROEKVELD 1, | P57: 1 | Q57: 0 | R57: 1 | S57: 33 | T57: 316774600208441 | U57: 770100448470 | V57: ИП ЭСТРИН КИРИЛЛ ВАДИМОВИЧ | W57: 129085, РОССИЯ, МОСКВА, ПРОСПЕКТ МИРА, Д.81, КВ.101 | X57: 45000 | Z57: 316774600208441 | AA57: 770100448470 | AB57: ИП ЭСТРИН КИРИЛЛ ВАДИМОВИЧ | AC57: 129085, РОССИЯ, МОСКВА, ПРОСПЕКТ МИРА, Д.81, КВ.101 | AD57: 45000 | AF57: BE | AG57: БЕЛЬГИЯ | AH57: 4560723.1 | AI57: 316774600208441 | AJ57: 770100448470 | AK57: ИП ЭСТРИН КИРИЛЛ ВАДИМОВИЧ | AL57: 129085, РОССИЯ, МОСКВА, ПРОСПЕКТ МИРА, Д.81, КВ.101 | AM57: 45000 | AO57: BE | AP57: БЕЛЬГИЯ | AQ57: БЕЛЬГИЯ | AR57: RU | AS57: РОССИЯ | AT57: 2 | AU57: 0 | AV57: FCA | AW57: ERPE-MERE | AX57: 1 | AY57: EUR | AZ57: 41496.12 | BC57: 99.9586 | BD57: 10 | BE57: 31 | BF57: 22040387/3292/0000/2/2 | BG57: 10106050-т/п Обнинский | BH57: 99 | BL57: КАЛУЖСКАЯ ОБЛ., БОРОВСКИЙ Р-Н | BM57: С. ВОРСИНО | BN57: СЕВЕРНАЯ ПРОМЗОНА, ВЛАД. 6 | BO57: 10106050 т/п Обнинский | BQ57: КОРМ ДЛЯ СОБАК И КОШЕК, РАСФАСОВАННЫЙ ДЛЯ РОЗНИЧНОЙ ПРОДАЖИ, БЕЗ СОДЕРЖАНИЯ КРАХМАЛА, БЕЗ СОДЕРЖАНИЯ МОЛОЧНЫХ ПРОДУКТОВ,БЕЗ СОДЕРЖАНИЯ ГМО, В АССОРТИМЕНТЕ: | BR57: =ISNUMBER(SEARCH($BR$1,Таблица1[[#This Row],[31_1 Описание и характеристика товара]]))*1 -> 1 | BT57: UNITED PETFOOD PRODUCERS NV | BU57: 33 | BV57: 0 | BW57: 0 | BY57: 0 | CA57: 1 | CB57: 2309101100 | CE57: BE | CF57: 16510.24 | CG57: ОООО-ОО | CH57: 4000000 | CI57: 16359.04 | CJ57: 0 | CM57: 41496.12 | CN57: 4147894.1 | CO57: 0 | CP57: 1 | CQ57: 4560723.1 | CR57: 50129.79 | CS57: 10 | CT57: 50058.662 | CU57: 3.06 | CV57: 45 | CW57: 2022/09 БР | CX57: ЯШИНА АННА СЕРГЕЕВНА | CY57: 68
A58: 1 | B58: 44998 | C58: =IF(YEAR(Таблица1[[#This Row],[Дата]])=2023,MONTH(Таблица1[[#This Row],[Дата]]),0) -> 3 | D58: 10131010/310723/3267476 | E58: 10131010 | F58: 3267476 | G58: ИМ | H58: 40 | L58: UNITED PETFOOD PRODUCERS NV | M58: 9400, , ERPE-MERE, EVENBROEKVELD 1, | P58: 1 | Q58: 0 | R58: 1 | S58: 33 | T58: 316774600208441 | U58: 770100448470 | V58: ИП ЭСТРИН КИРИЛЛ ВАДИМОВИЧ | W58: 129085, РОССИЯ, МОСКВА, ПРОСПЕКТ МИРА, Д.81, КВ.101 | X58: 45000 | Z58: 316774600208441 | AA58: 770100448470 | AB58: ИП ЭСТРИН КИРИЛЛ ВАДИМОВИЧ | AC58: 129085, РОССИЯ, МОСКВА, ПРОСПЕКТ МИРА, Д.81, КВ.101 | AD58: 45000 | AF58: BE | AG58: БЕЛЬГИЯ | AH58: 4459281.1 | AI58: 316774600208441 | AJ58: 770100448470 | AK58: ИП ЭСТРИН КИРИЛЛ ВАДИМОВИЧ | AL58: 129085, РОССИЯ, МОСКВА, ПРОСПЕКТ МИРА, Д.81, КВ.101 | AM58: 45000 | AO58: BE | AP58: БЕЛЬГИЯ | AQ58: БЕЛЬГИЯ | AR58: RU | AS58: РОССИЯ | AT58: 2 | AU58: 0 | AV58: FCA | AW58: ERPE-MERE | AX58: 1 | AY58: EUR | AZ58: 40481.28 | BC58: 99.9586 | BD58: 10 | BE58: 31 | BF58: 22040387/3292/0000/2/2 | BG58: 10106050-т/п Обнинский | BH58: 11 | BI58: 10106/100913/10053/9 | BL58: КАЛУЖСКАЯ ОБЛ., БОРОВСКИЙ Р-Н | BM58: С. ВОРСИНО | BN58: СЕВЕРНАЯ ПРОМЗОНА, ВЛД. 6 | BO58: 10106050 т/п Обнинский | BQ58: КОРМ ДЛЯ СОБАК И КОШЕК, РАСФАСОВАННЫЙ ДЛЯ РОЗНИЧНОЙ ПРОДАЖИ, БЕЗ СОДЕРЖАНИЯ КРАХМАЛА, БЕЗ СОДЕРЖАНИЯ МОЛОЧНЫХ ПРОДУКТОВ,БЕЗ СОДЕРЖАНИЯ ГМО, В АССОРТИМЕНТЕ | BR58: =ISNUMBER(SEARCH($BR$1,Таблица1[[#This Row],[31_1 Описание и характеристика товара]]))*1 -> 1 | BT58: UNITED PETFOOD PRODUCERS NV | BU58: 33 | BV58: 0 | BW58: 0 | BY58: 0 | CA58: 1 | CB58: 2309101100 | CE58: BE | CF58: 16162.18 | CG58: ОООО-ОО | CH58: 4000000 | CI58: 16054.18 | CJ58: 0 | CM58: 40481.28 | CN58: 4046452.1 | CO58: 0 | CP58: 1 | CQ58: 4459281.1 | CR58: 49014.78 | CS58: 10 | CT58: 48965.249 | CU58: 3.05 | CV58: 45 | CW58: 2022/09 БР | CX58: ЧУДИНА ЭЛЬВИРА РАИСОВНА | CY58: 212
A59: 1 | B59: 45163 | C59: =IF(YEAR(Таблица1[[#This Row],[Дата]])=2023,MONTH(Таблица1[[#This Row],[Дата]]),0) -> 8 | D59: 10131010/310723/3267102 | E59: 10131010 | F59: 3267102 | G59: ИМ | H59: 40 | L59: UNITED PETFOOD PRODUCERS NV | M59: 9400, , ERPE-MERE, EVENBROEKVELD 1, | P59: 1 | Q59: 0 | R59: 1 | S59: 33 | T59: 316774600208441 | U59: 770100448470 | V59: ИП ЭСТРИН КИРИЛЛ ВАДИМОВИЧ | W59: 129085, РОССИЯ, МОСКВА, ПРОСПЕКТ МИРА, Д.81, КВ.101 | X59: 45000 | Z59: 316774600208441 | AA59: 770100448470 | AB59: ИП ЭСТРИН КИРИЛЛ ВАДИМОВИЧ | AC59: 129085, РОССИЯ, МОСКВА, ПРОСПЕКТ МИРА, Д.81, КВ.101 | AD59: 45000 | AF59: BE | AG59: БЕЛЬГИЯ | AH59: 4325034.7 | AI59: 316774600208441 | AJ59: 770100448470 | AK59: ИП ЭСТРИН КИРИЛЛ ВАДИМОВИЧ | AL59: 129085, РОССИЯ, МОСКВА, ПРОСПЕКТ МИРА, Д.81, КВ.101 | AM59: 45000 | AO59: BE | AP59: БЕЛЬГИЯ | AQ59: БЕЛЬГИЯ | AR59: RU | AS59: РОССИЯ | AT59: 2 | AU59: 0 | AV59: FCA | AW59: ERPE-MERE | AX59: 1 | AY59: EUR | AZ59: 39138.26 | BC59: 99.9586 | BD59: 10 | BE59: 31 | BF59: 22040387/3292/0000/2/2 | BG59: 10106050-т/п Обнинский | BH59: 11 | BI59: 10106/100913/10053/9 | BL59: КАЛУЖСКАЯ ОБЛ., БОРОВСКИЙ Р-Н | BM59: С. ВОРСИНО | BN59: СЕВЕРНАЯ ПРОМЗОНА, ВЛД. 6 | BO59: 10106050 т/п Обнинский | BQ59: КОРМ ДЛЯ СОБАК И КОШЕК, РАСФАСОВАННЫЙ ДЛЯ РОЗНИЧНОЙ ПРОДАЖИ, БЕЗ СОДЕРЖАНИЯ КРАХМАЛА, БЕЗ СОДЕРЖАНИЯ МОЛОЧНЫХ ПРОДУКТОВ,БЕЗ СОДЕРЖАНИЯ ГМО, В АССОРТИМЕНТЕ: | BR59: =ISNUMBER(SEARCH($BR$1,Таблица1[[#This Row],[31_1 Описание и характеристика товара]]))*1 -> 1 | BT59: UNITED PETFOOD PRODUCERS NV | BU59: 33 | BV59: 0 | BW59: 0 | BY59: 0 | CA59: 1 | CB59: 2309101100 | CE59: BE | CF59: 17073.59 | CG59: ОООО-ОО | CH59: 4000000 | CI59: 17037.59 | CJ59: 0 | CM59: 39138.26 | CN59: 3912205.7 | CO59: 0 | CP59: 1 | CQ59: 4325034.7 | CR59: 47539.19 | CS59: 10 | CT59: 47534.876 | CU59: 2.79 | CV59: 45 | CW59: 2022/09 БР | CX59: ЯШИНА АННА СЕРГЕЕВНА | CY59: 337
A60: 1 | B60: 45131 | C60: =IF(YEAR(Таблица1[[#This Row],[Дата]])=2023,MONTH(Таблица1[[#This Row],[Дата]]),0) -> 7 | D60: 10131010/310723/3267093 | E60: 10131010 | F60: 3267093 | G60: ИМ | H60: 40 | L60: UNITED PETFOOD PRODUCERS NV | M60: 9400, , ERPE-MERE, EVENBROEKVELD 1, | P60: 1 | Q60: 0 | R60: 1 | S60: 33 | T60: 316774600208441 | U60: 770100448470 | V60: ИП ЭСТРИН КИРИЛЛ ВАДИМОВИЧ | W60: 129085, РОССИЯ, МОСКВА, ПРОСПЕКТ МИРА, Д.81, КВ.101 | X60: 45000 | Z60: 316774600208441 | AA60: 770100448470 | AB60: ИП ЭСТРИН КИРИЛЛ ВАДИМОВИЧ | AC60: 129085, РОССИЯ, МОСКВА, ПРОСПЕКТ МИРА, Д.81, КВ.101 | AD60: 45000 | AF60: BE | AG60: БЕЛЬГИЯ | AH60: 4554123.8 | AI60: 316774600208441 | AJ60: 770100448470 | AK60: ИП ЭСТРИН КИРИЛЛ ВАДИМОВИЧ | AL60: 129085, РОССИЯ, МОСКВА, ПРОСПЕКТ МИРА, Д.81, КВ.101 | AM60: 45000 | AO60: BE | AP60: БЕЛЬГИЯ | AQ60: БЕЛЬГИЯ | AR60: RU | AS60: РОССИЯ | AT60: 2 | AU60: 0 | AV60: FCA | AW60: ERPE-MERE | AX60: 1 | AY60: EUR | AZ60: 40910.1 | BC60: 99.9586 | BD60: 10 | BE60: 31 | BF60: 22040387/3292/0000/2/2 | BG60: 10106050-т/п Обнинский | BH60: 11 | BI60: 10106/100913/10053/9 | BL60: КАЛУЖСКАЯ ОБЛ., БОРОВСКИЙ Р-Н | BM60: С. ВОРСИНО | BN60: СЕВЕРНАЯ ПРОМЗОНА, ВЛД. 6 | BO60: 10106050 т/п Обнинский | BQ60: КОРМ ДЛЯ СОБАК И КОШЕК, РАСФАСОВАННЫЙ ДЛЯ РОЗНИЧНОЙ ПРОДАЖИ, БЕЗ СОДЕРЖАНИЯ КРАХМАЛА, БЕЗ СОДЕРЖАНИЯ МОЛОЧНЫХ ПРОДУКТОВ,БЕЗ СОДЕРЖАНИЯ ГМО, В АССОРТИМЕНТЕ | BR60: =ISNUMBER(SEARCH($BR$1,Таблица1[[#This Row],[31_1 Описание и характеристика товара]]))*1 -> 1 | BT60: UNITED PETFOOD PRODUCERS NV | BU60: 33 | BV60: 0 | BW60: 0 | BY60: 0 | CA60: 1 | CB60: 2309101100 | CE60: BE | CF60: 16919.83 | CG60: ОООО-ОО | CH60: 4000000 | CI60: 16826.23 | CJ60: 0 | CM60: 40910.1 | CN60: 4089316.3 | CO60: 0 | CP60: 1 | CQ60: 4554123.8 | CR60: 50057.25 | CS60: 10 | CT60: 49973.903 | CU60: 2.97 | CV60: 45 | CW60: 2022/09 БР | CX60: БЛАГОНРАВОВА ДАРЬЯ ДМИТРИЕВНА | CY60: 45
A61: 1 | B61: 45000 | C61: =IF(YEAR(Таблица1[[#This Row],[Дата]])=2023,MONTH(Таблица1[[#This Row],[Дата]]),0) -> 3 | D61: 10131010/310723/3267056 | E61: 10131010 | F61: 3267056 | G61: ИМ | H61: 40 | L61: UNITED PETFOOD PRODUCERS NV | M61: 9400, , ERPE-MERE, EVENBROEKVELD 1, | P61: 1 | Q61: 0 | R61: 1 | S61: 33 | T61: 316774600208441 | U61: 770100448470 | V61: ИП ЭСТРИН КИРИЛЛ ВАДИМОВИЧ | W61: 129085, РОССИЯ, МОСКВА, ПРОСПЕКТ МИРА, Д.81, КВ.101 | X61: 45000 | Z61: 316774600208441 | AA61: 770100448470 | AB61: ИП ЭСТРИН КИРИЛЛ ВАДИМОВИЧ | AC61: 129085, РОССИЯ, МОСКВА, ПРОСПЕКТ МИРА, Д.81, КВ.101 | AD61: 45000 | AF61: BE | AG61: БЕЛЬГИЯ | AH61: 4530391.6 | AI61: 316774600208441 | AJ61: 770100448470 | AK61: ИП ЭСТРИН КИРИЛЛ ВАДИМОВИЧ | AL61: 129085, РОССИЯ, МОСКВА, ПРОСПЕКТ МИРА, Д.81, КВ.101 | AM61: 45000 | AO61: BE | AP61: БЕЛЬГИЯ | AQ61: БЕЛЬГИЯ | AR61: RU | AS61: РОССИЯ | AT61: 2 | AU61: 0 | AV61: FCA | AW61: ERPE-MERE | AX61: 1 | AY61: EUR | AZ61: 40672.68 | BC61: 99.9586 | BD61: 10 | BE61: 31 | BF61: 22040387/3292/0000/2/2 | BG61: 10106050-т/п Обнинский | BH61: 11 | BI61: 10106/100913/10053/9 | BL61: КАЛУЖСКАЯ ОБЛ., БОРОВСКИЙ Р-Н | BM61: С. ВОРСИНО | BN61: СЕВЕРНАЯ ПРОМЗОНА, ВЛД. 6 | BO61: 10106050 т/п Обнинский | BQ61: КОРМ ДЛЯ СОБАК, РАСФАСОВАННЫЙ ДЛЯ РОЗНИЧНОЙ ПРОДАЖИ, БЕЗ СОДЕРЖАНИЯ КРАХМАЛА, БЕЗ СОДЕРЖАНИЯ МОЛОЧНЫХ ПРОДУКТОВ,БЕЗ СОДЕРЖАНИЯ ГМО, В АССОРТИМЕНТЕ | BR61: =ISNUMBER(SEARCH($BR$1,Таблица1[[#This Row],[31_1 Описание и характеристика товара]]))*1 -> 1 | BT61: UNITED PETFOOD PRODUCERS NV | BU61: 33 | BV61: 0 | BW61: 0 | BY61: 0 | CA61: 1 | CB61: 2309101100 | CE61: BE | CF61: 17085.44 | CG61: ОООО-ОО | CH61: 4000000 | CI61: 16999.04 | CJ61: 0 | CM61: 40672.68 | CN61: 4065584.1 | CO61: 0 | CP61: 1 | CQ61: 4530391.6 | CR61: 49796.4 | CS61: 10 | CT61: 49807.187 | CU61: 2.93 | CV61: 45 | CW61: 2022/09 БР | CX61: БЛАГОНРАВОВА ДАРЬЯ ДМИТРИЕВНА | CY61: 67
A62: 1 | B62: 45249 | C62: =IF(YEAR(Таблица1[[#This Row],[Дата]])=2023,MONTH(Таблица1[[#This Row],[Дата]]),0) -> 11 | D62: 10131010/310723/3267047 | E62: 10131010 | F62: 3267047 | G62: ИМ | H62: 40 | L62: UNITED PETFOOD PRODUCERS NV | M62: 9400, , ERPE-MERE, EVENBROEKVELD 1, | P62: 1 | Q62: 0 | R62: 1 | S62: 33 | T62: 316774600208441 | U62: 770100448470 | V62: ИП ЭСТРИН КИРИЛЛ ВАДИМОВИЧ | W62: 129085, РОССИЯ, МОСКВА, ПРОСПЕКТ МИРА, Д.81, КВ.101 | X62: 45000 | Z62: 316774600208441 | AA62: 770100448470 | AB62: ИП ЭСТРИН КИРИЛЛ ВАДИМОВИЧ | AC62: 129085, РОССИЯ, МОСКВА, ПРОСПЕКТ МИРА, Д.81, КВ.101 | AD62: 45000 | AF62: BE | AG62: БЕЛЬГИЯ | AH62: 4574484.4 | AI62: 316774600208441 | AJ62: 770100448470 | AK62: ИП ЭСТРИН КИРИЛЛ ВАДИМОВИЧ | AL62: 129085, РОССИЯ, МОСКВА, ПРОСПЕКТ МИРА, Д.81, КВ.101 | AM62: 45000 | AO62: BE | AP62: БЕЛЬГИЯ | AQ62: БЕЛЬГИЯ | AR62: RU | AS62: РОССИЯ | AT62: 2 | AU62: 0 | AV62: FCA | AW62: ERPE-MERE | AX62: 1 | AY62: EUR | AZ62: 40933.79 | BC62: 99.9586 | BD62: 10 | BE62: 31 | BF62: 22040387/3292/0000/2/2 | BG62: 10106050-т/п Обнинский | BH62: 11 | BI62: 10106/100913/10053/9 | BL62: КАЛУЖСКАЯ ОБЛ., БОРОВСКИЙ Р-Н | BM62: С. ВОРСИНО | BN62: СЕВЕРНАЯ ПРОМЗОНА, ВЛД. 6 | BO62: 10106050 т/п Обнинский | BQ62: КОРМ ДЛЯ СОБАК И КОШЕК, РАСФАСОВАННЫЙ ДЛЯ РОЗНИЧНОЙ ПРОДАЖИ, БЕЗ СОДЕРЖАНИЯ КРАХМАЛА, БЕЗ СОДЕРЖАНИЯ МОЛОЧНЫХ ПРОДУКТОВ,БЕЗ СОДЕРЖАНИЯ ГМО, В АССОРТИМЕНТЕ: | BR62: =ISNUMBER(SEARCH($BR$1,Таблица1[[#This Row],[31_1 Описание и характеристика товара]]))*1 -> 1 | BT62: UNITED PETFOOD PRODUCERS NV | BU62: 33 | BV62: 0 | BW62: 0 | BY62: 0 | CA62: 1 | CB62: 2309101100 | CE62: BE | CF62: 16429.2 | CG62: ОООО-ОО | CH62: 4000000 | CI62: 16296 | CJ62: 0 | CM62: 40933.79 | CN62: 4091684.3 | CO62: 0 | CP62: 1 | CQ62: 4574484.4 | CR62: 50281.05 | CS62: 10 | CT62: 50354.64 | CU62: 3.09 | CV62: 45 | CW62: 2022/09 БР | CX62: ЯШИНА АННА СЕРГЕЕВНА | CY62: 52
A63: 1 | B63: 45215 | C63: =IF(YEAR(Таблица1[[#This Row],[Дата]])=2023,MONTH(Таблица1[[#This Row],[Дата]]),0) -> 10 | D63: 10131010/310723/3267044 | E63: 10131010 | F63: 3267044 | G63: ИМ | H63: 40 | L63: UNITED PETFOOD PRODUCERS NV | M63: 9400, , ERPE-MERE, EVENBROEKVELD 1, | P63: 1 | Q63: 0 | R63: 1 | S63: 33 | T63: 316774600208441 | U63: 770100448470 | V63: ИП ЭСТРИН КИРИЛЛ ВАДИМОВИЧ | W63: 129085, РОССИЯ, МОСКВА, ПРОСПЕКТ МИРА, Д.81, КВ.101 | X63: 45000 | Z63: 316774600208441 | AA63: 770100448470 | AB63: ИП ЭСТРИН КИРИЛЛ ВАДИМОВИЧ | AC63: 129085, РОССИЯ, МОСКВА, ПРОСПЕКТ МИРА, Д.81, КВ.101 | AD63: 45000 | AF63: BE | AG63: БЕЛЬГИЯ | AH63: 4409721.6 | AI63: 316774600208441 | AJ63: 770100448470 | AK63: ИП ЭСТРИН КИРИЛЛ ВАДИМОВИЧ | AL63: 129085, РОССИЯ, МОСКВА, ПРОСПЕКТ МИРА, Д.81, КВ.101 | AM63: 45000 | AO63: BE | AP63: БЕЛЬГИЯ | AQ63: БЕЛЬГИЯ | AR63: RU | AS63: РОССИЯ | AT63: 2 | AU63: 0 | AV63: FCA | AW63: ERPE-MERE | AX63: 1 | AY63: EUR | AZ63: 39465.48 | BC63: 99.9586 | BD63: 10 | BE63: 31 | BF63: 22040387/3292/0000/2/2 | BG63: 10106050-т/п Обнинский | BH63: 11 | BI63: 10106/100913/10053/9 | BL63: КАЛУЖСКАЯ ОБЛ., БОРОВСКИЙ Р-Н | BM63: С. ВОРСИНО | BN63: СЕВЕРНАЯ ПРОМЗОНА, ВЛД. 6 | BO63: 10106050 т/п Обнинский | BQ63: КОРМ ДЛЯ СОБАК И КОШЕК, РАСФАСОВАННЫЙ ДЛЯ РОЗНИЧНОЙ ПРОДАЖИ, БЕЗ СОДЕРЖАНИЯ КРАХМАЛА, БЕЗ СОДЕРЖАНИЯ МОЛОЧНЫХ ПРОДУКТОВ,БЕЗ СОДЕРЖАНИЯ ГМО, В АССОРТИМЕНТЕ | BR63: =ISNUMBER(SEARCH($BR$1,Таблица1[[#This Row],[31_1 Описание и характеристика товара]]))*1 -> 1 | BT63: UNITED PETFOOD PRODUCERS NV | BU63: 33 | BV63: 0 | BW63: 0 | BY63: 0 | CA63: 1 | CB63: 2309101100 | CE63: BE | CF63: 17247.14 | CG63: ОООО-ОО | CH63: 4000000 | CI63: 17203.94 | CJ63: 0 | CM63: 39465.48 | CN63: 3944914.1 | CO63: 0 | CP63: 1 | CQ63: 4409721.6 | CR63: 48470.04 | CS63: 10 | CT63: 48515.111 | CU63: 2.82 | CV63: 45 | CW63: 2022/09 БР | CX63: ЧУДИНА ЭЛЬВИРА РАИСОВНА | CY63: 118
A64: 1 | B64: 45211 | C64: =IF(YEAR(Таблица1[[#This Row],[Дата]])=2023,MONTH(Таблица1[[#This Row],[Дата]]),0) -> 10 | D64: 10131010/310523/3195594 | E64: 10131010 | F64: 3195594 | G64: ИМ | H64: 40 | L64: UNITED PETFOOD PRODUCERS NV | M64: 9400, , ERPE-MERE, EVENBROEKVELD 1, .,.. | P64: 1 | Q64: 0 | R64: 1 | S64: 33 | T64: 316774600208441 | U64: 770100448470 | V64: ИП ЭСТРИН КИРИЛЛ ВАДИМОВИЧ | W64: 129085, РОССИЯ, МОСКВА, ПРОСПЕКТ МИРА, Д.81, КВ.101 | X64: 45000 | Z64: 316774600208441 | AA64: 770100448470 | AB64: ИП ЭСТРИН КИРИЛЛ ВАДИМОВИЧ | AC64: 129085, РОССИЯ, МОСКВА, ПРОСПЕКТ МИРА, Д.81, КВ.101 | AD64: 45000 | AF64: BE | AG64: БЕЛЬГИЯ | AH64: 4321262.5 | AI64: 316774600208441 | AJ64: 770100448470 | AK64: ИП ЭСТРИН КИРИЛЛ ВАДИМОВИЧ | AL64: 129085, РОССИЯ, МОСКВА, ПРОСПЕКТ МИРА, Д.81, КВ.101 | AM64: 45000 | AO64: BE | AP64: БЕЛЬГИЯ | AQ64: БЕЛЬГИЯ | AR64: RU | AS64: РОССИЯ | AT64: 2 | AU64: 0 | AV64: FCA | AW64: ERPE-MERE | AX64: 1 | AY64: EUR | AZ64: 45819.92 | BA64: 3963968 | BB64: 53555.74 | BC64: 86.5119 | BD64: 010 | BF64: 22040387/3292/0000/2/2 | BG64: - | BH64: 99 | BL64: КАЛУЖСКАЯ ОБЛ., БОРОВСКИЙ Р-Н | BM64: С. ВОРСИНО | BN64: СЕВЕРНАЯ ПРОМЗОНА, ВЛАД. 6,,,. | BO64: 10106050 т/п Обнинский | BP64: 1 | BQ64: КОРМ ДЛЯ СОБАК И КОШЕК,РАСФАСОВАННЫЙ ДЛЯ РОЗНИЧНОЙ ПРОДАЖИ,БЕЗ СОДЕРЖАНИЯ КРАХМАЛА,БЕЗ СОДЕРЖАНИЯ МОЛОЧНЫХ ПРОДУКТОВ,В АССОРТИМЕНТЕ | BR64: =ISNUMBER(SEARCH($BR$1,Таблица1[[#This Row],[31_1 Описание и характеристика товара]]))*1 -> 1 | BT64: UNITED PETFOOD PRODUCERS NV | BU64: 33 | BV64: 0 | BW64: 0 | BY64: 0 | CA64: 1 | CB64: 2309101100 | CE64: BE | CF64: 16803.92 | CG64: ОООО-ОО | CH64: 4000000 | CI64: 16803.92 | CJ64: 0 | CM64: 45819.92 | CN64: 3963968 | CO64: 0 | CP64: 1 | CQ64: 4321262.5 | CR64: 53555.74 | CS64: 10 | CT64: 53555.773 | CU64: 3.1871 | CV64: 45 | CW64: 2022/09 БР | CX64: БЛАГОНРАВОВА ДАРЬЯ ДМИТРИЕВНА | CY64: 286
A65: 1 | B65: 45135 | C65: =IF(YEAR(Таблица1[[#This Row],[Дата]])=2023,MONTH(Таблица1[[#This Row],[Дата]]),0) -> 7 | D65: 10131010/310523/3194814 | E65: 10131010 | F65: 3194814 | G65: ИМ | H65: 40 | L65: UNITED PETFOOD PRODUCERS NV | M65: 9400, , ERPE-MERE, EVENBROEKVELD 1, .,.. | P65: 1 | Q65: 0 | R65: 1 | S65: 33 | T65: 316774600208441 | U65: 770100448470 | V65: ИП ЭСТРИН КИРИЛЛ ВАДИМОВИЧ | W65: 129085, РОССИЯ, МОСКВА, ПРОСПЕКТ МИРА, Д.81, КВ.101 | X65: 45000 | Z65: 316774600208441 | AA65: 770100448470 | AB65: ИП ЭСТРИН КИРИЛЛ ВАДИМОВИЧ | AC65: 129085, РОССИЯ, МОСКВА, ПРОСПЕКТ МИРА, Д.81, КВ.101 | AD65: 45000 | AF65: BE | AG65: БЕЛЬГИЯ | AH65: 3936852 | AI65: 316774600208441 | AJ65: 770100448470 | AK65: ИП ЭСТРИН КИРИЛЛ ВАДИМОВИЧ | AL65: 129085, РОССИЯ, МОСКВА, ПРОСПЕКТ МИРА, Д.81, КВ.101 | AM65: 45000 | AO65: BE | AP65: БЕЛЬГИЯ | AQ65: БЕЛЬГИЯ | AR65: RU | AS65: РОССИЯ | AT65: 2 | AU65: 0 | AV65: FCA | AW65: ERPE-MERE | AX65: 1 | AY65: EUR | AZ65: 41376.48 | BA65: 3579558 | BB65: 48791.53 | BC65: 86.5119 | BD65: 010 | BF65: 22040387/3292/0000/2/2 | BG65: - | BH65: 99 | BL65: КАЛУЖСКАЯ ОБЛ., БОРОВСКИЙ Р-Н | BM65: С. ВОРСИНО | BN65: СЕВЕРНАЯ ПРОМЗОНА, ВЛАД. 6,,,. | BO65: 10106050 т/п Обнинский | BP65: 1 | BQ65: КОРМ ДЛЯ СОБАК И КОШЕК, РАСФАСОВАННЫЙ ДЛЯ РОЗНИЧНОЙ ПРОДАЖИ, БЕЗ СОДЕРЖАНИЯ КРАХМАЛА, БЕЗ СОДЕРЖАНИЯ МОЛОЧНЫХ ПРОДУКТОВ,БЕЗ СОДЕРЖАНИЯ ГМО, В АССОРТИМЕНТЕ | BR65: =ISNUMBER(SEARCH($BR$1,Таблица1[[#This Row],[31_1 Описание и характеристика товара]]))*1 -> 1 | BT65: UNITED PETFOOD PRODUCERS NV | BU65: 33 | BV65: 0 | BW65: 0 | BY65: 0 | CA65: 1 | CB65: 2309101100 | CE65: BE | CF65: 16871.78 | CG65: ОООО-ОО | CH65: 4000000 | CI65: 16806.98 | CJ65: 0 | CM65: 41376.48 | CN65: 3579558 | CO65: 0 | CP65: 1 | CQ65: 3936852 | CR65: 48791.53 | CS65: 10 | CT65: 48792.344 | CU65: 2.9031 | CV65: 45 | CW65: 2022/09 БР | CX65: БЛАГОНРАВОВА ДАРЬЯ ДМИТРИЕВНА | CY65: 108
A66: 1 | B66: 45192 | C66: =IF(YEAR(Таблица1[[#This Row],[Дата]])=2023,MONTH(Таблица1[[#This Row],[Дата]]),0) -> 9 | D66: 10131010/310523/3194813 | E66: 10131010 | F66: 3194813 | G66: ИМ | H66: 40 | L66: UNITED PETFOOD PRODUCERS NV | M66: 9400, , ERPE-MERE, EVENBROEKVELD 1, .,.. | P66: 1 | Q66: 0 | R66: 1 | S66: 33 | T66: 316774600208441 | U66: 770100448470 | V66: ИП ЭСТРИН КИРИЛЛ ВАДИМОВИЧ | W66: 129085, РОССИЯ, МОСКВА, ПРОСПЕКТ МИРА, Д.81, КВ.101 | X66: 45000 | Z66: 316774600208441 | AA66: 770100448470 | AB66: ИП ЭСТРИН КИРИЛЛ ВАДИМОВИЧ | AC66: 129085, РОССИЯ, МОСКВА, ПРОСПЕКТ МИРА, Д.81, КВ.101 | AD66: 45000 | AF66: BE | AG66: БЕЛЬГИЯ | AH66: 3822189.2 | AI66: 316774600208441 | AJ66: 770100448470 | AK66: ИП ЭСТРИН КИРИЛЛ ВАДИМОВИЧ | AL66: 129085, РОССИЯ, МОСКВА, ПРОСПЕКТ МИРА, Д.81, КВ.101 | AM66: 45000 | AO66: BE | AP66: БЕЛЬГИЯ | AQ66: БЕЛЬГИЯ | AR66: RU | AS66: РОССИЯ | AT66: 2 | AU66: 0 | AV66: FCA | AW66: ERPE-MERE | AX66: 1 | AY66: EUR | AZ66: 40051.08 | BA66: 3464895 | BB66: 47370.45 | BC66: 86.5119 | BD66: 010 | BF66: 22040387/3292/0000/2/2 | BG66: - | BH66: 99 | BL66: КАЛУЖСКАЯ ОБЛ., БОРОВСКИЙ Р-Н | BM66: С. ВОРСИНО | BN66: СЕВЕРНАЯ ПРОМЗОНА, ВЛАД. 6,,,. | BO66: 10106050 т/п Обнинский | BP66: 1 | BQ66: КОРМ ДЛЯ СОБАК И КОШЕК, РАСФАСOВАННЫЙ ДЛЯ РОЗНИЧНОЙ ПРОДАЖИ, БЕЗ СОДЕРЖАНИЯ КРАХМАЛА, БЕЗ СОДЕРЖАНИЯ МОЛОЧНЫХ ПРОДУКТОВ, В АССОРТИМЕНТЕ: | BR66: =ISNUMBER(SEARCH($BR$1,Таблица1[[#This Row],[31_1 Описание и характеристика товара]]))*1 -> 1 | BT66: UNITED PETFOOD PRODUCERS NV | BU66: 33 | BV66: 0 | BW66: 0 | BY66: 0 | CA66: 1 | CB66: 2309101100 | CE66: BE | CF66: 17096.84 | CG66: ОООО-ОО | CH66: 4000000 | CI66: 17096.84 | CJ66: 0 | CM66: 40051.08 | CN66: 3464895 | CO66: 0 | CP66: 1 | CQ66: 3822189.2 | CR66: 47370.45 | CS66: 10 | CT66: 47370.215 | CU66: 2.7707 | CV66: 45 | CW66: 2022/09 БР | CX66: ЧУДИНА ЭЛЬВИРА РАИСОВНА | CY66: 108
A67: 1 | B67: 45009 | C67: =IF(YEAR(Таблица1[[#This Row],[Дата]])=2023,MONTH(Таблица1[[#This Row],[Дата]]),0) -> 3 | D67: 10131010/310323/3112890 | E67: 10131010 | F67: 3112890 | G67: ИМ | H67: 40 | L67: UNITED PETFOOD PRODUCERS NV | M67: 9400, , ERPE-MERE, EVENBROEKVELD 1, | P67: 1 | Q67: 0 | R67: 1 | S67: 33 | T67: 316774600208441 | U67: 770100448470 | V67: ИП ЭСТРИН КИРИЛЛ ВАДИМОВИЧ | W67: 129085, РОССИЯ, МОСКВА, ПРОСПЕКТ МИРА, Д.81, КВ.101 | X67: 45000 | Z67: 316774600208441 | AA67: 770100448470 | AB67: ИП ЭСТРИН КИРИЛЛ ВАДИМОВИЧ | AC67: 129085, РОССИЯ, МОСКВА, ПРОСПЕКТ МИРА, Д.81, КВ.101 | AD67: 45000 | AF67: BE | AG67: БЕЛЬГИЯ | AH67: 4413109.5 | AI67: 316774600208441 | AJ67: 770100448470 | AK67: ИП ЭСТРИН КИРИЛЛ ВАДИМОВИЧ | AL67: 129085, РОССИЯ, МОСКВА, ПРОСПЕКТ МИРА, Д.81, КВ.101 | AM67: 45000 | AO67: BE | AP67: БЕЛЬГИЯ | AQ67: БЕЛЬГИЯ | AR67: RU | AS67: РОССИЯ | AT67: 2 | AU67: 0 | AV67: FCA | AW67: ERPE-MERE | AX67: 1 | AY67: EUR | AZ67: 48335.1 | BA67: 4048736 | BB67: 57248.95 | BC67: 83.7639 | BD67: 010 | BF67: 22040387/3292/0000/2/2 | BG67: - | BH67: 99 | BL67: КАЛУЖСКАЯ ОБЛ., БОРОВСКИЙ Р-Н | BM67: С. ВОРСИНО | BN67: СЕВЕРНАЯ ПРОМЗОНА, ВЛАД. 6,,,. | BO67: 10106050 т/п Обнинский | BP67: 1 | BQ67: КОРМ ДЛЯ СОБАК И КОШЕК, РАСФАСОВАННЫЙ ДЛЯ РОЗНИЧНОЙ ПРОДАЖИ, БЕЗ СОДЕРЖАНИЯ КРАХМАЛА, БЕЗ СОДЕРЖАНИЯ МОЛОЧНЫХ ПРОДУКТОВ, В АССОРТИМЕНТЕ | BR67: =ISNUMBER(SEARCH($BR$1,Таблица1[[#This Row],[31_1 Описание и характеристика товара]]))*1 -> 1 | BT67: UNITED PETFOOD PRODUCERS NV | BU67: 33 | BV67: 0 | BW67: 0 | BY67: 0 | CA67: 1 | CB67: 2309101100 | CE67: BE | CF67: 16581.45 | CG67: ОООО-ОО | CH67: 4000000 | CI67: 16470.45 | CJ67: 0 | CM67: 48335.1 | CN67: 4048736 | CO67: 0 | CP67: 1 | CQ67: 4413109.5 | CR67: 57248.95 | CS67: 10 | CT67: 57249.637 | CU67: 3.4759 | CV67: 45 | CW67: 2022/09 БР | CX67: БЛАГОНРАВОВА ДАРЬЯ ДМИТРИЕВНА | CY67: 37
A68: 1 | B68: 45131 | C68: =IF(YEAR(Таблица1[[#This Row],[Дата]])=2023,MONTH(Таблица1[[#This Row],[Дата]]),0) -> 7 | D68: 10131010/310323/3112818 | E68: 10131010 | F68: 3112818 | G68: ИМ | H68: 40 | L68: UNITED PETFOOD PRODUCERS NV | M68: 9400, , ERPE-MERE, EVENBROEKVELD 1, | P68: 1 | Q68: 0 | R68: 1 | S68: 38 | T68: 316774600208441 | U68: 770100448470 | V68: ИП ЭСТРИН КИРИЛЛ ВАДИМОВИЧ | W68: 129085, РОССИЯ, МОСКВА, ПРОСПЕКТ МИРА, Д.81, КВ.101 | X68: 45000 | Z68: 316774600208441 | AA68: 770100448470 | AB68: ИП ЭСТРИН КИРИЛЛ ВАДИМОВИЧ | AC68: 129085, РОССИЯ, МОСКВА, ПРОСПЕКТ МИРА, Д.81, КВ.101 | AD68: 45000 | AF68: BE | AG68: БЕЛЬГИЯ | AH68: 4480239.5 | AI68: 316774600208441 | AJ68: 770100448470 | AK68: ИП ЭСТРИН КИРИЛЛ ВАДИМОВИЧ | AL68: 129085, РОССИЯ, МОСКВА, ПРОСПЕКТ МИРА, Д.81, КВ.101 | AM68: 45000 | AO68: BE | AP68: БЕЛЬГИЯ | AQ68: БЕЛЬГИЯ | AR68: RU | AS68: РОССИЯ | AT68: 2 | AU68: 0 | AV68: FCA | AW68: ERPE-MERE | AX68: 1 | AY68: EUR | AZ68: 49136.52 | BA68: 4115867 | BB68: 58119.79 | BC68: 83.7639 | BD68: 010 | BF68: 22040387/3292/0000/2/2 | BG68: - | BH68: 99 | BL68: КАЛУЖСКАЯ ОБЛ., БОРОВСКИЙ Р-Н | BM68: С. ВОРСИНО | BN68: СЕВЕРНАЯ ПРОМЗОНА, ВЛАД. 6,,,. | BO68: 10106050 т/п Обнинский | BP68: 1 | BQ68: КОРМ ДЛЯ СОБАК И КОШЕК, РАСФАСОВАННЫЙ ДЛЯ РОЗНИЧНОЙ ПРОДАЖИ, БЕЗ СОДЕРЖАНИЯ КРАХМАЛА, БЕЗ СОДЕРЖАНИЯ МОЛОЧНЫХ ПРОДУКТОВ, В АССОРТИМЕНТЕ: | BR68: =ISNUMBER(SEARCH($BR$1,Таблица1[[#This Row],[31_1 Описание и характеристика товара]]))*1 -> 1 | BT68: UNITED PETFOOD PRODUCERS NV | BU68: 38 | BV68: 0 | BW68: 0 | BY68: 0 | CA68: 1 | CB68: 2309101100 | CE68: BE | CF68: 19057.73 | CG68: ОООО-ОО | CH68: 4000000 | CI68: 18949.73 | CJ68: 0 | CM68: 49136.52 | CN68: 4115867 | CO68: 0 | CP68: 1 | CQ68: 4480239.5 | CR68: 58119.79 | CS68: 10 | CT68: 58120.717 | CU68: 3.0671 | CV68: 45 | CW68: 2022/09 БР | CX68: ЯШИНА АННА СЕРГЕЕВНА | CY68: 128
A69: 1 | B69: 45199 | C69: =IF(YEAR(Таблица1[[#This Row],[Дата]])=2023,MONTH(Таблица1[[#This Row],[Дата]]),0) -> 9 | D69: 10131010/310323/3112725 | E69: 10131010 | F69: 3112725 | G69: ИМ | H69: 40 | L69: UNITED PETFOOD PRODUCERS NV | M69: 9400, , ERPE-MERE, EVENBROEKVELD 1, | P69: 1 | Q69: 0 | R69: 1 | S69: 33 | T69: 316774600208441 | U69: 770100448470 | V69: ИП ЭСТРИН КИРИЛЛ ВАДИМОВИЧ | W69: 129085, РОССИЯ, МОСКВА, ПРОСПЕКТ МИРА, Д.81, КВ.101 | X69: 45000 | Z69: 316774600208441 | AA69: 770100448470 | AB69: ИП ЭСТРИН КИРИЛЛ ВАДИМОВИЧ | AC69: 129085, РОССИЯ, МОСКВА, ПРОСПЕКТ МИРА, Д.81, КВ.101 | AD69: 45000 | AF69: BE | AG69: БЕЛЬГИЯ | AH69: 4037679.6 | AI69: 316774600208441 | AJ69: 770100448470 | AK69: ИП ЭСТРИН КИРИЛЛ ВАДИМОВИЧ | AL69: 129085, РОССИЯ, МОСКВА, ПРОСПЕКТ МИРА, Д.81, КВ.101 | AM69: 45000 | AO69: BE | AP69: БЕЛЬГИЯ | AQ69: БЕЛЬГИЯ | AR69: RU | AS69: РОССИЯ | AT69: 2 | AU69: 0 | AV69: FCA | AW69: ERPE-MERE | AX69: 1 | AY69: EUR | AZ69: 43853.1 | BA69: 3673307 | BB69: 52378.69 | BC69: 83.7639 | BD69: 010 | BF69: 22040387/3292/0000/2/2 | BG69: - | BH69: 99 | BL69: КАЛУЖСКАЯ ОБЛ., БОРОВСКИЙ Р-Н | BM69: С. ВОРСИНО | BN69: СЕВЕРНАЯ ПРОМЗОНА, ВЛАД. 6,,,. | BO69: 10106050 т/п Обнинский | BP69: 1 | BQ69: КОРМ ДЛЯ СOБАК И КОШЕК, РАСФАСОВАННЫЙ ДЛЯ РОЗНИЧНОЙ ПРОДАЖИ, БЕЗ СОДЕРЖАНИЯ КРАХМАЛА, БЕЗ СОДЕРЖАНИЯ МОЛОЧНЫХ ПРОДУКТОВ,БЕЗ СОДЕРЖАНИЯ ГМО, В АССОРТИМЕНТЕ | BR69: =ISNUMBER(SEARCH($BR$1,Таблица1[[#This Row],[31_1 Описание и характеристика товара]]))*1 -> 1 | BT69: UNITED PETFOOD PRODUCERS NV | BU69: 33 | BV69: 0 | BW69: 0 | BY69: 0 | CA69: 1 | CB69: 2309101100 | CE69: BE | CF69: 15747.01 | CG69: ОООО-ОО | CH69: 4000000 | CI69: 15495.01 | CJ69: 0 | CM69: 43853.1 | CN69: 3673307 | CO69: 0 | CP69: 1 | CQ69: 4037679.6 | CR69: 52378.69 | CS69: 10 | CT69: 52379.332 | CU69: 3.3804 | CV69: 45 | CW69: 2022/09 БР | CX69: ОСИПОВА ТАТЬЯНА ВЛАДИМИРОВНА | CY69: 319
A70: 1 | B70: 44992 | C70: =IF(YEAR(Таблица1[[#This Row],[Дата]])=2023,MONTH(Таблица1[[#This Row],[Дата]]),0) -> 3 | D70: 10131010/310123/3035307 | E70: 10131010 | F70: 3035307 | G70: ИМ | H70: 40 | L70: WELLPET BELGIUM BVBA | M70: 1831, ., DIEGEM, LEONARDO DA VINCILAAN, 19 | P70: 1 | Q70: 0 | R70: 1 | S70: 33 | T70: 1027700221438 | U70: 7718118019 | V70: АО "ВАЛТА ПЕТ ПРОДАКТС" | W70: 115230, РОССИЯ, МОСКВА, ВАРШАВСКОЕ ШОССЕ, Д.42, КОМНАТА 3134, | X70: 45000 | Y70: 772601001 | Z70: 1027700221438 | AA70: 7718118019 | AB70: АО "ВАЛТА ПЕТ ПРОДАКТС" | AC70: 115230, РОССИЯ, МОСКВА, ВАРШАВСКОЕ ШОССЕ, Д.42, КОМНАТА 3134, | AD70: 45000 | AE70: 772601001 | AF70: BE | AG70: БЕЛЬГИЯ | AH70: 3952766 | AI70: 1027700221438 | AJ70: 7718118019 | AK70: АО "ВАЛТА ПЕТ ПРОДАКТС" | AL70: 115230, РОССИЯ, МОСКВА, ВАРШАВСКОЕ ШОССЕ, Д.42, КОМНАТА 3134, | AM70: 45000 | AN70: 772601001 | AO70: BE | AP70: БЕЛЬГИЯ | AQ70: ФРАНЦИЯ | AR70: RU | AS70: РОССИЯ | AT70: 2 | AU70: 0 | AV70: EXW | AW70: GHENT | AX70: 1 | AY70: EUR | AZ70: 49047.14 | BA70: 3716787 | BB70: 56798.57 | BC70: 75.7799 | BD70: 010 | BE70: 31 | BF70: 18090220/1481/1948/2/1 | BG70: - | BH70: 99 | BJ70: . | BL70: СМОЛЕНСКАЯ ОБЛАСТЬ,СМОЛЕНСКИЙ Р-Н | BM70: СЕЛЬСКОЕ ПОСЕЛЕНИЕ СТАБНИНСКОЕ | BN70: СЕВЕРО-ВОСТОЧНЕЕ Д. СТАБНА,НА РАССТОЯНИИ 700 МЕТРО | BO70: 10113100 т/п Стабнинский | BP70: 1 | BQ70: СУХОЙ КОРМ ДЛЯ КОШЕК И СОБАК Т.М. "WELLNESS CORE", РАСФАСОВАННЫЙ ДЛЯ РОЗНИЧНОЙ ПРОДАЖИ В ИНДИВИДУАЛЬНУЮ УПАКОВКУ; СОДЕРЖИТ 10 МАС.% ИЛИ МЕНЕЕ КРАХМАЛА, НЕ СОДЕРЖИТ ГЛЮКОЗУ, МОЛОЧНЫЕ ПРОДУКТЫ И МАЛЬТОДЕКСТРИН | BR70: =ISNUMBER(SEARCH($BR$1,Таблица1[[#This Row],[31_1 Описание и характеристика товара]]))*1 -> 1 | BT70: UNITED PETFOOD FRANCE-UPF | BU70: 33 | BV70: 0 | BW70: 0 | BY70: 0 | CA70: 1 | CB70: 2309101100 | CE70: FR | CF70: 15044.16 | CG70: ОООО-ОО | CH70: 4000000 | CI70: 14931.12 | CJ70: 0 | CM70: 49047.14 | CN70: 3716787 | CO70: 0 | CP70: 1 | CQ70: 3952766 | CR70: 56798.57 | CS70: 10 | CT70: 56797.98 | CU70: 3.804 | CV70: 941 | CW70: 0770/СПБ/161 | CX70: ДАШКИН АЛЕКСЕЙ ХАЛИМОВИЧ | CY70: 221
A71: 1 | B71: 45027 | C71: =IF(YEAR(Таблица1[[#This Row],[Дата]])=2023,MONTH(Таблица1[[#This Row],[Дата]]),0) -> 4 | D71: 10131010/301222/3563723 | E71: 10131010 | F71: 3563723 | G71: ИМ | H71: 40 | L71: ZHONGSHAN POWTEK APPLIANCES MFG.,LTD | M71: , GUANGDONG, ZHONGSHAN, 23 HEALTH ROAD, | P71: 1 | Q71: 0 | R71: 1 | S71: 481 | T71: 1094025002246 | U71: 4025422770 | V71: АО ТАСКОМ | W71: 249020, КАЛУЖСКАЯ ОБЛАСТЬ, РАЙОН БОРОВСКИЙ, СЕЛО ВОРСИНО, СЕВЕРНАЯ ПРОМЫШЛЕННАЯ | X71: 29000 | Y71: 402501001 | Z71: 1157154020979 | AA71: 7104068905 | AB71: ООО ТУЛЬСКИЙ ЗАВОД ГАЗОВОГО ОБОРУДОВАНИЯ | AC71: 301212, ТУЛЬСКАЯ ОБЛАСТЬ, ЩЕКИНСКИЙ М.Р-Н, РАБОЧИЙ ПОСЕЛОК ПЕРВОМАЙСКИЙ Г.П., СИ | AD71: 70000 | AE71: 710401001 | AF71: CN | AG71: КИТАЙ | AH71: 8084712.1 | AI71: 1157154020979 | AJ71: 7104068905 | AK71: ООО ТУЛЬСКИЙ ЗАВОД ГАЗОВОГО ОБОРУДОВАНИЯ | AL71: 301212, ТУЛЬСКАЯ ОБЛАСТЬ, ЩЕКИНСКИЙ М.Р-Н, РАБОЧИЙ ПОСЕЛОК ПЕРВОМАЙСКИЙ Г.П., СИ | AM71: 70000 | AN71: 710401001 | AO71: CN | AP71: КИТАЙ | AQ71: КИТАЙ | AR71: RU | AS71: РОССИЯ | AT71: 1 | AU71: 1 | AV71: FOB | AW71: ZHONGSHAN | AX71: 0 | AY71: CNY | AZ71: 758621 | BA71: 7685286 | BB71: 112322.3 | BC71: 10.1306 | BD71: 010 | BF71: 22100053/3475/0000/2/1 | BG71: - | BH71: 11 | BI71: 10106/100913/10053/8 | BK71: 249020 | BL71: КАЛУЖСКАЯ ОБЛ., БОРОВСКИЙ Р-Н | BM71: С. ВОРСИНО | BN71: СЕВЕРНАЯ ПРОМЗОНА, ВЛД. 6 | BO71: 10106050 т/п Обнинский | BP71: 1 | BQ71: КОТЛЫ ЦЕНТРАЛЬНОГО ОТОПЛЕНИЯ, РАБОТАЮЩИЕ НА ПРИРОДНОМ ИЛИ СЖИЖЕННОМ ГАЗЕ. ПРЕДНАЗНАЧЕНЫ ДЛЯ ОТОПЛЕНИЯ И ГОРЯЧЕГО ВОДОСНАБЖЕНИЯ ЖИЛЫХ ПОМЕЩЕНИЙ. | BR71: =ISNUMBER(SEARCH($BR$1,Таблица1[[#This Row],[31_1 Описание и характеристика товара]]))*1 -> 0 | BT71: POWTEK INTERNATIONAL HOLDINGS LIMITED ZHONGSHAN POWTEK APPLIANCES MFG., LTD. | BU71: 481 | BV71: 1 | BW71: 481 | BX71: ШТ | BY71: 0 | CA71: 1 | CB71: 8403109000 | CE71: CN | CF71: 15152.95 | CG71: ОООО-ОО | CH71: 4000000 | CI71: 15152.95 | CJ71: 0 | CM71: 758621 | CN71: 7685286 | CO71: 0 | CP71: 1 | CQ71: 8084712.1 | CR71: 112322.3 | CS71: 10 | CT71: 7.4126 | CX71: БАТАЕВ ИЛЬЯ СЕРГЕЕВИЧ | CY71: 0
A72: 1 | B72: 45053 | C72: =IF(YEAR(Таблица1[[#This Row],[Дата]])=2023,MONTH(Таблица1[[#This Row],[Дата]]),0) -> 5 | D72: 10131010/301222/3563667 | E72: 10131010 | F72: 3563667 | G72: ИМ | H72: 40 | L72: ZHONGSHAN POWTEK APPLIANCES MFG.,LTD | M72: , GUANGDONG, ZHONGSHAN, 23 HEALTH ROAD, | P72: 2 | Q72: 0 | R72: 2 | S72: 1045 | T72: 1094025002246 | U72: 4025422770 | V72: АО ТАСКОМ | W72: 249020, КАЛУЖСКАЯ ОБЛАСТЬ, РАЙОН БОРОВСКИЙ, СЕЛО ВОРСИНО, СЕВЕРНАЯ ПРОМЫШЛЕННАЯ | X72: 29000 | Y72: 402501001 | Z72: 1157154020979 | AA72: 7104068905 | AB72: ООО ТУЛЬСКИЙ ЗАВОД ГАЗОВОГО ОБОРУДОВАНИЯ | AC72: 301212, ТУЛЬСКАЯ ОБЛАСТЬ, ЩЕКИНСКИЙ М.Р-Н, РАБОЧИЙ ПОСЕЛОК ПЕРВОМАЙСКИЙ Г.П., СИ | AD72: 70000 | AE72: 710401001 | AF72: CN | AG72: КИТАЙ | AH72: 6630716.6 | AI72: 1157154020979 | AJ72: 7104068905 | AK72: ООО ТУЛЬСКИЙ ЗАВОД ГАЗОВОГО ОБОРУДОВАНИЯ | AL72: 301212, ТУЛЬСКАЯ ОБЛАСТЬ, ЩЕКИНСКИЙ М.Р-Н, РАБОЧИЙ ПОСЕЛОК ПЕРВОМАЙСКИЙ Г.П., СИ | AM72: 70000 | AN72: 710401001 | AO72: CN | AP72: КИТАЙ | AQ72: КИТАЙ | AR72: RU | AS72: РОССИЯ | AT72: 1 | AU72: 1 | AV72: FOB | AW72: ZHONGSHAN | AX72: 0 | AY72: CNY | AZ72: 615095.89 | BA72: 6231290 | BB72: 92121.69 | BC72: 10.1306 | BD72: 010 | BF72: 22100053/3475/0000/2/1 | BG72: - | BH72: 11 | BI72: 10106/100913/10053/8 | BK72: 249020 | BL72: КАЛУЖСКАЯ ОБЛ., БОРОВСКИЙ Р-Н | BM72: С. ВОРСИНО | BN72: СЕВЕРНАЯ ПРОМЗОНА, ВЛД. 6 | BO72: 10106050 т/п Обнинский | BP72: 1 | BQ72: КОТЛЫ ЦЕНТРАЛЬНОГО ОТОПЛЕНИЯ, РАБОТАЮЩИЕ НА ПРИРОДНОМ ИЛИ СЖИЖЕННОМ ГАЗЕ. ПРЕДНАЗНАЧЕНЫ ДЛЯ ОТОПЛЕНИЯ И ГОРЯЧЕГО ВОДОСНАБЖЕНИЯ ЖИЛЫХ ПОМЕЩЕНИЙ. | BR72: =ISNUMBER(SEARCH($BR$1,Таблица1[[#This Row],[31_1 Описание и характеристика товара]]))*1 -> 0 | BT72: POWTEK INTERNATIONAL HOLDINGS LIMITED ZHONGSHAN POWTEK APPLIANCES MFG., LTD. | BU72: 119 | BV72: 1 | BW72: 119 | BX72: ШТ | BY72: 0 | CA72: 1 | CB72: 8403109000 | CE72: CN | CF72: 4153.05 | CG72: ОООО-ОО | CH72: 4000000 | CI72: 4153.05 | CJ72: 0 | CM72: 212159 | CN72: 2149298 | CO72: 0 | CP72: 1 | CQ72: 2299807.5 | CR72: 31951.62 | CS72: 10 | CT72: 7.6935 | CX72: БАТАЕВ ИЛЬЯ СЕРГЕЕВИЧ | CY72: 0
A73: 1 | B73: 45040 | C73: =IF(YEAR(Таблица1[[#This Row],[Дата]])=2023,MONTH(Таблица1[[#This Row],[Дата]]),0) -> 4 | D73: 10131010/301123/3394479 | E73: 10131010 | F73: 3394479 | G73: ИМ | H73: 40 | L73: UNITED PETFOOD PRODUCERS NV | M73: 9400, , ERPE-MERE, EVENBROEKVELD 1, | P73: 1 | R73: 1 | S73: 33 | U73: 770100448470 | V73: ИП ЭСТРИН КИРИЛЛ ВАДИМОВИЧ | W73: 129085, РОССИЯ, МОСКВА, ПРОСПЕКТ МИРА, Д.81, КВ.101 | X73: 45000 | AA73: 770100448470 | AB73: ИП ЭСТРИН КИРИЛЛ ВАДИМОВИЧ | AC73: 129085, РОССИЯ, МОСКВА, ПРОСПЕКТ МИРА, Д.81, КВ.101 | AD73: 45000 | AF73: BE | AG73: БЕЛЬГИЯ | AH73: 4228111.5 | AJ73: 770100448470 | AK73: ИП ЭСТРИН КИРИЛЛ ВАДИМОВИЧ | AL73: 129085, РОССИЯ, МОСКВА, ПРОСПЕКТ МИРА, Д.81, КВ.101 | AM73: 45000 | AO73: BE | AP73: БЕЛЬГИЯ | AQ73: БЕЛЬГИЯ | AR73: RU | AS73: РОССИЯ | AT73: 2 | AU73: 0 | AV73: FCA | AW73: ERPE-MERE | AY73: EUR | AZ73: 39308.5 | BC73: 97.6503 | BF73: 22040387/3292/0000/2/2 | BG73: - | BH73: 99 | BL73: "КАЛУЖСКАЯ ОБЛ., БОРОВСКИЙ Р-Н" | BM73: С. ВОРСИНО | BN73: СЕВЕРНАЯ ПРОМЗОНА, ВЛАД. 6 | BO73: 10106050 т/п Обнинский | BQ73: КОРМ ДЛЯ СОБАК, РАСФАСОВАННЫЙ ДЛЯ РОЗНИЧНОЙ ПРОДАЖИ, БЕЗ СОДЕРЖАНИЯ КРАХМАЛА, БЕЗ СОДЕРЖАНИЯ МОЛОЧНЫХ ПРОДУКТОВ, В АССОРТИМЕНТЕ: | BR73: =ISNUMBER(SEARCH($BR$1,Таблица1[[#This Row],[31_1 Описание и характеристика товара]]))*1 -> 1 | BT73: UNITED PETFOOD PRODUCERS NV | BU73: 33 | BV73: 0 | BW73: 0 | BY73: 0 | CA73: 1 | CB73: 2309101100 | CE73: BE | CF73: 16569.69 | CG73: ОООО-ОО | CH73: 4000000 | CI73: 16396.29 | CJ73: 0 | CM73: 39308.5 | CO73: 0 | CP73: 1 | CQ73: 4228111.5 | CR73: 47568.82 | CS73: 10 | CT73: 47549.241 | CU73: 2.9 | CV73: 45 | CX73: ЧУДИНА | CY73: 300
A74: 1 | B74: 44956 | C74: =IF(YEAR(Таблица1[[#This Row],[Дата]])=2023,MONTH(Таблица1[[#This Row],[Дата]]),0) -> 1 | D74: 10131010/301123/3394453 | E74: 10131010 | F74: 3394453 | G74: ИМ | H74: 40 | L74: UNITED PETFOOD PRODUCERS NV | M74: 9400, , ERPE-MERE, EVENBROEKVELD 1, | P74: 1 | R74: 1 | S74: 33 | U74: 770100448470 | V74: ИП ЭСТРИН КИРИЛЛ ВАДИМОВИЧ | W74: 129085, РОССИЯ, МОСКВА, ПРОСПЕКТ МИРА, Д.81, КВ.101 | X74: 45000 | AA74: 770100448470 | AB74: ИП ЭСТРИН КИРИЛЛ ВАДИМОВИЧ | AC74: 129085, РОССИЯ, МОСКВА, ПРОСПЕКТ МИРА, Д.81, КВ.101 | AD74: 45000 | AF74: BE | AG74: БЕЛЬГИЯ | AH74: 4423089.9 | AJ74: 770100448470 | AK74: ИП ЭСТРИН КИРИЛЛ ВАДИМОВИЧ | AL74: 129085, РОССИЯ, МОСКВА, ПРОСПЕКТ МИРА, Д.81, КВ.101 | AM74: 45000 | AO74: BE | AP74: БЕЛЬГИЯ | AQ74: БЕЛЬГИЯ | AR74: RU | AS74: РОССИЯ | AT74: 2 | AU74: 0 | AV74: FCA | AW74: ERPE-MERE | AY74: EUR | AZ74: 41305.2 | BC74: 97.6503 | BF74: 22040387/3292/0000/2/2 | BG74: - | BH74: 99 | BL74: "КАЛУЖСКАЯ ОБЛ., БОРОВСКИЙ Р-Н" | BM74: С. ВОРСИНО | BN74: СЕВЕРНАЯ ПРОМЗОНА, ВЛАД. 6 | BO74: 10106050 т/п Обнинский | BQ74: КОРМ ДЛЯ СОБАК И КОШЕК, РАСФАСОВАННЫЙ ДЛЯ РОЗНИЧНОЙ ПРОДАЖИ, БЕЗ СОДЕРЖАНИЯ КРАХМАЛА, БЕЗ СОДЕРЖАНИЯ МОЛОЧНЫХ ПРОДУКТОВ,БЕЗ СОДЕРЖАНИЯ ГМО, В АССОРТИМЕНТЕ | BR74: =ISNUMBER(SEARCH($BR$1,Таблица1[[#This Row],[31_1 Описание и характеристика товара]]))*1 -> 1 | BT74: UNITED PETFOOD PRODUCERS NV | BU74: 33 | BV74: 0 | BW74: 0 | BY74: 0 | CA74: 1 | CB74: 2309101100 | CE74: BE | CF74: 16952.7 | CG74: ОООО-ОО | CH74: 4000000 | CI74: 16952.7 | CJ74: 0 | CM74: 41305.2 | CO74: 0 | CP74: 1 | CQ74: 4423089.9 | CR74: 49762.44 | CS74: 10 | CT74: 49840.938 | CU74: 2.94 | CV74: 45 | CX74: БЛАГОНРАВОВА | CY74: 155
A75: 1 | B75: 45112 | C75: =IF(YEAR(Таблица1[[#This Row],[Дата]])=2023,MONTH(Таблица1[[#This Row],[Дата]]),0) -> 7 | D75: 10131010/301123/3394004 | E75: 10131010 | F75: 3394004 | G75: ИМ | H75: 40 | L75: UNITED PETFOOD PRODUCERS NV | M75: 9400, , ERPE-MERE, EVENBROEKVELD 1, | P75: 1 | R75: 1 | S75: 33 | U75: 770100448470 | V75: ИП ЭСТРИН КИРИЛЛ ВАДИМОВИЧ | W75: 129085, РОССИЯ, МОСКВА, ПРОСПЕКТ МИРА, Д.81, КВ.101 | X75: 45000 | AA75: 770100448470 | AB75: ИП ЭСТРИН КИРИЛЛ ВАДИМОВИЧ | AC75: 129085, РОССИЯ, МОСКВА, ПРОСПЕКТ МИРА, Д.81, КВ.101 | AD75: 45000 | AF75: BE | AG75: БЕЛЬГИЯ | AH75: 4315823 | AJ75: 770100448470 | AK75: ИП ЭСТРИН КИРИЛЛ ВАДИМОВИЧ | AL75: 129085, РОССИЯ, МОСКВА, ПРОСПЕКТ МИРА, Д.81, КВ.101 | AM75: 45000 | AO75: BE | AP75: БЕЛЬГИЯ | AQ75: БЕЛЬГИЯ | AR75: RU | AS75: РОССИЯ | AT75: 2 | AU75: 0 | AV75: FCA | AW75: ERPE-MERE | AY75: EUR | AZ75: 39506.72 | BC75: 97.6503 | BF75: 22040387/3292/0000/2/2 | BG75: - | BH75: 99 | BL75: "КАЛУЖСКАЯ ОБЛ., БОРОВСКИЙ Р-Н" | BM75: С. ВОРСИНО | BN75: СЕВЕРНАЯ ПРОМЗОНА, ВЛАД. 6 | BO75: 10106050 т/п Обнинский | BQ75: КОРМ ДЛЯ СОБАК И КОШЕК, РАСФАСОВАННЫЙ ДЛЯ РОЗНИЧНОЙ ПРОДАЖИ, БЕЗ СОДЕРЖАНИЯ КРАХМАЛА, БЕЗ СОДЕРЖАНИЯ МОЛОЧНЫХ ПРОДУКТОВ,БЕЗ СОДЕРЖАНИЯ ГМО, В АССОРТИМЕНТЕ | BR75: =ISNUMBER(SEARCH($BR$1,Таблица1[[#This Row],[31_1 Описание и характеристика товара]]))*1 -> 1 | BT75: UNITED PETFOOD PRODUCERS NV | BU75: 33 | BV75: 0 | BW75: 0 | BY75: 0 | CA75: 1 | CB75: 2309101100 | CE75: BE | CF75: 16196.28 | CG75: ОООО-ОО | CH75: 4000000 | CI75: 16196.28 | CJ75: 0 | CM75: 39506.72 | CO75: 0 | CP75: 1 | CQ75: 4315823 | CR75: 48555.62 | CS75: 10 | CT75: 48588.84 | CU75: 3 | CV75: 45 | CX75: ЧУДИНА | CY75: 284
A76: 1 | B76: 45003 | C76: =IF(YEAR(Таблица1[[#This Row],[Дата]])=2023,MONTH(Таблица1[[#This Row],[Дата]]),0) -> 3 | D76: 10131010/301123/3393532 | E76: 10131010 | F76: 3393532 | G76: ИМ | H76: 40 | L76: UNITED PETFOOD PRODUCERS NV | M76: 9400, , ERPE-MERE, EVENBROEKVELD 1, | P76: 1 | R76: 1 | S76: 33 | U76: 770100448470 | V76: ИП ЭСТРИН КИРИЛЛ ВАДИМОВИЧ | W76: 129085, РОССИЯ, МОСКВА, ПРОСПЕКТ МИРА, Д.81, КВ.101 | X76: 45000 | AA76: 770100448470 | AB76: ИП ЭСТРИН КИРИЛЛ ВАДИМОВИЧ | AC76: 129085, РОССИЯ, МОСКВА, ПРОСПЕКТ МИРА, Д.81, КВ.101 | AD76: 45000 | AF76: BE | AG76: БЕЛЬГИЯ | AH76: 4291068.6 | AJ76: 770100448470 | AK76: ИП ЭСТРИН КИРИЛЛ ВАДИМОВИЧ | AL76: 129085, РОССИЯ, МОСКВА, ПРОСПЕКТ МИРА, Д.81, КВ.101 | AM76: 45000 | AO76: BE | AP76: БЕЛЬГИЯ | AQ76: БЕЛЬГИЯ | AR76: RU | AS76: РОССИЯ | AT76: 2 | AU76: 0 | AV76: FCA | AW76: ERPE-MERE | AY76: EUR | AZ76: 39953.22 | BC76: 97.6503 | BF76: 22040387/3292/0000/2/2 | BG76: - | BH76: 99 | BL76: "КАЛУЖСКАЯ ОБЛ., БОРОВСКИЙ Р-Н" | BM76: С. ВОРСИНО | BN76: СЕВЕРНАЯ ПРОМЗОНА, ВЛАД. 6 | BO76: 10106050 т/п Обнинский | BQ76: КОРМ ДЛЯ СОБАК И КОШЕК, РАСФАСОВАННЫЙ ДЛЯ РОЗНИЧНОЙ ПРОДАЖИ, БЕЗ СОДЕРЖАНИЯ КРАХМАЛА, БЕЗ СОДЕРЖАНИЯ МОЛОЧНЫХ ПРОДУКТОВ, В АССОРТИМЕНТЕ; | BR76: =ISNUMBER(SEARCH($BR$1,Таблица1[[#This Row],[31_1 Описание и характеристика товара]]))*1 -> 1 | BT76: UNITED PETFOOD PRODUCERS NV | BU76: 33 | BV76: 0 | BW76: 0 | BY76: 0 | CA76: 1 | CB76: 2309101100 | CE76: BE | CF76: 16956.25 | CG76: ОООО-ОО | CH76: 4000000 | CI76: 16956.25 | CJ76: 0 | CM76: 39953.22 | CO76: 0 | CP76: 1 | CQ76: 4291068.6 | CR76: 48277.12 | CS76: 10 | CT76: 48325.312 | CU76: 2.85 | CV76: 45 | CX76: ОСИПОВА | CY76: 212
A77: 1 | B77: 45095 | C77: =IF(YEAR(Таблица1[[#This Row],[Дата]])=2023,MONTH(Таблица1[[#This Row],[Дата]]),0) -> 6 | D77: 10131010/301023/3360061 | E77: 10131010 | F77: 3360061 | G77: ИМ | H77: 40 | L77: UNITED PETFOOD PRODUCERS NV | M77: 9400, , ERPE-MERE, EVENBROEKVELD 1, | P77: 1 | R77: 1 | S77: 33 | U77: 770100448470 | V77: ИП ЭСТРИН КИРИЛЛ ВАДИМОВИЧ | W77: 129085, РОССИЯ, МОСКВА, ПРОСПЕКТ МИРА, Д.81, КВ.101 | X77: 45000 | AA77: 770100448470 | AB77: ИП ЭСТРИН КИРИЛЛ ВАДИМОВИЧ | AC77: 129085, РОССИЯ, МОСКВА, ПРОСПЕКТ МИРА, Д.81, КВ.101 | AD77: 45000 | AF77: BE | AG77: БЕЛЬГИЯ | AH77: 4773392.4 | AJ77: 770100448470 | AK77: ИП ЭСТРИН КИРИЛЛ ВАДИМОВИЧ | AL77: 129085, РОССИЯ, МОСКВА, ПРОСПЕКТ МИРА, Д.81, КВ.101 | AM77: 45000 | AO77: BE | AP77: БЕЛЬГИЯ | AQ77: БЕЛЬГИЯ | AR77: RU | AS77: РОССИЯ | AT77: 2 | AU77: 0 | AV77: FCA | AW77: ERPE-MERE | AY77: EUR | AZ77: 44544.55 | BC77: 98.3504 | BF77: 22040387/3292/0000/2/2 | BG77: - | BH77: 99 | BL77: "КАЛУЖСКАЯ ОБЛ., БОРОВСКИЙ Р-Н" | BM77: С. ВОРСИНО | BN77: СЕВЕРНАЯ ПРОМЗОНА, ВЛАД. 6 | BO77: 10106050 т/п Обнинский | BQ77: КОРМ ДЛЯ СОБАК И КОШЕК, РАСФАСОВАННЫЙ ДЛЯ РОЗНИЧНОЙ ПРОДАЖИ, БЕЗ СОДЕРЖАНИЯ КРАХМАЛА, БЕЗ СОДЕРЖАНИЯ МОЛОЧНЫХ ПРОДУКТОВ,БЕЗ СОДЕРЖАНИЯ ГМО, В АССОРТИМЕНТЕ | BR77: =ISNUMBER(SEARCH($BR$1,Таблица1[[#This Row],[31_1 Описание и характеристика товара]]))*1 -> 1 | BT77: UNITED PETFOOD PRODUCERS NV | BU77: 33 | BV77: 0 | BW77: 0 | BY77: 0 | CA77: 1 | CB77: 2309101100 | CE77: BE | CF77: 16745.23 | CG77: ОООО-ОО | CH77: 4000000 | CI77: 16745.23 | CJ77: 0 | CM77: 44544.55 | CO77: 0 | CP77: 1 | CQ77: 4773392.4 | CR77: 51207.1 | CS77: 10 | CT77: 51240.404 | CU77: 3.06 | CV77: 45 | CX77: ЧУДИНА | CY77: 236
A78: 1 | B78: 45037 | C78: =IF(YEAR(Таблица1[[#This Row],[Дата]])=2023,MONTH(Таблица1[[#This Row],[Дата]]),0) -> 4 | D78: 10131010/301023/3360055 | E78: 10131010 | F78: 3360055 | G78: ИМ | H78: 40 | L78: UNITED PETFOOD PRODUCERS NV | M78: 9400, , ERPE-MERE, EVENBROEKVELD 1, | P78: 1 | R78: 1 | S78: 33 | U78: 770100448470 | V78: ИП ЭСТРИН КИРИЛЛ ВАДИМОВИЧ | W78: 129085, РОССИЯ, МОСКВА, ПРОСПЕКТ МИРА, Д.81, КВ.101 | X78: 45000 | AA78: 770100448470 | AB78: ИП ЭСТРИН КИРИЛЛ ВАДИМОВИЧ | AC78: 129085, РОССИЯ, МОСКВА, ПРОСПЕКТ МИРА, Д.81, КВ.101 | AD78: 45000 | AF78: BE | AG78: БЕЛЬГИЯ | AH78: 4682364.2 | AJ78: 770100448470 | AK78: ИП ЭСТРИН КИРИЛЛ ВАДИМОВИЧ | AL78: 129085, РОССИЯ, МОСКВА, ПРОСПЕКТ МИРА, Д.81, КВ.101 | AM78: 45000 | AO78: BE | AP78: БЕЛЬГИЯ | AQ78: БЕЛЬГИЯ | AR78: RU | AS78: РОССИЯ | AT78: 2 | AU78: 0 | AV78: FCA | AW78: ERPE-MERE | AY78: EUR | AZ78: 43089 | BC78: 98.3504 | BF78: 22040387/3292/0000/2/2 | BG78: - | BH78: 99 | BL78: "КАЛУЖСКАЯ ОБЛ., БОРОВСКИЙ Р-Н" | BM78: С. ВОРСИНО | BN78: СЕВЕРНАЯ ПРОМЗОНА, ВЛАД. 6 | BO78: 10106050 т/п Обнинский | BQ78: КОРМ ДЛЯ СОБАК И КОШЕК, РАСФАСОВАННЫЙ ДЛЯ РОЗНИЧНОЙ ПРОДАЖИ, БЕЗ СОДЕРЖАНИЯ КРАХМАЛА, БЕЗ СОДЕРЖАНИЯ МОЛОЧНЫХ ПРОДУКТОВ,БЕЗ СОДЕРЖАНИЯ ГМО, В АССОРТИМЕНТЕ | BR78: =ISNUMBER(SEARCH($BR$1,Таблица1[[#This Row],[31_1 Описание и характеристика товара]]))*1 -> 1 | BT78: UNITED PETFOOD PRODUCERS NV | BU78: 33 | BV78: 0 | BW78: 0 | BY78: 0 | CA78: 1 | CB78: 2309101100 | CE78: BE | CF78: 17137.22 | CG78: ОООО-ОО | CH78: 4000000 | CI78: 17137.22 | CJ78: 0 | CM78: 43089 | CO78: 0 | CP78: 1 | CQ78: 4682364.2 | CR78: 50230.58 | CS78: 10 | CT78: 50212.055 | CU78: 2.93 | CV78: 45 | CX78: ОСИПОВА | CY78: 340
A79: 1 | B79: 45203 | C79: =IF(YEAR(Таблица1[[#This Row],[Дата]])=2023,MONTH(Таблица1[[#This Row],[Дата]]),0) -> 10 | D79: 10131010/301023/3359947 | E79: 10131010 | F79: 3359947 | G79: ИМ | H79: 40 | L79: UNITED PETFOOD PRODUCERS NV | M79: 9400, , ERPE-MERE, EVENBROEKVELD 1, | P79: 1 | R79: 1 | S79: 33 | U79: 770100448470 | V79: ИП ЭСТРИН КИРИЛЛ ВАДИМОВИЧ | W79: 129085, РОССИЯ, МОСКВА, ПРОСПЕКТ МИРА, Д.81, КВ.101 | X79: 45000 | AA79: 770100448470 | AB79: ИП ЭСТРИН КИРИЛЛ ВАДИМОВИЧ | AC79: 129085, РОССИЯ, МОСКВА, ПРОСПЕКТ МИРА, Д.81, КВ.101 | AD79: 45000 | AF79: BE | AG79: БЕЛЬГИЯ | AH79: 4667556.6 | AJ79: 770100448470 | AK79: ИП ЭСТРИН КИРИЛЛ ВАДИМОВИЧ | AL79: 129085, РОССИЯ, МОСКВА, ПРОСПЕКТ МИРА, Д.81, КВ.101 | AM79: 45000 | AO79: BE | AP79: БЕЛЬГИЯ | AQ79: БЕЛЬГИЯ | AR79: RU | AS79: РОССИЯ | AT79: 2 | AU79: 0 | AV79: FCA | AW79: ERPE-MERE | AY79: EUR | AZ79: 43468.44 | BC79: 98.3504 | BF79: 22040387/3292/0000/2/2 | BG79: - | BH79: 99 | BL79: "КАЛУЖСКАЯ ОБЛ., БОРОВСКИЙ Р-Н" | BM79: С. ВОРСИНО | BN79: СЕВЕРНАЯ ПРОМЗОНА, ВЛАД. 6 | BO79: 10106050 т/п Обнинский | BQ79: КОРМ ДЛЯ СОБАК И КОШЕК, РАСФАСОВАННЫЙ ДЛЯ РОЗНИЧНОЙ ПРОДАЖИ, БЕЗ СОДЕРЖАНИЯ КРАХМАЛА, БЕЗ СОДЕРЖАНИЯ МОЛОЧНЫХ ПРОДУКТОВ,БЕЗ СОДЕРЖАНИЯ ГМО, В АССОРТИМЕНТЕ | BR79: =ISNUMBER(SEARCH($BR$1,Таблица1[[#This Row],[31_1 Описание и характеристика товара]]))*1 -> 1 | BT79: UNITED PETFOOD PRODUCERS NV | BU79: 33 | BV79: 0 | BW79: 0 | BY79: 0 | CA79: 1 | CB79: 2309101100 | CE79: BE | CF79: 17087 | CG79: ОООО-ОО | CH79: 4000000 | CI79: 17087 | CJ79: 0 | CM79: 43468.44 | CO79: 0 | CP79: 1 | CQ79: 4667556.6 | CR79: 50071.73 | CS79: 10 | CT79: 50064.91 | CU79: 2.93 | CV79: 45 | CX79: БЛАГОНРАВОВА | CY79: 146
A80: 1 | B80: 45258 | C80: =IF(YEAR(Таблица1[[#This Row],[Дата]])=2023,MONTH(Таблица1[[#This Row],[Дата]]),0) -> 11 | D80: 10131010/301023/3359764 | E80: 10131010 | F80: 3359764 | G80: ИМ | H80: 40 | L80: UNITED PETFOOD PRODUCERS NV | M80: 9400, , ERPE-MERE, EVENBROEKVELD 1, | P80: 1 | R80: 1 | S80: 33 | U80: 770100448470 | V80: ИП ЭСТРИН КИРИЛЛ ВАДИМОВИЧ | W80: 129085, РОССИЯ, МОСКВА, ПРОСПЕКТ МИРА, Д.81, КВ.101 | X80: 45000 | AA80: 770100448470 | AB80: ИП ЭСТРИН КИРИЛЛ ВАДИМОВИЧ | AC80: 129085, РОССИЯ, МОСКВА, ПРОСПЕКТ МИРА, Д.81, КВ.101 | AD80: 45000 | AF80: BE | AG80: БЕЛЬГИЯ | AH80: 4689268.4 | AJ80: 770100448470 | AK80: ИП ЭСТРИН КИРИЛЛ ВАДИМОВИЧ | AL80: 129085, РОССИЯ, МОСКВА, ПРОСПЕКТ МИРА, Д.81, КВ.101 | AM80: 45000 | AO80: BE | AP80: БЕЛЬГИЯ | AQ80: БЕЛЬГИЯ | AR80: RU | AS80: РОССИЯ | AT80: 2 | AU80: 0 | AV80: FCA | AW80: ERPE-MERE | AY80: EUR | AZ80: 43159.2 | BC80: 98.3504 | BF80: 22040387/3292/0000/2/2 | BG80: - | BH80: 11 | BL80: "КАЛУЖСКАЯ ОБЛ., БОРОВСКИЙ Р-Н" | BM80: С. ВОРСИНО | BN80: СЕВЕРНАЯ ПРОМЗОНА, ВЛД. 6 | BO80: 10106050 т/п Обнинский | BQ80: КОРМ ДЛЯ СОБАК И КОШЕК, РАСФАСОВАННЫЙ ДЛЯ РОЗНИЧНОЙ ПРОДАЖИ, БЕЗ СОДЕРЖАНИЯ КРАХМАЛА, БЕЗ СОДЕРЖАНИЯ МОЛОЧНЫХ ПРОДУКТОВ, В АССОРТИМЕНТЕ | BR80: =ISNUMBER(SEARCH($BR$1,Таблица1[[#This Row],[31_1 Описание и характеристика товара]]))*1 -> 1 | BT80: UNITED PETFOOD PRODUCERS NV | BU80: 33 | BV80: 0 | BW80: 0 | BY80: 0 | CA80: 1 | CB80: 2309101100 | CE80: BE | CF80: 15554.88 | CG80: ОООО-ОО | CH80: 4000000 | CI80: 15306.48 | CJ80: 0 | CM80: 43159.2 | CO80: 0 | CP80: 1 | CQ80: 4689268.4 | CR80: 50304.65 | CS80: 10 | CT80: 50358.319 | CU80: 3.29 | CV80: 45 | CX80: БЛАГОНРАВОВА | CY80: 89
A81: 1 | B81: 45146 | C81: =IF(YEAR(Таблица1[[#This Row],[Дата]])=2023,MONTH(Таблица1[[#This Row],[Дата]]),0) -> 8 | D81: 10131010/301023/3359705 | E81: 10131010 | F81: 3359705 | G81: ИМ | H81: 40 | L81: UNITED PETFOOD PRODUCERS NV | M81: 9400, , ERPE-MERE, EVENBROEKVELD 1, | P81: 1 | R81: 1 | S81: 33 | U81: 770100448470 | V81: ИП ЭСТРИН КИРИЛЛ ВАДИМОВИЧ | W81: 129085, РОССИЯ, МОСКВА, ПРОСПЕКТ МИРА, Д.81, КВ.101 | X81: 45000 | AA81: 770100448470 | AB81: ИП ЭСТРИН КИРИЛЛ ВАДИМОВИЧ | AC81: 129085, РОССИЯ, МОСКВА, ПРОСПЕКТ МИРА, Д.81, КВ.101 | AD81: 45000 | AF81: BE | AG81: БЕЛЬГИЯ | AH81: 4702254.6 | AJ81: 770100448470 | AK81: ИП ЭСТРИН КИРИЛЛ ВАДИМОВИЧ | AL81: 129085, РОССИЯ, МОСКВА, ПРОСПЕКТ МИРА, Д.81, КВ.101 | AM81: 45000 | AO81: BE | AP81: БЕЛЬГИЯ | AQ81: БЕЛЬГИЯ | AR81: RU | AS81: РОССИЯ | AT81: 2 | AU81: 0 | AV81: FCA | AW81: ERPE-MERE | AY81: EUR | AZ81: 43821.24 | BC81: 98.3504 | BF81: 22040387/3292/0000/2/2 | BG81: - | BH81: 11 | BL81: "КАЛУЖСКАЯ ОБЛ., БОРОВСКИЙ Р-Н" | BM81: С. ВОРСИНО | BN81: СЕВЕРНАЯ ПРОМЗОНА, ВЛД. 6 | BO81: 10106050 т/п Обнинский | BQ81: КОРМ ДЛЯ СОБАК И КОШЕК, РАСФАСОВАННЫЙ ДЛЯ РОЗНИЧНОЙ ПРОДАЖИ, БЕЗ СОДЕРЖАНИЯ КРАХМАЛА, БЕЗ СОДЕРЖАНИЯ МОЛОЧНЫХ ПРОДУКТОВ,БЕЗ СОДЕРЖАНИЯ ГМО, В АССОРТИМЕНТЕ: | BR81: =ISNUMBER(SEARCH($BR$1,Таблица1[[#This Row],[31_1 Описание и характеристика товара]]))*1 -> 1 | BT81: UNITED PETFOOD PRODUCERS NV | BU81: 33 | BV81: 0 | BW81: 0 | BY81: 0 | CA81: 1 | CB81: 2309101100 | CE81: BE | CF81: 16027.11 | CG81: ОООО-ОО | CH81: 4000000 | CI81: 15937.11 | CJ81: 0 | CM81: 43821.24 | CO81: 0 | CP81: 1 | CQ81: 4702254.6 | CR81: 50443.96 | CS81: 10 | CT81: 50520.639 | CU81: 3.17 | CV81: 45 | CX81: ЯШИНА | CY81: 134
A82: 1 | B82: 45162 | C82: =IF(YEAR(Таблица1[[#This Row],[Дата]])=2023,MONTH(Таблица1[[#This Row],[Дата]]),0) -> 8 | D82: 10131010/301023/3359647 | E82: 10131010 | F82: 3359647 | G82: ИМ | H82: 40 | L82: UNITED PETFOOD PRODUCERS NV | M82: 9400, , ERPE-MERE, EVENBROEKVELD 1, | P82: 1 | R82: 1 | S82: 33 | U82: 770100448470 | V82: ИП ЭСТРИН КИРИЛЛ ВАДИМОВИЧ | W82: 129085, РОССИЯ, МОСКВА, ПРОСПЕКТ МИРА, Д.81, КВ.101 | X82: 45000 | AA82: 770100448470 | AB82: ИП ЭСТРИН КИРИЛЛ ВАДИМОВИЧ | AC82: 129085, РОССИЯ, МОСКВА, ПРОСПЕКТ МИРА, Д.81, КВ.101 | AD82: 45000 | AF82: BE | AG82: БЕЛЬГИЯ | AH82: 5029423.1 | AJ82: 770100448470 | AK82: ИП ЭСТРИН КИРИЛЛ ВАДИМОВИЧ | AL82: 129085, РОССИЯ, МОСКВА, ПРОСПЕКТ МИРА, Д.81, КВ.101 | AM82: 45000 | AO82: BE | AP82: БЕЛЬГИЯ | AQ82: БЕЛЬГИЯ | AR82: RU | AS82: РОССИЯ | AT82: 2 | AU82: 0 | AV82: FCA | AW82: ERPE-MERE | AY82: EUR | AZ82: 47147.8 | BC82: 98.3504 | BF82: 22040387/3292/0000/2/2 | BG82: - | BH82: 11 | BL82: "КАЛУЖСКАЯ ОБЛ., БОРОВСКИЙ Р-Н" | BM82: С. ВОРСИНО | BN82: СЕВЕРНАЯ ПРОМЗОНА, ВЛД. 6 | BO82: 10106050 т/п Обнинский | BQ82: КОРМ ДЛЯ СОБАК И КОШЕК, РАСФАСОВАННЫЙ ДЛЯ РОЗНИЧНОЙ ПРОДАЖИ, БЕЗ СОДЕРЖАНИЯ КРАХМАЛА, БЕЗ СОДЕРЖАНИЯ МОЛОЧНЫХ ПРОДУКТОВ,БЕЗ СОДЕРЖАНИЯ ГМО, В АССОРТИМЕНТЕ | BR82: =ISNUMBER(SEARCH($BR$1,Таблица1[[#This Row],[31_1 Описание и характеристика товара]]))*1 -> 1 | BT82: UNITED PETFOOD PRODUCERS NV | BU82: 33 | BV82: 0 | BW82: 0 | BY82: 0 | CA82: 1 | CB82: 2309101100 | CE82: BE | CF82: 16525.08 | CG82: ОООО-ОО | CH82: 4000000 | CI82: 16525.08 | CJ82: 0 | CM82: 47147.8 | CO82: 0 | CP82: 1 | CQ82: 5029423.1 | CR82: 53953.69 | CS82: 10 | CT82: 53871.761 | CU82: 3.26 | CV82: 45 | CX82: ОСИПОВА | CY82: 134
A83: 1 | B83: 45225 | C83: =IF(YEAR(Таблица1[[#This Row],[Дата]])=2023,MONTH(Таблица1[[#This Row],[Дата]]),0) -> 10 | D83: 10131010/300823/5020971 | E83: 10131010 | F83: 5020971 | G83: ИМ | H83: 40 | L83: UNITED PETFOOD PRODUCERS NV | M83: 9400, , ERPE-MERE, EVENBROEKVELD 1, | R83: 1 | S83: 33 | T83: 316774600208441 | U83: 770100448470 | V83: ИП ЭСТРИН КИРИЛЛ ВАДИМОВИЧ | W83: 129085, РОССИЯ, МОСКВА, ПРОСПЕКТ МИРА, Д.81, КВ.101 | X83: 45000 | Z83: 316774600208441 | AA83: 770100448470 | AB83: ИП ЭСТРИН КИРИЛЛ ВАДИМОВИЧ | AC83: 129085, РОССИЯ, МОСКВА, ПРОСПЕКТ МИРА, Д.81, КВ.101 | AD83: 45000 | AF83: BE | AG83: БЕЛЬГИЯ | AH83: 4889413.6 | AI83: 316774600208441 | AJ83: 770100448470 | AK83: ИП ЭСТРИН КИРИЛЛ ВАДИМОВИЧ | AL83: 129085, РОССИЯ, МОСКВА, ПРОСПЕКТ МИРА, Д.81, КВ.101 | AM83: 45000 | AO83: BE | AP83: БЕЛЬГИЯ | AQ83: БЕЛЬГИЯ | AR83: RU | AS83: РОССИЯ | AU83: 0 | AV83: FCA | AW83: ERPE-MERE | AY83: EUR | AZ83: 42601.44 | BC83: 103.4765 | BG83: - | BH83: 11 | BO83: 10106050 т/п Обнинский | BQ83: КОРМ ДЛЯ СОБАК И КОШЕК, РАСФАСОВАННЫЙ ДЛЯ РОЗНИЧНОЙ ПРОДАЖИ, БЕЗ СОДЕРЖАНИЯ КРАХМАЛА, БЕЗ СОДЕРЖАНИЯ МОЛОЧНЫХ ПРОДУКТОВ,БЕЗ СОДЕРЖАНИЯ ГМО, В АССОРТИМЕНТЕ | BR83: =ISNUMBER(SEARCH($BR$1,Таблица1[[#This Row],[31_1 Описание и характеристика товара]]))*1 -> 1 | BT83: UNITED PETFOOD PRODUCERS NV | BU83: 33 | CA83: 1 | CB83: 2309101100 | CE83: BE | CF83: 16809.91 | CG83: ОООО-ОО | CH83: 4000000 | CI83: 16791.91 | CM83: 42601.44 | CO83: 0 | CP83: 1 | CQ83: 4889413.6 | CR83: 51087.31 | CS83: 10 | CT83: 51047.406 | CU83: 3.04 | CY83: 547
A84: 1 | B84: 45282 | C84: =IF(YEAR(Таблица1[[#This Row],[Дата]])=2023,MONTH(Таблица1[[#This Row],[Дата]]),0) -> 12 | D84: 10131010/300823/5020960 | E84: 10131010 | F84: 5020960 | G84: ИМ | H84: 40 | L84: UNITED PETFOOD PRODUCERS NV | M84: 9400, , ERPE-MERE, EVENBROEKVELD 1, | R84: 1 | S84: 33 | T84: 316774600208441 | U84: 770100448470 | V84: ИП ЭСТРИН КИРИЛЛ ВАДИМОВИЧ | W84: 129085, РОССИЯ, МОСКВА, ПРОСПЕКТ МИРА, Д.81, КВ.101 | X84: 45000 | Z84: 316774600208441 | AA84: 770100448470 | AB84: ИП ЭСТРИН КИРИЛЛ ВАДИМОВИЧ | AC84: 129085, РОССИЯ, МОСКВА, ПРОСПЕКТ МИРА, Д.81, КВ.101 | AD84: 45000 | AF84: BE | AG84: БЕЛЬГИЯ | AH84: 5054330.3 | AI84: 316774600208441 | AJ84: 770100448470 | AK84: ИП ЭСТРИН КИРИЛЛ ВАДИМОВИЧ | AL84: 129085, РОССИЯ, МОСКВА, ПРОСПЕКТ МИРА, Д.81, КВ.101 | AM84: 45000 | AO84: BE | AP84: БЕЛЬГИЯ | AQ84: БЕЛЬГИЯ | AR84: RU | AS84: РОССИЯ | AU84: 0 | AV84: FCA | AW84: ERPE-MERE | AY84: EUR | AZ84: 44195.2 | BC84: 103.4765 | BG84: - | BH84: 11 | BO84: 10106050 т/п Обнинский | BQ84: КОРМ ДЛЯ СОБАК И КОШЕК, РАСФАСОВАННЫЙ ДЛЯ РОЗНИЧНОЙ ПРОДАЖИ, БЕЗ СОДЕРЖАНИЯ КРАХМАЛА, БЕЗ СОДЕРЖАНИЯ МОЛОЧНЫХ ПРОДУКТОВ,БЕЗ СОДЕРЖАНИЯ ГМО, В АССОРТИМЕНТЕ | BR84: =ISNUMBER(SEARCH($BR$1,Таблица1[[#This Row],[31_1 Описание и характеристика товара]]))*1 -> 1 | BT84: UNITED PETFOOD PRODUCERS NV | BU84: 33 | CA84: 1 | CB84: 2309101100 | CE84: BE | CF84: 16598.52 | CG84: ОООО-ОО | CH84: 4000000 | CI84: 16533.72 | CM84: 44195.2 | CO84: 0 | CP84: 1 | CQ84: 5054330.3 | CR84: 52810.46 | CS84: 10 | CT84: 52742.567 | CU84: 3.19 | CY84: 4
A85: 1 | B85: 44966 | C85: =IF(YEAR(Таблица1[[#This Row],[Дата]])=2023,MONTH(Таблица1[[#This Row],[Дата]]),0) -> 2 | D85: 10131010/300823/3298530 | E85: 10131010 | F85: 3298530 | G85: ЭК | H85: 40 | L85: UNITED PETFOOD PRODUCERS NV | M85: 9400, , ERPE-MERE, EVENBROEKVELD 1, | R85: 1 | S85: 33 | T85: 316774600208441 | U85: 770100448470 | V85: ИП ЭСТРИН КИРИЛЛ ВАДИМОВИЧ | W85: 129085, РОССИЯ, МОСКВА, ПРОСПЕКТ МИРА, Д.81, КВ.101 | X85: 45000 | Z85: 316774600208441 | AA85: 770100448470 | AB85: ИП ЭСТРИН КИРИЛЛ ВАДИМОВИЧ | AC85: 129085, РОССИЯ, МОСКВА, ПРОСПЕКТ МИРА, Д.81, КВ.101 | AD85: 45000 | AF85: BE | AG85: БЕЛЬГИЯ | AH85: 4570188.6 | AI85: 316774600208441 | AJ85: 770100448470 | AK85: ИП ЭСТРИН КИРИЛЛ ВАДИМОВИЧ | AL85: 129085, РОССИЯ, МОСКВА, ПРОСПЕКТ МИРА, Д.81, КВ.101 | AM85: 45000 | AO85: BE | AP85: БЕЛЬГИЯ | AQ85: БЕЛЬГИЯ | AR85: RU | AS85: РОССИЯ | AU85: 0 | AV85: FCA | AW85: ERPE-MERE | AY85: EUR | AZ85: 40036.44 | BC85: 103.4765 | BG85: - | BH85: 99 | BO85: 10106050 т/п Обнинский | BQ85: КОРМ ДЛЯ СОБАК И КОШЕК, РАСФАСОВАННЫЙ ДЛЯ РОЗНИЧНОЙ ПРОДАЖИ, БЕЗ СОДЕРЖАНИЯ КРАХМАЛА, БЕЗ СОДЕРЖАНИЯ МОЛОЧНЫХ ПРОДУКТОВ, В АССОРТИМЕНТЕ: | BR85: =ISNUMBER(SEARCH($BR$1,Таблица1[[#This Row],[31_1 Описание и характеристика товара]]))*1 -> 1 | BT85: UNITED PETFOOD PRODUCERS NV | BU85: 33 | BV85: 0 | BW85: 0 | CA85: 1 | CB85: 2309101100 | CE85: BE | CF85: 16861.57 | CG85: ОООО-ОО | CH85: 4000000 | CI85: 16796.77 | CJ85: 0 | CM85: 40036.44 | CO85: 0 | CP85: 1 | CQ85: 4570188.6 | CR85: 47751.87 | CS85: 10 | CT85: 47702.827 | CU85: 2.84 | CY85: 71
A86: 1 | B86: 45070 | C86: =IF(YEAR(Таблица1[[#This Row],[Дата]])=2023,MONTH(Таблица1[[#This Row],[Дата]]),0) -> 5 | D86: 10131010/300823/3298510 | E86: 10131010 | F86: 3298510 | G86: ЭК | H86: 40 | L86: UNITED PETFOOD PRODUCERS NV | M86: 9400, , ERPE-MERE, EVENBROEKVELD 1, | R86: 1 | S86: 33 | T86: 316774600208441 | U86: 770100448470 | V86: ИП ЭСТРИН КИРИЛЛ ВАДИМОВИЧ | W86: 129085, РОССИЯ, МОСКВА, ПРОСПЕКТ МИРА, Д.81, КВ.101 | X86: 45000 | Z86: 316774600208441 | AA86: 770100448470 | AB86: ИП ЭСТРИН КИРИЛЛ ВАДИМОВИЧ | AC86: 129085, РОССИЯ, МОСКВА, ПРОСПЕКТ МИРА, Д.81, КВ.101 | AD86: 45000 | AF86: BE | AG86: БЕЛЬГИЯ | AH86: 4716028.4 | AI86: 316774600208441 | AJ86: 770100448470 | AK86: ИП ЭСТРИН КИРИЛЛ ВАДИМОВИЧ | AL86: 129085, РОССИЯ, МОСКВА, ПРОСПЕКТ МИРА, Д.81, КВ.101 | AM86: 45000 | AO86: BE | AP86: БЕЛЬГИЯ | AQ86: БЕЛЬГИЯ | AR86: RU | AS86: РОССИЯ | AU86: 0 | AV86: FCA | AW86: ERPE-MERE | AY86: EUR | AZ86: 41445.84 | BC86: 103.4765 | BG86: - | BH86: 99 | BO86: 10106050 т/п Обнинский | BQ86: КОРМ ДЛЯ СОБАК И КОШЕК, РАСФАСОВАННЫЙ ДЛЯ РОЗНИЧНОЙ ПРОДАЖИ, БЕЗ СОДЕРЖАНИЯ КРАХМАЛА, БЕЗ СОДЕРЖАНИЯ МОЛОЧНЫХ ПРОДУКТОВ,БЕЗ СОДЕРЖАНИЯ ГМО, В АССОРТИМЕНТЕ | BR86: =ISNUMBER(SEARCH($BR$1,Таблица1[[#This Row],[31_1 Описание и характеристика товара]]))*1 -> 1 | BT86: UNITED PETFOOD PRODUCERS NV | BU86: 33 | BV86: 0 | BW86: 0 | CA86: 1 | CB86: 2309101100 | CE86: BE | CF86: 15908.47 | CG86: ОООО-ОО | CH86: 4000000 | CI86: 15746.47 | CJ86: 0 | CM86: 41445.84 | CO86: 0 | CP86: 1 | CQ86: 4716028.4 | CR86: 49275.69 | CS86: 10 | CT86: 49286.451 | CU86: 3.13 | CY86: 586
A87: 1 | B87: 45015 | C87: =IF(YEAR(Таблица1[[#This Row],[Дата]])=2023,MONTH(Таблица1[[#This Row],[Дата]]),0) -> 3 | D87: 10131010/300823/3298467 | E87: 10131010 | F87: 3298467 | G87: ЭК | H87: 40 | L87: UNITED PETFOOD PRODUCERS NV | M87: 9400, , ERPE-MERE, EVENBROEKVELD 1, | R87: 1 | S87: 33 | T87: 316774600208441 | U87: 770100448470 | V87: ИП ЭСТРИН КИРИЛЛ ВАДИМОВИЧ | W87: 129085, РОССИЯ, МОСКВА, ПРОСПЕКТ МИРА, Д.81, КВ.101 | X87: 45000 | Z87: 316774600208441 | AA87: 770100448470 | AB87: ИП ЭСТРИН КИРИЛЛ ВАДИМОВИЧ | AC87: 129085, РОССИЯ, МОСКВА, ПРОСПЕКТ МИРА, Д.81, КВ.101 | AD87: 45000 | AF87: BE | AG87: БЕЛЬГИЯ | AH87: 4959235.4 | AI87: 316774600208441 | AJ87: 770100448470 | AK87: ИП ЭСТРИН КИРИЛЛ ВАДИМОВИЧ | AL87: 129085, РОССИЯ, МОСКВА, ПРОСПЕКТ МИРА, Д.81, КВ.101 | AM87: 45000 | AO87: BE | AP87: БЕЛЬГИЯ | AQ87: БЕЛЬГИЯ | AR87: RU | AS87: РОССИЯ | AU87: 0 | AV87: FCA | AW87: ERPE-MERE | AY87: EUR | AZ87: 43276.2 | BC87: 103.4765 | BG87: - | BH87: 99 | BO87: 10106050 т/п Обнинский | BQ87: КОРМ ДЛЯ СОБАК И КОШЕК, РАСФАСОВАННЫЙ ДЛЯ РОЗНИЧНОЙ ПРОДАЖИ, БЕЗ СОДЕРЖАНИЯ КРАХМАЛА, БЕЗ СОДЕРЖАНИЯ МОЛОЧНЫХ ПРОДУКТОВ,БЕЗ СОДЕРЖАНИЯ ГМО, В АССОРТИМЕНТЕ | BR87: =ISNUMBER(SEARCH($BR$1,Таблица1[[#This Row],[31_1 Описание и характеристика товара]]))*1 -> 1 | BT87: UNITED PETFOOD PRODUCERS NV | BU87: 33 | BV87: 0 | BW87: 0 | CA87: 1 | CB87: 2309101100 | CE87: BE | CF87: 16856.76 | CG87: ОООО-ОО | CH87: 4000000 | CI87: 16791.96 | CJ87: 0 | CM87: 43276.2 | CO87: 0 | CP87: 1 | CQ87: 4959235.4 | CR87: 51816.85 | CS87: 10 | CT87: 51887.156 | CU87: 3.09 | CY87: 361
A88: 1 | B88: 45259 | C88: =IF(YEAR(Таблица1[[#This Row],[Дата]])=2023,MONTH(Таблица1[[#This Row],[Дата]]),0) -> 11 | D88: 10131010/300823/3298066 | E88: 10131010 | F88: 3298066 | G88: ЭК | H88: 40 | L88: UNITED PETFOOD PRODUCERS NV | M88: 9400, , ERPE-MERE, EVENBROEKVELD 1, | R88: 1 | S88: 33 | T88: 316774600208441 | U88: 770100448470 | V88: ИП ЭСТРИН КИРИЛЛ ВАДИМОВИЧ | W88: 129085, РОССИЯ, МОСКВА, ПРОСПЕКТ МИРА, Д.81, КВ.101 | X88: 45000 | Z88: 316774600208441 | AA88: 770100448470 | AB88: ИП ЭСТРИН КИРИЛЛ ВАДИМОВИЧ | AC88: 129085, РОССИЯ, МОСКВА, ПРОСПЕКТ МИРА, Д.81, КВ.101 | AD88: 45000 | AF88: BE | AG88: БЕЛЬГИЯ | AH88: 4664186.7 | AI88: 316774600208441 | AJ88: 770100448470 | AK88: ИП ЭСТРИН КИРИЛЛ ВАДИМОВИЧ | AL88: 129085, РОССИЯ, МОСКВА, ПРОСПЕКТ МИРА, Д.81, КВ.101 | AM88: 45000 | AO88: BE | AP88: БЕЛЬГИЯ | AQ88: БЕЛЬГИЯ | AR88: RU | AS88: РОССИЯ | AU88: 0 | AV88: FCA | AW88: ERPE-MERE | AY88: EUR | AZ88: 40944.84 | BC88: 103.4765 | BG88: - | BH88: 99 | BO88: 10106050 т/п Обнинский | BQ88: КОРМ ДЛЯ СОБАК И КОШЕК, РАСФАСОВАННЫЙ ДЛЯ РОЗНИЧНОЙ ПРОДАЖИ, БЕЗ СОДЕРЖАНИЯ КРАХМАЛА, БЕЗ СОДЕРЖАНИЯ МОЛОЧНЫХ ПРОДУКТОВ,БЕЗ СОДЕРЖАНИЯ ГМО, В АССОРТИМЕНТЕ | BR88: =ISNUMBER(SEARCH($BR$1,Таблица1[[#This Row],[31_1 Описание и характеристика товара]]))*1 -> 1 | BT88: UNITED PETFOOD PRODUCERS NV | BU88: 33 | BV88: 0 | BW88: 0 | CA88: 1 | CB88: 2309101100 | CE88: BE | CF88: 16861.57 | CG88: ОООО-ОО | CH88: 4000000 | CI88: 16796.77 | CJ88: 0 | CM88: 40944.84 | CO88: 0 | CP88: 1 | CQ88: 4664186.7 | CR88: 48734.02 | CS88: 10 | CT88: 48710.633 | CU88: 2.9 | CY88: 544
A89: 1 | B89: 45041 | C89: =IF(YEAR(Таблица1[[#This Row],[Дата]])=2023,MONTH(Таблица1[[#This Row],[Дата]]),0) -> 4 | D89: 10131010/300623/3236617 | E89: 10131010 | F89: 3236617 | G89: ЭК | H89: 40 | L89: UNITED PETFOOD PRODUCERS NV | M89: 9400, , ERPE-MERE, EVENBROEKVELD 1, | P89: 1 | Q89: 0 | R89: 1 | S89: 33 | T89: 316774600208441 | U89: 770100448470 | V89: ИП ЭСТРИН КИРИЛЛ ВАДИМОВИЧ | W89: 129085, РОССИЯ, МОСКВА, ПРОСПЕКТ МИРА, Д.81, КВ.101 | X89: 45000 | Z89: 316774600208441 | AA89: 770100448470 | AB89: ИП ЭСТРИН КИРИЛЛ ВАДИМОВИЧ | AC89: 129085, РОССИЯ, МОСКВА, ПРОСПЕКТ МИРА, Д.81, КВ.101 | AD89: 45000 | AF89: BE | AG89: БЕЛЬГИЯ | AH89: 4600295.6 | AI89: 316774600208441 | AJ89: 770100448470 | AK89: ИП ЭСТРИН КИРИЛЛ ВАДИМОВИЧ | AL89: 129085, РОССИЯ, МОСКВА, ПРОСПЕКТ МИРА, Д.81, КВ.101 | AM89: 45000 | AO89: BE | AP89: БЕЛЬГИЯ | AQ89: БЕЛЬГИЯ | AR89: RU | AS89: РОССИЯ | AT89: 2 | AU89: 0 | AV89: FCA | AW89: ERPE-MERE | AX89: 1 | AY89: EUR | AZ89: 44240.6 | BA89: 4207511 | BB89: 52856.24 | BC89: 95.1052 | BD89: 010 | BF89: 22040387/3292/0000/2/2 | BG89: - | BH89: 99 | BL89: КАЛУЖСКАЯ ОБЛ., БОРОВСКИЙ Р-Н | BM89: С. ВОРСИНО | BN89: СЕВЕРНАЯ ПРОМЗОНА, ВЛАД. 6,,,. | BO89: 10106050 т/п Обнинский | BP89: 1 | BQ89: КОРМ ДЛЯ СОБАК И КОШЕК, РАСФАСОВАННЫЙ ДЛЯ РОЗНИЧНОЙ ПРОДАЖИ, БЕЗ СОДЕРЖАHИЯ КРАХМАЛА, БЕЗ СОДЕРЖАНИЯ МОЛОЧНЫХ ПРОДУКТОВ, В АССОРТИМЕНТЕ: | BR89: =ISNUMBER(SEARCH($BR$1,Таблица1[[#This Row],[31_1 Описание и характеристика товара]]))*1 -> 1 | BT89: UNITED PETFOOD PRODUCERS NV | BU89: 33 | BV89: 0 | BW89: 0 | BY89: 0 | CA89: 1 | CB89: 2309101100 | CE89: BE | CF89: 16161.43 | CG89: ОООО-ОО | CH89: 4000000 | CI89: 16042.03 | CJ89: 0 | CM89: 44240.6 | CN89: 4207511 | CO89: 0 | CP89: 1 | CQ89: 4600295.6 | CR89: 52856.24 | CS89: 10 | CT89: 52778.279 | CU89: 3.29 | CV89: 45 | CW89: 2022/09 БР | CX89: ЧУДИНА ЭЛЬВИРА РАИСОВНА | CY89: 96
A90: 1 | B90: 45172 | C90: =IF(YEAR(Таблица1[[#This Row],[Дата]])=2023,MONTH(Таблица1[[#This Row],[Дата]]),0) -> 9 | D90: 10131010/300623/3236356 | E90: 10131010 | F90: 3236356 | G90: ЭК | H90: 40 | L90: UNITED PETFOOD PRODUCERS NV | M90: 9400, , ERPE-MERE, EVENBROEKVELD 1, | P90: 1 | Q90: 0 | R90: 1 | S90: 33 | T90: 316774600208441 | U90: 770100448470 | V90: ИП ЭСТРИН КИРИЛЛ ВАДИМОВИЧ | W90: 129085, РОССИЯ, МОСКВА, ПРОСПЕКТ МИРА, Д.81, КВ.101 | X90: 45000 | Z90: 316774600208441 | AA90: 770100448470 | AB90: ИП ЭСТРИН КИРИЛЛ ВАДИМОВИЧ | AC90: 129085, РОССИЯ, МОСКВА, ПРОСПЕКТ МИРА, Д.81, КВ.101 | AD90: 45000 | AF90: BE | AG90: БЕЛЬГИЯ | AH90: 4767338.4 | AI90: 316774600208441 | AJ90: 770100448470 | AK90: ИП ЭСТРИН КИРИЛЛ ВАДИМОВИЧ | AL90: 129085, РОССИЯ, МОСКВА, ПРОСПЕКТ МИРА, Д.81, КВ.101 | AM90: 45000 | AO90: BE | AP90: БЕЛЬГИЯ | AQ90: БЕЛЬГИЯ | AR90: RU | AS90: РОССИЯ | AT90: 2 | AU90: 0 | AV90: FCA | AW90: ERPE-MERE | AX90: 1 | AY90: EUR | AZ90: 45477 | BA90: 4325099 | BB90: 54775.52 | BC90: 95.1052 | BD90: 010 | BF90: 22040387/3292/0000/2/2 | BG90: - | BH90: 99 | BL90: КАЛУЖСКАЯ ОБЛ., БОРОВСКИЙ Р-Н | BM90: С. ВОРСИНО | BN90: СЕВЕРНАЯ ПРОМЗОНА, ВЛАД. 6,,,. | BO90: 10106050 т/п Обнинский | BP90: 1 | BQ90: КОРМ ДЛЯ СОБАК И КОШЕК, РАСФАСОВАННЫЙ ДЛЯ РОЗНИЧНОЙ ПРОДАЖИ, БЕЗ СОДЕРЖАНИЯ КРАХМАЛА, БЕЗ СОДЕРЖАНИЯ МОЛОЧНЫХ ПРОДУКТОВ; В АССОРТИМЕНТЕ: | BR90: =ISNUMBER(SEARCH($BR$1,Таблица1[[#This Row],[31_1 Описание и характеристика товара]]))*1 -> 1 | BT90: UNITED PETFOOD PRODUCERS NV | BU90: 33 | BV90: 0 | BW90: 0 | BY90: 0 | CA90: 1 | CB90: 2309101100 | CE90: BE | CF90: 16803 | CG90: ОООО-ОО | CH90: 4000000 | CI90: 16749 | CJ90: 0 | CM90: 45477 | CN90: 4325099 | CO90: 0 | CP90: 1 | CQ90: 4767338.4 | CR90: 54775.52 | CS90: 10 | CT90: 54769.23 | CU90: 3.27 | CV90: 45 | CW90: 2022/09 БР | CX90: ЧУДИНА ЭЛЬВИРА РАИСОВНА | CY90: 96
A91: 1 | B91: 45080 | C91: =IF(YEAR(Таблица1[[#This Row],[Дата]])=2023,MONTH(Таблица1[[#This Row],[Дата]]),0) -> 6 | D91: 10131010/300523/3193814 | E91: 10131010 | F91: 3193814 | G91: ЭК | H91: 40 | L91: UNITED PETFOOD PRODUCERS NV | M91: 9400, , ERPE-MERE, EVENBROEKVELD 1, .,.. | P91: 1 | Q91: 0 | R91: 1 | S91: 33 | T91: 316774600208441 | U91: 770100448470 | V91: ИП ЭСТРИН КИРИЛЛ ВАДИМОВИЧ | W91: 129085, РОССИЯ, МОСКВА, ПРОСПЕКТ МИРА, Д.81, КВ.101 | X91: 45000 | Z91: 316774600208441 | AA91: 770100448470 | AB91: ИП ЭСТРИН КИРИЛЛ ВАДИМОВИЧ | AC91: 129085, РОССИЯ, МОСКВА, ПРОСПЕКТ МИРА, Д.81, КВ.101 | AD91: 45000 | AF91: BE | AG91: БЕЛЬГИЯ | AH91: 3705921.2 | AI91: 316774600208441 | AJ91: 770100448470 | AK91: ИП ЭСТРИН КИРИЛЛ ВАДИМОВИЧ | AL91: 129085, РОССИЯ, МОСКВА, ПРОСПЕКТ МИРА, Д.81, КВ.101 | AM91: 45000 | AO91: BE | AP91: БЕЛЬГИЯ | AQ91: БЕЛЬГИЯ | AR91: RU | AS91: РОССИЯ | AT91: 2 | AU91: 0 | AV91: FCA | AW91: ERPE-MERE | AX91: 1 | AY91: EUR | AZ91: 39011.62 | BA91: 3351149 | BB91: 46291.9 | BC91: 85.9013 | BD91: 010 | BF91: 22040387/3292/0000/2/2 | BG91: - | BH91: 99 | BL91: КАЛУЖСКАЯ ОБЛ., БОРОВСКИЙ Р-Н | BM91: С. ВОРСИНО | BN91: СЕВЕРНАЯ ПРОМЗОНА, ВЛАД. 6,,,. | BO91: 10106050 т/п Обнинский | BP91: 1 | BQ91: КОРМ ДЛЯ СОБАК И КОШЕК, РАСФАСОBАННЫЙ ДЛЯ РОЗНИЧНОЙ ПРОДАЖИ, БЕЗ СОДЕРЖАНИЯ КРАХМАЛА, БЕЗ СОДЕРЖАНИЯ МОЛОЧНЫХ ПРОДУКТОВ,БЕЗ СОДЕРЖАНИЯ ГМО, В АССОРТИМЕНТЕ | BR91: =ISNUMBER(SEARCH($BR$1,Таблица1[[#This Row],[31_1 Описание и характеристика товара]]))*1 -> 1 | BT91: UNITED PETFOOD PRODUCERS NV | BU91: 33 | BV91: 0 | BW91: 0 | BY91: 0 | CA91: 1 | CB91: 2309101100 | CE91: BE | CF91: 17089.26 | CG91: ОООО-ОО | CH91: 4000000 | CI91: 17089.26 | CJ91: 0 | CM91: 39011.62 | CN91: 3351149 | CO91: 0 | CP91: 1 | CQ91: 3705921.2 | CR91: 46291.9 | CS91: 10 | CT91: 46291.387 | CU91: 2.7088 | CV91: 45 | CW91: 2022/09 БР | CX91: БЛАГОНРАВОВА ДАРЬЯ ДМИТРИЕВНА | CY91: 152
A92: 1 | B92: 45064 | C92: =IF(YEAR(Таблица1[[#This Row],[Дата]])=2023,MONTH(Таблица1[[#This Row],[Дата]]),0) -> 5 | D92: 10131010/300323/3111138 | E92: 10131010 | F92: 3111138 | G92: ЭК | H92: 40 | L92: UNITED PETFOOD PRODUCERS NV | M92: 9400, , ERPE-MERE, EVENBROEKVELD 1, | P92: 1 | Q92: 0 | R92: 1 | S92: 38 | T92: 316774600208441 | U92: 770100448470 | V92: ИП ЭСТРИН КИРИЛЛ ВАДИМОВИЧ | W92: 129085, РОССИЯ, МОСКВА, ПРОСПЕКТ МИРА, Д.81, КВ.101 | X92: 45000 | Z92: 316774600208441 | AA92: 770100448470 | AB92: ИП ЭСТРИН КИРИЛЛ ВАДИМОВИЧ | AC92: 129085, РОССИЯ, МОСКВА, ПРОСПЕКТ МИРА, Д.81, КВ.101 | AD92: 45000 | AF92: BE | AG92: БЕЛЬГИЯ | AH92: 4208180.3 | AI92: 316774600208441 | AJ92: 770100448470 | AK92: ИП ЭСТРИН КИРИЛЛ ВАДИМОВИЧ | AL92: 129085, РОССИЯ, МОСКВА, ПРОСПЕКТ МИРА, Д.81, КВ.101 | AM92: 45000 | AO92: BE | AP92: БЕЛЬГИЯ | AQ92: БЕЛЬГИЯ | AR92: RU | AS92: РОССИЯ | AT92: 2 | AU92: 0 | AV92: FCA | AW92: ERPE-MERE | AX92: 1 | AY92: EUR | AZ92: 46055.88 | BA92: 3845017 | BB92: 54667.24 | BC92: 83.4859 | BD92: 010 | BF92: 22040387/3292/0000/2/2 | BG92: - | BH92: 99 | BL92: КАЛУЖСКАЯ ОБЛ., БОРОВСКИЙ Р-Н | BM92: С. ВОРСИНО | BN92: СЕВЕРНАЯ ПРОМЗОНА, ВЛАД. 6,,,. | BO92: 10106050 т/п Обнинский | BP92: 1 | BQ92: КОРМ ДЛЯ СОБАК, РАСФАСОВАННЫЙ ДЛЯ РОЗНИЧНОЙ ПРОДАЖИ, БЕЗ СОДЕРЖАНИЯ КРАХМАЛА; БЕЗ СОДЕРЖАНИЯ МОЛОЧНЫХ ПРОДУКТОВ,БЕЗ СОДЕРЖАНИЯ ГМО, В АССОРТИМЕНТЕ: | BR92: =ISNUMBER(SEARCH($BR$1,Таблица1[[#This Row],[31_1 Описание и характеристика товара]]))*1 -> 1 | BT92: UNITED PETFOOD PRODUCERS NV | BU92: 38 | BV92: 0 | BW92: 0 | BY92: 0 | CA92: 1 | CB92: 2309101100 | CE92: BE | CF92: 18579.21 | CG92: ОООО-ОО | CH92: 4000000 | CI92: 18275.61 | CJ92: 0 | CM92: 46055.88 | CN92: 3845017 | CO92: 0 | CP92: 1 | CQ92: 4208180.3 | CR92: 54667.24 | CS92: 10 | CT92: 54667.832 | CU92: 2.9913 | CV92: 45 | CW92: 2022/09 БР | CX92: ЯШИНА АННА СЕРГЕЕВНА | CY92: 174
