Workbook

Sheet Задание
B2: Домашнее задание №1
B4: Описание
C5: Компания осуществляет продажи кормов для домашних животных
C7: Продукция компании:
C8: По видам животных: собаки и кошки
C9: По каналам продаж: онлайн и офлайн
C10: По сегментам: эконом и премиум
C11: Всего 80 продуктов (по 10 каждого типа)
C13: На листах приведены следующие данные:
C14: 1. Объем продаж (тонн)
C15: 2. Цены реализации - два листа (руб./кг)
C16: 3. Расходы на единицу товара (руб./кг)
B18: Задание
C19: 1. Свести* все данные (продажи, цены и расходы) на лист "Фин.результат" - обязательно, чтобы были ссылки на исходные данные цифры
C20: 2. Рассчитать следующие показатели по каждому продукту и по всем уровням (виды животных, каналы, сегменты) - по месяцам и просуммировать по годам
C21: Выручка
C22: Себестоимость
C23: Валовая прибыль (выручка - себестоимость)
C24: Валовая маржа (1 - себестоимость/выручка)
C26: * На сводном листе должно быть все залинковано на исходные листы
C27: * Аккуратно все структурировать и сгруппировать, закрепить столбцы/строки
C28: * Использовать корректные форматы чисел
C29: * Единообразный формат (заголовки, ссылки, итоги и пр.)
B31: Hints
C33: На всех исходных листах данные идут по порядку и имеют одинаковую структуру - не надо менять порядок!!!
C34: Можно ничего не менять на исходных листах
C35: Не нужно использовать никакие формулы, кроме "СУММ"

Sheet Фин.результат
D1: янв | E1: фев | F1: мар | G1: апр | H1: май | I1: июн | J1: июл | K1: авг | L1: сен | M1: окт | N1: ноя | O1: дек
A3: Объем продаж, т | D3: =D5+D53 -> 1995.2291 | E3: =E5+E53 -> 2151.5813 | F3: =F5+F53 -> 2571.5083 | G3: =G5+G53 -> 2578.5664 | H3: =H5+H53 -> 2821.3366 | I3: =I5+I53 -> 2231.9478 | J3: =J5+J53 -> 2546.578 | K3: =K5+K53 -> 2607.2525 | ... O3: =O5+O53 -> 2320.8746
A5: Корма для собак | D5: =D6+D29 -> 919.94381 | E5: =E6+E29 -> 998.03579 | F5: =F6+F29 -> 809.13426 | G5: =G6+G29 -> 1056.9313 | H5: =H6+H29 -> 1313.3957 | I5: =I6+I29 -> 1089.8733 | J5: =J6+J29 -> 1223.8686 | K5: =K6+K29 -> 1003.0931 | ... O5: =O6+O29 -> 1212.1195
A6: Онлайн продажи | D6: =D7+D18 -> 533.23056 | E6: =E7+E18 -> 455.27274 | F6: =F7+F18 -> 429.03799 | G6: =G7+G18 -> 582.84872 | H6: =H7+H18 -> 543.47727 | I6: =I7+I18 -> 551.11623 | J6: =J7+J18 -> 686.88686 | K6: =K7+K18 -> 485.73849 | ... O6: =O7+O18 -> 618.56699
A7: Эконом сегмент | D7: =SUM(D8:D17) -> 221.90827 | E7: =SUM(E8:E17) -> 224.12759 | F7: =SUM(F8:F17) -> 187.02007 | G7: =SUM(G8:G17) -> 355.95477 | H7: =SUM(H8:H17) -> 232.46749 | I7: =SUM(I8:I17) -> 330.94173 | J7: =SUM(J8:J17) -> 408.81103 | K7: =SUM(K8:K17) -> 226.63795 | ... O7: =SUM(O8:O17) -> 319.43778
A8: Бренд 1 | D8: ='продажи натураль.'!C7 -> 2.9205887 | E8: ='продажи натураль.'!D7 -> 9.5115027 | F8: ='продажи натураль.'!E7 -> 2.9569522 | G8: ='продажи натураль.'!F7 -> 29.085696 | H8: ='продажи натураль.'!G7 -> 3.7609401 | I8: ='продажи натураль.'!H7 -> 11.350544 | J8: ='продажи натураль.'!I7 -> 3.8941279 | K8: ='продажи натураль.'!J7 -> 3.6616761 | ... O8: ='продажи натураль.'!N7 -> 53.665164
A9: Бренд 2 | D9: ='продажи натураль.'!C8 -> 63.328307 | E9: ='продажи натураль.'!D8 -> 4.0526806 | F9: ='продажи натураль.'!E8 -> 27.224039 | G9: ='продажи натураль.'!F8 -> 83.106754 | H9: ='продажи натураль.'!G8 -> 22.786039 | I9: ='продажи натураль.'!H8 -> 19.789918 | J9: ='продажи натураль.'!I8 -> 6.3226629 | K9: ='продажи натураль.'!J8 -> 5.2214759 | ... O9: ='продажи натураль.'!N8 -> 7.1655691
A10: Бренд 3 | D10: ='продажи натураль.'!C9 -> 16.518393 | E10: ='продажи натураль.'!D9 -> 36.923947 | F10: ='продажи натураль.'!E9 -> 15.942065 | G10: ='продажи натураль.'!F9 -> 20.3666 | H10: ='продажи натураль.'!G9 -> 16.145601 | I10: ='продажи натураль.'!H9 -> 78.158713 | J10: ='продажи натураль.'!I9 -> 1.4517819 | K10: ='продажи натураль.'!J9 -> 34.545601 | ... O10: ='продажи натураль.'!N9 -> 44.390783
A11: Бренд 4 | D11: ='продажи натураль.'!C10 -> 12.874416 | E11: ='продажи натураль.'!D10 -> 1.2416532 | F11: ='продажи натураль.'!E10 -> 2.1283363 | G11: ='продажи натураль.'!F10 -> 12.025692 | H11: ='продажи натураль.'!G10 -> 33.936827 | I11: ='продажи натураль.'!H10 -> 15.260464 | J11: ='продажи натураль.'!I10 -> 62.370072 | K11: ='продажи натураль.'!J10 -> 69.458365 | ... O11: ='продажи натураль.'!N10 -> 26.896586
A12: Бренд 5 | D12: ='продажи натураль.'!C11 -> 47.452926 | E12: ='продажи натураль.'!D11 -> 9.6306634 | F12: ='продажи натураль.'!E11 -> 35.649551 | G12: ='продажи натураль.'!F11 -> 47.427644 | H12: ='продажи натураль.'!G11 -> 43.393758 | I12: ='продажи натураль.'!H11 -> 16.977001 | J12: ='продажи натураль.'!I11 -> 81.981773 | K12: ='продажи натураль.'!J11 -> 41.966994 | ... O12: ='продажи натураль.'!N11 -> 91.405769
A13: Бренд 6 | D13: ='продажи натураль.'!C12 -> 44.872531 | E13: ='продажи натураль.'!D12 -> 30.26307 | F13: ='продажи натураль.'!E12 -> 15.036106 | G13: ='продажи натураль.'!F12 -> 74.064884 | H13: ='продажи натураль.'!G12 -> 21.725135 | I13: ='продажи натураль.'!H12 -> 34.962944 | J13: ='продажи натураль.'!I12 -> 34.955475 | K13: ='продажи натураль.'!J12 -> 8.5644655 | ... O13: ='продажи натураль.'!N12 -> 1.9500381
A14: Бренд 7 | D14: ='продажи натураль.'!C13 -> 0.69506707 | E14: ='продажи натураль.'!D13 -> 53.460415 | F14: ='продажи натураль.'!E13 -> 39.073368 | G14: ='продажи натураль.'!F13 -> 23.516107 | H14: ='продажи натураль.'!G13 -> 47.78267 | I14: ='продажи натураль.'!H13 -> 17.272478 | J14: ='продажи натураль.'!I13 -> 20.560933 | K14: ='продажи натураль.'!J13 -> 21.882708 | ... O14: ='продажи натураль.'!N13 -> 62.349359
A15: Бренд 8 | D15: ='продажи натураль.'!C14 -> 4.149572 | E15: ='продажи натураль.'!D14 -> 39.488109 | F15: ='продажи натураль.'!E14 -> 25.265471 | G15: ='продажи натураль.'!F14 -> 22.456329 | H15: ='продажи натураль.'!G14 -> 15.648039 | I15: ='продажи натураль.'!H14 -> 35.713431 | J15: ='продажи натураль.'!I14 -> 52.085634 | K15: ='продажи натураль.'!J14 -> 17.240299 | ... O15: ='продажи натураль.'!N14 -> 11.967719
A16: Бренд 9 | D16: ='продажи натураль.'!C15 -> 21.640559 | E16: ='продажи натураль.'!D15 -> 7.17299 | F16: ='продажи натураль.'!E15 -> 8.3276978 | G16: ='продажи натураль.'!F15 -> 14.920891 | H16: ='продажи натураль.'!G15 -> 19.478847 | I16: ='продажи натураль.'!H15 -> 33.763382 | J16: ='продажи натураль.'!I15 -> 55.733841 | K16: ='продажи натураль.'!J15 -> 11.74505 | ... O16: ='продажи натураль.'!N15 -> 1.7100472
A17: Бренд 10 | D17: ='продажи натураль.'!C16 -> 7.4559148 | E17: ='продажи натураль.'!D16 -> 32.382564 | F17: ='продажи натураль.'!E16 -> 15.416481 | G17: ='продажи натураль.'!F16 -> 28.984176 | H17: ='продажи натураль.'!G16 -> 7.8096338 | I17: ='продажи натураль.'!H16 -> 67.692854 | J17: ='продажи натураль.'!I16 -> 89.454724 | K17: ='продажи натураль.'!J16 -> 12.351313 | ... O17: ='продажи натураль.'!N16 -> 17.936745
A18: Премиум сегмент | D18: =SUM(D19:D28) -> 311.32228 | E18: =SUM(E19:E28) -> 231.14514 | F18: =SUM(F19:F28) -> 242.01792 | G18: =SUM(G19:G28) -> 226.89395 | H18: =SUM(H19:H28) -> 311.00977 | I18: =SUM(I19:I28) -> 220.17451 | J18: =SUM(J19:J28) -> 278.07584 | K18: =SUM(K19:K28) -> 259.10054 | ... O18: =SUM(O19:O28) -> 299.12921
A19: Бренд 1 | D19: ='продажи натураль.'!C18 -> 49.34092 | E19: ='продажи натураль.'!D18 -> 27.1361 | F19: ='продажи натураль.'!E18 -> 28.929057 | G19: ='продажи натураль.'!F18 -> 7.7460073 | H19: ='продажи натураль.'!G18 -> 37.374258 | I19: ='продажи натураль.'!H18 -> 14.232158 | J19: ='продажи натураль.'!I18 -> 6.5901463 | K19: ='продажи натураль.'!J18 -> 11.201432 | ... O19: ='продажи натураль.'!N18 -> 35.091958
A20: Бренд 2 | D20: ='продажи натураль.'!C19 -> 34.835538 | E20: ='продажи натураль.'!D19 -> 7.6167736 | F20: ='продажи натураль.'!E19 -> 27.338799 | G20: ='продажи натураль.'!F19 -> 20.663425 | H20: ='продажи натураль.'!G19 -> 43.786375 | I20: ='продажи натураль.'!H19 -> 40.777536 | J20: ='продажи натураль.'!I19 -> 17.846269 | K20: ='продажи натураль.'!J19 -> 40.983693 | ... O20: ='продажи натураль.'!N19 -> 2.1408773
A21: Бренд 3 | D21: ='продажи натураль.'!C20 -> 7.1933052 | E21: ='продажи натураль.'!D20 -> 22.143705 | F21: ='продажи натураль.'!E20 -> 34.839175 | G21: ='продажи натураль.'!F20 -> 53.946326 | H21: ='продажи натураль.'!G20 -> 43.407642 | I21: ='продажи натураль.'!H20 -> 22.774957 | J21: ='продажи натураль.'!I20 -> 25.866388 | K21: ='продажи натураль.'!J20 -> 7.1072508 | ... O21: ='продажи натураль.'!N20 -> 4.726733
A22: Бренд 4 | D22: ='продажи натураль.'!C21 -> 21.465348 | E22: ='продажи натураль.'!D21 -> 21.72355 | F22: ='продажи натураль.'!E21 -> 47.151725 | G22: ='продажи натураль.'!F21 -> 16.708365 | H22: ='продажи натураль.'!G21 -> 37.951666 | I22: ='продажи натураль.'!H21 -> 21.451109 | J22: ='продажи натураль.'!I21 -> 39.646347 | K22: ='продажи натураль.'!J21 -> 36.89337 | ... O22: ='продажи натураль.'!N21 -> 34.133603
A23: Бренд 5 | D23: ='продажи натураль.'!C22 -> 33.786433 | E23: ='продажи натураль.'!D22 -> 6.7048856 | F23: ='продажи натураль.'!E22 -> 7.8109237 | G23: ='продажи натураль.'!F22 -> 9.5761729 | H23: ='продажи натураль.'!G22 -> 62.906628 | I23: ='продажи натураль.'!H22 -> 6.5363034 | J23: ='продажи натураль.'!I22 -> 30.893022 | K23: ='продажи натураль.'!J22 -> 36.132962 | ... O23: ='продажи натураль.'!N22 -> 32.355809
A24: Бренд 6 | D24: ='продажи натураль.'!C23 -> 55.979469 | E24: ='продажи натураль.'!D23 -> 38.047686 | F24: ='продажи натураль.'!E23 -> 5.0233745 | G24: ='продажи натураль.'!F23 -> 6.7465642 | H24: ='продажи натураль.'!G23 -> 29.972787 | I24: ='продажи натураль.'!H23 -> 11.702264 | J24: ='продажи натураль.'!I23 -> 39.868941 | K24: ='продажи натураль.'!J23 -> 21.674293 | ... O24: ='продажи натураль.'!N23 -> 5.2571401
A25: Бренд 7 | D25: ='продажи натураль.'!C24 -> 69.83957 | E25: ='продажи натураль.'!D24 -> 14.504757 | F25: ='продажи натураль.'!E24 -> 10.975808 | G25: ='продажи натураль.'!F24 -> 46.648343 | H25: ='продажи натураль.'!G24 -> 18.155249 | I25: ='продажи натураль.'!H24 -> 24.906214 | J25: ='продажи натураль.'!I24 -> 21.569305 | K25: ='продажи натураль.'!J24 -> 10.884708 | ... O25: ='продажи натураль.'!N24 -> 91.335335
A26: Бренд 8 | D26: ='продажи натураль.'!C25 -> 13.139919 | E26: ='продажи натураль.'!D25 -> 53.04678 | F26: ='продажи натураль.'!E25 -> 20.000865 | G26: ='продажи натураль.'!F25 -> 7.0201954 | H26: ='продажи натураль.'!G25 -> 23.132122 | I26: ='продажи натураль.'!H25 -> 35.823762 | J26: ='продажи натураль.'!I25 -> 17.871672 | K26: ='продажи натураль.'!J25 -> 26.530391 | ... O26: ='продажи натураль.'!N25 -> 14.863445
A27: Бренд 9 | D27: ='продажи натураль.'!C26 -> 25.143286 | E27: ='продажи натураль.'!D26 -> 21.046982 | F27: ='продажи натураль.'!E26 -> 31.331629 | G27: ='продажи натураль.'!F26 -> 38.340069 | H27: ='продажи натураль.'!G26 -> 1.6143339 | I27: ='продажи натураль.'!H26 -> 15.122471 | J27: ='продажи натураль.'!I26 -> 45.607641 | K27: ='продажи натураль.'!J26 -> 39.004328 | ... O27: ='продажи натураль.'!N26 -> 10.436922
A28: Бренд 10 | D28: ='продажи натураль.'!C27 -> 0.59849322 | E28: ='продажи натураль.'!D27 -> 19.173924 | F28: ='продажи натураль.'!E27 -> 28.616565 | G28: ='продажи натураль.'!F27 -> 19.498483 | H28: ='продажи натураль.'!G27 -> 12.708715 | I28: ='продажи натураль.'!H27 -> 26.847733 | J28: ='продажи натураль.'!I27 -> 32.316105 | K28: ='продажи натураль.'!J27 -> 28.688112 | ... O28: ='продажи натураль.'!N27 -> 68.787389
A29: Офлайн продажи | D29: =D30+D41 -> 386.71326 | E29: =E30+E41 -> 542.76305 | F29: =F30+F41 -> 380.09627 | G29: =G30+G41 -> 474.08254 | H29: =H30+H41 -> 769.91844 | I29: =I30+I41 -> 538.75702 | J29: =J30+J41 -> 536.98171 | K29: =K30+K41 -> 517.35461 | ... O29: =O30+O41 -> 593.55247
A30: Эконом сегмент | D30: =SUM(D31:D40) -> 193.7266 | E30: =SUM(E31:E40) -> 285.48051 | F30: =SUM(F31:F40) -> 223.86192 | G30: =SUM(G31:G40) -> 242.80089 | H30: =SUM(H31:H40) -> 392.93314 | I30: =SUM(I31:I40) -> 292.45625 | J30: =SUM(J31:J40) -> 311.66475 | K30: =SUM(K31:K40) -> 235.8898 | ... O30: =SUM(O31:O40) -> 282.71654
A31: Бренд 1 | D31: ='продажи натураль.'!C30 -> 49.917382 | E31: ='продажи натураль.'!D30 -> 19.496222 | F31: ='продажи натураль.'!E30 -> 52.013128 | G31: ='продажи натураль.'!F30 -> 68.587236 | H31: ='продажи натураль.'!G30 -> 42.340018 | I31: ='продажи натураль.'!H30 -> 8.4116198 | J31: ='продажи натураль.'!I30 -> 84.294354 | K31: ='продажи натураль.'!J30 -> 44.322938 | ... O31: ='продажи натураль.'!N30 -> 58.237276
A32: Бренд 2 | D32: ='продажи натураль.'!C31 -> 16.233441 | E32: ='продажи натураль.'!D31 -> 59.924532 | F32: ='продажи натураль.'!E31 -> 19.90603 | G32: ='продажи натураль.'!F31 -> 4.555899 | H32: ='продажи натураль.'!G31 -> 4.2701581 | I32: ='продажи натураль.'!H31 -> 22.937889 | J32: ='продажи натураль.'!I31 -> 31.466098 | K32: ='продажи натураль.'!J31 -> 42.510945 | ... O32: ='продажи натураль.'!N31 -> 63.376672
A33: Бренд 3 | D33: ='продажи натураль.'!C32 -> 18.987399 | E33: ='продажи натураль.'!D32 -> 44.326874 | F33: ='продажи натураль.'!E32 -> 26.350137 | G33: ='продажи натураль.'!F32 -> 31.989536 | H33: ='продажи натураль.'!G32 -> 28.4583 | I33: ='продажи натураль.'!H32 -> 40.816891 | J33: ='продажи натураль.'!I32 -> 31.239174 | K33: ='продажи натураль.'!J32 -> 4.7939377 | ... O33: ='продажи натураль.'!N32 -> 46.102108
A34: Бренд 4 | D34: ='продажи натураль.'!C33 -> 16.364334 | E34: ='продажи натураль.'!D33 -> 15.335892 | F34: ='продажи натураль.'!E33 -> 8.404687 | G34: ='продажи натураль.'!F33 -> 32.038149 | H34: ='продажи натураль.'!G33 -> 34.607624 | I34: ='продажи натураль.'!H33 -> 3.5539546 | J34: ='продажи натураль.'!I33 -> 31.802753 | K34: ='продажи натураль.'!J33 -> 28.20108 | ... O34: ='продажи натураль.'!N33 -> 38.167434
A35: Бренд 5 | D35: ='продажи натураль.'!C34 -> 13.637636 | E35: ='продажи натураль.'!D34 -> 48.57449 | F35: ='продажи натураль.'!E34 -> 42.490845 | G35: ='продажи натураль.'!F34 -> 2.9217132 | H35: ='продажи натураль.'!G34 -> 38.029841 | I35: ='продажи натураль.'!H34 -> 7.0081389 | J35: ='продажи натураль.'!I34 -> 15.693008 | K35: ='продажи натураль.'!J34 -> 63.979767 | ... O35: ='продажи натураль.'!N34 -> 9.5405538
A36: Бренд 6 | D36: ='продажи натураль.'!C35 -> 7.0767586 | E36: ='продажи натураль.'!D35 -> 30.799148 | F36: ='продажи натураль.'!E35 -> 12.222888 | G36: ='продажи натураль.'!F35 -> 1.526901 | H36: ='продажи натураль.'!G35 -> 95.014158 | I36: ='продажи натураль.'!H35 -> 70.066664 | J36: ='продажи натураль.'!I35 -> 17.469463 | K36: ='продажи натураль.'!J35 -> 2.107023 | ... O36: ='продажи натураль.'!N35 -> 16.13428
A37: Бренд 7 | D37: ='продажи натураль.'!C36 -> 43.727239 | E37: ='продажи натураль.'!D36 -> 13.241526 | F37: ='продажи натураль.'!E36 -> 1.1989395 | G37: ='продажи натураль.'!F36 -> 15.734061 | H37: ='продажи натураль.'!G36 -> 3.27422 | I37: ='продажи натураль.'!H36 -> 12.604854 | J37: ='продажи натураль.'!I36 -> 41.284093 | K37: ='продажи натураль.'!J36 -> 9.5499197 | ... O37: ='продажи натураль.'!N36 -> 2.9616219
A38: Бренд 8 | D38: ='продажи натураль.'!C37 -> 0.30706464 | E38: ='продажи натураль.'!D37 -> 5.7483139 | F38: ='продажи натураль.'!E37 -> 41.47568 | G38: ='продажи натураль.'!F37 -> 42.531873 | H38: ='продажи натураль.'!G37 -> 34.90155 | I38: ='продажи натураль.'!H37 -> 29.544549 | J38: ='продажи натураль.'!I37 -> 6.5543441 | K38: ='продажи натураль.'!J37 -> 12.867844 | ... O38: ='продажи натураль.'!N37 -> 31.537033
A39: Бренд 9 | D39: ='продажи натураль.'!C38 -> 16.641579 | E39: ='продажи натураль.'!D38 -> 8.4269745 | F39: ='продажи натураль.'!E38 -> 1.4194516 | G39: ='продажи натураль.'!F38 -> 33.023209 | H39: ='продажи натураль.'!G38 -> 48.384809 | I39: ='продажи натураль.'!H38 -> 16.690174 | J39: ='продажи натураль.'!I38 -> 33.292311 | K39: ='продажи натураль.'!J38 -> 8.1760036 | ... O39: ='продажи натураль.'!N38 -> 1.8249762
A40: Бренд 10 | D40: ='продажи натураль.'!C39 -> 10.83377 | E40: ='продажи натураль.'!D39 -> 39.606537 | F40: ='продажи натураль.'!E39 -> 18.380132 | G40: ='продажи натураль.'!F39 -> 9.8923086 | H40: ='продажи натураль.'!G39 -> 63.652466 | I40: ='продажи натураль.'!H39 -> 80.821517 | J40: ='продажи натураль.'!I39 -> 18.569153 | K40: ='продажи натураль.'!J39 -> 19.380344 | ... O40: ='продажи натураль.'!N39 -> 14.834584
A41: Премиум сегмент | D41: =SUM(D42:D51) -> 192.98665 | E41: =SUM(E42:E51) -> 257.28255 | F41: =SUM(F42:F51) -> 156.23436 | G41: =SUM(G42:G51) -> 231.28165 | H41: =SUM(H42:H51) -> 376.98529 | I41: =SUM(I42:I51) -> 246.30077 | J41: =SUM(J42:J51) -> 225.31696 | K41: =SUM(K42:K51) -> 281.46481 | ... O41: =SUM(O42:O51) -> 310.83593
A42: Бренд 1 | D42: ='продажи натураль.'!C41 -> 68.509687 | E42: ='продажи натураль.'!D41 -> 23.31188 | F42: ='продажи натураль.'!E41 -> 10.848903 | G42: ='продажи натураль.'!F41 -> 6.7080718 | H42: ='продажи натураль.'!G41 -> 25.10333 | I42: ='продажи натураль.'!H41 -> 37.586809 | J42: ='продажи натураль.'!I41 -> 13.732025 | K42: ='продажи натураль.'!J41 -> 1.3284248 | ... O42: ='продажи натураль.'!N41 -> 34.096283
A43: Бренд 2 | D43: ='продажи натураль.'!C42 -> 13.041433 | E43: ='продажи натураль.'!D42 -> 41.767809 | F43: ='продажи натураль.'!E42 -> 21.916558 | G43: ='продажи натураль.'!F42 -> 21.745065 | H43: ='продажи натураль.'!G42 -> 5.79663 | I43: ='продажи натураль.'!H42 -> 75.296316 | J43: ='продажи натураль.'!I42 -> 0.07285966 | K43: ='продажи натураль.'!J42 -> 11.43801 | ... O43: ='продажи натураль.'!N42 -> 30.47923
A44: Бренд 3 | D44: ='продажи натураль.'!C43 -> 23.423771 | E44: ='продажи натураль.'!D43 -> 8.7911999 | F44: ='продажи натураль.'!E43 -> 31.003327 | G44: ='продажи натураль.'!F43 -> 16.06431 | H44: ='продажи натураль.'!G43 -> 4.0700672 | I44: ='продажи натураль.'!H43 -> 23.717039 | J44: ='продажи натураль.'!I43 -> 5.9420175 | K44: ='продажи натураль.'!J43 -> 57.728833 | ... O44: ='продажи натураль.'!N43 -> 29.622102
A45: Бренд 4 | D45: ='продажи натураль.'!C44 -> 13.250761 | E45: ='продажи натураль.'!D44 -> 4.4939119 | F45: ='продажи натураль.'!E44 -> 3.8932642 | G45: ='продажи натураль.'!F44 -> 33.939907 | H45: ='продажи натураль.'!G44 -> 86.766471 | I45: ='продажи натураль.'!H44 -> 6.8734428 | J45: ='продажи натураль.'!I44 -> 46.775531 | K45: ='продажи натураль.'!J44 -> 11.847217 | ... O45: ='продажи натураль.'!N44 -> 2.1079315
A46: Бренд 5 | D46: ='продажи натураль.'!C45 -> 17.026083 | E46: ='продажи натураль.'!D45 -> 35.378308 | F46: ='продажи натураль.'!E45 -> 23.895634 | G46: ='продажи натураль.'!F45 -> 15.797448 | H46: ='продажи натураль.'!G45 -> 10.834599 | I46: ='продажи натураль.'!H45 -> 8.9376843 | J46: ='продажи натураль.'!I45 -> 50.272365 | K46: ='продажи натураль.'!J45 -> 47.801899 | ... O46: ='продажи натураль.'!N45 -> 25.607744
A47: Бренд 6 | D47: ='продажи натураль.'!C46 -> 15.253932 | E47: ='продажи натураль.'!D46 -> 18.313637 | F47: ='продажи натураль.'!E46 -> 6.6909946 | G47: ='продажи натураль.'!F46 -> 66.021619 | H47: ='продажи натураль.'!G46 -> 80.885699 | I47: ='продажи натураль.'!H46 -> 18.865711 | J47: ='продажи натураль.'!I46 -> 18.876499 | K47: ='продажи натураль.'!J46 -> 43.609843 | ... O47: ='продажи натураль.'!N46 -> 9.3492326
A48: Бренд 7 | D48: ='продажи натураль.'!C47 -> 7.9204595 | E48: ='продажи натураль.'!D47 -> 12.191389 | F48: ='продажи натураль.'!E47 -> 17.184747 | G48: ='продажи натураль.'!F47 -> 29.880712 | H48: ='продажи натураль.'!G47 -> 46.879948 | I48: ='продажи натураль.'!H47 -> 17.14838 | J48: ='продажи натураль.'!I47 -> 64.213243 | K48: ='продажи натураль.'!J47 -> 20.510382 | ... O48: ='продажи натураль.'!N47 -> 25.963747
A49: Бренд 8 | D49: ='продажи натураль.'!C48 -> 10.633949 | E49: ='продажи натураль.'!D48 -> 37.597192 | F49: ='продажи натураль.'!E48 -> 3.1503661 | G49: ='продажи натураль.'!F48 -> 6.3502823 | H49: ='продажи натураль.'!G48 -> 31.704285 | I49: ='продажи натураль.'!H48 -> 0.014383767 | J49: ='продажи натураль.'!I48 -> 16.015245 | K49: ='продажи натураль.'!J48 -> 4.7454771 | ... O49: ='продажи натураль.'!N48 -> 40.309297
A50: Бренд 9 | D50: ='продажи натураль.'!C49 -> 13.907426 | E50: ='продажи натураль.'!D49 -> 27.618582 | F50: ='продажи натураль.'!E49 -> 25.345884 | G50: ='продажи натураль.'!F49 -> 28.142298 | H50: ='продажи натураль.'!G49 -> 7.0283779 | I50: ='продажи натураль.'!H49 -> 24.382734 | J50: ='продажи натураль.'!I49 -> 1.8688868 | K50: ='продажи натураль.'!J49 -> 19.187332 | ... O50: ='продажи натураль.'!N49 -> 31.016747
A51: Бренд 10 | D51: ='продажи натураль.'!C50 -> 10.019151 | E51: ='продажи натураль.'!D50 -> 47.818637 | F51: ='продажи натураль.'!E50 -> 12.304677 | G51: ='продажи натураль.'!F50 -> 6.6319373 | H51: ='продажи натураль.'!G50 -> 77.915888 | I51: ='продажи натураль.'!H50 -> 33.478268 | J51: ='продажи натураль.'!I50 -> 7.5482916 | K51: ='продажи натураль.'!J50 -> 63.267393 | ... O51: ='продажи натураль.'!N50 -> 82.283619
A53: Корма для кошек | D53: =D54+D77 -> 1075.2853 | E53: =E54+E77 -> 1153.5455 | F53: =F54+F77 -> 1762.374 | G53: =G54+G77 -> 1521.6351 | H53: =H54+H77 -> 1507.9409 | I53: =I54+I77 -> 1142.0745 | J53: =J54+J77 -> 1322.7094 | K53: =K54+K77 -> 1604.1594 | ... O53: =O54+O77 -> 1108.7552
A54: Онлайн продажи | D54: =D55+D66 -> 429.01237 | E54: =E55+E66 -> 521.78334 | F54: =F55+F66 -> 641.30919 | G54: =G55+G66 -> 531.86453 | H54: =H55+H66 -> 603.5511 | I54: =I55+I66 -> 441.30446 | J54: =J55+J66 -> 535.61208 | K54: =K55+K66 -> 595.24076 | ... O54: =O55+O66 -> 452.46089
A55: Эконом сегмент | D55: =SUM(D56:D65) -> 164.50864 | E55: =SUM(E56:E65) -> 238.58801 | F55: =SUM(F56:F65) -> 323.25906 | G55: =SUM(G56:G65) -> 196.03272 | H55: =SUM(H56:H65) -> 344.96264 | I55: =SUM(I56:I65) -> 204.67803 | J55: =SUM(J56:J65) -> 272.71168 | K55: =SUM(K56:K65) -> 270.14438 | ... O55: =SUM(O56:O65) -> 295.01213
A56: Бренд 1 | D56: ='продажи натураль.'!C55 -> 14.741586 | E56: ='продажи натураль.'!D55 -> 0.22252912 | F56: ='продажи натураль.'!E55 -> 29.05809 | G56: ='продажи натураль.'!F55 -> 15.446216 | H56: ='продажи натураль.'!G55 -> 28.229552 | I56: ='продажи натураль.'!H55 -> 4.3920226 | J56: ='продажи натураль.'!I55 -> 9.9694974 | K56: ='продажи натураль.'!J55 -> 16.236113 | ... O56: ='продажи натураль.'!N55 -> 30.430843
A57: Бренд 2 | D57: ='продажи натураль.'!C56 -> 34.885628 | E57: ='продажи натураль.'!D56 -> 23.642576 | F57: ='продажи натураль.'!E56 -> 38.080955 | G57: ='продажи натураль.'!F56 -> 11.666727 | H57: ='продажи натураль.'!G56 -> 49.21916 | I57: ='продажи натураль.'!H56 -> 2.309582 | J57: ='продажи натураль.'!I56 -> 34.998756 | K57: ='продажи натураль.'!J56 -> 9.5311443 | ... O57: ='продажи натураль.'!N56 -> 19.487807
A58: Бренд 3 | D58: ='продажи натураль.'!C57 -> 4.0909481 | E58: ='продажи натураль.'!D57 -> 80.303958 | F58: ='продажи натураль.'!E57 -> 31.751147 | G58: ='продажи натураль.'!F57 -> 43.699102 | H58: ='продажи натураль.'!G57 -> 24.47821 | I58: ='продажи натураль.'!H57 -> 49.21454 | J58: ='продажи натураль.'!I57 -> 1.390803 | K58: ='продажи натураль.'!J57 -> 13.911102 | ... O58: ='продажи натураль.'!N57 -> 10.276514
A59: Бренд 4 | D59: ='продажи натураль.'!C58 -> 9.8472748 | E59: ='продажи натураль.'!D58 -> 2.8020327 | F59: ='продажи натураль.'!E58 -> 31.886021 | G59: ='продажи натураль.'!F58 -> 26.419945 | H59: ='продажи натураль.'!G58 -> 29.730123 | I59: ='продажи натураль.'!H58 -> 11.945943 | J59: ='продажи натураль.'!I58 -> 33.161864 | K59: ='продажи натураль.'!J58 -> 49.3304 | ... O59: ='продажи натураль.'!N58 -> 4.2236141
A60: Бренд 5 | D60: ='продажи натураль.'!C59 -> 9.3201798 | E60: ='продажи натураль.'!D59 -> 76.171961 | F60: ='продажи натураль.'!E59 -> 45.467436 | G60: ='продажи натураль.'!F59 -> 13.629793 | H60: ='продажи натураль.'!G59 -> 13.39695 | I60: ='продажи натураль.'!H59 -> 1.0335998 | J60: ='продажи натураль.'!I59 -> 13.691993 | K60: ='продажи натураль.'!J59 -> 23.424456 | ... O60: ='продажи натураль.'!N59 -> 73.37017
A61: Бренд 6 | D61: ='продажи натураль.'!C60 -> 1.281804 | E61: ='продажи натураль.'!D60 -> 3.8409132 | F61: ='продажи натураль.'!E60 -> 1.4868467 | G61: ='продажи натураль.'!F60 -> 30.651767 | H61: ='продажи натураль.'!G60 -> 35.972381 | I61: ='продажи натураль.'!H60 -> 2.503926 | J61: ='продажи натураль.'!I60 -> 22.183524 | K61: ='продажи натураль.'!J60 -> 51.734183 | ... O61: ='продажи натураль.'!N60 -> 87.189586
A62: Бренд 7 | D62: ='продажи натураль.'!C61 -> 7.7981467 | E62: ='продажи натураль.'!D61 -> 4.5447556 | F62: ='продажи натураль.'!E61 -> 76.202486 | G62: ='продажи натураль.'!F61 -> 25.93922 | H62: ='продажи натураль.'!G61 -> 65.142959 | I62: ='продажи натураль.'!H61 -> 46.861589 | J62: ='продажи натураль.'!I61 -> 27.029351 | K62: ='продажи натураль.'!J61 -> 6.7810045 | ... O62: ='продажи натураль.'!N61 -> 37.579403
A63: Бренд 8 | D63: ='продажи натураль.'!C62 -> 32.431888 | E63: ='продажи натураль.'!D62 -> 8.6217364 | F63: ='продажи натураль.'!E62 -> 18.020063 | G63: ='продажи натураль.'!F62 -> 9.6450072 | H63: ='продажи натураль.'!G62 -> 8.1815422 | I63: ='продажи натураль.'!H62 -> 45.521771 | J63: ='продажи натураль.'!I62 -> 44.313485 | K63: ='продажи натураль.'!J62 -> 20.531003 | ... O63: ='продажи натураль.'!N62 -> 3.7273894
A64: Бренд 9 | D64: ='продажи натураль.'!C63 -> 48.893272 | E64: ='продажи натураль.'!D63 -> 32.952903 | F64: ='продажи натураль.'!E63 -> 27.493834 | G64: ='продажи натураль.'!F63 -> 12.560585 | H64: ='продажи натураль.'!G63 -> 37.525544 | I64: ='продажи натураль.'!H63 -> 10.837921 | J64: ='продажи натураль.'!I63 -> 60.00269 | K64: ='продажи натураль.'!J63 -> 19.947383 | ... O64: ='продажи натураль.'!N63 -> 21.122723
A65: Бренд 10 | D65: ='продажи натураль.'!C64 -> 1.2179167 | E65: ='продажи натураль.'!D64 -> 5.4846441 | F65: ='продажи натураль.'!E64 -> 23.812185 | G65: ='продажи натураль.'!F64 -> 6.3743585 | H65: ='продажи натураль.'!G64 -> 53.086215 | I65: ='продажи натураль.'!H64 -> 30.057138 | J65: ='продажи натураль.'!I64 -> 25.969719 | K65: ='продажи натураль.'!J64 -> 58.717597 | ... O65: ='продажи натураль.'!N64 -> 7.6040781
A66: Премиум сегмент | D66: =SUM(D67:D76) -> 264.50373 | E66: =SUM(E67:E76) -> 283.19533 | F66: =SUM(F67:F76) -> 318.05013 | G66: =SUM(G67:G76) -> 335.83181 | H66: =SUM(H67:H76) -> 258.58846 | I66: =SUM(I67:I76) -> 236.62643 | J66: =SUM(J67:J76) -> 262.9004 | K66: =SUM(K67:K76) -> 325.09637 | ... O66: =SUM(O67:O76) -> 157.44877
A67: Бренд 1 | D67: ='продажи натураль.'!C66 -> 16.878766 | E67: ='продажи натураль.'!D66 -> 65.805173 | F67: ='продажи натураль.'!E66 -> 25.394737 | G67: ='продажи натураль.'!F66 -> 25.23827 | H67: ='продажи натураль.'!G66 -> 4.9644413 | I67: ='продажи натураль.'!H66 -> 10.576248 | J67: ='продажи натураль.'!I66 -> 13.450355 | K67: ='продажи натураль.'!J66 -> 1.4732018 | ... O67: ='продажи натураль.'!N66 -> 17.394593
A68: Бренд 2 | D68: ='продажи натураль.'!C67 -> 62.90042 | E68: ='продажи натураль.'!D67 -> 34.12202 | F68: ='продажи натураль.'!E67 -> 39.198566 | G68: ='продажи натураль.'!F67 -> 44.721617 | H68: ='продажи натураль.'!G67 -> 6.1578119 | I68: ='продажи натураль.'!H67 -> 56.992293 | J68: ='продажи натураль.'!I67 -> 3.2060801 | K68: ='продажи натураль.'!J67 -> 40.535083 | ... O68: ='продажи натураль.'!N67 -> 28.823068
A69: Бренд 3 | D69: ='продажи натураль.'!C68 -> 40.459711 | E69: ='продажи натураль.'!D68 -> 16.40695 | F69: ='продажи натураль.'!E68 -> 2.6415976 | G69: ='продажи натураль.'!F68 -> 15.232877 | H69: ='продажи натураль.'!G68 -> 32.526065 | I69: ='продажи натураль.'!H68 -> 48.21774 | J69: ='продажи натураль.'!I68 -> 6.8242805 | K69: ='продажи натураль.'!J68 -> 12.652773 | ... O69: ='продажи натураль.'!N68 -> 23.167603
A70: Бренд 4 | D70: ='продажи натураль.'!C69 -> 34.706566 | E70: ='продажи натураль.'!D69 -> 26.740014 | F70: ='продажи натураль.'!E69 -> 31.615373 | G70: ='продажи натураль.'!F69 -> 90.026236 | H70: ='продажи натураль.'!G69 -> 4.4181278 | I70: ='продажи натураль.'!H69 -> 15.740854 | J70: ='продажи натураль.'!I69 -> 50.565903 | K70: ='продажи натураль.'!J69 -> 55.014552 | ... O70: ='продажи натураль.'!N69 -> 31.588362
A71: Бренд 5 | D71: ='продажи натураль.'!C70 -> 7.4123465 | E71: ='продажи натураль.'!D70 -> 8.1565618 | F71: ='продажи натураль.'!E70 -> 4.201419 | G71: ='продажи натураль.'!F70 -> 40.239173 | H71: ='продажи натураль.'!G70 -> 38.242021 | I71: ='продажи натураль.'!H70 -> 32.75821 | J71: ='продажи натураль.'!I70 -> 64.598714 | K71: ='продажи натураль.'!J70 -> 36.349326 | ... O71: ='продажи натураль.'!N70 -> 7.1723749
A72: Бренд 6 | D72: ='продажи натураль.'!C71 -> 41.215925 | E72: ='продажи натураль.'!D71 -> 13.651169 | F72: ='продажи натураль.'!E71 -> 28.606664 | G72: ='продажи натураль.'!F71 -> 0.11968485 | H72: ='продажи натураль.'!G71 -> 17.767861 | I72: ='продажи натураль.'!H71 -> 8.8095265 | J72: ='продажи натураль.'!I71 -> 6.8743387 | K72: ='продажи натураль.'!J71 -> 11.181274 | ... O72: ='продажи натураль.'!N71 -> 16.964919
A73: Бренд 7 | D73: ='продажи натураль.'!C72 -> 0.92663594 | E73: ='продажи натураль.'!D72 -> 44.632069 | F73: ='продажи натураль.'!E72 -> 33.804652 | G73: ='продажи натураль.'!F72 -> 40.628217 | H73: ='продажи натураль.'!G72 -> 16.77294 | I73: ='продажи натураль.'!H72 -> 12.433187 | J73: ='продажи натураль.'!I72 -> 51.195786 | K73: ='продажи натураль.'!J72 -> 13.929853 | ... O73: ='продажи натураль.'!N72 -> 6.5351085
A74: Бренд 8 | D74: ='продажи натураль.'!C73 -> 3.3150677 | E74: ='продажи натураль.'!D73 -> 27.363792 | F74: ='продажи натураль.'!E73 -> 75.388426 | G74: ='продажи натураль.'!F73 -> 5.571042 | H74: ='продажи натураль.'!G73 -> 79.585909 | I74: ='продажи натураль.'!H73 -> 12.970165 | J74: ='продажи натураль.'!I73 -> 16.59301 | K74: ='продажи натураль.'!J73 -> 92.704457 | ... O74: ='продажи натураль.'!N73 -> 14.832285
A75: Бренд 9 | D75: ='продажи натураль.'!C74 -> 42.586866 | E75: ='продажи натураль.'!D74 -> 5.4990086 | F75: ='продажи натураль.'!E74 -> 6.0565051 | G75: ='продажи натураль.'!F74 -> 62.340037 | H75: ='продажи натураль.'!G74 -> 13.698389 | I75: ='продажи натураль.'!H74 -> 16.881794 | J75: ='продажи натураль.'!I74 -> 28.312886 | K75: ='продажи натураль.'!J74 -> 43.92167 | ... O75: ='продажи натураль.'!N74 -> 7.1324289
A76: Бренд 10 | D76: ='продажи натураль.'!C75 -> 14.101421 | E76: ='продажи натураль.'!D75 -> 40.818577 | F76: ='продажи натураль.'!E75 -> 71.142191 | G76: ='продажи натураль.'!F75 -> 11.714652 | H76: ='продажи натураль.'!G75 -> 44.454898 | I76: ='продажи натураль.'!H75 -> 21.246411 | J76: ='продажи натураль.'!I75 -> 21.279048 | K76: ='продажи натураль.'!J75 -> 17.334185 | ... O76: ='продажи натураль.'!N75 -> 3.8380259
A77: Офлайн продажи | D77: =D78+D89 -> 646.27288 | E77: =E78+E89 -> 631.76218 | F77: =F78+F89 -> 1121.0648 | G77: =G78+G89 -> 989.77061 | H77: =H78+H89 -> 904.38981 | I77: =I78+I89 -> 700.77005 | J77: =J78+J89 -> 787.09735 | K77: =K78+K89 -> 1008.9186 | ... O77: =O78+O89 -> 656.29428
A78: Эконом сегмент | D78: =SUM(D79:D88) -> 281.84381 | E78: =SUM(E79:E88) -> 278.8877 | F78: =SUM(F79:F88) -> 527.46729 | G78: =SUM(G79:G88) -> 358.57814 | H78: =SUM(H79:H88) -> 485.32985 | I78: =SUM(I79:I88) -> 325.69236 | J78: =SUM(J79:J88) -> 447.45604 | K78: =SUM(K79:K88) -> 496.91693 | ... O78: =SUM(O79:O88) -> 418.87952
A79: Бренд 1 | D79: ='продажи натураль.'!C78 -> 14.741586 | E79: ='продажи натураль.'!D78 -> 0.22252912 | F79: ='продажи натураль.'!E78 -> 58.116179 | G79: ='продажи натураль.'!F78 -> 15.446216 | H79: ='продажи натураль.'!G78 -> 28.229552 | I79: ='продажи натураль.'!H78 -> 4.3920226 | J79: ='продажи натураль.'!I78 -> 9.9694974 | K79: ='продажи натураль.'!J78 -> 32.472225 | ... O79: ='продажи натураль.'!N78 -> 30.430843
A80: Бренд 2 | D80: ='продажи натураль.'!C79 -> 69.771257 | E80: ='продажи натураль.'!D79 -> 23.642576 | F80: ='продажи натураль.'!E79 -> 76.16191 | G80: ='продажи натураль.'!F79 -> 11.666727 | H80: ='продажи натураль.'!G79 -> 49.21916 | I80: ='продажи натураль.'!H79 -> 4.6191641 | J80: ='продажи натураль.'!I79 -> 34.998756 | K80: ='продажи натураль.'!J79 -> 19.062289 | ... O80: ='продажи натураль.'!N79 -> 19.487807
A81: Бренд 3 | D81: ='продажи натураль.'!C80 -> 8.1818962 | E81: ='продажи натураль.'!D80 -> 80.303958 | F81: ='продажи натураль.'!E80 -> 31.751147 | G81: ='продажи натураль.'!F80 -> 87.398204 | H81: ='продажи натураль.'!G80 -> 24.47821 | I81: ='продажи натураль.'!H80 -> 49.21454 | J81: ='продажи натураль.'!I80 -> 2.7816059 | K81: ='продажи натураль.'!J80 -> 27.822203 | ... O81: ='продажи натураль.'!N80 -> 10.276514
A82: Бренд 4 | D82: ='продажи натураль.'!C81 -> 19.69455 | E82: ='продажи натураль.'!D81 -> 5.6040655 | F82: ='продажи натураль.'!E81 -> 63.772041 | G82: ='продажи натураль.'!F81 -> 52.83989 | H82: ='продажи натураль.'!G81 -> 59.460247 | I82: ='продажи натураль.'!H81 -> 23.891886 | J82: ='продажи натураль.'!I81 -> 66.323729 | K82: ='продажи натураль.'!J81 -> 98.6608 | ... O82: ='продажи натураль.'!N81 -> 8.4472281
A83: Бренд 5 | D83: ='продажи натураль.'!C82 -> 18.64036 | E83: ='продажи натураль.'!D82 -> 76.171961 | F83: ='продажи натураль.'!E82 -> 45.467436 | G83: ='продажи натураль.'!F82 -> 27.259586 | H83: ='продажи натураль.'!G82 -> 26.7939 | I83: ='продажи натураль.'!H82 -> 2.0671997 | J83: ='продажи натураль.'!I82 -> 27.383987 | K83: ='продажи натураль.'!J82 -> 23.424456 | ... O83: ='продажи натураль.'!N82 -> 73.37017
A84: Бренд 6 | D84: ='продажи натураль.'!C83 -> 2.563608 | E84: ='продажи натураль.'!D83 -> 3.8409132 | F84: ='продажи натураль.'!E83 -> 2.9736934 | G84: ='продажи натураль.'!F83 -> 61.303534 | H84: ='продажи натураль.'!G83 -> 71.944763 | I84: ='продажи натураль.'!H83 -> 5.0078521 | J84: ='продажи натураль.'!I83 -> 44.367048 | K84: ='продажи натураль.'!J83 -> 103.46837 | ... O84: ='продажи натураль.'!N83 -> 174.37917
A85: Бренд 7 | D85: ='продажи натураль.'!C84 -> 15.596293 | E85: ='продажи натураль.'!D84 -> 9.0895112 | F85: ='продажи натураль.'!E84 -> 152.40497 | G85: ='продажи натураль.'!F84 -> 51.87844 | H85: ='продажи натураль.'!G84 -> 65.142959 | I85: ='продажи натураль.'!H84 -> 93.723177 | J85: ='продажи натураль.'!I84 -> 27.029351 | K85: ='продажи натураль.'!J84 -> 13.562009 | ... O85: ='продажи натураль.'!N84 -> 37.579403
A86: Бренд 8 | D86: ='продажи натураль.'!C85 -> 32.431888 | E86: ='продажи натураль.'!D85 -> 8.6217364 | F86: ='продажи натураль.'!E85 -> 18.020063 | G86: ='продажи натураль.'!F85 -> 19.290014 | H86: ='продажи натураль.'!G85 -> 16.363084 | I86: ='продажи натураль.'!H85 -> 91.043541 | J86: ='продажи натураль.'!I85 -> 88.626969 | K86: ='продажи натураль.'!J85 -> 41.062006 | ... O86: ='продажи натураль.'!N85 -> 7.4547787
A87: Бренд 9 | D87: ='продажи натураль.'!C86 -> 97.786544 | E87: ='продажи натураль.'!D86 -> 65.905806 | F87: ='продажи натураль.'!E86 -> 54.987668 | G87: ='продажи натураль.'!F86 -> 25.12117 | H87: ='продажи натураль.'!G86 -> 37.525544 | I87: ='продажи натураль.'!H86 -> 21.675842 | J87: ='продажи натураль.'!I86 -> 120.00538 | K87: ='продажи натураль.'!J86 -> 19.947383 | ... O87: ='продажи натураль.'!N86 -> 42.245445
A88: Бренд 10 | D88: ='продажи натураль.'!C87 -> 2.4358335 | E88: ='продажи натураль.'!D87 -> 5.4846441 | F88: ='продажи натураль.'!E87 -> 23.812185 | G88: ='продажи натураль.'!F87 -> 6.3743585 | H88: ='продажи натураль.'!G87 -> 106.17243 | I88: ='продажи натураль.'!H87 -> 30.057138 | J88: ='продажи натураль.'!I87 -> 25.969719 | K88: ='продажи натураль.'!J87 -> 117.43519 | ... O88: ='продажи натураль.'!N87 -> 15.208156
A89: Премиум сегмент | D89: =SUM(D90:D99) -> 364.42907 | E89: =SUM(E90:E99) -> 352.87448 | F89: =SUM(F90:F99) -> 593.59751 | G89: =SUM(G90:G99) -> 631.19247 | H89: =SUM(H90:H99) -> 419.05996 | I89: =SUM(I90:I99) -> 375.07769 | J89: =SUM(J90:J99) -> 339.64131 | K89: =SUM(K90:K99) -> 512.00168 | ... O89: =SUM(O90:O99) -> 237.41476
A90: Бренд 1 | D90: ='продажи натураль.'!C89 -> 33.757533 | E90: ='продажи натураль.'!D89 -> 65.805173 | F90: ='продажи натураль.'!E89 -> 50.789475 | G90: ='продажи натураль.'!F89 -> 25.23827 | H90: ='продажи натураль.'!G89 -> 9.9288827 | I90: ='продажи натураль.'!H89 -> 21.152496 | J90: ='продажи натураль.'!I89 -> 26.90071 | K90: ='продажи натураль.'!J89 -> 1.4732018 | ... O90: ='продажи натураль.'!N89 -> 17.394593
A91: Бренд 2 | D91: ='продажи натураль.'!C90 -> 62.90042 | E91: ='продажи натураль.'!D90 -> 68.24404 | F91: ='продажи натураль.'!E90 -> 78.397133 | G91: ='продажи натураль.'!F90 -> 89.443233 | H91: ='продажи натураль.'!G90 -> 6.1578119 | I91: ='продажи натураль.'!H90 -> 113.98459 | J91: ='продажи натураль.'!I90 -> 3.2060801 | K91: ='продажи натураль.'!J90 -> 40.535083 | ... O91: ='продажи натураль.'!N90 -> 57.646136
A92: Бренд 3 | D92: ='продажи натураль.'!C91 -> 80.919422 | E92: ='продажи натураль.'!D91 -> 32.8139 | F92: ='продажи натураль.'!E91 -> 2.6415976 | G92: ='продажи натураль.'!F91 -> 15.232877 | H92: ='продажи натураль.'!G91 -> 32.526065 | I92: ='продажи натураль.'!H91 -> 48.21774 | J92: ='продажи натураль.'!I91 -> 13.648561 | K92: ='продажи натураль.'!J91 -> 12.652773 | ... O92: ='продажи натураль.'!N91 -> 46.335207
A93: Бренд 4 | D93: ='продажи натураль.'!C92 -> 34.706566 | E93: ='продажи натураль.'!D92 -> 26.740014 | F93: ='продажи натураль.'!E92 -> 63.230746 | G93: ='продажи натураль.'!F92 -> 180.05247 | H93: ='продажи натураль.'!G92 -> 4.4181278 | I93: ='продажи натураль.'!H92 -> 15.740854 | J93: ='продажи натураль.'!I92 -> 50.565903 | K93: ='продажи натураль.'!J92 -> 55.014552 | ... O93: ='продажи натураль.'!N92 -> 31.588362
A94: Бренд 5 | D94: ='продажи натураль.'!C93 -> 7.4123465 | E94: ='продажи натураль.'!D93 -> 8.1565618 | F94: ='продажи натураль.'!E93 -> 8.402838 | G94: ='продажи натураль.'!F93 -> 80.478345 | H94: ='продажи натураль.'!G93 -> 38.242021 | I94: ='продажи натураль.'!H93 -> 65.516419 | J94: ='продажи натураль.'!I93 -> 64.598714 | K94: ='продажи натураль.'!J93 -> 72.698653 | ... O94: ='продажи натураль.'!N93 -> 14.34475
A95: Бренд 6 | D95: ='продажи натураль.'!C94 -> 41.215925 | E95: ='продажи натураль.'!D94 -> 27.302338 | F95: ='продажи натураль.'!E94 -> 57.213328 | G95: ='продажи натураль.'!F94 -> 0.23936969 | H95: ='продажи натураль.'!G94 -> 35.535722 | I95: ='продажи натураль.'!H94 -> 17.619053 | J95: ='продажи натураль.'!I94 -> 13.748677 | K95: ='продажи натураль.'!J94 -> 11.181274 | ... O95: ='продажи натураль.'!N94 -> 33.929837
A96: Бренд 7 | D96: ='продажи натураль.'!C95 -> 0.92663594 | E96: ='продажи натураль.'!D95 -> 44.632069 | F96: ='продажи натураль.'!E95 -> 33.804652 | G96: ='продажи натураль.'!F95 -> 81.256435 | H96: ='продажи натураль.'!G95 -> 16.77294 | I96: ='продажи натураль.'!H95 -> 24.866374 | J96: ='продажи натураль.'!I95 -> 51.195786 | K96: ='продажи натураль.'!J95 -> 27.859705 | ... O96: ='продажи натураль.'!N95 -> 6.5351085
A97: Бренд 8 | D97: ='продажи натураль.'!C96 -> 3.3150677 | E97: ='продажи натураль.'!D96 -> 27.363792 | F97: ='продажи натураль.'!E96 -> 150.77685 | G97: ='продажи натураль.'!F96 -> 11.142084 | H97: ='продажи натураль.'!G96 -> 159.17182 | I97: ='продажи натураль.'!H96 -> 12.970165 | J97: ='продажи натураль.'!I96 -> 16.59301 | K97: ='продажи натураль.'!J96 -> 185.40891 | ... O97: ='продажи натураль.'!N96 -> 14.832285
A98: Бренд 9 | D98: ='продажи натураль.'!C97 -> 85.173732 | E98: ='продажи натураль.'!D97 -> 10.998017 | F98: ='продажи натураль.'!E97 -> 6.0565051 | G98: ='продажи натураль.'!F97 -> 124.68007 | H98: ='продажи натураль.'!G97 -> 27.396777 | I98: ='продажи натураль.'!H97 -> 33.763588 | J98: ='продажи натураль.'!I97 -> 56.625771 | K98: ='продажи натураль.'!J97 -> 87.84334 | ... O98: ='продажи натураль.'!N97 -> 7.1324289
A99: Бренд 10 | D99: ='продажи натураль.'!C98 -> 14.101421 | E99: ='продажи натураль.'!D98 -> 40.818577 | F99: ='продажи натураль.'!E98 -> 142.28438 | G99: ='продажи натураль.'!F98 -> 23.429304 | H99: ='продажи натураль.'!G98 -> 88.909795 | I99: ='продажи натураль.'!H98 -> 21.246411 | J99: ='продажи натураль.'!I98 -> 42.558095 | K99: ='продажи натураль.'!J98 -> 17.334185 | ... O99: ='продажи натураль.'!N98 -> 7.6760517
A101: Цены, руб./кг | D101: =D297/D3 -> 263.37699 | E101: =E297/E3 -> 249.1893 | F101: =F297/F3 -> 256.50197 | G101: =G297/G3 -> 263.05272 | H101: =H297/H3 -> 246.14184 | I101: =I297/I3 -> 253.85051 | J101: =J297/J3 -> 238.96406 | K101: =K297/K3 -> 253.67042 | ... O101: =O297/O3 -> 238.10439
A103: Корма для собак | D103: =D299/D5 -> 260.95419 | E103: =E299/E5 -> 238.06467 | F103: =F299/F5 -> 242.6705 | G103: =G299/G5 -> 232.71307 | H103: =H299/H5 -> 251.62563 | I103: =I299/I5 -> 250.10692 | J103: =J299/J5 -> 234.01875 | K103: =K299/K5 -> 258.76251 | ... O103: =O299/O5 -> 243.48223
A104: Онлайн продажи | D104: =D300/D6 -> 273.7856 | E104: =E300/E6 -> 247.44301 | F104: =F300/F6 -> 263.74873 | G104: =G300/G6 -> 216.24661 | H104: =H300/H6 -> 261.37407 | I104: =I300/I6 -> 233.0648 | J104: =J300/J6 -> 240.28307 | K104: =K300/K6 -> 263.73988 | ... O104: =O300/O6 -> 233.21088
A105: Эконом сегмент | D105: =D301/D7 -> 156.82142 | E105: =E301/E7 -> 150.47519 | F105: =F301/F7 -> 146.7907 | G105: =G301/G7 -> 133.50012 | H105: =H301/H7 -> 137.38351 | I105: =I301/I7 -> 147.73511 | J105: =J301/J7 -> 168.39169 | K105: =K301/K7 -> 180.80321 | ... O105: =O301/O7 -> 141.1268
...

Sheet Исходные данные→

Sheet продажи натураль.
B2: Продажи тонн
C3: 44927 | D3: 44958 | E3: 44986 | F3: 45017 | G3: 45047 | H3: 45078 | I3: 45108 | J3: 45139 | K3: 45170 | L3: 45200 | M3: 45231 | N3: 45261
B4: Корма для собак
B5: Онлайн продажи
B6: Эконом сегмент
B7: Бренд 1 | C7: 2.9205887 | D7: 9.5115027 | E7: 2.9569522 | F7: 29.085696 | G7: 3.7609401 | H7: 11.350544 | I7: 3.8941279 | J7: 3.6616761 | K7: 27.888846 | L7: 14.370095 | M7: 8.5289763 | N7: 53.665164
B8: Бренд 2 | C8: 63.328307 | D8: 4.0526806 | E8: 27.224039 | F8: 83.106754 | G8: 22.786039 | H8: 19.789918 | I8: 6.3226629 | J8: 5.2214759 | K8: 61.946695 | L8: 10.410475 | M8: 19.6122 | N8: 7.1655691
B9: Бренд 3 | C9: 16.518393 | D9: 36.923947 | E9: 15.942065 | F9: 20.3666 | G9: 16.145601 | H9: 78.158713 | I9: 1.4517819 | J9: 34.545601 | K9: 22.466362 | L9: 25.188829 | M9: 25.722622 | N9: 44.390783
B10: Бренд 4 | C10: 12.874416 | D10: 1.2416532 | E10: 2.1283363 | F10: 12.025692 | G10: 33.936827 | H10: 15.260464 | I10: 62.370072 | J10: 69.458365 | K10: 34.454465 | L10: 64.081954 | M10: 20.966734 | N10: 26.896586
B11: Бренд 5 | C11: 47.452926 | D11: 9.6306634 | E11: 35.649551 | F11: 47.427644 | G11: 43.393758 | H11: 16.977001 | I11: 81.981773 | J11: 41.966994 | K11: 58.527007 | L11: 44.811048 | M11: 24.305595 | N11: 91.405769
B12: Бренд 6 | C12: 44.872531 | D12: 30.26307 | E12: 15.036106 | F12: 74.064884 | G12: 21.725135 | H12: 34.962944 | I12: 34.955475 | J12: 8.5644655 | K12: 1.6553661 | L12: 3.5663248 | M12: 3.2240895 | N12: 1.9500381
B13: Бренд 7 | C13: 0.69506707 | D13: 53.460415 | E13: 39.073368 | F13: 23.516107 | G13: 47.78267 | H13: 17.272478 | I13: 20.560933 | J13: 21.882708 | K13: 19.384256 | L13: 2.0989694 | M13: 81.819257 | N13: 62.349359
B14: Бренд 8 | C14: 4.149572 | D14: 39.488109 | E14: 25.265471 | F14: 22.456329 | G14: 15.648039 | H14: 35.713431 | I14: 52.085634 | J14: 17.240299 | K14: 38.592293 | L14: 38.510077 | M14: 22.929858 | N14: 11.967719
B15: Бренд 9 | C15: 21.640559 | D15: 7.17299 | E15: 8.3276978 | F15: 14.920891 | G15: 19.478847 | H15: 33.763382 | I15: 55.733841 | J15: 11.74505 | K15: 12.234241 | L15: 82.824652 | M15: 17.504139 | N15: 1.7100472
B16: Бренд 10 | C16: 7.4559148 | D16: 32.382564 | E16: 15.416481 | F16: 28.984176 | G16: 7.8096338 | H16: 67.692854 | I16: 89.454724 | J16: 12.351313 | K16: 53.710928 | L16: 74.86404 | M16: 6.2341435 | N16: 17.936745
B17: Премиум сегмент
B18: Бренд 1 | C18: 49.34092 | D18: 27.1361 | E18: 28.929057 | F18: 7.7460073 | G18: 37.374258 | H18: 14.232158 | I18: 6.5901463 | J18: 11.201432 | K18: 63.302371 | L18: 5.2848462 | M18: 79.377562 | N18: 35.091958
B19: Бренд 2 | C19: 34.835538 | D19: 7.6167736 | E19: 27.338799 | F19: 20.663425 | G19: 43.786375 | H19: 40.777536 | I19: 17.846269 | J19: 40.983693 | K19: 24.381705 | L19: 9.0669676 | M19: 18.389933 | N19: 2.1408773
B20: Бренд 3 | C20: 7.1933052 | D20: 22.143705 | E20: 34.839175 | F20: 53.946326 | G20: 43.407642 | H20: 22.774957 | I20: 25.866388 | J20: 7.1072508 | K20: 2.9107977 | L20: 33.000407 | M20: 22.67471 | N20: 4.726733
B21: Бренд 4 | C21: 21.465348 | D21: 21.72355 | E21: 47.151725 | F21: 16.708365 | G21: 37.951666 | H21: 21.451109 | I21: 39.646347 | J21: 36.89337 | K21: 2.8911094 | L21: 59.050529 | M21: 3.7947341 | N21: 34.133603
B22: Бренд 5 | C22: 33.786433 | D22: 6.7048856 | E22: 7.8109237 | F22: 9.5761729 | G22: 62.906628 | H22: 6.5363034 | I22: 30.893022 | J22: 36.132962 | K22: 16.605613 | L22: 50.664063 | M22: 6.1071165 | N22: 32.355809
B23: Бренд 6 | C23: 55.979469 | D23: 38.047686 | E23: 5.0233745 | F23: 6.7465642 | G23: 29.972787 | H23: 11.702264 | I23: 39.868941 | J23: 21.674293 | K23: 8.3589443 | L23: 78.722464 | M23: 18.49092 | N23: 5.2571401
B24: Бренд 7 | C24: 69.83957 | D24: 14.504757 | E24: 10.975808 | F24: 46.648343 | G24: 18.155249 | H24: 24.906214 | I24: 21.569305 | J24: 10.884708 | K24: 14.689034 | L24: 2.8803547 | M24: 45.574424 | N24: 91.335335
B25: Бренд 8 | C25: 13.139919 | D25: 53.04678 | E25: 20.000865 | F25: 7.0201954 | G25: 23.132122 | H25: 35.823762 | I25: 17.871672 | J25: 26.530391 | K25: 22.215708 | L25: 30.223977 | M25: 49.356443 | N25: 14.863445
B26: Бренд 9 | C26: 25.143286 | D26: 21.046982 | E26: 31.331629 | F26: 38.340069 | G26: 1.6143339 | H26: 15.122471 | I26: 45.607641 | J26: 39.004328 | K26: 0.76205963 | L26: 13.370408 | M26: 41.16635 | N26: 10.436922
B27: Бренд 10 | C27: 0.59849322 | D27: 19.173924 | E27: 28.616565 | F27: 19.498483 | G27: 12.708715 | H27: 26.847733 | I27: 32.316105 | J27: 28.688112 | K27: 28.224056 | L27: 9.9606261 | M27: 29.573414 | N27: 68.787389
B28: Офлайн продажи
B29: Эконом сегмент
B30: Бренд 1 | C30: 49.917382 | D30: 19.496222 | E30: 52.013128 | F30: 68.587236 | G30: 42.340018 | H30: 8.4116198 | I30: 84.294354 | J30: 44.322938 | K30: 3.8462412 | L30: 19.041216 | M30: 22.478554 | N30: 58.237276
B31: Бренд 2 | C31: 16.233441 | D31: 59.924532 | E31: 19.90603 | F31: 4.555899 | G31: 4.2701581 | H31: 22.937889 | I31: 31.466098 | J31: 42.510945 | K31: 3.193302 | L31: 34.584155 | M31: 67.847532 | N31: 63.376672
B32: Бренд 3 | C32: 18.987399 | D32: 44.326874 | E32: 26.350137 | F32: 31.989536 | G32: 28.4583 | H32: 40.816891 | I32: 31.239174 | J32: 4.7939377 | K32: 40.316188 | L32: 19.694182 | M32: 18.248065 | N32: 46.102108
B33: Бренд 4 | C33: 16.364334 | D33: 15.335892 | E33: 8.404687 | F33: 32.038149 | G33: 34.607624 | H33: 3.5539546 | I33: 31.802753 | J33: 28.20108 | K33: 3.425136 | L33: 1.9040393 | M33: 45.417472 | N33: 38.167434
B34: Бренд 5 | C34: 13.637636 | D34: 48.57449 | E34: 42.490845 | F34: 2.9217132 | G34: 38.029841 | H34: 7.0081389 | I34: 15.693008 | J34: 63.979767 | K34: 34.424048 | L34: 9.4484185 | M34: 40.043731 | N34: 9.5405538
B35: Бренд 6 | C35: 7.0767586 | D35: 30.799148 | E35: 12.222888 | F35: 1.526901 | G35: 95.014158 | H35: 70.066664 | I35: 17.469463 | J35: 2.107023 | K35: 7.6002283 | L35: 20.227803 | M35: 55.755778 | N35: 16.13428
B36: Бренд 7 | C36: 43.727239 | D36: 13.241526 | E36: 1.1989395 | F36: 15.734061 | G36: 3.27422 | H36: 12.604854 | I36: 41.284093 | J36: 9.5499197 | K36: 20.84999 | L36: 20.330541 | M36: 45.138563 | N36: 2.9616219
B37: Бренд 8 | C37: 0.30706464 | D37: 5.7483139 | E37: 41.47568 | F37: 42.531873 | G37: 34.90155 | H37: 29.544549 | I37: 6.5543441 | J37: 12.867844 | K37: 12.890696 | L37: 34.535341 | M37: 22.366368 | N37: 31.537033
B38: Бренд 9 | C38: 16.641579 | D38: 8.4269745 | E38: 1.4194516 | F38: 33.023209 | G38: 48.384809 | H38: 16.690174 | I38: 33.292311 | J38: 8.1760036 | K38: 5.4364535 | L38: 7.6269869 | M38: 13.804761 | N38: 1.8249762
B39: Бренд 10 | C39: 10.83377 | D39: 39.606537 | E39: 18.380132 | F39: 9.8923086 | G39: 63.652466 | H39: 80.821517 | I39: 18.569153 | J39: 19.380344 | K39: 28.456452 | L39: 21.460883 | M39: 5.7222552 | N39: 14.834584
B40: Премиум сегмент
B41: Бренд 1 | C41: 68.509687 | D41: 23.31188 | E41: 10.848903 | F41: 6.7080718 | G41: 25.10333 | H41: 37.586809 | I41: 13.732025 | J41: 1.3284248 | K41: 55.606627 | L41: 23.004259 | M41: 79.496722 | N41: 34.096283
B42: Бренд 2 | C42: 13.041433 | D42: 41.767809 | E42: 21.916558 | F42: 21.745065 | G42: 5.79663 | H42: 75.296316 | I42: 0.07285966 | J42: 11.43801 | K42: 9.7964947 | L42: 30.271906 | M42: 62.049583 | N42: 30.47923
B43: Бренд 3 | C43: 23.423771 | D43: 8.7911999 | E43: 31.003327 | F43: 16.06431 | G43: 4.0700672 | H43: 23.717039 | I43: 5.9420175 | J43: 57.728833 | K43: 4.217215 | L43: 13.751773 | M43: 8.7114613 | N43: 29.622102
B44: Бренд 4 | C44: 13.250761 | D44: 4.4939119 | E44: 3.8932642 | F44: 33.939907 | G44: 86.766471 | H44: 6.8734428 | I44: 46.775531 | J44: 11.847217 | K44: 25.392694 | L44: 3.0383256 | M44: 20.065624 | N44: 2.1079315
B45: Бренд 5 | C45: 17.026083 | D45: 35.378308 | E45: 23.895634 | F45: 15.797448 | G45: 10.834599 | H45: 8.9376843 | I45: 50.272365 | J45: 47.801899 | K45: 47.245689 | L45: 13.59362 | M45: 11.003717 | N45: 25.607744
B46: Бренд 6 | C46: 15.253932 | D46: 18.313637 | E46: 6.6909946 | F46: 66.021619 | G46: 80.885699 | H46: 18.865711 | I46: 18.876499 | J46: 43.609843 | K46: 15.037882 | L46: 18.82816 | M46: 14.187904 | N46: 9.3492326
B47: Бренд 7 | C47: 7.9204595 | D47: 12.191389 | E47: 17.184747 | F47: 29.880712 | G47: 46.879948 | H47: 17.14838 | I47: 64.213243 | J47: 20.510382 | K47: 41.12654 | L47: 41.408461 | M47: 30.45445 | N47: 25.963747
B48: Бренд 8 | C48: 10.633949 | D48: 37.597192 | E48: 3.1503661 | F48: 6.3502823 | G48: 31.704285 | H48: 0.014383767 | I48: 16.015245 | J48: 4.7454771 | K48: 18.213628 | L48: 18.124371 | M48: 18.189547 | N48: 40.309297
B49: Бренд 9 | C49: 13.907426 | D49: 27.618582 | E49: 25.345884 | F49: 28.142298 | G49: 7.0283779 | H49: 24.382734 | I49: 1.8688868 | J49: 19.187332 | K49: 7.8630547 | L49: 67.754529 | M49: 7.4347556 | N49: 31.016747
B50: Бренд 10 | C50: 10.019151 | D50: 47.818637 | E50: 12.304677 | F50: 6.6319373 | G50: 77.915888 | H50: 33.478268 | I50: 7.5482916 | J50: 63.267393 | K50: 7.8311373 | L50: 2.6755574 | M50: 62.01635 | N50: 82.283619
B52: Корма для кошек
B53: Онлайн продажи
B54: Эконом сегмент
B55: Бренд 1 | C55: 14.741586 | D55: 0.22252912 | E55: 29.05809 | F55: 15.446216 | G55: 28.229552 | H55: 4.3920226 | I55: 9.9694974 | J55: 16.236113 | K55: 11.746536 | L55: 7.904783 | M55: 19.466814 | N55: 30.430843
B56: Бренд 2 | C56: 34.885628 | D56: 23.642576 | E56: 38.080955 | F56: 11.666727 | G56: 49.21916 | H56: 2.309582 | I56: 34.998756 | J56: 9.5311443 | K56: 27.788371 | L56: 9.3936631 | M56: 53.023202 | N56: 19.487807
B57: Бренд 3 | C57: 4.0909481 | D57: 80.303958 | E57: 31.751147 | F57: 43.699102 | G57: 24.47821 | H57: 49.21454 | I57: 1.390803 | J57: 13.911102 | K57: 0.71733015 | L57: 39.505965 | M57: 71.734219 | N57: 10.276514
B58: Бренд 4 | C58: 9.8472748 | D58: 2.8020327 | E58: 31.886021 | F58: 26.419945 | G58: 29.730123 | H58: 11.945943 | I58: 33.161864 | J58: 49.3304 | K58: 9.3467845 | L58: 72.309927 | M58: 9.2646485 | N58: 4.2236141
B59: Бренд 5 | C59: 9.3201798 | D59: 76.171961 | E59: 45.467436 | F59: 13.629793 | G59: 13.39695 | H59: 1.0335998 | I59: 13.691993 | J59: 23.424456 | K59: 1.1933015 | L59: 44.150741 | M59: 42.886423 | N59: 73.37017
B60: Бренд 6 | C60: 1.281804 | D60: 3.8409132 | E60: 1.4868467 | F60: 30.651767 | G60: 35.972381 | H60: 2.503926 | I60: 22.183524 | J60: 51.734183 | K60: 68.934655 | L60: 72.7237 | M60: 3.169973 | N60: 87.189586
B61: Бренд 7 | C61: 7.7981467 | D61: 4.5447556 | E61: 76.202486 | F61: 25.93922 | G61: 65.142959 | H61: 46.861589 | I61: 27.029351 | J61: 6.7810045 | K61: 22.283893 | L61: 36.554048 | M61: 19.422092 | N61: 37.579403
B62: Бренд 8 | C62: 32.431888 | D62: 8.6217364 | E62: 18.020063 | F62: 9.6450072 | G62: 8.1815422 | H62: 45.521771 | I62: 44.313485 | J62: 20.531003 | K62: 59.709412 | L62: 31.465266 | M62: 34.053863 | N62: 3.7273894
B63: Бренд 9 | C63: 48.893272 | D63: 32.952903 | E63: 27.493834 | F63: 12.560585 | G63: 37.525544 | H63: 10.837921 | I63: 60.00269 | J63: 19.947383 | K63: 17.221396 | L63: 36.693062 | M63: 7.9434257 | N63: 21.122723
B64: Бренд 10 | C64: 1.2179167 | D64: 5.4846441 | E64: 23.812185 | F64: 6.3743585 | G64: 53.086215 | H64: 30.057138 | I64: 25.969719 | J64: 58.717597 | K64: 39.50799 | L64: 2.0891049 | M64: 21.920693 | N64: 7.6040781
B65: Премиум сегмент
B66: Бренд 1 | C66: 16.878766 | D66: 65.805173 | E66: 25.394737 | F66: 25.23827 | G66: 4.9644413 | H66: 10.576248 | I66: 13.450355 | J66: 1.4732018 | K66: 18.584184 | L66: 31.451868 | M66: 22.675749 | N66: 17.394593
B67: Бренд 2 | C67: 62.90042 | D67: 34.12202 | E67: 39.198566 | F67: 44.721617 | G67: 6.1578119 | H67: 56.992293 | I67: 3.2060801 | J67: 40.535083 | K67: 43.183131 | L67: 41.91411 | M67: 18.151105 | N67: 28.823068
B68: Бренд 3 | C68: 40.459711 | D68: 16.40695 | E68: 2.6415976 | F68: 15.232877 | G68: 32.526065 | H68: 48.21774 | I68: 6.8242805 | J68: 12.652773 | K68: 10.323215 | L68: 49.785611 | M68: 26.42434 | N68: 23.167603
B69: Бренд 4 | C69: 34.706566 | D69: 26.740014 | E69: 31.615373 | F69: 90.026236 | G69: 4.4181278 | H69: 15.740854 | I69: 50.565903 | J69: 55.014552 | K69: 23.210361 | L69: 82.672407 | M69: 50.320556 | N69: 31.588362
B70: Бренд 5 | C70: 7.4123465 | D70: 8.1565618 | E70: 4.201419 | F70: 40.239173 | G70: 38.242021 | H70: 32.75821 | I70: 64.598714 | J70: 36.349326 | K70: 2.2495957 | L70: 20.102252 | M70: 71.142319 | N70: 7.1723749
B71: Бренд 6 | C71: 41.215925 | D71: 13.651169 | E71: 28.606664 | F71: 0.11968485 | G71: 17.767861 | H71: 8.8095265 | I71: 6.8743387 | J71: 11.181274 | K71: 4.0036677 | L71: 46.54648 | M71: 48.374488 | N71: 16.964919
B72: Бренд 7 | C72: 0.92663594 | D72: 44.632069 | E72: 33.804652 | F72: 40.628217 | G72: 16.77294 | H72: 12.433187 | I72: 51.195786 | J72: 13.929853 | K72: 0.93885519 | L72: 19.097792 | M72: 33.536428 | N72: 6.5351085
B73: Бренд 8 | C73: 3.3150677 | D73: 27.363792 | E73: 75.388426 | F73: 5.571042 | G73: 79.585909 | H73: 12.970165 | I73: 16.59301 | J73: 92.704457 | K73: 16.417151 | L73: 25.849782 | M73: 7.8886018 | N73: 14.832285
B74: Бренд 9 | C74: 42.586866 | D74: 5.4990086 | E74: 6.0565051 | F74: 62.340037 | G74: 13.698389 | H74: 16.881794 | I74: 28.312886 | J74: 43.92167 | K74: 81.742231 | L74: 28.377685 | M74: 23.373995 | N74: 7.1324289
B75: Бренд 10 | C75: 14.101421 | D75: 40.818577 | E75: 71.142191 | F75: 11.714652 | G75: 44.454898 | H75: 21.246411 | I75: 21.279048 | J75: 17.334185 | K75: 82.402629 | L75: 10.017179 | M75: 2.0783992 | N75: 3.8380259
B76: Офлайн продажи
B77: Эконом сегмент
B78: Бренд 1 | C78: 14.741586 | D78: 0.22252912 | E78: 58.116179 | F78: 15.446216 | G78: 28.229552 | H78: 4.3920226 | I78: 9.9694974 | J78: 32.472225 | K78: 23.493072 | L78: 7.904783 | M78: 19.466814 | N78: 30.430843
B79: Бренд 2 | C79: 69.771257 | D79: 23.642576 | E79: 76.16191 | F79: 11.666727 | G79: 49.21916 | H79: 4.6191641 | I79: 34.998756 | J79: 19.062289 | K79: 27.788371 | L79: 18.787326 | M79: 106.0464 | N79: 19.487807
B80: Бренд 3 | C80: 8.1818962 | D80: 80.303958 | E80: 31.751147 | F80: 87.398204 | G80: 24.47821 | H80: 49.21454 | I80: 2.7816059 | J80: 27.822203 | K80: 1.4346603 | L80: 39.505965 | M80: 71.734219 | N80: 10.276514
B81: Бренд 4 | C81: 19.69455 | D81: 5.6040655 | E81: 63.772041 | F81: 52.83989 | G81: 59.460247 | H81: 23.891886 | I81: 66.323729 | J81: 98.6608 | K81: 9.3467845 | L81: 144.61985 | M81: 9.2646485 | N81: 8.4472281
B82: Бренд 5 | C82: 18.64036 | D82: 76.171961 | E82: 45.467436 | F82: 27.259586 | G82: 26.7939 | H82: 2.0671997 | I82: 27.383987 | J82: 23.424456 | K82: 1.1933015 | L82: 88.301481 | M82: 85.772847 | N82: 73.37017
B83: Бренд 6 | C83: 2.563608 | D83: 3.8409132 | E83: 2.9736934 | F83: 61.303534 | G83: 71.944763 | H83: 5.0078521 | I83: 44.367048 | J83: 103.46837 | K83: 68.934655 | L83: 145.4474 | M83: 3.169973 | N83: 174.37917
B84: Бренд 7 | C84: 15.596293 | D84: 9.0895112 | E84: 152.40497 | F84: 51.87844 | G84: 65.142959 | H84: 93.723177 | I84: 27.029351 | J84: 13.562009 | K84: 44.567787 | L84: 73.108096 | M84: 38.844183 | N84: 37.579403
B85: Бренд 8 | C85: 32.431888 | D85: 8.6217364 | E85: 18.020063 | F85: 19.290014 | G85: 16.363084 | H85: 91.043541 | I85: 88.626969 | J85: 41.062006 | K85: 59.709412 | L85: 62.930533 | M85: 68.107726 | N85: 7.4547787
B86: Бренд 9 | C86: 97.786544 | D86: 65.905806 | E86: 54.987668 | F86: 25.12117 | G86: 37.525544 | H86: 21.675842 | I86: 120.00538 | J86: 19.947383 | K86: 34.442792 | L86: 36.693062 | M86: 15.886851 | N86: 42.245445
B87: Бренд 10 | C87: 2.4358335 | D87: 5.4846441 | E87: 23.812185 | F87: 6.3743585 | G87: 106.17243 | H87: 30.057138 | I87: 25.969719 | J87: 117.43519 | K87: 39.50799 | L87: 4.1782098 | M87: 43.841387 | N87: 15.208156
B88: Премиум сегмент
B89: Бренд 1 | C89: 33.757533 | D89: 65.805173 | E89: 50.789475 | F89: 25.23827 | G89: 9.9288827 | H89: 21.152496 | I89: 26.90071 | J89: 1.4732018 | K89: 18.584184 | L89: 31.451868 | M89: 22.675749 | N89: 17.394593
B90: Бренд 2 | C90: 62.90042 | D90: 68.24404 | E90: 78.397133 | F90: 89.443233 | G90: 6.1578119 | H90: 113.98459 | I90: 3.2060801 | J90: 40.535083 | K90: 43.183131 | L90: 83.828221 | M90: 18.151105 | N90: 57.646136
B91: Бренд 3 | C91: 80.919422 | D91: 32.8139 | E91: 2.6415976 | F91: 15.232877 | G91: 32.526065 | H91: 48.21774 | I91: 13.648561 | J91: 12.652773 | K91: 20.646431 | L91: 49.785611 | M91: 26.42434 | N91: 46.335207
B92: Бренд 4 | C92: 34.706566 | D92: 26.740014 | E92: 63.230746 | F92: 180.05247 | G92: 4.4181278 | H92: 15.740854 | I92: 50.565903 | J92: 55.014552 | K92: 46.420721 | L92: 82.672407 | M92: 50.320556 | N92: 31.588362
B93: Бренд 5 | C93: 7.4123465 | D93: 8.1565618 | E93: 8.402838 | F93: 80.478345 | G93: 38.242021 | H93: 65.516419 | I93: 64.598714 | J93: 72.698653 | K93: 2.2495957 | L93: 40.204505 | M93: 142.28464 | N93: 14.34475
B94: Бренд 6 | C94: 41.215925 | D94: 27.302338 | E94: 57.213328 | F94: 0.23936969 | G94: 35.535722 | H94: 17.619053 | I94: 13.748677 | J94: 11.181274 | K94: 4.0036677 | L94: 93.09296 | M94: 48.374488 | N94: 33.929837
B95: Бренд 7 | C95: 0.92663594 | D95: 44.632069 | E95: 33.804652 | F95: 81.256435 | G95: 16.77294 | H95: 24.866374 | I95: 51.195786 | J95: 27.859705 | K95: 1.8777104 | L95: 38.195585 | M95: 67.072857 | N95: 6.5351085
B96: Бренд 8 | C96: 3.3150677 | D96: 27.363792 | E96: 150.77685 | F96: 11.142084 | G96: 159.17182 | H96: 12.970165 | I96: 16.59301 | J96: 185.40891 | K96: 32.834301 | L96: 25.849782 | M96: 15.777204 | N96: 14.832285
B97: Бренд 9 | C97: 85.173732 | D97: 10.998017 | E97: 6.0565051 | F97: 124.68007 | G97: 27.396777 | H97: 33.763588 | I97: 56.625771 | J97: 87.84334 | K97: 163.48446 | L97: 28.377685 | M97: 46.747991 | N97: 7.1324289
B98: Бренд 10 | C98: 14.101421 | D98: 40.818577 | E98: 142.28438 | F98: 23.429304 | G98: 88.909795 | H98: 21.246411 | I98: 42.558095 | J98: 17.334185 | K98: 164.80526 | L98: 10.017179 | M98: 2.0783992 | N98: 7.6760517

Sheet цены 1 полуг
B1: 44927 | C1: 44958 | D1: 44986 | E1: 45017 | F1: 45047 | G1: 45078
A3: Цены
A4: Рублей/кило
A5: 1 полугодие
A19: Корма для собак
A20: Онлайн продажи
A21: Эконом сегмент
A22: Бренд 1 | B22: 113 | C22: 110 | D22: 104 | E22: 164 | F22: 162 | G22: 136
A23: Бренд 2 | B23: 114 | C23: 181 | D23: 126 | E23: 113 | F23: 156 | G23: 144
A24: Бренд 3 | B24: 157 | C24: 129 | D24: 120 | E24: 111 | F24: 124 | G24: 177
A25: Бренд 4 | B25: 153 | C25: 190 | D25: 186 | E25: 124 | F25: 164 | G25: 112
A26: Бренд 5 | B26: 182 | C26: 174 | D26: 171 | E26: 186 | F26: 104 | G26: 187
A27: Бренд 6 | B27: 190 | C27: 130 | D27: 162 | E27: 120 | F27: 143 | G27: 101
A28: Бренд 7 | B28: 193 | C28: 196 | D28: 138 | E28: 162 | F28: 131 | G28: 112
A29: Бренд 8 | B29: 139 | C29: 130 | D29: 200 | E29: 102 | F29: 130 | G29: 156
A30: Бренд 9 | B30: 157 | C30: 130 | D30: 101 | E30: 103 | F30: 155 | G30: 166
A31: Бренд 10 | B31: 190 | C31: 148 | D31: 103 | E31: 147 | F31: 163 | G31: 135
A32: Премиум сегмент
A33: Бренд 1 | B33: 388 | C33: 318 | D33: 345 | E33: 311 | F33: 383 | G33: 383
A34: Бренд 2 | B34: 323 | C34: 364 | D34: 333 | E34: 331 | F34: 301 | G34: 386
A35: Бренд 3 | B35: 372 | C35: 300 | D35: 314 | E35: 383 | F35: 331 | G35: 383
A36: Бренд 4 | B36: 365 | C36: 399 | D36: 375 | E36: 329 | F36: 395 | G36: 364
A37: Бренд 5 | B37: 344 | C37: 354 | D37: 374 | E37: 380 | F37: 366 | G37: 303
A38: Бренд 6 | B38: 335 | C38: 338 | D38: 382 | E38: 398 | F38: 335 | G38: 391
A39: Бренд 7 | B39: 381 | C39: 327 | D39: 338 | E39: 306 | F39: 369 | G39: 306
A40: Бренд 8 | B40: 339 | C40: 336 | D40: 397 | E40: 330 | F40: 393 | G40: 324
A41: Бренд 9 | B41: 344 | C41: 336 | D41: 344 | E41: 332 | F41: 336 | G41: 383
A42: Бренд 10 | B42: 327 | C42: 383 | D42: 375 | E42: 383 | F42: 304 | G42: 382
A43: Офлайн продажи
A44: Эконом сегмент
A45: Бренд 1 | B45: 199 | C45: 107 | D45: 115 | E45: 196 | F45: 149 | G45: 148
A46: Бренд 2 | B46: 164 | C46: 115 | D46: 133 | E46: 119 | F46: 150 | G46: 116
A47: Бренд 3 | B47: 114 | C47: 150 | D47: 114 | E47: 107 | F47: 104 | G47: 193
A48: Бренд 4 | B48: 106 | C48: 117 | D48: 167 | E48: 197 | F48: 122 | G48: 178
A49: Бренд 5 | B49: 119 | C49: 138 | D49: 101 | E49: 110 | F49: 153 | G49: 140
A50: Бренд 6 | B50: 166 | C50: 121 | D50: 175 | E50: 127 | F50: 138 | G50: 195
A51: Бренд 7 | B51: 156 | C51: 183 | D51: 180 | E51: 141 | F51: 144 | G51: 100
A52: Бренд 8 | B52: 120 | C52: 156 | D52: 162 | E52: 114 | F52: 152 | G52: 171
A53: Бренд 9 | B53: 105 | C53: 140 | D53: 199 | E53: 156 | F53: 197 | G53: 179
A54: Бренд 10 | B54: 147 | C54: 127 | D54: 169 | E54: 162 | F54: 142 | G54: 188
A55: Премиум сегмент
A56: Бренд 1 | B56: 315 | C56: 395 | D56: 361 | E56: 318 | F56: 365 | G56: 368
A57: Бренд 2 | B57: 328 | C57: 364 | D57: 313 | E57: 363 | F57: 367 | G57: 374
A58: Бренд 3 | B58: 348 | C58: 374 | D58: 338 | E58: 374 | F58: 370 | G58: 375
A59: Бренд 4 | B59: 389 | C59: 300 | D59: 362 | E59: 388 | F59: 334 | G59: 342
A60: Бренд 5 | B60: 324 | C60: 331 | D60: 305 | E60: 319 | F60: 395 | G60: 354
A61: Бренд 6 | B61: 372 | C61: 349 | D61: 386 | E61: 371 | F61: 346 | G61: 358
A62: Бренд 7 | B62: 395 | C62: 331 | D62: 323 | E62: 300 | F62: 365 | G62: 390
A63: Бренд 8 | B63: 366 | C63: 303 | D63: 371 | E63: 320 | F63: 381 | G63: 331
A64: Бренд 9 | B64: 302 | C64: 316 | D64: 399 | E64: 339 | F64: 307 | G64: 397
A65: Бренд 10 | B65: 300 | C65: 340 | D65: 328 | E65: 391 | F65: 329 | G65: 390
A67: Корма для кошек
A68: Онлайн продажи
A69: Эконом сегмент
A70: Бренд 1 | B70: 144 | C70: 142 | D70: 146 | E70: 177 | F70: 112 | G70: 148
A71: Бренд 2 | B71: 170 | C71: 157 | D71: 143 | E71: 186 | F71: 159 | G71: 135
A72: Бренд 3 | B72: 177 | C72: 165 | D72: 184 | E72: 106 | F72: 107 | G72: 134
A73: Бренд 4 | B73: 121 | C73: 181 | D73: 142 | E73: 145 | F73: 110 | G73: 115
A74: Бренд 5 | B74: 157 | C74: 186 | D74: 187 | E74: 193 | F74: 111 | G74: 169
A75: Бренд 6 | B75: 107 | C75: 195 | D75: 191 | E75: 119 | F75: 114 | G75: 167
A76: Бренд 7 | B76: 180 | C76: 160 | D76: 199 | E76: 115 | F76: 144 | G76: 172
A77: Бренд 8 | B77: 183 | C77: 176 | D77: 156 | E77: 193 | F77: 116 | G77: 178
A78: Бренд 9 | B78: 171 | C78: 166 | D78: 199 | E78: 175 | F78: 112 | G78: 137
A79: Бренд 10 | B79: 183 | C79: 129 | D79: 174 | E79: 186 | F79: 198 | G79: 111
A80: Премиум сегмент
A81: Бренд 1 | B81: 366 | C81: 316 | D81: 335 | E81: 373 | F81: 391 | G81: 307
A82: Бренд 2 | B82: 310 | C82: 321 | D82: 313 | E82: 337 | F82: 329 | G82: 334
A83: Бренд 3 | B83: 391 | C83: 390 | D83: 330 | E83: 340 | F83: 368 | G83: 400
A84: Бренд 4 | B84: 347 | C84: 348 | D84: 311 | E84: 330 | F84: 385 | G84: 344
A85: Бренд 5 | B85: 400 | C85: 308 | D85: 345 | E85: 344 | F85: 391 | G85: 326
A86: Бренд 6 | B86: 330 | C86: 398 | D86: 314 | E86: 377 | F86: 365 | G86: 344
A87: Бренд 7 | B87: 350 | C87: 344 | D87: 372 | E87: 379 | F87: 333 | G87: 396
A88: Бренд 8 | B88: 311 | C88: 308 | D88: 364 | E88: 356 | F88: 300 | G88: 325
A89: Бренд 9 | B89: 389 | C89: 320 | D89: 302 | E89: 347 | F89: 397 | G89: 337
A90: Бренд 10 | B90: 379 | C90: 353 | D90: 371 | E90: 346 | F90: 318 | G90: 338
A91: Офлайн продажи
A92: Эконом сегмент
A93: Бренд 1 | B93: 162 | C93: 100 | D93: 150 | E93: 122 | F93: 173 | G93: 163
A94: Бренд 2 | B94: 147 | C94: 149 | D94: 137 | E94: 161 | F94: 103 | G94: 153
A95: Бренд 3 | B95: 137 | C95: 200 | D95: 189 | E95: 129 | F95: 128 | G95: 142
A96: Бренд 4 | B96: 105 | C96: 182 | D96: 195 | E96: 167 | F96: 176 | G96: 159
A97: Бренд 5 | B97: 179 | C97: 114 | D97: 132 | E97: 172 | F97: 109 | G97: 131
A98: Бренд 6 | B98: 135 | C98: 113 | D98: 172 | E98: 197 | F98: 146 | G98: 194
A99: Бренд 7 | B99: 114 | C99: 127 | D99: 169 | E99: 174 | F99: 190 | G99: 102
A100: Бренд 8 | B100: 142 | C100: 184 | D100: 146 | E100: 200 | F100: 139 | G100: 196
A101: Бренд 9 | B101: 122 | C101: 105 | D101: 175 | E101: 139 | F101: 196 | G101: 135
A102: Бренд 10 | B102: 122 | C102: 181 | D102: 137 | E102: 198 | F102: 131 | G102: 199
A103: Премиум сегмент
A104: Бренд 1 | B104: 346 | C104: 394 | D104: 372 | E104: 337 | F104: 392 | G104: 336
A105: Бренд 2 | B105: 311 | C105: 323 | D105: 398 | E105: 391 | F105: 351 | G105: 340
A106: Бренд 3 | B106: 367 | C106: 300 | D106: 368 | E106: 335 | F106: 391 | G106: 334
A107: Бренд 4 | B107: 301 | C107: 330 | D107: 390 | E107: 385 | F107: 337 | G107: 354
A108: Бренд 5 | B108: 381 | C108: 307 | D108: 357 | E108: 369 | F108: 330 | G108: 381
A109: Бренд 6 | B109: 316 | C109: 324 | D109: 320 | E109: 367 | F109: 385 | G109: 348
A110: Бренд 7 | B110: 324 | C110: 367 | D110: 333 | E110: 314 | F110: 364 | G110: 392
A111: Бренд 8 | B111: 396 | C111: 391 | D111: 369 | E111: 314 | F111: 385 | G111: 345
A112: Бренд 9 | B112: 378 | C112: 364 | D112: 348 | E112: 353 | F112: 311 | G112: 326
A113: Бренд 10 | B113: 383 | C113: 316 | D113: 318 | E113: 391 | F113: 371 | G113: 337

Sheet цены 2 полуг
I3: Цены
I4: Рублей/кило
I5: 2 полугодие
M9: 45108 | N9: 45139 | O9: 45170 | P9: 45200 | Q9: 45231 | R9: 45261
H10: Корма для собак | I10: Онлайн продажи
I11: Эконом сегмент
I12: Бренд 1 | M12: 117 | N12: 198 | O12: 118 | P12: 147 | Q12: 159 | R12: 118
I13: Бренд 2 | M13: 137 | N13: 183 | O13: 124 | P13: 158 | Q13: 168 | R13: 188
I14: Бренд 3 | M14: 117 | N14: 189 | O14: 150 | P14: 136 | Q14: 121 | R14: 113
I15: Бренд 4 | M15: 162 | N15: 190 | O15: 153 | P15: 139 | Q15: 165 | R15: 196
I16: Бренд 5 | M16: 177 | N16: 193 | O16: 198 | P16: 137 | Q16: 176 | R16: 166
I17: Бренд 6 | M17: 149 | N17: 152 | O17: 174 | P17: 124 | Q17: 128 | R17: 138
I18: Бренд 7 | M18: 134 | N18: 169 | O18: 156 | P18: 126 | Q18: 141 | R18: 108
I19: Бренд 8 | M19: 153 | N19: 168 | O19: 113 | P19: 155 | Q19: 179 | R19: 126
I20: Бренд 9 | M20: 200 | N20: 135 | O20: 153 | P20: 178 | Q20: 144 | R20: 149
I21: Бренд 10 | M21: 175 | N21: 161 | O21: 110 | P21: 176 | Q21: 150 | R21: 177
I22: Премиум сегмент
I23: Бренд 1 | M23: 318 | N23: 326 | O23: 390 | P23: 318 | Q23: 313 | R23: 344
I24: Бренд 2 | M24: 347 | N24: 320 | O24: 313 | P24: 313 | Q24: 385 | R24: 365
I25: Бренд 3 | M25: 343 | N25: 314 | O25: 381 | P25: 389 | Q25: 303 | R25: 320
I26: Бренд 4 | M26: 362 | N26: 340 | O26: 349 | P26: 362 | Q26: 378 | R26: 308
I27: Бренд 5 | M27: 370 | N27: 308 | O27: 311 | P27: 387 | Q27: 340 | R27: 382
I28: Бренд 6 | M28: 300 | N28: 381 | O28: 365 | P28: 320 | Q28: 311 | R28: 328
I29: Бренд 7 | M29: 373 | N29: 343 | O29: 376 | P29: 352 | Q29: 343 | R29: 333
I30: Бренд 8 | M30: 349 | N30: 319 | O30: 326 | P30: 311 | Q30: 356 | R30: 352
I31: Бренд 9 | M31: 331 | N31: 386 | O31: 301 | P31: 326 | Q31: 304 | R31: 304
I32: Бренд 10 | M32: 369 | N32: 312 | O32: 324 | P32: 328 | Q32: 347 | R32: 311
I33: Офлайн продажи
I34: Эконом сегмент
I35: Бренд 1 | M35: 126 | N35: 113 | O35: 102 | P35: 103 | Q35: 200 | R35: 162
I36: Бренд 2 | M36: 182 | N36: 129 | O36: 179 | P36: 189 | Q36: 198 | R36: 180
I37: Бренд 3 | M37: 173 | N37: 194 | O37: 104 | P37: 138 | Q37: 191 | R37: 110
I38: Бренд 4 | M38: 156 | N38: 147 | O38: 125 | P38: 111 | Q38: 187 | R38: 165
I39: Бренд 5 | M39: 161 | N39: 199 | O39: 123 | P39: 176 | Q39: 137 | R39: 119
I40: Бренд 6 | M40: 114 | N40: 132 | O40: 149 | P40: 172 | Q40: 156 | R40: 108
I41: Бренд 7 | M41: 195 | N41: 116 | O41: 169 | P41: 118 | Q41: 183 | R41: 161
I42: Бренд 8 | M42: 100 | N42: 149 | O42: 121 | P42: 176 | Q42: 185 | R42: 149
I43: Бренд 9 | M43: 107 | N43: 108 | O43: 138 | P43: 138 | Q43: 165 | R43: 193
I44: Бренд 10 | M44: 178 | N44: 195 | O44: 146 | P44: 131 | Q44: 180 | R44: 105
I45: Премиум сегмент
I46: Бренд 1 | M46: 354 | N46: 322 | O46: 387 | P46: 342 | Q46: 334 | R46: 353
I47: Бренд 2 | M47: 308 | N47: 389 | O47: 393 | P47: 316 | Q47: 306 | R47: 309
I48: Бренд 3 | M48: 353 | N48: 325 | O48: 386 | P48: 308 | Q48: 385 | R48: 352
I49: Бренд 4 | M49: 303 | N49: 329 | O49: 362 | P49: 374 | Q49: 389 | R49: 346
I50: Бренд 5 | M50: 311 | N50: 349 | O50: 370 | P50: 338 | Q50: 318 | R50: 373
I51: Бренд 6 | M51: 304 | N51: 316 | O51: 376 | P51: 342 | Q51: 345 | R51: 393
I52: Бренд 7 | M52: 366 | N52: 388 | O52: 392 | P52: 379 | Q52: 365 | R52: 344
I53: Бренд 8 | M53: 348 | N53: 313 | O53: 320 | P53: 390 | Q53: 370 | R53: 350
I54: Бренд 9 | M54: 312 | N54: 348 | O54: 382 | P54: 351 | Q54: 381 | R54: 366
I55: Бренд 10 | M55: 314 | N55: 333 | O55: 315 | P55: 397 | Q55: 400 | R55: 346
H58: Корма для кошек | I58: Онлайн продажи
I59: Эконом сегмент
I60: Бренд 1 | M60: 160 | N60: 200 | O60: 190 | P60: 153 | Q60: 142 | R60: 194
I61: Бренд 2 | M61: 182 | N61: 183 | O61: 115 | P61: 120 | Q61: 100 | R61: 195
I62: Бренд 3 | M62: 191 | N62: 119 | O62: 109 | P62: 111 | Q62: 128 | R62: 138
I63: Бренд 4 | M63: 162 | N63: 197 | O63: 182 | P63: 179 | Q63: 114 | R63: 189
I64: Бренд 5 | M64: 193 | N64: 144 | O64: 194 | P64: 151 | Q64: 180 | R64: 173
I65: Бренд 6 | M65: 106 | N65: 189 | O65: 199 | P65: 155 | Q65: 138 | R65: 155
I66: Бренд 7 | M66: 177 | N66: 105 | O66: 159 | P66: 124 | Q66: 132 | R66: 188
I67: Бренд 8 | M67: 168 | N67: 156 | O67: 110 | P67: 128 | Q67: 151 | R67: 164
I68: Бренд 9 | M68: 165 | N68: 137 | O68: 113 | P68: 173 | Q68: 199 | R68: 115
I69: Бренд 10 | M69: 142 | N69: 184 | O69: 199 | P69: 118 | Q69: 134 | R69: 127
I70: Премиум сегмент
I71: Бренд 1 | M71: 313 | N71: 347 | O71: 388 | P71: 325 | Q71: 361 | R71: 372
I72: Бренд 2 | M72: 300 | N72: 317 | O72: 307 | P72: 304 | Q72: 338 | R72: 387
I73: Бренд 3 | M73: 332 | N73: 316 | O73: 339 | P73: 304 | Q73: 311 | R73: 383
I74: Бренд 4 | M74: 399 | N74: 331 | O74: 317 | P74: 384 | Q74: 303 | R74: 357
I75: Бренд 5 | M75: 320 | N75: 374 | O75: 324 | P75: 350 | Q75: 368 | R75: 303
I76: Бренд 6 | M76: 314 | N76: 304 | O76: 331 | P76: 327 | Q76: 345 | R76: 316
I77: Бренд 7 | M77: 384 | N77: 353 | O77: 334 | P77: 353 | Q77: 312 | R77: 400
I78: Бренд 8 | M78: 352 | N78: 310 | O78: 342 | P78: 324 | Q78: 396 | R78: 310
I79: Бренд 9 | M79: 375 | N79: 347 | O79: 374 | P79: 309 | Q79: 381 | R79: 343
I80: Бренд 10 | M80: 345 | N80: 325 | O80: 392 | P80: 357 | Q80: 313 | R80: 301
I81: Офлайн продажи
I82: Эконом сегмент
I83: Бренд 1 | M83: 172 | N83: 177 | O83: 177 | P83: 121 | Q83: 135 | R83: 144
I84: Бренд 2 | M84: 159 | N84: 115 | O84: 131 | P84: 118 | Q84: 115 | R84: 126
I85: Бренд 3 | M85: 125 | N85: 119 | O85: 117 | P85: 172 | Q85: 192 | R85: 109
I86: Бренд 4 | M86: 191 | N86: 139 | O86: 184 | P86: 142 | Q86: 188 | R86: 135
I87: Бренд 5 | M87: 166 | N87: 130 | O87: 192 | P87: 116 | Q87: 148 | R87: 102
I88: Бренд 6 | M88: 197 | N88: 158 | O88: 174 | P88: 176 | Q88: 108 | R88: 187
I89: Бренд 7 | M89: 185 | N89: 119 | O89: 169 | P89: 121 | Q89: 171 | R89: 118
I90: Бренд 8 | M90: 144 | N90: 107 | O90: 128 | P90: 126 | Q90: 190 | R90: 147
I91: Бренд 9 | M91: 112 | N91: 183 | O91: 145 | P91: 127 | Q91: 129 | R91: 161
I92: Бренд 10 | M92: 111 | N92: 148 | O92: 155 | P92: 161 | Q92: 166 | R92: 156
I93: Премиум сегмент
I94: Бренд 1 | M94: 375 | N94: 336 | O94: 318 | P94: 384 | Q94: 380 | R94: 373
I95: Бренд 2 | M95: 359 | N95: 356 | O95: 311 | P95: 313 | Q95: 329 | R95: 396
I96: Бренд 3 | M96: 368 | N96: 347 | O96: 325 | P96: 376 | Q96: 358 | R96: 376
I97: Бренд 4 | M97: 391 | N97: 318 | O97: 346 | P97: 336 | Q97: 390 | R97: 367
I98: Бренд 5 | M98: 336 | N98: 392 | O98: 319 | P98: 308 | Q98: 340 | R98: 383
I99: Бренд 6 | M99: 377 | N99: 340 | O99: 397 | P99: 396 | Q99: 335 | R99: 356
I100: Бренд 7 | M100: 300 | N100: 394 | O100: 371 | P100: 322 | Q100: 400 | R100: 376
I101: Бренд 8 | M101: 303 | N101: 320 | O101: 390 | P101: 378 | Q101: 380 | R101: 327
I102: Бренд 9 | M102: 347 | N102: 346 | O102: 379 | P102: 372 | Q102: 388 | R102: 364
I103: Бренд 10 | M103: 310 | N103: 378 | O103: 307 | P103: 335 | Q103: 388 | R103: 320

Sheet Расходы
B3: Затраты рублей на 1 кило
E9: 44927 | F9: 44958 | G9: 44986 | H9: 45017 | I9: 45047 | J9: 45078 | K9: 45108 | L9: 45139 | M9: 45170 | N9: 45200 | O9: 45231 | P9: 45261
B12: Корма для собак | C12: Онлайн продажи
B13: Корма для собак | C13: Эконом сегмент
B14: Корма для собак | C14: Бренд 1 | E14: 73.68745 | F14: 96.479189 | G14: 68.053013 | H14: 103.55351 | I14: 142.55331 | J14: 103.99019 | K14: 98.324176 | L14: 202.1684 | M14: 133.82838 | N14: 125.52615 | O14: 121.55107 | P14: 103.99419
B15: Корма для собак | C15: Бренд 2 | E15: 113.76376 | F15: 207.54996 | G15: 145.7709 | H15: 71.269187 | I15: 107.8372 | J15: 146.08756 | K15: 77.642335 | L15: 201.0971 | M15: 93.040861 | N15: 178.52564 | O15: 189.41568 | P15: 174.32709
B16: Корма для собак | C16: Бренд 3 | E16: 158.97745 | F16: 136.04412 | G16: 96.337489 | H16: 126.77373 | I16: 110.30804 | J16: 166.15905 | K16: 131.00135 | L16: 218.93305 | M16: 158.91509 | N16: 109.72604 | O16: 90.082491 | P16: 101.0503
B17: Корма для собак | C17: Бренд 4 | E17: 155.74072 | F17: 178.35061 | G17: 164.67512 | H17: 136.72686 | I17: 186.01308 | J17: 94.705678 | K17: 200.86377 | L17: 116.97876 | M17: 156.91925 | N17: 117.63249 | O17: 123.22341 | P17: 206.23773
B18: Корма для собак | C18: Бренд 5 | E18: 160.15559 | F18: 163.15784 | G18: 204.79837 | H18: 200.77033 | I18: 118.04719 | J18: 144.23594 | K18: 197.3595 | L18: 238.44965 | M18: 157.12074 | N18: 97.938732 | O18: 214.69738 | P18: 115.2591
B19: Корма для собак | C19: Бренд 6 | E19: 164.14089 | F19: 95.730857 | G19: 181.95688 | H19: 86.898666 | I19: 88.794245 | J19: 95.290166 | K19: 135.05312 | L19: 96.741904 | M19: 113.02344 | N19: 79.407619 | O19: 119.13425 | P19: 154.55379
B20: Корма для собак | C20: Бренд 7 | E20: 162.09985 | F20: 120.17278 | G20: 139.56107 | H20: 203.54711 | I20: 119.55518 | J20: 117.75781 | K20: 147.0249 | L20: 115.81659 | M20: 130.16139 | N20: 136.87862 | O20: 99.149188 | P20: 115.62319
B21: Корма для собак | C21: Бренд 8 | E21: 150.83837 | F21: 120.31677 | G21: 159.67742 | H21: 70.829999 | I21: 144.88447 | J21: 193.27453 | K21: 121.07124 | L21: 122.54206 | M21: 80.615686 | N21: 168.81613 | O21: 105.31913 | P21: 152.85991
B22: Корма для собак | C22: Бренд 9 | E22: 105.48649 | F22: 108.08928 | G22: 73.041405 | H22: 103.92511 | I22: 160.55824 | J22: 132.37691 | K22: 135.13362 | L22: 110.33458 | M22: 124.1447 | N22: 220.68534 | O22: 177.64252 | P22: 161.51689
B23: Корма для собак | C23: Бренд 10 | E23: 174.86751 | F23: 175.65337 | G23: 68.705118 | H23: 135.47936 | I23: 157.90157 | J23: 81.245845 | K23: 215.42402 | L23: 142.9234 | M23: 128.8738 | N23: 187.46531 | O23: 98.222373 | P23: 211.4416
B24: Корма для собак | C24: Премиум сегмент
B25: Корма для собак | C25: Бренд 1 | E25: 318.04236 | F25: 194.28134 | G25: 292.28776 | H25: 338.40309 | I25: 308.02895 | J25: 343.80431 | K25: 308.9503 | L25: 245.88654 | M25: 242.71475 | N25: 364.2034 | O25: 330.42763 | P25: 324.46537
B26: Корма для собак | C26: Бренд 2 | E26: 349.1158 | F26: 422.37055 | G26: 261.51466 | H26: 368.00175 | I26: 190.9169 | J26: 329.23245 | K26: 293.62121 | L26: 220.23785 | M26: 291.26588 | N26: 322.80878 | O26: 468.05382 | P26: 384.59304
B27: Корма для собак | C27: Бренд 3 | E27: 385.25811 | F27: 289.449 | G27: 247.74055 | H27: 356.77754 | I27: 345.66587 | J27: 487.31145 | K27: 237.52911 | L27: 228.236 | M27: 437.00437 | N27: 313.49308 | O27: 305.16539 | P27: 337.74911
B28: Корма для собак | C28: Бренд 4 | E28: 454.10057 | F28: 334.66836 | G28: 431.68525 | H28: 388.8117 | I28: 503.37686 | J28: 241.40188 | K28: 276.91418 | L28: 273.32948 | M28: 253.51119 | N28: 401.79119 | O28: 384.87516 | P28: 204.66064
B29: Корма для собак | C29: Бренд 5 | E29: 213.2344 | F29: 428.03714 | G29: 465.25805 | H29: 236.45591 | I29: 445.18789 | J29: 244.10273 | K29: 441.08362 | L29: 188.30985 | M29: 289.6656 | N29: 344.09025 | O29: 212.38752 | P29: 425.7026
B30: Корма для собак | C30: Бренд 6 | E30: 210.06079 | F30: 356.48582 | G30: 377.18258 | H30: 339.09655 | I30: 340.87676 | J30: 342.60847 | K30: 218.37071 | L30: 434.78276 | M30: 431.20241 | N30: 246.59351 | O30: 307.54743 | P30: 383.79567
B31: Корма для собак | C31: Бренд 7 | E31: 310.78739 | F31: 339.21064 | G31: 254.5262 | H31: 219.61278 | I31: 377.19852 | J31: 321.38588 | K31: 379.36661 | L31: 210.91472 | M31: 379.6618 | N31: 435.45123 | O31: 259.49138 | P31: 406.2916
B32: Корма для собак | C32: Бренд 8 | E32: 417.0995 | F32: 269.1926 | G32: 448.63306 | H32: 304.83838 | I32: 451.70717 | J32: 407.3209 | K32: 295.29847 | L32: 351.74158 | M32: 298.32096 | N32: 346.1413 | O32: 260.60401 | P32: 243.15838
B33: Корма для собак | C33: Бренд 9 | E33: 437.27158 | F33: 289.64618 | G33: 269.8525 | H33: 393.13713 | I33: 338.36746 | J33: 458.44533 | K33: 200.47071 | L33: 260.58486 | M33: 188.71336 | N33: 228.23642 | O33: 363.81138 | P33: 363.78906
B34: Корма для собак | C34: Бренд 10 | E34: 283.64791 | F34: 419.55597 | G34: 301.71083 | H34: 364.81955 | I34: 355.8404 | J34: 487.00844 | K34: 361.48353 | L34: 273.89843 | M34: 385.27589 | N34: 381.412 | O34: 408.98232 | P34: 344.47202
B35: Корма для собак | C35: Офлайн продажи
B36: Корма для собак | C36: Эконом сегмент
B37: Корма для собак | C37: Бренд 1 | E37: 184.16612 | F37: 122.03036 | G37: 84.722494 | H37: 211.27503 | I37: 156.20408 | J37: 170.26838 | K37: 144.96684 | L37: 82.985005 | M37: 116.62329 | N37: 78.533897 | O37: 125.91311 | P37: 99.407262
B38: Корма для собак | C38: Бренд 2 | E38: 164.33684 | F38: 116.19355 | G38: 150.0347 | H38: 87.884076 | I38: 181.20593 | J38: 143.44436 | K38: 159.22875 | L38: 120.54979 | M38: 220.02778 | N38: 198.50371 | O38: 122.97078 | P38: 168.85938
B39: Корма для собак | C39: Бренд 3 | E39: 75.629036 | F39: 128.88708 | G39: 80.538869 | H39: 88.606197 | I39: 91.837729 | J39: 235.04846 | K39: 118.82072 | L39: 226.19385 | M39: 116.71605 | N39: 142.56228 | O39: 134.83121 | P39: 88.520554
B40: Корма для собак | C40: Бренд 4 | E40: 88.728991 | F40: 98.526549 | G40: 144.38917 | H40: 199.85067 | I40: 111.96823 | J40: 165.11171 | K40: 131.03599 | L40: 114.00599 | M40: 124.00132 | N40: 115.56181 | O40: 126.14651 | P40: 158.87787
B41: Корма для собак | C41: Бренд 5 | E41: 91.008058 | F41: 131.06764 | G41: 89.618347 | H41: 75.117436 | I41: 148.03825 | J41: 106.07047 | K41: 107.09507 | L41: 162.92789 | M41: 79.348443 | N41: 192.84124 | O41: 166.5302 | P41: 67.641891
B42: Корма для собак | C42: Бренд 6 | E42: 134.0535 | F42: 135.80404 | G42: 134.53014 | H42: 84.635586 | I42: 124.42487 | J42: 197.58153 | K42: 71.527287 | L42: 88.368091 | M42: 149.25693 | N42: 207.94649 | O42: 126.06782 | P42: 100.04975
B43: Корма для собак | C43: Бренд 7 | E43: 103.82094 | F43: 158.70384 | G43: 143.88852 | H43: 134.03357 | I43: 143.42611 | J43: 121.36934 | K43: 203.91216 | L43: 97.830053 | M43: 140.62658 | N43: 89.547117 | O43: 160.99019 | P43: 156.29051
B44: Корма для собак | C44: Бренд 8 | E44: 106.7347 | F44: 132.30623 | G44: 191.5468 | H44: 106.98027 | I44: 182.62534 | J44: 188.92956 | K44: 114.53096 | L44: 181.48952 | M44: 74.55201 | N44: 218.6157 | O44: 135.67613 | P44: 111.08505
B45: Корма для собак | C45: Бренд 9 | E45: 101.64479 | F45: 149.91605 | G45: 173.37976 | H45: 108.29716 | I45: 233.71648 | J45: 119.49897 | K45: 73.817034 | L45: 122.55082 | M45: 94.64609 | N45: 149.32553 | O45: 170.08912 | P45: 151.3485
B46: Корма для собак | C46: Бренд 10 | E46: 98.467517 | F46: 94.862657 | G46: 134.27103 | H46: 131.43991 | I46: 100.87855 | J46: 152.38879 | K46: 125.56006 | L46: 165.2232 | M46: 149.34794 | N46: 140.12549 | O46: 143.24325 | P46: 115.10837
B47: Корма для собак | C47: Премиум сегмент
B48: Корма для собак | C48: Бренд 1 | E48: 249.5694 | F48: 434.77049 | G48: 393.29677 | H48: 198.39662 | I48: 423.31136 | J48: 379.73971 | K48: 411.50809 | L48: 246.64605 | M48: 283.54433 | N48: 354.12168 | O48: 249.32139 | P48: 423.89901
B49: Корма для собак | C49: Бренд 2 | E49: 407.69364 | F49: 421.44733 | G49: 221.89942 | H49: 306.87305 | I49: 327.17368 | J49: 329.27777 | K49: 258.18296 | L49: 249.08761 | M49: 474.35356 | N49: 386.85206 | O49: 340.16368 | P49: 382.71267
B50: Корма для собак | C50: Бренд 3 | E50: 393.43856 | F50: 260.44078 | G50: 333.0515 | H50: 369.84312 | I50: 369.63759 | J50: 302.5318 | K50: 376.57351 | L50: 303.22637 | M50: 393.78075 | N50: 345.87172 | O50: 310.04743 | P50: 318.31233
B51: Корма для собак | C51: Бренд 4 | E51: 292.57036 | F51: 343.93926 | G51: 329.58613 | H51: 411.2127 | I51: 231.21894 | J51: 259.01266 | K51: 298.08236 | L51: 251.02629 | M51: 432.99209 | N51: 389.16218 | O51: 394.68225 | P51: 361.40958
B52: Корма для собак | C52: Бренд 5 | E52: 253.6842 | F52: 363.20404 | G52: 337.63327 | H52: 320.65124 | I52: 267.89999 | J52: 373.17767 | K52: 240.72222 | L52: 333.49773 | M52: 299.21011 | N52: 206.14431 | O52: 215.01255 | P52: 327.79323
B53: Корма для собак | C53: Бренд 6 | E53: 395.8917 | F53: 239.9827 | G53: 288.53102 | H53: 298.62849 | I53: 352.08009 | J53: 351.62223 | K53: 272.89471 | L53: 378.9626 | M53: 426.08684 | N53: 421.66472 | O53: 226.56347 | P53: 487.45196
B54: Корма для собак | C54: Бренд 7 | E54: 269.05057 | F54: 365.68314 | G54: 200.70273 | H54: 209.03814 | I54: 452.31232 | J54: 358.46219 | K54: 284.28293 | L54: 306.73627 | M54: 318.55443 | N54: 288.12798 | O54: 356.63274 | P54: 369.117
B55: Корма для собак | C55: Бренд 8 | E55: 320.49114 | F55: 301.97892 | G55: 407.08145 | H55: 366.78262 | I55: 293.3614 | J55: 244.10969 | K55: 350.61909 | L55: 221.23522 | M55: 357.97849 | N55: 489.70844 | O55: 334.61575 | P55: 274.43206
B56: Корма для собак | C56: Бренд 9 | E56: 226.25423 | F56: 215.94583 | G56: 302.7458 | H56: 243.34443 | I56: 365.93589 | J56: 383.19723 | K56: 242.08481 | L56: 236.55786 | M56: 441.54841 | N56: 216.15588 | O56: 321.58138 | P56: 232.51348
B57: Корма для собак | C57: Бренд 10 | E57: 228.11431 | F57: 428.16572 | G57: 344.67048 | H57: 341.72287 | I57: 294.21199 | J57: 485.3446 | K57: 283.61782 | L57: 301.82686 | M57: 391.4342 | N57: 361.1337 | O57: 335.88666 | P57: 222.38228
B60: Корма для кошек | C60: Онлайн продажи
B61: Корма для кошек | C61: Эконом сегмент
B62: Корма для кошек | C62: Бренд 1 | E62: 150.2131 | F62: 142.39839 | G62: 124.03358 | H62: 193.13694 | I62: 97.291673 | J62: 114.10481 | K62: 106.79539 | L62: 171.90437 | M62: 150.95919 | N62: 144.27242 | O62: 123.58581 | P62: 212.77992
B63: Корма для кошек | C63: Бренд 2 | E63: 178.50312 | F63: 184.10092 | G63: 123.13844 | H63: 114.64394 | I63: 143.8314 | J63: 121.04616 | K63: 223.42237 | L63: 182.35007 | M63: 65.543456 | N63: 89.226699 | O63: 95.491837 | P63: 208.13984
B64: Корма для кошек | C64: Бренд 3 | E64: 105.87492 | F64: 172.36849 | G64: 129.08565 | H64: 62.22601 | I64: 105.37245 | J64: 116.427 | K64: 218.80545 | L64: 81.077728 | M64: 79.989332 | N64: 128.42898 | O64: 77.998849 | P64: 134.98592
B65: Корма для кошек | C65: Бренд 4 | E65: 110.69412 | F65: 221.59831 | G65: 147.76897 | H65: 86.909767 | I65: 97.057325 | J65: 116.15594 | K65: 127.42247 | L65: 125.78752 | M65: 119.84296 | N65: 220.24231 | O65: 76.193526 | P65: 187.90421
B66: Корма для кошек | C66: Бренд 5 | E66: 168.77899 | F66: 214.87407 | G66: 193.31655 | H66: 238.93475 | I66: 120.54229 | J66: 102.09018 | K66: 192.13274 | L66: 95.372524 | M66: 193.34384 | N66: 184.39293 | O66: 174.7244 | P66: 173.22906
B67: Корма для кошек | C67: Бренд 6 | E67: 93.303217 | F67: 237.56051 | G67: 217.36158 | H67: 89.861923 | I67: 116.01022 | J67: 192.99799 | K67: 119.00319 | L67: 230.33073 | M67: 180.83344 | N67: 153.31493 | O67: 144.33696 | P67: 90.715541
B68: Корма для кошек | C68: Бренд 7 | E68: 212.2301 | F68: 133.4377 | G68: 207.87728 | H68: 120.11599 | I68: 123.95178 | J68: 154.39877 | K68: 143.35297 | L68: 96.232324 | M68: 103.90537 | N68: 137.32516 | O68: 117.65224 | P68: 226.27043
B69: Корма для кошек | C69: Бренд 8 | E69: 119.26222 | F69: 160.37688 | G69: 93.1533 | H69: 243.55853 | I69: 138.10401 | J69: 221.10712 | K69: 187.36282 | L69: 111.93683 | M69: 101.15432 | N69: 153.89179 | O69: 105.91812 | P69: 148.72486
B70: Корма для кошек | C70: Бренд 9 | E70: 152.40033 | F70: 110.65084 | G70: 197.78494 | H70: 145.85 | I70: 125.93986 | J70: 107.58553 | K70: 130.38806 | L70: 162.26043 | M70: 70.979533 | N70: 101.84555 | O70: 176.0328 | P70: 137.76471
B71: Корма для кошек | C71: Бренд 10 | E71: 146.99012 | F71: 138.95614 | G71: 173.05095 | H71: 127.976 | I71: 214.79406 | J71: 128.05618 | K71: 166.60938 | L71: 186.57919 | M71: 127.55377 | N71: 130.12007 | O71: 166.04245 | P71: 151.8642
B72: Корма для кошек | C72: Премиум сегмент
B73: Корма для кошек | C73: Бренд 1 | E73: 233.56774 | F73: 233.02816 | G73: 318.8905 | H73: 228.89152 | I73: 467.72542 | J73: 282.16508 | K73: 198.32727 | L73: 377.57498 | M73: 282.55723 | N73: 261.0778 | O73: 287.72608 | P73: 447.44594
B74: Корма для кошек | C74: Бренд 2 | E74: 296.36925 | F74: 377.55251 | G74: 244.10314 | H74: 310.69708 | I74: 329.79185 | J74: 201.88736 | K74: 318.68911 | L74: 339.41427 | M74: 332.79875 | N74: 355.91492 | O74: 422.25702 | P74: 475.42833
B75: Корма для кошек | C75: Бренд 3 | E75: 239.72613 | F75: 447.92037 | G75: 362.11678 | H75: 209.84311 | I75: 427.84628 | J75: 277.25683 | K75: 234.01927 | L75: 190.44598 | M75: 270.02615 | N75: 295.75758 | O75: 236.33041 | P75: 399.37498
B76: Корма для кошек | C76: Бренд 4 | E76: 363.37983 | F76: 298.13876 | G76: 393.51699 | H76: 353.22828 | I76: 401.38428 | J76: 283.89381 | K76: 450.70469 | L76: 373.12647 | M76: 283.23434 | N76: 437.34088 | O76: 267.02521 | P76: 292.68768
B77: Корма для кошек | C77: Бренд 5 | E77: 398.48512 | F77: 330.10614 | G77: 403.2284 | H77: 226.06771 | I77: 299.51678 | J77: 320.25186 | K77: 228.06341 | L77: 339.24701 | M77: 344.46891 | N77: 245.19764 | O77: 226.75871 | P77: 302.74258
B78: Корма для кошек | C78: Бренд 6 | E78: 386.40845 | F78: 428.49516 | G78: 218.51252 | H78: 459.17097 | I78: 353.11538 | J78: 376.59493 | K78: 227.46513 | L78: 360.63526 | M78: 232.71681 | N78: 405.28073 | O78: 261.0037 | P78: 241.2229
B79: Корма для кошек | C79: Бренд 7 | E79: 307.12839 | F79: 240.50291 | G79: 352.04285 | H79: 342.41512 | I79: 239.25749 | J79: 301.11987 | K79: 462.53673 | L79: 381.47588 | M79: 236.76132 | N79: 283.0559 | O79: 293.54347 | P79: 262.76982
B80: Корма для кошек | C80: Бренд 8 | E80: 354.95998 | F80: 217.29419 | G80: 381.13046 | H80: 316.71054 | I80: 254.82708 | J80: 297.14406 | K80: 380.46175 | L80: 196.03371 | M80: 267.10345 | N80: 221.23568 | O80: 441.4633 | P80: 372.20093
B81: Корма для кошек | C81: Бренд 9 | E81: 418.57232 | F81: 374.91737 | G81: 273.58844 | H81: 418.59243 | I81: 356.58039 | J81: 369.76824 | K81: 423.97881 | L81: 252.56417 | M81: 297.34568 | N81: 380.12891 | O81: 361.91962 | P81: 241.77408
B82: Корма для кошек | C82: Бренд 10 | E82: 402.67544 | F82: 252.18002 | G82: 340.26701 | H82: 391.68027 | I82: 283.85121 | J82: 209.28679 | K82: 357.13092 | L82: 234.05741 | M82: 460.78936 | N82: 215.50131 | O82: 303.61711 | P82: 209.71867
B83: Корма для кошек | C83: Офлайн продажи
B84: Корма для кошек | C84: Эконом сегмент
B85: Корма для кошек | C85: Бренд 1 | E85: 110.2456 | F85: 70.55039 | G85: 150.50218 | H85: 82.979837 | I85: 161.17108 | J85: 114.14722 | K85: 158.24345 | L85: 114.73949 | M85: 167.60932 | N85: 76.324413 | O85: 86.379015 | P85: 98.133638
B86: Корма для кошек | C86: Бренд 2 | E86: 158.65786 | F86: 171.92932 | G86: 97.097332 | H86: 186.52262 | I86: 102.48253 | J86: 184.86747 | K86: 161.91033 | L86: 135.42422 | M86: 139.20844 | N86: 118.29539 | O86: 109.53054 | P86: 102.2431
B87: Корма для кошек | C87: Бренд 3 | E87: 104.6819 | F87: 229.64115 | G87: 187.65316 | H87: 91.298176 | I87: 142.09729 | J87: 160.46802 | K87: 80.682821 | L87: 97.321478 | M87: 127.74967 | N87: 200.60348 | O87: 242.04741 | P87: 68.9274
B88: Корма для кошек | C88: Бренд 4 | E88: 116.00663 | F88: 113.92381 | G88: 161.40122 | H88: 96.395369 | I88: 180.24024 | J88: 133.24884 | K88: 167.96427 | L88: 103.71705 | M88: 125.75922 | N88: 84.852418 | O88: 169.83605 | P88: 94.363033
B89: Корма для кошек | C89: Бренд 5 | E89: 162.1832 | F89: 128.70051 | G89: 136.43001 | H89: 108.00872 | I89: 106.15456 | J89: 139.08064 | K89: 105.65939 | L89: 83.507915 | M89: 189.96869 | N89: 105.6641 | O89: 147.21962 | P89: 77.110916
B90: Корма для кошек | C90: Бренд 6 | E90: 116.08909 | F90: 100.18825 | G90: 152.12633 | H90: 238.15224 | I90: 176.75191 | J90: 197.87277 | K90: 238.50448 | L90: 176.55741 | M90: 168.60722 | N90: 188.03649 | O90: 98.57541 | P90: 214.88653
B91: Корма для кошек | C91: Бренд 7 | E91: 132.10407 | F91: 84.745984 | G91: 112.24188 | H91: 141.6802 | I91: 222.11774 | J91: 59.412662 | K91: 211.32667 | L91: 146.19827 | M91: 187.17731 | N91: 127.52924 | O91: 155.38414 | P91: 116.1191
B92: Корма для кошек | C92: Бренд 8 | E92: 153.43816 | F92: 131.11162 | G92: 173.67684 | H92: 120.28917 | I92: 89.623255 | J92: 199.43278 | K92: 125.0655 | L92: 96.27219 | M92: 99.34116 | N92: 154.48914 | O92: 145.65672 | P92: 161.66697
B93: Корма для кошек | C93: Бренд 9 | E93: 150.55238 | F93: 63.855056 | G93: 170.97994 | H93: 169.51667 | I93: 132.36533 | J93: 165.11362 | K93: 132.02131 | L93: 121.98234 | M93: 131.41469 | N93: 138.63649 | O93: 73.443919 | P93: 192.43554
B94: Корма для кошек | C94: Бренд 10 | E94: 114.56802 | F94: 110.45918 | G94: 86.027002 | H94: 149.17018 | I94: 130.96317 | J94: 216.31173 | K94: 92.929322 | L94: 144.96256 | M94: 184.7809 | N94: 115.99826 | O94: 143.31836 | P94: 141.16355
B95: Корма для кошек | C95: Премиум сегмент
B96: Корма для кошек | C96: Бренд 1 | E96: 223.48755 | F96: 367.00628 | G96: 245.16557 | H96: 272.39349 | I96: 299.43412 | J96: 231.60818 | K96: 316.23311 | L96: 323.68094 | M96: 391.79317 | N96: 397.1527 | O96: 269.47387 | P96: 369.0932
B97: Корма для кошек | C97: Бренд 2 | E97: 220.75437 | F97: 332.01055 | G97: 373.36563 | H97: 310.09546 | I97: 373.72938 | J97: 398.19293 | K97: 216.75885 | L97: 333.16942 | M97: 233.89641 | N97: 334.00047 | O97: 287.35138 | P97: 336.90525
B98: Корма для кошек | C98: Бренд 3 | E98: 362.40549 | F98: 340.38038 | G98: 245.21438 | H98: 368.4408 | I98: 302.03386 | J98: 287.67291 | K98: 337.37102 | L98: 392.74683 | M98: 331.53892 | N98: 441.56185 | O98: 363.55773 | P98: 232.44322
B99: Корма для кошек | C99: Бренд 4 | E99: 274.20531 | F99: 283.82757 | G99: 362.5603 | H99: 301.98073 | I99: 242.57204 | J99: 350.797 | K99: 491.13901 | L99: 390.94674 | M99: 417.22451 | N99: 239.30874 | O99: 454.89163 | P99: 425.28714
B100: Корма для кошек | C100: Бренд 5 | E100: 383.94012 | F100: 260.5637 | G100: 216.95156 | H100: 247.75108 | I100: 317.80235 | J100: 444.82587 | K100: 262.80319 | L100: 277.58664 | M100: 194.59552 | N100: 360.63035 | O100: 400.58221 | P100: 382.21264
B101: Корма для кошек | C101: Бренд 6 | E101: 277.4105 | F101: 407.82914 | G101: 363.92807 | H101: 308.98676 | I101: 311.47953 | J101: 416.62934 | K101: 290.6511 | L101: 417.20636 | M101: 256.04643 | N101: 269.896 | O101: 358.21965 | P101: 350.03255
B102: Корма для кошек | C102: Бренд 7 | E102: 280.27467 | F102: 361.15898 | G102: 272.06657 | H102: 198.17073 | I102: 373.28577 | J102: 354.6783 | K102: 246.17603 | L102: 323.34203 | M102: 451.34743 | N102: 323.05932 | O102: 478.35766 | P102: 323.41818
B103: Корма для кошек | C103: Бренд 8 | E103: 252.69377 | F103: 396.64312 | G103: 339.72049 | H103: 323.37559 | I103: 428.48486 | J103: 251.89099 | K103: 235.60291 | L103: 223.3872 | M103: 466.18382 | N103: 335.53485 | O103: 465.81391 | P103: 394.77243
B104: Корма для кошек | C104: Бренд 9 | E104: 318.35084 | F104: 408.78007 | G104: 231.85059 | H104: 218.49288 | I104: 227.12061 | J104: 235.25718 | K104: 212.44166 | L104: 394.27431 | M104: 399.01795 | N104: 467.22358 | O104: 295.86521 | P104: 426.05945
B105: Корма для кошек | C105: Бренд 10 | E105: 263.19074 | F105: 252.09292 | G105: 235.5496 | H105: 283.00354 | I105: 388.80971 | J105: 217.68589 | K105: 206.97947 | L105: 253.02027 | M105: 238.38768 | N105: 256.54603 | O105: 441.50404 | P105: 375.41862
