Workbook

Sheet Содержание
B3: Тренинг «Навыки работы в Excel»
B6: Содержание
B7: Блок 1
B8: ='Настройки Excel'!$A$1 -> Настройки Excel
B9: =HotKeys!$A$1 -> HotKeys
B10: ='Плохие примеры'!$A$1 -> Плохие примеры оформления
B11: ='Форматы ячеек'!A1 -> Форматы ячеек
B12: ='Структура и оформление'!$A$1 -> Структура и оформление
B14: Блок 2
B15: ='Текст по столбцам'!$A$1 -> Текст по столбцам
B16: ='Анализ деклараций'!$A$1 -> Анализ таможенных деклараций
B17: ='Анализ чувствительности'!$A$1 -> Анализ чувствительности
B18: ='Консолидация данных'!$A$1 -> Консолидация данных
B20: Блок 3
B21: =Архитектура!A1 -> Архитектура
B22: =Дубликаты!A1 -> Дубликаты и ссылки на другие листы

Sheet Блок 1->

Sheet Настройки Excel
A1: Настройки Excel
B3: Настройка параметров Excel
C5: Убрать галочку в "разрешить редактировать в ячейках"
C7: Позволяет переходить на влияющую ячейку, если два раза на ячейку левой кнопкой мыши
C8: Если форула ссылается на несколько ячеек - то при нажатии пеходит на первую ссылку
Y10: Нажать 2 раза
C27: Пример | D27: =Y10 -> Нажать 2 раза
B30: Настройка ленты
C32: Вывести на панель быстрого доступа: влияющие ячейки, зависимые ячейки и убрать стрелки
C44: Влияющие ячейки: показывает, какие ячейки участвуют в расчете этой ячейки
C46: Пример | D46: =F46*G46-H46 -> 59 | F46: 12 | G46: 5 | H46: 1
C48: Зависимые ячейки: показывает, где используется данная ячейка
C50: Пример | D50: 14 | F50: =D50*2-1 -> 27 | G50: =F50*7-D46 -> 130 | H50: =D50-7 -> 7
C52: Убрать стрелки: убирает синие стрелки
C54: Показывать зависимые/влияющие ячейки можно через Alt+"цифра"
C65: Если влияющие ячейки на одном листе - можно нажать F2 - и ячейки будут подсвечиваться
J67: Пример
J68: =F46*G46-H46 -> 59
C74: Если влияющие/зависимые ячейки на разных листа - нужно нажать два раза ЛКМ на синию пунктирную линию
J79: Пример
J80: =Содержание!B9 -> HotKeys

Sheet HotKeys
A1: HotKeys
B2: HotKeys | C2: Описание
B3: Навигация
B4: Перемещение
B6: Стрелка | C6: перемещение на одной ячейку | E6: Продукт | F6: 2018 | G6: =F6+1 -> 2019 | H6: =G6+1 -> 2020 | I6: =H6+1 -> 2021 | J6: =I6+1 -> 2022 | K6: =J6+1 -> 2023 | L6: =K6+1 -> 2024 | O6: 2030
B7: Ctrl+Стрелка | C7: перемещение до конца непустых ячеек или до первой непустой ячейки | E7: Пр.1 | F7: 1 | G7: =F7*2 -> 2 | H7: =G7*2 -> 4 | I7: =H7*2 -> 8 | J7: =I7*2 -> 16 | K7: =J7*2 -> 32 | L7: =K7*2 -> 64 | O7: =L7*2 -> 128
B8: Ctrl+Home | C8: переход в ячейку A1 | E8: Пр.5 | F8: =F7+2 -> 3 | G8: =G7+2 -> 4 | H8: =H7+2 -> 6 | I8: =I7+2 -> 10 | J8: =J7+2 -> 18 | K8: =K7+2 -> 34 | L8: =L7+2 -> 66 | O8: =L8+2 -> 68
B9: Ctrl+Page Up (Page Down) | C9: переход на следующий лист (предыдущий) | E9: Пр.3 | F9: =F8+2 -> 5 | G9: =G8+2 -> 6 | H9: =H8+2 -> 8 | I9: =I8+2 -> 12 | J9: =J8+2 -> 20 | K9: =K8+2 -> 36 | L9: =L8+2 -> 68 | O9: =L9+2 -> 70
B10: F5 | C10: переход на прошлую редактируемую ячейку | E10: Пр.2 | F10: =F9*F7 -> 5 | G10: =G9*G7 -> 12 | H10: =H9*H7 -> 32 | I10: =I9*I7 -> 96 | J10: =J9*J7 -> 320 | K10: =K9*K7 -> 1152 | L10: =L9*L7 -> 4352 | O10: =L10+2 -> 4354
B11: Ctrl+[ | C11: проваливание во влияющую ячейку (работает, только если книга запущена при английской раскладке) | O11: =L11+2 -> 2
B12: Ctrl+] | C12: проваливание в зависимую ячейку (работает, только если книга запущена при английской раскладке)
B13: Enter | C13: на 1 ячейку вниз. Shift+Enter - вверх
B14: Tab | C14: на 1 ячейку вправо. Shift+Tab - вниз
B16: Выделение
B18: Shift+Стрелка | C18: выделение одной ячейки за каждое нажатие
B19: Ctrl+Shift+Стрелка | C19: выделение диапазона ячеек – до конца
B20: Shift+Пробел | C20: выделение строки
B21: Ctrl+Пробел | C21: выделение столбца
B22: Ctrl+Shift+Пробел (или Ctrl+A) | C22: выделение всей таблицы (если несколько раз нажать)
B24: Растягивание формул и копирование ячеек
B25: Растягивание формул
B27: Ctrl+R | C27: растягивание формулы по вправо
B28: Ctrl+D | C28: растягивание формулы по вниз
B30: Копирование ячеек
B32: Ctrl+С | C32: копировать
B33: Ctrl+X | C33: вырезать (аккуратно с этим действие)
B34: Ctrl+V | C34: вставить (вставляются формулы и форматирование)
B35: Ctrl+Alt+V | C35: специальная вставка
B36: Ctrl+«+» | C36: вставить ячейку со смещением (если выделен столбец/строка + добавляется целиком)
B37: Ctrl+«-» | C37: удалить ячейку (если выделен столбец/строка + добавляется целиком)
B39: Прочие
B41: F2 | C41: перейти в редактирование формулы. Показывает влияющие ячейки
B42: Tab (в момент редактирования формулы) | C42: дозаполняет формулу: пример если после ввода "=су" - нажать Tab - выберется формула СУММ. Выбор нужной формулу - через стрелки
B43: Alt+F1 | C43: быстрое построение столбчатое диаграммы
B44: Ctrl+Shift+L | C44: поставить/снять фильтр (важно выделять всю таблицу)
B45: Alt+стрелка вниз (на заголовке фильтра) | C45: параметры фильтрации
B46: Alt+Shift+Вправо (Влево) | C46: oгруппировать (разгруппировать) строки/столбцы (нужно выделить строку/столбец целиком)
B47: F4 | C47: повторение прошлого действия
B48: F4 (в редактировании формулы) | C48: фиксирование ячейки
B49: Alt,… | C49: огромное количество действий
B50: Ctrl+Shift+1 | C50: быстрое разделение разрядов чисел
B51: Alt, Z, 9 | C51: убрать 1 знак после запятой
B52: Alt, Z, 0, 1 | C52: добавить 1 знак после запятой
B54: Список Hot Keys
B56: https://support.microsoft.com/ru-ru/office/%D1%81%D0%BE%D1%87%D0%B5%D1%82%D0%B0%D0%BD%D0%B8%D1%8F-%D0%BA%D0%BB%D0%B0%D0%B2%D0%B8%D1%88-%D0%B2-excel-1798d9d5-842a-42b8-9c99-9b7213f0040f

Sheet Плохие примеры
A1: Плохие примеры оформления
B3: Основное
B5: → | C5: Отсутствие структуры
B7: → | C7: Харды вместо ссылок
B9: → | C9: Отсутствие источников
B11: Общий формат чисел
D13: Bad | E13: Good
C14: Выручка | D14: 158910.11 | E14: =D14 -> 158910.11
C15: Себестоимость | D15: -174801.49 | E15: =D15 -> -174801.49
C16: EBITDA | D16: =SUM(D14:D15) -> -15891.378 | E16: =SUM(E14:E15) -> -15891.378
C17: EBITDA margin | D17: =D16/D14 -> -0.10000231 | E17: =E16/E14 -> -0.10000231
B19: Объединение ячеек в таблицах
C21: Bad
C22: Показатель | D22: 2021 | E22: 2022
C23: Выручка | D23: 200 | E23: 250
C24: Себестоимость | D24: -200
C25: EBITDA | D25: =SUM(D23:D24) -> 0 | E25: =SUM(E23:E24) -> 250
B27: Разная ширина/высота (в тч на разных листах)
C29: Выручка | D29: 158910 | E29: Bad
C30: Себестоимость | D30: =-D29*1.1 -> -174801 | E30: Bad
C31: EBITDA | D31: =D29+D30 -> -15891
B33: Весь лист одним форматом
C35: Bad | F35: Good
C37: Компания 1 | F37: Компания 1
C38: Выручка | D38: =SUM(D39:D42) -> 750 | F38: Выручка | G38: =SUM(G39:G42) -> 750
C39: Продукт 1 | D39: 50 | F39: Продукт 1 | G39: 50
C40: Продукт 2 | D40: =D39*2 -> 100 | F40: Продукт 2 | G40: =G39*2 -> 100
C41: Продукт 3 | D41: =D40*2 -> 200 | F41: Продукт 3 | G41: =G40*2 -> 200
C42: Продукт 4 | D42: =D41*2 -> 400 | F42: Продукт 4 | G42: =G41*2 -> 400
C43: Себестоимость | D43: -200 | F43: Себестоимость | G43: -200
C44: EBITDA | D44: =D38+D43 -> 550 | F44: EBITDA | G44: =G38+G43 -> 550
C46: Компания 2 | F46: Компания 2
C47: Выручка | D47: =SUM(D48:D51) -> 750 | F47: Выручка | G47: =SUM(G48:G51) -> 750
C48: Продукт 1 | D48: 50 | F48: Продукт 1 | G48: 50
C49: Продукт 2 | D49: =D48*2 -> 100 | F49: Продукт 2 | G49: =G48*2 -> 100
C50: Продукт 3 | D50: =D49*2 -> 200 | F50: Продукт 3 | G50: =G49*2 -> 200
C51: Продукт 4 | D51: =D50*2 -> 400 | F51: Продукт 4 | G51: =G50*2 -> 400
C52: Себестоимость | D52: -200 | F52: Себестоимость | G52: -200
C53: EBITDA | D53: =D47+D52 -> 550 | F53: EBITDA | G53: =G47+G52 -> 550
C55: Всего выручка | D55: =D38+D47 -> 1500 | F55: Всего выручка | G55: =G38+G47 -> 1500
B58: Разное форматирование схожих данных
C60: Bad | F60: Good
C62: Компания 1 | F62: Компания 1
C63: Выручка | D63: =SUM(D64:D67) -> 750 | F63: Выручка | G63: =SUM(G64:G67) -> 750
C64: Продукт 1 | D64: 50 | F64: Продукт 1 | G64: 50
C65: Продукт 2 | D65: =D64*2 -> 100 | F65: Продукт 2 | G65: =G64*2 -> 100
C66: Продукт 3 | D66: =D65*2 -> 200 | F66: Продукт 3 | G66: =G65*2 -> 200
C67: Продукт 4 | D67: =D66*2 -> 400 | F67: Продукт 4 | G67: =G66*2 -> 400
C68: Себестоимость | D68: -200 | F68: Себестоимость | G68: -200
C69: EBITDA | D69: =D63+D68 -> 550 | F69: EBITDA | G69: =G63+G68 -> 550
C71: Компания 2 | F71: Компания 2
C72: Выручка | D72: =SUM(D73:D76) -> 750 | F72: Выручка | G72: =SUM(G73:G76) -> 750
C73: Продукт 1 | D73: 50 | F73: Продукт 1 | G73: 50
C74: Продукт 2 | D74: =D73*2 -> 100 | F74: Продукт 2 | G74: =G73*2 -> 100
C75: Продукт 3 | D75: =D74*2 -> 200 | F75: Продукт 3 | G75: =G74*2 -> 200
C76: Продукт 4 | D76: =D75*2 -> 400 | F76: Продукт 4 | G76: =G75*2 -> 400
C77: Себестоимость | D77: -200 | F77: Себестоимость | G77: -200
C78: EBITDA | D78: =D72+D77 -> 550 | F78: EBITDA | G78: =G72+G77 -> 550
C80: Всего выручка | D80: =D63+D72 -> 1500 | F80: Всего выручка | G80: =G63+G72 -> 1500
B82: Излишняя пестрость, выделение цветом всей строки
C84: Bad
C85: Компания 2
C86: Выручка | D86: =SUM(D87:D90) -> 750
C87: Продукт 1 | D87: 50
C88: Продукт 2 | D88: =D87*2 -> 100
C89: Продукт 3 | D89: =D88*2 -> 200
C90: Продукт 4 | D90: =D89*2 -> 400
C91: Себестоимость | D91: -200
C92: EBITDA | D92: =D86+D91 -> 550
C94: Bad | D94: !!! Может очень сильно утяжелить файл. Плюс бегунок перестает нормально работать
C95: Выручка | D95: 614
B97: Скрытые строки вместо группировки
C99: Bad
C100: Выручка | D100: =SUM(D101:D104) -> 750
C101: Продукт 1 | D101: 50
C102: Продукт 2 | D102: =D101*2 -> 100
C103: Продукт 3 | D103: =D102*2 -> 200
C104: Продукт 4 | D104: =D103*2 -> 400
C105: Себестоимость | D105: -750
C106: EBITDA | D106: =SUM(D100:D105) -> 750
C108: Good
C109: Выручка | D109: =SUM(D110:D113) -> 750
C110: Продукт 1 | D110: 50
C111: Продукт 2 | D111: =D110*2 -> 100
C112: Продукт 3 | D112: =D111*2 -> 200
C113: Продукт 4 | D113: =D112*2 -> 400
C114: Себестоимость | D114: -750
C115: EBITDA | D115: =D109+D114 -> 0
B117: Непонятные названия листов
C119: Лист 1 | D119: Bad
C120: ываыва | D120: Bad
C121: Выручка_2 (2)_new | D121: Bad
B123: Изменяющиеся формулы в строке/столбце без выделения
C125: 1 | D125: 2 | E125: 3 | F125: 4
B126: Bad | C126: =C$125^2 -> 1 | D126: =D$125^2 -> 4 | E126: =E$125^3 -> 27 | F126: =F$125^3 -> 64
B128: Good | C128: =C$125^2 -> 1 | D128: =D$125^2 -> 4 | E128: =E$125^3 -> 27 | F128: =F$125^2 -> 16
B130: Прочее
C132: Незакрепление верхних столбцов/левых строк
C134: Разное расположение строк/столбцов у одинаковых по структуре листов

Sheet Структура и оформление
A1: Структура и оформление | J1: 2018 | K1: =J1+1 -> 2019 | L1: =K1+1 -> 2020 | M1: =L1+1 -> 2021 | N1: =M1+1 -> 2022 | O1: =N1+1 -> 2023 | P1: =O1+1 -> 2024 | Q1: =P1+1 -> 2025 | R1: =Q1+1 -> 2026 | ... V1: =U1+1 -> 2030
B2: Показатель | F2: ед. изм. | G2: Константа | H2: Источник
B4: Структурирование данных на листе и в книге
B6: Структурирование данных
C7: Данные на листе надо структурировать по блокам (выручка, расходы и тд)
C8: Большие блоки информации лучше группировать
C9: И крайне нежелательно скрывать столбцы/строки
C10: Закрепление строк и столбцов
B12: Листы в книге
C13: Название листа – соответствует тому, что там есть
C14: Крайне желательно, чтобы на разных листах находились одинаковые периоды по столбцам
C15: Листы должны содержать схожую информацию - если много листов в книге
B17: Выделение ячеек
C19: Стиль выделения должен быть единым во всей книге
C20: Желательно приводить легенду
C22: Что выделяется:
D23: Харды | G23: 100
D24: Ссылки на другие листы | G24: 100
D25: Изменение формулы в строке | G25: 100
D26: Переключатели | G26: 100 | J26: 561161
D27: Предварительные итоги | G27: 100
D28: Итоги | G28: 100
C30: Как выделяется:
D31: Заливка
D32: Границы
D33: Жирный/курсив
B35: HotKeys
E37: Ctrl+Shift+→ | F37: Группировать
E38: Ctrl+Shift+← | F38: Разгруппировать
B40: Пример
B42: Выручка
C43: Производство
D44: Мощности производства
E45: Линия 1 | F45: т/год | G45: 20 | H45: Клиент
E46: Линия 2 | F46: т/год | G46: 30 | H46: Клиент
D48: Загрузка производства
E49: Линия 1 | F49: % | H49: Клиент | J49: 0 | K49: 0 | L49: 0.1 | M49: 0.3 | N49: 0.7 | O49: 1 | P49: 1 | Q49: 1 | R49: 1 | S49: 1 | T49: 1 | U49: 1 | V49: 1
E50: Линия 2 | F50: % | H50: Клиент | J50: 0 | K50: 0 | L50: 0 | M50: 0.5 | N50: 0.7 | O50: 1 | P50: 1 | Q50: 1 | R50: 1 | S50: 1 | T50: 1 | U50: 1 | V50: 1
D52: Структура производства
D53: Линия 1
E54: Продукт 1 | F54: т | G54: 0.08 | H54: КП от… | J54: =$G$45*J$49*$G54 -> 0 | K54: =$G$45*K$49*$G54 -> 0 | L54: =$G$45*L$49*$G54 -> 0.16 | M54: =$G$45*M$49*$G54 -> 0.48 | N54: =$G$45*N$49*$G54 -> 1.12 | O54: =$G$45*O$49*$G54 -> 1.6 | P54: =$G$45*P$49*$G54 -> 1.6 | Q54: =$G$45*Q$49*$G54 -> 1.6 | ... V54: =$G$45*V$49*$G54 -> 1.6
E55: Продукт 2 | F55: т | G55: 0.15 | H55: КП от… | J55: =$G$45*J$49*$G55 -> 0 | K55: =$G$45*K$49*$G55 -> 0 | L55: =$G$45*L$49*$G55 -> 0.3 | M55: =$G$45*M$49*$G55 -> 0.9 | N55: =$G$45*N$49*$G55 -> 2.1 | O55: =$G$45*O$49*$G55 -> 3 | P55: =$G$45*P$49*$G55 -> 3 | Q55: =$G$45*Q$49*$G55 -> 3 | ... V55: =$G$45*V$49*$G55 -> 3
E56: Продукт 3 | F56: т | G56: 0.19 | H56: КП от… | J56: =$G$45*J$49*$G56 -> 0 | K56: =$G$45*K$49*$G56 -> 0 | L56: =$G$45*L$49*$G56 -> 0.38 | M56: =$G$45*M$49*$G56 -> 1.14 | N56: =$G$45*N$49*$G56 -> 2.66 | O56: =$G$45*O$49*$G56 -> 3.8 | P56: =$G$45*P$49*$G56 -> 3.8 | Q56: =$G$45*Q$49*$G56 -> 3.8 | ... V56: =$G$45*V$49*$G56 -> 3.8
E57: Продукт 4 | F57: т | G57: 0.29 | H57: КП от… | J57: =$G$45*J$49*$G57 -> 0 | K57: =$G$45*K$49*$G57 -> 0 | L57: =$G$45*L$49*$G57 -> 0.58 | M57: =$G$45*M$49*$G57 -> 1.74 | N57: =$G$45*N$49*$G57 -> 4.06 | O57: =$G$45*O$49*$G57 -> 5.8 | P57: =$G$45*P$49*$G57 -> 5.8 | Q57: =$G$45*Q$49*$G57 -> 5.8 | ... V57: =$G$45*V$49*$G57 -> 5.8
E58: Продукт 5 | F58: т | G58: 0.29 | H58: КП от… | J58: =$G$45*J$49*$G58 -> 0 | K58: =$G$45*K$49*$G58 -> 0 | L58: =$G$45*L$49*$G58 -> 0.58 | M58: =$G$45*M$49*$G58 -> 1.74 | N58: =$G$45*N$49*$G58 -> 4.06 | O58: =$G$45*O$49*$G58 -> 5.8 | P58: =$G$45*P$49*$G58 -> 5.8 | Q58: =$G$45*Q$49*$G58 -> 5.8 | ... V58: =$G$45*V$49*$G58 -> 5.8
E59: Всего | F59: т | J59: =SUM(J54:J58) -> 0 | K59: =SUM(K54:K58) -> 0 | L59: =SUM(L54:L58) -> 2 | M59: =SUM(M54:M58) -> 6 | N59: =SUM(N54:N58) -> 14 | O59: =SUM(O54:O58) -> 20 | P59: =SUM(P54:P58) -> 20 | Q59: =SUM(Q54:Q58) -> 20 | ... V59: =SUM(V54:V58) -> 20
D61: Линия 2
E62: Продукт 1 | F62: % | G62: 0.088 | H62: КП от… | J62: =$G$46*J$50*$G62 -> 0 | K62: =$G$46*K$50*$G62 -> 0 | L62: =$G$46*L$50*$G62 -> 0 | M62: =$G$46*M$50*$G62 -> 1.32 | N62: =$G$46*N$50*$G62 -> 1.848 | O62: =$G$46*O$50*$G62 -> 2.64 | P62: =$G$46*P$50*$G62 -> 2.64 | Q62: =$G$46*Q$50*$G62 -> 2.64 | ... V62: =$G$46*V$50*$G62 -> 2.64
E63: Продукт 2 | F63: % | G63: 0.165 | H63: КП от… | J63: =$G$46*J$50*$G63 -> 0 | K63: =$G$46*K$50*$G63 -> 0 | L63: =$G$46*L$50*$G63 -> 0 | M63: =$G$46*M$50*$G63 -> 2.475 | N63: =$G$46*N$50*$G63 -> 3.465 | O63: =$G$46*O$50*$G63 -> 4.95 | P63: =$G$46*P$50*$G63 -> 4.95 | Q63: =$G$46*Q$50*$G63 -> 4.95 | ... V63: =$G$46*V$50*$G63 -> 4.95
E64: Продукт 3 | F64: % | G64: 0.209 | H64: КП от… | J64: =$G$46*J$50*$G64 -> 0 | K64: =$G$46*K$50*$G64 -> 0 | L64: =$G$46*L$50*$G64 -> 0 | M64: =$G$46*M$50*$G64 -> 3.135 | N64: =$G$46*N$50*$G64 -> 4.389 | O64: =$G$46*O$50*$G64 -> 6.27 | P64: =$G$46*P$50*$G64 -> 6.27 | Q64: =$G$46*Q$50*$G64 -> 6.27 | ... V64: =$G$46*V$50*$G64 -> 6.27
E65: Продукт 4 | F65: % | G65: 0.319 | H65: КП от… | J65: =$G$46*J$50*$G65 -> 0 | K65: =$G$46*K$50*$G65 -> 0 | L65: =$G$46*L$50*$G65 -> 0 | M65: =$G$46*M$50*$G65 -> 4.785 | N65: =$G$46*N$50*$G65 -> 6.699 | O65: =$G$46*O$50*$G65 -> 9.57 | P65: =$G$46*P$50*$G65 -> 9.57 | Q65: =$G$46*Q$50*$G65 -> 9.57 | ... V65: =$G$46*V$50*$G65 -> 9.57
E66: Продукт 5 | F66: % | G66: 0.219 | H66: КП от… | J66: =$G$46*J$50*$G66 -> 0 | K66: =$G$46*K$50*$G66 -> 0 | L66: =$G$46*L$50*$G66 -> 0 | M66: =$G$46*M$50*$G66 -> 3.285 | N66: =$G$46*N$50*$G66 -> 4.599 | O66: =$G$46*O$50*$G66 -> 6.57 | P66: =$G$46*P$50*$G66 -> 6.57 | Q66: =$G$46*Q$50*$G66 -> 6.57 | ... V66: =$G$46*V$50*$G66 -> 6.57
E67: Всего | F67: т | J67: =SUM(J62:J66) -> 0 | K67: =SUM(K62:K66) -> 0 | L67: =SUM(L62:L66) -> 0 | M67: =SUM(M62:M66) -> 15 | N67: =SUM(N62:N66) -> 21 | O67: =SUM(O62:O66) -> 30 | P67: =SUM(P62:P66) -> 30 | Q67: =SUM(Q62:Q66) -> 30 | ... V67: =SUM(V62:V66) -> 30
D69: Всего производство | F69: т | J69: =J59+J67 -> 0 | K69: =K59+K67 -> 0 | L69: =L59+L67 -> 2 | M69: =M59+M67 -> 21 | N69: =N59+N67 -> 35 | O69: =O59+O67 -> 50 | P69: =P59+P67 -> 50 | Q69: =Q59+Q67 -> 50 | ... V69: =V59+V67 -> 50
C71: Цены реализации
C73: Цены без НДС
E74: Продукт 1 | F74: руб./т | G74: 12 | H74: https://www.fedstat.ru/indicator/57698
E75: Продукт 2 | F75: руб./т | G75: 13.2 | H75: https://www.fedstat.ru/indicator/57698
E76: Продукт 3 | F76: руб./т | G76: 14.52 | H76: https://www.fedstat.ru/indicator/57698
E77: Продукт 4 | F77: руб./т | G77: 15.972 | H77: https://www.fedstat.ru/indicator/57698
E78: Продукт 5 | F78: руб./т | G78: 17.5692 | H78: https://www.fedstat.ru/indicator/57698
B81: Расходы
C83: Расходы сырья на единицу продукции
E85: …
E86: …
E87: …
C89: Цены на сырье
E91: …
E92: …
E93: …
B97: ываыва

Sheet Форматы ячеек
A1: Форматы ячеек
B3: Форматы чисел
C5: Формат | D5: Положительное | E5: Отрицательное | F5: Ноль
C6: Базовый | D6: 100500 | E6: -100500 | F6: 0 | G6: Плохо
C7: Базовый | D7: 1.05 | E7: -1.05 | F7: 0 | G7: Плохо
C8: # ##0;(# ##0);- | D8: 100500 | E8: -100500 | F8: 0 | G8: Хорошо
C9: # ##0%;(# ##0%);- | D9: 1.05 | E9: -1.05 | F9: 0 | G9: Хорошо
C10: # ##0x;(# ##0x);- | D10: 105 | E10: -105 | F10: 0 | G10: Хорошо
B13: Форматы дат
C15: Формат | D15: Дата
C16: ДД.ММ.ГГГГ (базовый) | D16: =TODAY() -> 46078
C17: МММ.ГГ | D17: =TODAY() -> 46078
C18: МММ. ГГ | D18: =TODAY() -> 46078
C19: МММ.ГГГГ | D19: =TODAY() -> 46078
C20: ДД.МММ.ГГ | D20: =TODAY() -> 46078
C21: [$-x-sysdate]ДДДД, ММММ ДД, ГГГГ | D21: =TODAY() -> 46078
B23: HotKeys
C25: Ctrl+1 | D25: Меню формата ячеек
C26: Ctrl+Shift+1 | D26: Числовой формат с разделителями
C27: Ctrl+Shift+5 | D27: Проценты
C28: Alt - Z - 9 | D28: Убрать один разряд
C29: Alt - Z - 01 | D29: Добавить один разряд

Sheet Блок 2->

Sheet Формулы
A1: Формулы
B2: Формула | C2: Описание | D2: Пример 1 | E2: Пример 2 | F2: Комментарий | H2: Исходные данные
B3: Условия. Логические операторы
B5: И | D5: =AND(H5>=100,I5>=100) -> TRUE | E5: =AND(H5>=200,I5>=100) -> FALSE | H5: 100 | I5: 200
B6: ИЛИ | D6: =OR(H6>=100,I6>=100) -> TRUE | E6: =OR(H6>200,I6>200) -> FALSE | H6: 100 | I6: 200
B8: ЕСЛИ | D8: =IF(H8>0,1,0) -> 1 | E8: =IF(H8<0,1,0) -> 0 | H8: 100
B9: ЕСЛИ | D9: =IF(H9>0,"Верно","Не верно") -> Верно | E9: =IF(H9<0,"Верно","Не верно") -> Не верно | H9: 100
B10: ЕСЛИ(И…) | C10: С несколькими условиями вар.1 | D10: =IF(AND(H10>0,I10>0),1,0) -> 1 | E10: =IF(AND(H10<0,I10<0),1,0) -> 0 | H10: 100 | I10: 200
B11: ЕСЛИ(ЕСЛИ...) | C11: С несколькими условиями вар.2 | D11: =IF(H11>0,IF(I11>0,1,0),0) -> 1 | E11: =IF(H11<0,IF(I11<0,1,0),0) -> 0 | H11: 100 | I11: 200
B13: ЕСЛИОШИБКА | D13: =IFERROR(H13,0) -> 0 | E13: =IFERROR(H13,"Ошибка") -> Ошибка | H13: =ыва/2 -> #NAME?
B14: ЕСЛИОШИБКА | D14: =IFERROR(H14,0) -> 0 | E14: =IFERROR(H14,"Ошибка") -> Ошибка | H14: ="ыва"/2 -> #VALUE!
B15: ЕСЛИОШИБКА | D15: =IFERROR(H15,0) -> 0 | E15: =IFERROR(H15,"Ошибка") -> Ошибка | H15: =2/0 -> #DIV/0!
B16: ЕСЛИОШИБКА | D16: =IFERROR(H16,0) -> 0 | E16: =IFERROR(H16,"Ошибка") -> Ошибка | H16: =#REF! -> #REF!
B18: СУММЕСЛИ. СРЗНАЧЕСЛИ. СЧЕТЕСЛИ
B20: СУММЕСЛИ | C20: Суммирование по 1 условию | D20: =SUMIF($H$20:$H$24,"Продукт 1",$K$20:$K$24) -> 1 | H20: Продукт 1 | I20: Категория А | J20: Москва | K20: 1
B21: СУММЕСЛИ | C21: Суммирование, если больше/меньше/равно(не) | D21: =SUMIF($K$20:$K$24,">3") -> 4 | E21: =SUMIF($K$20:$K$25,"<>0") -> 11 | H21: Продукт 2 | I21: Категория А | J21: Тверь | K21: -2
B22: СУММЕСЛИ | C22: Суммирование по частичному совпадению условия | D22: =SUMIF($J$20:$J$24,"Моск" & "*",$K$20:$K$24) -> 5 | F22: Учитывается только совпадение текста с самого начала | H22: Продукт 3 | I22: Категория А | J22: Екб | K22: 3
B23: СУММЕСЛИМН | C23: Суммирование по нескольким условиям | D23: =SUMIFS($K$20:$K$24,$H$20:$H$24,"Продукт 1",$I$20:$I$24,"Категория А") -> 1 | H23: Продукт 4 | I23: Категория А | J23: Московская обл. | K23: 4
H24: Продукт 1 | I24: Категория Б | J24: Сочи | K24: 0
B25: СЧЁТЕСЛИ | C25: Счет, если больше/меньше/равно(не) | D25: =COUNTIF(K20:K25,"<>0") -> 5 | H25: Продукт 1 | J25: Сбб | K25: 5
B26: СЧЁТЕСЛИМН | D26: =COUNTIFS($K$20:$K$25,">0",$I$20:$I$25,"<>0") -> 4
B28: СРЗНАЧЕСЛИ | D28: =AVERAGEIF($H$20:$H$25,"Продукт 1",$K$20:$K$25) -> 2
B29: СРЗНАЧЕСЛИМН | D29: =AVERAGEIFS($K$20:$K$25,$I$20:$I$25,"Категория А",$J$20:$J$25,"Моск" & "*") -> 2.5
B31: Важно !
B32: Обязательно должна быть одинаковая длина диапазонов
B33: Не забывай фиксировать ячейки (F4)
B35: Извлечение значений из таблиц
B37: ВПР | D37: Продукт 5 | E37: =VLOOKUP($D$37,$H$37:$I$42,2,FALSE) -> Томаты | H37: Продукт 1 | I37: Две мясных котлеты гриль | J37: 200 ккал | L37: 1 кв. | M37: 2 кв. | N37: 3 кв. | O37: 4 кв.
B38: ГПР | D38: 3 кв. | E38: =HLOOKUP($D$38,$L$37:$O$38,2,FALSE) -> 15 | H38: Продукт 2 | I38: Спец.соус | J38: 100 ккал | L38: 5 | M38: 10 | N38: 15 | O38: 20
H39: Продукт 3 | I39: Сыр | J39: 50 ккал
B40: ИНДЕКС(ПОИСКПОЗ…) | D40: Продукт 5 | E40: =INDEX($J$37:$J$42,MATCH($D$40,$H$37:$H$42,0)) -> 15 ккал | H40: Продукт 4 | I40: Огурцы | J40: 10 ккал
H41: Продукт 5 | I41: Томаты | J41: 15 ккал
H42: Продукт 6 | I42: Лук | J42: 5 ккал
B43: Важно !
B44: ВПР и ГПР позволяют работать только с одним условием
B45: ВПР и ГПР искомое значения обязательно должно быть в первом столбце/строке
B46: Индекс+ПоискПоз - не имеет значение положением строк/столбоц
B47: Для всех функций - обязательно проверять единственность искомого значения (функции берут только первое)
B49: Извлечение значения по интервалам | I49: Выручка | J49: Тип фирмы
B50: ВПР | D50: 21 | E50: =VLOOKUP($D$50,$I$50:$J$54,2,TRUE) -> Маленькая | I50: 0 | J50: Микро
B51: ИНДЕКС(ПОИСКПОЗ…) | D51: 74 | E51: =INDEX($J$50:$J$54,MATCH($D$51,$I$50:$I$54,1)) -> Большая | I51: 20 | J51: Маленькая
I52: 40 | J52: Средняя
I53: 60 | J53: Большая
I54: 80 | J54: Крупная
B56: Работа с текстом
B58: ПРАВСИМВ | C58: Взять N символов справа | D58: =RIGHT(H58,E58) -> FOC | E58: 3 | H58: 123-Продукт/17А-FOC
B59: ЛЕВСИМВ | C59: Взять N символов слева | D59: =LEFT(H59,E59) -> 123 | E59: 3 | H59: 123-Продукт/17А-FOC
B60: ДЛСТР | C60: Длина строки (кол-во симолов) | D60: =LEN(H60) -> 19 | H60: 123-Продукт/17А-FOC
B62: ПСТР | C62: Взять N символов справа, начиная с K символа | D62: =MID(H62,5,7) -> Продукт | H62: 123-Продукт/17А-FOC
B63: ЛЕВСИМВ(ПСТР…) | C63: Удалить N символов с конца | D63: =LEFT(H63,LEN(H63)-E63) -> 123-Продукт/17А | E63: 4 | H63: 123-Продукт/17А-FOC
B64: ПРАВСИМВ(ПСТР…) | C64: Удалить N символов с начала | D64: =RIGHT(H64,LEN(H64)-E64) -> Продукт/17А-FOC | E64: 4 | H64: 123-Продукт/17А-FOC
B66: ПСТР(ПОИСК…) | C66: Взять N символов после "/" | D66: =MID(H66,SEARCH("/",H66)+E66-2,E66) -> 17А | E66: 3 | H66: 123-Продукт/17А-FOC
B67: ПСТР(ПОИСК…) | C67: Взять N символов до "/" | D67: =MID(H67,SEARCH("/",H67)-E67,E67) -> Продукт | E67: 7 | H67: 123-Продукт/17А-FOC
D69: ИНКУБАЦИОННЫЕ ЯЙЦА | E69: Столовые яйца
B70: МИН(ЕСЛИОШИБКА(ПОИСК…) | C70: Поиск текста в ячейке | D70: =MIN(1,IFERROR(SEARCH(D69,H70),0)) -> 1 | E70: =MIN(1,IFERROR(SEARCH(E69,H70),0)) -> 0 | H70: ИНКУБАЦИОННЫЕ ЯЙЦА ДОМАШНЕЙ ПТИЦЫ, ОПЛОДОТВОРЁННЫЕ (ДЛЯ ИНКУБАЦИИ): ПЛЕМЕННОЕ ЯЙЦО УТКИ (ANAS PLATYRHYNCHOS L.) ПЕКИНСКОЙ-13400 ШТУК;РАЗМЕЩЕНЫ С ЦЕЛЬЮ ПРЕДОТВРАЩЕНИЯ БОЯ И УНИЧТОЖЕНИЯ В КАРТОННЫХ КОРОБКАХ (200 ЯИЦ В ОДНОЙ КОРОБКЕ)
B72: Объединение ячеек
B74: СЦЕПИТЬ | C74: Объдеинение текста | D74: =H74 & "_" & I74 -> Продукт_123 | E74: =CONCATENATE(H74,"_",I74) -> Продукт_123 | H74: Продукт | I74: 123
B75: СЦЕПИТЬ | C75: Объдеинение с датой | D75: =CONCATENATE(H75,"_",TEXT(I75,"ДД.ММ.ГГГ")) -> Договор_25.02.2026 | F75: Или другой формат данных | H75: Договор | I75: =TODAY() -> 46078
B76: СЦЕПИТЬ | C76: Объдеинение с числом | D76: =CONCATENATE(H76,"_",TEXT(I76,"# ##0,0;(# ##0,0);-")," руб.") -> Остаток_1,7 руб. | F76: "#0,0" - нули после запятой можно править | H76: Остаток | I76: =5/3 -> 1.6666667
B78: СМЕЩ. СУММ(СМЕЩ…)
B80: СМЕЩ | C80: Когда нужно смещаться на N ячеек | G80: кв. | H80: 1 | I80: =H80+1 -> 2 | J80: =I80+1 -> 3 | K80: =J80+1 -> 4 | L80: =H80 -> 1 | M80: =I80 -> 2 | N80: =J80 -> 3 | O80: =K80 -> 4 | P80: =L80 -> 1 | Q80: =M80 -> 2 | R80: =N80 -> 3 | S80: =O80 -> 4 | ... AI80: =AE80 -> 4
G81: год | H81: 2024 | I81: 2024 | J81: 2024 | K81: 2024 | L81: =H81+1 -> 2025 | M81: =I81+1 -> 2025 | N81: =J81+1 -> 2025 | O81: =K81+1 -> 2025 | P81: =L81+1 -> 2026 | Q81: =M81+1 -> 2026 | R81: =N81+1 -> 2026 | S81: =O81+1 -> 2026 | ... AI81: =AE81+1 -> 2030
C82: Ввод в эксплуатацию, флаг | J82: 1
C83: Возмещение НДС, кв. после ввода | D83: 2
C84: Возмещение НДС, флаг | H84: =OFFSET(H82,0,-$D$83,1,1) -> 0 | I84: =OFFSET(I82,0,-$D$83,1,1) -> 0 | J84: =OFFSET(J82,0,-$D$83,1,1) -> 0 | K84: =OFFSET(K82,0,-$D$83,1,1) -> 0 | L84: =OFFSET(L82,0,-$D$83,1,1) -> 1 | M84: =OFFSET(M82,0,-$D$83,1,1) -> 0 | N84: =OFFSET(N82,0,-$D$83,1,1) -> 0 | O84: =OFFSET(O82,0,-$D$83,1,1) -> 0 | ... AI84: =OFFSET(AI82,0,-$D$83,1,1) -> 0
B86: СУММ(СМЕЩ…) | C86: Расчет амортизации | G86: кв. | H86: 1 | I86: =H86+1 -> 2 | J86: =I86+1 -> 3 | K86: =J86+1 -> 4 | L86: =H86 -> 1 | M86: =I86 -> 2 | N86: =J86 -> 3 | O86: =K86 -> 4 | P86: =L86 -> 1 | Q86: =M86 -> 2 | R86: =N86 -> 3 | S86: =O86 -> 4 | ... AI86: =AE86 -> 4
G87: год | H87: 2024 | I87: 2024 | J87: 2024 | K87: 2024 | L87: =H87+1 -> 2025 | M87: =I87+1 -> 2025 | N87: =J87+1 -> 2025 | O87: =K87+1 -> 2025 | P87: =L87+1 -> 2026 | Q87: =M87+1 -> 2026 | R87: =N87+1 -> 2026 | S87: =O87+1 -> 2026 | ... AI87: =AE87+1 -> 2030
G88: Фактор | H88: 0.25 | I88: 0.25 | J88: 0.25 | K88: 0.25 | L88: 0.25 | M88: 0.25 | N88: 0.25 | O88: 0.25 | P88: 0.25 | Q88: 0.25 | R88: 0.25 | S88: 0.25 | T88: 0.25 | U88: 0.25 | V88: 0.25 | W88: 0.25 | X88: 0.25 | Y88: 0.25 | Z88: 0.25 | AA88: 0.25 | AB88: 0.25 | AC88: 0.25 | AD88: 0.25 | AE88: 0.25 | AF88: 0.25 | AG88: 0.25 | AH88: 0.25 | AI88: 0.25
C90: Ввод в эксплуатацию, руб. | D90: 1600 | G90: =G82*$D90 -> 0 | H90: =H82*$D90 -> 0 | I90: =I82*$D90 -> 0 | J90: =J82*$D90 -> 1600 | K90: =K82*$D90 -> 0 | L90: =L82*$D90 -> 0 | M90: =M82*$D90 -> 0 | N90: =N82*$D90 -> 0 | ... AI90: =AI82*$D90 -> 0
C91: Срок полезного использования, лет | D91: 2
C92: Амортизация | H92: =IFERROR(SUM(OFFSET(H90,,-1,1,-MIN(COUNT($H88:H88),$D91*(1/H$88))))/($D91*(1/H$88)),0) -> 0 | I92: =IFERROR(SUM(OFFSET(I90,,-1,1,-MIN(COUNT($H88:I88),$D91*(1/I$88))))/($D91*(1/I$88)),0) -> 0 | J92: =IFERROR(SUM(OFFSET(J90,,-1,1,-MIN(COUNT($H88:J88),$D91*(1/J$88))))/($D91*(1/J$88)),0) -> 0 | K92: =IFERROR(SUM(OFFSET(K90,,-1,1,-MIN(COUNT($H88:K88),$D91*(1/K$88))))/($D91*(1/K$88)),0) -> 200 | L92: =IFERROR(SUM(OFFSET(L90,,-1,1,-MIN(COUNT($H88:L88),$D91*(1/L$88))))/($D91*(1/L$88)),0) -> 200 | M92: =IFERROR(SUM(OFFSET(M90,,-1,1,-MIN(COUNT($H88:M88),$D91*(1/M$88))))/($D91*(1/M$88)),0) -> 200 | N92: =IFERROR(SUM(OFFSET(N90,,-1,1,-MIN(COUNT($H88:N88),$D91*(1/N$88))))/($D91*(1/N$88)),0) -> 200 | O92: =IFERROR(SUM(OFFSET(O90,,-1,1,-MIN(COUNT($H88:O88),$D91*(1/O$88))))/($D91*(1/O$88)),0) -> 200 | ... AI92: =IFERROR(SUM(OFFSET(AI90,,-1,1,-MIN(COUNT($H88:AI88),$D91*(1/AI$88))))/($D91*(1/AI$88)),0) -> 0
B94: Важно !
B95: В строку ввод в эксплуатацию можно добавлять, например, капексы на подержание, если СПИ такой же

Sheet Текст по столбцам
A1: Текст по столбцам
B2: Текст по столбцам
B4: Исходные данные | E4: Разделение текста | H4: Готовые данные
B5: Domain Code,Domain,Area Code (M49),Area,Element Code,Element,Item Code (CPC),Item,Year Code,Year,Unit,Value,Flag,Flag Description,Note | H5: Domain Code | I5: Domain | J5: Area Code (M49) | K5: Area | L5: Element Code | M5: Element | N5: Item Code (CPC) | O5: Item | P5: Year Code | Q5: Year | R5: Unit | S5: Value | T5: Flag | U5: Flag Description
B6: QCL,"Crops and livestock products","008","Albania","5510","Production","01234","Tomatoes","2020","2020","t","313109","A","Official figure","" | E6: Данные → Текст по столбцам → | H6: QCL | I6: Crops and livestock products | J6: 8 | K6: Albania | L6: 5510 | M6: Production | N6: 1234 | O6: Tomatoes | P6: 2020 | Q6: 2020 | R6: t | S6: 313109 | T6: A | U6: Official figure
B7: QCL,"Crops and livestock products","008","Albania","5510","Production","01234","Tomatoes","2021","2021","t","314470.1","A","Official figure","" | E7: → С разделителями → выбрать "символ-разделитель" | H7: QCL | I7: Crops and livestock products | J7: 8 | K7: Albania | L7: 5510 | M7: Production | N7: 1234 | O7: Tomatoes | P7: 2021 | Q7: 2021 | R7: t | S7: 314470.1 | T7: A | U7: Official figure
B8: QCL,"Crops and livestock products","008","Albania","5510","Production","01234","Tomatoes","2022","2022","t","315057.3","A","Official figure","" | H8: QCL | I8: Crops and livestock products | J8: 8 | K8: Albania | L8: 5510 | M8: Production | N8: 1234 | O8: Tomatoes | P8: 2022 | Q8: 2022 | R8: t | S8: 315057.3 | T8: A | U8: Official figure
B9: QCL,"Crops and livestock products","012","Algeria","5510","Production","01234","Tomatoes","2020","2020","t","1635616.3","A","Official figure","" | H9: QCL | I9: Crops and livestock products | J9: 12 | K9: Algeria | L9: 5510 | M9: Production | N9: 1234 | O9: Tomatoes | P9: 2020 | Q9: 2020 | R9: t | S9: 1635616.3 | T9: A | U9: Official figure
B10: QCL,"Crops and livestock products","012","Algeria","5510","Production","01234","Tomatoes","2021","2021","t","1641636","A","Official figure","" | E10: Если получаются некорректные форматы из-за "." или "," в числах: выделить столбец | H10: QCL | I10: Crops and livestock products | J10: 12 | K10: Algeria | L10: 5510 | M10: Production | N10: 1234 | O10: Tomatoes | P10: 2021 | Q10: 2021 | R10: t | S10: 1641636 | T10: A | U10: Official figure
B11: QCL,"Crops and livestock products","012","Algeria","5510","Production","01234","Tomatoes","2022","2022","t","1661664.37","I","Imputed value","" | H11: QCL | I11: Crops and livestock products | J11: 12 | K11: Algeria | L11: 5510 | M11: Production | N11: 1234 | O11: Tomatoes | P11: 2022 | Q11: 2022 | R11: t | S11: 1661664.4 | T11: I | U11: Imputed value
B12: QCL,"Crops and livestock products","024","Angola","5510","Production","01234","Tomatoes","2020","2020","t","589664","A","Official figure","" | H12: QCL | I12: Crops and livestock products | J12: 24 | K12: Angola | L12: 5510 | M12: Production | N12: 1234 | O12: Tomatoes | P12: 2020 | Q12: 2020 | R12: t | S12: 589664 | T12: A | U12: Official figure
B13: QCL,"Crops and livestock products","024","Angola","5510","Production","01234","Tomatoes","2021","2021","t","561666","A","Official figure","" | H13: QCL | I13: Crops and livestock products | J13: 24 | K13: Angola | L13: 5510 | M13: Production | N13: 1234 | O13: Tomatoes | P13: 2021 | Q13: 2021 | R13: t | S13: 561666 | T13: A | U13: Official figure
B14: QCL,"Crops and livestock products","024","Angola","5510","Production","01234","Tomatoes","2022","2022","t","587785","A","Official figure","" | H14: QCL | I14: Crops and livestock products | J14: 24 | K14: Angola | L14: 5510 | M14: Production | N14: 1234 | O14: Tomatoes | P14: 2022 | Q14: 2022 | R14: t | S14: 587785 | T14: A | U14: Official figure
B15: QCL,"Crops and livestock products","028","Antigua and Barbuda","5510","Production","01234","Tomatoes","2020","2020","t","34.7","A","Official figure","" | H15: QCL | I15: Crops and livestock products | J15: 28 | K15: Antigua and Barbuda | L15: 5510 | M15: Production | N15: 1234 | O15: Tomatoes | P15: 2020 | Q15: 2020 | R15: t | S15: 34.7 | T15: A | U15: Official figure
B16: QCL,"Crops and livestock products","028","Antigua and Barbuda","5510","Production","01234","Tomatoes","2021","2021","t","71.45","A","Official figure","" | H16: QCL | I16: Crops and livestock products | J16: 28 | K16: Antigua and Barbuda | L16: 5510 | M16: Production | N16: 1234 | O16: Tomatoes | P16: 2021 | Q16: 2021 | R16: t | S16: 71.45 | T16: A | U16: Official figure
B17: QCL,"Crops and livestock products","028","Antigua and Barbuda","5510","Production","01234","Tomatoes","2022","2022","t","90.5","A","Official figure","" | H17: QCL | I17: Crops and livestock products | J17: 28 | K17: Antigua and Barbuda | L17: 5510 | M17: Production | N17: 1234 | O17: Tomatoes | P17: 2022 | Q17: 2022 | R17: t | S17: 90.5 | T17: A | U17: Official figure
B18: QCL,"Crops and livestock products","032","Argentina","5510","Production","01234","Tomatoes","2020","2020","t","1221000","A","Official figure","" | H18: QCL | I18: Crops and livestock products | J18: 32 | K18: Argentina | L18: 5510 | M18: Production | N18: 1234 | O18: Tomatoes | P18: 2020 | Q18: 2020 | R18: t | S18: 1221000 | T18: A | U18: Official figure
B19: QCL,"Crops and livestock products","032","Argentina","5510","Production","01234","Tomatoes","2021","2021","t","1362000","A","Official figure","" | H19: QCL | I19: Crops and livestock products | J19: 32 | K19: Argentina | L19: 5510 | M19: Production | N19: 1234 | O19: Tomatoes | P19: 2021 | Q19: 2021 | R19: t | S19: 1362000 | T19: A | U19: Official figure
B20: QCL,"Crops and livestock products","032","Argentina","5510","Production","01234","Tomatoes","2022","2022","t","1393000","A","Official figure","" | H20: QCL | I20: Crops and livestock products | J20: 32 | K20: Argentina | L20: 5510 | M20: Production | N20: 1234 | O20: Tomatoes | P20: 2022 | Q20: 2022 | R20: t | S20: 1393000 | T20: A | U20: Official figure
B21: QCL,"Crops and livestock products","051","Armenia","5510","Production","01234","Tomatoes","2020","2020","t","183656.9","A","Official figure","" | H21: QCL | I21: Crops and livestock products | J21: 51 | K21: Armenia | L21: 5510 | M21: Production | N21: 1234 | O21: Tomatoes | P21: 2020 | Q21: 2020 | R21: t | S21: 183656.9 | T21: A | U21: Official figure
B22: QCL,"Crops and livestock products","051","Armenia","5510","Production","01234","Tomatoes","2021","2021","t","206085.5","A","Official figure","" | H22: QCL | I22: Crops and livestock products | J22: 51 | K22: Armenia | L22: 5510 | M22: Production | N22: 1234 | O22: Tomatoes | P22: 2021 | Q22: 2021 | R22: t | S22: 206085.5 | T22: A | U22: Official figure
... B28: QCL,"Crops and livestock products","040","Austria","5510","Production","01234","Tomatoes","2021","2021","t","59770","A","Official figure","" | H28: QCL | I28: Crops and livestock products | J28: 40 | K28: Austria | L28: 5510 | M28: Production | N28: 1234 | O28: Tomatoes | P28: 2021 | Q28: 2021 | R28: t | S28: 59770 | T28: A | U28: Official figure
B29: QCL,"Crops and livestock products","044","Bahamas","5510","Production","01234","Tomatoes","2020","2020","t","7642.44","E","Estimated value","" | E29: Затем - автозамена "." на "," | H29: QCL | I29: Crops and livestock products | J29: 44 | K29: Bahamas | L29: 5510 | M29: Production | N29: 1234 | O29: Tomatoes | P29: 2020 | Q29: 2020 | R29: t | S29: 7642.44 | T29: E | U29: Estimated value
B30: QCL,"Crops and livestock products","044","Bahamas","5510","Production","01234","Tomatoes","2021","2021","t","7512.81","E","Estimated value","" | H30: QCL | I30: Crops and livestock products | J30: 44 | K30: Bahamas | L30: 5510 | M30: Production | N30: 1234 | O30: Tomatoes | P30: 2021 | Q30: 2021 | R30: t | S30: 7512.81 | T30: E | U30: Estimated value
B32: Объединение ячеек
B34: Исходные данные | E34: Готовые данные: 1 | F34: Готовые данные: 2
B36: Имя | C36: Фамилия | E36: Имя_Фамилия | F36: Имя_Фамилия
B37: Имя1 | C37: Фамилия1 | E37: =B37 & "_" & C37 -> Имя1_Фамилия1 | F37: =CONCATENATE(B37,"_",C37) -> Имя1_Фамилия1
B38: Имя2 | C38: Фамилия2 | E38: =B38 & "_" & C38 -> Имя2_Фамилия2 | F38: =CONCATENATE(B38,"_",C38) -> Имя2_Фамилия2
B39: Имя3 | C39: Фамилия3 | E39: =B39 & "_" & C39 -> Имя3_Фамилия3 | F39: =CONCATENATE(B39,"_",C39) -> Имя3_Фамилия3
B40: Имя4 | C40: Фамилия4 | E40: =B40 & "_" & C40 -> Имя4_Фамилия4 | F40: =CONCATENATE(B40,"_",C40) -> Имя4_Фамилия4
B41: Имя5 | C41: Фамилия5 | E41: =B41 & "_" & C41 -> Имя5_Фамилия5 | F41: =CONCATENATE(B41,"_",C41) -> Имя5_Фамилия5

Sheet Анализ деклараций
A1: Анализ таможенных деклараций
B2: Показатель | G2: ед. изм. | H2: Константа
B3: Первичная обработка
C5: 1 | D5: Скопировать как значения (сильно уменьшает вес файла)
C6: 2 | D6: Закрепить области
C7: 3 | D7: Поставить фильтр
C8: 4 | D8: Проверить, что по столбцам одинаковая информация (особенно, если объединено несколько сводных таблиц)
C9: 5 | D9: Опционально - сгруппировать скрытые столбцы
C10: 6 | D10: Сделать замену (Ctrl+H) символов ", > и < (некорретно считается со знаками)
B12: Сведение данных
C13: СУММЕСЛИ. СУММЕСЛИМН
I14: Выделение диапазона | L14: Выделение всего столбца (увеличивает время расчета)
D15: Объемы торговли, штуки | I15: СУММЕСЛИ | J15: СУММЕСЛИМН | L15: СУММЕСЛИ | M15: СУММЕСЛИМН
E16: ИМ | G16: тыс. шт. | I16: =SUMIF('Декларации_Исх. данные'!$I$3:$I$343,$E16,'Декларации_Исх. данные'!$CA$3:$CA$343)/1000 -> 18515.6 | J16: =SUMIFS('Декларации_Исх. данные'!$CA$3:$CA$343,'Декларации_Исх. данные'!$I$3:$I$343,$E16)/1000 -> 18515.6 | L16: =SUMIF('Декларации_Исх. данные'!$I:$I,$E16,'Декларации_Исх. данные'!$CA:$CA)/1000 -> 18515.6 | M16: =SUMIFS('Декларации_Исх. данные'!$CA:$CA,'Декларации_Исх. данные'!$I:$I,$E16)/1000 -> 18515.6
E17: ЭК | G17: тыс. шт. | I17: =SUMIF('Декларации_Исх. данные'!$I$3:$I$343,$E17,'Декларации_Исх. данные'!$CA$3:$CA$343)/1000 -> 1152 | J17: =SUMIFS('Декларации_Исх. данные'!$CA$3:$CA$343,'Декларации_Исх. данные'!$I$3:$I$343,$E17)/1000 -> 1152 | L17: =SUMIF('Декларации_Исх. данные'!$I:$I,$E17,'Декларации_Исх. данные'!$CA:$CA)/1000 -> 1152 | M17: =SUMIFS('Декларации_Исх. данные'!$CA:$CA,'Декларации_Исх. данные'!$I:$I,$E17)/1000 -> 1152
C19: Важно !
E20: Обязательно должна быть одинаковая длина диапазонов
E21: Не забывай фиксировать ячейки (F4)
C23: Удаление дубликатов
C25: 1 | D25: Выделить весь столбец
C26: 2 | D26: Скопировать и вставить отдельно
C27: 3 | D27: Данные → Удалить дубликаты → Сортировать в пределах указанного диапазона
D29: Импорт. Страна отправления
D30: ИМ | E30: ВЕНГРИЯ | G30: тыс. шт. | I30: =SUMIFS('Декларации_Исх. данные'!$CA:$CA,'Декларации_Исх. данные'!$I:$I,$D30,'Декларации_Исх. данные'!$AR:$AR,$E30)/1000 -> 3113.7
D31: ИМ | E31: КАНАДА | G31: тыс. шт. | I31: =SUMIFS('Декларации_Исх. данные'!$CA:$CA,'Декларации_Исх. данные'!$I:$I,$D31,'Декларации_Исх. данные'!$AR:$AR,$E31)/1000 -> 5626.2
D32: ИМ | E32: СОЕДИНЕННОЕ КОРОЛЕВСТВО | G32: тыс. шт. | I32: =SUMIFS('Декларации_Исх. данные'!$CA:$CA,'Декларации_Исх. данные'!$I:$I,$D32,'Декларации_Исх. данные'!$AR:$AR,$E32)/1000 -> 644.6
D33: ИМ | E33: ГЕРМАНИЯ | G33: тыс. шт. | I33: =SUMIFS('Декларации_Исх. данные'!$CA:$CA,'Декларации_Исх. данные'!$I:$I,$D33,'Декларации_Исх. данные'!$AR:$AR,$E33)/1000 -> 5140.9
D34: ИМ | E34: ФРАНЦИЯ | G34: тыс. шт. | I34: =SUMIFS('Декларации_Исх. данные'!$CA:$CA,'Декларации_Исх. данные'!$I:$I,$D34,'Декларации_Исх. данные'!$AR:$AR,$E34)/1000 -> 1530
D35: ИМ | E35: СЛОВАКИЯ | G35: тыс. шт. | I35: =SUMIFS('Декларации_Исх. данные'!$CA:$CA,'Декларации_Исх. данные'!$I:$I,$D35,'Декларации_Исх. данные'!$AR:$AR,$E35)/1000 -> 1941.2
D36: ИМ | E36: ИСПАНИЯ | G36: тыс. шт. | I36: =SUMIFS('Декларации_Исх. данные'!$CA:$CA,'Декларации_Исх. данные'!$I:$I,$D36,'Декларации_Исх. данные'!$AR:$AR,$E36)/1000 -> 156
D37: ИМ | E37: ИТАЛИЯ | G37: тыс. шт. | I37: =SUMIFS('Декларации_Исх. данные'!$CA:$CA,'Декларации_Исх. данные'!$I:$I,$D37,'Декларации_Исх. данные'!$AR:$AR,$E37)/1000 -> 363
D38: ИМ | E38: РОССИЯ | G38: тыс. шт. | I38: =SUMIFS('Декларации_Исх. данные'!$CA:$CA,'Декларации_Исх. данные'!$I:$I,$D38,'Декларации_Исх. данные'!$AR:$AR,$E38)/1000 -> 0
E39: Всего | G39: тыс. шт. | I39: =SUM(I30:I38) -> 18515.6
F40: Проверка | I40: =I39-I16 -> 0
C42: Частичное совпадение
D44: Импорт по производителям
D45: ИМ | E45: CUDDY FARMS LIMITED 2008 | G45: тыс. шт. | I45: =SUMIFS('Декларации_Исх. данные'!$CA:$CA,'Декларации_Исх. данные'!$I:$I,$D45,'Декларации_Исх. данные'!$BX:$BX,$E45)/1000 -> 5341.4
D46: ИМ | E46: CUDDY FARMS LIMITED 2008, ПЛЕМЗАВОД: KRS0000042053 | G46: тыс. шт. | I46: =SUMIFS('Декларации_Исх. данные'!$CA:$CA,'Декларации_Исх. данные'!$I:$I,$D46,'Декларации_Исх. данные'!$BX:$BX,$E46)/1000 -> 24
D47: ИМ | E47: HENDRIX GENETICS TURKEYS FRANCE | G47: тыс. шт. | I47: =SUMIFS('Декларации_Исх. данные'!$CA:$CA,'Декларации_Исх. данные'!$I:$I,$D47,'Декларации_Исх. данные'!$BX:$BX,$E47)/1000 -> 611.6
D48: ИМ | E48: HENDRIX GENETICS TURKEYS FRANCE SAS | G48: тыс. шт. | I48: =SUMIFS('Декларации_Исх. данные'!$CA:$CA,'Декларации_Исх. данные'!$I:$I,$D48,'Декларации_Исх. данные'!$BX:$BX,$E48)/1000 -> 148.2
D50: Расчет с частиным совпадением текста
D51: ИМ | E51: CUDDY | G51: тыс. шт. | I51: =SUMIFS('Декларации_Исх. данные'!$CA:$CA,'Декларации_Исх. данные'!$I:$I,$D51,'Декларации_Исх. данные'!$BX:$BX,$E51 & "*")/1000 -> 5593.4
D52: ИМ | E52: HENDRIX | G52: тыс. шт. | I52: =SUMIFS('Декларации_Исх. данные'!$CA:$CA,'Декларации_Исх. данные'!$I:$I,$D52,'Декларации_Исх. данные'!$BX:$BX,$E52 & "*")/1000 -> 759.8
C54: Важно !
D55: Учитывается только совпадение текста с самого начала
C57: Суммирование значений больше/меньше заданного
D59: Объем импорта: поставки не менее | G59: шт. | I59: 100000
D60: ИМ | E60: CUDDY | G60: тыс. шт. | I60: =SUMIFS('Декларации_Исх. данные'!$CA:$CA,'Декларации_Исх. данные'!$I:$I,$D60,'Декларации_Исх. данные'!$BX:$BX,$E60 & "*",'Декларации_Исх. данные'!$CA:$CA,">"&$I$59)/1000 -> 1471.6
D61: ИМ | E61: HENDRIX | G61: тыс. шт. | I61: =SUMIFS('Декларации_Исх. данные'!$CA:$CA,'Декларации_Исх. данные'!$I:$I,$D61,'Декларации_Исх. данные'!$BX:$BX,$E61 & "*",'Декларации_Исх. данные'!$CA:$CA,">"&$I$59)/1000 -> 112.8
C63: Сводные таблицы
D65: Выделить исходную таблицу → Вставка → Сводная таблица
C79: Важно !
D80: В исходной таблице обязательно должны быть названия столбцов
D81: Если меняются данные в исходной таблице – нужно обновлять сводную таблицу вручную (можно поставить автообновление при открытии книги)
D82: После обновления ширина столбцов таблицы данных меняется – это можно отключить в настройках таблицы данных
D83: Если в исходную таблицу добавляются строки снизу таблицы – нужно изменить диапазон в сводной таблице
B85: Анализ по тексту
C87: ='Декларации_Исх. данные'!$BT$1 -> Пример | F87: Если много строк, и считается медленно - можно вставить хардами
D89: Объемы торговли - индейка, штуки
E90: ИМ | G90: тыс. шт. | I90: =SUMIFS('Декларации_Исх. данные'!$CM:$CM,'Декларации_Исх. данные'!$I:$I,$E90,'Декларации_Исх. данные'!$BV:$BV,1)/1000 -> 1237.398
E91: ЭК | G91: тыс. шт. | I91: =SUMIFS('Декларации_Исх. данные'!$CM:$CM,'Декларации_Исх. данные'!$I:$I,$E91,'Декларации_Исх. данные'!$BV:$BV,1)/1000 -> 0
D93: Объемы торговли - индейка, доллары
E94: ИМ | G94: тыс. шт. | I94: =SUMIFS('Декларации_Исх. данные'!$CM:$CM,'Декларации_Исх. данные'!$I:$I,$E94,'Декларации_Исх. данные'!$BV:$BV,1)/1000 -> 1237.398
E95: ЭК | G95: тыс. шт. | I95: =SUMIFS('Декларации_Исх. данные'!$CM:$CM,'Декларации_Исх. данные'!$I:$I,$E95,'Декларации_Исх. данные'!$BV:$BV,1)/1000 -> 0
B97: Авторанжирование
C99: Исходные данные
C100: Импорт. Страна отправления | I100: Ранг
D101: ИМ | E101: ВЕНГРИЯ | G101: тыс. шт. | H101: =SUMIFS('Декларации_Исх. данные'!$CA:$CA,'Декларации_Исх. данные'!$I:$I,$D101,'Декларации_Исх. данные'!$AR:$AR,$E101)/1000 -> 3113.7 | I101: =IFERROR(_xlfn.RANK.EQ(H101,$H$101:$H$109,0),0) -> 3 | J101: =H101 -> 3113.7
D102: ИМ | E102: КАНАДА | G102: тыс. шт. | H102: =SUMIFS('Декларации_Исх. данные'!$CA:$CA,'Декларации_Исх. данные'!$I:$I,$D102,'Декларации_Исх. данные'!$AR:$AR,$E102)/1000 -> 5626.2 | I102: =IFERROR(_xlfn.RANK.EQ(H102,$H$101:$H$109,0),0) -> 1 | J102: =H102 -> 5626.2
D103: ИМ | E103: СОЕДИНЕННОЕ КОРОЛЕВСТВО | G103: тыс. шт. | H103: =SUMIFS('Декларации_Исх. данные'!$CA:$CA,'Декларации_Исх. данные'!$I:$I,$D103,'Декларации_Исх. данные'!$AR:$AR,$E103)/1000 -> 644.6 | I103: =IFERROR(_xlfn.RANK.EQ(H103,$H$101:$H$109,0),0) -> 6 | J103: =H103 -> 644.6
D104: ИМ | E104: ГЕРМАНИЯ | G104: тыс. шт. | H104: =SUMIFS('Декларации_Исх. данные'!$CA:$CA,'Декларации_Исх. данные'!$I:$I,$D104,'Декларации_Исх. данные'!$AR:$AR,$E104)/1000 -> 5140.9 | I104: =IFERROR(_xlfn.RANK.EQ(H104,$H$101:$H$109,0),0) -> 2 | J104: =H104 -> 5140.9
D105: ИМ | E105: ФРАНЦИЯ | G105: тыс. шт. | H105: =SUMIFS('Декларации_Исх. данные'!$CA:$CA,'Декларации_Исх. данные'!$I:$I,$D105,'Декларации_Исх. данные'!$AR:$AR,$E105)/1000 -> 1530 | I105: =IFERROR(_xlfn.RANK.EQ(H105,$H$101:$H$109,0),0) -> 5 | J105: =H105 -> 1530
D106: ИМ | E106: СЛОВАКИЯ | G106: тыс. шт. | H106: =SUMIFS('Декларации_Исх. данные'!$CA:$CA,'Декларации_Исх. данные'!$I:$I,$D106,'Декларации_Исх. данные'!$AR:$AR,$E106)/1000 -> 1941.2 | I106: =IFERROR(_xlfn.RANK.EQ(H106,$H$101:$H$109,0),0) -> 4 | J106: =H106 -> 1941.2
D107: ИМ | E107: ИСПАНИЯ | G107: тыс. шт. | H107: =SUMIFS('Декларации_Исх. данные'!$CA:$CA,'Декларации_Исх. данные'!$I:$I,$D107,'Декларации_Исх. данные'!$AR:$AR,$E107)/1000 -> 156 | I107: =IFERROR(_xlfn.RANK.EQ(H107,$H$101:$H$109,0),0) -> 8 | J107: =H107 -> 156
D108: ИМ | E108: ИТАЛИЯ | G108: тыс. шт. | H108: =SUMIFS('Декларации_Исх. данные'!$CA:$CA,'Декларации_Исх. данные'!$I:$I,$D108,'Декларации_Исх. данные'!$AR:$AR,$E108)/1000 -> 363 | I108: =IFERROR(_xlfn.RANK.EQ(H108,$H$101:$H$109,0),0) -> 7 | J108: =H108 -> 363
D109: ИМ | E109: РОССИЯ | G109: тыс. шт. | H109: =SUMIFS('Декларации_Исх. данные'!$CA:$CA,'Декларации_Исх. данные'!$I:$I,$D109,'Декларации_Исх. данные'!$AR:$AR,$E109)/1000 -> 0 | I109: =IFERROR(_xlfn.RANK.EQ(H109,$H$101:$H$109,0),0) -> 9 | J109: =H109 -> 0
E110: Всего | G110: тыс. шт. | H110: =SUM(H101:H109) -> 18515.6
C112: Отсортированные данные
C113: Импорт. Страна отправления | I113: ВПР | J113: Индекс+ПоискПоз
D114: ИМ | E114: =INDEX($E$101:$E$109,MATCH($H114,$I$101:$I$109,0)) -> КАНАДА | G114: тыс. шт. | H114: 1 | I114: =VLOOKUP($H114,$I$101:$J$109,2,FALSE) -> 5626.2 | J114: =INDEX($J$101:$J$109,MATCH($H114,$I$101:$I$109,0)) -> 5626.2
D115: ИМ | E115: =INDEX($E$101:$E$109,MATCH($H115,$I$101:$I$109,0)) -> ГЕРМАНИЯ | G115: тыс. шт. | H115: =H114+1 -> 2 | I115: =VLOOKUP($H115,$I$101:$J$109,2,FALSE) -> 5140.9 | J115: =INDEX($J$101:$J$109,MATCH($H115,$I$101:$I$109,0)) -> 5140.9
D116: ИМ | E116: =INDEX($E$101:$E$109,MATCH($H116,$I$101:$I$109,0)) -> ВЕНГРИЯ | G116: тыс. шт. | H116: =H115+1 -> 3 | I116: =VLOOKUP($H116,$I$101:$J$109,2,FALSE) -> 3113.7 | J116: =INDEX($J$101:$J$109,MATCH($H116,$I$101:$I$109,0)) -> 3113.7
D117: ИМ | E117: =INDEX($E$101:$E$109,MATCH($H117,$I$101:$I$109,0)) -> СЛОВАКИЯ | G117: тыс. шт. | H117: =H116+1 -> 4 | I117: =VLOOKUP($H117,$I$101:$J$109,2,FALSE) -> 1941.2 | J117: =INDEX($J$101:$J$109,MATCH($H117,$I$101:$I$109,0)) -> 1941.2
D118: ИМ | E118: =INDEX($E$101:$E$109,MATCH($H118,$I$101:$I$109,0)) -> ФРАНЦИЯ | G118: тыс. шт. | H118: =H117+1 -> 5 | I118: =VLOOKUP($H118,$I$101:$J$109,2,FALSE) -> 1530 | J118: =INDEX($J$101:$J$109,MATCH($H118,$I$101:$I$109,0)) -> 1530
D119: ИМ | E119: =INDEX($E$101:$E$109,MATCH($H119,$I$101:$I$109,0)) -> СОЕДИНЕННОЕ КОРОЛЕВСТВО | G119: тыс. шт. | H119: =H118+1 -> 6 | I119: =VLOOKUP($H119,$I$101:$J$109,2,FALSE) -> 644.6 | J119: =INDEX($J$101:$J$109,MATCH($H119,$I$101:$I$109,0)) -> 644.6
D120: ИМ | E120: =INDEX($E$101:$E$109,MATCH($H120,$I$101:$I$109,0)) -> ИТАЛИЯ | G120: тыс. шт. | H120: =H119+1 -> 7 | I120: =VLOOKUP($H120,$I$101:$J$109,2,FALSE) -> 363 | J120: =INDEX($J$101:$J$109,MATCH($H120,$I$101:$I$109,0)) -> 363
D121: ИМ | E121: =INDEX($E$101:$E$109,MATCH($H121,$I$101:$I$109,0)) -> ИСПАНИЯ | G121: тыс. шт. | H121: =H120+1 -> 8 | I121: =VLOOKUP($H121,$I$101:$J$109,2,FALSE) -> 156 | J121: =INDEX($J$101:$J$109,MATCH($H121,$I$101:$I$109,0)) -> 156
D122: ИМ | E122: =INDEX($E$101:$E$109,MATCH($H122,$I$101:$I$109,0)) -> РОССИЯ | G122: тыс. шт. | H122: =H121+1 -> 9 | I122: =VLOOKUP($H122,$I$101:$J$109,2,FALSE) -> 0 | J122: =INDEX($J$101:$J$109,MATCH($H122,$I$101:$I$109,0)) -> 0
E123: Всего | G123: тыс. шт. | I123: =SUM(I114:I122) -> 18515.6
C125: Важно !
D126: ВПР и ГПР позволяют работать только с одним условием
D127: ВПР и ГПР искомое значения обязательно должно быть в первом столбце/строке
D128: Индекс+ПоискПоз - несколько условий + не имеет значение положением строк/столбоц
D129: Для всех функций - обязательно проверять единственность искомого значения (функции берут только первое)
B131: Hints
C133: 1 | D133: Если долго пересчитывается:
E134: Формулы → Параметры вычислений → Вручную
E135: Shift+F9 - пересчет листа
E136: F9 - пересчет книги

Sheet Декларации_Исх. данные
BT1: Пример
B2: Учет | C2: D1 Дата выпуска груза | D2: Месяц | E2: ND Номер декларации на товары | F2: 071 Таможня оформления ДТ | G2: 072 Дата ДТ | H2: 073 Порядковый № ДТ | I2: 011 ИМ.ЭК - направление перемещения | J2: 012 Основной таможенный режим | K2: 013 Дополнительный признак | L2: 020 ОГРН.ОГРНИП отправителя | M2: 021 ИНН отправителя | N2: 022 Наименование.ФИО отправителя | O2: 023 Адрес отправителя | P2: 024 ОКАТО отправителя | Q2: 027 КПП отправителя | R2: 03 Листов ДТ | S2: 04 Спецификаций ДТ | T2: 05 Товаров всего | U2: 06 Мест товара всего | V2: 080 ОГРН.ОГРНИП получателя | W2: 081 ИНН получателя | X2: 082 Наименование.ФИО получателя | Y2: 083 Адрес получателя | Z2: 084 ОКАТО получателя | AA2: 087 КПП получателя | AB2: 090 ОГРН.ОГРНИП контрактодержателя | AC2: 091 ИНН контрактодержателя | AD2: 092 Наименование.ФИО контрактодержателя | AE2: 093 Адрес контрактодержателя | AF2: 094 ОКАТО контрактодержателя | AG2: 097 КПП контрактодержателя | AH2: 11 Код торгующей страны | AI2: 11 Торгующая страна | AJ2: 12 Общая таможенная стоимость | AK2: 140 ОГРН.ОГРНИП декларанта | AL2: 141 ИНН контрактодержателя | AM2: 142 Наименование.ФИО декларанта | AN2: 143 Адрес контрактодержателя | AO2: 144 ОКАТО контрактодержателя | AP2: 147 КПП контрактодержателя | AQ2: 15А Код страны отправления | AR2: 15 Страна отправления | AS2: 16 Страна происхождения | AT2: 17А Код страны назначения | AU2: 17 Страна назначения | AV2: 18 Кол-во транспорта при отправлении | AW2: 19 Признак контейнерных перевозок 0ю1 | AX2: 202 Условие поставки | AY2: 2021 Пункт поставки товара | AZ2: 21 Кол-во трансп на границе | BA2: 221 Валюта контракта | BB2: 222 Общая фактурная стоимость | BC2: 2220 Общая фактурная стоимость, руб | BD2: 226 Статистическая стоимость суммарная | BE2: 23 Курс валюты | BF2: 24 Характер сделки | BG2: 25 Вид транспортного средства | BH2: 28 ОКПО банка.паспорт сделки | BI2: 29 Таможня на границе | BJ2: 300 Тип информации | BK2: 301 № свидетельства СВХ.ТС | BL2: 302 Вид документа.Вид ТС | BM2: 30POST Индекс места нахождения товара | BN2: 30SUBD Регион | BO2: 30CITY Населенный пункт | BP2: 30STREET Адрес местонахождения товара | BQ2: 3012 Таможня в зоне которой склад | BR2: 3 Порядковый № листа ДТ | BS2: 31_1 Описание и характеристика товара | BT2: Индей | BU2: Индюш | BV2: Индейка | BW2: 31_11 Товарный знак | BX2: 31_12 Наименование фирмы изготовителя | BY2: 31_2 Кол-во мест товара | BZ2: 31_3 Кол-во контейнеров | CA2: 31_7 Кол-во товара в доп ед. измерения | CB2: 31_71 Дополнительная единица | CC2: 31_8 Кол-во товара в доп единице | CD2: 31_81 Дополнительная единица | CE2: 32 Номер товара по ДТ | CF2: 33 Код товара по ТН ВЭД РФ | CG2: 331 Признак нетарифного регулирования | CH2: 332 Признак объекта интеллект собственности | CI2: 34 Код страны происхождения | CJ2: 35 Вес брутто, кг | CK2: 36 Преференции | CL2: 37 Процедура | CM2: 38 Вес нетто, кг | CN2: 39 Квота | CO2: 391 Код валюты квоты | CP2: 392 Единица измерения квоты | CQ2: 42 Фактурная стоимость | CR2: 420 Фактурная стоимость, руб | CS2: 43 Признак корректировки таможенной стоимости (КТС) | CT2: 431 Метод определения таможенной стоимости | CU2: 45 Таможенная стоимость | CV2: 46 Статистическая стоимость | CW2: D0 Код завршения таможенного оформления | CX2: USD/KG Статистическая стоимость, USD/Dtc НЕТТО, кг | CY2: 541 Свидетельство таможенного брокера | CZ2: 5411 Договор брокера с декларантом | DA2: 5441 ФИО заполнившего ДТ | DB2: ЛНП выпускающего инспектора | DC2: ND_DEL Признак удаления декларации
B3: 1 | C3: 08.08.2023 | D3: 8 | E3: 10013160/080823/3352101 | F3: 10013160 | G3: 08.08.2023 | H3: 3352101 | I3: ИМ | J3: 40 | N3: NAGISZ ZRT. | O3: 4181, , NADUDVAR, FO UT 119, | T3: 1 | U3: 591 | V3: 1047796588146 | W3: 7710553010 | X3: ООО "АГРОИМПОРТ" | Y3: 143421, МОСКОВСКАЯ ОБЛ., КРАСНОГОРСКИЙ Р-Н, 26 КМ А/Д "БАЛТИЯ", БЦ "РИГА-ЛЕНД", | Z3: 46000 | AA3: 502401001 | AB3: 1047796588146 | AC3: 7710553010 | AD3: ООО "АГРОИМПОРТ" | AE3: 143421, МОСКОВСКАЯ ОБЛ., КРАСНОГОРСКИЙ Р-Н, 26 КМ А/Д "БАЛТИЯ", БЦ "РИГА-ЛЕНД", | AF3: 46000 | AG3: 502401001 | AH3: HU | AI3: ВЕНГРИЯ | AJ3: 15945264 | AK3: 1047796588146 | AL3: 7710553010 | AM3: ООО "АГРОИМПОРТ" | AN3: 143421, МОСКОВСКАЯ ОБЛ., КРАСНОГОРСКИЙ Р-Н, 26 КМ А/Д "БАЛТИЯ", БЦ "РИГА-ЛЕНД", | AO3: 46000 | AP3: 502401001 | AQ3: HU | AR3: ВЕНГРИЯ | AS3: ВЕНГРИЯ | AT3: RU | AU3: РОССИЯ | AW3: 0 | AX3: FCA | AY3: NADUDVAR | BA3: EUR | BB3: 147750 | BE3: 106.0543 | BI3: - | BJ3: 99 | BQ3: 10413090 т/п Пензенский областной | BS3: ИНДЮШАЧЬИ ЯЙЦА ДЛЯ ИНКУБАЦИИ, ОПЛОДОТВОРЕННЫЕ, MELEAGRIS GALLOPAVO L., ПОРОДА БЕЛАЯ ШИРОКОГРУДАЯ КРОССА БИГ-6, РАЗМЕЩЕНЫ С ЦЕЛЬЮ ПРЕДОТВРАЩЕНИЯ БОЯ И УНИЧТОЖЕНИЯ В КАРТОННЫХ КОРОБКАХ | BT3: =MIN(1,IFERROR(SEARCH(BT$2,$BS3),0)) -> 0 | BU3: =MIN(1,IFERROR(SEARCH(BU$2,$BS3),0)) -> 1 | BV3: =MAX(BT3,BU3) -> 1 | BW3: ОТСУТСТВУЕТ | BX3: NAGISZ ZRT. | BY3: 591 | BZ3: 0 | CA3: 118200 | CB3: ШТ | CE3: 1 | CF3: 0407191100 | CI3: HU | CJ3: 13002 | CK3: ОООО-ЛП | CL3: 4000000 | CM3: 12411 | CN3: 0 | CQ3: 147750 | CS3: 0 | CT3: 1 | CU3: 15945264 | CV3: 165121.59 | CW3: 10 | CX3: 13.3 | DB3: 1432
B4: 1 | C4: 05.08.2023 | D4: 8 | E4: 10013160/050823/3349274 | F4: 10013160 | G4: 05.08.2023 | H4: 3349274 | I4: ИМ | J4: 40 | N4: NAGISZ ZRT. | O4: 4181, , NADUDVAR, FO UT 119, | T4: 1 | U4: 326 | V4: 1047796588146 | W4: 7710553010 | X4: ООО "АГРОИМПОРТ" | Y4: 143421, МОСКОВСКАЯ ОБЛ., КРАСНОГОРСКИЙ Р-Н, 26 КМ А/Д "БАЛТИЯ", БЦ "РИГА-ЛЕНД", | Z4: 46000 | AA4: 502401001 | AB4: 1047796588146 | AC4: 7710553010 | AD4: ООО "АГРОИМПОРТ" | AE4: 143421, МОСКОВСКАЯ ОБЛ., КРАСНОГОРСКИЙ Р-Н, 26 КМ А/Д "БАЛТИЯ", БЦ "РИГА-ЛЕНД", | AF4: 46000 | AG4: 502401001 | AH4: HU | AI4: ВЕНГРИЯ | AJ4: 8920298.6 | AK4: 1047796588146 | AL4: 7710553010 | AM4: ООО "АГРОИМПОРТ" | AN4: 143421, МОСКОВСКАЯ ОБЛ., КРАСНОГОРСКИЙ Р-Н, 26 КМ А/Д "БАЛТИЯ", БЦ "РИГА-ЛЕНД", | AO4: 46000 | AP4: 502401001 | AQ4: HU | AR4: ВЕНГРИЯ | AS4: ВЕНГРИЯ | AT4: RU | AU4: РОССИЯ | AW4: 0 | AX4: FCA | AY4: NADUDVAR | BA4: EUR | BB4: 83456 | BE4: 103.8379 | BI4: - | BJ4: СВ | BQ4: 10113020 т/п Вяземский | BS4: ИНДЮШАЧЬИ ЯЙЦА ДЛЯ ИНКУБАЦИИ, ОПЛОДОТВОРЕННЫЕ, MELEAGRIS GALLOPAVO L., ПОРОДА БЕЛАЯ ШИРОКОГРУДАЯ КРОССА БИГ-6, РАЗМЕЩЕНЫ С ЦЕЛЬЮ ПРЕДОТВРАЩЕНИЯ БОЯ И УНИЧТОЖЕНИЯ В КАРТОННЫХ КОРОБКАХ | BT4: =MIN(1,IFERROR(SEARCH(BT$2,$BS4),0)) -> 0 | BU4: =MIN(1,IFERROR(SEARCH(BU$2,$BS4),0)) -> 1 | BV4: =MAX(BT4,BU4) -> 1 | BW4: ОТСУТСТВУЕТ | BX4: NAGISZ ZRT. | BY4: 326 | CA4: 65200 | CB4: ШТ | CE4: 1 | CF4: 0407191100 | CI4: HU | CJ4: 7172 | CK4: ОООО-ЛП | CL4: 4000000 | CM4: 6846 | CN4: 0 | CQ4: 83456 | CU4: 8920298.6 | CV4: 94088.43 | CW4: 10 | CX4: 13.74 | DB4: 1390
B5: 1 | C5: 01.08.2023 | D5: 8 | E5: 10013160/010823/3342116 | F5: 10013160 | G5: 01.08.2023 | H5: 3342116 | I5: ИМ | J5: 40 | N5: NAGISZ ZRT. | O5: 4181, , NADUDVAR, FO UT 119, | T5: 1 | U5: 330 | V5: 1047796588146 | W5: 7710553010 | X5: ООО "АГРОИМПОРТ" | Y5: 143421, МОСКОВСКАЯ ОБЛ., КРАСНОГОРСКИЙ Р-Н, 26 КМ А/Д "БАЛТИЯ", БЦ "РИГА-ЛЕНД", | Z5: 46000 | AA5: 502401001 | AB5: 1047796588146 | AC5: 7710553010 | AD5: ООО "АГРОИМПОРТ" | AE5: 143421, МОСКОВСКАЯ ОБЛ., КРАСНОГОРСКИЙ Р-Н, 26 КМ А/Д "БАЛТИЯ", БЦ "РИГА-ЛЕНД", | AF5: 46000 | AG5: 502401001 | AH5: HU | AI5: ВЕНГРИЯ | AJ5: 8590232.3 | AK5: 1047796588146 | AL5: 7710553010 | AM5: ООО "АГРОИМПОРТ" | AN5: 143421, МОСКОВСКАЯ ОБЛ., КРАСНОГОРСКИЙ Р-Н, 26 КМ А/Д "БАЛТИЯ", БЦ "РИГА-ЛЕНД", | AO5: 46000 | AP5: 502401001 | AQ5: HU | AR5: ВЕНГРИЯ | AS5: ВЕНГРИЯ | AT5: RU | AU5: РОССИЯ | AW5: 0 | AX5: FCA | AY5: NADUDVAR | BA5: EUR | BB5: 82500 | BE5: 100.9428 | BI5: - | BJ5: Ин | BQ5: 10413090 т/п Пензенский областной | BS5: ИНДЮШАЧЬИ ЯЙЦА ДЛЯ ИНКУБАЦИИ, ОПЛОДОТВОРЕННЫЕ, MELEAGRIS GALLOPAVO L., ПОРОДА БЕЛАЯ ШИРОКОГРУДАЯ КРОССА БИГ-6, РАЗМЕЩЕНЫ С ЦЕЛЬЮ ПРЕДОТВРАЩЕНИЯ БОЯ И УНИЧТОЖЕНИЯ В КАРТОННЫХ КОРОБКАХ | BT5: =MIN(1,IFERROR(SEARCH(BT$2,$BS5),0)) -> 0 | BU5: =MIN(1,IFERROR(SEARCH(BU$2,$BS5),0)) -> 1 | BV5: =MAX(BT5,BU5) -> 1 | BW5: ОТСУТСТВУЕТ | BX5: NAGISZ ZRT. | BY5: 330 | CA5: 66000 | CB5: ШТ | CE5: 1 | CF5: 0407191100 | CI5: HU | CJ5: 7260 | CK5: ОООО-ЛП | CL5: 4000000 | CM5: 6930 | CN5: 0 | CQ5: 82500 | CU5: 8590232.3 | CV5: 93787.71 | CW5: 10 | CX5: 13.53 | DB5: 1372
B6: 1 | C6: 30.08.2023 | D6: 8 | E6: 10005030/300823/3232114 | F6: 10005030 | G6: 30.08.2023 | H6: 3232114 | I6: ИМ | J6: 40 | N6: CUDDY FARMS LIMITED 2008 | O6: 28429, ONTARIO, STRATHROY, N7G3H6 CENTRE ROAD RR, | T6: 1 | U6: 543 | V6: 1047796588146 | W6: 7710553010 | X6: ООО "АГРОИМПОРТ" | Y6: 143421, МОСКОВСКАЯ ОБЛ., КРАСНОГОРСКИЙ Р-Н, 26 КМ А/Д "БАЛТИЯ", БЦ "РИГА-ЛЕНД", | Z6: 46000 | AA6: 502401001 | AB6: 1047796588146 | AC6: 7710553010 | AD6: ООО "АГРОИМПОРТ" | AE6: 143421, МОСКОВСКАЯ ОБЛ., КРАСНОГОРСКИЙ Р-Н, 26 КМ А/Д "БАЛТИЯ", БЦ "РИГА-ЛЕНД", | AF6: 46000 | AG6: 502401001 | AH6: CA | AI6: КАНАДА | AJ6: 15620192 | AK6: 1047796588146 | AL6: 7710553010 | AM6: ООО "АГРОИМПОРТ" | AN6: 143421, МОСКОВСКАЯ ОБЛ., КРАСНОГОРСКИЙ Р-Н, 26 КМ А/Д "БАЛТИЯ", БЦ "РИГА-ЛЕНД", | AO6: 46000 | AP6: 502401001 | AQ6: CA | AR6: КАНАДА | AS6: КАНАДА | AT6: RU | AU6: РОССИЯ | AW6: 0 | AX6: CPT | AY6: МОСКВА | BA6: EUR | BB6: 150954 | BE6: 103.4765 | BG6: 40 | BI6: - | BJ6: 11 | BQ6: 10001020 т/п Аэропорт Внуково (грузовой) | BS6: ИНДЮШАЧЬИ ЯЙЦА ДЛЯ ИНКУБАЦИИ. ПОРОДА MELEAGRIS GALLOPAVO L. "БЕЛАЯ ШИРОКОГРУДАЯ" (HCONV), КРОСС ХАЙБРИД КОНВЕРТЕР, КАТЕГОРИЯ БРОЙЛЕР, НЕ ПЛЕМЕННЫЕ, РАЗМЕЩЕНЫ В КАРТОННЫХ КАССЕТАХ ПО ДВАДЦАТЬ (20) ЯИЦ В КАЖДОЙ И УПАКОВАНО В ОРИГИНАЛЬНЫЕ КАРТОННЫЕ | BT6: =MIN(1,IFERROR(SEARCH(BT$2,$BS6),0)) -> 0 | BU6: =MIN(1,IFERROR(SEARCH(BU$2,$BS6),0)) -> 1 | BV6: =MAX(BT6,BU6) -> 1 | BW6: ОТСУТСТВУЕТ | BX6: CUDDY FARMS LIMITED 2008 | BY6: 543 | BZ6: 0 | CA6: 108600 | CB6: ШТ | CE6: 1 | CF6: 0407191100 | CI6: CA | CJ6: 10860 | CK6: ОООО-ЛП | CL6: 4000000 | CM6: 9774 | CN6: 0 | CQ6: 150954 | CS6: 0 | CT6: 1 | CU6: 15620192 | CV6: 163208.45 | CW6: 10 | CX6: 16.7 | DB6: 1069
B7: 1 | C7: 20.08.2023 | D7: 8 | E7: 10005030/200823/3221966 | F7: 10005030 | G7: 20.08.2023 | H7: 3221966 | I7: ИМ | J7: 40 | N7: CUDDY FARMS LIMITED 2008 | O7: , , RR #5-28429 CENTRE ROAD, STRATHROY ON N76 3H6, | T7: 1 | U7: 282 | W7: 263034881 | X7: ООО "СПП" | Y7: 453854, РЕСПУБЛИКА БАШКОРТОСТАН, М.Р-Н МЕЛЕУЗОВСКИЙ, Г.МЕЛЕУЗ, УЛ.СОВХОЗНАЯ, ЗДА | AC7: 263034881 | AD7: ООО "СПП" | AE7: 453854, РЕСПУБЛИКА БАШКОРТОСТАН, М.Р-Н МЕЛЕУЗОВСКИЙ, Г.МЕЛЕУЗ, УЛ.СОВХОЗНАЯ, ЗДА | AH7: CA | AI7: КАНАДА | AJ7: 8756929.4 | AL7: 263034881 | AM7: ООО "СПП" | AN7: 453854, РЕСПУБЛИКА БАШКОРТОСТАН, М.Р-Н МЕЛЕУЗОВСКИЙ, Г.МЕЛЕУЗ, УЛ.СОВХОЗНАЯ, ЗДА | AQ7: CA | AR7: КАНАДА | AS7: КАНАДА | AT7: RU | AU7: РОССИЯ | AW7: 0 | AX7: CPT | AY7: МОСКВА | BA7: EUR | BB7: 86292 | BE7: 101.4802 | BG7: 40 | BI7: - | BJ7: 11 | BQ7: 10001020 т/п Аэропорт Внуково (грузовой) | BS7: ОПЛОДОТВОРЕННЫЕ ЯЙЦА ИНДЮШАЧЬИ ДЛЯ ИНКУБАЦИИ, КОД ОКП 98 4766 (ОКПД2 01.47.23.140): ЦЕЛЬ ВВОЗА - ДЛЯ ИНКУБИРОВАНИЯ. | BT7: =MIN(1,IFERROR(SEARCH(BT$2,$BS7),0)) -> 0 | BU7: =MIN(1,IFERROR(SEARCH(BU$2,$BS7),0)) -> 1 | BV7: =MAX(BT7,BU7) -> 1 | BW7: CUDDY FARMS | BX7: CUDDY FARMS LIMITED 2008 | BY7: 282 | BZ7: 0 | CA7: 56400 | CB7: ШТ | CE7: 1 | CF7: 0407191100 | CI7: CA | CJ7: 5640 | CK7: ОООО-ЛП | CL7: 4000000 | CM7: 5076 | CN7: 0 | CQ7: 86292 | CS7: 0 | CT7: 1 | CU7: 8756929.4 | CV7: 93752.56 | CW7: 10 | CX7: 18.47 | DB7: 473
B8: 1 | C8: 19.08.2023 | D8: 8 | E8: 10005030/190823/3221665 | F8: 10005030 | G8: 19.08.2023 | H8: 3221665 | I8: ИМ | J8: 40 | N8: CUDDY FARMS LIMITED 2008 | O8: N7G3H6, ONTARIO, STRATHROY, 28429 CENTRAL ROAD, R. | T8: 1 | U8: 120 | V8: 1177746508235 | W8: 7751046971 | X8: ООО "ЭГМАРТ" | Y8: 108841, , Г. МОСКВА, Г. ТРОИЦК, УЛ. ТЕКСТИЛЬЩИКОВ, ДОМ 3 КОР. 3, ОФ. 4, | Z8: 45000 | AA8: 775101001 | AB8: 1177746508235 | AC8: 7751046971 | AD8: ООО "ЭГМАРТ" | AE8: 108841, , Г. МОСКВА, Г. ТРОИЦК, УЛ. ТЕКСТИЛЬЩИКОВ, ДОМ 3 КОР. 3, ОФ. 4, | AF8: 45000 | AG8: 775101001 | AH8: CA | AI8: КАНАДА | AJ8: 3701997.7 | AK8: 1177746508235 | AL8: 7751046971 | AM8: ООО "ЭГМАРТ" | AN8: 108841, , Г. МОСКВА, Г. ТРОИЦК, УЛ. ТЕКСТИЛЬЩИКОВ, ДОМ 3 КОР. 3, ОФ. 4, | AO8: 45000 | AP8: 775101001 | AQ8: CA | AR8: КАНАДА | AS8: КАНАДА | AT8: RU | AU8: РОССИЯ | AW8: 0 | AX8: CPT | AY8: Г МОСКВА | BA8: EUR | BB8: 36480 | BE8: 101.4802 | BG8: 40 | BI8: - | BJ8: 11 | BQ8: 10001020 т/п Аэропорт Внуково (грузовой) | BS8: ОПЛОДОТВОРЕННЫЕ ИНКУБАЦИОННЫЕ ЯЙЦА ИНДЕЕК (MELEAGRIS GALLOPAVAL.), ДЛЯ ИНКУБАЦИИ И ВЫВЕДЕНИЯ ИНДЕЕК, ДЛЯ ПОСЛЕДУЮЩЕГО ВЫРАЩИВАНИЯ И УБОЯ НА МЯСО. КРОССА "HYBRID CONVERTER"(БЕЛАЯ ШИРОКОГРУДАЯ), СВЕЖИЕ (В КОРОБКЕ ПО 200 ШТ.): | BT8: =MIN(1,IFERROR(SEARCH(BT$2,$BS8),0)) -> 0 | BU8: =MIN(1,IFERROR(SEARCH(BU$2,$BS8),0)) -> 0 | BV8: =MAX(BT8,BU8) -> 0 | BW8: CUDDY | BX8: CUDDY FARMS LIMITED 2008 | BY8: 120 | BZ8: 0 | CA8: 24000 | CB8: ШТ | CE8: 1 | CF8: 0407191100 | CI8: CA | CJ8: 2510 | CK8: ОООО-ЛП | CL8: 4000000 | CM8: 2160 | CN8: 0 | CQ8: 36480 | CS8: 0 | CT8: 1 | CU8: 3701997.7 | CV8: 39633.96 | CW8: 10 | CX8: 18.35 | DB8: 610
B9: 1 | C9: 19.08.2023 | D9: 8 | E9: 10005030/190823/3221568 | F9: 10005030 | G9: 19.08.2023 | H9: 3221568 | I9: ИМ | J9: 40 | N9: AVIAGEN TURKEYS LTD. | O9: , CHESTER CH3 9GA, TATTENHALL, CHOWLEY OAK BUSINES | T9: 1 | U9: 290 | V9: 1047796588146 | W9: 7710553010 | X9: ООО "АГРОИМПОРТ" | Y9: 143421, МОСКОВСКАЯ ОБЛ., КРАСНОГОРСКИЙ Р-Н, 26 КМ А/Д "БАЛТИЯ", БЦ "РИГА-ЛЕНД", | Z9: 46000 | AA9: 502401001 | AB9: 1047796588146 | AC9: 7710553010 | AD9: ООО "АГРОИМПОРТ" | AE9: 143421, МОСКОВСКАЯ ОБЛ., КРАСНОГОРСКИЙ Р-Н, 26 КМ А/Д "БАЛТИЯ", БЦ "РИГА-ЛЕНД", | AF9: 46000 | AG9: 502401001 | AH9: GB | AI9: СОЕДИНЕННОЕ КОРОЛЕВСТВО | AJ9: 39418969 | AK9: 1047796588146 | AL9: 7710553010 | AM9: ООО "АГРОИМПОРТ" | AN9: 143421, МОСКОВСКАЯ ОБЛ., КРАСНОГОРСКИЙ Р-Н, 26 КМ А/Д "БАЛТИЯ", БЦ "РИГА-ЛЕНД", | AO9: 46000 | AP9: 502401001 | AQ9: GB | AR9: СОЕДИНЕННОЕ КОРОЛЕВСТВО | AS9: СОЕДИНЕННОЕ КОРОЛЕВСТВО | AT9: RU | AU9: РОССИЯ | AW9: 0 | AX9: DAP | AY9: МОСКВА | BA9: EUR | BB9: 388440 | BE9: 101.4802 | BG9: 40 | BI9: - | BJ9: 11 | BQ9: 10001020 т/п Аэропорт Внуково (грузовой) | BS9: ПЛЕМЕННЫЕ ИНДЮШАЧЬИ ЯЙЦА ДЛЯ ИНКУБАЦИИ, ОПЛОДОТВОРЁННЫЕ, ДЛЯ ВЫВЕДЕНИЯ РОДИТЕЛЬСКОГО СТАДА MELEAGRIS GALLOPAVO L. ПОРОДЫ БЕЛАЯ ШИРОКОГРУДАЯ BIG 6, РАЗМЕЩЕННЫЕ С ЦЕЛЬЮ ПРЕДОТВРАЩЕНИЯ БОЯ И УНИЧТОЖЕНИЯ В КАРТОННЫХ КОРОБКАХ. | BT9: =MIN(1,IFERROR(SEARCH(BT$2,$BS9),0)) -> 0 | BU9: =MIN(1,IFERROR(SEARCH(BU$2,$BS9),0)) -> 1 | BV9: =MAX(BT9,BU9) -> 1 | BW9: ... | BX9: AVIAGEN TURKEYS INC. | BY9: 290 | BZ9: 0 | CA9: 58000 | CB9: ШТ | CE9: 1 | CF9: 0407191100 | CI9: GB | CJ9: 6090 | CK9: ОООО-ПС | CL9: 4000000 | CM9: 5800 | CN9: 0 | CQ9: 388440 | CS9: 0 | CT9: 1 | CU9: 39418969 | CV9: 422023.4 | CW9: 10 | CX9: 72.76 | DB9: 678
B10: 1 | C10: 19.08.2023 | D10: 8 | E10: 10005030/190823/3221529 | F10: 10005030 | G10: 19.08.2023 | H10: 3221529 | I10: ИМ | J10: 40 | N10: CUDDY FARMS, A DIVISION OF HENDRIX GENETICS LIMITED | O10: N7G3H6, ONTARIO, STRATHROY, ROUTE # 5, | T10: 1 | U10: 120 | V10: 1132651023570 | W10: 2624801566 | X10: ООО "ПТИЧИЙ ДВОР" | Y10: 356800, СТАВРОПОЛЬСКИЙ КРАЙ, Г. БУДЕННОВСК, УЛ. ВОДНИКОВ, Д.7, | Z10: 07000 | AA10: 262401001 | AB10: 1132651023570 | AC10: 2624801566 | AD10: ООО "ПТИЧИЙ ДВОР" | AE10: 356800, СТАВРОПОЛЬСКИЙ КРАЙ, Г. БУДЕННОВСК, УЛ. ВОДНИКОВ, Д.7, | AF10: 07000 | AG10: 262401001 | AH10: CA | AI10: КАНАДА | AJ10: 3701997.7 | AK10: 1132651023570 | AL10: 2624801566 | AM10: ООО "ПТИЧИЙ ДВОР" | AN10: 356800, СТАВРОПОЛЬСКИЙ КРАЙ, Г. БУДЕННОВСК, УЛ. ВОДНИКОВ, Д.7, | AO10: 07000 | AP10: 262401001 | AQ10: CA | AR10: КАНАДА | AS10: КАНАДА | AT10: RU | AU10: РОССИЯ | AW10: 0 | AX10: CPT | AY10: МОСКВА | BA10: EUR | BB10: 36480 | BE10: 101.4802 | BG10: 40 | BI10: - | BJ10: 11 | BQ10: 10001020 т/п Аэропорт Внуково (грузовой) | BS10: СВЕЖИЕ ОПЛОДОТВОРЕННЫЕ ИНКУБАЦИОННЫЕ ЯЙЦА ИНДЕЙКИ (TURKEY HATCHING EGGS), ЛАТИНСКОЕ НАЗВАНИЕ ВИДА "MELEAGRIS GALLOPAVO L." ПОРОДЫ ХАЙБРИД КОНВЕРТЕР, ДЛЯ ИНКУБАЦИИ, ДЛЯ ПОСЛЕДУЮЩЕГО ВЫРАЩИВАНИЯ И УБОЯ НА МЯСО | BT10: =MIN(1,IFERROR(SEARCH(BT$2,$BS10),0)) -> 1 | BU10: =MIN(1,IFERROR(SEARCH(BU$2,$BS10),0)) -> 0 | BV10: =MAX(BT10,BU10) -> 1 | BW10: ОТСУТСТВУЕТ | BX10: CUDDY FARMS LIMITED 2008, ПЛЕМЗАВОД: KRS0000042053 | BY10: 120 | BZ10: 0 | CA10: 24000 | CB10: ШТ | CE10: 1 | CF10: 0407191100 | CI10: CA | CJ10: 2400 | CK10: ОООО-ЛП | CL10: 4000000 | CM10: 2160 | CN10: 0 | CQ10: 36480 | CS10: 0 | CT10: 1 | CU10: 3701997.7 | CV10: 39633.96 | CW10: 10 | CX10: 18.35 | DB10: 636
B11: 1 | C11: 17.08.2023 | D11: 8 | E11: 10005030/170823/3220327 | F11: 10005030 | G11: 17.08.2023 | H11: 3220327 | I11: ИМ | J11: 40 | N11: CUDDY FARMS LIMITED 2008 | O11: , , RR #5-28429 CENTRE ROAD, STRATHROY ON N76 3H6, | T11: 1 | U11: 423 | W11: 263034881 | X11: ООО "СПП" | Y11: 453854, РЕСПУБЛИКА БАШКОРТОСТАН, М.Р-Н МЕЛЕУЗОВСКИЙ, Г.МЕЛЕУЗ, УЛ.СОВХОЗНАЯ, ЗДА | AC11: 263034881 | AD11: ООО "СПП" | AE11: 453854, РЕСПУБЛИКА БАШКОРТОСТАН, М.Р-Н МЕЛЕУЗОВСКИЙ, Г.МЕЛЕУЗ, УЛ.СОВХОЗНАЯ, ЗДА | AH11: CA | AI11: КАНАДА | AJ11: 13676303 | AL11: 263034881 | AM11: ООО "СПП" | AN11: 453854, РЕСПУБЛИКА БАШКОРТОСТАН, М.Р-Н МЕЛЕУЗОВСКИЙ, Г.МЕЛЕУЗ, УЛ.СОВХОЗНАЯ, ЗДА | AQ11: CA | AR11: КАНАДА | AS11: КАНАДА | AT11: RU | AU11: РОССИЯ | AW11: 0 | AX11: CPT | AY11: МОСКВА | BA11: EUR | BB11: 129438 | BE11: 105.6591 | BG11: 40 | BI11: - | BJ11: 11 | BQ11: 10001020 т/п Аэропорт Внуково (грузовой) | BS11: ОПЛОДОТВОРЕННЫЕ ЯЙЦА ИНДЮШАЧЬИ ДЛЯ ИНКУБАЦИИ, КОД ОКП 98 4766 (ОКПД2 01.47.23.140): ЦЕЛЬ ВВОЗА - ДЛЯ ИНКУБИРОВАНИЯ. | BT11: =MIN(1,IFERROR(SEARCH(BT$2,$BS11),0)) -> 0 | BU11: =MIN(1,IFERROR(SEARCH(BU$2,$BS11),0)) -> 1 | BV11: =MAX(BT11,BU11) -> 1 | BW11: CUDDY FARMS | BX11: CUDDY FARMS LIMITED 2008 | BY11: 423 | BZ11: 0 | CA11: 84600 | CB11: ШТ | CE11: 1 | CF11: 0407191100 | CI11: CA | CJ11: 8460 | CK11: ОООО-ЛП | CL11: 4000000 | CM11: 7614 | CN11: 0 | CQ11: 129438 | CS11: 0 | CT11: 1 | CU11: 13676303 | CV11: 141423.64 | CW11: 10 | CX11: 18.57 | DB11: 953
B12: 1 | C12: 14.08.2023 | D12: 8 | E12: 10005030/140823/3216844 | F12: 10005030 | G12: 14.08.2023 | H12: 3216844 | I12: ИМ | J12: 40 | N12: CUDDY FARMS LIMITED 2008 | O12: 28429, ONTARIO, STRATHROY, N7G3H6 CENTRE ROAD RR, | T12: 1 | U12: 362 | V12: 1047796588146 | W12: 7710553010 | X12: ООО "АГРОИМПОРТ" | Y12: 143421, МОСКОВСКАЯ ОБЛ., КРАСНОГОРСКИЙ Р-Н, 26 КМ А/Д "БАЛТИЯ", БЦ "РИГА-ЛЕНД", | Z12: 46000 | AA12: 502401001 | AB12: 1047796588146 | AC12: 7710553010 | AD12: ООО "АГРОИМПОРТ" | AE12: 143421, МОСКОВСКАЯ ОБЛ., КРАСНОГОРСКИЙ Р-Н, 26 КМ А/Д "БАЛТИЯ", БЦ "РИГА-ЛЕНД", | AF12: 46000 | AG12: 502401001 | AH12: CA | AI12: КАНАДА | AJ12: 10865900 | AK12: 1047796588146 | AL12: 7710553010 | AM12: ООО "АГРОИМПОРТ" | AN12: 143421, МОСКОВСКАЯ ОБЛ., КРАСНОГОРСКИЙ Р-Н, 26 КМ А/Д "БАЛТИЯ", БЦ "РИГА-ЛЕНД", | AO12: 46000 | AP12: 502401001 | AQ12: CA | AR12: КАНАДА | AS12: КАНАДА | AT12: RU | AU12: РОССИЯ | AW12: 0 | AX12: CPT | AY12: МОСКВА | BA12: EUR | BB12: 100636 | BE12: 107.9723 | BG12: 40 | BI12: - | BJ12: 11 | BQ12: 10001020 т/п Аэропорт Внуково (грузовой) | BS12: ИНДЮШАЧЬИ ЯЙЦА ДЛЯ ИНКУБАЦИИ, ПОРОДА MELEAGRIS GALLOPAVO L. "БЕЛАЯ ШИРОКОГРУДАЯ" (HCONV), КРОСС ХАЙБРИД КОНВЕРТЕР. КАТЕГОРИЯ БРОЙЛЕР, НЕ ПЛЕМЕННЫЕ, РАЗМЕЩЕНЫ В КАРТОННЫХ КАССЕТАХ ПО ДВАДЦАТЬ (20) ЯИЦ В КАЖДОЙ И УПАКОВАНО В ОРИГИНАЛЬНЫЕ КАРТОННЫЕ | BT12: =MIN(1,IFERROR(SEARCH(BT$2,$BS12),0)) -> 0 | BU12: =MIN(1,IFERROR(SEARCH(BU$2,$BS12),0)) -> 1 | BV12: =MAX(BT12,BU12) -> 1 | BW12: ОТСУТСТВУЕТ | BX12: CUDDY FARMS LIMITED 2008 | BY12: 362 | BZ12: 0 | CA12: 72400 | CB12: ШТ | CE12: 1 | CF12: 0407191100 | CI12: CA | CJ12: 7432 | CK12: ОООО-ЛП | CL12: 4000000 | CM12: 6516 | CN12: 0 | CQ12: 100636 | CS12: 0 | CT12: 1 | CU12: 10865900 | CV12: 110643.28 | CW12: 10 | CX12: 16.98 | DB12: 993
B13: 1 | C13: 13.08.2023 | D13: 8 | E13: 10005030/130823/3215662 | F13: 10005030 | G13: 13.08.2023 | H13: 3215662 | I13: ИМ | J13: 40 | N13: CUDDY FARMS LIMITED 2008 | O13: , , RR #5-28429 CENTRE ROAD, STRATHROY ON N76 3H6, | T13: 1 | U13: 160 | V13: 1144813001046 | W13: 4805016071 | X13: ООО "КРИВЕЦ-ПТИЦА" | Y13: 399174, ЛИПЕЦКАЯ ОБЛ., ДОБРОВСКИЙ РАЙОН, СЕЛО КРИВЕЦ, УЛ. НОВАЯ, Д.2, ПОМЕЩЕНИЕ | Z13: 42000 | AA13: 480501001 | AB13: 1144813001046 | AC13: 4805016071 | AD13: ООО "КРИВЕЦ-ПТИЦА" | AE13: 399174, ЛИПЕЦКАЯ ОБЛ., ДОБРОВСКИЙ РАЙОН, СЕЛО КРИВЕЦ, УЛ. НОВАЯ, Д.2, ПОМЕЩЕНИЕ | AF13: 42000 | AG13: 480501001 | AH13: CA | AI13: КАНАДА | AJ13: 5182670.4 | AK13: 1144813001046 | AL13: 4805016071 | AM13: ООО "КРИВЕЦ-ПТИЦА" | AN13: 399174, ЛИПЕЦКАЯ ОБЛ., ДОБРОВСКИЙ РАЙОН, СЕЛО КРИВЕЦ, УЛ. НОВАЯ, Д.2, ПОМЕЩЕНИЕ | AO13: 42000 | AP13: 480501001 | AQ13: CA | AR13: КАНАДА | AS13: КАНАДА | AT13: RU | AU13: РОССИЯ | AW13: 0 | AX13: CPT | AY13: МОСКВА | BA13: EUR | BB13: 48000 | BE13: 107.9723 | BG13: 40 | BI13: - | BJ13: 11 | BQ13: 10001020 т/п Аэропорт Внуково (грузовой) | BS13: ОПЛОДОТВОРЕННЫЕ ЯЙЦА ИНДЮШАЧЬИ ДЛЯ ИНКУБАЦИИ, КОД ОКП 98 4766 (ОКПД2 01.47.23.140): ЦЕЛЬ ВВОЗА: ИНКУБИРОВАНИЕ И ДАЛЬНЕЙШЕЕ ВЫРАЩИВАНИЕ. | BT13: =MIN(1,IFERROR(SEARCH(BT$2,$BS13),0)) -> 0 | BU13: =MIN(1,IFERROR(SEARCH(BU$2,$BS13),0)) -> 1 | BV13: =MAX(BT13,BU13) -> 1 | BW13: CUDDY FARMS | BX13: CUDDY FARMS LIMITED 2008 | BY13: 160 | BZ13: 0 | CA13: 32000 | CB13: ШТ | CE13: 1 | CF13: 0407191100 | CI13: CA | CJ13: 3200 | CK13: ОООО-ЛП | CL13: 4000000 | CM13: 2880 | CN13: 0 | CQ13: 48000 | CS13: 0 | CT13: 1 | CU13: 5182670.4 | CV13: 52773.14 | CW13: 10 | CX13: 18.32 | DB13: 724
B14: 1 | C14: 12.08.2023 | D14: 8 | E14: 10005030/120823/3215350 | F14: 10005030 | G14: 12.08.2023 | H14: 3215350 | I14: ИМ | J14: 40 | N14: CUDDY FARMS A DIVISION OF HENDRIX GENETICS LTD | O14: N7G 3H6, ONTARIO, STRATHROY, CENTRE ROAD, RR#5, 28 | T14: 1 | U14: 380 | V14: 1116829006910 | W14: 6829076796 | X14: ООО "ТАМБОВСКАЯ ИНДЕЙКА" | Y14: 392000, ТАМБОВСКАЯ ОБЛ., ТАМБОВ, УЛ. СТУДЕНЕЦКАЯ, Д.16А, КОРП.1, ПОМ.16 | Z14: 68000 | AA14: 682901001 | AB14: 1116829006910 | AC14: 6829076796 | AD14: ООО "ТАМБОВСКАЯ ИНДЕЙКА" | AE14: 392000, ТАМБОВСКАЯ ОБЛ., ТАМБОВ, УЛ. СТУДЕНЕЦКАЯ, Д.16А, КОРП.1, ПОМ.16 | AF14: 68000 | AG14: 682901001 | AH14: CA | AI14: КАНАДА | AJ14: 12965314 | AK14: 1116829006910 | AL14: 6829076796 | AM14: ООО "ТАМБОВСКАЯ ИНДЕЙКА" | AN14: 392000, ТАМБОВСКАЯ ОБЛ., ТАМБОВ, УЛ. СТУДЕНЕЦКАЯ, Д.16А, КОРП.1, ПОМ.16 | AO14: 68000 | AP14: 682901001 | AQ14: CA | AR14: КАНАДА | AS14: КАНАДА | AT14: RU | AU14: РОССИЯ | AW14: 0 | AX14: CPT | AY14: МОСКВА | BA14: EUR | BB14: 120080 | BE14: 107.9723 | BG14: 40 | BI14: - | BJ14: 11 | BQ14: 10001020 т/п Аэропорт Внуково (грузовой) | BS14: ЯЙЦА ИНДЕЕК ДОМАШНИХ. СВЕЖИЕ, ОПЛОДОТВОРЕННЫЕ ДЛЯ ИНКУБАЦИИ, ПОРОДЫ HYBRID CONVERTER, НЕ ПЛЕМЕННЫЕ, ДЛЯ ПОСЛЕДУЮЩЕГО ВЫРАЩИВАНИЯ И УБОЯ НА МЯСО СВЕЖЕЕ, В КАРТОННЫХ КОРОБКАХ | BT14: =MIN(1,IFERROR(SEARCH(BT$2,$BS14),0)) -> 0 | BU14: =MIN(1,IFERROR(SEARCH(BU$2,$BS14),0)) -> 0 | BV14: =MAX(BT14,BU14) -> 0 | BW14: CUDDY | BX14: CUDDY FARMS | BY14: 380 | BZ14: 0 | CA14: 76000 | CB14: ШТ | CE14: 1 | CF14: 0407191100 | CI14: CA | CJ14: 7790 | CK14: ОООО-ЛП | CL14: 4000000 | CM14: 6840 | CN14: 0 | CQ14: 120080 | CS14: 0 | CT14: 1 | CU14: 12965314 | CV14: 132020.8 | CW14: 10 | CX14: 19.3 | DB14: 786
B15: 1 | C15: 12.08.2023 | D15: 8 | E15: 10005030/120823/3215210 | F15: 10005030 | G15: 12.08.2023 | H15: 3215210 | I15: ИМ | J15: 40 | N15: AVIAGEN TURKEYS LTD. | O15: , CHESTER CH3 9GA, TATTENHALL, CHOWLEY OAK BUSINES | T15: 1 | U15: 223 | V15: 1047796588146 | W15: 7710553010 | X15: ООО "АГРОИМПОРТ" | Y15: 143421, МОСКОВСКАЯ ОБЛ., КРАСНОГОРСКИЙ Р-Н, 26 КМ А/Д "БАЛТИЯ", БЦ "РИГА-ЛЕНД", | Z15: 46000 | AA15: 502401001 | AB15: 1047796588146 | AC15: 7710553010 | AD15: ООО "АГРОИМПОРТ" | AE15: 143421, МОСКОВСКАЯ ОБЛ., КРАСНОГОРСКИЙ Р-Н, 26 КМ А/Д "БАЛТИЯ", БЦ "РИГА-ЛЕНД", | AF15: 46000 | AG15: 502401001 | AH15: GB | AI15: СОЕДИНЕННОЕ КОРОЛЕВСТВО | AJ15: 32250030 | AK15: 1047796588146 | AL15: 7710553010 | AM15: ООО "АГРОИМПОРТ" | AN15: 143421, МОСКОВСКАЯ ОБЛ., КРАСНОГОРСКИЙ Р-Н, 26 КМ А/Д "БАЛТИЯ", БЦ "РИГА-ЛЕНД", | AO15: 46000 | AP15: 502401001 | AQ15: GB | AR15: СОЕДИНЕННОЕ КОРОЛЕВСТВО | AS15: СОЕДИНЕННОЕ КОРОЛЕВСТВО | AT15: RU | AU15: РОССИЯ | AW15: 0 | AX15: DAP | AY15: МОСКВА | BA15: EUR | BB15: 298688 | BE15: 107.9723 | BG15: 40 | BI15: - | BJ15: 11 | BQ15: 10001020 т/п Аэропорт Внуково (грузовой) | BS15: ПЛЕМЕННЫЕ ИНДЮШАЧЬИ ЯЙЦА ДЛЯ ИНКУБАЦИИ, ОПЛОДОТВОРЁННЫЕ, ДЛЯ ВЫВЕДЕНИЯ РОДИТЕЛЬСКОГО СТАДА MELEAGRIS GALLOPAVO L. ПОРОДЫ БЕЛАЯ ШИРОКОГРУДАЯ BIG 6, РАЗМЕЩЕННЫЕ С ЦЕЛЬЮ ПРЕДОТВРАЩЕНИЯ БОЯ И УНИЧТОЖЕНИЯ В КАРТОННЫХ КОРОБКАХ. | BT15: =MIN(1,IFERROR(SEARCH(BT$2,$BS15),0)) -> 0 | BU15: =MIN(1,IFERROR(SEARCH(BU$2,$BS15),0)) -> 1 | BV15: =MAX(BT15,BU15) -> 1 | BW15: ... | BX15: AVIAGEN TURKEYS INC. | BY15: 223 | BZ15: 0 | CA15: 44600 | CB15: ШТ | CE15: 1 | CF15: 0407191100 | CI15: GB | CJ15: 4683 | CK15: ОООО-ПС | CL15: 4000000 | CM15: 4460 | CN15: 0 | CQ15: 298688 | CS15: 0 | CT15: 1 | CU15: 32250030 | CV15: 328389.64 | CW15: 10 | CX15: 73.63 | DB15: 473
B16: 1 | C16: 10.08.2023 | D16: 8 | E16: 10005030/100823/3213832 | F16: 10005030 | G16: 10.08.2023 | H16: 3213832 | I16: ИМ | J16: 40 | N16: CUDDY FARMS A DIVISION OF HENDRIX GENETICS LTD | O16: N7G 3H6, ONTARIO, STRATHROY, CENTRE ROAD, RR#5, 28 | T16: 1 | U16: 380 | V16: 1116829006910 | W16: 6829076796 | X16: ООО "ТАМБОВСКАЯ ИНДЕЙКА" | Y16: 392000, ТАМБОВСКАЯ ОБЛ., ТАМБОВ, УЛ. СТУДЕНЕЦКАЯ, Д.16А, КОРП.1, ПОМ.16 | Z16: 68000 | AA16: 682901001 | AB16: 1116829006910 | AC16: 6829076796 | AD16: ООО "ТАМБОВСКАЯ ИНДЕЙКА" | AE16: 392000, ТАМБОВСКАЯ ОБЛ., ТАМБОВ, УЛ. СТУДЕНЕЦКАЯ, Д.16А, КОРП.1, ПОМ.16 | AF16: 68000 | AG16: 682901001 | AH16: CA | AI16: КАНАДА | AJ16: 12835315 | AK16: 1116829006910 | AL16: 6829076796 | AM16: ООО "ТАМБОВСКАЯ ИНДЕЙКА" | AN16: 392000, ТАМБОВСКАЯ ОБЛ., ТАМБОВ, УЛ. СТУДЕНЕЦКАЯ, Д.16А, КОРП.1, ПОМ.16 | AO16: 68000 | AP16: 682901001 | AQ16: CA | AR16: КАНАДА | AS16: КАНАДА | AT16: RU | AU16: РОССИЯ | AW16: 0 | AX16: CPT | AY16: МОСКВА | BA16: EUR | BB16: 120080 | BE16: 106.8897 | BG16: 40 | BI16: - | BJ16: 11 | BQ16: 10001020 т/п Аэропорт Внуково (грузовой) | BS16: ЯЙЦА ИНДЕЕК ДОМАШНИХ. СВЕЖИЕ, ОПЛОДОТВОРЕННЫЕ ДЛЯ ИНКУБАЦИИ, ПОРОДЫ HYBRID CONVERTER, НЕ ПЛЕМЕННЫЕ, ДЛЯ ПОСЛЕДУЮЩЕГО ВЫРАЩИВАНИЯ И УБОЯ НА МЯСО СВЕЖЕЕ, В КАРТОННЫХ КОРОБКАХ | BT16: =MIN(1,IFERROR(SEARCH(BT$2,$BS16),0)) -> 0 | BU16: =MIN(1,IFERROR(SEARCH(BU$2,$BS16),0)) -> 0 | BV16: =MAX(BT16,BU16) -> 0 | BW16: CUDDY | BX16: CUDDY FARMS | BY16: 380 | BZ16: 0 | CA16: 76000 | CB16: ШТ | CE16: 1 | CF16: 0407191100 | CJ16: 7600 | CK16: ОООО-ЛП | CL16: 4000000 | CM16: 6840 | CN16: 0 | CQ16: 120080 | CS16: 0 | CT16: 1 | CU16: 12835315 | CV16: 131779.55 | CW16: 10 | CX16: 19.27 | DB16: 708
B17: 1 | C17: 05.08.2023 | D17: 8 | E17: 10005030/050823/5009453 | F17: 10005030 | G17: 05.08.2023 | H17: 5009453 | I17: ИМ | J17: 40 | N17: CUDDY FARMS LIMITED 2008 | O17: N7G3H6, ONTARIO, STRATHROY, 28429 CENTRAL ROAD, R. | T17: 1 | U17: 120 | V17: 1177746508235 | W17: 7751046971 | X17: ООО "ЭГМАРТ" | Y17: 108841, , Г. МОСКВА, Г. ТРОИЦК, УЛ. ТЕКСТИЛЬЩИКОВ, ДОМ 3 КОР. 3, ОФ. 4, | Z17: 45000 | AA17: 775101001 | AB17: 1177746508235 | AC17: 7751046971 | AD17: ООО "ЭГМАРТ" | AE17: 108841, , Г. МОСКВА, Г. ТРОИЦК, УЛ. ТЕКСТИЛЬЩИКОВ, ДОМ 3 КОР. 3, ОФ. 4, | AF17: 45000 | AG17: 775101001 | AH17: CA | AI17: КАНАДА | AJ17: 3788006.6 | AK17: 1177746508235 | AL17: 7751046971 | AM17: ООО "ЭГМАРТ" | AN17: 108841, , Г. МОСКВА, Г. ТРОИЦК, УЛ. ТЕКСТИЛЬЩИКОВ, ДОМ 3 КОР. 3, ОФ. 4, | AO17: 45000 | AP17: 775101001 | AQ17: CA | AR17: КАНАДА | AS17: КАНАДА | AT17: RU | AU17: РОССИЯ | AW17: 0 | AX17: CPT | AY17: Г МОСКВА | BA17: EUR | BB17: 36480 | BE17: 103.8379 | BG17: 40 | BI17: - | BJ17: СВ | BQ17: 10001020 т/п Аэропорт Внуково (грузовой) | BS17: ОПЛОДОТВОРЕННЫЕ ИНКУБАЦИОННЫЕ ЯЙЦА ИНДЕЕК (MELEAGRIS GALLOPAVAL.). ДЛЯ ИНКУБАЦИИ И ВЫВЕДЕНИЯ ИНДЕЕК, ДЛЯ ПОСЛЕДУЮЩЕГО ВЫРАЩИВАНИЯ И УБОЯ НА МЯСО, КРОССА "HYBRID CONVERTER"(БЕЛАЯ ШИРОКОГРУДАЯ), СВЕЖИЕ (В КОРОБКЕ ПО 200 ШТ.): | BT17: =MIN(1,IFERROR(SEARCH(BT$2,$BS17),0)) -> 0 | BU17: =MIN(1,IFERROR(SEARCH(BU$2,$BS17),0)) -> 0 | BV17: =MAX(BT17,BU17) -> 0 | BW17: CUDDY | BX17: CUDDY FARMS LIMITED 2008 | BY17: 120 | CA17: 24000 | CB17: ШТ | CE17: 1 | CF17: 0407191100 | CI17: CA | CJ17: 2502 | CK17: ОООО-ЛП | CL17: 4000000 | CM17: 2160 | CN17: 0 | CQ17: 36480 | CU17: 3788006.6 | CV17: 39954.67 | CW17: 10 | CX17: 18.5 | DB17: 789
B18: 1 | C18: 05.08.2023 | D18: 8 | E18: 10005030/050823/3208921 | F18: 10005030 | G18: 05.08.2023 | H18: 3208921 | I18: ИМ | J18: 40 | N18: CUDDY FARMS, A DIVISION OF HENDRIX GENETICS LIMITED | O18: 28429, ONTARIO, STRATHROY N7G 3H6, ROUTE #5, | T18: 1 | U18: 55 | V18: 1193668026507 | W18: 3613005236 | X18: ООО "ДОНСКАЯ ИНДЕЙКА" | Y18: 396347, ВОРОНЕЖСКАЯ ОБЛАСТЬ, М.Р-Н КАШИРСКИЙ, С.П. ДЗЕРЖИНСКОЕ, П.ИМ.ДЗЕРЖИНСКОГ | Z18: 20000 | AA18: 361301001 | AB18: 1193668026507 | AC18: 3613005236 | AD18: ООО "ДОНСКАЯ ИНДЕЙКА" | AE18: 396347, ВОРОНЕЖСКАЯ ОБЛАСТЬ, М.Р-Н КАШИРСКИЙ, С.П. ДЗЕРЖИНСКОЕ, П.ИМ.ДЗЕРЖИНСКОГ | AF18: 20000 | AG18: 361301001 | AH18: CA | AI18: КАНАДА | AJ18: 1770436.2 | AK18: 1193668026507 | AL18: 3613005236 | AM18: ООО "ДОНСКАЯ ИНДЕЙКА" | AN18: 396347, ВОРОНЕЖСКАЯ ОБЛАСТЬ, М.Р-Н КАШИРСКИЙ, С.П. ДЗЕРЖИНСКОЕ, П.ИМ.ДЗЕРЖИНСКОГ | AO18: 20000 | AP18: 361301001 | AQ18: CA | AR18: КАНАДА | AS18: КАНАДА | AT18: RU | AU18: РОССИЯ | AW18: 0 | AX18: CPT | AY18: МОСКВА | BA18: EUR | BB18: 17050 | BE18: 103.8379 | BG18: 40 | BI18: - | BJ18: СВ | BQ18: 10001020 т/п Аэропорт Внуково (грузовой) | BS18: ОПЛОДОТВОРЕННЫЕ ЯЙЦА ИНДЮШАЧЬИ ДЛЯ ИНКУБАЦИИ, КОД ОКП 98 4766 (ОКПД2 01.47.23.140): | BT18: =MIN(1,IFERROR(SEARCH(BT$2,$BS18),0)) -> 0 | BU18: =MIN(1,IFERROR(SEARCH(BU$2,$BS18),0)) -> 1 | BV18: =MAX(BT18,BU18) -> 1 | BW18: CUDDY FARMS | BX18: CUDDY FARMS LIMITED 2008 | BY18: 55 | CA18: 11000 | CB18: ШТ | CE18: 1 | CF18: 0407191100 | CI18: CA | CJ18: 1158 | CK18: ОООО-ЛП | CL18: 4000000 | CM18: 990 | CN18: 0 | CQ18: 17050 | CU18: 1770436.2 | CV18: 18673.99 | CW18: 10 | CX18: 18.86 | DB18: 1146
B19: 1 | C19: 07.08.2023 | D19: 8 | E19: 10805010/070823/5003781 | F19: 10805010 | G19: 07.08.2023 | H19: 5003781 | I19: ИМ | J19: 40 | N19: PARTIZ 2000 KFT. | O19: 5540, , SZARVAS, RACOKZI U.6/1, | T19: 1 | U19: 125 | V19: 1132651023570 | W19: 2624801566 | X19: ООО "ПТИЧИЙ ДВОР" | Y19: 356800, СТАВРОПОЛЬСКИЙ КРАЙ, Г. БУДЕННОВСК, УЛ. ВОДНИКОВ, Д.7, | Z19: 07000 | AA19: 262401001 | AB19: 1132651023570 | AC19: 2624801566 | AD19: ООО "ПТИЧИЙ ДВОР" | AE19: 356800, СТАВРОПОЛЬСКИЙ КРАЙ, Г. БУДЕННОВСК, УЛ. ВОДНИКОВ, Д.7, | AF19: 07000 | AG19: 262401001 | AH19: HU | AI19: ВЕНГРИЯ | AJ19: 3608367 | AK19: 1132651023570 | AL19: 2624801566 | AM19: ООО "ПТИЧИЙ ДВОР" | AN19: 356800, СТАВРОПОЛЬСКИЙ КРАЙ, Г. БУДЕННОВСК, УЛ. ВОДНИКОВ, Д.7, | AO19: 07000 | AP19: 262401001 | AQ19: HU | AR19: ВЕНГРИЯ | AS19: ВЕНГРИЯ | AT19: RU | AU19: РОССИЯ | AW19: 0 | AX19: FCA | AY19: SZARVAS | BA19: EUR | BB19: 33750 | BE19: 103.8379 | BI19: - | BJ19: 99 | BQ19: 10113100 т/п Стабнинский | BS19: ОПЛОДОТВОРЕННЫЕ НЕПЛЕМЕННЫЕ ИНКУБАЦИОННЫЕ ЯЙЦА ИНДЕЙКИ (TURKEY HATCHING EGGS), ДЛЯ ИНКУБАЦИИ, ДЛЯ ПОСЛЕДУЮЩЕГО ВЫРАЩИВАНИЯ И УБОЯ НА МЯСО, СВЕЖИЕ, ПО 200 ШТ В КОРОБКЕ. | BT19: =MIN(1,IFERROR(SEARCH(BT$2,$BS19),0)) -> 1 | BU19: =MIN(1,IFERROR(SEARCH(BU$2,$BS19),0)) -> 0 | BV19: =MAX(BT19,BU19) -> 1 | BW19: PARTIZ 2000 | BX19: GALLI-EGGS KFT., ПЛЕМЗАВОД HU1009994 | BY19: 125 | CA19: 25000 | CB19: ШТ | CE19: 1 | CF19: 0407191100 | CI19: HU | CJ19: 2625 | CK19: ОООО-ЛП | CL19: 4000000 | CM19: 2500 | CQ19: 33750 | CS19: 0 | CT19: 1 | CU19: 3608367 | CV19: 38059.89 | CW19: 10 | CX19: 15.22 | DB19: 26
B20: 1 | C20: 31.08.2023 | D20: 8 | E20: 10131010/310823/3299352 | F20: 10131010 | G20: 31.08.2023 | H20: 3299352 | I20: ИМ | J20: 40 | N20: MOORGUT KARTZFEHN TURKEY BREEDER GMBH | O20: 26219, ., BOSEL, KARTZ-VON-KAMEKE-ALLEE, 7 | R20: 1 | T20: 1 | U20: 753 | W20: 6829076796 | X20: ООО "ТАМБОВСКАЯ ИНДЕЙКА" | Y20: 392000, ТАМБОВСКАЯ ОБЛ., ТАМБОВ, УЛ. СТУДЕНЕЦКАЯ, Д.16А, КОРП.1, ПОМ.16 | Z20: 68000 | AC20: 6829076796 | AD20: ООО "ТАМБОВСКАЯ ИНДЕЙКА" | AE20: 392000, ТАМБОВСКАЯ ОБЛ., ТАМБОВ, УЛ. СТУДЕНЕЦКАЯ, Д.16А, КОРП.1, ПОМ.16 | AF20: 68000 | AH20: DE | AI20: ГЕРМАНИЯ | AJ20: 29371019 | AL20: 6829076796 | AM20: ООО "ТАМБОВСКАЯ ИНДЕЙКА" | AN20: 392000, ТАМБОВСКАЯ ОБЛ., ТАМБОВ, УЛ. СТУДЕНЕЦКАЯ, Д.16А, КОРП.1, ПОМ.16 | AO20: 68000 | AQ20: DE | AR20: ГЕРМАНИЯ | AS20: ГЕРМАНИЯ | AT20: RU | AU20: РОССИЯ | AV20: 2 | AW20: 0 | AX20: DAP | AY20: ТАМБОВ | BA20: EUR | BB20: 281198 | BE20: 104.4496 | BG20: 31 | BH20: 22121027/3292/0000/2/1 | BI20: 11209103-11209103 | BJ20: 11 | BN20: БРЯНСКАЯ ОБЛ. | BO20: Г.НОВОЗЫБКОВ | BP20: УЛ.РОС | BQ20: 10102073 ОТО и ТК №3 т/п Новозыбковский | BS20: ЯЙЦА ИНДЕЕК ДОМАШНИХ, СВЕЖИЕ, ОПЛОДОТВОРЕННЫЕ ДЛЯ ИНКУБАЦИИ, ПОРОДЫ BUT BIG-6 (WHITE WIDE CASE), НЕ ПЛЕМЕННЫЕ, ДЛЯ ПОСЛЕДУЮЩЕГО ВЫРАЩИВАНИЯ И УБОЯ НА МЯСО СВЕЖЕЕ, В КАРТОННЫХ КОРОБКАХ | BT20: =MIN(1,IFERROR(SEARCH(BT$2,$BS20),0)) -> 0 | BU20: =MIN(1,IFERROR(SEARCH(BU$2,$BS20),0)) -> 0 | BV20: =MAX(BT20,BU20) -> 0 | BW20: KARTZFEHN | BX20: KARTZFEHN MARKISCHE PUTEN GMBH | BY20: 753 | BZ20: 0 | CA20: 150600 | CB20: ШТ | CC20: 0 | CE20: 1 | CF20: 0407191100 | CI20: DE | CJ20: 16566 | CK20: ОООО-ЛП | CL20: 4000000 | CM20: 15060 | CN20: 0 | CQ20: 281198 | CS20: 0 | CT20: 1 | CU20: 29371019 | CV20: 306176.79 | CW20: 10 | CX20: 20.33 | CY20: 933 | DA20: АЛИМПИЕВА | DB20: 551
B21: 1 | C21: 28.08.2023 | D21: 8 | E21: 10418010/280823/3119021 | F21: 10418010 | G21: 28.08.2023 | H21: 3119021 | I21: ИМ | J21: 40 | N21: HENDRIX GENETICS TURKEYS FRANCE | O21: 49290, , MAUGES SUR LOIRE, LA BOHARDIERE ; BP 1 - | T21: 1 | U21: 564 | W21: 263034881 | X21: ООО "СПП" | Y21: 453854, РЕСПУБЛИКА БАШКОРТОСТАН, М.Р-Н МЕЛЕУЗОВСКИЙ, Г.МЕЛЕУЗ, УЛ.СОВХОЗНАЯ, ЗДА | AC21: 263034881 | AD21: ООО "СПП" | AE21: 453854, РЕСПУБЛИКА БАШКОРТОСТАН, М.Р-Н МЕЛЕУЗОВСКИЙ, Г.МЕЛЕУЗ, УЛ.СОВХОЗНАЯ, ЗДА | AH21: FR | AI21: ФРАНЦИЯ | AJ21: 17079231 | AL21: 263034881 | AM21: ООО "СПП" | AN21: 453854, РЕСПУБЛИКА БАШКОРТОСТАН, М.Р-Н МЕЛЕУЗОВСКИЙ, Г.МЕЛЕУЗ, УЛ.СОВХОЗНАЯ, ЗДА | AQ21: FR | AR21: ФРАНЦИЯ | AS21: ФРАНЦИЯ | AT21: RU | AU21: РОССИЯ | AW21: 0 | AX21: DAP | AY21: МЕЛЕУЗ | BA21: EUR | BB21: 167020 | BE21: 102.2586 | BI21: - | BJ21: 11 | BQ21: 10113100 т/п Стабнинский | BS21: ОПЛОДОТВОРЕННЫЕ ЯЙЦА ИНДЮШАЧЬИ ДЛЯ ИНКУБАЦИИ, КОД ОКП 98 4766 (ОКПД2 01.47.23.140): ЦЕЛЬ ВВОЗА - ДЛЯ ИНКУБИРОВАНИЯ И ДАЛЬНЕЙШЕГО ВЫРАЩИВАНИЯ. | BT21: =MIN(1,IFERROR(SEARCH(BT$2,$BS21),0)) -> 0 | BU21: =MIN(1,IFERROR(SEARCH(BU$2,$BS21),0)) -> 1 | BV21: =MAX(BT21,BU21) -> 1 | BW21: ОТСУТСТВУЕТ | BX21: HENDRIX GENETICS TURKEYS FRANCE | BY21: 564 | BZ21: 0 | CA21: 112800 | CB21: ШТ | CE21: 1 | CF21: 0407191100 | CI21: FR | CJ21: 11844 | CK21: ОООО-ЛП | CL21: 4000000 | CM21: 11280 | CN21: 0 | CQ21: 167020 | CS21: 0 | CT21: 1 | CU21: 17079231 | CV21: 180328.63 | CW21: 10 | CX21: 15.99 | DB21: 30
B22: 1 | C22: 02.08.2023 | D22: 8 | E22: 10418010/020823/3107226 | F22: 10418010 | G22: 02.08.2023 | H22: 3107226 | I22: ИМ | J22: 40 | N22: BRANKO NITRA, A.S. | O22: 94905, , NITRA, NOVOZAMOCKA 184, | T22: 1 | U22: 16 | W22: 263034881 | X22: ООО "СПП" | Y22: 453854, РЕСПУБЛИКА БАШКОРТОСТАН, М.Р-Н МЕЛЕУЗОВСКИЙ, Г.МЕЛЕУЗ, УЛ.СОВХОЗНАЯ, ЗДА | AC22: 263034881 | AD22: ООО "СПП" | AE22: 453854, РЕСПУБЛИКА БАШКОРТОСТАН, М.Р-Н МЕЛЕУЗОВСКИЙ, Г.МЕЛЕУЗ, УЛ.СОВХОЗНАЯ, ЗДА | AH22: SK | AI22: СЛОВАКИЯ | AJ22: 10732478 | AL22: 263034881 | AM22: ООО "СПП" | AN22: 453854, РЕСПУБЛИКА БАШКОРТОСТАН, М.Р-Н МЕЛЕУЗОВСКИЙ, Г.МЕЛЕУЗ, УЛ.СОВХОЗНАЯ, ЗДА | AQ22: SK | AR22: СЛОВАКИЯ | AS22: СЛОВАКИЯ | AT22: RU | AU22: РОССИЯ | AW22: 0 | AX22: DAP | AY22: МЕЛЕУЗ | BA22: EUR | BB22: 106580 | BE22: 100.6988 | BI22: - | BJ22: СВ | BQ22: 10113100 т/п Стабнинский | BS22: ОПЛОДОТВОРЕННЫЕ ЯЙЦА ИНДЮШАЧЬИ ДЛЯ ИНКУБАЦИИ, КОД ОКП 98 4766 (ОКПД2 01.47.23.140): ЦЕЛЬ ВВОЗА - ДЛЯ ИНКУБИРОВАНИЯ. | BT22: =MIN(1,IFERROR(SEARCH(BT$2,$BS22),0)) -> 0 | BU22: =MIN(1,IFERROR(SEARCH(BU$2,$BS22),0)) -> 1 | BV22: =MAX(BT22,BU22) -> 1 | BW22: ОТСУТСТВУЕТ | BX22: PRODUKCNA FARMA PODHORANY (SK- RH-NR-18) | BY22: 16 | CA22: 73000 | CB22: ШТ | CE22: 1 | CF22: 0407191100 | CI22: SK | CJ22: 7665 | CK22: ОООО-ЛП | CL22: 4000000 | CM22: 7118 | CN22: 0 | CQ22: 106580 | CU22: 10732478 | CV22: 116942.74 | CW22: 10 | CX22: 16.43 | DB22: 125
B23: 1 | C23: 21.08.2023 | D23: 8 | E23: 10131010/210823/5018415 | F23: 10131010 | G23: 21.08.2023 | H23: 5018415 | I23: ИМ | J23: 40 | N23: GRIMAUD FRERES SELECTION S.A.S. | O23: 49450, , SEVREMOINE, 3 LA CORBIERE-ROUSSAY, | T23: 1 | U23: 121 | V23: 1173668015586 | W23: 3627030120 | X23: ООО "АЛГА" | Y23: 397902, ВОРОНЕЖСКАЯ ОБЛАСТЬ, ЛИСКИНСКИЙ Р-Н, Г. ЛИСКИ, ВОРОНЕЖСКАЯ УЛ, ЗД. 35/1, | Z23: 20000 | AA23: 362701001 | AB23: 1173668015586 | AC23: 3627030120 | AD23: ООО "АЛГА" | AE23: 397902, ВОРОНЕЖСКАЯ ОБЛАСТЬ, ЛИСКИНСКИЙ Р-Н, Г. ЛИСКИ, ВОРОНЕЖСКАЯ УЛ, ЗД. 35/1, | AF23: 20000 | AG23: 362701001 | AH23: FR | AI23: ФРАНЦИЯ | AJ23: 7584630.2 | AK23: 1173668015586 | AL23: 3627030120 | AM23: ООО "АЛГА" | AN23: 397902, ВОРОНЕЖСКАЯ ОБЛАСТЬ, ЛИСКИНСКИЙ Р-Н, Г. ЛИСКИ, ВОРОНЕЖСКАЯ УЛ, ЗД. 35/1, | AO23: 20000 | AP23: 362701001 | AQ23: FR | AR23: ФРАНЦИЯ | AS23: ФРАНЦИЯ | AT23: RU | AU23: РОССИЯ | AW23: 0 | AX23: CPT | AY23: ХУТОР УКРАИНСКИЙ | BA23: EUR | BB23: 74740 | BE23: 101.4802 | BI23: - | BJ23: 99 | BQ23: 10013070 т/п Красноармейский | BS23: ОПЛОДОТВОРЕННЫЕ ИНКУБАЦИОННЫЕ ЯЙЦА РОДИТЕЛЬСКОГО СТАДА ПЛЕМЕННОЙ ПЕКИНСКОЙ УТКИ, ДЛЯ ИНКУБАЦИИ И ВЫВЕДЕНИЯ ПОРОДЫ ПЕКИНСКИХ УТОК, СВЕЖИЕ, (В ОДНОЙ КОРОБКЕ 200 ШТ. ) | BT23: =MIN(1,IFERROR(SEARCH(BT$2,$BS23),0)) -> 0 | BU23: =MIN(1,IFERROR(SEARCH(BU$2,$BS23),0)) -> 0 | BV23: =MAX(BT23,BU23) -> 0 | BW23: GRIMAUD FRERES | BX23: GRIMAUD FRERES SELECTION S.A.S. | BY23: 121 | CA23: 24200 | CB23: ШТ | CE23: 1 | CF23: 0407191900 | CI23: FR | CJ23: 2371.6 | CK23: ОООО-ПС | CL23: 4000000 | CM23: 1936 | CQ23: 74740 | CS23: 0 | CT23: 1 | CU23: 7584630.2 | CV23: 81201.8 | CW23: 10 | CX23: 41.94 | DB23: 166
B24: 1 | C24: 21.08.2023 | D24: 8 | E24: 10131010/210823/3288849 | F24: 10131010 | G24: 21.08.2023 | H24: 3288849 | I24: ИМ | J24: 40 | N24: "HENDRIX GENETICS TURKEYS FRANCE SAS" | O24: 49290, MAUGES SUR LOIRE, SAINT LAURENT DE LA PLAIN | T24: 1 | U24: 420 | V24: 1116829006910 | W24: 6829076796 | X24: ООО "ТАМБОВСКАЯ ИНДЕЙКА" | Y24: 392000, ТАМБОВСКАЯ ОБЛ., ТАМБОВ, УЛ. СТУДЕНЕЦКАЯ, Д.16А, КОРП.1, ПОМ.16 | Z24: 68000 | AA24: 682901001 | AB24: 1116829006910 | AC24: 6829076796 | AD24: ООО "ТАМБОВСКАЯ ИНДЕЙКА" | AE24: 392000, ТАМБОВСКАЯ ОБЛ., ТАМБОВ, УЛ. СТУДЕНЕЦКАЯ, Д.16А, КОРП.1, ПОМ.16 | AF24: 68000 | AG24: 682901001 | AH24: FR | AI24: ФРАНЦИЯ | AJ24: 13953893 | AK24: 1116829006910 | AL24: 6829076796 | AM24: ООО "ТАМБОВСКАЯ ИНДЕЙКА" | AN24: 392000, ТАМБОВСКАЯ ОБЛ., ТАМБОВ, УЛ. СТУДЕНЕЦКАЯ, Д.16А, КОРП.1, ПОМ.16 | AO24: 68000 | AP24: 682901001 | AQ24: HU | AR24: ВЕНГРИЯ | AS24: ВЕНГРИЯ | AT24: RU | AU24: РОССИЯ | AW24: 0 | AX24: DAP | AY24: ПЕРВОМАЙСКИЙ, ТАМБОВ. ОБЛ. | BA24: EUR | BB24: 137503.6 | BE24: 101.4802 | BG24: 31 | BI24: - | BJ24: 11 | BQ24: 10102073 ОТО и ТК №3 т/п Новозыбковский | BS24: ЯЙЦА ИНДЕЕК ДОМАШНИХ, СВЕЖИЕ, ОПЛОДОТВОРЕННЫЕ ДЛЯ ИНКУБАЦИИ, ПОРОДЫ HYBRID CONVERTER, НЕ ПЛЕМЕННЫЕ, ДЛЯ ПОСЛЕДУЮЩЕГО ВЫРАЩИВАНИЯ И УБОЯ НА МЯСО СВЕЖЕЕ. В КАРТОННЫХ КОРОБКАХ | BT24: =MIN(1,IFERROR(SEARCH(BT$2,$BS24),0)) -> 0 | BU24: =MIN(1,IFERROR(SEARCH(BU$2,$BS24),0)) -> 0 | BV24: =MAX(BT24,BU24) -> 0 | BW24: ОТСУТСТВУЕТ | BX24: NAGISZ ZRT. | BY24: 420 | BZ24: 0 | CA24: 84000 | CB24: ШТ | CE24: 1 | CF24: 0407191100 | CI24: HU | CJ24: 8820 | CK24: ОООО-ЛП | CL24: 4000000 | CM24: 8400 | CN24: 0 | CQ24: 137503.6 | CS24: 0 | CT24: 1 | CU24: 13953893 | CV24: 149391.76 | CW24: 10 | CX24: 17.78 | DB24: 71
B25: 1 | C25: 18.08.2023 | D25: 8 | E25: 10131010/180823/3286446 | F25: 10131010 | G25: 18.08.2023 | H25: 3286446 | I25: ИМ | J25: 40 | N25: MOORGUT KARTZFEHN TURKEY BREEDER GMBH | O25: 26219, ., BOSEL, KARTZ-VON-KAMEKE-ALLEE, 7 | T25: 1 | U25: 420 | V25: 1116829006910 | W25: 6829076796 | X25: ООО "ТАМБОВСКАЯ ИНДЕЙКА" | Y25: 392000, ТАМБОВСКАЯ ОБЛ., ТАМБОВ, УЛ. СТУДЕНЕЦКАЯ, Д.16А, КОРП.1, ПОМ.16 | Z25: 68000 | AA25: 682901001 | AB25: 1116829006910 | AC25: 6829076796 | AD25: ООО "ТАМБОВСКАЯ ИНДЕЙКА" | AE25: 392000, ТАМБОВСКАЯ ОБЛ., ТАМБОВ, УЛ. СТУДЕНЕЦКАЯ, Д.16А, КОРП.1, ПОМ.16 | AF25: 68000 | AG25: 682901001 | AH25: DE | AI25: ГЕРМАНИЯ | AJ25: 16279477 | AK25: 1116829006910 | AL25: 6829076796 | AM25: ООО "ТАМБОВСКАЯ ИНДЕЙКА" | AN25: 392000, ТАМБОВСКАЯ ОБЛ., ТАМБОВ, УЛ. СТУДЕНЕЦКАЯ, Д.16А, КОРП.1, ПОМ.16 | AO25: 68000 | AP25: 682901001 | AQ25: DE | AR25: ГЕРМАНИЯ | AS25: ГЕРМАНИЯ | AT25: RU | AU25: РОССИЯ | AW25: 0 | AX25: DAP | AY25: ТАМБОВ | BA25: EUR | BB25: 159320 | BE25: 102.181 | BI25: - | BJ25: 11 | BQ25: 10102073 ОТО и ТК №3 т/п Новозыбковский | BS25: ЯЙЦА ИНДЕЕК ДОМАШНИХ. СВЕЖИЕ, ОПЛОДОТВОРЕННЫЕ ДЛЯ ИНКУБАЦИИ, ПОРОДЫ BUT BIG-6 (WHITE WIDE CASE), НЕ ПЛЕМЕННЫЕ, ДЛЯ ПОСЛЕДУЮЩЕГО ВЫРАЩИВАНИЯ И УБОЯ НА МЯСО СВЕЖЕЕ, В КАРТОННЫХ КОРОБКАХ | BT25: =MIN(1,IFERROR(SEARCH(BT$2,$BS25),0)) -> 0 | BU25: =MIN(1,IFERROR(SEARCH(BU$2,$BS25),0)) -> 0 | BV25: =MAX(BT25,BU25) -> 0 | BW25: KARTZFEHN | BX25: KARTZFEHN MARKISCHE PUTEN GMBH | BY25: 420 | BZ25: 0 | CA25: 84000 | CB25: ШТ | CE25: 1 | CF25: 0407191100 | CI25: DE | CJ25: 9240 | CK25: ОООО-ЛП | CL25: 4000000 | CM25: 8400 | CN25: 0 | CQ25: 159320 | CS25: 0 | CT25: 1 | CU25: 16279477 | CV25: 173655.16 | CW25: 10 | CX25: 20.67 | DB25: 94
B26: 1 | C26: 13.08.2023 | D26: 8 | E26: 10131010/130823/3279866 | F26: 10131010 | G26: 13.08.2023 | H26: 3279866 | I26: ИМ | J26: 40 | N26: HENDRIX GENETICS TURKEYS FRANCE SAS | O26: 49290, , MAUGES SUR LOIRE, B.P.1-LA BOHARDIERE SAI | T26: 1 | U26: 13 | V26: 1193668026507 | W26: 3613005236 | X26: ООО "ДОНСКАЯ ИНДЕЙКА" | Y26: 396350, ВОРОНЕЖСКАЯ ОБЛАСТЬ, КАШИРСКИЙ РАЙОН, П. ИМ. ДЗЕРЖИНСКОЕ, УЛ. ПОЛЕВАЯ,, | Z26: 20000 | AA26: 361301001 | AB26: 1193668026507 | AC26: 3613005236 | AD26: ООО "ДОНСКАЯ ИНДЕЙКА" | AE26: 396350, ВОРОНЕЖСКАЯ ОБЛАСТЬ, КАШИРСКИЙ РАЙОН, П. ИМ. ДЗЕРЖИНСКОЕ, УЛ. ПОЛЕВАЯ,, | AF26: 20000 | AG26: 361301001 | AH26: FR | AI26: ФРАНЦИЯ | AJ26: 9285617.8 | AK26: 1193668026507 | AL26: 3613005236 | AM26: ООО "ДОНСКАЯ ИНДЕЙКА" | AN26: 396350, ВОРОНЕЖСКАЯ ОБЛАСТЬ, КАШИРСКИЙ РАЙОН, П. ИМ. ДЗЕРЖИНСКОЕ, УЛ. ПОЛЕВАЯ,, | AO26: 20000 | AP26: 361301001 | AQ26: FR | AR26: ФРАНЦИЯ | AS26: ФРАНЦИЯ | AT26: RU | AU26: РОССИЯ | AW26: 0 | AX26: DAP | AY26: П. ИМ. ДЗЕРЖИНСКОГО | BA26: EUR | BB26: 86000 | BE26: 107.9723 | BI26: - | BJ26: 99 | BQ26: 10113100 т/п Стабнинский | BS26: ОПЛОДОТВОРЕННЫЕ ИНКУБАЦИОННЫЕ ЯЙЦА ИНДЕЕК (MELEAGRUS GAILOPANO L), ДЛЯ ИНКУБАЦИИ И ВЫВЕДЕНИЯ ИНДЕЕК, ДЛЯ ПОСЛЕДУЮЩЕГО ВЫРАЩИВАНИЯ И УБОЯ НА МЯСО, СВЕЖИЕ, (В КОРОБКЕ 10 ЛОТКОВ ПО 20 ШТ.): | BT26: =MIN(1,IFERROR(SEARCH(BT$2,$BS26),0)) -> 0 | BU26: =MIN(1,IFERROR(SEARCH(BU$2,$BS26),0)) -> 0 | BV26: =MAX(BT26,BU26) -> 0 | BW26: ОТСУТСТВУЕТ | BX26: HENDRIX GENETICS TURKEYS FRANCE | BY26: 13 | BZ26: 0 | CA26: 58000 | CB26: ШТ | CE26: 1 | CF26: 0407191100 | CI26: FR | CJ26: 6090 | CK26: ОООО-ЛП | CL26: 4000000 | CM26: 5800 | CN26: 0 | CQ26: 86000 | CS26: 0 | CT26: 1 | CU26: 9285617.8 | CV26: 94551.87 | CW26: 10 | CX26: 16.3 | DB26: 4
B27: 1 | C27: 05.08.2023 | D27: 8 | E27: 10131010/050823/5013823 | F27: 10131010 | G27: 05.08.2023 | H27: 5013823 | I27: ИМ | J27: 40 | N27: GRIMAUD FRERES SELECTION S.A.S. | O27: 49450, , SEVREMOINE, 3 LA CORBIERE-ROUSSAY, | T27: 1 | U27: 83 | V27: 1173668015586 | W27: 3627030120 | X27: ООО "АЛГА" | Y27: 397902, ВОРОНЕЖСКАЯ ОБЛАСТЬ, ЛИСКИНСКИЙ Р-Н, Г. ЛИСКИ, ВОРОНЕЖСКАЯ УЛ, ЗД. 35/1, | Z27: 20000 | AA27: 362701001 | AB27: 1173668015586 | AC27: 3627030120 | AD27: ООО "АЛГА" | AE27: 397902, ВОРОНЕЖСКАЯ ОБЛАСТЬ, ЛИСКИНСКИЙ Р-Н, Г. ЛИСКИ, ВОРОНЕЖСКАЯ УЛ, ЗД. 35/1, | AF27: 20000 | AG27: 362701001 | AH27: FR | AI27: ФРАНЦИЯ | AJ27: 10441524 | AK27: 1173668015586 | AL27: 3627030120 | AM27: ООО "АЛГА" | AN27: 397902, ВОРОНЕЖСКАЯ ОБЛАСТЬ, ЛИСКИНСКИЙ Р-Н, Г. ЛИСКИ, ВОРОНЕЖСКАЯ УЛ, ЗД. 35/1, | AO27: 20000 | AP27: 362701001 | AQ27: FR | AR27: ФРАНЦИЯ | AS27: ФРАНЦИЯ | AT27: RU | AU27: РОССИЯ | AW27: 0 | AX27: CPT | AY27: ХУТОР УКРАИНСКИЙ | BA27: EUR | BB27: 100556 | BE27: 103.8379 | BI27: - | BJ27: Ин | BQ27: 10013070 т/п Красноармейский | BS27: ОПЛОДОТВОРЕННЫЕ ИНКУБАЦИОННЫЕ ЯЙЦА РОДИТЕЛЬСКОГО СТАДА ПЛЕМЕННОЙ ПЕКИНСКОЙ УТКИ, ДЛЯ ИНКУБАЦИИ И ВЫВЕДЕНИЯ ПОРОДЫ ПЕКИНСКИХ УТОК, СВЕЖИЕ, (В ОДНОЙ КОРОБКЕ 200 ШТ. ) | BT27: =MIN(1,IFERROR(SEARCH(BT$2,$BS27),0)) -> 0 | BU27: =MIN(1,IFERROR(SEARCH(BU$2,$BS27),0)) -> 0 | BV27: =MAX(BT27,BU27) -> 0 | BW27: GRIMAUD FRERES | BX27: GRIMAUD FRERES SELECTION S.A.S. | BY27: 83 | CA27: 16600 | CB27: ШТ | CE27: 1 | CF27: 0407191900 | CI27: FR | CJ27: 1626.8 | CK27: ОООО-ПС | CL27: 4000000 | CM27: 1328 | CN27: 0 | CQ27: 100556 | CU27: 10441524 | CV27: 110133.83 | CW27: 10 | CX27: 82.93 | DB27: 324
B28: 1 | C28: 31.07.2023 | D28: 7 | E28: 10620010/310723/3112817 | F28: 10620010 | G28: 31.07.2023 | H28: 3112817 | I28: ИМ | J28: 40 | N28: GRIMAUD FRERES SELECTION S.A.S. | O28: 49450, SEVREMOINE, ROUSSAY, 3 LA CORBIERE, | R28: 1 | S28: 0 | T28: 1 | U28: 115 | V28: 1165476055030 | W28: 5446017473 | X28: ООО ПФ "УЛЫБИНО" | Y28: 633204, НОВОСИБИРСКАЯ ОБЛАСТЬ, Г.ИСКИТИМ, УЛ.ЭЛЕВАТОРНАЯ, Д.5/1,ОФИС 310, | Z28: 50000 | AA28: 544601001 | AB28: 1165476055030 | AC28: 5446017473 | AD28: ООО ПФ "УЛЫБИНО" | AE28: 633204, НОВОСИБИРСКАЯ ОБЛАСТЬ, Г.ИСКИТИМ, УЛ.ЭЛЕВАТОРНАЯ, Д.5/1,ОФИС 310, | AF28: 50000 | AG28: 544601001 | AH28: FR | AI28: ФРАНЦИЯ | AJ28: 8126634.2 | AK28: 1165476055030 | AL28: 5446017473 | AM28: ООО ПФ "УЛЫБИНО" | AN28: 633204, НОВОСИБИРСКАЯ ОБЛАСТЬ, Г.ИСКИТИМ, УЛ.ЭЛЕВАТОРНАЯ, Д.5/1,ОФИС 310, | AO28: 50000 | AQ28: FR | AR28: ФРАНЦИЯ | AS28: ФРАНЦИЯ | AT28: RU | AU28: РОССИЯ | AV28: 2 | AW28: 0 | AX28: DAP | AY28: ИСКИТИМ | AZ28: 1 | BA28: EUR | BB28: 81300 | BE28: 99.9586 | BF28: 10 | BG28: 31 | BH28: 23050005/2216/0004/2/1 | BI28: 10609060-т/п Аэропорт Толмачево | BJ28: 99 | BN28: НОВОСИБИРСКАЯ ОБЛ. | BO28: Г. ОБЬ | BP28: ПР-КТ МОЗЖЕРИНА, СТР.1,СТР.22; АЭРОПОРТ ТОЛМАЧЕВО | BQ28: 10609060 т/п Аэропорт Толмачево | BS28: ОПЛОДОТВОРЕННЫЕ ЯЙЦА ДОМАШНЕЙ ПЕКИНСКОЙ УТКИ ДЛЯ ИНКУБАЦИИ | BT28: =MIN(1,IFERROR(SEARCH(BT$2,$BS28),0)) -> 0 | BU28: =MIN(1,IFERROR(SEARCH(BU$2,$BS28),0)) -> 0 | BV28: =MAX(BT28,BU28) -> 0 | BW28: ОТСУТСТВУЕТ | BX28: GRIMAUD FRERES SELECTION S.A.S. | BY28: 115 | BZ28: 0 | CA28: 23000 | CB28: ШТ | CC28: 0 | CE28: 1 | CF28: 0407191900 | CI28: FR | CJ28: 2254 | CK28: ОООО-ПС | CL28: 4000000 | CM28: 1840 | CN28: 0 | CQ28: 81300 | CR28: 8126634.2 | CS28: 0 | CT28: 1 | CU28: 8126634.2 | CV28: 89324.97 | CW28: 10 | CX28: 48.55 | CY28: 1069 | CZ28: 0582-19-23-413 | DA28: КАЙГОРОДОВА ОЛЬГА СЕРГЕЕВНА | DB28: 123
B29: 1 | C29: 31.07.2023 | D29: 7 | E29: 10418010/310723/5008062 | F29: 10418010 | G29: 31.07.2023 | H29: 5008062 | I29: ИМ | J29: 40 | N29: BRANKO NITRA, A. S. | O29: 949 05, , NITRA, NOVOZAMOCKA, 184 | R29: 1 | T29: 1 | U29: 10 | V29: 1191690037549 | W29: 1623014613 | X29: ООО "БРАНКО РУС" | Y29: 422060, РЕСПУБЛИКА ТАТАРСТАН, САБИНСКИЙ РАЙОН, ПГТ. БОГАТЫЕ САБЫ, УЛ. ЗАВОДСКАЯ, | Z29: 92000 | AA29: 162301001 | AB29: 1191690037549 | AC29: 1623014613 | AD29: ООО "БРАНКО РУС" | AE29: 422060, РЕСПУБЛИКА ТАТАРСТАН, САБИНСКИЙ РАЙОН, ПГТ. БОГАТЫЕ САБЫ, УЛ. ЗАВОДСКАЯ, | AF29: 92000 | AG29: 162301001 | AH29: SK | AI29: СЛОВАКИЯ | AJ29: 7576861.9 | AK29: 1191690037549 | AL29: 1623014613 | AM29: ООО "БРАНКО РУС" | AN29: 422060, РЕСПУБЛИКА ТАТАРСТАН, САБИНСКИЙ РАЙОН, ПГТ. БОГАТЫЕ САБЫ, УЛ. ЗАВОДСКАЯ, | AO29: 92000 | AQ29: SK | AR29: СЛОВАКИЯ | AS29: СЛОВАКИЯ | AT29: RU | AU29: РОССИЯ | AV29: 2 | AW29: 0 | AX29: DAP | AY29: БОГАТЫЕ САБЫ | AZ29: 1 | BA29: EUR | BB29: 75800 | BE29: 99.9586 | BF29: 10 | BG29: 31 | BH29: 23030299/2766/0000/2/1 | BI29: 10113100-т/п Стабнинский | BJ29: 99 | BN29: СМОЛЕНСКАЯ ОБЛ., СМОЛЕНСКИЙ Р-ОН | BO29: С.П.СТАБЕНСКОЕ | BP29: СЕВЕРО-ВОСТОЧНЕЕ Д. СТАБНА, НА РАСТОЯНИИ 700 М | BQ29: 10113100 т/п Стабнинский | BS29: ОПЛОДОТВОРЕННЫЕ ЯЙЦА ИНДЮШАЧЬИ СВЕЖИЕ,ДЛЯ ИНКУБАЦИИ (ВСЕГО 46000 ШТ) ЯЙЦО ИНКУБАЦИОННОЕ ИНДЕЙКИ MELEAGRIS GALLOPAVO L., ПОРОДЫ BUT BIG 6 , БЕЛАЯ ШИРОКОГРУДАЯ, ВЕС ЯЙЦА МЕЖДУ 75 - 100 Г, НЕ ЯВЛЯЕТСЯ ПЛЕМЕННЫМ, (УПАКОВАНО В КОРОБКАХ ПО 200 ШТ)(ФЕРМА RF | BT29: =MIN(1,IFERROR(SEARCH(BT$2,$BS29),0)) -> 1 | BU29: =MIN(1,IFERROR(SEARCH(BU$2,$BS29),0)) -> 1 | BV29: =MAX(BT29,BU29) -> 1 | BW29: ОТСУТСТВУЕТ | BX29: BRANKO NITRA, A. S. | BY29: 10 | CA29: 46000 | CB29: ШТ | CE29: 1 | CF29: 0407191100 | CI29: SK | CJ29: 4830 | CK29: ОООО-ЛП | CL29: 4000000 | CM29: 4485 | CQ29: 75800 | CR29: 7576861.9 | CS29: 0 | CT29: 1 | CU29: 7576861.9 | CV29: 83282.08 | CW29: 10 | CX29: 18.57 | DA29: КРАЙНОВА ЛЮДМИЛА АНАТОЛЬЕВНА | DB29: 91
B30: 1 | C30: 31.07.2023 | D30: 7 | E30: 10013160/310723/5007331 | F30: 10013160 | G30: 31.07.2023 | H30: 5007331 | I30: ИМ | J30: 40 | N30: BRANKO NITRA, A.S. | O30: 94905, , NITRA, NOVOZAMOCKA 184, | R30: 1 | T30: 1 | U30: 5 | V30: 1175027024820 | W30: 5040151421 | X30: ООО "БРОННИЦКАЯ ПТИЦЕФАБРИКА" | Y30: 140157, МОСКОВСКАЯ ОБЛ., РАМЕНСКИЙ Г. О., ПОС. РЫЛЕЕВО, УЛ. 4-Й КМ (АВТОДОРОГА М | Z30: 46000 | AA30: 504001001 | AB30: 1175027024820 | AC30: 5040151421 | AD30: ООО "БРОННИЦКАЯ ПТИЦЕФАБРИКА" | AE30: 140157, МОСКОВСКАЯ ОБЛ., РАМЕНСКИЙ Г. О., ПОС. РЫЛЕЕВО, УЛ. 4-Й КМ (АВТОДОРОГА М | AF30: 46000 | AG30: 504001001 | AH30: SK | AI30: СЛОВАКИЯ | AJ30: 4269231.8 | AK30: 1175027024820 | AL30: 5040151421 | AM30: ООО "БРОННИЦКАЯ ПТИЦЕФАБРИКА" | AN30: 140157, МОСКОВСКАЯ ОБЛ., РАМЕНСКИЙ Г. О., ПОС. РЫЛЕЕВО, УЛ. 4-Й КМ (АВТОДОРОГА М | AO30: 46000 | AQ30: SK | AR30: СЛОВАКИЯ | AS30: СЛОВАКИЯ | AT30: RU | AU30: РОССИЯ | AV30: 2 | AW30: 0 | AX30: FCA | AY30: НИТРА | AZ30: 1 | BA30: EUR | BB30: 41100 | BE30: 99.9586 | BF30: 10 | BG30: 31 | BH30: 23010003/2551/0001/2/1 | BI30: 10113100-т/п Стабнинский | BJ30: 99 | BN30: СМОЛЕНСКАЯ ОБЛ., СМОЛЕНСКИЙ Р-Н | BO30: С.П. СТАБЕНСКОЕ | BP30: СЕВЕРО-ВОСТОЧНЕЕ Д. СТАБНА, НА РАСТОЯНИИ 700 М | BQ30: 10113100 т/п Стабнинский | BS30: ОПЛОДОТВОРЕННЫЕ НЕПЛЕМЕННЫЕ ИНКУБАЦИОННЫЕ ЯЙЦА ИНДЕЙКИ (MELAGRIS GALLOPAVO L.) ДЛЯ ИНКУБАЦИИ И ВЫВЕДЕНИЯ ПОРОДЫ ИНДЕЕК, ДЛЯ ПОСЛЕДУЮЩЕГО ВЫРАЩИВАНИЯ И УБОЯ НА МЯСО, СВЕЖИЕ, ПОРОДЫ БЕЛАЯ ШИРОКОГРУДАЯ, КРОСС БИГ 6, ВЕС ЯЙЦА 75-100 Г, УПАКОВАНО ВКАРТОНН | BT30: =MIN(1,IFERROR(SEARCH(BT$2,$BS30),0)) -> 1 | BU30: =MIN(1,IFERROR(SEARCH(BU$2,$BS30),0)) -> 0 | BV30: =MAX(BT30,BU30) -> 1 | BW30: ОТСУТСТВУЕТ | BX30: BRANKO NITRA, A.S. ПЛЕМЗАВ.: SK-RH-NR-13 | BY30: 5 | CA30: 27400 | CB30: ШТ | CE30: 1 | CF30: 0407191100 | CI30: SK | CJ30: 2877 | CK30: ОООО-ЛП | CL30: 4000000 | CM30: 2672 | CQ30: 41100 | CR30: 4108298.5 | CS30: 0 | CT30: 1 | CU30: 4269231.8 | CV30: 46925.83 | CW30: 10 | CX30: 17.56 | DA30: КИРАКОСЯН АЗНИВ МЕРУЖАНОВНА | DB30: 1295
B31: 1 | C31: 31.07.2023 | D31: 7 | E31: 10013160/310723/3340393 | F31: 10013160 | G31: 31.07.2023 | H31: 3340393 | I31: ИМ | J31: 40 | N31: BRANKO NITRA, A.S. | O31: 94905, , NITRA, NOVOZAMOCKA, 184 | R31: 1 | S31: 0 | T31: 1 | U31: 21 | V31: 1047796588146 | W31: 7710553010 | X31: ООО "АГРОИМПОРТ" | Y31: 143421, МОСКОВСКАЯ ОБЛ., КРАСНОГОРСКИЙ Р-Н, 26 КМ А/Д "БАЛТИЯ", БЦ "РИГА-ЛЕНД", | Z31: 46000 | AA31: 502401001 | AB31: 1047796588146 | AC31: 7710553010 | AD31: ООО "АГРОИМПОРТ" | AE31: 143421, МОСКОВСКАЯ ОБЛ., КРАСНОГОРСКИЙ Р-Н, 26 КМ А/Д "БАЛТИЯ", БЦ "РИГА-ЛЕНД", | AF31: 46000 | AG31: 502401001 | AH31: SK | AI31: СЛОВАКИЯ | AJ31: 15041770 | AK31: 1047796588146 | AL31: 7710553010 | AM31: ООО "АГРОИМПОРТ" | AN31: 143421, МОСКОВСКАЯ ОБЛ., КРАСНОГОРСКИЙ Р-Н, 26 КМ А/Д "БАЛТИЯ", БЦ "РИГА-ЛЕНД", | AO31: 46000 | AQ31: SK | AR31: СЛОВАКИЯ | AS31: СЛОВАКИЯ | AT31: RU | AU31: РОССИЯ | AV31: 2 | AW31: 0 | AX31: DAP | AY31: С. ГОЛИЦЫНО | AZ31: 1 | BA31: EUR | BB31: 150480 | BE31: 99.9586 | BF31: 10 | BG31: 31 | BH31: 20121482/1326/0000/2/1 | BI31: 10413090-т/п Пензенский областной | BJ31: 99 | BN31: ПЕНЗЕНСКАЯ | BO31: ПЕНЗА | BP31: АУСТРИНА | BQ31: 10413090 т/п Пензенский областной | BS31: ИНДЮШАЧЬИ ЯЙЦА ДЛЯ ИНКУБАЦИИ, ОПЛОДОТВОРЕННЫЕ, MELEAGRIS GALLOPAVO L., ПОРОДА БЕЛАЯ ШИРОКОГРУДАЯ КРОССА БИГ-6, РАЗМЕЩЕНЫ С ЦЕЛЬЮ ПРЕДОТВРАЩЕНИЯ БОЯ И УНИЧТОЖЕНИЯ В КАРТОННЫХ КОРОБКАХ | BT31: =MIN(1,IFERROR(SEARCH(BT$2,$BS31),0)) -> 0 | BU31: =MIN(1,IFERROR(SEARCH(BU$2,$BS31),0)) -> 1 | BV31: =MAX(BT31,BU31) -> 1 | BW31: ОТСУТСТВУЕТ | BX31: BRANKO NITRA, A.S. | BY31: 21 | BZ31: 0 | CA31: 99000 | CB31: ШТ | CC31: 0 | CE31: 1 | CF31: 0407191100 | CI31: SK | CJ31: 10395 | CK31: ОООО-ЛП | CL31: 4000000 | CM31: 9653 | CN31: 0 | CQ31: 150480 | CR31: 15041770 | CS31: 0 | CT31: 1 | CU31: 15041770 | CV31: 165333.6 | CW31: 10 | CX31: 17.13 | DA31: КУДЕЛЬКИН ВЛАДИМИР ВЛАДИМИРОВИЧ | DB31: 1333
B32: 1 | C32: 28.08.2023 | D32: 8 | E32: 10013160/280823/3379543 | F32: 10013160 | G32: 28.08.2023 | H32: 3379543 | I32: ИМ | J32: 40 | N32: BRANKO NITRA, A.S. | O32: 94905, , NITRA, NOVOZAMOCKA 184, | T32: 1 | U32: 1 | V32: 1215000062364 | W32: 5040173714 | X32: ООО "Р.И.П.С." | Y32: 140166, МОСКОВСКАЯ ОБЛАСТЬ, Г.О. РАМЕНСКИЙ, Д.ВЛАДИМИРОВКА, СТР.1, ПОМЕЩ.1, | Z32: 46000 | AA32: 504001001 | AB32: 1215000062364 | AC32: 5040173714 | AD32: ООО "Р.И.П.С." | AE32: 140166, МОСКОВСКАЯ ОБЛАСТЬ, Г.О. РАМЕНСКИЙ, Д.ВЛАДИМИРОВКА, СТР.1, ПОМЕЩ.1, | AF32: 46000 | AG32: 504001001 | AH32: SK | AI32: СЛОВАКИЯ | AJ32: 218731.15 | AK32: 1215000062364 | AL32: 5040173714 | AM32: ООО "Р.И.П.С." | AN32: 140166, МОСКОВСКАЯ ОБЛАСТЬ, Г.О. РАМЕНСКИЙ, Д.ВЛАДИМИРОВКА, СТР.1, ПОМЕЩ.1, | AO32: 46000 | AP32: 504001001 | AQ32: SK | AR32: СЛОВАКИЯ | AS32: СЛОВАКИЯ | AT32: RU | AU32: РОССИЯ | AW32: 0 | AX32: FCA | AY32: НИТРА | BA32: EUR | BB32: 2030 | BE32: 102.2586 | BG32: 30 | BI32: - | BJ32: 99 | BQ32: 10113100 т/п Стабнинский | BS32: ОПЛОДОТВОРЕННЫЕ НЕПЛЕМЕННЫЕ ИНКУБАЦИОННЫЕ ЯЙЦА ИНДЕЙКИ (MELAGRIS GALLOPAVO L.) ДЛЯ ИНКУБАЦИИ И ВЫВЕДЕНИЯ ПОРОДЫ ИНДЕЕК, ДЛЯ ПОСЛЕДУЮЩЕГО ВЫРАЩИВАНИЯ И УБОЯ НА МЯСО, СВЕЖИЕ, ПОРОДЫ БЕЛАЯ ШИРОКОГРУДАЯ | BT32: =MIN(1,IFERROR(SEARCH(BT$2,$BS32),0)) -> 1 | BU32: =MIN(1,IFERROR(SEARCH(BU$2,$BS32),0)) -> 0 | BV32: =MAX(BT32,BU32) -> 1 | BW32: ОТСУТСТВУЕТ | BX32: BRANKO NITRA, A.S., ПЛЕМЗАВ.: SK-RH-NR-12 | BY32: 1 | BZ32: 0 | CA32: 1400 | CB32: ШТ | CE32: 1 | CF32: 0407191100 | CI32: SK | CJ32: 147 | CK32: ОООО-ЛП | CL32: 4000000 | CM32: 137 | CN32: 0 | CQ32: 2030 | CS32: 0 | CT32: 1 | CU32: 218731.15 | CV32: 2309.44 | CW32: 10 | CX32: 16.86 | DB32: 1125
B33: 1 | C33: 28.08.2023 | D33: 8 | E33: 10013160/280823/3379487 | F33: 10013160 | G33: 28.08.2023 | H33: 3379487 | I33: ИМ | J33: 40 | N33: BRANKO NITRA, A.S. | O33: 94905, , NITRA, NOVOZAMOCKA 184, | T33: 1 | U33: 4 | V33: 1175027024820 | W33: 5040151421 | X33: ООО "БРОННИЦКАЯ ПТИЦЕФАБРИКА" | Y33: 140157, МОСКОВСКАЯ ОБЛ., РАМЕНСКИЙ Г. О., ПОС. РЫЛЕЕВО, УЛ. 4-Й КМ (АВТОДОРОГА М | Z33: 46000 | AA33: 504001001 | AB33: 1175027024820 | AC33: 5040151421 | AD33: ООО "БРОННИЦКАЯ ПТИЦЕФАБРИКА" | AE33: 140157, МОСКОВСКАЯ ОБЛ., РАМЕНСКИЙ Г. О., ПОС. РЫЛЕЕВО, УЛ. 4-Й КМ (АВТОДОРОГА М | AF33: 46000 | AG33: 504001001 | AH33: SK | AI33: СЛОВАКИЯ | AJ33: 3548373.4 | AK33: 1175027024820 | AL33: 5040151421 | AM33: ООО "БРОННИЦКАЯ ПТИЦЕФАБРИКА" | AN33: 140157, МОСКОВСКАЯ ОБЛ., РАМЕНСКИЙ Г. О., ПОС. РЫЛЕЕВО, УЛ. 4-Й КМ (АВТОДОРОГА М | AO33: 46000 | AP33: 504001001 | AQ33: SK | AR33: СЛОВАКИЯ | AS33: СЛОВАКИЯ | AT33: RU | AU33: РОССИЯ | AW33: 0 | AX33: FCA | AY33: НИТРА | BA33: EUR | BB33: 33000 | BE33: 102.2586 | BG33: 30 | BI33: - | BJ33: 99 | BQ33: 10113100 т/п Стабнинский | BS33: ОПЛОДОТВОРЕННЫЕ НЕПЛЕМЕННЫЕ ИНКУБАЦИОННЫЕ ЯЙЦА ИНДЕЙКИ (MELAGRIS GALLOPAVO L.) ДЛЯ ИНКУБАЦИИ И ВЫВЕДЕНИЯ ПОРОДЫ ИНДЕЕК, ДЛЯ ПОСЛЕДУЮЩЕГО ВЫРАЩИВАНИЯ И УБОЯ НА МЯСО. СВЕЖИЕ, ПОРОДЫ БЕЛАЯ ШИРОКОГРУДАЯ, КРОСС БИГ 6, ВЕС ЯЙЦА 75-100 Г, УПАКОВАНО В | BT33: =MIN(1,IFERROR(SEARCH(BT$2,$BS33),0)) -> 1 | BU33: =MIN(1,IFERROR(SEARCH(BU$2,$BS33),0)) -> 0 | BV33: =MAX(BT33,BU33) -> 1 | BW33: ОТСУТСТВУЕТ | BX33: BRANKO NITRA, A.S. ПЛЕМЗАВ.: SK-RH-NR-12, SK-RH-NR-18 | BY33: 4 | BZ33: 0 | CA33: 22000 | CB33: ШТ | CE33: 1 | CF33: 0407191100 | CI33: SK | CJ33: 2310 | CK33: ОООО-ЛП | CL33: 4000000 | CM33: 2145 | CN33: 0 | CQ33: 33000 | CS33: 0 | CT33: 1 | CU33: 3548373.4 | CV33: 37465 | CW33: 10 | CX33: 17.47 | DB33: 1186
B34: 1 | C34: 27.08.2023 | D34: 8 | E34: 10013160/270823/5012525 | F34: 10013160 | G34: 27.08.2023 | H34: 5012525 | I34: ИМ | J34: 40 | N34: NAGISZ ZRT. | O34: 4181, , NADUDVAR, FO UT 119, | T34: 1 | U34: 724 | V34: 1047796588146 | W34: 7710553010 | X34: ООО "АГРОИМПОРТ" | Y34: 143421, МОСКОВСКАЯ ОБЛ., КРАСНОГОРСКИЙ Р-Н, 26 КМ А/Д "БАЛТИЯ", БЦ "РИГА-ЛЕНД", | Z34: 46000 | AA34: 502401001 | AB34: 1047796588146 | AC34: 7710553010 | AD34: ООО "АГРОИМПОРТ" | AE34: 143421, МОСКОВСКАЯ ОБЛ., КРАСНОГОРСКИЙ Р-Н, 26 КМ А/Д "БАЛТИЯ", БЦ "РИГА-ЛЕНД", | AF34: 46000 | AG34: 502401001 | AH34: HU | AI34: ВЕНГРИЯ | AJ34: 18774679 | AK34: 1047796588146 | AL34: 7710553010 | AM34: ООО "АГРОИМПОРТ" | AN34: 143421, МОСКОВСКАЯ ОБЛ., КРАСНОГОРСКИЙ Р-Н, 26 КМ А/Д "БАЛТИЯ", БЦ "РИГА-ЛЕНД", | AO34: 46000 | AP34: 502401001 | AQ34: HU | AR34: ВЕНГРИЯ | AS34: ВЕНГРИЯ | AT34: RU | AU34: РОССИЯ | AW34: 0 | AX34: FCA | AY34: NADUDVAR | BA34: EUR | BB34: 181000 | BE34: 102.2586 | BI34: - | BJ34: 99 | BQ34: 10413090 т/п Пензенский областной | BS34: ИНДЮШАЧЬИ ЯЙЦА ДЛЯ ИНКУБАЦИИ, ОПЛОДОТВОРЕННЫЕ, MELEAGRIS GALLOPAVO L., ПОРОДА БЕЛАЯ ШИРОКОГРУДАЯ КРОССА БИГ-6, РАЗМЕЩЕНЫ С ЦЕЛЬЮ ПРЕДОТВРАЩЕНИЯ БОЯ И УНИЧТОЖЕНИЯ В КАРТОННЫХ КОРОБКАХ | BT34: =MIN(1,IFERROR(SEARCH(BT$2,$BS34),0)) -> 0 | BU34: =MIN(1,IFERROR(SEARCH(BU$2,$BS34),0)) -> 1 | BV34: =MAX(BT34,BU34) -> 1 | BW34: ОТСУТСТВУЕТ | BX34: NAGISZ ZRT. | BY34: 724 | CA34: 144800 | CB34: ШТ | CE34: 1 | CF34: 0407191100 | CI34: HU | CJ34: 15928 | CK34: ОООО-ЛП | CL34: 4000000 | CM34: 15204 | CQ34: 181000 | CS34: 0 | CT34: 1 | CU34: 18774679 | CV34: 198229.77 | CW34: 10 | CX34: 13.04 | DB34: 1047
B35: 1 | C35: 22.08.2023 | D35: 8 | E35: 10013160/220823/3372136 | F35: 10013160 | G35: 22.08.2023 | H35: 3372136 | I35: ИМ | J35: 40 | N35: NAGISZ ZRT. | O35: 4181, , NADUDVAR, FO UT 119, | T35: 1 | U35: 543 | V35: 1047796588146 | W35: 7710553010 | X35: ООО "АГРОИМПОРТ" | Y35: 143421, МОСКОВСКАЯ ОБЛ., КРАСНОГОРСКИЙ Р-Н, 26 КМ А/Д "БАЛТИЯ", БЦ "РИГА-ЛЕНД", | Z35: 46000 | AA35: 502401001 | AB35: 1047796588146 | AC35: 7710553010 | AD35: ООО "АГРОИМПОРТ" | AE35: 143421, МОСКОВСКАЯ ОБЛ., КРАСНОГОРСКИЙ Р-Н, 26 КМ А/Д "БАЛТИЯ", БЦ "РИГА-ЛЕНД", | AF35: 46000 | AG35: 502401001 | AH35: HU | AI35: ВЕНГРИЯ | AJ35: 14190822 | AK35: 1047796588146 | AL35: 7710553010 | AM35: ООО "АГРОИМПОРТ" | AN35: 143421, МОСКОВСКАЯ ОБЛ., КРАСНОГОРСКИЙ Р-Н, 26 КМ А/Д "БАЛТИЯ", БЦ "РИГА-ЛЕНД", | AO35: 46000 | AP35: 502401001 | AQ35: HU | AR35: ВЕНГРИЯ | AS35: ВЕНГРИЯ | AT35: RU | AU35: РОССИЯ | AW35: 0 | AX35: FCA | AY35: NADUDVAR | BA35: EUR | BB35: 135750 | BE35: 102.5719 | BI35: - | BJ35: 99 | BQ35: 10413090 т/п Пензенский областной | BS35: ИНДЮШАЧЬИ ЯЙЦА ДЛЯ ИНКУБАЦИИ, ОПЛОДОТВОРЕННЫЕ, MELEAGRIS GALLOPAVO L., ПОРОДА БЕЛАЯ ШИРОКОГРУДАЯ КРОССА БИГ-6, РАЗМЕЩЕНЫ С ЦЕЛЬЮ ПРЕДОТВРАЩЕНИЯ БОЯ И УНИЧТОЖЕНИЯ В КАРТОННЫХ КОРОБКАХ | BT35: =MIN(1,IFERROR(SEARCH(BT$2,$BS35),0)) -> 0 | BU35: =MIN(1,IFERROR(SEARCH(BU$2,$BS35),0)) -> 1 | BV35: =MAX(BT35,BU35) -> 1 | BW35: ОТСУТСТВУЕТ | BX35: NAGISZ ZRT. | BY35: 543 | BZ35: 0 | CA35: 108600 | CB35: ШТ | CE35: 1 | CF35: 0407191100 | CI35: HU | CJ35: 11946 | CK35: ОООО-ЛП | CL35: 4000000 | CM35: 11403 | CN35: 0 | CQ35: 135750 | CS35: 0 | CT35: 1 | CU35: 14190822 | CV35: 150737.84 | CW35: 10 | CX35: 13.22 | DB35: 1364
B36: 1 | C36: 30.07.2023 | D36: 7 | E36: 10005030/300723/3202469 | F36: 10005030 | G36: 30.07.2023 | H36: 3202469 | I36: ИМ | J36: 40 | N36: CUDDY FARMS, A DIVISION OF HENDRIX GENETICS LIMITED | O36: 28429, ONТARIO, SТRAТHROY N7G 3H6, ROUТE #5, ... | R36: 1 | S36: 0 | T36: 1 | U36: 120 | V36: 1193668026507 | W36: 3613005236 | X36: ООО "ДОНСКАЯ ИНДЕЙКА" | Y36: 396347, ВОРОНЕЖСКАЯ ОБЛАСТЬ, М.Р-Н КАШИРСКИЙ, С.П. ДЗЕРЖИНСКОЕ, П.ИМ.ДЗЕРЖИНСКОГ | Z36: 20000 | AA36: 361301001 | AB36: 1193668026507 | AC36: 3613005236 | AD36: ООО "ДОНСКАЯ ИНДЕЙКА" | AE36: 396347, ВОРОНЕЖСКАЯ ОБЛАСТЬ, М.Р-Н КАШИРСКИЙ, С.П. ДЗЕРЖИНСКОЕ, П.ИМ.ДЗЕРЖИНСКОГ | AF36: 20000 | AG36: 361301001 | AH36: CA | AI36: КАНАДА | AJ36: 3718459.9 | AK36: 1193668026507 | AL36: 3613005236 | AM36: ООО "ДОНСКАЯ ИНДЕЙКА" | AN36: 396347, ВОРОНЕЖСКАЯ ОБЛАСТЬ, М.Р-Н КАШИРСКИЙ, С.П. ДЗЕРЖИНСКОЕ, П.ИМ.ДЗЕРЖИНСКОГ | AO36: 20000 | AP36: 361301001 | AQ36: CA | AR36: КАНАДА | AS36: КАНАДА | AT36: RU | AU36: РОССИЯ | AV36: 0 | AW36: 0 | AX36: CPT | AY36: МОСКВА | AZ36: 1 | BA36: EUR | BB36: 37200 | BC36: 3718460 | BD36: 40871.94 | BE36: 99.9586 | BF36: 010 | BG36: 40 | BH36: 23010677/3292/0000/2/1 | BI36: - | BJ36: 11 | BK36: 10001/311210/10001/10 | BM36: 141400 | BO36: МОСКВА | BP36: ТЕРРИТОРИЯ "АЭРОПОРТ ВНУКОВО", Д. 1, СТР. 19,,,. | BQ36: 10001020 т/п Аэропорт Внуково (грузовой) | BR36: 1 | BS36: ОПЛОДОТВОРЕННЫЕ ЯЙЦА ИНДЮШАЧЬИ ДЛЯ ИНКУБАЦИИ, КОД ОКП 98 4766 (OКПД2 01.47.23.140): | BT36: =MIN(1,IFERROR(SEARCH(BT$2,$BS36),0)) -> 0 | BU36: =MIN(1,IFERROR(SEARCH(BU$2,$BS36),0)) -> 1 | BV36: =MAX(BT36,BU36) -> 1 | BW36: CUDDY FARMS | BX36: CUDDY FARMS LIMITED 2008 | BY36: 120 | BZ36: 0 | CA36: 24000 | CB36: ШТ | CC36: 0 | CE36: 1 | CF36: 0407191100 | CI36: CA | CJ36: 2488 | CK36: ОООО-ЛП | CL36: 4000000 | CM36: 2160 | CN36: 0 | CQ36: 37200 | CR36: 3718460 | CS36: 0 | CT36: 1 | CU36: 3718459.9 | CV36: 40871.94 | CW36: 10 | CX36: 18.92 | DA36: ДЕНИСОВ ОЛЕГ ВИТАЛЬЕВИЧ | DB36: 609
B37: 1 | C37: 30.07.2023 | D37: 7 | E37: 10131010/300723/3265983 | F37: 10131010 | G37: 30.07.2023 | H37: 3265983 | I37: ИМ | J37: 40 | N37: MOORGUT KARTZFEHN TURKEY BREEDER GMBH | O37: 26219, ., BOSEL, KARТZ-VON-KAMEKE-ALLEE, 7... | R37: 1 | S37: 0 | T37: 1 | U37: 760 | V37: 1116829006910 | W37: 6829076796 | X37: ООО "ТАМБОВСКАЯ ИНДЕЙКА" | Y37: 392000, ТАМБОВСКАЯ ОБЛ., ТАМБОВ, УЛ. СТУДЕНЕЦКАЯ, Д.16А, КОРП.1, ПОМ.16 | Z37: 68000 | AA37: 682901001 | AB37: 1116829006910 | AC37: 6829076796 | AD37: ООО "ТАМБОВСКАЯ ИНДЕЙКА" | AE37: 392000, ТАМБОВСКАЯ ОБЛ., ТАМБОВ, УЛ. СТУДЕНЕЦКАЯ, Д.16А, КОРП.1, ПОМ.16 | AF37: 68000 | AG37: 682901001 | AH37: DE | AI37: ГЕРМАНИЯ | AJ37: 28364252 | AK37: 1116829006910 | AL37: 6829076796 | AM37: ООО "ТАМБОВСКАЯ ИНДЕЙКА" | AN37: 392000, ТАМБОВСКАЯ ОБЛ., ТАМБОВ, УЛ. СТУДЕНЕЦКАЯ, Д.16А, КОРП.1, ПОМ.16 | AO37: 68000 | AP37: 682901001 | AQ37: DE | AR37: ГЕРМАНИЯ | AS37: ГЕРМАНИЯ | AT37: RU | AU37: РОССИЯ | AV37: 2 | AW37: 0 | AX37: DAP | AY37: ТАМБОВ | AZ37: 1 | BA37: EUR | BB37: 283760 | BC37: 28364252 | BD37: 311769.43 | BE37: 99.9586 | BF37: 010 | BH37: 22121027/3292/0000/2/1 | BI37: - | BJ37: 11 | BK37: 10102/011010/10036/1 | BM37: 243025 | BN37: БРЯНСКАЯ ОБЛ. | BO37: Г.НОВОЗЫБКОВ | BP37: УЛ.РОС,,,. | BQ37: 10102073 ОТО и ТК №3 т/п Новозыбковский | BR37: 1 | BS37: ЯЙЦА ИНДЕЕК ДОМАШНИХ,СВЕЖИЕ,ОПЛОДОТВОРЕННЫЕ ДЛЯ ИНКУБАЦИИ,ПОРОДЫ BUT BIG-6 (WHITE WIDE CASE),НЕ ПЛЕМЕННЫЕ,ДЛЯ ПОСЛЕДУЮЩЕГО ВЫРАЩИВАНИЯ И УБОЯ НА МЯСО СВЕЖЕЕ,В КАРТОННЫХ КОРОБКАХ | BT37: =MIN(1,IFERROR(SEARCH(BT$2,$BS37),0)) -> 0 | BU37: =MIN(1,IFERROR(SEARCH(BU$2,$BS37),0)) -> 0 | BV37: =MAX(BT37,BU37) -> 0 | BW37: KARTZFEHN | BX37: KARTZFEHN MARKISCHE PUTEN GMBH | BY37: 760 | BZ37: 0 | CA37: 152000 | CB37: ШТ | CC37: 0 | CE37: 1 | CF37: 0407191100 | CI37: DE | CJ37: 16720 | CK37: ОООО-ЛП | CL37: 4000000 | CM37: 15200 | CN37: 0 | CQ37: 283760 | CR37: 28364252 | CS37: 0 | CT37: 1 | CU37: 28364252 | CV37: 311769.43 | CW37: 10 | CX37: 20.51 | CY37: 933 | CZ37: 0933/01-20-010 | DA37: АЛИМПИЕВА АННА ВАЛЕРЬЕВНА | DB37: 213
B38: 1 | C38: 25.07.2023 | D38: 7 | E38: 10005030/250723/3198023 | F38: 10005030 | G38: 25.07.2023 | H38: 3198023 | I38: ИМ | J38: 40 | N38: CUDDY FARMS LIMITED 2008 | O38: , , RR #5-28429 CENТRE ROAD, SТRAТHROY ON N76 3H6, ... | R38: 1 | S38: 0 | T38: 1 | U38: 160 | V38: 1144813001046 | W38: 4805016071 | X38: ООО "КРИВЕЦ-ПТИЦА" | Y38: 399174, ЛИПЕЦКАЯ ОБЛ., ДОБРОВСКИЙ РАЙОН, СЕЛО КРИВЕЦ, УЛ. НОВАЯ, Д.2, ПОМЕЩЕНИЕ | Z38: 42000 | AA38: 480501001 | AB38: 1144813001046 | AC38: 4805016071 | AD38: ООО "КРИВЕЦ-ПТИЦА" | AE38: 399174, ЛИПЕЦКАЯ ОБЛ., ДОБРОВСКИЙ РАЙОН, СЕЛО КРИВЕЦ, УЛ. НОВАЯ, Д.2, ПОМЕЩЕНИЕ | AF38: 42000 | AG38: 480501001 | AH38: CA | AI38: КАНАДА | AJ38: 4817347.2 | AK38: 1144813001046 | AL38: 4805016071 | AM38: ООО "КРИВЕЦ-ПТИЦА" | AN38: 399174, ЛИПЕЦКАЯ ОБЛ., ДОБРОВСКИЙ РАЙОН, СЕЛО КРИВЕЦ, УЛ. НОВАЯ, Д.2, ПОМЕЩЕНИЕ | AO38: 42000 | AP38: 480501001 | AQ38: CA | AR38: КАНАДА | AS38: КАНАДА | AT38: RU | AU38: РОССИЯ | AV38: 0 | AW38: 0 | AX38: CPT | AY38: МОСКВА | AZ38: 1 | BA38: EUR | BB38: 48000 | BC38: 4817347 | BD38: 53236.83 | BE38: 100.3614 | BF38: 010 | BG38: 40 | BH38: 22121474/3292/0000/2/1 | BI38: - | BJ38: 11 | BK38: 10001/311210/10001/10 | BM38: 141400 | BO38: МОСКВА | BP38: ТЕРРИТОРИЯ "АЭРОПОРТ ВНУКОВО", Д. 1, СТР. 19,,,. | BQ38: 10001020 т/п Аэропорт Внуково (грузовой) | BR38: 1 | BS38: ОПЛОДОТВОРЕННЫЕ ЯЙЦА ИНДЮШАЧЬИ ДЛЯ ИНКУБАЦИИ, КОД ОКП 98 4766 (ОКПД2 01.47.23.140): ЦЕЛЬ ВВОЗА: ИНКУБИРOВАНИЕ И ДАЛЬНЕЙШЕЕ ВЫРАЩИВАНИЕ. | BT38: =MIN(1,IFERROR(SEARCH(BT$2,$BS38),0)) -> 0 | BU38: =MIN(1,IFERROR(SEARCH(BU$2,$BS38),0)) -> 1 | BV38: =MAX(BT38,BU38) -> 1 | BW38: CUDDY FARMS | BX38: CUDDY FARMS LIMITED 2008 | BY38: 160 | BZ38: 0 | CA38: 32000 | CB38: ШТ | CC38: 0 | CE38: 1 | CF38: 0407191100 | CI38: CA | CJ38: 3200 | CK38: ОООО-ЛП | CL38: 4000000 | CM38: 2880 | CN38: 0 | CQ38: 48000 | CR38: 4817347 | CS38: 0 | CT38: 1 | CU38: 4817347.2 | CV38: 53236.83 | CW38: 10 | CX38: 18.49 | DA38: ШАДРИН ДЕНИС НИКОЛАЕВИЧ | DB38: 760
B39: 1 | C39: 24.07.2023 | D39: 7 | E39: 10013160/240723/3330597 | F39: 10013160 | G39: 24.07.2023 | H39: 3330597 | I39: ИМ | J39: 40 | N39: GRIMAUD FRERES SELECTION S.A.S. | O39: 49450, , SEVREMOINE, ROUSSAY, RA3 LA CORBIERE, ... | R39: 1 | S39: 0 | T39: 1 | U39: 78 | V39: 1217700533511 | W39: 9704098398 | X39: ООО "ИМПОРТЭГГЗ" | Y39: 117393, , МОСКВА, УЛ. АРХИТЕКТОРА ВЛАСОВА, Д. 55 | Z39: 45000 | AA39: 772801001 | AB39: 1217700533511 | AC39: 9704098398 | AD39: ООО "ИМПОРТЭГГЗ" | AE39: 117393, , МОСКВА, УЛ. АРХИТЕКТОРА ВЛАСОВА, Д. 55 | AF39: 45000 | AG39: 772801001 | AH39: FR | AI39: ФРАНЦИЯ | AJ39: 9336277.2 | AK39: 1217700533511 | AL39: 9704098398 | AM39: ООО "ИМПОРТЭГГЗ" | AN39: 117393, , МОСКВА, УЛ. АРХИТЕКТОРА ВЛАСОВА, Д. 55 | AO39: 45000 | AP39: 772801001 | AQ39: FR | AR39: ФРАНЦИЯ | AS39: ФРАНЦИЯ | AT39: RU | AU39: РОССИЯ | AV39: 2 | AW39: 0 | AX39: FCA | AY39: MESLAY DU MAINE | AZ39: 1 | BA39: EUR | BB39: 88104.12 | BC39: 8868226 | BD39: 103295 | BE39: 100.6562 | BF39: 010 | BH39: 23070368/0354/0000/2/1 | BI39: - | BJ39: 11 | BK39: 10013/200111/10045/6 | BM39: 215119 | BN39: МОСКОВСКАЯ ОБЛ. | BO39: Г. КРАСНОЗНАМЕНСК | BP39: УЛ. БЕРЕЗОВАЯ АЛЛЕЯ 1/2; ОТКР.ПЛОЩАДКА: МО, Г. КРА | BQ39: 10013070 т/п Красноармейский | BR39: 1 | BS39: ИHКУБАЦИОННЫЕ ЯЙЦА ДОМАШНЕЙ ПТИЦЫ (УТИНЫЕ), ОПЛОДОТВОРЁННЫЕ (ДЛЯ ИНКУБАЦИИ). РАЗМЕЩЕНЫ С ЦЕЛЬЮ ПРЕДОТВРАЩЕНИЯ БОЯ И УНИЧТОЖЕНИЯ В КАРТОННЫХ КОРОБКАХ (200 ЯИЦ В ОДНОЙ КОРОБКЕ) | BT39: =MIN(1,IFERROR(SEARCH(BT$2,$BS39),0)) -> 0 | BU39: =MIN(1,IFERROR(SEARCH(BU$2,$BS39),0)) -> 0 | BV39: =MAX(BT39,BU39) -> 0 | BW39: ОТСУТСТВУЕТ | BX39: GRIMAUD FRERES SELECTION S.A.S. | BY39: 78 | BZ39: 0 | CA39: 15600 | CB39: ШТ | CC39: 0 | CE39: 1 | CF39: 0407191900 | CI39: FR | CJ39: 1528.8 | CK39: ОООО-ЛП | CL39: 4000000 | CM39: 1267 | CN39: 0 | CQ39: 88104.12 | CR39: 8868226 | CS39: 0 | CT39: 1 | CU39: 9336277.2 | CV39: 103295 | CW39: 10 | CX39: 81.53 | DA39: ПЯТАЕВ АЛЕКСЕЙ АНАТОЛЬЕВИЧ | DB39: 1267
B40: 1 | C40: 24.07.2023 | D40: 7 | E40: 10805010/240723/3012104 | F40: 10805010 | G40: 24.07.2023 | H40: 3012104 | I40: ИМ | J40: 40 | N40: PARTIZ 2000 KFT. | O40: 5540, , SZARVAS, RACOKZI U.6/1, ... | R40: 1 | S40: 0 | T40: 1 | U40: 60 | V40: 1132651023570 | W40: 2624801566 | X40: ООО "ПТИЧИЙ ДВОР" | Y40: 356800, СТАВРОПОЛЬСКИЙ КРАЙ, Г. БУДЕННОВСК, УЛ. ВОДНИКОВ, Д.7, | Z40: 07000 | AA40: 262401001 | AB40: 1132651023570 | AC40: 2624801566 | AD40: ООО "ПТИЧИЙ ДВОР" | AE40: 356800, СТАВРОПОЛЬСКИЙ КРАЙ, Г. БУДЕННОВСК, УЛ. ВОДНИКОВ, Д.7, | AF40: 07000 | AG40: 262401001 | AH40: HU | AI40: ВЕНГРИЯ | AJ40: 1791680.4 | AK40: 1132651023570 | AL40: 2624801566 | AM40: ООО "ПТИЧИЙ ДВОР" | AN40: 356800, СТАВРОПОЛЬСКИЙ КРАЙ, Г. БУДЕННОВСК, УЛ. ВОДНИКОВ, Д.7, | AO40: 07000 | AP40: 262401001 | AQ40: HU | AR40: ВЕНГРИЯ | AS40: ВЕНГРИЯ | AT40: RU | AU40: РОССИЯ | AV40: 2 | AW40: 0 | AX40: FCA | AY40: SZARVAS | AZ40: 1 | BA40: EUR | BB40: 16800 | BC40: 1691024 | BD40: 19822.85 | BE40: 100.6562 | BF40: 010 | BH40: 22050611/2673/0000/2/1 | BI40: - | BJ40: 99 | BN40: СМОЛЕНСКАЯ ОБЛ., СМОЛЕНСКИЙ Р-Н | BO40: С.П. СТАБЕНСКОЕ | BP40: СЕВЕРО-ВОСТОЧНЕЕ Д. СТАБНА, НА РАСТОЯНИИ 700 М,,,. | BQ40: 10113100 т/п Стабнинский | BR40: 1 | BS40: ОПЛОДОТВОРЕННЫЕ НЕПЛЕМЕННЫЕ ИНКУБАЦИОННЫЕ ЯЙЦА ИНДЕЙКИ (TURKEY HATCHING EGGS), ДЛЯ ИНКУБАЦИИ, ДЛЯ ПОСЛЕДУЮЩЕГО ВЫРАЩИВАНИЯ И УБОЯ НА МЯСО, СВЕЖИЕ, ПО 200 ШТ В КОРОБКЕ. | BT40: =MIN(1,IFERROR(SEARCH(BT$2,$BS40),0)) -> 1 | BU40: =MIN(1,IFERROR(SEARCH(BU$2,$BS40),0)) -> 0 | BV40: =MAX(BT40,BU40) -> 1 | BW40: PARTIZ 2000 | BX40: GALLI-EGGS KFT., ПЛЕМЗАВОД HU1009994 | BY40: 60 | BZ40: 0 | CA40: 12000 | CB40: ШТ | CC40: 0 | CE40: 1 | CF40: 0407191100 | CI40: HU | CJ40: 1260 | CK40: ОООО-ЛП | CL40: 4000000 | CM40: 1200 | CN40: 0 | CQ40: 16800 | CR40: 1691024 | CS40: 0 | CT40: 1 | CU40: 1791680.4 | CV40: 19822.85 | CW40: 10 | CX40: 16.52 | DA40: ПИЛИПЕНКО ОЛЬГА НИКОЛАЕВНА | DB40: 26
B41: 1 | C41: 23.07.2023 | D41: 7 | E41: 10005030/230723/3195878 | F41: 10005030 | G41: 23.07.2023 | H41: 3195878 | I41: ИМ | J41: 40 | N41: CUDDY FARMS LIMITED 2008 | O41: , , RR #5-28429 CENTRE ROAD, STRATHROY ON N76 3H6, .,.. | R41: 1 | S41: 0 | T41: 1 | U41: 282 | X41: ООО "СПП" | Y41: 453854, РЕСПУБЛИКА БАШКОРТОСТАН, М.Р-Н МЕЛЕУЗОВСКИЙ, Г.МЕЛЕУЗ, УЛ.СОВХОЗНАЯ, ЗДА | AD41: ООО "СПП" | AE41: 453854, РЕСПУБЛИКА БАШКОРТОСТАН, М.Р-Н МЕЛЕУЗОВСКИЙ, Г.МЕЛЕУЗ, УЛ.СОВХОЗНАЯ, ЗДА | AH41: CA | AI41: КАНАДА | AJ41: 8685824.8 | AM41: ООО "СПП" | AN41: 453854, РЕСПУБЛИКА БАШКОРТОСТАН, М.Р-Н МЕЛЕУЗОВСКИЙ, Г.МЕЛЕУЗ, УЛ.СОВХОЗНАЯ, ЗДА | AQ41: CA | AR41: КАНАДА | AS41: КАНАДА | AT41: RU | AU41: РОССИЯ | AV41: 0 | AW41: 0 | AX41: CPT | AY41: МОСКВА | AZ41: 1 | BA41: EUR | BB41: 86292 | BC41: 8685825 | BD41: 96098.5 | BE41: 100.6562 | BF41: 010 | BG41: 40 | BH41: 22120357/3292/0006/2/1 | BI41: - | BJ41: 11 | BK41: 10001/311210/10001/10 | BM41: 141400 | BO41: МОСКВА | BP41: ТЕРРИТОРИЯ "АЭРОПОРТ ВНУКОВО", Д. 1, СТР. 19,,,. | BQ41: 10001020 т/п Аэропорт Внуково (грузовой) | BR41: 1 | BS41: ОПЛОДОТВОРЕННЫЕ ЯЙЦА ИНДЮШАЧЬИ ДЛЯ ИНКУБАЦИИ, КОД ОКП 98 4766 (ОКПД2 01.47.23.140): ЦЕЛЬ ВBОЗА - ДЛЯ ИНКУБИРОВАНИЯ. | BT41: =MIN(1,IFERROR(SEARCH(BT$2,$BS41),0)) -> 0 | BU41: =MIN(1,IFERROR(SEARCH(BU$2,$BS41),0)) -> 1 | BV41: =MAX(BT41,BU41) -> 1 | BW41: CUDDY FARMS | BX41: CUDDY FARMS LIMITED 2008 | BY41: 282 | BZ41: 0 | CA41: 56400 | CB41: ШТ | CC41: 0 | CE41: 1 | CF41: 0407191100 | CI41: CA | CJ41: 5844 | CK41: ОООО-ЛП | CL41: 4000000 | CM41: 5076 | CN41: 0 | CQ41: 86292 | CR41: 8685825 | CS41: 0 | CT41: 1 | CU41: 8685824.8 | CV41: 96098.5 | CW41: 10 | CX41: 18.93 | DA41: БАЕРОВ АНДРЕЙ ВАСИЛЬЕВИЧ | DB41: 945
B42: 1 | C42: 22.07.2023 | D42: 7 | E42: 10005030/220723/5006764 | F42: 10005030 | G42: 22.07.2023 | H42: 5006764 | I42: ИМ | J42: 40 | N42: CUDDY FARMS LIMITED 2008 | O42: N7G3H6, ONTARIO, STRATHROY, 28429 CENTRAL ROAD, R.R. # 5, .,.. | R42: 1 | T42: 1 | U42: 120 | V42: 1177746508235 | W42: 7751046971 | X42: ООО "ЭГМАРТ" | Y42: 108841, , Г. МОСКВА, Г. ТРОИЦК, УЛ. ТЕКСТИЛЬЩИКОВ, ДОМ 3 КОР. 3, ОФ. 4, | Z42: 45000 | AA42: 775101001 | AB42: 1177746508235 | AC42: 7751046971 | AD42: ООО "ЭГМАРТ" | AE42: 108841, , Г. МОСКВА, Г. ТРОИЦК, УЛ. ТЕКСТИЛЬЩИКОВ, ДОМ 3 КОР. 3, ОФ. 4, | AF42: 45000 | AG42: 775101001 | AH42: CA | AI42: КАНАДА | AJ42: 3671938.2 | AK42: 1177746508235 | AL42: 7751046971 | AM42: ООО "ЭГМАРТ" | AN42: 108841, , Г. МОСКВА, Г. ТРОИЦК, УЛ. ТЕКСТИЛЬЩИКОВ, ДОМ 3 КОР. 3, ОФ. 4, | AO42: 45000 | AP42: 775101001 | AQ42: CA | AR42: КАНАДА | AS42: КАНАДА | AT42: RU | AU42: РОССИЯ | AW42: 0 | AX42: CPT | AY42: Г МОСКВА | AZ42: 1 | BA42: EUR | BB42: 36480 | BC42: 3671938 | BD42: 40625.71 | BE42: 100.6562 | BF42: 010 | BG42: 40 | BH42: 22122630/3292/0000/2/1 | BI42: - | BJ42: 11 | BK42: 10001/311210/10001/10 | BM42: 141800 | BO42: МОСКВА | BP42: ТЕРРИТОРИЯ "АЭРОПОРТ ВНУКОВО", Д. 1, СТР. 19,,,. | BQ42: 10001020 т/п Аэропорт Внуково (грузовой) | BR42: 1 | BS42: ОПЛОДОТВОРЕННЫЕ ИНКУБАЦИОННЫЕ ЯЙЦА ИНДЕЕК (MELEAGRIS GALLOPAVAL.), ДЛЯ ИНКУБАЦИИ И ВЫВЕДЕНИЯ ИНДЕЕК, ДЛЯ ПОСЛЕДУЮЩЕГО ВЫРАЩИВАНИЯ И УБОЯ НА МЯСО, КРОССА "HYBRID CONVERTER"(БЕЛАЯ ШИРОКОГРУДАЯ), СВЕЖИЕ (В КОРОБКЕ ПО 200 ШT.): | BT42: =MIN(1,IFERROR(SEARCH(BT$2,$BS42),0)) -> 0 | BU42: =MIN(1,IFERROR(SEARCH(BU$2,$BS42),0)) -> 0 | BV42: =MAX(BT42,BU42) -> 0 | BW42: CUDDY | BX42: CUDDY FARMS LIMITED 2008 | BY42: 120 | CA42: 24000 | CB42: ШТ | CE42: 1 | CF42: 0407191100 | CI42: CA | CJ42: 2488 | CK42: ОООО-ЛП | CL42: 4000000 | CM42: 2160 | CQ42: 36480 | CR42: 3671938 | CS42: 0 | CT42: 1 | CU42: 3671938.2 | CV42: 40625.71 | CW42: 10 | CX42: 18.81 | DA42: ЕФРЕМОВ СЕРГЕЙ АРКАДЬЕВИЧ | DB42: 1164
B43: 1 | C43: 22.07.2023 | D43: 7 | E43: 10005030/220723/3195512 | F43: 10005030 | G43: 22.07.2023 | H43: 3195512 | I43: ИМ | J43: 40 | N43: CUDDY FARMS, A DIVISION OF HENDRIX GENETICS LIMITED | O43: 28429, ONTARIO, STRATHROY N7G 3H6, ROUTE #5, .,.. | R43: 1 | S43: 0 | T43: 1 | U43: 282 | V43: 1165658075703 | W43: 5607141393 | X43: ООО "ВОСТОЧНАЯ-АГРО" | Y43: 462353, ОРЕНБУРГСКАЯ ОБЛАСТЬ, Г.НОВОТРОИЦК, УЛ. ЗАВОДСКАЯ, Д.1, | Z43: 53000 | AA43: 560701001 | AB43: 1165658075703 | AC43: 5607141393 | AD43: ООО "ВОСТОЧНАЯ-АГРО" | AE43: 462353, ОРЕНБУРГСКАЯ ОБЛАСТЬ, Г.НОВОТРОИЦК, УЛ. ЗАВОДСКАЯ, Д.1, | AF43: 53000 | AG43: 560701001 | AH43: CA | AI43: КАНАДА | AJ43: 7862658.4 | AK43: 1165658075703 | AL43: 5607141393 | AM43: ООО "ВОСТОЧНАЯ-АГРО" | AN43: 462353, ОРЕНБУРГСКАЯ ОБЛАСТЬ, Г.НОВОТРОИЦК, УЛ. ЗАВОДСКАЯ, Д.1, | AO43: 53000 | AP43: 560701001 | AQ43: CA | AR43: КАНАДА | AS43: КАНАДА | AT43: RU | AU43: РОССИЯ | AV43: 0 | AW43: 0 | AX43: CPT | AY43: МОСКВА | AZ43: 1 | BA43: CAD | BB43: 114576.09 | BC43: 7904146 | BD43: 86991.13 | BE43: 68.6239 | BF43: 010 | BG43: 40 | BH43: 22120471/3292/0006/2/1 | BI43: - | BJ43: 11 | BK43: 10001/311210/10001/10 | BM43: 141426 | BO43: МОСКВА | BP43: ТЕРРИТОРИЯ "АЭРОПОРТ ВНУКОВО", Д. 1, СТР. 19,,,. | BQ43: 10001020 т/п Аэропорт Внуково (грузовой) | BR43: 1 | BS43: ОПЛОДОТВОРЕННЫЕ ЯЙЦА ИНДЮШАЧЬИ ДЛЯ ИНКУБАЦИИ, КОД ОКП 98 4766 (ОКПД2 01.47.23.140): ЦЕЛЬ ВВОЗА - ДЛЯ ИНКУБИРОВАНИЯ. | BT43: =MIN(1,IFERROR(SEARCH(BT$2,$BS43),0)) -> 0 | BU43: =MIN(1,IFERROR(SEARCH(BU$2,$BS43),0)) -> 1 | BV43: =MAX(BT43,BU43) -> 1 | BW43: CUDDY FARMS | BX43: CUDDY FARMS LIMITED 2008 | BY43: 282 | BZ43: 0 | CA43: 56400 | CB43: ШТ | CC43: 0 | CE43: 1 | CF43: 0407191100 | CI43: CA | CJ43: 5894 | CK43: ОООО-ЛП | CL43: 4000000 | CM43: 5076 | CN43: 0 | CQ43: 114576.09 | CR43: 7904146 | CS43: 0 | CT43: 1 | CU43: 7862658.4 | CV43: 86991.13 | CW43: 10 | CX43: 17.14 | DA43: БАЕРОВ АНДРЕЙ ВАСИЛЬЕВИЧ | DB43: 678
B44: 1 | C44: 21.07.2023 | D44: 7 | E44: 10013160/210723/3327588 | F44: 10013160 | G44: 21.07.2023 | H44: 3327588 | I44: ИМ | J44: 40 | N44: NAGISZ ZRT. | O44: 4181, , NADUDVAR, FO UT 119, .,.. | R44: 1 | S44: 0 | T44: 1 | U44: 495 | V44: 1047796588146 | W44: 7710553010 | X44: ООО "АГРОИМПОРТ" | Y44: 143421, МОСКОВСКАЯ ОБЛ., КРАСНОГОРСКИЙ Р-Н, 26 КМ А/Д "БАЛТИЯ", БЦ "РИГА-ЛЕНД", | Z44: 46000 | AA44: 502401001 | AB44: 1047796588146 | AC44: 7710553010 | AD44: ООО "АГРОИМПОРТ" | AE44: 143421, МОСКОВСКАЯ ОБЛ., КРАСНОГОРСКИЙ Р-Н, 26 КМ А/Д "БАЛТИЯ", БЦ "РИГА-ЛЕНД", | AF44: 46000 | AG44: 502401001 | AH44: HU | AI44: ВЕНГРИЯ | AJ44: 12902241 | AK44: 1047796588146 | AL44: 7710553010 | AM44: ООО "АГРОИМПОРТ" | AN44: 143421, МОСКОВСКАЯ ОБЛ., КРАСНОГОРСКИЙ Р-Н, 26 КМ А/Д "БАЛТИЯ", БЦ "РИГА-ЛЕНД", | AO44: 46000 | AP44: 502401001 | AQ44: HU | AR44: ВЕНГРИЯ | AS44: ВЕНГРИЯ | AT44: RU | AU44: РОССИЯ | AV44: 2 | AW44: 0 | AX44: FCA | AY44: NADUDVAR | AZ44: 1 | BA44: EUR | BB44: 123750 | BC44: 12601834 | BD44: 142009.93 | BE44: 101.833 | BF44: 010 | BH44: 22120524/3292/0000/2/1 | BI44: - | BJ44: 99 | BN44: ПЕНЗЕНСКАЯ | BO44: ПЕНЗА | BP44: АУСТРИНА,,,. | BQ44: 10413090 т/п Пензенский областной | BR44: 1 | BS44: ИНДЮШАЧЬИ ЯЙЦА ДЛЯ ИНКУБАЦИИ, ОПЛОДОТВОРЕННЫЕ, MELEAGRIS GALLOPAVO L., ПОРОДА БЕЛАЯ ШИРОКОГРУДАЯ КРОССА БИГ-6, РАЗМЕЩЕНЫ С ЦЕЛЬЮ ПРЕДОТВРАЩЕНИЯ БОЯ И УНИЧТОЖEНИЯ В КАРТОННЫХ КОРОБКАХ | BT44: =MIN(1,IFERROR(SEARCH(BT$2,$BS44),0)) -> 0 | BU44: =MIN(1,IFERROR(SEARCH(BU$2,$BS44),0)) -> 1 | BV44: =MAX(BT44,BU44) -> 1 | BW44: ОТСУТСТВУЕТ | BX44: NAGISZ ZRT. | BY44: 495 | BZ44: 0 | CA44: 99000 | CB44: ШТ | CC44: 0 | CE44: 1 | CF44: 0407191100 | CI44: HU | CJ44: 10890 | CK44: ОООО-ЛП | CL44: 4000000 | CM44: 10395 | CN44: 0 | CQ44: 123750 | CR44: 12601834 | CS44: 0 | CT44: 1 | CU44: 12902241 | CV44: 142009.93 | CW44: 10 | CX44: 13.66 | DA44: КУДЕЛЬКИН ВЛАДИМИР ВЛАДИМИРОВИЧ | DB44: 1234
B45: 1 | C45: 20.07.2023 | D45: 7 | E45: 10131010/190723/5009183 | F45: 10131010 | G45: 19.07.2023 | H45: 5009183 | I45: ИМ | J45: 40 | N45: MOORGUT KARTZFEHN TURKEY BREEDER GMBH | O45: 26219, ., BOSEL, KARTZ-VON-KAMEKE-ALLEE, 7.,.. | R45: 1 | T45: 1 | U45: 760 | V45: 1116829006910 | W45: 6829076796 | X45: ООО "ТАМБОВСКАЯ ИНДЕЙКА" | Y45: 392000, ТАМБОВСКАЯ ОБЛ., ТАМБОВ, УЛ. СТУДЕНЕЦКАЯ, Д.16А, КОРП.1, ПОМ.16 | Z45: 68000 | AA45: 682901001 | AB45: 1116829006910 | AC45: 6829076796 | AD45: ООО "ТАМБОВСКАЯ ИНДЕЙКА" | AE45: 392000, ТАМБОВСКАЯ ОБЛ., ТАМБОВ, УЛ. СТУДЕНЕЦКАЯ, Д.16А, КОРП.1, ПОМ.16 | AF45: 68000 | AG45: 682901001 | AH45: DE | AI45: ГЕРМАНИЯ | AJ45: 28951210 | AK45: 1116829006910 | AL45: 6829076796 | AM45: ООО "ТАМБОВСКАЯ ИНДЕЙКА" | AN45: 392000, ТАМБОВСКАЯ ОБЛ., ТАМБОВ, УЛ. СТУДЕНЕЦКАЯ, Д.16А, КОРП.1, ПОМ.16 | AO45: 68000 | AP45: 682901001 | AQ45: DE | AR45: ГЕРМАНИЯ | AS45: ГЕРМАНИЯ | AT45: RU | AU45: РОССИЯ | AV45: 2 | AW45: 0 | AX45: DAP | AY45: ТАМБОВ | AZ45: 1 | BA45: EUR | BB45: 283760 | BC45: 28951210 | BD45: 319230.55 | BE45: 102.0271 | BF45: 010 | BH45: 22121027/3292/0000/2/1 | BI45: - | BJ45: 11 | BK45: 10102/011010/10036/1 | BM45: 243025 | BN45: БРЯНСКАЯ ОБЛ. | BO45: Г.НОВОЗЫБКОВ | BP45: УЛ.РОС,,,. | BQ45: 10102073 ОТО и ТК №3 т/п Новозыбковский | BR45: 1 | BS45: ЯЙЦА ИНДЕЕК ДОМАШНИХ, СBЕЖИЕ, ОПЛОДОТВОРЕННЫЕ ДЛЯ ИНКУБАЦИИ, ПОРОДЫ BUT BIG-6 (WHITE WIDE CASE), НЕ ПЛЕМЕННЫЕ, ДЛЯ ПОСЛЕДУЮЩЕГО ВЫРАЩИВАНИЯ И УБОЯ НА МЯСО СВЕЖЕЕ, В КАРТОННЫХ КОРОБКАХ | BT45: =MIN(1,IFERROR(SEARCH(BT$2,$BS45),0)) -> 0 | BU45: =MIN(1,IFERROR(SEARCH(BU$2,$BS45),0)) -> 0 | BV45: =MAX(BT45,BU45) -> 0 | BW45: KARTZFEHN | BX45: KARTZFEHN MARKISCHE PUTEN GMBH | BY45: 760 | CA45: 152000 | CB45: ШТ | CE45: 1 | CF45: 0407191100 | CI45: DE | CJ45: 16720 | CK45: ОООО-ЛП | CL45: 4000000 | CM45: 15200 | CQ45: 283760 | CR45: 28951210 | CS45: 0 | CT45: 1 | CU45: 28951210 | CV45: 319230.55 | CW45: 10 | CX45: 21 | CY45: 933 | CZ45: 0933/01-20-010 | DA45: АЛИМПИЕВА АННА ВАЛЕРЬЕВНА | DB45: 180
B46: 1 | C46: 19.07.2023 | D46: 7 | E46: 10005030/190723/3192627 | F46: 10005030 | G46: 19.07.2023 | H46: 3192627 | I46: ИМ | J46: 40 | N46: AVIAGEN TURKEYS LTD. | O46: , CHESTER CH3 9GA, TATTENHALL, CHOWLEY OAK BUSINESS PARK, CHOWLEY 5.,.. | R46: 1 | S46: 0 | T46: 1 | U46: 228 | V46: 1047796588146 | W46: 7710553010 | X46: ООО "АГРОИМПОРТ" | Y46: 143421, МОСКОВСКАЯ ОБЛ., КРАСНОГОРСКИЙ Р-Н, 26 КМ А/Д "БАЛТИЯ", БЦ "РИГА-ЛЕНД", | Z46: 46000 | AA46: 502401001 | AB46: 1047796588146 | AC46: 7710553010 | AD46: ООО "АГРОИМПОРТ" | AE46: 143421, МОСКОВСКАЯ ОБЛ., КРАСНОГОРСКИЙ Р-Н, 26 КМ А/Д "БАЛТИЯ", БЦ "РИГА-ЛЕНД", | AF46: 46000 | AG46: 502401001 | AH46: GB | AI46: СОЕДИНЕННОЕ КОРОЛЕВСТВО | AJ46: 31217028 | AK46: 1047796588146 | AL46: 7710553010 | AM46: ООО "АГРОИМПОРТ" | AN46: 143421, МОСКОВСКАЯ ОБЛ., КРАСНОГОРСКИЙ Р-Н, 26 КМ А/Д "БАЛТИЯ", БЦ "РИГА-ЛЕНД", | AO46: 46000 | AP46: 502401001 | AQ46: GB | AR46: СОЕДИНЕННОЕ КОРОЛЕВСТВО | AS46: СОЕДИНЕННОЕ КОРОЛЕВСТВО | AT46: RU | AU46: РОССИЯ | AV46: 0 | AW46: 0 | AX46: DAP | AY46: МОСКВА | AZ46: 1 | BA46: EUR | BB46: 305968 | BC46: 31217028 | BD46: 344214.59 | BE46: 102.0271 | BF46: 010 | BG46: 40 | BH46: 22030808/3292/0000/2/1 | BI46: - | BJ46: 11 | BK46: 10001/311210/10001/10 | BM46: 141400 | BN46: МОСКОВСКАЯ | BO46: ТЕРРИТОРИЯ АЭРОПОРТА | BP46: "ВНУКОВО" СТР.19,,,. | BQ46: 10001020 т/п Аэропорт Внуково (грузовой) | BR46: 1 | BS46: ПЛЕМЕННЫЕ ИНДЮШАЧЬИ ЯЙЦА ДЛЯ ИНКУБАЦИИ, ОПЛОДОТВОРЁННЫЕ, ДЛЯ ВЫВEДЕНИЯ РОДИТЕЛЬСКОГО СТАДА MELEAGRIS GALLOPAVO L. ПОРОДЫ БЕЛАЯ ШИРОКОГРУДАЯ BIG 6, РАЗМЕЩЕННЫЕ С ЦЕЛЬЮ ПРЕДОТВРАЩЕНИЯ БОЯ И УНИЧТОЖЕНИЯ В КАРТОННЫХ КОРОБКАХ. | BT46: =MIN(1,IFERROR(SEARCH(BT$2,$BS46),0)) -> 0 | BU46: =MIN(1,IFERROR(SEARCH(BU$2,$BS46),0)) -> 1 | BV46: =MAX(BT46,BU46) -> 1 | BW46: ... | BX46: AVIAGEN TURKEYS INC. | BY46: 228 | BZ46: 0 | CA46: 45600 | CB46: ШТ | CC46: 0 | CE46: 1 | CF46: 0407191100 | CI46: GB | CJ46: 4788 | CK46: ОООО-ПС | CL46: 4000000 | CM46: 4560 | CN46: 0 | CQ46: 305968 | CR46: 31217028 | CS46: 0 | CT46: 1 | CU46: 31217028 | CV46: 344214.59 | CW46: 10 | CX46: 75.49 | DA46: КУДЕЛЬКИН ВЛАДИМИР ВЛАДИМИРОВИЧ | DB46: 1176
B47: 1 | C47: 19.07.2023 | D47: 7 | E47: 10005030/190723/3192650 | F47: 10005030 | G47: 19.07.2023 | H47: 3192650 | I47: ИМ | J47: 40 | N47: CUDDY FARMS LIMITED 2008 | O47: , , RR #5-28429 CENTRE ROAD, STRATHROY ON N76 3H6, .,.. | R47: 1 | S47: 0 | T47: 1 | U47: 423 | X47: ООО "СПП" | Y47: 453854, РЕСПУБЛИКА БАШКОРТОСТАН, М.Р-Н МЕЛЕУЗОВСКИЙ, Г.МЕЛЕУЗ, УЛ.СОВХОЗНАЯ, ЗДА | AD47: ООО "СПП" | AE47: 453854, РЕСПУБЛИКА БАШКОРТОСТАН, М.Р-Н МЕЛЕУЗОВСКИЙ, Г.МЕЛЕУЗ, УЛ.СОВХОЗНАЯ, ЗДА | AH47: CA | AI47: КАНАДА | AJ47: 13206184 | AM47: ООО "СПП" | AN47: 453854, РЕСПУБЛИКА БАШКОРТОСТАН, М.Р-Н МЕЛЕУЗОВСКИЙ, Г.МЕЛЕУЗ, УЛ.СОВХОЗНАЯ, ЗДА | AQ47: CA | AR47: КАНАДА | AS47: КАНАДА | AT47: RU | AU47: РОССИЯ | AV47: 0 | AW47: 0 | AX47: CPT | AY47: МОСКВА | AZ47: 1 | BA47: EUR | BB47: 129438 | BC47: 13206184 | BD47: 145618 | BE47: 102.0271 | BF47: 010 | BG47: 40 | BH47: 22120357/3292/0006/2/1 | BI47: - | BJ47: 11 | BK47: 10001/311210/10001/10 | BM47: 141400 | BO47: МОСКВА | BP47: ТЕРРИТОРИЯ "АЭРОПОРТ ВНУКОВО", Д. 1, СТР. 19,,,. | BQ47: 10001020 т/п Аэропорт Внуково (грузовой) | BR47: 1 | BS47: ОПЛОДОТВОРЕННЫЕ ЯЙЦА ИНДЮШАЧЬИ ДЛЯ ИНКУБАЦИИ,КОД ОКП 98 4766 (ОКПД2 01.47.23.140): ЦЕЛЬ ВВОЗА - ДЛЯ ИНКУБИРОВАНИЯ. | BT47: =MIN(1,IFERROR(SEARCH(BT$2,$BS47),0)) -> 0 | BU47: =MIN(1,IFERROR(SEARCH(BU$2,$BS47),0)) -> 1 | BV47: =MAX(BT47,BU47) -> 1 | BW47: CUDDY FARMS | BX47: CUDDY FARMS LIMITED 2008 | BY47: 423 | BZ47: 0 | CA47: 84600 | CB47: ШТ | CC47: 0 | CE47: 1 | CF47: 0407191100 | CI47: CA | CJ47: 8460 | CK47: ОООО-ЛП | CL47: 4000000 | CM47: 7614 | CN47: 0 | CQ47: 129438 | CR47: 13206184 | CS47: 0 | CT47: 1 | CU47: 13206184 | CV47: 145618 | CW47: 10 | CX47: 19.13 | DA47: БАЕРОВ АНДРЕЙ ВАСИЛЬЕВИЧ | DB47: 751
B48: 1 | C48: 15.07.2023 | D48: 7 | E48: 10013160/150723/5004172 | F48: 10013160 | G48: 15.07.2023 | H48: 5004172 | I48: ИМ | J48: 40 | N48: NAGISZ ZRT. | O48: 4181, , NADUDVAR, FO UT 119, ,, | R48: 1 | T48: 1 | U48: 495 | V48: 1047796588146 | W48: 7710553010 | X48: ООО "АГРОИМПОРТ" | Y48: 143421, МОСКОВСКАЯ ОБЛ., КРАСНОГОРСКИЙ Р-Н, 26 КМ А/Д "БАЛТИЯ", БЦ "РИГА-ЛЕНД", | Z48: 46000 | AA48: 502401001 | AB48: 1047796588146 | AC48: 7710553010 | AD48: ООО "АГРОИМПОРТ" | AE48: 143421, МОСКОВСКАЯ ОБЛ., КРАСНОГОРСКИЙ Р-Н, 26 КМ А/Д "БАЛТИЯ", БЦ "РИГА-ЛЕНД", | AF48: 46000 | AG48: 502401001 | AH48: HU | AI48: ВЕНГРИЯ | AJ48: 12821939 | AK48: 1047796588146 | AL48: 7710553010 | AM48: ООО "АГРОИМПОРТ" | AN48: 143421, МОСКОВСКАЯ ОБЛ., КРАСНОГОРСКИЙ Р-Н, 26 КМ А/Д "БАЛТИЯ", БЦ "РИГА-ЛЕНД", | AO48: 46000 | AP48: 502401001 | AQ48: HU | AR48: ВЕНГРИЯ | AS48: ВЕНГРИЯ | AT48: RU | AU48: РОССИЯ | AV48: 2 | AW48: 0 | AX48: FCA | AY48: NADUDVAR | AZ48: 1 | BA48: EUR | BB48: 123750 | BC48: 12523401 | BD48: 142277.86 | BE48: 101.1992 | BF48: 010 | BH48: 22120524/3292/0000/2/1 | BI48: - | BJ48: 99 | BN48: ПЕНЗЕНСКАЯ | BO48: ПЕНЗА | BP48: АУСТРИНА,,,. | BQ48: 10413090 т/п Пензенский областной | BR48: 1 | BS48: ИНДЮШАЧЬИ ЯЙЦА ДЛЯ ИНКУБАЦИИ, ОПЛОДОТВОРЕННЫЕ, MELEAGRIS GALLOPAVO L.; ПОРОДА БЕЛАЯ ШИРОКОГРУДАЯ КРОССА БИГ-6, РАЗМЕЩЕНЫ С ЦЕЛЬЮ ПРЕДОТВРАЩЕНИЯ БОЯ И УНИЧТОЖЕНИЯ В КАРТОННЫХ КОРОБКАХ | BT48: =MIN(1,IFERROR(SEARCH(BT$2,$BS48),0)) -> 0 | BU48: =MIN(1,IFERROR(SEARCH(BU$2,$BS48),0)) -> 1 | BV48: =MAX(BT48,BU48) -> 1 | BW48: ОТСУТСТВУЕТ | BX48: NAGISZ ZRT. | BY48: 495 | CA48: 99000 | CB48: ШТ | CE48: 1 | CF48: 0407191100 | CI48: HU | CJ48: 10890 | CK48: ОООО-ЛП | CL48: 4000000 | CM48: 10395 | CQ48: 123750 | CR48: 12523401 | CS48: 0 | CT48: 1 | CU48: 12821939 | CV48: 142277.86 | CW48: 10 | CX48: 13.69 | DA48: КУДЕЛЬКИН ВЛАДИМИР ВЛАДИМИРОВИЧ | DB48: 1610
B49: 1 | C49: 14.07.2023 | D49: 7 | E49: 10013160/140723/5004015 | F49: 10013160 | G49: 14.07.2023 | H49: 5004015 | I49: ИМ | J49: 40 | N49: MOORGUT KARTZFEHN TURKEY BREEDER GMBH | O49: 26219, , BOSEL, KARTZ-VON-KAMEKE-ALLEE, 7,, | R49: 1 | T49: 1 | U49: 484 | V49: 1047796588146 | W49: 7710553010 | X49: ООО "АГРОИМПОРТ" | Y49: 143421, МОСКОВСКАЯ ОБЛ., КРАСНОГОРСКИЙ Р-Н, 26 КМ А/Д "БАЛТИЯ", БЦ "РИГА-ЛЕНД", | Z49: 46000 | AA49: 502401001 | AB49: 1047796588146 | AC49: 7710553010 | AD49: ООО "АГРОИМПОРТ" | AE49: 143421, МОСКОВСКАЯ ОБЛ., КРАСНОГОРСКИЙ Р-Н, 26 КМ А/Д "БАЛТИЯ", БЦ "РИГА-ЛЕНД", | AF49: 46000 | AG49: 502401001 | AH49: DE | AI49: ГЕРМАНИЯ | AJ49: 17542274 | AK49: 1047796588146 | AL49: 7710553010 | AM49: ООО "АГРОИМПОРТ" | AN49: 143421, МОСКОВСКАЯ ОБЛ., КРАСНОГОРСКИЙ Р-Н, 26 КМ А/Д "БАЛТИЯ", БЦ "РИГА-ЛЕНД", | AO49: 46000 | AP49: 502401001 | AQ49: DE | AR49: ГЕРМАНИЯ | AS49: ГЕРМАНИЯ | AT49: RU | AU49: РОССИЯ | AV49: 2 | AW49: 0 | AX49: DAP | AY49: С. ГОЛИЦЫНО | AZ49: 1 | BA49: EUR | BB49: 174240 | BC49: 17542274 | BD49: 194534.38 | BE49: 100.6788 | BF49: 010 | BH49: 20121446/1326/0000/2/1 | BI49: - | BJ49: 99 | BN49: ПЕНЗЕНСКАЯ | BO49: ПЕНЗА | BP49: АУСТРИНА,,,. | BQ49: 10413090 т/п Пензенский областной | BR49: 1 | BS49: ИНДЮШАЧЬИ ЯЙЦА ДЛЯ ИНКУБАЦИИ, ОПЛОДОТВОРЕННЫЕ, MELEAGRIS GALLOPAVO L., ПОРОДА БЕЛАЯ ШИРОКОГРУДАЯ КРОССА БИГ-6, КАТЕГОРИЯ БРОЙЛЕР РАЗМЕЩЕНЫ С ЦЕЛЬЮ ПРЕДОТВРАЩЕНИЯ БОЯ И УНИЧТОЖЕНИЯ В КАРТОННЫХ КОРОБКАХ | BT49: =MIN(1,IFERROR(SEARCH(BT$2,$BS49),0)) -> 0 | BU49: =MIN(1,IFERROR(SEARCH(BU$2,$BS49),0)) -> 1 | BV49: =MAX(BT49,BU49) -> 1 | BW49: ОТСУТСТВУЕТ | BX49: MOORGUT KARTZFEHN TURKEY BREEDER GMBH | BY49: 484 | CA49: 96800 | CB49: ШТ | CE49: 1 | CF49: 0407191100 | CI49: DE | CJ49: 10648 | CK49: ОООО-ЛП | CL49: 4000000 | CM49: 9680 | CQ49: 174240 | CR49: 17542274 | CS49: 0 | CT49: 1 | CU49: 17542274 | CV49: 194534.38 | CW49: 10 | CX49: 20.1 | DA49: КУДЕЛЬКИН ВЛАДИМИР ВЛАДИМИРОВИЧ | DB49: 1442
B50: 1 | C50: 13.07.2023 | D50: 7 | E50: 10013160/130723/5003818 | F50: 10013160 | G50: 13.07.2023 | H50: 5003818 | I50: ИМ | J50: 40 | N50: NAGISZ ZRT. | O50: 4181, , NADUDVAR, FO UT 119, ,, | R50: 1 | T50: 1 | U50: 495 | V50: 1047796588146 | W50: 7710553010 | X50: ООО "АГРОИМПОРТ" | Y50: 143421, МОСКОВСКАЯ ОБЛ., КРАСНОГОРСКИЙ Р-Н, 26 КМ А/Д "БАЛТИЯ", БЦ "РИГА-ЛЕНД", | Z50: 46000 | AA50: 502401001 | AB50: 1047796588146 | AC50: 7710553010 | AD50: ООО "АГРОИМПОРТ" | AE50: 143421, МОСКОВСКАЯ ОБЛ., КРАСНОГОРСКИЙ Р-Н, 26 КМ А/Д "БАЛТИЯ", БЦ "РИГА-ЛЕНД", | AF50: 46000 | AG50: 502401001 | AH50: HU | AI50: ВЕНГРИЯ | AJ50: 12655936 | AK50: 1047796588146 | AL50: 7710553010 | AM50: ООО "АГРОИМПОРТ" | AN50: 143421, МОСКОВСКАЯ ОБЛ., КРАСНОГОРСКИЙ Р-Н, 26 КМ А/Д "БАЛТИЯ", БЦ "РИГА-ЛЕНД", | AO50: 46000 | AP50: 502401001 | AQ50: HU | AR50: ВЕНГРИЯ | AS50: ВЕНГРИЯ | AT50: RU | AU50: РОССИЯ | AV50: 2 | AW50: 0 | AX50: FCA | AY50: NADUDVAR | AZ50: 1 | BA50: EUR | BB50: 123750 | BC50: 12361264 | BD50: 139651.25 | BE50: 99.889 | BF50: 010 | BH50: 22120524/3292/0000/2/1 | BI50: - | BJ50: 99 | BN50: ПЕНЗЕНСКАЯ | BO50: ПЕНЗА | BP50: АУСТРИНА,,,. | BQ50: 10413090 т/п Пензенский областной | BR50: 1 | BS50: ИНДЮШАЧЬИ ЯЙЦА ДЛЯ ИНКУБАЦИИ, ОПЛОДОТВОРЕННЫЕ, MELEAGRIS GALLOPAVO L., ПОРОДА БЕЛАЯ ШИРОКОГРУДАЯ КРОССА БИГ-6, РАЗМЕЩЕНЫ С ЦЕЛЬЮ ПРЕДОТВРАЩЕНИЯ БОЯ И УНИЧТОЖЕНИЯ В КАРТОННЫX КОРОБКАХ | BT50: =MIN(1,IFERROR(SEARCH(BT$2,$BS50),0)) -> 0 | BU50: =MIN(1,IFERROR(SEARCH(BU$2,$BS50),0)) -> 1 | BV50: =MAX(BT50,BU50) -> 1 | BW50: ОТСУТСТВУЕТ | BX50: NAGISZ ZRT. | BY50: 495 | CA50: 99000 | CB50: ШТ | CE50: 1 | CF50: 0407191100 | CI50: HU | CJ50: 10890 | CK50: ОООО-ЛП | CL50: 4000000 | CM50: 10395 | CQ50: 123750 | CR50: 12361264 | CS50: 0 | CT50: 1 | CU50: 12655936 | CV50: 139651.25 | CW50: 10 | CX50: 13.43 | DA50: КУДЕЛЬКИН ВЛАДИМИР ВЛАДИМИРОВИЧ | DB50: 1484
B51: 1 | C51: 10.07.2023 | D51: 7 | E51: 10323010/100723/3053577 | F51: 10323010 | G51: 10.07.2023 | H51: 3053577 | I51: ИМ | J51: 40 | N51: GRIMAUD FRERES SELECTION SAS | O51: 49450, , ROUSSAY, 3 LA CORBIERE, ,, | R51: 1 | S51: 0 | T51: 1 | U51: 67 | V51: 1026101066309 | W51: 6113000637 | X51: АО ППФ "ЮБИЛЕЙНАЯ" | Y51: 347716, РОСТОВСКАЯ ОБЛ., КАГАЛЬНИЦКИЙ Р-Н, С. НОВОБАТАЙСК, ПЕР. БАЗАРНЫЙ, Д. 18 | Z51: 60000 | AA51: 611301001 | AB51: 1026101066309 | AC51: 6113000637 | AD51: АО ППФ "ЮБИЛЕЙНАЯ" | AE51: 347716, РОСТОВСКАЯ ОБЛ., КАГАЛЬНИЦКИЙ Р-Н, С. НОВОБАТАЙСК, ПЕР. БАЗАРНЫЙ, Д. 18 | AF51: 60000 | AG51: 611301001 | AH51: FR | AI51: ФРАНЦИЯ | AJ51: 4177480.9 | AK51: 1026101066309 | AL51: 6113000637 | AM51: АО ППФ "ЮБИЛЕЙНАЯ" | AN51: 347716, РОСТОВСКАЯ ОБЛ., КАГАЛЬНИЦКИЙ Р-Н, С. НОВОБАТАЙСК, ПЕР. БАЗАРНЫЙ, Д. 18 | AO51: 60000 | AP51: 611301001 | AQ51: FR | AR51: ФРАНЦИЯ | AS51: ФРАНЦИЯ | AT51: RU | AU51: РОССИЯ | AV51: 2 | AW51: 0 | AX51: FCA | AY51: MESLAY DU MAINE | AZ51: 1 | BA51: EUR | BB51: 37200.6 | BC51: 3713323 | BD51: 45561.96 | BE51: 99.8189 | BF51: 010 | BH51: 23060002/2766/0009/2/1 | BI51: - | BJ51: 11 | BK51: 10013/200111/10045/6 | BM51: 215119 | BN51: МОСКОВСКАЯ ОБЛ. | BO51: Г. КРАСНОЗНАМЕНСК | BP51: УЛ. БЕРЕЗОВАЯ АЛЛЕЯ 1/2; ОТКР.ПЛОЩАДКА: МО, Г. КРА | BQ51: 10013070 т/п Красноармейский | BR51: 1 | BS51: ИНКУБАЦИОННЫЕ ЯЙЦА ДОМАШНЕЙ ПТИЦЫ, ОПЛОДОТВОРЁННЫЕ (ДЛЯ ИНКУБАЦИИ): ПЛЕМЕННОЕ ЯЙЦО УТКИ (ANAS PLATYRHYNCHOS L.) ПЕКИНСКОЙ-13400 ШТУК;РАЗМЕЩЕНЫ С ЦЕЛЬЮ ПРЕДОТВРАЩЕНИЯ БОЯ И УНИЧТОЖЕНИЯ В КАРТОННЫХ КОРОБКАХ (200 ЯИЦ В ОДНОЙ КОРОБКЕ) | BT51: =MIN(1,IFERROR(SEARCH(BT$2,$BS51),0)) -> 0 | BU51: =MIN(1,IFERROR(SEARCH(BU$2,$BS51),0)) -> 0 | BV51: =MAX(BT51,BU51) -> 0 | BW51: ОТСУТСТВУЕТ | BX51: GRIMAUD FRERES SELECTION SAS | BY51: 67 | BZ51: 0 | CA51: 13400 | CB51: ШТ | CC51: 0 | CE51: 1 | CF51: 0407191900 | CI51: FR | CJ51: 1313.2 | CK51: ОООО-ПС | CL51: 4000000 | CM51: 1072 | CN51: 0 | CQ51: 37200.6 | CR51: 3713323 | CS51: 0 | CT51: 1 | CU51: 4177480.9 | CV51: 45561.96 | CW51: 10 | CX51: 42.5 | DA51: ЧЕБОТАРЕВА ВИКТОРИЯ МИХАЙЛОВНА | DB51: 41
B52: 1 | C52: 09.07.2023 | D52: 7 | E52: 10013160/090723/5003568 | F52: 10013160 | G52: 09.07.2023 | H52: 5003568 | I52: ИМ | J52: 40 | N52: NAGISZ ZRT. | O52: 4181, , NADUDVAR, FO UT 119, .. | R52: 1 | T52: 1 | U52: 495 | V52: 1047796588146 | W52: 7710553010 | X52: ООО "АГРОИМПОРТ" | Y52: 143421, МОСКОВСКАЯ ОБЛ., КРАСНОГОРСКИЙ Р-Н, 26 КМ А/Д "БАЛТИЯ", БЦ "РИГА-ЛЕНД", | Z52: 46000 | AA52: 502401001 | AB52: 1047796588146 | AC52: 7710553010 | AD52: ООО "АГРОИМПОРТ" | AE52: 143421, МОСКОВСКАЯ ОБЛ., КРАСНОГОРСКИЙ Р-Н, 26 КМ А/Д "БАЛТИЯ", БЦ "РИГА-ЛЕНД", | AF52: 46000 | AG52: 502401001 | AH52: HU | AI52: ВЕНГРИЯ | AJ52: 12647055 | AK52: 1047796588146 | AL52: 7710553010 | AM52: ООО "АГРОИМПОРТ" | AN52: 143421, МОСКОВСКАЯ ОБЛ., КРАСНОГОРСКИЙ Р-Н, 26 КМ А/Д "БАЛТИЯ", БЦ "РИГА-ЛЕНД", | AO52: 46000 | AP52: 502401001 | AQ52: HU | AR52: ВЕНГРИЯ | AS52: ВЕНГРИЯ | AT52: RU | AU52: РОССИЯ | AV52: 2 | AW52: 0 | AX52: FCA | AY52: NADUDVAR | AZ52: 1 | BA52: EUR | BB52: 123750 | BC52: 12352589 | BD52: 137935.92 | BE52: 99.8189 | BF52: 010 | BH52: 22120524/3292/0000/2/1 | BI52: - | BJ52: 99 | BN52: ПЕНЗЕНСКАЯ | BO52: ПЕНЗА | BP52: АУСТРИНА,,,. | BQ52: 10413090 т/п Пензенский областной | BR52: 1 | BS52: ИНДЮШАЧЬИ ЯЙЦА ДЛЯ ИНКУБАЦИИ, ОПЛОДОТВОРЕННЫЕ, MELEAGRIS GALLOPAVO L., ПОРОДА БЕЛАЯ ШИРОКОГРУДАЯ КРОССА БИГ-6, РАЗМЕЩЕНЫ С ЦЕЛЬЮ ПРЕДОТВРАЩЕНИЯ БОЯ И УНИЧТОЖЕНИЯ В КАРТОННЫХ КОРОБКАХ | BT52: =MIN(1,IFERROR(SEARCH(BT$2,$BS52),0)) -> 0 | BU52: =MIN(1,IFERROR(SEARCH(BU$2,$BS52),0)) -> 1 | BV52: =MAX(BT52,BU52) -> 1 | BW52: ОТСУТСТВУЕТ | BX52: NAGISZ ZRT. | BY52: 495 | CA52: 99000 | CB52: ШТ | CE52: 1 | CF52: 0407191100 | CI52: HU | CJ52: 10890 | CK52: ОООО-ЛП | CL52: 4000000 | CM52: 10395 | CQ52: 123750 | CR52: 12352589 | CS52: 0 | CT52: 1 | CU52: 12647055 | CV52: 137935.92 | CW52: 10 | CX52: 13.27 | DA52: КУДЕЛЬКИН ВЛАДИМИР ВЛАДИМИРОВИЧ | DB52: 1629
B53: 1 | C53: 09.07.2023 | D53: 7 | E53: 10805010/090723/5002557 | F53: 10805010 | G53: 09.07.2023 | H53: 5002557 | I53: ИМ | J53: 40 | N53: PARTIZ 2000 KFT. | O53: 5540, , SZARVAS, RACOKZI U.6/1, .. | R53: 1 | T53: 1 | U53: 120 | V53: 1132651023570 | W53: 2624801566 | X53: ООО "ПТИЧИЙ ДВОР" | Y53: 356800, СТАВРОПОЛЬСКИЙ КРАЙ, Г. БУДЕННОВСК, УЛ. ВОДНИКОВ, Д.7, | Z53: 07000 | AA53: 262401001 | AB53: 1132651023570 | AC53: 2624801566 | AD53: ООО "ПТИЧИЙ ДВОР" | AE53: 356800, СТАВРОПОЛЬСКИЙ КРАЙ, Г. БУДЕННОВСК, УЛ. ВОДНИКОВ, Д.7, | AF53: 07000 | AG53: 262401001 | AH53: HU | AI53: ВЕНГРИЯ | AJ53: 3453733.9 | AK53: 1132651023570 | AL53: 2624801566 | AM53: ООО "ПТИЧИЙ ДВОР" | AN53: 356800, СТАВРОПОЛЬСКИЙ КРАЙ, Г. БУДЕННОВСК, УЛ. ВОДНИКОВ, Д.7, | AO53: 07000 | AP53: 262401001 | AQ53: HU | AR53: ВЕНГРИЯ | AS53: ВЕНГРИЯ | AT53: RU | AU53: РОССИЯ | AV53: 2 | AW53: 0 | AX53: FCA | AY53: SZARVAS | AZ53: 1 | BA53: EUR | BB53: 33600 | BC53: 3353915 | BD53: 37668.37 | BE53: 99.8189 | BF53: 010 | BH53: 22050611/2673/0000/2/1 | BI53: - | BJ53: 99 | BN53: СМОЛЕНСКАЯ ОБЛ., СМОЛЕНСКИЙ Р-Н | BO53: С.П. СТАБЕНСКОЕ | BP53: СЕВЕРО-ВОСТОЧНЕЕ Д. СТАБНА, НА РАСТОЯНИИ 700 М,,,. | BQ53: 10113100 т/п Стабнинский | BR53: 1 | BS53: ОПЛОДОТВОРЕННЫЕ НЕПЛЕМЕННЫЕ ИНКУБАЦИОННЫЕ ЯЙЦА ИНДЕЙКИ (TURKEY HATCHING EGGS),ДЛЯ ИНКУБАЦИИ,ДЛЯ ПОСЛЕДУЮЩЕГО ВЫРАЩИВАНИЯ И УБОЯ НА МЯСО,СВЕЖИЕ,ПО 200 ШТ В КОРОБКЕ. | BT53: =MIN(1,IFERROR(SEARCH(BT$2,$BS53),0)) -> 1 | BU53: =MIN(1,IFERROR(SEARCH(BU$2,$BS53),0)) -> 0 | BV53: =MAX(BT53,BU53) -> 1 | BW53: PARTIZ 2000 | BX53: GALLI-EGGS KFT., ПЛЕМЗАВОД HU1009994 | BY53: 120 | CA53: 24000 | CB53: ШТ | CE53: 1 | CF53: 0407191100 | CI53: HU | CJ53: 2520 | CK53: ОООО-ЛП | CL53: 4000000 | CM53: 2400 | CQ53: 33600 | CR53: 3353915 | CS53: 0 | CT53: 1 | CU53: 3453733.9 | CV53: 37668.37 | CW53: 10 | CX53: 15.7 | DA53: ПИЛИПЕНКО ОЛЬГА НИКОЛАЕВНА | DB53: 36
B54: 1 | C54: 09.07.2023 | D54: 7 | E54: 10005030/090723/3182862 | F54: 10005030 | G54: 09.07.2023 | H54: 3182862 | I54: ИМ | J54: 40 | N54: CUDDY FARMS LIMITED 2008 | O54: N7G 3H6, ONTARIO, STRATHROY, CENTRE ROAD, RR#5, 28429.. | R54: 1 | S54: 0 | T54: 1 | U54: 380 | V54: 1116829006910 | W54: 6829076796 | X54: ООО "ТАМБОВСКАЯ ИНДЕЙКА" | Y54: 392000, ТАМБОВСКАЯ ОБЛ., ТАМБОВ, УЛ. СТУДЕНЕЦКАЯ, Д.16А, КОРП.1, ПОМ.16 | Z54: 68000 | AA54: 682901001 | AB54: 1116829006910 | AC54: 6829076796 | AD54: ООО "ТАМБОВСКАЯ ИНДЕЙКА" | AE54: 392000, ТАМБОВСКАЯ ОБЛ., ТАМБОВ, УЛ. СТУДЕНЕЦКАЯ, Д.16А, КОРП.1, ПОМ.16 | AF54: 68000 | AG54: 682901001 | AH54: CA | AI54: КАНАДА | AJ54: 11986254 | AK54: 1116829006910 | AL54: 6829076796 | AM54: ООО "ТАМБОВСКАЯ ИНДЕЙКА" | AN54: 392000, ТАМБОВСКАЯ ОБЛ., ТАМБОВ, УЛ. СТУДЕНЕЦКАЯ, Д.16А, КОРП.1, ПОМ.16 | AO54: 68000 | AP54: 682901001 | AQ54: CA | AR54: КАНАДА | AS54: КАНАДА | AT54: RU | AU54: РОССИЯ | AV54: 0 | AW54: 0 | AX54: CPT | AY54: МОСКВА | AZ54: 1 | BA54: EUR | BB54: 120080 | BC54: 11986254 | BD54: 130728.85 | BE54: 99.8189 | BF54: 010 | BG54: 40 | BH54: 22112282/3292/0000/2/1 | BI54: - | BJ54: 11 | BK54: 10001/311210/10001/10 | BM54: 119027 | BN54: Г | BO54: МОСКВА | BP54: ТЕРРИТОРИЯ АЭРОПОРТ ВНУКОВО,,,. | BQ54: 10001020 т/п Аэропорт Внуково (грузовой) | BR54: 1 | BS54: ЯЙЦА ИНДЕЕК ДОМАШНИХ, СВЕЖИЕ, ОПЛОДОТВОРЕННЫЕ ДЛЯ ИНКУБАЦИИ, ПОРОДЫ HYBRID CONVERTER, НЕ ПЛЕМЕННЫЕ, ДЛЯ ПОСЛЕДУЮЩЕГО ВЫРАЩИВАНИЯ И УБОЯ НА MЯСО СВЕЖЕЕ, В КАРТОННЫХ КОРОБКАХ | BT54: =MIN(1,IFERROR(SEARCH(BT$2,$BS54),0)) -> 0 | BU54: =MIN(1,IFERROR(SEARCH(BU$2,$BS54),0)) -> 0 | BV54: =MAX(BT54,BU54) -> 0 | BW54: CUDDY | BX54: CUDDY FARMS | BY54: 380 | BZ54: 0 | CA54: 76000 | CB54: ШТ | CC54: 0 | CE54: 1 | CF54: 0407191100 | CI54: CA | CJ54: 7600 | CK54: ОООО-ЛП | CL54: 4000000 | CM54: 6840 | CN54: 0 | CQ54: 120080 | CR54: 11986254 | CS54: 0 | CT54: 1 | CU54: 11986254 | CV54: 130728.85 | CW54: 10 | CX54: 19.11 | CY54: 933 | CZ54: 0933/01-20-010 | DA54: АЛИМПИЕВА АННА ВАЛЕРЬЕВНА | DB54: 976
B55: 1 | C55: 08.07.2023 | D55: 7 | E55: 10131010/070723/3244384 | F55: 10131010 | G55: 07.07.2023 | H55: 3244384 | I55: ИМ | J55: 40 | N55: MOORGUT KARTZFEHN TURKEY BREEDER GMBH | O55: 26219, ., BOSEL, KARTZ-VON-KAMEKE-ALLEE, 7.. | R55: 1 | S55: 0 | T55: 1 | U55: 380 | V55: 1116829006910 | W55: 6829076796 | X55: ООО "ТАМБОВСКАЯ ИНДЕЙКА" | Y55: 392000, ТАМБОВСКАЯ ОБЛ., ТАМБОВ, УЛ. СТУДЕНЕЦКАЯ, Д.16А, КОРП.1, ПОМ.16 | Z55: 68000 | AA55: 682901001 | AB55: 1116829006910 | AC55: 6829076796 | AD55: ООО "ТАМБОВСКАЯ ИНДЕЙКА" | AE55: 392000, ТАМБОВСКАЯ ОБЛ., ТАМБОВ, УЛ. СТУДЕНЕЦКАЯ, Д.16А, КОРП.1, ПОМ.16 | AF55: 68000 | AG55: 682901001 | AH55: DE | AI55: ГЕРМАНИЯ | AJ55: 14571634 | AK55: 1116829006910 | AL55: 6829076796 | AM55: ООО "ТАМБОВСКАЯ ИНДЕЙКА" | AN55: 392000, ТАМБОВСКАЯ ОБЛ., ТАМБОВ, УЛ. СТУДЕНЕЦКАЯ, Д.16А, КОРП.1, ПОМ.16 | AO55: 68000 | AP55: 682901001 | AQ55: DE | AR55: ГЕРМАНИЯ | AS55: ГЕРМАНИЯ | AT55: RU | AU55: РОССИЯ | AV55: 2 | AW55: 0 | AX55: DAP | AY55: ТАМБОВ | AZ55: 1 | BA55: EUR | BB55: 144680 | BC55: 14571634 | BD55: 157412.91 | BE55: 100.7163 | BF55: 010 | BH55: 22121027/3292/0000/2/1 | BI55: - | BJ55: 11 | BK55: 10102/011010/10036/1 | BM55: 243025 | BN55: БРЯНСКАЯ ОБЛ. | BO55: Г.НОВОЗЫБКОВ | BP55: УЛ.РОС,,,. | BQ55: 10102073 ОТО и ТК №3 т/п Новозыбковский | BR55: 1 | BS55: ЯЙЦА ИНДЕЕК ДОМАШНИХ, СВЕЖИЕ, ОПЛОДОТВOРЕННЫЕ ДЛЯ ИНКУБАЦИИ, ПОРОДЫ BUT BIG-6 (WHITE WIDE CASE), НЕ ПЛЕМЕННЫЕ, ДЛЯ ПОСЛЕДУЮЩЕГО ВЫРАЩИВАНИЯ И УБОЯ НА МЯСО СВЕЖЕЕ, В КАРТОННЫХ КОРОБКАХ | BT55: =MIN(1,IFERROR(SEARCH(BT$2,$BS55),0)) -> 0 | BU55: =MIN(1,IFERROR(SEARCH(BU$2,$BS55),0)) -> 0 | BV55: =MAX(BT55,BU55) -> 0 | BW55: KARTZFEHN | BX55: KARTZFEHN MARKISCHE PUTEN GMBH | BY55: 380 | BZ55: 0 | CA55: 76000 | CB55: ШТ | CC55: 0 | CE55: 1 | CF55: 0407191100 | CI55: DE | CJ55: 8360 | CK55: ОООО-ЛП | CL55: 4000000 | CM55: 7600 | CN55: 0 | CQ55: 144680 | CR55: 14571634 | CS55: 0 | CT55: 1 | CU55: 14571634 | CV55: 157412.91 | CW55: 10 | CX55: 20.71 | CY55: 933 | CZ55: 0933/01-20-010 | DA55: АЛИМПИЕВА АННА ВАЛЕРЬЕВНА | DB55: 553
B56: 1 | C56: 08.07.2023 | D56: 7 | E56: 10005030/080723/3182349 | F56: 10005030 | G56: 08.07.2023 | H56: 3182349 | I56: ИМ | J56: 40 | N56: CUDDY FARMS LIMITED 2008 | O56: N7G3H6, ONTARIO, STRATHROY, 28429 CENTRAL ROAD, R.R. # 5, .. | R56: 1 | S56: 0 | T56: 1 | U56: 80 | V56: 1177746508235 | W56: 7751046971 | X56: ООО "ЭГМАРТ" | Y56: 108841, , Г. МОСКВА, Г. ТРОИЦК, УЛ. ТЕКСТИЛЬЩИКОВ, ДОМ 3 КОР. 3, ОФ. 4, | Z56: 45000 | AA56: 775101001 | AB56: 1177746508235 | AC56: 7751046971 | AD56: ООО "ЭГМАРТ" | AE56: 108841, , Г. МОСКВА, Г. ТРОИЦК, УЛ. ТЕКСТИЛЬЩИКОВ, ДОМ 3 КОР. 3, ОФ. 4, | AF56: 45000 | AG56: 775101001 | AH56: CA | AI56: КАНАДА | AJ56: 2427595.6 | AK56: 1177746508235 | AL56: 7751046971 | AM56: ООО "ЭГМАРТ" | AN56: 108841, , Г. МОСКВА, Г. ТРОИЦК, УЛ. ТЕКСТИЛЬЩИКОВ, ДОМ 3 КОР. 3, ОФ. 4, | AO56: 45000 | AP56: 775101001 | AQ56: CA | AR56: КАНАДА | AS56: КАНАДА | AT56: RU | AU56: РОССИЯ | AV56: 0 | AW56: 0 | AX56: CPT | AY56: Г МОСКВА | AZ56: 1 | BA56: EUR | BB56: 24320 | BC56: 2427596 | BD56: 26476.73 | BE56: 99.8189 | BF56: 010 | BG56: 40 | BH56: 22122630/3292/0000/2/1 | BI56: - | BJ56: 11 | BK56: 10001/311210/10001/10 | BM56: 141800 | BO56: МОСКВА | BP56: ТЕРРИТОРИЯ "АЭРОПОРТ ВНУКОВО", Д. 1, СТР. 19,,,. | BQ56: 10001020 т/п Аэропорт Внуково (грузовой) | BR56: 1 | BS56: ОПЛОДОТВОРЕННЫЕ ИНКУБАЦИОННЫЕ ЯЙЦА ИНДЕЕК (MELEAGRIS GALLOPAVAL.), ДЛЯ ИНКУБАЦИИ И ВЫВЕДЕНИЯ ИНДЕЕК, ДЛЯ ПОСЛЕДУЮЩЕГО ВЫРАЩИВАНИЯ И УБОЯ НА MЯСО, КРОССА "HYBRID CONVERTER"(БЕЛАЯ ШИРОКОГРУДАЯ), СВЕЖИЕ (В КОРОБКЕ ПО 200 ШТ.): | BT56: =MIN(1,IFERROR(SEARCH(BT$2,$BS56),0)) -> 0 | BU56: =MIN(1,IFERROR(SEARCH(BU$2,$BS56),0)) -> 0 | BV56: =MAX(BT56,BU56) -> 0 | BW56: CUDDY | BX56: CUDDY FARMS LIMITED 2008 | BY56: 80 | BZ56: 0 | CA56: 16000 | CB56: ШТ | CC56: 0 | CE56: 1 | CF56: 0407191100 | CI56: CA | CJ56: 1696 | CK56: ОООО-ЛП | CL56: 4000000 | CM56: 1440 | CN56: 0 | CQ56: 24320 | CR56: 2427596 | CS56: 0 | CT56: 1 | CU56: 2427595.6 | CV56: 26476.73 | CW56: 10 | CX56: 18.39 | DA56: ЕФРЕМОВ СЕРГЕЙ АРКАДЬЕВИЧ | DB56: 765
B57: 1 | C57: 07.07.2023 | D57: 7 | E57: 10005030/070723/3181790 | F57: 10005030 | G57: 07.07.2023 | H57: 3181790 | I57: ИМ | J57: 40 | N57: CUDDY FARMS, A DIVISION OF HENDRIX GENETICS LIMITED | O57: 28429, ONTARIO, STRATHROY N7G 3H6, ROUTE #5, .. | R57: 1 | S57: 0 | T57: 1 | U57: 183 | V57: 1193668026507 | W57: 3613005236 | X57: ООО "ДОНСКАЯ ИНДЕЙКА" | Y57: 396347, ВОРОНЕЖСКАЯ ОБЛАСТЬ, М.Р-Н КАШИРСКИЙ, С.П. ДЗЕРЖИНСКОЕ, П.ИМ.ДЗЕРЖИНСКОГ | Z57: 20000 | AA57: 361301001 | AB57: 1193668026507 | AC57: 3613005236 | AD57: ООО "ДОНСКАЯ ИНДЕЙКА" | AE57: 396347, ВОРОНЕЖСКАЯ ОБЛАСТЬ, М.Р-Н КАШИРСКИЙ, С.П. ДЗЕРЖИНСКОЕ, П.ИМ.ДЗЕРЖИНСКОГ | AF57: 20000 | AG57: 361301001 | AH57: CA | AI57: КАНАДА | AJ57: 5713635.7 | AK57: 1193668026507 | AL57: 3613005236 | AM57: ООО "ДОНСКАЯ ИНДЕЙКА" | AN57: 396347, ВОРОНЕЖСКАЯ ОБЛАСТЬ, М.Р-Н КАШИРСКИЙ, С.П. ДЗЕРЖИНСКОЕ, П.ИМ.ДЗЕРЖИНСКОГ | AO57: 20000 | AP57: 361301001 | AQ57: CA | AR57: КАНАДА | AS57: КАНАДА | AT57: RU | AU57: РОССИЯ | AV57: 0 | AW57: 0 | AX57: CPT | AY57: МОСКВА | AZ57: 1 | BA57: EUR | BB57: 56730 | BC57: 5713636 | BD57: 61722.66 | BE57: 100.7163 | BF57: 010 | BG57: 40 | BH57: 23010677/3292/0000/2/1 | BI57: - | BJ57: 11 | BK57: 10001/311210/10001/10 | BM57: 141400 | BO57: МОСКВА | BP57: ТЕРРИТОРИЯ "АЭРОПОРТ ВНУКОВО", Д. 1, СТР. 19,,,. | BQ57: 10001020 т/п Аэропорт Внуково (грузовой) | BR57: 1 | BS57: ОПЛОДОТВОРЕННЫЕ ЯЙЦА ИНДЮШАЧЬИ ДЛЯ ИНКУБАЦИИ, КОД ОКП 98 4766 (ОКПД2 01.47.23.140): | BT57: =MIN(1,IFERROR(SEARCH(BT$2,$BS57),0)) -> 0 | BU57: =MIN(1,IFERROR(SEARCH(BU$2,$BS57),0)) -> 1 | BV57: =MAX(BT57,BU57) -> 1 | BW57: CUDDY FARMS | BX57: CUDDY FARMS LIMITED 2008 | BY57: 183 | BZ57: 0 | CA57: 36600 | CB57: ШТ | CC57: 0 | CE57: 1 | CF57: 0407191100 | CI57: CA | CJ57: 3822 | CK57: ОООО-ЛП | CL57: 4000000 | CM57: 3294 | CN57: 0 | CQ57: 56730 | CR57: 5713636 | CS57: 0 | CT57: 1 | CU57: 5713635.7 | CV57: 61722.66 | CW57: 10 | CX57: 18.74 | DA57: ДЕНИСОВ ОЛЕГ ВИТАЛЬЕВИЧ | DB57: 1113
B58: 1 | C58: 07.07.2023 | D58: 7 | E58: 10005030/070723/3181831 | F58: 10005030 | G58: 07.07.2023 | H58: 3181831 | I58: ИМ | J58: 40 | N58: CUDDY FARMS LIMITED 2008 | O58: , , RR #5-28429 CENTRE ROAD, STRATHROY ON N76 3H6, .. | R58: 1 | S58: 0 | T58: 1 | U58: 564 | X58: ООО "СПП" | Y58: 453854, РЕСПУБЛИКА БАШКОРТОСТАН, М.Р-Н МЕЛЕУЗОВСКИЙ, Г.МЕЛЕУЗ, УЛ.СОВХОЗНАЯ, ЗДА | AD58: ООО "СПП" | AE58: 453854, РЕСПУБЛИКА БАШКОРТОСТАН, М.Р-Н МЕЛЕУЗОВСКИЙ, Г.МЕЛЕУЗ, УЛ.СОВХОЗНАЯ, ЗДА | AH58: CA | AI58: КАНАДА | AJ58: 17354756 | AM58: ООО "СПП" | AN58: 453854, РЕСПУБЛИКА БАШКОРТОСТАН, М.Р-Н МЕЛЕУЗОВСКИЙ, Г.МЕЛЕУЗ, УЛ.СОВХОЗНАЯ, ЗДА | AQ58: CA | AR58: КАНАДА | AS58: КАНАДА | AT58: RU | AU58: РОССИЯ | AV58: 0 | AW58: 0 | AX58: CPT | AY58: МОСКВА | AZ58: 1 | BA58: EUR | BB58: 172313.28 | BC58: 17354756 | BD58: 187478.12 | BE58: 100.7163 | BF58: 010 | BG58: 40 | BH58: 22120357/3292/0006/2/1 | BI58: - | BJ58: 11 | BK58: 10001/311210/10001/10 | BM58: 141400 | BO58: МОСКВА | BP58: ТЕРРИТОРИЯ "АЭРОПОРТ ВНУКОВО", Д. 1, СТР. 19,,,. | BQ58: 10001020 т/п Аэропорт Внуково (грузовой) | BR58: 1 | BS58: ОПЛОДОТВОРЕННЫЕ ЯЙЦА ИHДЮШАЧЬИ ДЛЯ ИНКУБАЦИИ, КОД ОКП 98 4766 (ОКПД2 01.47.23.140): ЦЕЛЬ ВВОЗА - ДЛЯ ИНКУБИРОВАНИЯ. | BT58: =MIN(1,IFERROR(SEARCH(BT$2,$BS58),0)) -> 0 | BU58: =MIN(1,IFERROR(SEARCH(BU$2,$BS58),0)) -> 0 | BV58: =MAX(BT58,BU58) -> 0 | BW58: CUDDY FARMS | BX58: CUDDY FARMS LIMITED 2008 | BY58: 564 | BZ58: 0 | CA58: 112800 | CB58: ШТ | CC58: 0 | CE58: 1 | CF58: 0407191100 | CI58: CA | CJ58: 11575 | CK58: ОООО-ЛП | CL58: 4000000 | CM58: 10152 | CN58: 0 | CQ58: 172313.28 | CR58: 17354756 | CS58: 0 | CT58: 1 | CU58: 17354756 | CV58: 187478.12 | CW58: 10 | CX58: 18.47 | DA58: БАЕРОВ АНДРЕЙ ВАСИЛЬЕВИЧ | DB58: 891
B59: 1 | C59: 06.07.2023 | D59: 7 | E59: 10005030/050723/3180011 | F59: 10005030 | G59: 05.07.2023 | H59: 3180011 | I59: ИМ | J59: 40 | N59: AVIAGEN TURKEYS LTD. | O59: , CHESTER CH3 9GA, TATTENHALL, CHOWLEY OAK BUSINESS PARK, CHOWLEY 5.. | R59: 1 | S59: 0 | T59: 1 | U59: 290 | V59: 1047796588146 | W59: 7710553010 | X59: ООО "АГРОИМПОРТ" | Y59: 143421, МОСКОВСКАЯ ОБЛ., КРАСНОГОРСКИЙ Р-Н, 26 КМ А/Д "БАЛТИЯ", БЦ "РИГА-ЛЕНД", | Z59: 46000 | AA59: 502401001 | AB59: 1047796588146 | AC59: 7710553010 | AD59: ООО "АГРОИМПОРТ" | AE59: 143421, МОСКОВСКАЯ ОБЛ., КРАСНОГОРСКИЙ Р-Н, 26 КМ А/Д "БАЛТИЯ", БЦ "РИГА-ЛЕНД", | AF59: 46000 | AG59: 502401001 | AH59: GB | AI59: СОЕДИНЕННОЕ КОРОЛЕВСТВО | AJ59: 37965426 | AK59: 1047796588146 | AL59: 7710553010 | AM59: ООО "АГРОИМПОРТ" | AN59: 143421, МОСКОВСКАЯ ОБЛ., КРАСНОГОРСКИЙ Р-Н, 26 КМ А/Д "БАЛТИЯ", БЦ "РИГА-ЛЕНД", | AO59: 46000 | AP59: 502401001 | AQ59: GB | AR59: СОЕДИНЕННОЕ КОРОЛЕВСТВО | AS59: СОЕДИНЕННОЕ КОРОЛЕВСТВО | AT59: RU | AU59: РОССИЯ | AV59: 0 | AW59: 0 | AX59: DAP | AY59: МОСКВА | AZ59: 1 | BA59: EUR | BB59: 388440 | BC59: 37965426 | BD59: 423981.53 | BE59: 97.7382 | BF59: 010 | BG59: 40 | BH59: 22030808/3292/0000/2/1 | BI59: - | BJ59: 11 | BK59: 10001/311210/10001/10 | BM59: 141400 | BN59: МОСКОВСКАЯ | BO59: ТЕРРИТОРИЯ АЭРОПОРТА | BP59: "ВНУКОВО" СТР.19,,,. | BQ59: 10001020 т/п Аэропорт Внуково (грузовой) | BR59: 1 | BS59: ПЛЕМЕННЫЕ ИНДЮШАЧЬИ ЯЙЦА ДЛЯ ИНКУБАЦИИ, ОПЛОДОТВОРЁННЫЕ, ДЛЯ ВЫВЕДЕНИЯ РОДИТЕЛЬСКОГО СТАДА MELEAGRIS GALLOPAVO L. ПОРОДЫ БЕЛАЯ ШИРОКОГРУДАЯ BIG 6; РАЗМЕЩЕННЫЕ С ЦЕЛЬЮ ПРЕДОТВРАЩЕНИЯ БОЯ И УНИЧТОЖЕНИЯ В КАРТОННЫХ КОРОБКАХ. | BT59: =MIN(1,IFERROR(SEARCH(BT$2,$BS59),0)) -> 0 | BU59: =MIN(1,IFERROR(SEARCH(BU$2,$BS59),0)) -> 1 | BV59: =MAX(BT59,BU59) -> 1 | BW59: ... | BX59: AVIAGEN TURKEYS INC. | BY59: 290 | BZ59: 0 | CA59: 58000 | CB59: ШТ | CC59: 0 | CE59: 1 | CF59: 0407191100 | CI59: GB | CJ59: 6090 | CK59: ОООО-ПС | CL59: 4000000 | CM59: 5800 | CN59: 0 | CQ59: 388440 | CR59: 37965426 | CS59: 0 | CT59: 1 | CU59: 37965426 | CV59: 423981.53 | CW59: 10 | CX59: 73.1 | DA59: КУДЕЛЬКИН ВЛАДИМИР ВЛАДИМИРОВИЧ | DB59: 1062
B60: 1 | C60: 06.07.2023 | D60: 7 | E60: 10013160/060723/3305043 | F60: 10013160 | G60: 06.07.2023 | H60: 3305043 | I60: ИМ | J60: 40 | N60: NAGISZ ZRT. | O60: 4181, , NADUDVAR, FO UT 119, .. | R60: 1 | S60: 0 | T60: 1 | U60: 495 | V60: 1047796588146 | W60: 7710553010 | X60: ООО "АГРОИМПОРТ" | Y60: 143421, МОСКОВСКАЯ ОБЛ., КРАСНОГОРСКИЙ Р-Н, 26 КМ А/Д "БАЛТИЯ", БЦ "РИГА-ЛЕНД", | Z60: 46000 | AA60: 502401001 | AB60: 1047796588146 | AC60: 7710553010 | AD60: ООО "АГРОИМПОРТ" | AE60: 143421, МОСКОВСКАЯ ОБЛ., КРАСНОГОРСКИЙ Р-Н, 26 КМ А/Д "БАЛТИЯ", БЦ "РИГА-ЛЕНД", | AF60: 46000 | AG60: 502401001 | AH60: HU | AI60: ВЕНГРИЯ | AJ60: 12469104 | AK60: 1047796588146 | AL60: 7710553010 | AM60: ООО "АГРОИМПОРТ" | AN60: 143421, МОСКОВСКАЯ ОБЛ., КРАСНОГОРСКИЙ Р-Н, 26 КМ А/Д "БАЛТИЯ", БЦ "РИГА-ЛЕНД", | AO60: 46000 | AP60: 502401001 | AQ60: HU | AR60: ВЕНГРИЯ | AS60: ВЕНГРИЯ | AT60: RU | AU60: РОССИЯ | AV60: 2 | AW60: 0 | AX60: FCA | AY60: NADUDVAR | AZ60: 1 | BA60: EUR | BB60: 123750 | BC60: 12178782 | BD60: 138027.24 | BE60: 98.4144 | BF60: 010 | BH60: 22120524/3292/0000/2/1 | BI60: - | BJ60: 99 | BN60: ПЕНЗЕНСКАЯ | BO60: ПЕНЗА | BP60: АУСТРИНА,,,. | BQ60: 10413090 т/п Пензенский областной | BR60: 1 | BS60: ИНДЮШАЧЬИ ЯЙЦА ДЛЯ ИНКУБАЦИИ, ОПЛОДОТВОРЕННЫЕ, MELEAGRIS GALLOPAVO L., ПОРОДА БЕЛАЯ ШИРОКОГРУДАЯ КРОССА БИГ-6, РАЗMЕЩЕНЫ С ЦЕЛЬЮ ПРЕДОТВРАЩЕНИЯ БОЯ И УНИЧТОЖЕНИЯ В КАРТОННЫХ КОРОБКАХ | BT60: =MIN(1,IFERROR(SEARCH(BT$2,$BS60),0)) -> 0 | BU60: =MIN(1,IFERROR(SEARCH(BU$2,$BS60),0)) -> 1 | BV60: =MAX(BT60,BU60) -> 1 | BW60: ОТСУТСТВУЕТ | BX60: NAGISZ ZRT. | BY60: 495 | BZ60: 0 | CA60: 99000 | CB60: ШТ | CC60: 0 | CE60: 1 | CF60: 0407191100 | CI60: HU | CJ60: 10890 | CK60: ОООО-ЛП | CL60: 4000000 | CM60: 10395 | CN60: 0 | CQ60: 123750 | CR60: 12178782 | CS60: 0 | CT60: 1 | CU60: 12469104 | CV60: 138027.24 | CW60: 10 | CX60: 13.28 | DA60: КУДЕЛЬКИН ВЛАДИМИР ВЛАДИМИРОВИЧ | DB60: 1163
B61: 1 | C61: 04.07.2023 | D61: 7 | E61: 10013160/030723/3300692 | F61: 10013160 | G61: 03.07.2023 | H61: 3300692 | I61: ИМ | J61: 40 | N61: GRIMAUD FRERES SELECTION S.A.S. | O61: 49450, , SEVREMOINE, ROUSSAY, RA3 LA CORBIERE, .. | R61: 1 | S61: 0 | T61: 1 | U61: 82 | V61: 1217700533511 | W61: 9704098398 | X61: ООО "ИМПОРТЭГГЗ" | Y61: 117393, , МОСКВА, УЛ. АРХИТЕКТОРА ВЛАСОВА, Д. 55 | Z61: 45000 | AA61: 772801001 | AB61: 1217700533511 | AC61: 9704098398 | AD61: ООО "ИМПОРТЭГГЗ" | AE61: 117393, , МОСКВА, УЛ. АРХИТЕКТОРА ВЛАСОВА, Д. 55 | AF61: 45000 | AG61: 772801001 | AH61: FR | AI61: ФРАНЦИЯ | AJ61: 8873891.8 | AK61: 1217700533511 | AL61: 9704098398 | AM61: ООО "ИМПОРТЭГГЗ" | AN61: 117393, , МОСКВА, УЛ. АРХИТЕКТОРА ВЛАСОВА, Д. 55 | AO61: 45000 | AP61: 772801001 | AQ61: FR | AR61: ФРАНЦИЯ | AS61: ФРАНЦИЯ | AT61: RU | AU61: РОССИЯ | AV61: 2 | AW61: 0 | AX61: FCA | AY61: MESLAY DU MAINE | AZ61: 1 | BA61: EUR | BB61: 87767.6 | BC61: 8427401 | BD61: 100401.11 | BE61: 96.0195 | BF61: 010 | BH61: 23060586/0354/0000/2/1 | BI61: - | BJ61: 11 | BK61: 10013/200111/10045/6 | BM61: 215119 | BN61: МОСКОВСКАЯ ОБЛ. | BO61: Г. КРАСНОЗНАМЕНСК | BP61: УЛ. БЕРЕЗОВАЯ АЛЛЕЯ 1/2; ОТКР.ПЛОЩАДКА: МО, Г. КРА | BQ61: 10013070 т/п Красноармейский | BR61: 1 | BS61: ИНКУБАЦИОННЫЕ ЯЙЦА ДОМАШНЕЙ ПТИЦЫ (УТИНЫЕ); ОПЛОДОТВОРЁННЫЕ (ДЛЯ ИНКУБАЦИИ). РАЗМЕЩЕНЫ С ЦЕЛЬЮ ПРЕДОТВРАЩЕНИЯ БОЯ И УНИЧТОЖЕНИЯ В КАРТОННЫХ КОРОБКАХ (200 ЯИЦ В ОДНОЙ КОРОБКЕ) | BT61: =MIN(1,IFERROR(SEARCH(BT$2,$BS61),0)) -> 0 | BU61: =MIN(1,IFERROR(SEARCH(BU$2,$BS61),0)) -> 0 | BV61: =MAX(BT61,BU61) -> 0 | BW61: ОТСУТСТВУЕТ | BX61: GRIMAUD FRERES SELECTION S.A.S. | BY61: 82 | BZ61: 0 | CA61: 16400 | CB61: ШТ | CC61: 0 | CE61: 1 | CF61: 0407191900 | CI61: FR | CJ61: 1707.2 | CK61: ОООО-ЛП | CL61: 4000000 | CM61: 1312 | CN61: 0 | CQ61: 87767.6 | CR61: 8427401 | CS61: 0 | CT61: 1 | CU61: 8873891.8 | CV61: 100401.11 | CW61: 10 | CX61: 76.53 | DA61: ПЯТАЕВ АЛЕКСЕЙ АНАТОЛЬЕВИЧ | DB61: 1208
B62: 1 | C62: 04.07.2023 | D62: 7 | E62: 10131010/040723/3240063 | F62: 10131010 | G62: 04.07.2023 | H62: 3240063 | I62: ИМ | J62: 40 | N62: HENDRIX GENETICS TURKEYS FRANCE SAS | O62: 49290, , MAUGES SUR LOIRE, B.P.1-LA BOHARDIERE SAINT LAURENT DE LA PLAINE, .. | R62: 1 | S62: 0 | T62: 1 | U62: 12 | V62: 1193668026507 | W62: 3613005236 | X62: ООО "ДОНСКАЯ ИНДЕЙКА" | Y62: 396350, ВОРОНЕЖСКАЯ ОБЛАСТЬ, КАШИРСКИЙ РАЙОН, П. ИМ. ДЗЕРЖИНСКОЕ, УЛ. ПОЛЕВАЯ,, | Z62: 20000 | AA62: 361301001 | AB62: 1193668026507 | AC62: 3613005236 | AD62: ООО "ДОНСКАЯ ИНДЕЙКА" | AE62: 396350, ВОРОНЕЖСКАЯ ОБЛАСТЬ, КАШИРСКИЙ РАЙОН, П. ИМ. ДЗЕРЖИНСКОЕ, УЛ. ПОЛЕВАЯ,, | AF62: 20000 | AG62: 361301001 | AH62: FR | AI62: ФРАНЦИЯ | AJ62: 8151404.3 | AK62: 1193668026507 | AL62: 3613005236 | AM62: ООО "ДОНСКАЯ ИНДЕЙКА" | AN62: 396350, ВОРОНЕЖСКАЯ ОБЛАСТЬ, КАШИРСКИЙ РАЙОН, П. ИМ. ДЗЕРЖИНСКОЕ, УЛ. ПОЛЕВАЯ,, | AO62: 20000 | AP62: 361301001 | AQ62: FR | AR62: ФРАНЦИЯ | AS62: ФРАНЦИЯ | AT62: RU | AU62: РОССИЯ | AV62: 2 | AW62: 0 | AX62: DAP | AY62: П. ИМ. ДЗЕРЖИНСКОГО | AZ62: 1 | BA62: EUR | BB62: 83812 | BC62: 8151404 | BD62: 91255.06 | BE62: 97.2582 | BF62: 010 | BH62: 23010142/3292/0000/2/1 | BI62: - | BJ62: 99 | BL62: 10113/171210/10036/8 | BN62: СМОЛЕНСКАЯ ОБЛ., СМОЛЕНСКИЙ Р-Н | BO62: Д. СТАБНА | BP62: СЕВЕРО-ВОСТОЧНЕЕ Д. СТАБНА, НА РАСТОЯНИИ 700 М,,,. | BQ62: 10113100 т/п Стабнинский | BR62: 1 | BS62: ОПЛОДОТВОРЕННЫЕ ИНКУБАЦИОННЫЕ ЯЙЦА ИНДЕЕК (MELEAGRUS GAILOPANO L), ДЛЯ ИНКУБАЦИИ И ВЫВЕДЕНИЯ ИНДЕЕК, ДЛЯ ПОСЛЕДУЮЩЕГО ВЫРАЩИВАНИЯ И УБОЯ НА МЯСО, СВЕЖИЕ, (В КОРОБКЕ 10 ЛОТКОВ ПО 20 ШТ.): | BT62: =MIN(1,IFERROR(SEARCH(BT$2,$BS62),0)) -> 0 | BU62: =MIN(1,IFERROR(SEARCH(BU$2,$BS62),0)) -> 0 | BV62: =MAX(BT62,BU62) -> 0 | BW62: ОТСУТСТВУЕТ | BX62: HENDRIX GENETICS TURKEYS FRANCE | BY62: 12 | BZ62: 0 | CA62: 53600 | CB62: ШТ | CC62: 0 | CE62: 1 | CF62: 0407191100 | CI62: FR | CJ62: 5628 | CK62: ОООО-ЛП | CL62: 4000000 | CM62: 5360 | CN62: 0 | CQ62: 83812 | CR62: 8151404 | CS62: 0 | CT62: 1 | CU62: 8151404.3 | CV62: 91255.06 | CW62: 10 | CX62: 17.03 | CY62: 35 | CZ62: 0035/03-20-2139 | DA62: ИЛЬИНА ОЛЬГА АЛЕКСАНДРОВНА | DB62: 342
B63: 1 | C63: 03.07.2023 | D63: 7 | E63: 10013160/020723/3298309 | F63: 10013160 | G63: 02.07.2023 | H63: 3298309 | I63: ИМ | J63: 40 | N63: MIQUEL AVICOLA,S.A. | O63: 17843, , PALOL DE REVARDIT (GIRONA), CTRA GIRONA BANYOLES, KM. 8,2, .. | R63: 2 | S63: 0 | T63: 2 | U63: 27 | V63: 1225000075190 | W63: 5038165515 | X63: ООО "ЛИДЕР СТ" | Y63: 141241, МОСКОВСКАЯ ОБЛАСТЬ, Г.О.ПУШКИНСКИЙ, Г.ПУШКИНО, МКР.МАМОНТОВКА, УЛ.РАБОЧА | Z63: 46000 | AA63: 503801001 | AB63: 1225000075190 | AC63: 5038165515 | AD63: ООО "ЛИДЕР СТ" | AE63: 141241, МОСКОВСКАЯ ОБЛАСТЬ, Г.О.ПУШКИНСКИЙ, Г.ПУШКИНО, МКР.МАМОНТОВКА, УЛ.РАБОЧА | AF63: 46000 | AG63: 503801001 | AH63: ES | AI63: ИСПАНИЯ | AJ63: 6566005.5 | AK63: 1225000075190 | AL63: 5038165515 | AM63: ООО "ЛИДЕР СТ" | AN63: 141241, МОСКОВСКАЯ ОБЛАСТЬ, Г.О.ПУШКИНСКИЙ, Г.ПУШКИНО, МКР.МАМОНТОВКА, УЛ.РАБОЧА | AO63: 46000 | AP63: 503801001 | AQ63: ES | AR63: ИСПАНИЯ | AS63: ИСПАНИЯ | AT63: RU | AU63: РОССИЯ | AV63: 2 | AW63: 0 | AX63: DAP | AY63: СТАНИЦА ПОЛТАВСКАЯ | AZ63: 1 | BA63: EUR | BB63: 68382 | BC63: 6566005 | BD63: 74289.19 | BE63: 96.0195 | BF63: 010 | BH63: 22123199/3292/0000/2/1 | BI63: - | BJ63: 99 | BN63: СМОЛЕНСКАЯ ОБЛ., СМОЛЕНСКИЙ Р-Н | BO63: С.П. СТАБЕНСКОЕ | BP63: СЕВЕРО-ВОСТОЧНЕЕ Д. СТАБНА, НА РАСТОЯНИИ 700 М,,,. | BQ63: 10113100 т/п Стабнинский | BR63: 2 | BS63: ОПЛОДОТВОРЕННЫЕ ИНКУБАЦИОННЫЕ ЯЙЦА ИНДЕЙКИ (MELAGRIS GALLOPAVO L.) ДЛЯ ИНКУБАЦИИ И ВЫВЕДЕНИЯ ПОРОДЫ ИНДЕЕК, ДЛЯ ПОСЛЕДУЮЩЕГО ВЫРАЩИВАНИЯ И УБОЯ НА МЯСО, СВЕЖИЕ, ПОРОДЫ БЕЛАЯ ШИРОКОГРУДАЯ, УПАКОВАНО В КАРТОННЫХ КОРОБКАХ ПО 200 ШТ. | BT63: =MIN(1,IFERROR(SEARCH(BT$2,$BS63),0)) -> 1 | BU63: =MIN(1,IFERROR(SEARCH(BU$2,$BS63),0)) -> 0 | BV63: =MAX(BT63,BU63) -> 1 | BW63: MIQUEL AVICOLA | BX63: ПРОИЗВ.: CARAMELLA II, ПЛЕМЗАВ.:ES430050035961 | BY63: 1 | BZ63: 0 | CA63: 1000 | CB63: ШТ | CC63: 0 | CE63: 2 | CF63: 0407191100 | CI63: ES | CJ63: 115 | CK63: ОООО-ЛП | CL63: 4000000 | CM63: 95 | CN63: 0 | CQ63: 1606.32 | CR63: 154238 | CS63: 0 | CT63: 1 | CU63: 154238.04 | CV63: 1745.08 | CW63: 10 | CX63: 18.37 | DA63: АНДРЕЕВА ЕЛЕНА НИКОЛАЕВНА | DB63: 1210
B64: 1 | C64: 03.07.2023 | D64: 7 | E64: 10013160/030723/3298380 | F64: 10013160 | G64: 03.07.2023 | H64: 3298380 | I64: ИМ | J64: 40 | N64: BRANKO NITRA, A.S. | O64: 94905, , NITRA, NOVOZAMOCKA 184, .. | R64: 1 | S64: 0 | T64: 1 | U64: 4 | V64: 1175027024820 | W64: 5040151421 | X64: ООО "БРОННИЦКАЯ ПТИЦЕФАБРИКА" | Y64: 140157, МОСКОВСКАЯ ОБЛ., РАМЕНСКИЙ Г. О., ПОС. РЫЛЕЕВО, УЛ. 4-Й КМ (АВТОДОРОГА М | Z64: 46000 | AA64: 504001001 | AB64: 1175027024820 | AC64: 5040151421 | AD64: ООО "БРОННИЦКАЯ ПТИЦЕФАБРИКА" | AE64: 140157, МОСКОВСКАЯ ОБЛ., РАМЕНСКИЙ Г. О., ПОС. РЫЛЕЕВО, УЛ. 4-Й КМ (АВТОДОРОГА М | AF64: 46000 | AG64: 504001001 | AH64: SK | AI64: СЛОВАКИЯ | AJ64: 3509512.7 | AK64: 1175027024820 | AL64: 5040151421 | AM64: ООО "БРОННИЦКАЯ ПТИЦЕФАБРИКА" | AN64: 140157, МОСКОВСКАЯ ОБЛ., РАМЕНСКИЙ Г. О., ПОС. РЫЛЕЕВО, УЛ. 4-Й КМ (АВТОДОРОГА М | AO64: 46000 | AP64: 504001001 | AQ64: SK | AR64: СЛОВАКИЯ | AS64: СЛОВАКИЯ | AT64: RU | AU64: РОССИЯ | AV64: 2 | AW64: 0 | AX64: FCA | AY64: НИТРА | AZ64: 1 | BA64: EUR | BB64: 35200 | BC64: 3379886 | BD64: 39707.38 | BE64: 96.0195 | BF64: 010 | BG64: 30 | BH64: 23010003/2551/0001/2/1 | BI64: - | BJ64: 11 | BK64: 10113/171210/10036/8 | BN64: СМОЛЕНСКАЯ ОБЛ., СМОЛЕНСКИЙ Р-Н | BO64: С.П. СТАБЕНСКОЕ | BP64: СЕВЕРО-ВОСТОЧНЕЕ Д. СТАБНА, НА РАСТОЯНИИ 700 М,,,. | BQ64: 10113100 т/п Стабнинский | BR64: 1 | BS64: ОПЛОДОТВОРЕННЫE НЕПЛЕМЕННЫЕ ИНКУБАЦИОННЫЕ ЯЙЦА ИНДЕЙКИ (MELAGRIS GALLOPAVO L.) ДЛЯ ИНКУБАЦИИ И ВЫВЕДЕНИЯ ПОРОДЫ ИНДЕЕК, ДЛЯ ПОСЛЕДУЮЩЕГО ВЫРАЩИВАНИЯ И УБОЯ НА МЯСО, СВЕЖИЕ, ПОРОДЫ БЕЛАЯ ШИРОКОГРУДАЯ, КРОСС БИГ 6, ВЕС ЯЙЦА 75-100 Г, УПАКОВАНО В | BT64: =MIN(1,IFERROR(SEARCH(BT$2,$BS64),0)) -> 1 | BU64: =MIN(1,IFERROR(SEARCH(BU$2,$BS64),0)) -> 0 | BV64: =MAX(BT64,BU64) -> 1 | BW64: ОТСУТСТВУЕТ | BX64: BRANKO NITRA, A.S. ПЛЕМЗАВ.: SK-RH-NR-13 | BY64: 4 | BZ64: 0 | CA64: 22000 | CB64: ШТ | CC64: 0 | CE64: 1 | CF64: 0407191100 | CI64: SK | CJ64: 2310 | CK64: ОООО-ЛП | CL64: 4000000 | CM64: 2145 | CN64: 0 | CQ64: 35200 | CR64: 3379886 | CS64: 0 | CT64: 1 | CU64: 3509512.7 | CV64: 39707.38 | CW64: 10 | CX64: 18.51 | DA64: КИРАКОСЯН АЗНИВ МЕРУЖАНОВНА | DB64: 1186
B65: 1 | C65: 02.07.2023 | D65: 7 | E65: 10005030/020723/3176379 | F65: 10005030 | G65: 02.07.2023 | H65: 3176379 | I65: ИМ | J65: 40 | N65: AVIAGEN TURKEYS LTD. | O65: , CHESTER CH3 9GA, TATTENHALL, CHOWLEY OAK BUSINESS PARK, CHOWLEY 5 | R65: 1 | S65: 0 | T65: 1 | U65: 223 | V65: 1047796588146 | W65: 7710553010 | X65: ООО "АГРОИМПОРТ" | Y65: 143421, МОСКОВСКАЯ ОБЛ., КРАСНОГОРСКИЙ Р-Н, 26 КМ А/Д "БАЛТИЯ", БЦ "РИГА-ЛЕНД", | Z65: 46000 | AA65: 502401001 | AB65: 1047796588146 | AC65: 7710553010 | AD65: ООО "АГРОИМПОРТ" | AE65: 143421, МОСКОВСКАЯ ОБЛ., КРАСНОГОРСКИЙ Р-Н, 26 КМ А/Д "БАЛТИЯ", БЦ "РИГА-ЛЕНД", | AF65: 46000 | AG65: 502401001 | AH65: GB | AI65: СОЕДИНЕННОЕ КОРОЛЕВСТВО | AJ65: 28465749 | AK65: 1047796588146 | AL65: 7710553010 | AM65: ООО "АГРОИМПОРТ" | AN65: 143421, МОСКОВСКАЯ ОБЛ., КРАСНОГОРСКИЙ Р-Н, 26 КМ А/Д "БАЛТИЯ", БЦ "РИГА-ЛЕНД", | AO65: 46000 | AP65: 502401001 | AQ65: GB | AR65: СОЕДИНЕННОЕ КОРОЛЕВСТВО | AS65: СОЕДИНЕННОЕ КОРОЛЕВСТВО | AT65: RU | AU65: РОССИЯ | AV65: 0 | AW65: 0 | AX65: DAP | AY65: МОСКВА | AZ65: 1 | BA65: EUR | BB65: 296458 | BC65: 28465749 | BD65: 322067.57 | BE65: 96.0195 | BF65: 010 | BG65: 40 | BH65: 22030808/3292/0000/2/1 | BI65: - | BJ65: 11 | BK65: 10001/311210/10001/10 | BM65: 141400 | BN65: МОСКОВСКАЯ | BO65: ТЕРРИТОРИЯ АЭРОПОРТА | BP65: "ВНУКОВО" СТР.19,,,. | BQ65: 10001020 т/п Аэропорт Внуково (грузовой) | BR65: 1 | BS65: ПЛЕМЕННЫЕ ИНДЮШАЧЬИ ЯЙЦА ДЛЯ ИНКУБАЦИИ, ОПЛОДОТВОРЁННЫЕ, ДЛЯ BЫВЕДЕНИЯ РОДИТЕЛЬСКОГО СТАДА MELEAGRIS GALLOPAVO L. ПОРОДЫ БЕЛАЯ ШИРОКОГРУДАЯ BIG 6, РАЗМЕЩЕННЫЕ С ЦЕЛЬЮ ПРЕДОТВРАЩЕНИЯ БОЯ И УНИЧТОЖЕНИЯ В КАРТОННЫХ КОРОБКАХ. | BT65: =MIN(1,IFERROR(SEARCH(BT$2,$BS65),0)) -> 0 | BU65: =MIN(1,IFERROR(SEARCH(BU$2,$BS65),0)) -> 1 | BV65: =MAX(BT65,BU65) -> 1 | BW65: ... | BX65: AVIAGEN TURKEYS INC. | BY65: 223 | BZ65: 0 | CA65: 44600 | CB65: ШТ | CC65: 0 | CE65: 1 | CF65: 0407191100 | CI65: GB | CJ65: 4683 | CK65: ОООО-ПС | CL65: 4000000 | CM65: 4460 | CN65: 0 | CQ65: 296458 | CR65: 28465749 | CS65: 0 | CT65: 1 | CU65: 28465749 | CV65: 322067.57 | CW65: 10 | CX65: 72.21 | DA65: КУДЕЛЬКИН ВЛАДИМИР ВЛАДИМИРОВИЧ | DB65: 640
B66: 1 | C66: 02.07.2023 | D66: 7 | E66: 10005030/020723/3176393 | F66: 10005030 | G66: 02.07.2023 | H66: 3176393 | I66: ИМ | J66: 40 | N66: CUDDY FARMS LIMITED 2008 | O66: , , RR #5-28429 CENTRE ROAD, STRATHROY ON N76 3H6, | R66: 1 | S66: 0 | T66: 1 | U66: 150 | V66: 1144813001046 | W66: 4805016071 | X66: ООО "КРИВЕЦ-ПТИЦА" | Y66: 399174, ЛИПЕЦКАЯ ОБЛ., ДОБРОВСКИЙ РАЙОН, СЕЛО КРИВЕЦ, УЛ. НОВАЯ, Д.2, ПОМЕЩЕНИЕ | Z66: 42000 | AA66: 480501001 | AB66: 1144813001046 | AC66: 4805016071 | AD66: ООО "КРИВЕЦ-ПТИЦА" | AE66: 399174, ЛИПЕЦКАЯ ОБЛ., ДОБРОВСКИЙ РАЙОН, СЕЛО КРИВЕЦ, УЛ. НОВАЯ, Д.2, ПОМЕЩЕНИЕ | AF66: 42000 | AG66: 480501001 | AH66: CA | AI66: КАНАДА | AJ66: 4320877.5 | AK66: 1144813001046 | AL66: 4805016071 | AM66: ООО "КРИВЕЦ-ПТИЦА" | AN66: 399174, ЛИПЕЦКАЯ ОБЛ., ДОБРОВСКИЙ РАЙОН, СЕЛО КРИВЕЦ, УЛ. НОВАЯ, Д.2, ПОМЕЩЕНИЕ | AO66: 42000 | AP66: 480501001 | AQ66: CA | AR66: КАНАДА | AS66: КАНАДА | AT66: RU | AU66: РОССИЯ | AV66: 0 | AW66: 0 | AX66: CPT | AY66: МОСКВА | AZ66: 1 | BA66: EUR | BB66: 45000 | BC66: 4320878 | BD66: 48887.33 | BE66: 96.0195 | BF66: 010 | BG66: 40 | BH66: 22121474/3292/0000/2/1 | BI66: - | BJ66: 11 | BK66: 10001/311210/10001/10 | BM66: 141400 | BO66: МОСКВА | BP66: ТЕРРИТОРИЯ "АЭРОПОРТ ВНУКОВО", Д. 1, СТР. 19,,,. | BQ66: 10001020 т/п Аэропорт Внуково (грузовой) | BR66: 1 | BS66: ОПЛОДОТВОРЕННЫЕ ЯЙЦА ИНДЮШАЧЬИ ДЛЯ ИНКУБАЦИИ, КОД ОКП 98 4766 (ОКПД2 01.47.23.140): ЦЕЛЬ ВВОЗА: ИНКУБИРОВАНИЕ И ДАЛЬНЕЙШЕЕ ВЫРАЩИВАНИЕ. | BT66: =MIN(1,IFERROR(SEARCH(BT$2,$BS66),0)) -> 0 | BU66: =MIN(1,IFERROR(SEARCH(BU$2,$BS66),0)) -> 1 | BV66: =MAX(BT66,BU66) -> 1 | BW66: CUDDY FARMS | BX66: CUDDY FARMS LIMITED 2008 | BY66: 150 | BZ66: 0 | CA66: 30000 | CB66: ШТ | CC66: 0 | CE66: 1 | CF66: 0407191100 | CI66: CA | CJ66: 3000 | CK66: ОООО-ЛП | CL66: 4000000 | CM66: 2700 | CN66: 0 | CQ66: 45000 | CR66: 4320878 | CS66: 0 | CT66: 1 | CU66: 4320877.5 | CV66: 48887.33 | CW66: 10 | CX66: 18.11 | DA66: ШАДРИН ДЕНИС НИКОЛАЕВИЧ | DB66: 640
B67: 0 | C67: 02.07.2023 | D67: 7 | E67: 10013160/010723/3297658 | F67: 10013160 | G67: 01.07.2023 | H67: 3297658 | I67: ИМ | J67: 40 | N67: BRANKO NITRA, A.S. | O67: 94905, , NITRA, NOVOZAMOCKA 184, | R67: 1 | S67: 0 | T67: 1 | U67: 4 | V67: 1175027024820 | W67: 5040151421 | X67: ООО "БРОННИЦКАЯ ПТИЦЕФАБРИКА" | Y67: 140157, МОСКОВСКАЯ ОБЛ., РАМЕНСКИЙ Г. О., ПОС. РЫЛЕЕВО, УЛ. 4-Й КМ (АВТОДОРОГА М | Z67: 46000 | AA67: 504001001 | AB67: 1175027024820 | AC67: 5040151421 | AD67: ООО "БРОННИЦКАЯ ПТИЦЕФАБРИКА" | AE67: 140157, МОСКОВСКАЯ ОБЛ., РАМЕНСКИЙ Г. О., ПОС. РЫЛЕЕВО, УЛ. 4-Й КМ (АВТОДОРОГА М | AF67: 46000 | AG67: 504001001 | AH67: SK | AI67: СЛОВАКИЯ | AJ67: 3509512.7 | AK67: 1175027024820 | AL67: 5040151421 | AM67: ООО "БРОННИЦКАЯ ПТИЦЕФАБРИКА" | AN67: 140157, МОСКОВСКАЯ ОБЛ., РАМЕНСКИЙ Г. О., ПОС. РЫЛЕЕВО, УЛ. 4-Й КМ (АВТОДОРОГА М | AO67: 46000 | AP67: 504001001 | AQ67: SK | AR67: СЛОВАКИЯ | AS67: СЛОВАКИЯ | AT67: RU | AU67: РОССИЯ | AV67: 2 | AW67: 0 | AX67: FCA | AY67: НИТРА | AZ67: 1 | BA67: EUR | BB67: 35200 | BC67: 3379886 | BD67: 39707.38 | BE67: 96.0195 | BF67: 010 | BG67: 30 | BH67: 23010003/2551/0001/2/1 | BI67: - | BJ67: 99 | BN67: СМОЛЕНСКАЯ ОБЛ., СМОЛЕНСКИЙ Р-Н | BO67: С.П. СТАБЕНСКОЕ | BP67: СЕВЕРО-ВОСТОЧНЕЕ Д. СТАБНА, НА РАСТОЯНИИ 700 М,,,. | BQ67: 10113100 т/п Стабнинский | BR67: 1 | BS67: ОПЛОДОTВОРЕННЫЕ НЕПЛЕМЕННЫЕ ИНКУБАЦИОННЫЕ ЯЙЦА ИНДЕЙКИ (MELAGRIS GALLOPAVO L.) ДЛЯ ИНКУБАЦИИ И ВЫВЕДЕНИЯ ПОРОДЫ ИНДЕЕК, ДЛЯ ПОСЛЕДУЮЩЕГО ВЫРАЩИВАНИЯ И УБОЯ НА МЯСО, СВЕЖИЕ, ПОРОДЫ БЕЛАЯ ШИРОКОГРУДАЯ, КРОСС БИГ 6, ВЕС ЯЙЦА 75-100 Г, УПАКОВАНО В | BT67: =MIN(1,IFERROR(SEARCH(BT$2,$BS67),0)) -> 1 | BU67: =MIN(1,IFERROR(SEARCH(BU$2,$BS67),0)) -> 0 | BV67: =MAX(BT67,BU67) -> 1 | BW67: ОТСУТСТВУЕТ | BX67: BRANKO NITRA, A.S. ПЛЕМЗАВ.: SK-RH-NR-13 | BY67: 4 | BZ67: 0 | CA67: 22000 | CB67: ШТ | CC67: 0 | CE67: 1 | CF67: 0407191100 | CI67: SK | CJ67: 2310 | CK67: ОООО-ЛП | CL67: 4000000 | CM67: 2145 | CN67: 0 | CQ67: 35200 | CR67: 3379886 | CS67: 0 | CT67: 1 | CU67: 3509512.7 | CV67: 39707.38 | CW67: 90 | CX67: 18.51 | DA67: КИРАКОСЯН АЗНИВ МЕРУЖАНОВНА | DB67: 1442
B68: 1 | C68: 02.07.2023 | D68: 7 | E68: 10013160/020723/3297688 | F68: 10013160 | G68: 02.07.2023 | H68: 3297688 | I68: ИМ | J68: 40 | N68: MOORGUT KARTZFEHN TURKEY BREEDER GMBH | O68: 26219, , BOSEL, KARTZ-VON-KAMEKE-ALLEE, 7 | R68: 1 | S68: 0 | T68: 1 | U68: 528 | V68: 1047796588146 | W68: 7710553010 | X68: ООО "АГРОИМПОРТ" | Y68: 143421, МОСКОВСКАЯ ОБЛ., КРАСНОГОРСКИЙ Р-Н, 26 КМ А/Д "БАЛТИЯ", БЦ "РИГА-ЛЕНД", | Z68: 46000 | AA68: 502401001 | AB68: 1047796588146 | AC68: 7710553010 | AD68: ООО "АГРОИМПОРТ" | AE68: 143421, МОСКОВСКАЯ ОБЛ., КРАСНОГОРСКИЙ Р-Н, 26 КМ А/Д "БАЛТИЯ", БЦ "РИГА-ЛЕНД", | AF68: 46000 | AG68: 502401001 | AH68: DE | AI68: ГЕРМАНИЯ | AJ68: 18251387 | AK68: 1047796588146 | AL68: 7710553010 | AM68: ООО "АГРОИМПОРТ" | AN68: 143421, МОСКОВСКАЯ ОБЛ., КРАСНОГОРСКИЙ Р-Н, 26 КМ А/Д "БАЛТИЯ", БЦ "РИГА-ЛЕНД", | AO68: 46000 | AP68: 502401001 | AQ68: DE | AR68: ГЕРМАНИЯ | AS68: ГЕРМАНИЯ | AT68: RU | AU68: РОССИЯ | AV68: 2 | AW68: 0 | AX68: DAP | AY68: С. ГОЛИЦЫНО | AZ68: 1 | BA68: EUR | BB68: 190080 | BC68: 18251387 | BD68: 206500.09 | BE68: 96.0195 | BF68: 010 | BH68: 20121446/1326/0000/2/1 | BI68: - | BJ68: 60 | BK68: RU/0004/ТИП2 | BL68: RU/0004/ТИП2 | BN68: ПЕНЗЕНСКАЯ, НИЖНЕЛОМОВСКИЙ | BO68: ГОЛИЦЫНО | BP68: ГОЛИЦЫНСКИЙ СЕЛЬСОВЕТ,,,. | BQ68: 10413090 т/п Пензенский областной | BR68: 1 | BS68: ИНДЮШАЧЬИ ЯЙЦА ДЛЯ ИНКУБАЦИИ, ОПЛОДОТВОРЕННЫЕ, MELEAGRIS GALLOPAVO L., ПОРОДА БЕЛАЯ ШИРОКОГРУДАЯ КРОССА БИГ-6, КАТЕГОРИЯ БРОЙЛЕР РАЗМЕЩЕНЫ С ЦЕЛЬЮ ПРЕДОТВРАЩЕНИЯ БОЯ И УНИЧТОЖЕНИЯ В КАРТОННЫХ КОРОБКАХ | BT68: =MIN(1,IFERROR(SEARCH(BT$2,$BS68),0)) -> 0 | BU68: =MIN(1,IFERROR(SEARCH(BU$2,$BS68),0)) -> 1 | BV68: =MAX(BT68,BU68) -> 1 | BW68: ОТСУТСТВУЕТ | BX68: MOORGUT KARTZFEHN TURKEY BREEDER GMBH | BY68: 528 | BZ68: 0 | CA68: 105600 | CB68: ШТ | CC68: 0 | CE68: 1 | CF68: 0407191100 | CI68: DE | CJ68: 11616 | CK68: ОООО-ЛП | CL68: 4000000 | CM68: 10560 | CN68: 0 | CQ68: 190080 | CR68: 18251387 | CS68: 0 | CT68: 1 | CU68: 18251387 | CV68: 206500.09 | CW68: 10 | CX68: 19.55 | DA68: КУДЕЛЬКИН ВЛАДИМИР ВЛАДИМИРОВИЧ | DB68: 1326
B69: 1 | C69: 01.07.2023 | D69: 7 | E69: 10005030/010723/3176079 | F69: 10005030 | G69: 01.07.2023 | H69: 3176079 | I69: ИМ | J69: 40 | N69: CUDDY FARMS LIMITED 2008 | O69: N7G3H6, ONTARIO, STRATHROY, 28429 CENTRAL ROAD, R.R. # 5, | R69: 1 | S69: 0 | T69: 1 | U69: 120 | V69: 1177746508235 | W69: 7751046971 | X69: ООО "ЭГМАРТ" | Y69: 108841, , Г. МОСКВА, Г. ТРОИЦК, УЛ. ТЕКСТИЛЬЩИКОВ, ДОМ 3 КОР. 3, ОФ. 4, | Z69: 45000 | AA69: 775101001 | AB69: 1177746508235 | AC69: 7751046971 | AD69: ООО "ЭГМАРТ" | AE69: 108841, , Г. МОСКВА, Г. ТРОИЦК, УЛ. ТЕКСТИЛЬЩИКОВ, ДОМ 3 КОР. 3, ОФ. 4, | AF69: 45000 | AG69: 775101001 | AH69: CA | AI69: КАНАДА | AJ69: 3502791.4 | AK69: 1177746508235 | AL69: 7751046971 | AM69: ООО "ЭГМАРТ" | AN69: 108841, , Г. МОСКВА, Г. ТРОИЦК, УЛ. ТЕКСТИЛЬЩИКОВ, ДОМ 3 КОР. 3, ОФ. 4, | AO69: 45000 | AP69: 775101001 | AQ69: CA | AR69: КАНАДА | AS69: КАНАДА | AT69: RU | AU69: РОССИЯ | AV69: 0 | AW69: 0 | AX69: CPT | AY69: Г МОСКВА | AZ69: 1 | BA69: EUR | BB69: 36480 | BC69: 3502791 | BD69: 39631.33 | BE69: 96.0195 | BF69: 010 | BG69: 40 | BH69: 22122630/3292/0000/2/1 | BI69: - | BJ69: 11 | BK69: 10001/311210/10001/10 | BM69: 141800 | BO69: МОСКВА | BP69: ТЕРРИТОРИЯ "АЭРОПОРТ ВНУКОВО", Д. 1, СТР. 19,,,. | BQ69: 10001020 т/п Аэропорт Внуково (грузовой) | BR69: 1 | BS69: ОПЛОДОТВОРЕННЫЕ ИНКУБАЦИОННЫЕ ЯЙЦА ИНДЕЕК (MELEAGRIS GALLOPAVAL.),ДЛЯ ИНКУБАЦИИ И ВЫВЕДЕНИЯ ИНДЕЕК,ДЛЯ ПОСЛЕДУЮЩЕГО ВЫРАЩИВАНИЯ И УБОЯ НА МЯСО,КРОССА "HYBRID CONVERTER"(БЕЛАЯ ШИРОКОГРУДАЯ),СВЕЖИЕ (В КОРОБКЕ ПО 200 ШТ.): | BT69: =MIN(1,IFERROR(SEARCH(BT$2,$BS69),0)) -> 0 | BU69: =MIN(1,IFERROR(SEARCH(BU$2,$BS69),0)) -> 0 | BV69: =MAX(BT69,BU69) -> 0 | BW69: CUDDY | BX69: CUDDY FARMS LIMITED 2008 | BY69: 120 | BZ69: 0 | CA69: 24000 | CB69: ШТ | CC69: 0 | CE69: 1 | CF69: 0407191100 | CI69: CA | CJ69: 2482 | CK69: ОООО-ЛП | CL69: 4000000 | CM69: 2160 | CN69: 0 | CQ69: 36480 | CR69: 3502791 | CS69: 0 | CT69: 1 | CU69: 3502791.4 | CV69: 39631.33 | CW69: 10 | CX69: 18.35 | DA69: ЕФРЕМОВ СЕРГЕЙ АРКАДЬЕВИЧ | DB69: 770
B70: 1 | C70: 01.07.2023 | D70: 7 | E70: 10131010/010723/3237257 | F70: 10131010 | G70: 01.07.2023 | H70: 3237257 | I70: ИМ | J70: 40 | N70: "HENDRIX GENETICS TURKEYS FRANCE SAS" | O70: 49290, MAUGES SUR LOIRE, SAINT LAURENT DE LA PLAINE, LA BOHARDIERE BP., 1 | R70: 1 | S70: 0 | T70: 1 | U70: 380 | V70: 1116829006910 | W70: 6829076796 | X70: ООО "ТАМБОВСКАЯ ИНДЕЙКА" | Y70: 392000, ТАМБОВСКАЯ ОБЛ., ТАМБОВ, УЛ. СТУДЕНЕЦКАЯ, Д.16А, КОРП.1, ПОМ.16 | Z70: 68000 | AA70: 682901001 | AB70: 1116829006910 | AC70: 6829076796 | AD70: ООО "ТАМБОВСКАЯ ИНДЕЙКА" | AE70: 392000, ТАМБОВСКАЯ ОБЛ., ТАМБОВ, УЛ. СТУДЕНЕЦКАЯ, Д.16А, КОРП.1, ПОМ.16 | AF70: 68000 | AG70: 682901001 | AH70: FR | AI70: ФРАНЦИЯ | AJ70: 12488527 | AK70: 1116829006910 | AL70: 6829076796 | AM70: ООО "ТАМБОВСКАЯ ИНДЕЙКА" | AN70: 392000, ТАМБОВСКАЯ ОБЛ., ТАМБОВ, УЛ. СТУДЕНЕЦКАЯ, Д.16А, КОРП.1, ПОМ.16 | AO70: 68000 | AP70: 682901001 | AQ70: HU | AR70: ВЕНГРИЯ | AS70: ВЕНГРИЯ | AT70: RU | AU70: РОССИЯ | AV70: 2 | AW70: 0 | AX70: DAP | AY70: ПЕРВОМАЙСКИЙ, ТАМБОВ. ОБЛ. | AZ70: 1 | BA70: EUR | BB70: 130062.4 | BC70: 12488527 | BD70: 141297.86 | BE70: 96.0195 | BF70: 010 | BG70: 31 | BH70: 22122459/3292/0000/2/1 | BI70: - | BJ70: 11 | BK70: 10102/011010/10036/1 | BM70: 243025 | BN70: БРЯНСКАЯ ОБЛ. | BO70: Г.НОВОЗЫБКОВ | BP70: УЛ.РОС,,,. | BQ70: 10102073 ОТО и ТК №3 т/п Новозыбковский | BR70: 1 | BS70: ЯЙЦА ИНДЕЕK ДОМАШНИХ, СВЕЖИЕ, ОПЛОДОТВОРЕННЫЕ ДЛЯ ИНКУБАЦИИ, ПОРОДЫ HYBRID CONVERTER, НЕ ПЛЕМЕННЫЕ, ДЛЯ ПОСЛЕДУЮЩЕГО ВЫРАЩИВАНИЯ И УБОЯ НА МЯСО СВЕЖЕЕ, В КАРТОННЫХ КОРОБКАХ | BT70: =MIN(1,IFERROR(SEARCH(BT$2,$BS70),0)) -> 0 | BU70: =MIN(1,IFERROR(SEARCH(BU$2,$BS70),0)) -> 0 | BV70: =MAX(BT70,BU70) -> 0 | BW70: ОТСУТСТВУЕТ | BX70: NAGISZ ZRT. | BY70: 380 | BZ70: 0 | CA70: 76000 | CB70: ШТ | CC70: 0 | CE70: 1 | CF70: 0407191100 | CI70: HU | CJ70: 7980 | CK70: ОООО-ЛП | CL70: 4000000 | CM70: 7600 | CN70: 0 | CQ70: 130062.4 | CR70: 12488527 | CS70: 0 | CT70: 1 | CU70: 12488527 | CV70: 141297.86 | CW70: 10 | CX70: 18.59 | CY70: 933 | CZ70: 0933/01-20-010 | DA70: АЛИМПИЕВА АННА ВАЛЕРЬЕВНА | DB70: 180
B71: 1 | C71: 01.07.2023 | D71: 7 | E71: 10013160/010723/3297660 | F71: 10013160 | G71: 01.07.2023 | H71: 3297660 | I71: ИМ | J71: 40 | N71: PARTIZ 2000 KFT. | O71: 5540, , SZARVAS, RACOKZI U.6/1, | R71: 1 | S71: 0 | T71: 1 | U71: 54 | V71: 1215000062364 | W71: 5040173714 | X71: ООО "Р.И.П.С." | Y71: 140166, МОСКОВСКАЯ ОБЛАСТЬ, Г.О. РАМЕНСКИЙ, Д.ВЛАДИМИРОВКА, СТР.1, ПОМЕЩ.1, | Z71: 46000 | AA71: 504001001 | AB71: 1215000062364 | AC71: 5040173714 | AD71: ООО "Р.И.П.С." | AE71: 140166, МОСКОВСКАЯ ОБЛАСТЬ, Г.О. РАМЕНСКИЙ, Д.ВЛАДИМИРОВКА, СТР.1, ПОМЕЩ.1, | AF71: 46000 | AG71: 504001001 | AH71: HU | AI71: ВЕНГРИЯ | AJ71: 1523157.3 | AK71: 1215000062364 | AL71: 5040173714 | AM71: ООО "Р.И.П.С." | AN71: 140166, МОСКОВСКАЯ ОБЛАСТЬ, Г.О. РАМЕНСКИЙ, Д.ВЛАДИМИРОВКА, СТР.1, ПОМЕЩ.1, | AO71: 46000 | AP71: 504001001 | AQ71: HU | AR71: ВЕНГРИЯ | AS71: ВЕНГРИЯ | AT71: RU | AU71: РОССИЯ | AV71: 2 | AW71: 0 | AX71: FCA | AY71: SZARVAS | AZ71: 1 | BA71: EUR | BB71: 15120 | BC71: 1451815 | BD71: 17233.33 | BE71: 96.0195 | BF71: 010 | BH71: 22080443/1326/0000/2/1 | BI71: - | BJ71: 99 | BN71: СМОЛЕНСКАЯ ОБЛ., СМОЛЕНСКИЙ Р-Н | BO71: С.П. СТАБЕНСКОЕ | BP71: СЕВЕРО-ВОСТОЧНЕЕ Д. СТАБНА, НА РАСТОЯНИИ 700 М,,,. | BQ71: 10113100 т/п Стабнинский | BR71: 1 | BS71: ОПЛОДОТВОРЕННЫЕ НЕПЛЕМЕННЫЕ ИНКУБАЦИОННЫЕ ЯЙЦА ИНДЕЙКИ (TURKEY HATCHING EGGS), ДЛЯ ИНКУБАЦИИ, ДЛЯ ПОСЛЕДУЮЩЕГО ВЫРАЩИВАНИЯ И УБОЯ НА МЯСО, СВЕЖИЕ, ПО 200 ШТ В КОРОБКЕ. | BT71: =MIN(1,IFERROR(SEARCH(BT$2,$BS71),0)) -> 1 | BU71: =MIN(1,IFERROR(SEARCH(BU$2,$BS71),0)) -> 0 | BV71: =MAX(BT71,BU71) -> 1 | BW71: PARTIZ 2000 | BX71: "PARTIZ 2000 KFT.", ПЛЕМЗАВОД HU1009994 | BY71: 54 | BZ71: 0 | CA71: 10800 | CB71: ШТ | CC71: 0 | CE71: 1 | CF71: 0407191100 | CI71: HU | CJ71: 1135 | CK71: ОООО-ЛП | CL71: 4000000 | CM71: 1080 | CN71: 0 | CQ71: 15120 | CR71: 1451815 | CS71: 0 | CT71: 1 | CU71: 1523157.3 | CV71: 17233.33 | CW71: 10 | CX71: 15.96 | CY71: 1535 | CZ71: ТП ВЭД-1535/7 | DA71: ЛОПАТКИН ВЛАДИМИР НИКОЛАЕВИЧ | DB71: 1234
B72: 1 | C72: 01.07.2023 | D72: 7 | E72: 10013160/010723/3297664 | F72: 10013160 | G72: 01.07.2023 | H72: 3297664 | I72: ИМ | J72: 40 | N72: BRANKO NITRA, A.S. | O72: 94905, , NITRA, NOVOZAMOCKA 184, | R72: 1 | S72: 0 | T72: 1 | U72: 1 | V72: 1215000062364 | W72: 5040173714 | X72: ООО "Р.И.П.С." | Y72: 140166, МОСКОВСКАЯ ОБЛАСТЬ, Г.О. РАМЕНСКИЙ, Д.ВЛАДИМИРОВКА, СТР.1, ПОМЕЩ.1, | Z72: 46000 | AA72: 504001001 | AB72: 1215000062364 | AC72: 5040173714 | AD72: ООО "Р.И.П.С." | AE72: 140166, МОСКОВСКАЯ ОБЛАСТЬ, Г.О. РАМЕНСКИЙ, Д.ВЛАДИМИРОВКА, СТР.1, ПОМЕЩ.1, | AF72: 46000 | AG72: 504001001 | AH72: SK | AI72: СЛОВАКИЯ | AJ72: 341349.33 | AK72: 1215000062364 | AL72: 5040173714 | AM72: ООО "Р.И.П.С." | AN72: 140166, МОСКОВСКАЯ ОБЛАСТЬ, Г.О. РАМЕНСКИЙ, Д.ВЛАДИМИРОВКА, СТР.1, ПОМЕЩ.1, | AO72: 46000 | AP72: 504001001 | AQ72: SK | AR72: СЛОВАКИЯ | AS72: СЛОВАКИЯ | AT72: RU | AU72: РОССИЯ | AV72: 2 | AW72: 0 | AX72: FCA | AY72: НИТРА | AZ72: 1 | BA72: EUR | BB72: 3410 | BC72: 327426 | BD72: 3862.1 | BE72: 96.0195 | BF72: 010 | BG72: 30 | BH72: 23010117/1326/0000/2/1 | BI72: - | BJ72: 99 | BN72: СМОЛЕНСКАЯ ОБЛ., СМОЛЕНСКИЙ Р-Н | BO72: С.П. СТАБЕНСКОЕ | BP72: СЕВЕРО-ВОСТОЧНЕЕ Д. СТАБНА, НА РАСТОЯНИИ 700 М,,,. | BQ72: 10113100 т/п Стабнинский | BR72: 1 | BS72: OПЛОДОТВОРЕННЫЕ НЕПЛЕМЕННЫЕ ИНКУБАЦИОННЫЕ ЯЙЦА ИНДЕЙКИ (MELAGRIS GALLOPAVO L.) ДЛЯ ИНКУБАЦИИ И ВЫВЕДЕНИЯ ПОРОДЫ ИНДЕЕК, ДЛЯ ПОСЛЕДУЮЩЕГО ВЫРАЩИВАНИЯ И УБОЯ НА МЯСО, СВЕЖИЕ, ПОРОДЫ БЕЛАЯ ШИРОКОГРУДАЯ | BT72: =MIN(1,IFERROR(SEARCH(BT$2,$BS72),0)) -> 1 | BU72: =MIN(1,IFERROR(SEARCH(BU$2,$BS72),0)) -> 0 | BV72: =MAX(BT72,BU72) -> 1 | BW72: ОТСУТСТВУЕТ | BX72: BRANKO NITRA, A.S., ПЛЕМЗАВ.: SK-RH-NR-13 | BY72: 1 | BZ72: 0 | CA72: 2200 | CB72: ШТ | CC72: 0 | CE72: 1 | CF72: 0407191100 | CI72: SK | CJ72: 231 | CK72: ОООО-ЛП | CL72: 4000000 | CM72: 215 | CN72: 0 | CQ72: 3410 | CR72: 327426 | CS72: 0 | CT72: 1 | CU72: 341349.33 | CV72: 3862.1 | CW72: 10 | CX72: 17.96 | CY72: 1535 | CZ72: ТП ВЭД-1535/7 | DA72: ЛОПАТКИН ВЛАДИМИР НИКОЛАЕВИЧ | DB72: 1234
B73: 1 | C73: 30.06.2023 | D73: 6 | E73: 10131010/300623/3236941 | F73: 10131010 | G73: 30.06.2023 | H73: 3236941 | I73: ИМ | J73: 40 | N73: HENDRIX GENETICS TURKEYS FRANCE SAS | O73: 49290, , MAUGES SUR LOIRE, B.P.1-LA BOHARDIERE SAINT LAURENT DE LA PLAINE, | R73: 1 | S73: 0 | T73: 1 | U73: 13 | V73: 1193668026507 | W73: 3613005236 | X73: ООО "ДОНСКАЯ ИНДЕЙКА" | Y73: 396350, ВОРОНЕЖСКАЯ ОБЛАСТЬ, КАШИРСКИЙ РАЙОН, П. ИМ. ДЗЕРЖИНСКОЕ, УЛ. ПОЛЕВАЯ,, | Z73: 20000 | AA73: 361301001 | AB73: 1193668026507 | AC73: 3613005236 | AD73: ООО "ДОНСКАЯ ИНДЕЙКА" | AE73: 396350, ВОРОНЕЖСКАЯ ОБЛАСТЬ, КАШИРСКИЙ РАЙОН, П. ИМ. ДЗЕРЖИНСКОЕ, УЛ. ПОЛЕВАЯ,, | AF73: 20000 | AG73: 361301001 | AH73: FR | AI73: ФРАНЦИЯ | AJ73: 8970322.5 | AK73: 1193668026507 | AL73: 3613005236 | AM73: ООО "ДОНСКАЯ ИНДЕЙКА" | AN73: 396350, ВОРОНЕЖСКАЯ ОБЛАСТЬ, КАШИРСКИЙ РАЙОН, П. ИМ. ДЗЕРЖИНСКОЕ, УЛ. ПОЛЕВАЯ,, | AO73: 20000 | AP73: 361301001 | AQ73: FR | AR73: ФРАНЦИЯ | AS73: ФРАНЦИЯ | AT73: RU | AU73: РОССИЯ | AV73: 2 | AW73: 0 | AX73: DAP | AY73: П. ИМ. ДЗЕРЖИНСКОГО | AZ73: 1 | BA73: EUR | BB73: 94320 | BC73: 8970322 | BD73: 103066.76 | BE73: 95.1052 | BF73: 010 | BH73: 23010142/3292/0000/2/1 | BI73: - | BJ73: 99 | BL73: 10113/171210/10036/8 | BN73: СМОЛЕНСКАЯ ОБЛ., СМОЛЕНСКИЙ Р-Н | BO73: Д. СТАБНА | BP73: СЕВЕРО-ВОСТОЧНЕЕ Д. СТАБНА, НА РАСТОЯНИИ 700 М,,,. | BQ73: 10113100 т/п Стабнинский | BR73: 1 | BS73: ОПЛОДОТВОРЕННЫЕ ИНКУБАЦИОННЫЕ ЯЙЦА ИНДЕЕК (MELEAGRUS GAILOPANO L), ДЛЯ ИНКУБАЦИИ И ВЫВЕДЕНИЯ ИНДЕЕК, ДЛЯ ПОСЛЕДУЮЩЕГО ВЫРАЩИВАНИЯ И УБОЯ НА МЯСО, СВЕЖИЕ, (В КОРОБКЕ 10 ЛОТКОВ ПО 20 ШТ.): | BT73: =MIN(1,IFERROR(SEARCH(BT$2,$BS73),0)) -> 0 | BU73: =MIN(1,IFERROR(SEARCH(BU$2,$BS73),0)) -> 0 | BV73: =MAX(BT73,BU73) -> 0 | BW73: ОТСУТСТВУЕТ | BX73: HENDRIX GENETICS TURKEYS FRANCE | BY73: 13 | BZ73: 0 | CA73: 61000 | CB73: ШТ | CC73: 0 | CE73: 1 | CF73: 0407191100 | CI73: FR | CJ73: 6405 | CK73: ОООО-ЛП | CL73: 4000000 | CM73: 6100 | CN73: 0 | CQ73: 94320 | CR73: 8970322 | CS73: 0 | CT73: 1 | CU73: 8970322.5 | CV73: 103066.76 | CW73: 10 | CX73: 16.9 | CY73: 35 | CZ73: 0035/03-20-2139 | DA73: ИЛЬИНА ОЛЬГА АЛЕКСАНДРОВНА | DB73: 166
B74: 1 | C74: 27.06.2023 | D74: 6 | E74: 10620010/260623/3091396 | F74: 10620010 | G74: 26.06.2023 | H74: 3091396 | I74: ИМ | J74: 40 | K74: ПТД | N74: GRIMAUD FRERES SELECTION S.A.S. | O74: 49450, SEVREMOINE, ROUSSAY, 3 LA CORBIERE, | R74: 1 | S74: 0 | T74: 1 | U74: 117 | V74: 1165476055030 | W74: 5446017473 | X74: ООО ПФ "УЛЫБИНО" | Y74: 633204, НОВОСИБИРСКАЯ ОБЛАСТЬ, Г.ИСКИТИМ, УЛ.ЭЛЕВАТОРНАЯ, Д.5/1,ОФИС 310, | Z74: 50000 | AA74: 544601001 | AB74: 1165476055030 | AC74: 5446017473 | AD74: ООО ПФ "УЛЫБИНО" | AE74: 633204, НОВОСИБИРСКАЯ ОБЛАСТЬ, Г.ИСКИТИМ, УЛ.ЭЛЕВАТОРНАЯ, Д.5/1,ОФИС 310, | AF74: 50000 | AG74: 544601001 | AH74: FR | AI74: ФРАНЦИЯ | AJ74: 7551857 | AK74: 1165476055030 | AL74: 5446017473 | AM74: ООО ПФ "УЛЫБИНО" | AN74: 633204, НОВОСИБИРСКАЯ ОБЛАСТЬ, Г.ИСКИТИМ, УЛ.ЭЛЕВАТОРНАЯ, Д.5/1,ОФИС 310, | AO74: 50000 | AP74: 544601001 | AQ74: FR | AR74: ФРАНЦИЯ | AS74: ФРАНЦИЯ | AT74: RU | AU74: РОССИЯ | AV74: 2 | AW74: 0 | AX74: DAP | AY74: ИСКИТИМ | AZ74: 1 | BA74: EUR | BB74: 82540 | BC74: 7551857 | BD74: 89818.27 | BE74: 91.4933 | BF74: 010 | BG74: 10 | BH74: 23050005/2216/0004/2/1 | BI74: - | BJ74: 99 | BN74: НОВОСИБИРСКАЯ ОБЛ. | BO74: Г. ОБЬ | BP74: ПР-КТ МОЗЖЕРИНА, СТР.1,СТР.22; АЭРОПОРТ ТОЛМАЧЕВО, | BQ74: 10609060 т/п Аэропорт Толмачево | BR74: 1 | BS74: ОПЛОДОТВОРЕННЫЕ ЯЙЦА ДОМАШНЕЙ ПЕКИНСКОЙ УТКИ ДЛЯ ИНКУБАЦИИ | BT74: =MIN(1,IFERROR(SEARCH(BT$2,$BS74),0)) -> 0 | BU74: =MIN(1,IFERROR(SEARCH(BU$2,$BS74),0)) -> 0 | BV74: =MAX(BT74,BU74) -> 0 | BW74: ОТСУТСТВУЕТ | BX74: GRIMAUD FRERES SELECTION S.A.S. | BY74: 117 | BZ74: 0 | CA74: 23400 | CB74: ШТ | CC74: 0 | CE74: 1 | CF74: 0407191900 | CI74: FR | CJ74: 2293.2 | CK74: ОООО-ПС | CL74: 4000000 | CM74: 1872 | CN74: 0 | CQ74: 82540 | CR74: 7551857 | CS74: 0 | CT74: 1 | CU74: 7551857 | CV74: 89818.27 | CW74: 10 | CX74: 47.98 | CY74: 1069 | CZ74: 0582-19-23-413 | DA74: ЖАХОВСКАЯ ЕКАТЕРИНА МИХАЙЛОВНА | DB74: 164
B75: 1 | C75: 27.06.2023 | D75: 6 | E75: 10013160/270623/3289891 | F75: 10013160 | G75: 27.06.2023 | H75: 3289891 | I75: ИМ | J75: 40 | N75: CHERRY VALLEY FARMS GERMANY GMBH | O75: 15320, DEUTSCHLEND, NEUHARDENBERG, KARLSDORF, 28 | R75: 1 | S75: 0 | T75: 1 | U75: 18 | V75: 1047796588146 | W75: 7710553010 | X75: ООО "АГРОИМПОРТ" | Y75: 143421, МОСКОВСКАЯ ОБЛ., КРАСНОГОРСКИЙ Р-Н, 26 КМ А/Д "БАЛТИЯ", БЦ "РИГА-ЛЕНД", | Z75: 46000 | AA75: 502401001 | AB75: 1047796588146 | AC75: 7710553010 | AD75: ООО "АГРОИМПОРТ" | AE75: 143421, МОСКОВСКАЯ ОБЛ., КРАСНОГОРСКИЙ Р-Н, 26 КМ А/Д "БАЛТИЯ", БЦ "РИГА-ЛЕНД", | AF75: 46000 | AG75: 502401001 | AH75: DE | AI75: ГЕРМАНИЯ | AJ75: 11710169 | AK75: 1047796588146 | AL75: 7710553010 | AM75: ООО "АГРОИМПОРТ" | AN75: 143421, МОСКОВСКАЯ ОБЛ., КРАСНОГОРСКИЙ Р-Н, 26 КМ А/Д "БАЛТИЯ", БЦ "РИГА-ЛЕНД", | AO75: 46000 | AP75: 502401001 | AQ75: DE | AR75: ГЕРМАНИЯ | AS75: ГЕРМАНИЯ | AT75: RU | AU75: РОССИЯ | AV75: 2 | AW75: 0 | AX75: DAP | AY75: Х. РЕДКОДУБ | AZ75: 1 | BA75: EUR | BB75: 126875 | BC75: 11710169 | BD75: 138313.11 | BE75: 92.2969 | BF75: 010 | BH75: 22041586/3292/0000/2/1 | BI75: - | BJ75: 11 | BK75: 10113/261110/10021/1 | BM75: 215119 | BN75: СМОЛЕНСКАЯ | BO75: ВЯЗЬМА | BP75: ЭЛЕВАТОРНАЯ,,,. | BQ75: 10113020 т/п Вяземский | BR75: 1 | BS75: ЯЙЦА УТКИ, ПЛЕМЕННЫЕ ДЛЯ ИНКУБАЦИИ, ОПЛОДОТВОРЁННЫЕ, ДЛЯ ВЫВЕДЕНИЯ РОДИТЕЛЬСКОГО СТAДА ПОРОДЫ ПЕКИНСКАЯ УТКА, РАЗМЕЩЕННЫЕ С ЦЕЛЬЮ ПРЕДОТВРАЩЕНИЯ БОЯ И УНИЧТОЖЕНИЯ В КАРТОННЫХ КОРОБКАХ. | BT75: =MIN(1,IFERROR(SEARCH(BT$2,$BS75),0)) -> 0 | BU75: =MIN(1,IFERROR(SEARCH(BU$2,$BS75),0)) -> 0 | BV75: =MAX(BT75,BU75) -> 0 | BW75: ОТСУТСТВУЕТ | BX75: CHERRY VALLEY FARMS GERMANY GMBH | BY75: 313 | BZ75: 0 | CA75: 62500 | CB75: ШТ | CC75: 0 | CE75: 1 | CF75: 0407191900 | CI75: DE | CJ75: 6260 | CK75: ОООО-ПС | CL75: 4000000 | CM75: 5634 | CN75: 0 | CQ75: 126875 | CR75: 11710169 | CS75: 0 | CT75: 1 | CU75: 11710169 | CV75: 138313.11 | CW75: 10 | CX75: 24.55 | DA75: КУДЕЛЬКИН ВЛАДИМИР ВЛАДИМИРОВИЧ | DB75: 1442
B76: 1 | C76: 26.06.2023 | D76: 6 | E76: 10013160/260623/3288675 | F76: 10013160 | G76: 26.06.2023 | H76: 3288675 | I76: ИМ | J76: 40 | N76: GRIMAUD FRERES SELECTION S.A.S. | O76: 49450, , SEVREMOINE, ROUSSAY, RA3 LA CORBIERE, | R76: 1 | S76: 0 | T76: 1 | U76: 74 | V76: 1217700533511 | W76: 9704098398 | X76: ООО "ИМПОРТЭГГЗ" | Y76: 117393, , МОСКВА, УЛ. АРХИТЕКТОРА ВЛАСОВА, Д. 55 | Z76: 45000 | AA76: 772801001 | AB76: 1217700533511 | AC76: 9704098398 | AD76: ООО "ИМПОРТЭГГЗ" | AE76: 117393, , МОСКВА, УЛ. АРХИТЕКТОРА ВЛАСОВА, Д. 55 | AF76: 45000 | AG76: 772801001 | AH76: FR | AI76: ФРАНЦИЯ | AJ76: 7020269.9 | AK76: 1217700533511 | AL76: 9704098398 | AM76: ООО "ИМПОРТЭГГЗ" | AN76: 117393, , МОСКВА, УЛ. АРХИТЕКТОРА ВЛАСОВА, Д. 55 | AO76: 45000 | AP76: 772801001 | AQ76: FR | AR76: ФРАНЦИЯ | AS76: ФРАНЦИЯ | AT76: RU | AU76: РОССИЯ | AV76: 2 | AW76: 0 | AX76: FCA | AY76: MESLAY DU MAINE | AZ76: 1 | BA76: EUR | BB76: 75213.6 | BC76: 6881540 | BD76: 83495.82 | BE76: 91.4933 | BF76: 010 | BH76: 23060174/0354/0000/2/1 | BI76: - | BJ76: 11 | BK76: 10013/200111/10045/6 | BM76: 215119 | BN76: МОСКОВСКАЯ ОБЛ. | BO76: Г. КРАСНОЗНАМЕНСК | BP76: УЛ. БЕРЕЗОВАЯ АЛЛЕЯ 1/2; ОТКР.ПЛОЩАДКА: МО, Г. КРА | BQ76: 10013070 т/п Красноармейский | BR76: 1 | BS76: ИНКУБАЦИОННЫЕ ЯЙЦА ДОМАШНЕЙ ПТИЦЫ (УТИНЫЕ), ОПЛОДОТBОРЁННЫЕ (ДЛЯ ИНКУБАЦИИ). РАЗМЕЩЕНЫ С ЦЕЛЬЮ ПРЕДОТВРАЩЕНИЯ БОЯ И УНИЧТОЖЕНИЯ В КАРТОННЫХ КОРОБКАХ (200 ЯИЦ В ОДНОЙ КОРОБКЕ) | BT76: =MIN(1,IFERROR(SEARCH(BT$2,$BS76),0)) -> 0 | BU76: =MIN(1,IFERROR(SEARCH(BU$2,$BS76),0)) -> 0 | BV76: =MAX(BT76,BU76) -> 0 | BW76: ОТСУТСТВУЕТ | BX76: GRIMAUD FRERES SELECTION S.A.S. | BY76: 74 | BZ76: 0 | CA76: 14800 | CB76: ШТ | CC76: 0 | CE76: 1 | CF76: 0407191900 | CI76: FR | CJ76: 1525.4 | CK76: ОООО-ЛП | CL76: 4000000 | CM76: 1184 | CN76: 0 | CQ76: 75213.6 | CR76: 6881540 | CS76: 0 | CT76: 1 | CU76: 7020269.9 | CV76: 83495.82 | CW76: 10 | CX76: 70.52 | DA76: ПЯТАЕВ АЛЕКСЕЙ АНАТОЛЬЕВИЧ | DB76: 1308
B77: 1 | C77: 26.06.2023 | D77: 6 | E77: 10418010/260623/3088587 | F77: 10418010 | G77: 26.06.2023 | H77: 3088587 | I77: ИМ | J77: 40 | N77: BRANKO NITRA, A. S. | O77: 949 05, , NITRA, NOVOZAMOCKA, 184 | R77: 1 | S77: 0 | T77: 1 | U77: 9 | V77: 1191690037549 | W77: 1623014613 | X77: ООО "БРАНКО РУС" | Y77: 422060, РЕСПУБЛИКА ТАТАРСТАН, САБИНСКИЙ РАЙОН, ПГТ. БОГАТЫЕ САБЫ, УЛ. ЗАВОДСКАЯ, | Z77: 92000 | AA77: 162301001 | AB77: 1191690037549 | AC77: 1623014613 | AD77: ООО "БРАНКО РУС" | AE77: 422060, РЕСПУБЛИКА ТАТАРСТАН, САБИНСКИЙ РАЙОН, ПГТ. БОГАТЫЕ САБЫ, УЛ. ЗАВОДСКАЯ, | AF77: 92000 | AG77: 162301001 | AH77: SK | AI77: СЛОВАКИЯ | AJ77: 6194096.4 | AK77: 1191690037549 | AL77: 1623014613 | AM77: ООО "БРАНКО РУС" | AN77: 422060, РЕСПУБЛИКА ТАТАРСТАН, САБИНСКИЙ РАЙОН, ПГТ. БОГАТЫЕ САБЫ, УЛ. ЗАВОДСКАЯ, | AO77: 92000 | AP77: 162301001 | AQ77: SK | AR77: СЛОВАКИЯ | AS77: СЛОВАКИЯ | AT77: RU | AU77: РОССИЯ | AV77: 2 | AW77: 0 | AX77: DAP | AY77: БОГАТЫЕ САБЫ | AZ77: 1 | BA77: EUR | BB77: 67700 | BC77: 6194096 | BD77: 73669.7 | BE77: 91.4933 | BF77: 010 | BG77: 10 | BH77: 23030299/2766/0000/2/1 | BI77: - | BJ77: 99 | BN77: СМОЛЕНСКАЯ ОБЛ., СМОЛЕНСКИЙ Р-ОН | BO77: С.П.СТАБЕНСКОЕ | BP77: СЕВЕРО-ВОСТОЧНЕЕ Д. СТАБНА, НА РАСТОЯНИИ 700 М,,,. | BQ77: 10113100 т/п Стабнинский | BR77: 1 | BS77: ОПЛОДОТВОРЕННЫЕ ЯЙЦА ИНДЮШАЧЬИ СВЕЖИЕ,ДЛЯ ИНКУБАЦИИ (ВСЕГО 42000 ШТ) ЯЙЦО ИНКУБАЦИОННОЕ ИНДЕЙКИ MELEAGRIS GALLOPAVO L., ПОРОДЫ BUT BIG 6 , БЕЛАЯ ШИРОКОГРУДАЯ, ВЕС ЯЙЦА МЕЖДУ 75 -100 Г, НЕ ЯВЛЯЕТСЯ ПЛЕМЕННЫМ, (УПАКОВАНО В КОРОБКАХ ПО 200 ШТ) | BT77: =MIN(1,IFERROR(SEARCH(BT$2,$BS77),0)) -> 1 | BU77: =MIN(1,IFERROR(SEARCH(BU$2,$BS77),0)) -> 1 | BV77: =MAX(BT77,BU77) -> 1 | BW77: ОТСУТСТВУЕТ | BX77: BRANKO NITRA, A. S. | BY77: 9 | BZ77: 0 | CA77: 42000 | CB77: ШТ | CC77: 0 | CE77: 1 | CF77: 0407191100 | CI77: SK | CJ77: 4410 | CK77: ОООО-ЛП | CL77: 4000000 | CM77: 4095 | CN77: 0 | CQ77: 67700 | CR77: 6194096 | CS77: 0 | CT77: 1 | CU77: 6194096.4 | CV77: 73669.7 | CW77: 10 | CX77: 17.99 | DA77: КРАЙНОВА ЛЮДМИЛА АНАТОЛЬЕВНА | DB77: 74
B78: 1 | C78: 26.06.2023 | D78: 6 | E78: 10805010/260623/3010891 | F78: 10805010 | G78: 26.06.2023 | H78: 3010891 | I78: ИМ | J78: 40 | N78: PARTIZ 2000 KFT. | O78: 5540, , SZARVAS, RACOKZI U.6/1, | R78: 1 | S78: 0 | T78: 1 | U78: 150 | V78: 1132651023570 | W78: 2624801566 | X78: ООО "ПТИЧИЙ ДВОР" | Y78: 356800, СТАВРОПОЛЬСКИЙ КРАЙ, Г. БУДЕННОВСК, УЛ. ВОДНИКОВ, Д.7, | Z78: 07000 | AA78: 262401001 | AB78: 1132651023570 | AC78: 2624801566 | AD78: ООО "ПТИЧИЙ ДВОР" | AE78: 356800, СТАВРОПОЛЬСКИЙ КРАЙ, Г. БУДЕННОВСК, УЛ. ВОДНИКОВ, Д.7, | AF78: 07000 | AG78: 262401001 | AH78: HU | AI78: ВЕНГРИЯ | AJ78: 4254438.5 | AK78: 1132651023570 | AL78: 2624801566 | AM78: ООО "ПТИЧИЙ ДВОР" | AN78: 356800, СТАВРОПОЛЬСКИЙ КРАЙ, Г. БУДЕННОВСК, УЛ. ВОДНИКОВ, Д.7, | AO78: 07000 | AP78: 262401001 | AQ78: HU | AR78: ВЕНГРИЯ | AS78: ВЕНГРИЯ | AT78: RU | AU78: РОССИЯ | AV78: 2 | AW78: 0 | AX78: FCA | AY78: SZARVAS | AZ78: 1 | BA78: EUR | BB78: 43500 | BC78: 3979959 | BD78: 50600.31 | BE78: 91.4933 | BF78: 010 | BH78: 22050611/2673/0000/2/1 | BI78: - | BJ78: 99 | BN78: СМОЛЕНСКАЯ ОБЛ., СМОЛЕНСКИЙ Р-Н | BO78: С.П. СТАБЕНСКОЕ | BP78: СЕВЕРО-ВОСТОЧНЕЕ Д. СТАБНА, НА РАСТОЯНИИ 700 М,,,. | BQ78: 10113100 т/п Стабнинский | BR78: 1 | BS78: ОПЛОДОТВОРЕННЫЕ НЕПЛЕМЕННЫЕ ИНКУБАЦИОННЫЕ ЯЙЦА ИНДЕЙКИ (TURKEY HATCHING EGGS), ДЛЯ ИНКУБАЦИИ, ДЛЯ ПОСЛЕДУЮЩЕГО ВЫРАЩИВАНИЯ И УБОЯ НА МЯСО, СВЕЖИЕ, ПО 200 ШТ В КОРОБКЕ. | BT78: =MIN(1,IFERROR(SEARCH(BT$2,$BS78),0)) -> 1 | BU78: =MIN(1,IFERROR(SEARCH(BU$2,$BS78),0)) -> 0 | BV78: =MAX(BT78,BU78) -> 1 | BW78: PARTIZ 2000 | BX78: GALLI-EGGS KFT., ПЛЕМЗАВОД HU1009976 | BY78: 150 | BZ78: 0 | CA78: 30000 | CB78: ШТ | CC78: 0 | CE78: 1 | CF78: 0407191100 | CI78: HU | CJ78: 3150 | CK78: ОООО-ЛП | CL78: 4000000 | CM78: 3000 | CN78: 0 | CQ78: 43500 | CR78: 3979959 | CS78: 0 | CT78: 1 | CU78: 4254438.5 | CV78: 50600.31 | CW78: 10 | CX78: 16.87 | DA78: ПИЛИПЕНКО ОЛЬГА НИКОЛАЕВНА | DB78: 9
B79: 1 | C79: 26.06.2023 | D79: 6 | E79: 10005030/260623/3169699 | F79: 10005030 | G79: 26.06.2023 | H79: 3169699 | I79: ИМ | J79: 40 | N79: CUDDY FARMS LIMITED 2008 | O79: 28429, ONTARIO, STRATHROY, N7G3H6 CENTRE ROAD RR, 5 | R79: 1 | S79: 0 | T79: 1 | U79: 594 | V79: 1047796588146 | W79: 7710553010 | X79: ООО "АГРОИМПОРТ" | Y79: 143421, МОСКОВСКАЯ ОБЛ., КРАСНОГОРСКИЙ Р-Н, 26 КМ А/Д "БАЛТИЯ", БЦ "РИГА-ЛЕНД", | Z79: 46000 | AA79: 502401001 | AB79: 1047796588146 | AC79: 7710553010 | AD79: ООО "АГРОИМПОРТ" | AE79: 143421, МОСКОВСКАЯ ОБЛ., КРАСНОГОРСКИЙ Р-Н, 26 КМ А/Д "БАЛТИЯ", БЦ "РИГА-ЛЕНД", | AF79: 46000 | AG79: 502401001 | AH79: CA | AI79: КАНАДА | AJ79: 15108472 | AK79: 1047796588146 | AL79: 7710553010 | AM79: ООО "АГРОИМПОРТ" | AN79: 143421, МОСКОВСКАЯ ОБЛ., КРАСНОГОРСКИЙ Р-Н, 26 КМ А/Д "БАЛТИЯ", БЦ "РИГА-ЛЕНД", | AO79: 46000 | AP79: 502401001 | AQ79: CA | AR79: КАНАДА | AS79: КАНАДА | AT79: RU | AU79: РОССИЯ | AV79: 0 | AW79: 0 | AX79: CPT | AY79: МОСКВА | AZ79: 1 | BA79: EUR | BB79: 165132 | BC79: 15108472 | BD79: 179693.12 | BE79: 91.4933 | BF79: 010 | BG79: 40 | BH79: 22120523/3292/0000/2/1 | BI79: - | BJ79: 11 | BK79: 10001/311210/10001/10 | BM79: 141400 | BN79: МОСКОВСКАЯ | BO79: ТЕРРИТОРИЯ АЭРОПОРТА | BP79: "ВНУКОВО", СТР. 19,,,. | BQ79: 10001020 т/п Аэропорт Внуково (грузовой) | BR79: 1 | BS79: ИНДЮШАЧЬИ ЯЙЦА ДЛЯ ИНКУБАЦИИ, ПОРОДА MELEAGRIS GALLOPAVO L. "БЕЛАЯ ШИРОКОГРУДАЯ" (HCONV), КРОСС ХАЙБРИД КОНВЕРТЕР, КАТЕГОРИЯ БРОЙЛЕР, НЕ ПЛЕМЕННЫЕ, РАЗМЕЩЕНЫ В КАРТОННЫХ КАССЕТАХ ПО ДВАДЦАТЬ (20) ЯИЦ В KАЖДОЙ И УПАКОВАНО В ОРИГИНАЛЬНЫЕ КАРТОННЫЕ | BT79: =MIN(1,IFERROR(SEARCH(BT$2,$BS79),0)) -> 0 | BU79: =MIN(1,IFERROR(SEARCH(BU$2,$BS79),0)) -> 1 | BV79: =MAX(BT79,BU79) -> 1 | BW79: ОТСУТСТВУЕТ | BX79: CUDDY FARMS LIMITED 2008 | BY79: 594 | BZ79: 0 | CA79: 118800 | CB79: ШТ | CC79: 0 | CE79: 1 | CF79: 0407191100 | CI79: CA | CJ79: 13000 | CK79: ОООО-ЛП | CL79: 4000000 | CM79: 10692 | CN79: 0 | CQ79: 165132 | CR79: 15108472 | CS79: 0 | CT79: 1 | CU79: 15108472 | CV79: 179693.12 | CW79: 10 | CX79: 16.81 | DA79: КУДЕЛЬКИН ВЛАДИМИР ВЛАДИМИРОВИЧ | DB79: 1055
B80: 1 | C80: 26.06.2023 | D80: 6 | E80: 10013160/260623/3287912 | F80: 10013160 | G80: 26.06.2023 | H80: 3287912 | I80: ИМ | J80: 40 | N80: NAGISZ ZRT. | O80: 4181, , NADUDVAR, FO UT 119, | R80: 1 | S80: 0 | T80: 1 | U80: 546 | V80: 1047796588146 | W80: 7710553010 | X80: ООО "АГРОИМПОРТ" | Y80: 143421, МОСКОВСКАЯ ОБЛ., КРАСНОГОРСКИЙ Р-Н, 26 КМ А/Д "БАЛТИЯ", БЦ "РИГА-ЛЕНД", | Z80: 46000 | AA80: 502401001 | AB80: 1047796588146 | AC80: 7710553010 | AD80: ООО "АГРОИМПОРТ" | AE80: 143421, МОСКОВСКАЯ ОБЛ., КРАСНОГОРСКИЙ Р-Н, 26 КМ А/Д "БАЛТИЯ", БЦ "РИГА-ЛЕНД", | AF80: 46000 | AG80: 502401001 | AH80: HU | AI80: ВЕНГРИЯ | AJ80: 12758741 | AK80: 1047796588146 | AL80: 7710553010 | AM80: ООО "АГРОИМПОРТ" | AN80: 143421, МОСКОВСКАЯ ОБЛ., КРАСНОГОРСКИЙ Р-Н, 26 КМ А/Д "БАЛТИЯ", БЦ "РИГА-ЛЕНД", | AO80: 46000 | AP80: 502401001 | AQ80: HU | AR80: ВЕНГРИЯ | AS80: ВЕНГРИЯ | AT80: RU | AU80: РОССИЯ | AV80: 2 | AW80: 0 | AX80: FCA | AY80: NADUDVAR | AZ80: 1 | BA80: EUR | BB80: 136500 | BC80: 12488835 | BD80: 151746.51 | BE80: 91.4933 | BF80: 010 | BH80: 22120524/3292/0000/2/1 | BI80: - | BJ80: 99 | BN80: ПЕНЗЕНСКАЯ | BO80: ПЕНЗА | BP80: АУСТРИНА,,,. | BQ80: 10413090 т/п Пензенский областной | BR80: 1 | BS80: ИHДЮШАЧЬИ ЯЙЦА ДЛЯ ИНКУБАЦИИ, ОПЛОДОТВОРЕННЫЕ, MELEAGRIS GALLOPAVO L., ПОРОДА БЕЛАЯ ШИРОКОГРУДАЯ КРОССА БИГ-6, РАЗМЕЩЕНЫ С ЦЕЛЬЮ ПРЕДОТВРАЩЕНИЯ БОЯ И УНИЧТОЖЕНИЯ В КАРТОННЫХ КОРОБКАХ | BT80: =MIN(1,IFERROR(SEARCH(BT$2,$BS80),0)) -> 0 | BU80: =MIN(1,IFERROR(SEARCH(BU$2,$BS80),0)) -> 0 | BV80: =MAX(BT80,BU80) -> 0 | BW80: ОТСУТСТВУЕТ | BX80: NAGISZ ZRT. | BY80: 546 | BZ80: 0 | CA80: 109200 | CB80: ШТ | CC80: 0 | CE80: 1 | CF80: 0407191100 | CI80: HU | CJ80: 12012 | CK80: ОООО-ЛП | CL80: 4000000 | CM80: 11466 | CN80: 0 | CQ80: 136500 | CR80: 12488835 | CS80: 0 | CT80: 1 | CU80: 12758741 | CV80: 151746.51 | CW80: 10 | CX80: 13.23 | DA80: КУДЕЛЬКИН ВЛАДИМИР ВЛАДИМИРОВИЧ | DB80: 1579
B81: 1 | C81: 26.06.2023 | D81: 6 | E81: 10013160/260623/3288280 | F81: 10013160 | G81: 26.06.2023 | H81: 3288280 | I81: ИМ | J81: 40 | N81: PARTIZ 2000 KFT | O81: 5540, , SZARVAS, RAKOCZI U. 6/1, | R81: 1 | S81: 0 | T81: 1 | U81: 30 | V81: 1217700533511 | W81: 9704098398 | X81: ООО "ИМПОРТЭГГЗ" | Y81: 117393, , МОСКВА, УЛ. АРХИТЕКТОРА ВЛАСОВА, Д. 55 | Z81: 45000 | AA81: 772801001 | AB81: 1217700533511 | AC81: 9704098398 | AD81: ООО "ИМПОРТЭГГЗ" | AE81: 117393, , МОСКВА, УЛ. АРХИТЕКТОРА ВЛАСОВА, Д. 55 | AF81: 45000 | AG81: 772801001 | AH81: HU | AI81: ВЕНГРИЯ | AJ81: 803315.75 | AK81: 1217700533511 | AL81: 9704098398 | AM81: ООО "ИМПОРТЭГГЗ" | AN81: 117393, , МОСКВА, УЛ. АРХИТЕКТОРА ВЛАСОВА, Д. 55 | AO81: 45000 | AP81: 772801001 | AQ81: HU | AR81: ВЕНГРИЯ | AS81: ВЕНГРИЯ | AT81: RU | AU81: РОССИЯ | AV81: 2 | AW81: 0 | AX81: FCA | AY81: SZARVAS | AZ81: 1 | BA81: EUR | BB81: 8700 | BC81: 795992 | BD81: 9554.26 | BE81: 91.4933 | BF81: 010 | BH81: 23020963/3292/0000/2/1 | BI81: - | BJ81: 11 | BK81: 10013/200111/10045/6 | BM81: 215119 | BN81: МОСКОВСКАЯ ОБЛ. | BO81: Г. КРАСНОЗНАМЕНСК | BP81: УЛ. БЕРЕЗОВАЯ АЛЛЕЯ 1/2; ОТКР.ПЛОЩАДКА: МО, Г. КРА | BQ81: 10013070 т/п Красноармейский | BR81: 1 | BS81: ИНКУБАЦИОННЫЕ ЯЙЦА ИНДЮШАЧЬИ, ОПЛОДОТВОРЁННЫЕ (ДЛЯ ИНКУБАЦИИ). РАЗМЕЩЕНЫ С ЦЕЛЬЮ ПPЕДОТВРАЩЕНИЯ БОЯ И УНИЧТОЖЕНИЯ В КАРТОННЫХ КОРОБКАХ (200 ЯИЦ В ОДНОЙ КОРОБКЕ) | BT81: =MIN(1,IFERROR(SEARCH(BT$2,$BS81),0)) -> 0 | BU81: =MIN(1,IFERROR(SEARCH(BU$2,$BS81),0)) -> 1 | BV81: =MAX(BT81,BU81) -> 1 | BW81: ОТСУТСТВУЕТ | BX81: PARTIZ 2000 KFT | BY81: 30 | BZ81: 0 | CA81: 6000 | CB81: ШТ | CC81: 0 | CE81: 1 | CF81: 0407191100 | CI81: HU | CJ81: 630 | CK81: ОООО-ЛП | CL81: 4000000 | CM81: 600 | CN81: 0 | CQ81: 8700 | CR81: 795992 | CS81: 0 | CT81: 1 | CU81: 803315.75 | CV81: 9554.26 | CW81: 10 | CX81: 15.92 | DA81: ПЯТАЕВ АЛЕКСЕЙ АНАТОЛЬЕВИЧ | DB81: 1208
B82: 1 | C82: 26.06.2023 | D82: 6 | E82: 10013160/260623/3286323 | F82: 10013160 | G82: 26.06.2023 | H82: 3286323 | I82: ИМ | J82: 40 | N82: MOORGUT KARTZFEHN TURKEY BREEDER GMBH | O82: 26219, , BOSEL, KARTZ-VON-KAMEKE-ALLEE, 7 | R82: 1 | S82: 0 | T82: 1 | U82: 358 | V82: 1047796588146 | W82: 7710553010 | X82: ООО "АГРОИМПОРТ" | Y82: 143421, МОСКОВСКАЯ ОБЛ., КРАСНОГОРСКИЙ Р-Н, 26 КМ А/Д "БАЛТИЯ", БЦ "РИГА-ЛЕНД", | Z82: 46000 | AA82: 502401001 | AB82: 1047796588146 | AC82: 7710553010 | AD82: ООО "АГРОИМПОРТ" | AE82: 143421, МОСКОВСКАЯ ОБЛ., КРАСНОГОРСКИЙ Р-Н, 26 КМ А/Д "БАЛТИЯ", БЦ "РИГА-ЛЕНД", | AF82: 46000 | AG82: 502401001 | AH82: DE | AI82: ГЕРМАНИЯ | AJ82: 11791656 | AK82: 1047796588146 | AL82: 7710553010 | AM82: ООО "АГРОИМПОРТ" | AN82: 143421, МОСКОВСКАЯ ОБЛ., КРАСНОГОРСКИЙ Р-Н, 26 КМ А/Д "БАЛТИЯ", БЦ "РИГА-ЛЕНД", | AO82: 46000 | AP82: 502401001 | AQ82: DE | AR82: ГЕРМАНИЯ | AS82: ГЕРМАНИЯ | AT82: RU | AU82: РОССИЯ | AV82: 2 | AW82: 0 | AX82: DAP | AY82: С. ГОЛИЦЫНО | AZ82: 1 | BA82: EUR | BB82: 128880 | BC82: 11791657 | BD82: 140244.47 | BE82: 91.4933 | BF82: 010 | BH82: 20121446/1326/0000/2/1 | BI82: - | BJ82: 60 | BK82: RU/0004/ТИП2 | BL82: RU/0004/ТИП2 | BN82: ПЕНЗЕНСКАЯ, НИЖНЕЛОМОВСКИЙ | BO82: ГОЛИЦЫНО | BP82: ГОЛИЦЫНСКИЙ СЕЛЬСОВЕТ,,,. | BQ82: 10413090 т/п Пензенский областной | BR82: 1 | BS82: ИНДЮШАЧЬИ ЯЙЦА ДЛЯ ИНКУБАЦИИ, ОПЛОДОТВОРЕННЫЕ, MELEAGRIS GALLOPAVO L., ПОРОДА БЕЛАЯ ШИРОКОГРУДАЯ КРОССА БИГ-6, КАТЕГОРИЯ БРОЙЛЕР РАЗМЕЩЕНЫ С ЦЕЛЬЮ ПРЕДОТВРАЩЕНИЯ БОЯ И УНИЧТОЖЕНИЯ В КАРТОННЫХ КОРОБКАХ | BT82: =MIN(1,IFERROR(SEARCH(BT$2,$BS82),0)) -> 0 | BU82: =MIN(1,IFERROR(SEARCH(BU$2,$BS82),0)) -> 1 | BV82: =MAX(BT82,BU82) -> 1 | BW82: ОТСУТСТВУЕТ | BX82: MOORGUT KARTZFEHN TURKEY BREEDER GMBH | BY82: 358 | BZ82: 0 | CA82: 71600 | CB82: ШТ | CC82: 0 | CE82: 1 | CF82: 0407191100 | CI82: DE | CJ82: 7876 | CK82: ОООО-ЛП | CL82: 4000000 | CM82: 7160 | CN82: 0 | CQ82: 128880 | CR82: 11791657 | CS82: 0 | CT82: 1 | CU82: 11791656 | CV82: 140244.47 | CW82: 10 | CX82: 19.59 | DA82: КУДЕЛЬКИН ВЛАДИМИР ВЛАДИМИРОВИЧ | DB82: 1101
